Workbook

Sheet RC Customers by plan
A1: RC Customers by plan
A2: RC Customers & revenue · Main Scenario
A4: Variable / dimension | B4: 2026-11 | C4: 2026-12 | D4: 2027-01 | E4: 2027-02 | F4: 2027-03 | G4: 2027-04 | H4: 2027-05 | I4: 2027-06 | J4: 2027-07 | K4: 2027-08 | L4: 2027-09 | M4: 2027-10 | N4: 2027-11 | O4: 2027-12 | P4: 2028-01 | Q4: 2028-02 | R4: 2028-03 | S4: 2028-04
A5: Model month | B5: =(YEAR(DATE(2026,11,1))-2026)*12+MONTH(DATE(2026,11,1))-11 -> 0 | C5: =(YEAR(DATE(2026,12,1))-2026)*12+MONTH(DATE(2026,12,1))-11 -> 1 | D5: =(YEAR(DATE(2027,1,1))-2026)*12+MONTH(DATE(2027,1,1))-11 -> 2 | E5: =(YEAR(DATE(2027,2,1))-2026)*12+MONTH(DATE(2027,2,1))-11 -> 3 | F5: =(YEAR(DATE(2027,3,1))-2026)*12+MONTH(DATE(2027,3,1))-11 -> 4 | G5: =(YEAR(DATE(2027,4,1))-2026)*12+MONTH(DATE(2027,4,1))-11 -> 5 | H5: =(YEAR(DATE(2027,5,1))-2026)*12+MONTH(DATE(2027,5,1))-11 -> 6 | I5: =(YEAR(DATE(2027,6,1))-2026)*12+MONTH(DATE(2027,6,1))-11 -> 7 | J5: =(YEAR(DATE(2027,7,1))-2026)*12+MONTH(DATE(2027,7,1))-11 -> 8 | K5: =(YEAR(DATE(2027,8,1))-2026)*12+MONTH(DATE(2027,8,1))-11 -> 9 | L5: =(YEAR(DATE(2027,9,1))-2026)*12+MONTH(DATE(2027,9,1))-11 -> 10 | M5: =(YEAR(DATE(2027,10,1))-2026)*12+MONTH(DATE(2027,10,1))-11 -> 11 | N5: =(YEAR(DATE(2027,11,1))-2026)*12+MONTH(DATE(2027,11,1))-11 -> 12 | O5: =(YEAR(DATE(2027,12,1))-2026)*12+MONTH(DATE(2027,12,1))-11 -> 13 | P5: =(YEAR(DATE(2028,1,1))-2026)*12+MONTH(DATE(2028,1,1))-11 -> 14 | Q5: =(YEAR(DATE(2028,2,1))-2026)*12+MONTH(DATE(2028,2,1))-11 -> 15 | R5: =(YEAR(DATE(2028,3,1))-2026)*12+MONTH(DATE(2028,3,1))-11 -> 16 | S5: =(YEAR(DATE(2028,4,1))-2026)*12+MONTH(DATE(2028,4,1))-11 -> 17
A6: Opening customers | B6: =SUM('RC Customers by plan'!B7,'RC Customers by plan'!B8,'RC Customers by plan'!B9) -> 47 | C6: =SUM('RC Customers by plan'!C7,'RC Customers by plan'!C8,'RC Customers by plan'!C9) -> 47 | D6: =SUM('RC Customers by plan'!D7,'RC Customers by plan'!D8,'RC Customers by plan'!D9) -> 84.905 | E6: =SUM('RC Customers by plan'!E7,'RC Customers by plan'!E8,'RC Customers by plan'!E9) -> 110.9505 | F6: =SUM('RC Customers by plan'!F7,'RC Customers by plan'!F8,'RC Customers by plan'!F9) -> 138.05103 | G6: =SUM('RC Customers by plan'!G7,'RC Customers by plan'!G8,'RC Customers by plan'!G9) -> 166.36012 | H6: =SUM('RC Customers by plan'!H7,'RC Customers by plan'!H8,'RC Customers by plan'!H9) -> 196.04007 | I6: =SUM('RC Customers by plan'!I7,'RC Customers by plan'!I8,'RC Customers by plan'!I9) -> 227.26287 | ... S6: =SUM('RC Customers by plan'!S7,'RC Customers by plan'!S8,'RC Customers by plan'!S9) -> 582.97988
A7: Indie | B7: =IF(IF(IF(ISERROR('RC Customers by plan'!B5=0),'RC Customers by plan'!B5=0,IF('RC Customers by plan'!B5="","",'RC Customers by plan'!B5=0))="",FALSE,IF(ISERROR('RC Customers by plan'!B5=0),'RC Customers by plan'!B5=0,IF('RC Customers by plan'!B5="","",'RC Customers by plan'!B5=0))),IF('Model inputs'!AG86="","",'Model inputs'!AG86),IF('Model inputs'!N38="","",'Model inputs'!N38)) -> 40 | C7: =IF(IF(IF(ISERROR('RC Customers by plan'!C5=0),'RC Customers by plan'!C5=0,IF('RC Customers by plan'!C5="","",'RC Customers by plan'!C5=0))="",FALSE,IF(ISERROR('RC Customers by plan'!C5=0),'RC Customers by plan'!C5=0,IF('RC Customers by plan'!C5="","",'RC Customers by plan'!C5=0))),IF('Model inputs'!AG86="","",'Model inputs'!AG86),IF('RC Customers by plan'!B31="","",'RC Customers by plan'!B31)) -> 40 | D7: =IF(IF(IF(ISERROR('RC Customers by plan'!D5=0),'RC Customers by plan'!D5=0,IF('RC Customers by plan'!D5="","",'RC Customers by plan'!D5=0))="",FALSE,IF(ISERROR('RC Customers by plan'!D5=0),'RC Customers by plan'!D5=0,IF('RC Customers by plan'!D5="","",'RC Customers by plan'!D5=0))),IF('Model inputs'!AG86="","",'Model inputs'!AG86),IF('RC Customers by plan'!C31="","",'RC Customers by plan'!C31)) -> 74.333333 | E7: =IF(IF(IF(ISERROR('RC Customers by plan'!E5=0),'RC Customers by plan'!E5=0,IF('RC Customers by plan'!E5="","",'RC Customers by plan'!E5=0))="",FALSE,IF(ISERROR('RC Customers by plan'!E5=0),'RC Customers by plan'!E5=0,IF('RC Customers by plan'!E5="","",'RC Customers by plan'!E5=0))),IF('Model inputs'!AG86="","",'Model inputs'!AG86),IF('RC Customers by plan'!D31="","",'RC Customers by plan'!D31)) -> 96.377778 | F7: =IF(IF(IF(ISERROR('RC Customers by plan'!F5=0),'RC Customers by plan'!F5=0,IF('RC Customers by plan'!F5="","",'RC Customers by plan'!F5=0))="",FALSE,IF(ISERROR('RC Customers by plan'!F5=0),'RC Customers by plan'!F5=0,IF('RC Customers by plan'!F5="","",'RC Customers by plan'!F5=0))),IF('Model inputs'!AG86="","",'Model inputs'!AG86),IF('RC Customers by plan'!E31="","",'RC Customers by plan'!E31)) -> 119.11259 | G7: =IF(IF(IF(ISERROR('RC Customers by plan'!G5=0),'RC Customers by plan'!G5=0,IF('RC Customers by plan'!G5="","",'RC Customers by plan'!G5=0))="",FALSE,IF(ISERROR('RC Customers by plan'!G5=0),'RC Customers by plan'!G5=0,IF('RC Customers by plan'!G5="","",'RC Customers by plan'!G5=0))),IF('Model inputs'!AG86="","",'Model inputs'!AG86),IF('RC Customers by plan'!F31="","",'RC Customers by plan'!F31)) -> 142.66455 | H7: =IF(IF(IF(ISERROR('RC Customers by plan'!H5=0),'RC Customers by plan'!H5=0,IF('RC Customers by plan'!H5="","",'RC Customers by plan'!H5=0))="",FALSE,IF(ISERROR('RC Customers by plan'!H5=0),'RC Customers by plan'!H5=0,IF('RC Customers by plan'!H5="","",'RC Customers by plan'!H5=0))),IF('Model inputs'!AG86="","",'Model inputs'!AG86),IF('RC Customers by plan'!G31="","",'RC Customers by plan'!G31)) -> 167.16581 | I7: =IF(IF(IF(ISERROR('RC Customers by plan'!I5=0),'RC Customers by plan'!I5=0,IF('RC Customers by plan'!I5="","",'RC Customers by plan'!I5=0))="",FALSE,IF(ISERROR('RC Customers by plan'!I5=0),'RC Customers by plan'!I5=0,IF('RC Customers by plan'!I5="","",'RC Customers by plan'!I5=0))),IF('Model inputs'!AG86="","",'Model inputs'!AG86),IF('RC Customers by plan'!H31="","",'RC Customers by plan'!H31)) -> 192.75462 | J7: =IF(IF(IF(ISERROR('RC Customers by plan'!J5=0),'RC Customers by plan'!J5=0,IF('RC Customers by plan'!J5="","",'RC Customers by plan'!J5=0))="",FALSE,IF(ISERROR('RC Customers by plan'!J5=0),'RC Customers by plan'!J5=0,IF('RC Customers by plan'!J5="","",'RC Customers by plan'!J5=0))),IF('Model inputs'!AG86="","",'Model inputs'!AG86),IF('RC Customers by plan'!I31="","",'RC Customers by plan'!I31)) -> 219.57617 | K7: =IF(IF(IF(ISERROR('RC Customers by plan'!K5=0),'RC Customers by plan'!K5=0,IF('RC Customers by plan'!K5="","",'RC Customers by plan'!K5=0))="",FALSE,IF(ISERROR('RC Customers by plan'!K5=0),'RC Customers by plan'!K5=0,IF('RC Customers by plan'!K5="","",'RC Customers by plan'!K5=0))),IF('Model inputs'!AG86="","",'Model inputs'!AG86),IF('RC Customers by plan'!J31="","",'RC Customers by plan'!J31)) -> 247.78337 | L7: =IF(IF(IF(ISERROR('RC Customers by plan'!L5=0),'RC Customers by plan'!L5=0,IF('RC Customers by plan'!L5="","",'RC Customers by plan'!L5=0))="",FALSE,IF(ISERROR('RC Customers by plan'!L5=0),'RC Customers by plan'!L5=0,IF('RC Customers by plan'!L5="","",'RC Customers by plan'!L5=0))),IF('Model inputs'!AG86="","",'Model inputs'!AG86),IF('RC Customers by plan'!K31="","",'RC Customers by plan'!K31)) -> 275.82391 | M7: =IF(IF(IF(ISERROR('RC Customers by plan'!M5=0),'RC Customers by plan'!M5=0,IF('RC Customers by plan'!M5="","",'RC Customers by plan'!M5=0))="",FALSE,IF(ISERROR('RC Customers by plan'!M5=0),'RC Customers by plan'!M5=0,IF('RC Customers by plan'!M5="","",'RC Customers by plan'!M5=0))),IF('Model inputs'!AG86="","",'Model inputs'!AG86),IF('RC Customers by plan'!L31="","",'RC Customers by plan'!L31)) -> 303.77745 | N7: =IF(IF(IF(ISERROR('RC Customers by plan'!N5=0),'RC Customers by plan'!N5=0,IF('RC Customers by plan'!N5="","",'RC Customers by plan'!N5=0))="",FALSE,IF(ISERROR('RC Customers by plan'!N5=0),'RC Customers by plan'!N5=0,IF('RC Customers by plan'!N5="","",'RC Customers by plan'!N5=0))),IF('Model inputs'!AG86="","",'Model inputs'!AG86),IF('RC Customers by plan'!M31="","",'RC Customers by plan'!M31)) -> 331.7211 | O7: =IF(IF(IF(ISERROR('RC Customers by plan'!O5=0),'RC Customers by plan'!O5=0,IF('RC Customers by plan'!O5="","",'RC Customers by plan'!O5=0))="",FALSE,IF(ISERROR('RC Customers by plan'!O5=0),'RC Customers by plan'!O5=0,IF('RC Customers by plan'!O5="","",'RC Customers by plan'!O5=0))),IF('Model inputs'!AG86="","",'Model inputs'!AG86),IF('RC Customers by plan'!N31="","",'RC Customers by plan'!N31)) -> 359.72966 | P7: =IF(IF(IF(ISERROR('RC Customers by plan'!P5=0),'RC Customers by plan'!P5=0,IF('RC Customers by plan'!P5="","",'RC Customers by plan'!P5=0))="",FALSE,IF(ISERROR('RC Customers by plan'!P5=0),'RC Customers by plan'!P5=0,IF('RC Customers by plan'!P5="","",'RC Customers by plan'!P5=0))),IF('Model inputs'!AG86="","",'Model inputs'!AG86),IF('RC Customers by plan'!O31="","",'RC Customers by plan'!O31)) -> 387.87592 | Q7: =IF(IF(IF(ISERROR('RC Customers by plan'!Q5=0),'RC Customers by plan'!Q5=0,IF('RC Customers by plan'!Q5="","",'RC Customers by plan'!Q5=0))="",FALSE,IF(ISERROR('RC Customers by plan'!Q5=0),'RC Customers by plan'!Q5=0,IF('RC Customers by plan'!Q5="","",'RC Customers by plan'!Q5=0))),IF('Model inputs'!AG86="","",'Model inputs'!AG86),IF('RC Customers by plan'!P31="","",'RC Customers by plan'!P31)) -> 416.23088 | R7: =IF(IF(IF(ISERROR('RC Customers by plan'!R5=0),'RC Customers by plan'!R5=0,IF('RC Customers by plan'!R5="","",'RC Customers by plan'!R5=0))="",FALSE,IF(ISERROR('RC Customers by plan'!R5=0),'RC Customers by plan'!R5=0,IF('RC Customers by plan'!R5="","",'RC Customers by plan'!R5=0))),IF('Model inputs'!AG86="","",'Model inputs'!AG86),IF('RC Customers by plan'!Q31="","",'RC Customers by plan'!Q31)) -> 444.86405 | S7: =IF(IF(IF(ISERROR('RC Customers by plan'!S5=0),'RC Customers by plan'!S5=0,IF('RC Customers by plan'!S5="","",'RC Customers by plan'!S5=0))="",FALSE,IF(ISERROR('RC Customers by plan'!S5=0),'RC Customers by plan'!S5=0,IF('RC Customers by plan'!S5="","",'RC Customers by plan'!S5=0))),IF('Model inputs'!AG86="","",'Model inputs'!AG86),IF('RC Customers by plan'!R31="","",'RC Customers by plan'!R31)) -> 473.84362
A8: Launch | B8: =IF(IF(IF(ISERROR('RC Customers by plan'!B5=0),'RC Customers by plan'!B5=0,IF('RC Customers by plan'!B5="","",'RC Customers by plan'!B5=0))="",FALSE,IF(ISERROR('RC Customers by plan'!B5=0),'RC Customers by plan'!B5=0,IF('RC Customers by plan'!B5="","",'RC Customers by plan'!B5=0))),IF('Model inputs'!AG87="","",'Model inputs'!AG87),IF('Model inputs'!N39="","",'Model inputs'!N39)) -> 1 | C8: =IF(IF(IF(ISERROR('RC Customers by plan'!C5=0),'RC Customers by plan'!C5=0,IF('RC Customers by plan'!C5="","",'RC Customers by plan'!C5=0))="",FALSE,IF(ISERROR('RC Customers by plan'!C5=0),'RC Customers by plan'!C5=0,IF('RC Customers by plan'!C5="","",'RC Customers by plan'!C5=0))),IF('Model inputs'!AG87="","",'Model inputs'!AG87),IF('RC Customers by plan'!B32="","",'RC Customers by plan'!B32)) -> 1 | D8: =IF(IF(IF(ISERROR('RC Customers by plan'!D5=0),'RC Customers by plan'!D5=0,IF('RC Customers by plan'!D5="","",'RC Customers by plan'!D5=0))="",FALSE,IF(ISERROR('RC Customers by plan'!D5=0),'RC Customers by plan'!D5=0,IF('RC Customers by plan'!D5="","",'RC Customers by plan'!D5=0))),IF('Model inputs'!AG87="","",'Model inputs'!AG87),IF('RC Customers by plan'!C32="","",'RC Customers by plan'!C32)) -> 1.51 | E8: =IF(IF(IF(ISERROR('RC Customers by plan'!E5=0),'RC Customers by plan'!E5=0,IF('RC Customers by plan'!E5="","",'RC Customers by plan'!E5=0))="",FALSE,IF(ISERROR('RC Customers by plan'!E5=0),'RC Customers by plan'!E5=0,IF('RC Customers by plan'!E5="","",'RC Customers by plan'!E5=0))),IF('Model inputs'!AG87="","",'Model inputs'!AG87),IF('RC Customers by plan'!D32="","",'RC Customers by plan'!D32)) -> 2.0251069 | F8: =IF(IF(IF(ISERROR('RC Customers by plan'!F5=0),'RC Customers by plan'!F5=0,IF('RC Customers by plan'!F5="","",'RC Customers by plan'!F5=0))="",FALSE,IF(ISERROR('RC Customers by plan'!F5=0),'RC Customers by plan'!F5=0,IF('RC Customers by plan'!F5="","",'RC Customers by plan'!F5=0))),IF('Model inputs'!AG87="","",'Model inputs'!AG87),IF('RC Customers by plan'!E32="","",'RC Customers by plan'!E32)) -> 2.5470121 | G8: =IF(IF(IF(ISERROR('RC Customers by plan'!G5=0),'RC Customers by plan'!G5=0,IF('RC Customers by plan'!G5="","",'RC Customers by plan'!G5=0))="",FALSE,IF(ISERROR('RC Customers by plan'!G5=0),'RC Customers by plan'!G5=0,IF('RC Customers by plan'!G5="","",'RC Customers by plan'!G5=0))),IF('Model inputs'!AG87="","",'Model inputs'!AG87),IF('RC Customers by plan'!F32="","",'RC Customers by plan'!F32)) -> 3.0771045 | H8: =IF(IF(IF(ISERROR('RC Customers by plan'!H5=0),'RC Customers by plan'!H5=0,IF('RC Customers by plan'!H5="","",'RC Customers by plan'!H5=0))="",FALSE,IF(ISERROR('RC Customers by plan'!H5=0),'RC Customers by plan'!H5=0,IF('RC Customers by plan'!H5="","",'RC Customers by plan'!H5=0))),IF('Model inputs'!AG87="","",'Model inputs'!AG87),IF('RC Customers by plan'!G32="","",'RC Customers by plan'!G32)) -> 3.6168582 | I8: =IF(IF(IF(ISERROR('RC Customers by plan'!I5=0),'RC Customers by plan'!I5=0,IF('RC Customers by plan'!I5="","",'RC Customers by plan'!I5=0))="",FALSE,IF(ISERROR('RC Customers by plan'!I5=0),'RC Customers by plan'!I5=0,IF('RC Customers by plan'!I5="","",'RC Customers by plan'!I5=0))),IF('Model inputs'!AG87="","",'Model inputs'!AG87),IF('RC Customers by plan'!H32="","",'RC Customers by plan'!H32)) -> 4.1678445 | J8: =IF(IF(IF(ISERROR('RC Customers by plan'!J5=0),'RC Customers by plan'!J5=0,IF('RC Customers by plan'!J5="","",'RC Customers by plan'!J5=0))="",FALSE,IF(ISERROR('RC Customers by plan'!J5=0),'RC Customers by plan'!J5=0,IF('RC Customers by plan'!J5="","",'RC Customers by plan'!J5=0))),IF('Model inputs'!AG87="","",'Model inputs'!AG87),IF('RC Customers by plan'!I32="","",'RC Customers by plan'!I32)) -> 4.7317452 | K8: =IF(IF(IF(ISERROR('RC Customers by plan'!K5=0),'RC Customers by plan'!K5=0,IF('RC Customers by plan'!K5="","",'RC Customers by plan'!K5=0))="",FALSE,IF(ISERROR('RC Customers by plan'!K5=0),'RC Customers by plan'!K5=0,IF('RC Customers by plan'!K5="","",'RC Customers by plan'!K5=0))),IF('Model inputs'!AG87="","",'Model inputs'!AG87),IF('RC Customers by plan'!J32="","",'RC Customers by plan'!J32)) -> 5.3103669 | L8: =IF(IF(IF(ISERROR('RC Customers by plan'!L5=0),'RC Customers by plan'!L5=0,IF('RC Customers by plan'!L5="","",'RC Customers by plan'!L5=0))="",FALSE,IF(ISERROR('RC Customers by plan'!L5=0),'RC Customers by plan'!L5=0,IF('RC Customers by plan'!L5="","",'RC Customers by plan'!L5=0))),IF('Model inputs'!AG87="","",'Model inputs'!AG87),IF('RC Customers by plan'!K32="","",'RC Customers by plan'!K32)) -> 5.9056563 | M8: =IF(IF(IF(ISERROR('RC Customers by plan'!M5=0),'RC Customers by plan'!M5=0,IF('RC Customers by plan'!M5="","",'RC Customers by plan'!M5=0))="",FALSE,IF(ISERROR('RC Customers by plan'!M5=0),'RC Customers by plan'!M5=0,IF('RC Customers by plan'!M5="","",'RC Customers by plan'!M5=0))),IF('Model inputs'!AG87="","",'Model inputs'!AG87),IF('RC Customers by plan'!L32="","",'RC Customers by plan'!L32)) -> 6.5182553 | N8: =IF(IF(IF(ISERROR('RC Customers by plan'!N5=0),'RC Customers by plan'!N5=0,IF('RC Customers by plan'!N5="","",'RC Customers by plan'!N5=0))="",FALSE,IF(ISERROR('RC Customers by plan'!N5=0),'RC Customers by plan'!N5=0,IF('RC Customers by plan'!N5="","",'RC Customers by plan'!N5=0))),IF('Model inputs'!AG87="","",'Model inputs'!AG87),IF('RC Customers by plan'!M32="","",'RC Customers by plan'!M32)) -> 7.1487999 | O8: =IF(IF(IF(ISERROR('RC Customers by plan'!O5=0),'RC Customers by plan'!O5=0,IF('RC Customers by plan'!O5="","",'RC Customers by plan'!O5=0))="",FALSE,IF(ISERROR('RC Customers by plan'!O5=0),'RC Customers by plan'!O5=0,IF('RC Customers by plan'!O5="","",'RC Customers by plan'!O5=0))),IF('Model inputs'!AG87="","",'Model inputs'!AG87),IF('RC Customers by plan'!N32="","",'RC Customers by plan'!N32)) -> 7.7979243 | P8: =IF(IF(IF(ISERROR('RC Customers by plan'!P5=0),'RC Customers by plan'!P5=0,IF('RC Customers by plan'!P5="","",'RC Customers by plan'!P5=0))="",FALSE,IF(ISERROR('RC Customers by plan'!P5=0),'RC Customers by plan'!P5=0,IF('RC Customers by plan'!P5="","",'RC Customers by plan'!P5=0))),IF('Model inputs'!AG87="","",'Model inputs'!AG87),IF('RC Customers by plan'!O32="","",'RC Customers by plan'!O32)) -> 8.466264 | Q8: =IF(IF(IF(ISERROR('RC Customers by plan'!Q5=0),'RC Customers by plan'!Q5=0,IF('RC Customers by plan'!Q5="","",'RC Customers by plan'!Q5=0))="",FALSE,IF(ISERROR('RC Customers by plan'!Q5=0),'RC Customers by plan'!Q5=0,IF('RC Customers by plan'!Q5="","",'RC Customers by plan'!Q5=0))),IF('Model inputs'!AG87="","",'Model inputs'!AG87),IF('RC Customers by plan'!P32="","",'RC Customers by plan'!P32)) -> 9.1544595 | R8: =IF(IF(IF(ISERROR('RC Customers by plan'!R5=0),'RC Customers by plan'!R5=0,IF('RC Customers by plan'!R5="","",'RC Customers by plan'!R5=0))="",FALSE,IF(ISERROR('RC Customers by plan'!R5=0),'RC Customers by plan'!R5=0,IF('RC Customers by plan'!R5="","",'RC Customers by plan'!R5=0))),IF('Model inputs'!AG87="","",'Model inputs'!AG87),IF('RC Customers by plan'!Q32="","",'RC Customers by plan'!Q32)) -> 9.8631592 | S8: =IF(IF(IF(ISERROR('RC Customers by plan'!S5=0),'RC Customers by plan'!S5=0,IF('RC Customers by plan'!S5="","",'RC Customers by plan'!S5=0))="",FALSE,IF(ISERROR('RC Customers by plan'!S5=0),'RC Customers by plan'!S5=0,IF('RC Customers by plan'!S5="","",'RC Customers by plan'!S5=0))),IF('Model inputs'!AG87="","",'Model inputs'!AG87),IF('RC Customers by plan'!R32="","",'RC Customers by plan'!R32)) -> 10.593023
A9: Team | B9: =IF(IF(IF(ISERROR('RC Customers by plan'!B5=0),'RC Customers by plan'!B5=0,IF('RC Customers by plan'!B5="","",'RC Customers by plan'!B5=0))="",FALSE,IF(ISERROR('RC Customers by plan'!B5=0),'RC Customers by plan'!B5=0,IF('RC Customers by plan'!B5="","",'RC Customers by plan'!B5=0))),IF('Model inputs'!AG88="","",'Model inputs'!AG88),IF('Model inputs'!N40="","",'Model inputs'!N40)) -> 6 | C9: =IF(IF(IF(ISERROR('RC Customers by plan'!C5=0),'RC Customers by plan'!C5=0,IF('RC Customers by plan'!C5="","",'RC Customers by plan'!C5=0))="",FALSE,IF(ISERROR('RC Customers by plan'!C5=0),'RC Customers by plan'!C5=0,IF('RC Customers by plan'!C5="","",'RC Customers by plan'!C5=0))),IF('Model inputs'!AG88="","",'Model inputs'!AG88),IF('RC Customers by plan'!B33="","",'RC Customers by plan'!B33)) -> 6 | D9: =IF(IF(IF(ISERROR('RC Customers by plan'!D5=0),'RC Customers by plan'!D5=0,IF('RC Customers by plan'!D5="","",'RC Customers by plan'!D5=0))="",FALSE,IF(ISERROR('RC Customers by plan'!D5=0),'RC Customers by plan'!D5=0,IF('RC Customers by plan'!D5="","",'RC Customers by plan'!D5=0))),IF('Model inputs'!AG88="","",'Model inputs'!AG88),IF('RC Customers by plan'!C33="","",'RC Customers by plan'!C33)) -> 9.0616667 | E9: =IF(IF(IF(ISERROR('RC Customers by plan'!E5=0),'RC Customers by plan'!E5=0,IF('RC Customers by plan'!E5="","",'RC Customers by plan'!E5=0))="",FALSE,IF(ISERROR('RC Customers by plan'!E5=0),'RC Customers by plan'!E5=0,IF('RC Customers by plan'!E5="","",'RC Customers by plan'!E5=0))),IF('Model inputs'!AG88="","",'Model inputs'!AG88),IF('RC Customers by plan'!D33="","",'RC Customers by plan'!D33)) -> 12.547615 | F9: =IF(IF(IF(ISERROR('RC Customers by plan'!F5=0),'RC Customers by plan'!F5=0,IF('RC Customers by plan'!F5="","",'RC Customers by plan'!F5=0))="",FALSE,IF(ISERROR('RC Customers by plan'!F5=0),'RC Customers by plan'!F5=0,IF('RC Customers by plan'!F5="","",'RC Customers by plan'!F5=0))),IF('Model inputs'!AG88="","",'Model inputs'!AG88),IF('RC Customers by plan'!E33="","",'RC Customers by plan'!E33)) -> 16.391424 | G9: =IF(IF(IF(ISERROR('RC Customers by plan'!G5=0),'RC Customers by plan'!G5=0,IF('RC Customers by plan'!G5="","",'RC Customers by plan'!G5=0))="",FALSE,IF(ISERROR('RC Customers by plan'!G5=0),'RC Customers by plan'!G5=0,IF('RC Customers by plan'!G5="","",'RC Customers by plan'!G5=0))),IF('Model inputs'!AG88="","",'Model inputs'!AG88),IF('RC Customers by plan'!F33="","",'RC Customers by plan'!F33)) -> 20.618467 | H9: =IF(IF(IF(ISERROR('RC Customers by plan'!H5=0),'RC Customers by plan'!H5=0,IF('RC Customers by plan'!H5="","",'RC Customers by plan'!H5=0))="",FALSE,IF(ISERROR('RC Customers by plan'!H5=0),'RC Customers by plan'!H5=0,IF('RC Customers by plan'!H5="","",'RC Customers by plan'!H5=0))),IF('Model inputs'!AG88="","",'Model inputs'!AG88),IF('RC Customers by plan'!G33="","",'RC Customers by plan'!G33)) -> 25.2574 | I9: =IF(IF(IF(ISERROR('RC Customers by plan'!I5=0),'RC Customers by plan'!I5=0,IF('RC Customers by plan'!I5="","",'RC Customers by plan'!I5=0))="",FALSE,IF(ISERROR('RC Customers by plan'!I5=0),'RC Customers by plan'!I5=0,IF('RC Customers by plan'!I5="","",'RC Customers by plan'!I5=0))),IF('Model inputs'!AG88="","",'Model inputs'!AG88),IF('RC Customers by plan'!H33="","",'RC Customers by plan'!H33)) -> 30.340408 | J9: =IF(IF(IF(ISERROR('RC Customers by plan'!J5=0),'RC Customers by plan'!J5=0,IF('RC Customers by plan'!J5="","",'RC Customers by plan'!J5=0))="",FALSE,IF(ISERROR('RC Customers by plan'!J5=0),'RC Customers by plan'!J5=0,IF('RC Customers by plan'!J5="","",'RC Customers by plan'!J5=0))),IF('Model inputs'!AG88="","",'Model inputs'!AG88),IF('RC Customers by plan'!I33="","",'RC Customers by plan'!I33)) -> 35.903491 | K9: =IF(IF(IF(ISERROR('RC Customers by plan'!K5=0),'RC Customers by plan'!K5=0,IF('RC Customers by plan'!K5="","",'RC Customers by plan'!K5=0))="",FALSE,IF(ISERROR('RC Customers by plan'!K5=0),'RC Customers by plan'!K5=0,IF('RC Customers by plan'!K5="","",'RC Customers by plan'!K5=0))),IF('Model inputs'!AG88="","",'Model inputs'!AG88),IF('RC Customers by plan'!J33="","",'RC Customers by plan'!J33)) -> 41.986781 | L9: =IF(IF(IF(ISERROR('RC Customers by plan'!L5=0),'RC Customers by plan'!L5=0,IF('RC Customers by plan'!L5="","",'RC Customers by plan'!L5=0))="",FALSE,IF(ISERROR('RC Customers by plan'!L5=0),'RC Customers by plan'!L5=0,IF('RC Customers by plan'!L5="","",'RC Customers by plan'!L5=0))),IF('Model inputs'!AG88="","",'Model inputs'!AG88),IF('RC Customers by plan'!K33="","",'RC Customers by plan'!K33)) -> 48.284119 | M9: =IF(IF(IF(ISERROR('RC Customers by plan'!M5=0),'RC Customers by plan'!M5=0,IF('RC Customers by plan'!M5="","",'RC Customers by plan'!M5=0))="",FALSE,IF(ISERROR('RC Customers by plan'!M5=0),'RC Customers by plan'!M5=0,IF('RC Customers by plan'!M5="","",'RC Customers by plan'!M5=0))),IF('Model inputs'!AG88="","",'Model inputs'!AG88),IF('RC Customers by plan'!L33="","",'RC Customers by plan'!L33)) -> 54.796435 | N9: =IF(IF(IF(ISERROR('RC Customers by plan'!N5=0),'RC Customers by plan'!N5=0,IF('RC Customers by plan'!N5="","",'RC Customers by plan'!N5=0))="",FALSE,IF(ISERROR('RC Customers by plan'!N5=0),'RC Customers by plan'!N5=0,IF('RC Customers by plan'!N5="","",'RC Customers by plan'!N5=0))),IF('Model inputs'!AG88="","",'Model inputs'!AG88),IF('RC Customers by plan'!M33="","",'RC Customers by plan'!M33)) -> 61.525531 | O9: =IF(IF(IF(ISERROR('RC Customers by plan'!O5=0),'RC Customers by plan'!O5=0,IF('RC Customers by plan'!O5="","",'RC Customers by plan'!O5=0))="",FALSE,IF(ISERROR('RC Customers by plan'!O5=0),'RC Customers by plan'!O5=0,IF('RC Customers by plan'!O5="","",'RC Customers by plan'!O5=0))),IF('Model inputs'!AG88="","",'Model inputs'!AG88),IF('RC Customers by plan'!N33="","",'RC Customers by plan'!N33)) -> 68.474053 | P9: =IF(IF(IF(ISERROR('RC Customers by plan'!P5=0),'RC Customers by plan'!P5=0,IF('RC Customers by plan'!P5="","",'RC Customers by plan'!P5=0))="",FALSE,IF(ISERROR('RC Customers by plan'!P5=0),'RC Customers by plan'!P5=0,IF('RC Customers by plan'!P5="","",'RC Customers by plan'!P5=0))),IF('Model inputs'!AG88="","",'Model inputs'!AG88),IF('RC Customers by plan'!O33="","",'RC Customers by plan'!O33)) -> 75.645458 | Q9: =IF(IF(IF(ISERROR('RC Customers by plan'!Q5=0),'RC Customers by plan'!Q5=0,IF('RC Customers by plan'!Q5="","",'RC Customers by plan'!Q5=0))="",FALSE,IF(ISERROR('RC Customers by plan'!Q5=0),'RC Customers by plan'!Q5=0,IF('RC Customers by plan'!Q5="","",'RC Customers by plan'!Q5=0))),IF('Model inputs'!AG88="","",'Model inputs'!AG88),IF('RC Customers by plan'!P33="","",'RC Customers by plan'!P33)) -> 83.04399 | R9: =IF(IF(IF(ISERROR('RC Customers by plan'!R5=0),'RC Customers by plan'!R5=0,IF('RC Customers by plan'!R5="","",'RC Customers by plan'!R5=0))="",FALSE,IF(ISERROR('RC Customers by plan'!R5=0),'RC Customers by plan'!R5=0,IF('RC Customers by plan'!R5="","",'RC Customers by plan'!R5=0))),IF('Model inputs'!AG88="","",'Model inputs'!AG88),IF('RC Customers by plan'!Q33="","",'RC Customers by plan'!Q33)) -> 90.674663 | S9: =IF(IF(IF(ISERROR('RC Customers by plan'!S5=0),'RC Customers by plan'!S5=0,IF('RC Customers by plan'!S5="","",'RC Customers by plan'!S5=0))="",FALSE,IF(ISERROR('RC Customers by plan'!S5=0),'RC Customers by plan'!S5=0,IF('RC Customers by plan'!S5="","",'RC Customers by plan'!S5=0))),IF('Model inputs'!AG88="","",'Model inputs'!AG88),IF('RC Customers by plan'!R33="","",'RC Customers by plan'!R33)) -> 98.543234
A10: Organic new logos | B10: =SUM('RC Customers by plan'!B11,'RC Customers by plan'!B12,'RC Customers by plan'!B13) -> 0 | C10: =SUM('RC Customers by plan'!C11,'RC Customers by plan'!C12,'RC Customers by plan'!C13) -> 28.5 | D10: =SUM('RC Customers by plan'!D11,'RC Customers by plan'!D12,'RC Customers by plan'!D13) -> 30.8 | E10: =SUM('RC Customers by plan'!E11,'RC Customers by plan'!E12,'RC Customers by plan'!E13) -> 33.29 | F10: =SUM('RC Customers by plan'!F11,'RC Customers by plan'!F12,'RC Customers by plan'!F13) -> 35.9858 | G10: =SUM('RC Customers by plan'!G11,'RC Customers by plan'!G12,'RC Customers by plan'!G13) -> 38.904524 | H10: =SUM('RC Customers by plan'!H11,'RC Customers by plan'!H12,'RC Customers by plan'!H13) -> 42.064732 | I10: =SUM('RC Customers by plan'!I11,'RC Customers by plan'!I12,'RC Customers by plan'!I13) -> 45.486541 | ... S10: =SUM('RC Customers by plan'!S11,'RC Customers by plan'!S12,'RC Customers by plan'!S13) -> 69.803554
A11: Indie | B11: =IF(IF(IF(ISERROR('RC Customers by plan'!B5<1),'RC Customers by plan'!B5<1,IF('RC Customers by plan'!B5="","",'RC Customers by plan'!B5<1))="",FALSE,IF(ISERROR('RC Customers by plan'!B5<1),'RC Customers by plan'!B5<1,IF('RC Customers by plan'!B5="","",'RC Customers by plan'!B5<1))),0,IF(IF(IF(ISERROR('RC Customers by plan'!B5=1),'RC Customers by plan'!B5=1,IF('RC Customers by plan'!B5="","",'RC Customers by plan'!B5=1))="",FALSE,IF(ISERROR('RC Customers by plan'!B5=1),'RC Customers by plan'!B5=1,IF('RC Customers by plan'!B5="","",'RC Customers by plan'!B5=1))),IF('Model inputs'!AG69="","",'Model inputs'!AG69),'Model inputs'!N77*(1+IF(IF(IF(IF(ISERROR('RC Customers by plan'!B5<=8),'RC Customers by plan'!B5<=8,IF('RC Customers by plan'!B5="","",'RC Customers by plan'!B5<=8))="",FALSE,IF(ISERROR('RC Customers by plan'!B5<=8),'RC Customers by plan'!B5<=8,IF('RC Customers by plan'!B5="","",'RC Customers by plan'!B5<=8))),IF('Model inputs'!AG50="","",'Model inputs'!AG50),IF('Model inputs'!AG46="","",'Model inputs'!AG46))="",0,IF(IF(IF(ISERROR('RC Customers by plan'!B5<=8),'RC Customers by plan'!B5<=8,IF('RC Customers by plan'!B5="","",'RC Customers by plan'!B5<=8))="",FALSE,IF(ISERROR('RC Customers by plan'!B5<=8),'RC Customers by plan'!B5<=8,IF('RC Customers by plan'!B5="","",'RC Customers by plan'!B5<=8))),IF('Model inputs'!AG50="","",'Model inputs'!AG50),IF('Model inputs'!AG46="","",'Model inputs'!AG46)))))) -> 0 | C11: =IF(IF(IF(ISERROR('RC Customers by plan'!C5<1),'RC Customers by plan'!C5<1,IF('RC Customers by plan'!C5="","",'RC Customers by plan'!C5<1))="",FALSE,IF(ISERROR('RC Customers by plan'!C5<1),'RC Customers by plan'!C5<1,IF('RC Customers by plan'!C5="","",'RC Customers by plan'!C5<1))),0,IF(IF(IF(ISERROR('RC Customers by plan'!C5=1),'RC Customers by plan'!C5=1,IF('RC Customers by plan'!C5="","",'RC Customers by plan'!C5=1))="",FALSE,IF(ISERROR('RC Customers by plan'!C5=1),'RC Customers by plan'!C5=1,IF('RC Customers by plan'!C5="","",'RC Customers by plan'!C5=1))),IF('Model inputs'!AG69="","",'Model inputs'!AG69),'RC Customers by plan'!B11*(1+IF(IF(IF(IF(ISERROR('RC Customers by plan'!C5<=8),'RC Customers by plan'!C5<=8,IF('RC Customers by plan'!C5="","",'RC Customers by plan'!C5<=8))="",FALSE,IF(ISERROR('RC Customers by plan'!C5<=8),'RC Customers by plan'!C5<=8,IF('RC Customers by plan'!C5="","",'RC Customers by plan'!C5<=8))),IF('Model inputs'!AG50="","",'Model inputs'!AG50),IF('Model inputs'!AG46="","",'Model inputs'!AG46))="",0,IF(IF(IF(ISERROR('RC Customers by plan'!C5<=8),'RC Customers by plan'!C5<=8,IF('RC Customers by plan'!C5="","",'RC Customers by plan'!C5<=8))="",FALSE,IF(ISERROR('RC Customers by plan'!C5<=8),'RC Customers by plan'!C5<=8,IF('RC Customers by plan'!C5="","",'RC Customers by plan'!C5<=8))),IF('Model inputs'!AG50="","",'Model inputs'!AG50),IF('Model inputs'!AG46="","",'Model inputs'!AG46)))))) -> 25 | D11: =IF(IF(IF(ISERROR('RC Customers by plan'!D5<1),'RC Customers by plan'!D5<1,IF('RC Customers by plan'!D5="","",'RC Customers by plan'!D5<1))="",FALSE,IF(ISERROR('RC Customers by plan'!D5<1),'RC Customers by plan'!D5<1,IF('RC Customers by plan'!D5="","",'RC Customers by plan'!D5<1))),0,IF(IF(IF(ISERROR('RC Customers by plan'!D5=1),'RC Customers by plan'!D5=1,IF('RC Customers by plan'!D5="","",'RC Customers by plan'!D5=1))="",FALSE,IF(ISERROR('RC Customers by plan'!D5=1),'RC Customers by plan'!D5=1,IF('RC Customers by plan'!D5="","",'RC Customers by plan'!D5=1))),IF('Model inputs'!AG69="","",'Model inputs'!AG69),'RC Customers by plan'!C11*(1+IF(IF(IF(IF(ISERROR('RC Customers by plan'!D5<=8),'RC Customers by plan'!D5<=8,IF('RC Customers by plan'!D5="","",'RC Customers by plan'!D5<=8))="",FALSE,IF(ISERROR('RC Customers by plan'!D5<=8),'RC Customers by plan'!D5<=8,IF('RC Customers by plan'!D5="","",'RC Customers by plan'!D5<=8))),IF('Model inputs'!AG50="","",'Model inputs'!AG50),IF('Model inputs'!AG46="","",'Model inputs'!AG46))="",0,IF(IF(IF(ISERROR('RC Customers by plan'!D5<=8),'RC Customers by plan'!D5<=8,IF('RC Customers by plan'!D5="","",'RC Customers by plan'!D5<=8))="",FALSE,IF(ISERROR('RC Customers by plan'!D5<=8),'RC Customers by plan'!D5<=8,IF('RC Customers by plan'!D5="","",'RC Customers by plan'!D5<=8))),IF('Model inputs'!AG50="","",'Model inputs'!AG50),IF('Model inputs'!AG46="","",'Model inputs'!AG46)))))) -> 27 | E11: =IF(IF(IF(ISERROR('RC Customers by plan'!E5<1),'RC Customers by plan'!E5<1,IF('RC Customers by plan'!E5="","",'RC Customers by plan'!E5<1))="",FALSE,IF(ISERROR('RC Customers by plan'!E5<1),'RC Customers by plan'!E5<1,IF('RC Customers by plan'!E5="","",'RC Customers by plan'!E5<1))),0,IF(IF(IF(ISERROR('RC Customers by plan'!E5=1),'RC Customers by plan'!E5=1,IF('RC Customers by plan'!E5="","",'RC Customers by plan'!E5=1))="",FALSE,IF(ISERROR('RC Customers by plan'!E5=1),'RC Customers by plan'!E5=1,IF('RC Customers by plan'!E5="","",'RC Customers by plan'!E5=1))),IF('Model inputs'!AG69="","",'Model inputs'!AG69),'RC Customers by plan'!D11*(1+IF(IF(IF(IF(ISERROR('RC Customers by plan'!E5<=8),'RC Customers by plan'!E5<=8,IF('RC Customers by plan'!E5="","",'RC Customers by plan'!E5<=8))="",FALSE,IF(ISERROR('RC Customers by plan'!E5<=8),'RC Customers by plan'!E5<=8,IF('RC Customers by plan'!E5="","",'RC Customers by plan'!E5<=8))),IF('Model inputs'!AG50="","",'Model inputs'!AG50),IF('Model inputs'!AG46="","",'Model inputs'!AG46))="",0,IF(IF(IF(ISERROR('RC Customers by plan'!E5<=8),'RC Customers by plan'!E5<=8,IF('RC Customers by plan'!E5="","",'RC Customers by plan'!E5<=8))="",FALSE,IF(ISERROR('RC Customers by plan'!E5<=8),'RC Customers by plan'!E5<=8,IF('RC Customers by plan'!E5="","",'RC Customers by plan'!E5<=8))),IF('Model inputs'!AG50="","",'Model inputs'!AG50),IF('Model inputs'!AG46="","",'Model inputs'!AG46)))))) -> 29.16 | F11: =IF(IF(IF(ISERROR('RC Customers by plan'!F5<1),'RC Customers by plan'!F5<1,IF('RC Customers by plan'!F5="","",'RC Customers by plan'!F5<1))="",FALSE,IF(ISERROR('RC Customers by plan'!F5<1),'RC Customers by plan'!F5<1,IF('RC Customers by plan'!F5="","",'RC Customers by plan'!F5<1))),0,IF(IF(IF(ISERROR('RC Customers by plan'!F5=1),'RC Customers by plan'!F5=1,IF('RC Customers by plan'!F5="","",'RC Customers by plan'!F5=1))="",FALSE,IF(ISERROR('RC Customers by plan'!F5=1),'RC Customers by plan'!F5=1,IF('RC Customers by plan'!F5="","",'RC Customers by plan'!F5=1))),IF('Model inputs'!AG69="","",'Model inputs'!AG69),'RC Customers by plan'!E11*(1+IF(IF(IF(IF(ISERROR('RC Customers by plan'!F5<=8),'RC Customers by plan'!F5<=8,IF('RC Customers by plan'!F5="","",'RC Customers by plan'!F5<=8))="",FALSE,IF(ISERROR('RC Customers by plan'!F5<=8),'RC Customers by plan'!F5<=8,IF('RC Customers by plan'!F5="","",'RC Customers by plan'!F5<=8))),IF('Model inputs'!AG50="","",'Model inputs'!AG50),IF('Model inputs'!AG46="","",'Model inputs'!AG46))="",0,IF(IF(IF(ISERROR('RC Customers by plan'!F5<=8),'RC Customers by plan'!F5<=8,IF('RC Customers by plan'!F5="","",'RC Customers by plan'!F5<=8))="",FALSE,IF(ISERROR('RC Customers by plan'!F5<=8),'RC Customers by plan'!F5<=8,IF('RC Customers by plan'!F5="","",'RC Customers by plan'!F5<=8))),IF('Model inputs'!AG50="","",'Model inputs'!AG50),IF('Model inputs'!AG46="","",'Model inputs'!AG46)))))) -> 31.4928 | G11: =IF(IF(IF(ISERROR('RC Customers by plan'!G5<1),'RC Customers by plan'!G5<1,IF('RC Customers by plan'!G5="","",'RC Customers by plan'!G5<1))="",FALSE,IF(ISERROR('RC Customers by plan'!G5<1),'RC Customers by plan'!G5<1,IF('RC Customers by plan'!G5="","",'RC Customers by plan'!G5<1))),0,IF(IF(IF(ISERROR('RC Customers by plan'!G5=1),'RC Customers by plan'!G5=1,IF('RC Customers by plan'!G5="","",'RC Customers by plan'!G5=1))="",FALSE,IF(ISERROR('RC Customers by plan'!G5=1),'RC Customers by plan'!G5=1,IF('RC Customers by plan'!G5="","",'RC Customers by plan'!G5=1))),IF('Model inputs'!AG69="","",'Model inputs'!AG69),'RC Customers by plan'!F11*(1+IF(IF(IF(IF(ISERROR('RC Customers by plan'!G5<=8),'RC Customers by plan'!G5<=8,IF('RC Customers by plan'!G5="","",'RC Customers by plan'!G5<=8))="",FALSE,IF(ISERROR('RC Customers by plan'!G5<=8),'RC Customers by plan'!G5<=8,IF('RC Customers by plan'!G5="","",'RC Customers by plan'!G5<=8))),IF('Model inputs'!AG50="","",'Model inputs'!AG50),IF('Model inputs'!AG46="","",'Model inputs'!AG46))="",0,IF(IF(IF(ISERROR('RC Customers by plan'!G5<=8),'RC Customers by plan'!G5<=8,IF('RC Customers by plan'!G5="","",'RC Customers by plan'!G5<=8))="",FALSE,IF(ISERROR('RC Customers by plan'!G5<=8),'RC Customers by plan'!G5<=8,IF('RC Customers by plan'!G5="","",'RC Customers by plan'!G5<=8))),IF('Model inputs'!AG50="","",'Model inputs'!AG50),IF('Model inputs'!AG46="","",'Model inputs'!AG46)))))) -> 34.012224 | H11: =IF(IF(IF(ISERROR('RC Customers by plan'!H5<1),'RC Customers by plan'!H5<1,IF('RC Customers by plan'!H5="","",'RC Customers by plan'!H5<1))="",FALSE,IF(ISERROR('RC Customers by plan'!H5<1),'RC Customers by plan'!H5<1,IF('RC Customers by plan'!H5="","",'RC Customers by plan'!H5<1))),0,IF(IF(IF(ISERROR('RC Customers by plan'!H5=1),'RC Customers by plan'!H5=1,IF('RC Customers by plan'!H5="","",'RC Customers by plan'!H5=1))="",FALSE,IF(ISERROR('RC Customers by plan'!H5=1),'RC Customers by plan'!H5=1,IF('RC Customers by plan'!H5="","",'RC Customers by plan'!H5=1))),IF('Model inputs'!AG69="","",'Model inputs'!AG69),'RC Customers by plan'!G11*(1+IF(IF(IF(IF(ISERROR('RC Customers by plan'!H5<=8),'RC Customers by plan'!H5<=8,IF('RC Customers by plan'!H5="","",'RC Customers by plan'!H5<=8))="",FALSE,IF(ISERROR('RC Customers by plan'!H5<=8),'RC Customers by plan'!H5<=8,IF('RC Customers by plan'!H5="","",'RC Customers by plan'!H5<=8))),IF('Model inputs'!AG50="","",'Model inputs'!AG50),IF('Model inputs'!AG46="","",'Model inputs'!AG46))="",0,IF(IF(IF(ISERROR('RC Customers by plan'!H5<=8),'RC Customers by plan'!H5<=8,IF('RC Customers by plan'!H5="","",'RC Customers by plan'!H5<=8))="",FALSE,IF(ISERROR('RC Customers by plan'!H5<=8),'RC Customers by plan'!H5<=8,IF('RC Customers by plan'!H5="","",'RC Customers by plan'!H5<=8))),IF('Model inputs'!AG50="","",'Model inputs'!AG50),IF('Model inputs'!AG46="","",'Model inputs'!AG46)))))) -> 36.733202 | I11: =IF(IF(IF(ISERROR('RC Customers by plan'!I5<1),'RC Customers by plan'!I5<1,IF('RC Customers by plan'!I5="","",'RC Customers by plan'!I5<1))="",FALSE,IF(ISERROR('RC Customers by plan'!I5<1),'RC Customers by plan'!I5<1,IF('RC Customers by plan'!I5="","",'RC Customers by plan'!I5<1))),0,IF(IF(IF(ISERROR('RC Customers by plan'!I5=1),'RC Customers by plan'!I5=1,IF('RC Customers by plan'!I5="","",'RC Customers by plan'!I5=1))="",FALSE,IF(ISERROR('RC Customers by plan'!I5=1),'RC Customers by plan'!I5=1,IF('RC Customers by plan'!I5="","",'RC Customers by plan'!I5=1))),IF('Model inputs'!AG69="","",'Model inputs'!AG69),'RC Customers by plan'!H11*(1+IF(IF(IF(IF(ISERROR('RC Customers by plan'!I5<=8),'RC Customers by plan'!I5<=8,IF('RC Customers by plan'!I5="","",'RC Customers by plan'!I5<=8))="",FALSE,IF(ISERROR('RC Customers by plan'!I5<=8),'RC Customers by plan'!I5<=8,IF('RC Customers by plan'!I5="","",'RC Customers by plan'!I5<=8))),IF('Model inputs'!AG50="","",'Model inputs'!AG50),IF('Model inputs'!AG46="","",'Model inputs'!AG46))="",0,IF(IF(IF(ISERROR('RC Customers by plan'!I5<=8),'RC Customers by plan'!I5<=8,IF('RC Customers by plan'!I5="","",'RC Customers by plan'!I5<=8))="",FALSE,IF(ISERROR('RC Customers by plan'!I5<=8),'RC Customers by plan'!I5<=8,IF('RC Customers by plan'!I5="","",'RC Customers by plan'!I5<=8))),IF('Model inputs'!AG50="","",'Model inputs'!AG50),IF('Model inputs'!AG46="","",'Model inputs'!AG46)))))) -> 39.671858 | J11: =IF(IF(IF(ISERROR('RC Customers by plan'!J5<1),'RC Customers by plan'!J5<1,IF('RC Customers by plan'!J5="","",'RC Customers by plan'!J5<1))="",FALSE,IF(ISERROR('RC Customers by plan'!J5<1),'RC Customers by plan'!J5<1,IF('RC Customers by plan'!J5="","",'RC Customers by plan'!J5<1))),0,IF(IF(IF(ISERROR('RC Customers by plan'!J5=1),'RC Customers by plan'!J5=1,IF('RC Customers by plan'!J5="","",'RC Customers by plan'!J5=1))="",FALSE,IF(ISERROR('RC Customers by plan'!J5=1),'RC Customers by plan'!J5=1,IF('RC Customers by plan'!J5="","",'RC Customers by plan'!J5=1))),IF('Model inputs'!AG69="","",'Model inputs'!AG69),'RC Customers by plan'!I11*(1+IF(IF(IF(IF(ISERROR('RC Customers by plan'!J5<=8),'RC Customers by plan'!J5<=8,IF('RC Customers by plan'!J5="","",'RC Customers by plan'!J5<=8))="",FALSE,IF(ISERROR('RC Customers by plan'!J5<=8),'RC Customers by plan'!J5<=8,IF('RC Customers by plan'!J5="","",'RC Customers by plan'!J5<=8))),IF('Model inputs'!AG50="","",'Model inputs'!AG50),IF('Model inputs'!AG46="","",'Model inputs'!AG46))="",0,IF(IF(IF(ISERROR('RC Customers by plan'!J5<=8),'RC Customers by plan'!J5<=8,IF('RC Customers by plan'!J5="","",'RC Customers by plan'!J5<=8))="",FALSE,IF(ISERROR('RC Customers by plan'!J5<=8),'RC Customers by plan'!J5<=8,IF('RC Customers by plan'!J5="","",'RC Customers by plan'!J5<=8))),IF('Model inputs'!AG50="","",'Model inputs'!AG50),IF('Model inputs'!AG46="","",'Model inputs'!AG46)))))) -> 42.845607 | K11: =IF(IF(IF(ISERROR('RC Customers by plan'!K5<1),'RC Customers by plan'!K5<1,IF('RC Customers by plan'!K5="","",'RC Customers by plan'!K5<1))="",FALSE,IF(ISERROR('RC Customers by plan'!K5<1),'RC Customers by plan'!K5<1,IF('RC Customers by plan'!K5="","",'RC Customers by plan'!K5<1))),0,IF(IF(IF(ISERROR('RC Customers by plan'!K5=1),'RC Customers by plan'!K5=1,IF('RC Customers by plan'!K5="","",'RC Customers by plan'!K5=1))="",FALSE,IF(ISERROR('RC Customers by plan'!K5=1),'RC Customers by plan'!K5=1,IF('RC Customers by plan'!K5="","",'RC Customers by plan'!K5=1))),IF('Model inputs'!AG69="","",'Model inputs'!AG69),'RC Customers by plan'!J11*(1+IF(IF(IF(IF(ISERROR('RC Customers by plan'!K5<=8),'RC Customers by plan'!K5<=8,IF('RC Customers by plan'!K5="","",'RC Customers by plan'!K5<=8))="",FALSE,IF(ISERROR('RC Customers by plan'!K5<=8),'RC Customers by plan'!K5<=8,IF('RC Customers by plan'!K5="","",'RC Customers by plan'!K5<=8))),IF('Model inputs'!AG50="","",'Model inputs'!AG50),IF('Model inputs'!AG46="","",'Model inputs'!AG46))="",0,IF(IF(IF(ISERROR('RC Customers by plan'!K5<=8),'RC Customers by plan'!K5<=8,IF('RC Customers by plan'!K5="","",'RC Customers by plan'!K5<=8))="",FALSE,IF(ISERROR('RC Customers by plan'!K5<=8),'RC Customers by plan'!K5<=8,IF('RC Customers by plan'!K5="","",'RC Customers by plan'!K5<=8))),IF('Model inputs'!AG50="","",'Model inputs'!AG50),IF('Model inputs'!AG46="","",'Model inputs'!AG46)))))) -> 44.559431 | L11: =IF(IF(IF(ISERROR('RC Customers by plan'!L5<1),'RC Customers by plan'!L5<1,IF('RC Customers by plan'!L5="","",'RC Customers by plan'!L5<1))="",FALSE,IF(ISERROR('RC Customers by plan'!L5<1),'RC Customers by plan'!L5<1,IF('RC Customers by plan'!L5="","",'RC Customers by plan'!L5<1))),0,IF(IF(IF(ISERROR('RC Customers by plan'!L5=1),'RC Customers by plan'!L5=1,IF('RC Customers by plan'!L5="","",'RC Customers by plan'!L5=1))="",FALSE,IF(ISERROR('RC Customers by plan'!L5=1),'RC Customers by plan'!L5=1,IF('RC Customers by plan'!L5="","",'RC Customers by plan'!L5=1))),IF('Model inputs'!AG69="","",'Model inputs'!AG69),'RC Customers by plan'!K11*(1+IF(IF(IF(IF(ISERROR('RC Customers by plan'!L5<=8),'RC Customers by plan'!L5<=8,IF('RC Customers by plan'!L5="","",'RC Customers by plan'!L5<=8))="",FALSE,IF(ISERROR('RC Customers by plan'!L5<=8),'RC Customers by plan'!L5<=8,IF('RC Customers by plan'!L5="","",'RC Customers by plan'!L5<=8))),IF('Model inputs'!AG50="","",'Model inputs'!AG50),IF('Model inputs'!AG46="","",'Model inputs'!AG46))="",0,IF(IF(IF(ISERROR('RC Customers by plan'!L5<=8),'RC Customers by plan'!L5<=8,IF('RC Customers by plan'!L5="","",'RC Customers by plan'!L5<=8))="",FALSE,IF(ISERROR('RC Customers by plan'!L5<=8),'RC Customers by plan'!L5<=8,IF('RC Customers by plan'!L5="","",'RC Customers by plan'!L5<=8))),IF('Model inputs'!AG50="","",'Model inputs'!AG50),IF('Model inputs'!AG46="","",'Model inputs'!AG46)))))) -> 46.341808 | M11: =IF(IF(IF(ISERROR('RC Customers by plan'!M5<1),'RC Customers by plan'!M5<1,IF('RC Customers by plan'!M5="","",'RC Customers by plan'!M5<1))="",FALSE,IF(ISERROR('RC Customers by plan'!M5<1),'RC Customers by plan'!M5<1,IF('RC Customers by plan'!M5="","",'RC Customers by plan'!M5<1))),0,IF(IF(IF(ISERROR('RC Customers by plan'!M5=1),'RC Customers by plan'!M5=1,IF('RC Customers by plan'!M5="","",'RC Customers by plan'!M5=1))="",FALSE,IF(ISERROR('RC Customers by plan'!M5=1),'RC Customers by plan'!M5=1,IF('RC Customers by plan'!M5="","",'RC Customers by plan'!M5=1))),IF('Model inputs'!AG69="","",'Model inputs'!AG69),'RC Customers by plan'!L11*(1+IF(IF(IF(IF(ISERROR('RC Customers by plan'!M5<=8),'RC Customers by plan'!M5<=8,IF('RC Customers by plan'!M5="","",'RC Customers by plan'!M5<=8))="",FALSE,IF(ISERROR('RC Customers by plan'!M5<=8),'RC Customers by plan'!M5<=8,IF('RC Customers by plan'!M5="","",'RC Customers by plan'!M5<=8))),IF('Model inputs'!AG50="","",'Model inputs'!AG50),IF('Model inputs'!AG46="","",'Model inputs'!AG46))="",0,IF(IF(IF(ISERROR('RC Customers by plan'!M5<=8),'RC Customers by plan'!M5<=8,IF('RC Customers by plan'!M5="","",'RC Customers by plan'!M5<=8))="",FALSE,IF(ISERROR('RC Customers by plan'!M5<=8),'RC Customers by plan'!M5<=8,IF('RC Customers by plan'!M5="","",'RC Customers by plan'!M5<=8))),IF('Model inputs'!AG50="","",'Model inputs'!AG50),IF('Model inputs'!AG46="","",'Model inputs'!AG46)))))) -> 48.195481 | N11: =IF(IF(IF(ISERROR('RC Customers by plan'!N5<1),'RC Customers by plan'!N5<1,IF('RC Customers by plan'!N5="","",'RC Customers by plan'!N5<1))="",FALSE,IF(ISERROR('RC Customers by plan'!N5<1),'RC Customers by plan'!N5<1,IF('RC Customers by plan'!N5="","",'RC Customers by plan'!N5<1))),0,IF(IF(IF(ISERROR('RC Customers by plan'!N5=1),'RC Customers by plan'!N5=1,IF('RC Customers by plan'!N5="","",'RC Customers by plan'!N5=1))="",FALSE,IF(ISERROR('RC Customers by plan'!N5=1),'RC Customers by plan'!N5=1,IF('RC Customers by plan'!N5="","",'RC Customers by plan'!N5=1))),IF('Model inputs'!AG69="","",'Model inputs'!AG69),'RC Customers by plan'!M11*(1+IF(IF(IF(IF(ISERROR('RC Customers by plan'!N5<=8),'RC Customers by plan'!N5<=8,IF('RC Customers by plan'!N5="","",'RC Customers by plan'!N5<=8))="",FALSE,IF(ISERROR('RC Customers by plan'!N5<=8),'RC Customers by plan'!N5<=8,IF('RC Customers by plan'!N5="","",'RC Customers by plan'!N5<=8))),IF('Model inputs'!AG50="","",'Model inputs'!AG50),IF('Model inputs'!AG46="","",'Model inputs'!AG46))="",0,IF(IF(IF(ISERROR('RC Customers by plan'!N5<=8),'RC Customers by plan'!N5<=8,IF('RC Customers by plan'!N5="","",'RC Customers by plan'!N5<=8))="",FALSE,IF(ISERROR('RC Customers by plan'!N5<=8),'RC Customers by plan'!N5<=8,IF('RC Customers by plan'!N5="","",'RC Customers by plan'!N5<=8))),IF('Model inputs'!AG50="","",'Model inputs'!AG50),IF('Model inputs'!AG46="","",'Model inputs'!AG46)))))) -> 50.1233 | O11: =IF(IF(IF(ISERROR('RC Customers by plan'!O5<1),'RC Customers by plan'!O5<1,IF('RC Customers by plan'!O5="","",'RC Customers by plan'!O5<1))="",FALSE,IF(ISERROR('RC Customers by plan'!O5<1),'RC Customers by plan'!O5<1,IF('RC Customers by plan'!O5="","",'RC Customers by plan'!O5<1))),0,IF(IF(IF(ISERROR('RC Customers by plan'!O5=1),'RC Customers by plan'!O5=1,IF('RC Customers by plan'!O5="","",'RC Customers by plan'!O5=1))="",FALSE,IF(ISERROR('RC Customers by plan'!O5=1),'RC Customers by plan'!O5=1,IF('RC Customers by plan'!O5="","",'RC Customers by plan'!O5=1))),IF('Model inputs'!AG69="","",'Model inputs'!AG69),'RC Customers by plan'!N11*(1+IF(IF(IF(IF(ISERROR('RC Customers by plan'!O5<=8),'RC Customers by plan'!O5<=8,IF('RC Customers by plan'!O5="","",'RC Customers by plan'!O5<=8))="",FALSE,IF(ISERROR('RC Customers by plan'!O5<=8),'RC Customers by plan'!O5<=8,IF('RC Customers by plan'!O5="","",'RC Customers by plan'!O5<=8))),IF('Model inputs'!AG50="","",'Model inputs'!AG50),IF('Model inputs'!AG46="","",'Model inputs'!AG46))="",0,IF(IF(IF(ISERROR('RC Customers by plan'!O5<=8),'RC Customers by plan'!O5<=8,IF('RC Customers by plan'!O5="","",'RC Customers by plan'!O5<=8))="",FALSE,IF(ISERROR('RC Customers by plan'!O5<=8),'RC Customers by plan'!O5<=8,IF('RC Customers by plan'!O5="","",'RC Customers by plan'!O5<=8))),IF('Model inputs'!AG50="","",'Model inputs'!AG50),IF('Model inputs'!AG46="","",'Model inputs'!AG46)))))) -> 52.128232 | P11: =IF(IF(IF(ISERROR('RC Customers by plan'!P5<1),'RC Customers by plan'!P5<1,IF('RC Customers by plan'!P5="","",'RC Customers by plan'!P5<1))="",FALSE,IF(ISERROR('RC Customers by plan'!P5<1),'RC Customers by plan'!P5<1,IF('RC Customers by plan'!P5="","",'RC Customers by plan'!P5<1))),0,IF(IF(IF(ISERROR('RC Customers by plan'!P5=1),'RC Customers by plan'!P5=1,IF('RC Customers by plan'!P5="","",'RC Customers by plan'!P5=1))="",FALSE,IF(ISERROR('RC Customers by plan'!P5=1),'RC Customers by plan'!P5=1,IF('RC Customers by plan'!P5="","",'RC Customers by plan'!P5=1))),IF('Model inputs'!AG69="","",'Model inputs'!AG69),'RC Customers by plan'!O11*(1+IF(IF(IF(IF(ISERROR('RC Customers by plan'!P5<=8),'RC Customers by plan'!P5<=8,IF('RC Customers by plan'!P5="","",'RC Customers by plan'!P5<=8))="",FALSE,IF(ISERROR('RC Customers by plan'!P5<=8),'RC Customers by plan'!P5<=8,IF('RC Customers by plan'!P5="","",'RC Customers by plan'!P5<=8))),IF('Model inputs'!AG50="","",'Model inputs'!AG50),IF('Model inputs'!AG46="","",'Model inputs'!AG46))="",0,IF(IF(IF(ISERROR('RC Customers by plan'!P5<=8),'RC Customers by plan'!P5<=8,IF('RC Customers by plan'!P5="","",'RC Customers by plan'!P5<=8))="",FALSE,IF(ISERROR('RC Customers by plan'!P5<=8),'RC Customers by plan'!P5<=8,IF('RC Customers by plan'!P5="","",'RC Customers by plan'!P5<=8))),IF('Model inputs'!AG50="","",'Model inputs'!AG50),IF('Model inputs'!AG46="","",'Model inputs'!AG46)))))) -> 54.213361 | Q11: =IF(IF(IF(ISERROR('RC Customers by plan'!Q5<1),'RC Customers by plan'!Q5<1,IF('RC Customers by plan'!Q5="","",'RC Customers by plan'!Q5<1))="",FALSE,IF(ISERROR('RC Customers by plan'!Q5<1),'RC Customers by plan'!Q5<1,IF('RC Customers by plan'!Q5="","",'RC Customers by plan'!Q5<1))),0,IF(IF(IF(ISERROR('RC Customers by plan'!Q5=1),'RC Customers by plan'!Q5=1,IF('RC Customers by plan'!Q5="","",'RC Customers by plan'!Q5=1))="",FALSE,IF(ISERROR('RC Customers by plan'!Q5=1),'RC Customers by plan'!Q5=1,IF('RC Customers by plan'!Q5="","",'RC Customers by plan'!Q5=1))),IF('Model inputs'!AG69="","",'Model inputs'!AG69),'RC Customers by plan'!P11*(1+IF(IF(IF(IF(ISERROR('RC Customers by plan'!Q5<=8),'RC Customers by plan'!Q5<=8,IF('RC Customers by plan'!Q5="","",'RC Customers by plan'!Q5<=8))="",FALSE,IF(ISERROR('RC Customers by plan'!Q5<=8),'RC Customers by plan'!Q5<=8,IF('RC Customers by plan'!Q5="","",'RC Customers by plan'!Q5<=8))),IF('Model inputs'!AG50="","",'Model inputs'!AG50),IF('Model inputs'!AG46="","",'Model inputs'!AG46))="",0,IF(IF(IF(ISERROR('RC Customers by plan'!Q5<=8),'RC Customers by plan'!Q5<=8,IF('RC Customers by plan'!Q5="","",'RC Customers by plan'!Q5<=8))="",FALSE,IF(ISERROR('RC Customers by plan'!Q5<=8),'RC Customers by plan'!Q5<=8,IF('RC Customers by plan'!Q5="","",'RC Customers by plan'!Q5<=8))),IF('Model inputs'!AG50="","",'Model inputs'!AG50),IF('Model inputs'!AG46="","",'Model inputs'!AG46)))))) -> 56.381895 | R11: =IF(IF(IF(ISERROR('RC Customers by plan'!R5<1),'RC Customers by plan'!R5<1,IF('RC Customers by plan'!R5="","",'RC Customers by plan'!R5<1))="",FALSE,IF(ISERROR('RC Customers by plan'!R5<1),'RC Customers by plan'!R5<1,IF('RC Customers by plan'!R5="","",'RC Customers by plan'!R5<1))),0,IF(IF(IF(ISERROR('RC Customers by plan'!R5=1),'RC Customers by plan'!R5=1,IF('RC Customers by plan'!R5="","",'RC Customers by plan'!R5=1))="",FALSE,IF(ISERROR('RC Customers by plan'!R5=1),'RC Customers by plan'!R5=1,IF('RC Customers by plan'!R5="","",'RC Customers by plan'!R5=1))),IF('Model inputs'!AG69="","",'Model inputs'!AG69),'RC Customers by plan'!Q11*(1+IF(IF(IF(IF(ISERROR('RC Customers by plan'!R5<=8),'RC Customers by plan'!R5<=8,IF('RC Customers by plan'!R5="","",'RC Customers by plan'!R5<=8))="",FALSE,IF(ISERROR('RC Customers by plan'!R5<=8),'RC Customers by plan'!R5<=8,IF('RC Customers by plan'!R5="","",'RC Customers by plan'!R5<=8))),IF('Model inputs'!AG50="","",'Model inputs'!AG50),IF('Model inputs'!AG46="","",'Model inputs'!AG46))="",0,IF(IF(IF(ISERROR('RC Customers by plan'!R5<=8),'RC Customers by plan'!R5<=8,IF('RC Customers by plan'!R5="","",'RC Customers by plan'!R5<=8))="",FALSE,IF(ISERROR('RC Customers by plan'!R5<=8),'RC Customers by plan'!R5<=8,IF('RC Customers by plan'!R5="","",'RC Customers by plan'!R5<=8))),IF('Model inputs'!AG50="","",'Model inputs'!AG50),IF('Model inputs'!AG46="","",'Model inputs'!AG46)))))) -> 58.637171 | S11: =IF(IF(IF(ISERROR('RC Customers by plan'!S5<1),'RC Customers by plan'!S5<1,IF('RC Customers by plan'!S5="","",'RC Customers by plan'!S5<1))="",FALSE,IF(ISERROR('RC Customers by plan'!S5<1),'RC Customers by plan'!S5<1,IF('RC Customers by plan'!S5="","",'RC Customers by plan'!S5<1))),0,IF(IF(IF(ISERROR('RC Customers by plan'!S5=1),'RC Customers by plan'!S5=1,IF('RC Customers by plan'!S5="","",'RC Customers by plan'!S5=1))="",FALSE,IF(ISERROR('RC Customers by plan'!S5=1),'RC Customers by plan'!S5=1,IF('RC Customers by plan'!S5="","",'RC Customers by plan'!S5=1))),IF('Model inputs'!AG69="","",'Model inputs'!AG69),'RC Customers by plan'!R11*(1+IF(IF(IF(IF(ISERROR('RC Customers by plan'!S5<=8),'RC Customers by plan'!S5<=8,IF('RC Customers by plan'!S5="","",'RC Customers by plan'!S5<=8))="",FALSE,IF(ISERROR('RC Customers by plan'!S5<=8),'RC Customers by plan'!S5<=8,IF('RC Customers by plan'!S5="","",'RC Customers by plan'!S5<=8))),IF('Model inputs'!AG50="","",'Model inputs'!AG50),IF('Model inputs'!AG46="","",'Model inputs'!AG46))="",0,IF(IF(IF(ISERROR('RC Customers by plan'!S5<=8),'RC Customers by plan'!S5<=8,IF('RC Customers by plan'!S5="","",'RC Customers by plan'!S5<=8))="",FALSE,IF(ISERROR('RC Customers by plan'!S5<=8),'RC Customers by plan'!S5<=8,IF('RC Customers by plan'!S5="","",'RC Customers by plan'!S5<=8))),IF('Model inputs'!AG50="","",'Model inputs'!AG50),IF('Model inputs'!AG46="","",'Model inputs'!AG46)))))) -> 60.982658
A12: Launch | B12: =IF(IF(IF(ISERROR('RC Customers by plan'!B5<1),'RC Customers by plan'!B5<1,IF('RC Customers by plan'!B5="","",'RC Customers by plan'!B5<1))="",FALSE,IF(ISERROR('RC Customers by plan'!B5<1),'RC Customers by plan'!B5<1,IF('RC Customers by plan'!B5="","",'RC Customers by plan'!B5<1))),0,IF(IF(IF(ISERROR('RC Customers by plan'!B5=1),'RC Customers by plan'!B5=1,IF('RC Customers by plan'!B5="","",'RC Customers by plan'!B5=1))="",FALSE,IF(ISERROR('RC Customers by plan'!B5=1),'RC Customers by plan'!B5=1,IF('RC Customers by plan'!B5="","",'RC Customers by plan'!B5=1))),IF('Model inputs'!AG70="","",'Model inputs'!AG70),'Model inputs'!N78*(1+IF(IF(IF(IF(ISERROR('RC Customers by plan'!B5<=8),'RC Customers by plan'!B5<=8,IF('RC Customers by plan'!B5="","",'RC Customers by plan'!B5<=8))="",FALSE,IF(ISERROR('RC Customers by plan'!B5<=8),'RC Customers by plan'!B5<=8,IF('RC Customers by plan'!B5="","",'RC Customers by plan'!B5<=8))),IF('Model inputs'!AG51="","",'Model inputs'!AG51),IF('Model inputs'!AG47="","",'Model inputs'!AG47))="",0,IF(IF(IF(ISERROR('RC Customers by plan'!B5<=8),'RC Customers by plan'!B5<=8,IF('RC Customers by plan'!B5="","",'RC Customers by plan'!B5<=8))="",FALSE,IF(ISERROR('RC Customers by plan'!B5<=8),'RC Customers by plan'!B5<=8,IF('RC Customers by plan'!B5="","",'RC Customers by plan'!B5<=8))),IF('Model inputs'!AG51="","",'Model inputs'!AG51),IF('Model inputs'!AG47="","",'Model inputs'!AG47)))))) -> 0 | C12: =IF(IF(IF(ISERROR('RC Customers by plan'!C5<1),'RC Customers by plan'!C5<1,IF('RC Customers by plan'!C5="","",'RC Customers by plan'!C5<1))="",FALSE,IF(ISERROR('RC Customers by plan'!C5<1),'RC Customers by plan'!C5<1,IF('RC Customers by plan'!C5="","",'RC Customers by plan'!C5<1))),0,IF(IF(IF(ISERROR('RC Customers by plan'!C5=1),'RC Customers by plan'!C5=1,IF('RC Customers by plan'!C5="","",'RC Customers by plan'!C5=1))="",FALSE,IF(ISERROR('RC Customers by plan'!C5=1),'RC Customers by plan'!C5=1,IF('RC Customers by plan'!C5="","",'RC Customers by plan'!C5=1))),IF('Model inputs'!AG70="","",'Model inputs'!AG70),'RC Customers by plan'!B12*(1+IF(IF(IF(IF(ISERROR('RC Customers by plan'!C5<=8),'RC Customers by plan'!C5<=8,IF('RC Customers by plan'!C5="","",'RC Customers by plan'!C5<=8))="",FALSE,IF(ISERROR('RC Customers by plan'!C5<=8),'RC Customers by plan'!C5<=8,IF('RC Customers by plan'!C5="","",'RC Customers by plan'!C5<=8))),IF('Model inputs'!AG51="","",'Model inputs'!AG51),IF('Model inputs'!AG47="","",'Model inputs'!AG47))="",0,IF(IF(IF(ISERROR('RC Customers by plan'!C5<=8),'RC Customers by plan'!C5<=8,IF('RC Customers by plan'!C5="","",'RC Customers by plan'!C5<=8))="",FALSE,IF(ISERROR('RC Customers by plan'!C5<=8),'RC Customers by plan'!C5<=8,IF('RC Customers by plan'!C5="","",'RC Customers by plan'!C5<=8))),IF('Model inputs'!AG51="","",'Model inputs'!AG51),IF('Model inputs'!AG47="","",'Model inputs'!AG47)))))) -> 0.5 | D12: =IF(IF(IF(ISERROR('RC Customers by plan'!D5<1),'RC Customers by plan'!D5<1,IF('RC Customers by plan'!D5="","",'RC Customers by plan'!D5<1))="",FALSE,IF(ISERROR('RC Customers by plan'!D5<1),'RC Customers by plan'!D5<1,IF('RC Customers by plan'!D5="","",'RC Customers by plan'!D5<1))),0,IF(IF(IF(ISERROR('RC Customers by plan'!D5=1),'RC Customers by plan'!D5=1,IF('RC Customers by plan'!D5="","",'RC Customers by plan'!D5=1))="",FALSE,IF(ISERROR('RC Customers by plan'!D5=1),'RC Customers by plan'!D5=1,IF('RC Customers by plan'!D5="","",'RC Customers by plan'!D5=1))),IF('Model inputs'!AG70="","",'Model inputs'!AG70),'RC Customers by plan'!C12*(1+IF(IF(IF(IF(ISERROR('RC Customers by plan'!D5<=8),'RC Customers by plan'!D5<=8,IF('RC Customers by plan'!D5="","",'RC Customers by plan'!D5<=8))="",FALSE,IF(ISERROR('RC Customers by plan'!D5<=8),'RC Customers by plan'!D5<=8,IF('RC Customers by plan'!D5="","",'RC Customers by plan'!D5<=8))),IF('Model inputs'!AG51="","",'Model inputs'!AG51),IF('Model inputs'!AG47="","",'Model inputs'!AG47))="",0,IF(IF(IF(ISERROR('RC Customers by plan'!D5<=8),'RC Customers by plan'!D5<=8,IF('RC Customers by plan'!D5="","",'RC Customers by plan'!D5<=8))="",FALSE,IF(ISERROR('RC Customers by plan'!D5<=8),'RC Customers by plan'!D5<=8,IF('RC Customers by plan'!D5="","",'RC Customers by plan'!D5<=8))),IF('Model inputs'!AG51="","",'Model inputs'!AG51),IF('Model inputs'!AG47="","",'Model inputs'!AG47)))))) -> 0.5 | E12: =IF(IF(IF(ISERROR('RC Customers by plan'!E5<1),'RC Customers by plan'!E5<1,IF('RC Customers by plan'!E5="","",'RC Customers by plan'!E5<1))="",FALSE,IF(ISERROR('RC Customers by plan'!E5<1),'RC Customers by plan'!E5<1,IF('RC Customers by plan'!E5="","",'RC Customers by plan'!E5<1))),0,IF(IF(IF(ISERROR('RC Customers by plan'!E5=1),'RC Customers by plan'!E5=1,IF('RC Customers by plan'!E5="","",'RC Customers by plan'!E5=1))="",FALSE,IF(ISERROR('RC Customers by plan'!E5=1),'RC Customers by plan'!E5=1,IF('RC Customers by plan'!E5="","",'RC Customers by plan'!E5=1))),IF('Model inputs'!AG70="","",'Model inputs'!AG70),'RC Customers by plan'!D12*(1+IF(IF(IF(IF(ISERROR('RC Customers by plan'!E5<=8),'RC Customers by plan'!E5<=8,IF('RC Customers by plan'!E5="","",'RC Customers by plan'!E5<=8))="",FALSE,IF(ISERROR('RC Customers by plan'!E5<=8),'RC Customers by plan'!E5<=8,IF('RC Customers by plan'!E5="","",'RC Customers by plan'!E5<=8))),IF('Model inputs'!AG51="","",'Model inputs'!AG51),IF('Model inputs'!AG47="","",'Model inputs'!AG47))="",0,IF(IF(IF(ISERROR('RC Customers by plan'!E5<=8),'RC Customers by plan'!E5<=8,IF('RC Customers by plan'!E5="","",'RC Customers by plan'!E5<=8))="",FALSE,IF(ISERROR('RC Customers by plan'!E5<=8),'RC Customers by plan'!E5<=8,IF('RC Customers by plan'!E5="","",'RC Customers by plan'!E5<=8))),IF('Model inputs'!AG51="","",'Model inputs'!AG51),IF('Model inputs'!AG47="","",'Model inputs'!AG47)))))) -> 0.5 | F12: =IF(IF(IF(ISERROR('RC Customers by plan'!F5<1),'RC Customers by plan'!F5<1,IF('RC Customers by plan'!F5="","",'RC Customers by plan'!F5<1))="",FALSE,IF(ISERROR('RC Customers by plan'!F5<1),'RC Customers by plan'!F5<1,IF('RC Customers by plan'!F5="","",'RC Customers by plan'!F5<1))),0,IF(IF(IF(ISERROR('RC Customers by plan'!F5=1),'RC Customers by plan'!F5=1,IF('RC Customers by plan'!F5="","",'RC Customers by plan'!F5=1))="",FALSE,IF(ISERROR('RC Customers by plan'!F5=1),'RC Customers by plan'!F5=1,IF('RC Customers by plan'!F5="","",'RC Customers by plan'!F5=1))),IF('Model inputs'!AG70="","",'Model inputs'!AG70),'RC Customers by plan'!E12*(1+IF(IF(IF(IF(ISERROR('RC Customers by plan'!F5<=8),'RC Customers by plan'!F5<=8,IF('RC Customers by plan'!F5="","",'RC Customers by plan'!F5<=8))="",FALSE,IF(ISERROR('RC Customers by plan'!F5<=8),'RC Customers by plan'!F5<=8,IF('RC Customers by plan'!F5="","",'RC Customers by plan'!F5<=8))),IF('Model inputs'!AG51="","",'Model inputs'!AG51),IF('Model inputs'!AG47="","",'Model inputs'!AG47))="",0,IF(IF(IF(ISERROR('RC Customers by plan'!F5<=8),'RC Customers by plan'!F5<=8,IF('RC Customers by plan'!F5="","",'RC Customers by plan'!F5<=8))="",FALSE,IF(ISERROR('RC Customers by plan'!F5<=8),'RC Customers by plan'!F5<=8,IF('RC Customers by plan'!F5="","",'RC Customers by plan'!F5<=8))),IF('Model inputs'!AG51="","",'Model inputs'!AG51),IF('Model inputs'!AG47="","",'Model inputs'!AG47)))))) -> 0.5 | G12: =IF(IF(IF(ISERROR('RC Customers by plan'!G5<1),'RC Customers by plan'!G5<1,IF('RC Customers by plan'!G5="","",'RC Customers by plan'!G5<1))="",FALSE,IF(ISERROR('RC Customers by plan'!G5<1),'RC Customers by plan'!G5<1,IF('RC Customers by plan'!G5="","",'RC Customers by plan'!G5<1))),0,IF(IF(IF(ISERROR('RC Customers by plan'!G5=1),'RC Customers by plan'!G5=1,IF('RC Customers by plan'!G5="","",'RC Customers by plan'!G5=1))="",FALSE,IF(ISERROR('RC Customers by plan'!G5=1),'RC Customers by plan'!G5=1,IF('RC Customers by plan'!G5="","",'RC Customers by plan'!G5=1))),IF('Model inputs'!AG70="","",'Model inputs'!AG70),'RC Customers by plan'!F12*(1+IF(IF(IF(IF(ISERROR('RC Customers by plan'!G5<=8),'RC Customers by plan'!G5<=8,IF('RC Customers by plan'!G5="","",'RC Customers by plan'!G5<=8))="",FALSE,IF(ISERROR('RC Customers by plan'!G5<=8),'RC Customers by plan'!G5<=8,IF('RC Customers by plan'!G5="","",'RC Customers by plan'!G5<=8))),IF('Model inputs'!AG51="","",'Model inputs'!AG51),IF('Model inputs'!AG47="","",'Model inputs'!AG47))="",0,IF(IF(IF(ISERROR('RC Customers by plan'!G5<=8),'RC Customers by plan'!G5<=8,IF('RC Customers by plan'!G5="","",'RC Customers by plan'!G5<=8))="",FALSE,IF(ISERROR('RC Customers by plan'!G5<=8),'RC Customers by plan'!G5<=8,IF('RC Customers by plan'!G5="","",'RC Customers by plan'!G5<=8))),IF('Model inputs'!AG51="","",'Model inputs'!AG51),IF('Model inputs'!AG47="","",'Model inputs'!AG47)))))) -> 0.5 | H12: =IF(IF(IF(ISERROR('RC Customers by plan'!H5<1),'RC Customers by plan'!H5<1,IF('RC Customers by plan'!H5="","",'RC Customers by plan'!H5<1))="",FALSE,IF(ISERROR('RC Customers by plan'!H5<1),'RC Customers by plan'!H5<1,IF('RC Customers by plan'!H5="","",'RC Customers by plan'!H5<1))),0,IF(IF(IF(ISERROR('RC Customers by plan'!H5=1),'RC Customers by plan'!H5=1,IF('RC Customers by plan'!H5="","",'RC Customers by plan'!H5=1))="",FALSE,IF(ISERROR('RC Customers by plan'!H5=1),'RC Customers by plan'!H5=1,IF('RC Customers by plan'!H5="","",'RC Customers by plan'!H5=1))),IF('Model inputs'!AG70="","",'Model inputs'!AG70),'RC Customers by plan'!G12*(1+IF(IF(IF(IF(ISERROR('RC Customers by plan'!H5<=8),'RC Customers by plan'!H5<=8,IF('RC Customers by plan'!H5="","",'RC Customers by plan'!H5<=8))="",FALSE,IF(ISERROR('RC Customers by plan'!H5<=8),'RC Customers by plan'!H5<=8,IF('RC Customers by plan'!H5="","",'RC Customers by plan'!H5<=8))),IF('Model inputs'!AG51="","",'Model inputs'!AG51),IF('Model inputs'!AG47="","",'Model inputs'!AG47))="",0,IF(IF(IF(ISERROR('RC Customers by plan'!H5<=8),'RC Customers by plan'!H5<=8,IF('RC Customers by plan'!H5="","",'RC Customers by plan'!H5<=8))="",FALSE,IF(ISERROR('RC Customers by plan'!H5<=8),'RC Customers by plan'!H5<=8,IF('RC Customers by plan'!H5="","",'RC Customers by plan'!H5<=8))),IF('Model inputs'!AG51="","",'Model inputs'!AG51),IF('Model inputs'!AG47="","",'Model inputs'!AG47)))))) -> 0.5 | I12: =IF(IF(IF(ISERROR('RC Customers by plan'!I5<1),'RC Customers by plan'!I5<1,IF('RC Customers by plan'!I5="","",'RC Customers by plan'!I5<1))="",FALSE,IF(ISERROR('RC Customers by plan'!I5<1),'RC Customers by plan'!I5<1,IF('RC Customers by plan'!I5="","",'RC Customers by plan'!I5<1))),0,IF(IF(IF(ISERROR('RC Customers by plan'!I5=1),'RC Customers by plan'!I5=1,IF('RC Customers by plan'!I5="","",'RC Customers by plan'!I5=1))="",FALSE,IF(ISERROR('RC Customers by plan'!I5=1),'RC Customers by plan'!I5=1,IF('RC Customers by plan'!I5="","",'RC Customers by plan'!I5=1))),IF('Model inputs'!AG70="","",'Model inputs'!AG70),'RC Customers by plan'!H12*(1+IF(IF(IF(IF(ISERROR('RC Customers by plan'!I5<=8),'RC Customers by plan'!I5<=8,IF('RC Customers by plan'!I5="","",'RC Customers by plan'!I5<=8))="",FALSE,IF(ISERROR('RC Customers by plan'!I5<=8),'RC Customers by plan'!I5<=8,IF('RC Customers by plan'!I5="","",'RC Customers by plan'!I5<=8))),IF('Model inputs'!AG51="","",'Model inputs'!AG51),IF('Model inputs'!AG47="","",'Model inputs'!AG47))="",0,IF(IF(IF(ISERROR('RC Customers by plan'!I5<=8),'RC Customers by plan'!I5<=8,IF('RC Customers by plan'!I5="","",'RC Customers by plan'!I5<=8))="",FALSE,IF(ISERROR('RC Customers by plan'!I5<=8),'RC Customers by plan'!I5<=8,IF('RC Customers by plan'!I5="","",'RC Customers by plan'!I5<=8))),IF('Model inputs'!AG51="","",'Model inputs'!AG51),IF('Model inputs'!AG47="","",'Model inputs'!AG47)))))) -> 0.5 | J12: =IF(IF(IF(ISERROR('RC Customers by plan'!J5<1),'RC Customers by plan'!J5<1,IF('RC Customers by plan'!J5="","",'RC Customers by plan'!J5<1))="",FALSE,IF(ISERROR('RC Customers by plan'!J5<1),'RC Customers by plan'!J5<1,IF('RC Customers by plan'!J5="","",'RC Customers by plan'!J5<1))),0,IF(IF(IF(ISERROR('RC Customers by plan'!J5=1),'RC Customers by plan'!J5=1,IF('RC Customers by plan'!J5="","",'RC Customers by plan'!J5=1))="",FALSE,IF(ISERROR('RC Customers by plan'!J5=1),'RC Customers by plan'!J5=1,IF('RC Customers by plan'!J5="","",'RC Customers by plan'!J5=1))),IF('Model inputs'!AG70="","",'Model inputs'!AG70),'RC Customers by plan'!I12*(1+IF(IF(IF(IF(ISERROR('RC Customers by plan'!J5<=8),'RC Customers by plan'!J5<=8,IF('RC Customers by plan'!J5="","",'RC Customers by plan'!J5<=8))="",FALSE,IF(ISERROR('RC Customers by plan'!J5<=8),'RC Customers by plan'!J5<=8,IF('RC Customers by plan'!J5="","",'RC Customers by plan'!J5<=8))),IF('Model inputs'!AG51="","",'Model inputs'!AG51),IF('Model inputs'!AG47="","",'Model inputs'!AG47))="",0,IF(IF(IF(ISERROR('RC Customers by plan'!J5<=8),'RC Customers by plan'!J5<=8,IF('RC Customers by plan'!J5="","",'RC Customers by plan'!J5<=8))="",FALSE,IF(ISERROR('RC Customers by plan'!J5<=8),'RC Customers by plan'!J5<=8,IF('RC Customers by plan'!J5="","",'RC Customers by plan'!J5<=8))),IF('Model inputs'!AG51="","",'Model inputs'!AG51),IF('Model inputs'!AG47="","",'Model inputs'!AG47)))))) -> 0.5 | K12: =IF(IF(IF(ISERROR('RC Customers by plan'!K5<1),'RC Customers by plan'!K5<1,IF('RC Customers by plan'!K5="","",'RC Customers by plan'!K5<1))="",FALSE,IF(ISERROR('RC Customers by plan'!K5<1),'RC Customers by plan'!K5<1,IF('RC Customers by plan'!K5="","",'RC Customers by plan'!K5<1))),0,IF(IF(IF(ISERROR('RC Customers by plan'!K5=1),'RC Customers by plan'!K5=1,IF('RC Customers by plan'!K5="","",'RC Customers by plan'!K5=1))="",FALSE,IF(ISERROR('RC Customers by plan'!K5=1),'RC Customers by plan'!K5=1,IF('RC Customers by plan'!K5="","",'RC Customers by plan'!K5=1))),IF('Model inputs'!AG70="","",'Model inputs'!AG70),'RC Customers by plan'!J12*(1+IF(IF(IF(IF(ISERROR('RC Customers by plan'!K5<=8),'RC Customers by plan'!K5<=8,IF('RC Customers by plan'!K5="","",'RC Customers by plan'!K5<=8))="",FALSE,IF(ISERROR('RC Customers by plan'!K5<=8),'RC Customers by plan'!K5<=8,IF('RC Customers by plan'!K5="","",'RC Customers by plan'!K5<=8))),IF('Model inputs'!AG51="","",'Model inputs'!AG51),IF('Model inputs'!AG47="","",'Model inputs'!AG47))="",0,IF(IF(IF(ISERROR('RC Customers by plan'!K5<=8),'RC Customers by plan'!K5<=8,IF('RC Customers by plan'!K5="","",'RC Customers by plan'!K5<=8))="",FALSE,IF(ISERROR('RC Customers by plan'!K5<=8),'RC Customers by plan'!K5<=8,IF('RC Customers by plan'!K5="","",'RC Customers by plan'!K5<=8))),IF('Model inputs'!AG51="","",'Model inputs'!AG51),IF('Model inputs'!AG47="","",'Model inputs'!AG47)))))) -> 0.5 | L12: =IF(IF(IF(ISERROR('RC Customers by plan'!L5<1),'RC Customers by plan'!L5<1,IF('RC Customers by plan'!L5="","",'RC Customers by plan'!L5<1))="",FALSE,IF(ISERROR('RC Customers by plan'!L5<1),'RC Customers by plan'!L5<1,IF('RC Customers by plan'!L5="","",'RC Customers by plan'!L5<1))),0,IF(IF(IF(ISERROR('RC Customers by plan'!L5=1),'RC Customers by plan'!L5=1,IF('RC Customers by plan'!L5="","",'RC Customers by plan'!L5=1))="",FALSE,IF(ISERROR('RC Customers by plan'!L5=1),'RC Customers by plan'!L5=1,IF('RC Customers by plan'!L5="","",'RC Customers by plan'!L5=1))),IF('Model inputs'!AG70="","",'Model inputs'!AG70),'RC Customers by plan'!K12*(1+IF(IF(IF(IF(ISERROR('RC Customers by plan'!L5<=8),'RC Customers by plan'!L5<=8,IF('RC Customers by plan'!L5="","",'RC Customers by plan'!L5<=8))="",FALSE,IF(ISERROR('RC Customers by plan'!L5<=8),'RC Customers by plan'!L5<=8,IF('RC Customers by plan'!L5="","",'RC Customers by plan'!L5<=8))),IF('Model inputs'!AG51="","",'Model inputs'!AG51),IF('Model inputs'!AG47="","",'Model inputs'!AG47))="",0,IF(IF(IF(ISERROR('RC Customers by plan'!L5<=8),'RC Customers by plan'!L5<=8,IF('RC Customers by plan'!L5="","",'RC Customers by plan'!L5<=8))="",FALSE,IF(ISERROR('RC Customers by plan'!L5<=8),'RC Customers by plan'!L5<=8,IF('RC Customers by plan'!L5="","",'RC Customers by plan'!L5<=8))),IF('Model inputs'!AG51="","",'Model inputs'!AG51),IF('Model inputs'!AG47="","",'Model inputs'!AG47)))))) -> 0.5 | M12: =IF(IF(IF(ISERROR('RC Customers by plan'!M5<1),'RC Customers by plan'!M5<1,IF('RC Customers by plan'!M5="","",'RC Customers by plan'!M5<1))="",FALSE,IF(ISERROR('RC Customers by plan'!M5<1),'RC Customers by plan'!M5<1,IF('RC Customers by plan'!M5="","",'RC Customers by plan'!M5<1))),0,IF(IF(IF(ISERROR('RC Customers by plan'!M5=1),'RC Customers by plan'!M5=1,IF('RC Customers by plan'!M5="","",'RC Customers by plan'!M5=1))="",FALSE,IF(ISERROR('RC Customers by plan'!M5=1),'RC Customers by plan'!M5=1,IF('RC Customers by plan'!M5="","",'RC Customers by plan'!M5=1))),IF('Model inputs'!AG70="","",'Model inputs'!AG70),'RC Customers by plan'!L12*(1+IF(IF(IF(IF(ISERROR('RC Customers by plan'!M5<=8),'RC Customers by plan'!M5<=8,IF('RC Customers by plan'!M5="","",'RC Customers by plan'!M5<=8))="",FALSE,IF(ISERROR('RC Customers by plan'!M5<=8),'RC Customers by plan'!M5<=8,IF('RC Customers by plan'!M5="","",'RC Customers by plan'!M5<=8))),IF('Model inputs'!AG51="","",'Model inputs'!AG51),IF('Model inputs'!AG47="","",'Model inputs'!AG47))="",0,IF(IF(IF(ISERROR('RC Customers by plan'!M5<=8),'RC Customers by plan'!M5<=8,IF('RC Customers by plan'!M5="","",'RC Customers by plan'!M5<=8))="",FALSE,IF(ISERROR('RC Customers by plan'!M5<=8),'RC Customers by plan'!M5<=8,IF('RC Customers by plan'!M5="","",'RC Customers by plan'!M5<=8))),IF('Model inputs'!AG51="","",'Model inputs'!AG51),IF('Model inputs'!AG47="","",'Model inputs'!AG47)))))) -> 0.5 | N12: =IF(IF(IF(ISERROR('RC Customers by plan'!N5<1),'RC Customers by plan'!N5<1,IF('RC Customers by plan'!N5="","",'RC Customers by plan'!N5<1))="",FALSE,IF(ISERROR('RC Customers by plan'!N5<1),'RC Customers by plan'!N5<1,IF('RC Customers by plan'!N5="","",'RC Customers by plan'!N5<1))),0,IF(IF(IF(ISERROR('RC Customers by plan'!N5=1),'RC Customers by plan'!N5=1,IF('RC Customers by plan'!N5="","",'RC Customers by plan'!N5=1))="",FALSE,IF(ISERROR('RC Customers by plan'!N5=1),'RC Customers by plan'!N5=1,IF('RC Customers by plan'!N5="","",'RC Customers by plan'!N5=1))),IF('Model inputs'!AG70="","",'Model inputs'!AG70),'RC Customers by plan'!M12*(1+IF(IF(IF(IF(ISERROR('RC Customers by plan'!N5<=8),'RC Customers by plan'!N5<=8,IF('RC Customers by plan'!N5="","",'RC Customers by plan'!N5<=8))="",FALSE,IF(ISERROR('RC Customers by plan'!N5<=8),'RC Customers by plan'!N5<=8,IF('RC Customers by plan'!N5="","",'RC Customers by plan'!N5<=8))),IF('Model inputs'!AG51="","",'Model inputs'!AG51),IF('Model inputs'!AG47="","",'Model inputs'!AG47))="",0,IF(IF(IF(ISERROR('RC Customers by plan'!N5<=8),'RC Customers by plan'!N5<=8,IF('RC Customers by plan'!N5="","",'RC Customers by plan'!N5<=8))="",FALSE,IF(ISERROR('RC Customers by plan'!N5<=8),'RC Customers by plan'!N5<=8,IF('RC Customers by plan'!N5="","",'RC Customers by plan'!N5<=8))),IF('Model inputs'!AG51="","",'Model inputs'!AG51),IF('Model inputs'!AG47="","",'Model inputs'!AG47)))))) -> 0.5 | O12: =IF(IF(IF(ISERROR('RC Customers by plan'!O5<1),'RC Customers by plan'!O5<1,IF('RC Customers by plan'!O5="","",'RC Customers by plan'!O5<1))="",FALSE,IF(ISERROR('RC Customers by plan'!O5<1),'RC Customers by plan'!O5<1,IF('RC Customers by plan'!O5="","",'RC Customers by plan'!O5<1))),0,IF(IF(IF(ISERROR('RC Customers by plan'!O5=1),'RC Customers by plan'!O5=1,IF('RC Customers by plan'!O5="","",'RC Customers by plan'!O5=1))="",FALSE,IF(ISERROR('RC Customers by plan'!O5=1),'RC Customers by plan'!O5=1,IF('RC Customers by plan'!O5="","",'RC Customers by plan'!O5=1))),IF('Model inputs'!AG70="","",'Model inputs'!AG70),'RC Customers by plan'!N12*(1+IF(IF(IF(IF(ISERROR('RC Customers by plan'!O5<=8),'RC Customers by plan'!O5<=8,IF('RC Customers by plan'!O5="","",'RC Customers by plan'!O5<=8))="",FALSE,IF(ISERROR('RC Customers by plan'!O5<=8),'RC Customers by plan'!O5<=8,IF('RC Customers by plan'!O5="","",'RC Customers by plan'!O5<=8))),IF('Model inputs'!AG51="","",'Model inputs'!AG51),IF('Model inputs'!AG47="","",'Model inputs'!AG47))="",0,IF(IF(IF(ISERROR('RC Customers by plan'!O5<=8),'RC Customers by plan'!O5<=8,IF('RC Customers by plan'!O5="","",'RC Customers by plan'!O5<=8))="",FALSE,IF(ISERROR('RC Customers by plan'!O5<=8),'RC Customers by plan'!O5<=8,IF('RC Customers by plan'!O5="","",'RC Customers by plan'!O5<=8))),IF('Model inputs'!AG51="","",'Model inputs'!AG51),IF('Model inputs'!AG47="","",'Model inputs'!AG47)))))) -> 0.5 | P12: =IF(IF(IF(ISERROR('RC Customers by plan'!P5<1),'RC Customers by plan'!P5<1,IF('RC Customers by plan'!P5="","",'RC Customers by plan'!P5<1))="",FALSE,IF(ISERROR('RC Customers by plan'!P5<1),'RC Customers by plan'!P5<1,IF('RC Customers by plan'!P5="","",'RC Customers by plan'!P5<1))),0,IF(IF(IF(ISERROR('RC Customers by plan'!P5=1),'RC Customers by plan'!P5=1,IF('RC Customers by plan'!P5="","",'RC Customers by plan'!P5=1))="",FALSE,IF(ISERROR('RC Customers by plan'!P5=1),'RC Customers by plan'!P5=1,IF('RC Customers by plan'!P5="","",'RC Customers by plan'!P5=1))),IF('Model inputs'!AG70="","",'Model inputs'!AG70),'RC Customers by plan'!O12*(1+IF(IF(IF(IF(ISERROR('RC Customers by plan'!P5<=8),'RC Customers by plan'!P5<=8,IF('RC Customers by plan'!P5="","",'RC Customers by plan'!P5<=8))="",FALSE,IF(ISERROR('RC Customers by plan'!P5<=8),'RC Customers by plan'!P5<=8,IF('RC Customers by plan'!P5="","",'RC Customers by plan'!P5<=8))),IF('Model inputs'!AG51="","",'Model inputs'!AG51),IF('Model inputs'!AG47="","",'Model inputs'!AG47))="",0,IF(IF(IF(ISERROR('RC Customers by plan'!P5<=8),'RC Customers by plan'!P5<=8,IF('RC Customers by plan'!P5="","",'RC Customers by plan'!P5<=8))="",FALSE,IF(ISERROR('RC Customers by plan'!P5<=8),'RC Customers by plan'!P5<=8,IF('RC Customers by plan'!P5="","",'RC Customers by plan'!P5<=8))),IF('Model inputs'!AG51="","",'Model inputs'!AG51),IF('Model inputs'!AG47="","",'Model inputs'!AG47)))))) -> 0.5 | Q12: =IF(IF(IF(ISERROR('RC Customers by plan'!Q5<1),'RC Customers by plan'!Q5<1,IF('RC Customers by plan'!Q5="","",'RC Customers by plan'!Q5<1))="",FALSE,IF(ISERROR('RC Customers by plan'!Q5<1),'RC Customers by plan'!Q5<1,IF('RC Customers by plan'!Q5="","",'RC Customers by plan'!Q5<1))),0,IF(IF(IF(ISERROR('RC Customers by plan'!Q5=1),'RC Customers by plan'!Q5=1,IF('RC Customers by plan'!Q5="","",'RC Customers by plan'!Q5=1))="",FALSE,IF(ISERROR('RC Customers by plan'!Q5=1),'RC Customers by plan'!Q5=1,IF('RC Customers by plan'!Q5="","",'RC Customers by plan'!Q5=1))),IF('Model inputs'!AG70="","",'Model inputs'!AG70),'RC Customers by plan'!P12*(1+IF(IF(IF(IF(ISERROR('RC Customers by plan'!Q5<=8),'RC Customers by plan'!Q5<=8,IF('RC Customers by plan'!Q5="","",'RC Customers by plan'!Q5<=8))="",FALSE,IF(ISERROR('RC Customers by plan'!Q5<=8),'RC Customers by plan'!Q5<=8,IF('RC Customers by plan'!Q5="","",'RC Customers by plan'!Q5<=8))),IF('Model inputs'!AG51="","",'Model inputs'!AG51),IF('Model inputs'!AG47="","",'Model inputs'!AG47))="",0,IF(IF(IF(ISERROR('RC Customers by plan'!Q5<=8),'RC Customers by plan'!Q5<=8,IF('RC Customers by plan'!Q5="","",'RC Customers by plan'!Q5<=8))="",FALSE,IF(ISERROR('RC Customers by plan'!Q5<=8),'RC Customers by plan'!Q5<=8,IF('RC Customers by plan'!Q5="","",'RC Customers by plan'!Q5<=8))),IF('Model inputs'!AG51="","",'Model inputs'!AG51),IF('Model inputs'!AG47="","",'Model inputs'!AG47)))))) -> 0.5 | R12: =IF(IF(IF(ISERROR('RC Customers by plan'!R5<1),'RC Customers by plan'!R5<1,IF('RC Customers by plan'!R5="","",'RC Customers by plan'!R5<1))="",FALSE,IF(ISERROR('RC Customers by plan'!R5<1),'RC Customers by plan'!R5<1,IF('RC Customers by plan'!R5="","",'RC Customers by plan'!R5<1))),0,IF(IF(IF(ISERROR('RC Customers by plan'!R5=1),'RC Customers by plan'!R5=1,IF('RC Customers by plan'!R5="","",'RC Customers by plan'!R5=1))="",FALSE,IF(ISERROR('RC Customers by plan'!R5=1),'RC Customers by plan'!R5=1,IF('RC Customers by plan'!R5="","",'RC Customers by plan'!R5=1))),IF('Model inputs'!AG70="","",'Model inputs'!AG70),'RC Customers by plan'!Q12*(1+IF(IF(IF(IF(ISERROR('RC Customers by plan'!R5<=8),'RC Customers by plan'!R5<=8,IF('RC Customers by plan'!R5="","",'RC Customers by plan'!R5<=8))="",FALSE,IF(ISERROR('RC Customers by plan'!R5<=8),'RC Customers by plan'!R5<=8,IF('RC Customers by plan'!R5="","",'RC Customers by plan'!R5<=8))),IF('Model inputs'!AG51="","",'Model inputs'!AG51),IF('Model inputs'!AG47="","",'Model inputs'!AG47))="",0,IF(IF(IF(ISERROR('RC Customers by plan'!R5<=8),'RC Customers by plan'!R5<=8,IF('RC Customers by plan'!R5="","",'RC Customers by plan'!R5<=8))="",FALSE,IF(ISERROR('RC Customers by plan'!R5<=8),'RC Customers by plan'!R5<=8,IF('RC Customers by plan'!R5="","",'RC Customers by plan'!R5<=8))),IF('Model inputs'!AG51="","",'Model inputs'!AG51),IF('Model inputs'!AG47="","",'Model inputs'!AG47)))))) -> 0.5 | S12: =IF(IF(IF(ISERROR('RC Customers by plan'!S5<1),'RC Customers by plan'!S5<1,IF('RC Customers by plan'!S5="","",'RC Customers by plan'!S5<1))="",FALSE,IF(ISERROR('RC Customers by plan'!S5<1),'RC Customers by plan'!S5<1,IF('RC Customers by plan'!S5="","",'RC Customers by plan'!S5<1))),0,IF(IF(IF(ISERROR('RC Customers by plan'!S5=1),'RC Customers by plan'!S5=1,IF('RC Customers by plan'!S5="","",'RC Customers by plan'!S5=1))="",FALSE,IF(ISERROR('RC Customers by plan'!S5=1),'RC Customers by plan'!S5=1,IF('RC Customers by plan'!S5="","",'RC Customers by plan'!S5=1))),IF('Model inputs'!AG70="","",'Model inputs'!AG70),'RC Customers by plan'!R12*(1+IF(IF(IF(IF(ISERROR('RC Customers by plan'!S5<=8),'RC Customers by plan'!S5<=8,IF('RC Customers by plan'!S5="","",'RC Customers by plan'!S5<=8))="",FALSE,IF(ISERROR('RC Customers by plan'!S5<=8),'RC Customers by plan'!S5<=8,IF('RC Customers by plan'!S5="","",'RC Customers by plan'!S5<=8))),IF('Model inputs'!AG51="","",'Model inputs'!AG51),IF('Model inputs'!AG47="","",'Model inputs'!AG47))="",0,IF(IF(IF(ISERROR('RC Customers by plan'!S5<=8),'RC Customers by plan'!S5<=8,IF('RC Customers by plan'!S5="","",'RC Customers by plan'!S5<=8))="",FALSE,IF(ISERROR('RC Customers by plan'!S5<=8),'RC Customers by plan'!S5<=8,IF('RC Customers by plan'!S5="","",'RC Customers by plan'!S5<=8))),IF('Model inputs'!AG51="","",'Model inputs'!AG51),IF('Model inputs'!AG47="","",'Model inputs'!AG47)))))) -> 0.5
A13: Team | B13: =IF(IF(IF(ISERROR('RC Customers by plan'!B5<1),'RC Customers by plan'!B5<1,IF('RC Customers by plan'!B5="","",'RC Customers by plan'!B5<1))="",FALSE,IF(ISERROR('RC Customers by plan'!B5<1),'RC Customers by plan'!B5<1,IF('RC Customers by plan'!B5="","",'RC Customers by plan'!B5<1))),0,IF(IF(IF(ISERROR('RC Customers by plan'!B5=1),'RC Customers by plan'!B5=1,IF('RC Customers by plan'!B5="","",'RC Customers by plan'!B5=1))="",FALSE,IF(ISERROR('RC Customers by plan'!B5=1),'RC Customers by plan'!B5=1,IF('RC Customers by plan'!B5="","",'RC Customers by plan'!B5=1))),IF('Model inputs'!AG71="","",'Model inputs'!AG71),'Model inputs'!N79*(1+IF(IF(IF(IF(ISERROR('RC Customers by plan'!B5<=8),'RC Customers by plan'!B5<=8,IF('RC Customers by plan'!B5="","",'RC Customers by plan'!B5<=8))="",FALSE,IF(ISERROR('RC Customers by plan'!B5<=8),'RC Customers by plan'!B5<=8,IF('RC Customers by plan'!B5="","",'RC Customers by plan'!B5<=8))),IF('Model inputs'!AG52="","",'Model inputs'!AG52),IF('Model inputs'!AG48="","",'Model inputs'!AG48))="",0,IF(IF(IF(ISERROR('RC Customers by plan'!B5<=8),'RC Customers by plan'!B5<=8,IF('RC Customers by plan'!B5="","",'RC Customers by plan'!B5<=8))="",FALSE,IF(ISERROR('RC Customers by plan'!B5<=8),'RC Customers by plan'!B5<=8,IF('RC Customers by plan'!B5="","",'RC Customers by plan'!B5<=8))),IF('Model inputs'!AG52="","",'Model inputs'!AG52),IF('Model inputs'!AG48="","",'Model inputs'!AG48)))))) -> 0 | C13: =IF(IF(IF(ISERROR('RC Customers by plan'!C5<1),'RC Customers by plan'!C5<1,IF('RC Customers by plan'!C5="","",'RC Customers by plan'!C5<1))="",FALSE,IF(ISERROR('RC Customers by plan'!C5<1),'RC Customers by plan'!C5<1,IF('RC Customers by plan'!C5="","",'RC Customers by plan'!C5<1))),0,IF(IF(IF(ISERROR('RC Customers by plan'!C5=1),'RC Customers by plan'!C5=1,IF('RC Customers by plan'!C5="","",'RC Customers by plan'!C5=1))="",FALSE,IF(ISERROR('RC Customers by plan'!C5=1),'RC Customers by plan'!C5=1,IF('RC Customers by plan'!C5="","",'RC Customers by plan'!C5=1))),IF('Model inputs'!AG71="","",'Model inputs'!AG71),'RC Customers by plan'!B13*(1+IF(IF(IF(IF(ISERROR('RC Customers by plan'!C5<=8),'RC Customers by plan'!C5<=8,IF('RC Customers by plan'!C5="","",'RC Customers by plan'!C5<=8))="",FALSE,IF(ISERROR('RC Customers by plan'!C5<=8),'RC Customers by plan'!C5<=8,IF('RC Customers by plan'!C5="","",'RC Customers by plan'!C5<=8))),IF('Model inputs'!AG52="","",'Model inputs'!AG52),IF('Model inputs'!AG48="","",'Model inputs'!AG48))="",0,IF(IF(IF(ISERROR('RC Customers by plan'!C5<=8),'RC Customers by plan'!C5<=8,IF('RC Customers by plan'!C5="","",'RC Customers by plan'!C5<=8))="",FALSE,IF(ISERROR('RC Customers by plan'!C5<=8),'RC Customers by plan'!C5<=8,IF('RC Customers by plan'!C5="","",'RC Customers by plan'!C5<=8))),IF('Model inputs'!AG52="","",'Model inputs'!AG52),IF('Model inputs'!AG48="","",'Model inputs'!AG48)))))) -> 3 | D13: =IF(IF(IF(ISERROR('RC Customers by plan'!D5<1),'RC Customers by plan'!D5<1,IF('RC Customers by plan'!D5="","",'RC Customers by plan'!D5<1))="",FALSE,IF(ISERROR('RC Customers by plan'!D5<1),'RC Customers by plan'!D5<1,IF('RC Customers by plan'!D5="","",'RC Customers by plan'!D5<1))),0,IF(IF(IF(ISERROR('RC Customers by plan'!D5=1),'RC Customers by plan'!D5=1,IF('RC Customers by plan'!D5="","",'RC Customers by plan'!D5=1))="",FALSE,IF(ISERROR('RC Customers by plan'!D5=1),'RC Customers by plan'!D5=1,IF('RC Customers by plan'!D5="","",'RC Customers by plan'!D5=1))),IF('Model inputs'!AG71="","",'Model inputs'!AG71),'RC Customers by plan'!C13*(1+IF(IF(IF(IF(ISERROR('RC Customers by plan'!D5<=8),'RC Customers by plan'!D5<=8,IF('RC Customers by plan'!D5="","",'RC Customers by plan'!D5<=8))="",FALSE,IF(ISERROR('RC Customers by plan'!D5<=8),'RC Customers by plan'!D5<=8,IF('RC Customers by plan'!D5="","",'RC Customers by plan'!D5<=8))),IF('Model inputs'!AG52="","",'Model inputs'!AG52),IF('Model inputs'!AG48="","",'Model inputs'!AG48))="",0,IF(IF(IF(ISERROR('RC Customers by plan'!D5<=8),'RC Customers by plan'!D5<=8,IF('RC Customers by plan'!D5="","",'RC Customers by plan'!D5<=8))="",FALSE,IF(ISERROR('RC Customers by plan'!D5<=8),'RC Customers by plan'!D5<=8,IF('RC Customers by plan'!D5="","",'RC Customers by plan'!D5<=8))),IF('Model inputs'!AG52="","",'Model inputs'!AG52),IF('Model inputs'!AG48="","",'Model inputs'!AG48)))))) -> 3.3 | E13: =IF(IF(IF(ISERROR('RC Customers by plan'!E5<1),'RC Customers by plan'!E5<1,IF('RC Customers by plan'!E5="","",'RC Customers by plan'!E5<1))="",FALSE,IF(ISERROR('RC Customers by plan'!E5<1),'RC Customers by plan'!E5<1,IF('RC Customers by plan'!E5="","",'RC Customers by plan'!E5<1))),0,IF(IF(IF(ISERROR('RC Customers by plan'!E5=1),'RC Customers by plan'!E5=1,IF('RC Customers by plan'!E5="","",'RC Customers by plan'!E5=1))="",FALSE,IF(ISERROR('RC Customers by plan'!E5=1),'RC Customers by plan'!E5=1,IF('RC Customers by plan'!E5="","",'RC Customers by plan'!E5=1))),IF('Model inputs'!AG71="","",'Model inputs'!AG71),'RC Customers by plan'!D13*(1+IF(IF(IF(IF(ISERROR('RC Customers by plan'!E5<=8),'RC Customers by plan'!E5<=8,IF('RC Customers by plan'!E5="","",'RC Customers by plan'!E5<=8))="",FALSE,IF(ISERROR('RC Customers by plan'!E5<=8),'RC Customers by plan'!E5<=8,IF('RC Customers by plan'!E5="","",'RC Customers by plan'!E5<=8))),IF('Model inputs'!AG52="","",'Model inputs'!AG52),IF('Model inputs'!AG48="","",'Model inputs'!AG48))="",0,IF(IF(IF(ISERROR('RC Customers by plan'!E5<=8),'RC Customers by plan'!E5<=8,IF('RC Customers by plan'!E5="","",'RC Customers by plan'!E5<=8))="",FALSE,IF(ISERROR('RC Customers by plan'!E5<=8),'RC Customers by plan'!E5<=8,IF('RC Customers by plan'!E5="","",'RC Customers by plan'!E5<=8))),IF('Model inputs'!AG52="","",'Model inputs'!AG52),IF('Model inputs'!AG48="","",'Model inputs'!AG48)))))) -> 3.63 | F13: =IF(IF(IF(ISERROR('RC Customers by plan'!F5<1),'RC Customers by plan'!F5<1,IF('RC Customers by plan'!F5="","",'RC Customers by plan'!F5<1))="",FALSE,IF(ISERROR('RC Customers by plan'!F5<1),'RC Customers by plan'!F5<1,IF('RC Customers by plan'!F5="","",'RC Customers by plan'!F5<1))),0,IF(IF(IF(ISERROR('RC Customers by plan'!F5=1),'RC Customers by plan'!F5=1,IF('RC Customers by plan'!F5="","",'RC Customers by plan'!F5=1))="",FALSE,IF(ISERROR('RC Customers by plan'!F5=1),'RC Customers by plan'!F5=1,IF('RC Customers by plan'!F5="","",'RC Customers by plan'!F5=1))),IF('Model inputs'!AG71="","",'Model inputs'!AG71),'RC Customers by plan'!E13*(1+IF(IF(IF(IF(ISERROR('RC Customers by plan'!F5<=8),'RC Customers by plan'!F5<=8,IF('RC Customers by plan'!F5="","",'RC Customers by plan'!F5<=8))="",FALSE,IF(ISERROR('RC Customers by plan'!F5<=8),'RC Customers by plan'!F5<=8,IF('RC Customers by plan'!F5="","",'RC Customers by plan'!F5<=8))),IF('Model inputs'!AG52="","",'Model inputs'!AG52),IF('Model inputs'!AG48="","",'Model inputs'!AG48))="",0,IF(IF(IF(ISERROR('RC Customers by plan'!F5<=8),'RC Customers by plan'!F5<=8,IF('RC Customers by plan'!F5="","",'RC Customers by plan'!F5<=8))="",FALSE,IF(ISERROR('RC Customers by plan'!F5<=8),'RC Customers by plan'!F5<=8,IF('RC Customers by plan'!F5="","",'RC Customers by plan'!F5<=8))),IF('Model inputs'!AG52="","",'Model inputs'!AG52),IF('Model inputs'!AG48="","",'Model inputs'!AG48)))))) -> 3.993 | G13: =IF(IF(IF(ISERROR('RC Customers by plan'!G5<1),'RC Customers by plan'!G5<1,IF('RC Customers by plan'!G5="","",'RC Customers by plan'!G5<1))="",FALSE,IF(ISERROR('RC Customers by plan'!G5<1),'RC Customers by plan'!G5<1,IF('RC Customers by plan'!G5="","",'RC Customers by plan'!G5<1))),0,IF(IF(IF(ISERROR('RC Customers by plan'!G5=1),'RC Customers by plan'!G5=1,IF('RC Customers by plan'!G5="","",'RC Customers by plan'!G5=1))="",FALSE,IF(ISERROR('RC Customers by plan'!G5=1),'RC Customers by plan'!G5=1,IF('RC Customers by plan'!G5="","",'RC Customers by plan'!G5=1))),IF('Model inputs'!AG71="","",'Model inputs'!AG71),'RC Customers by plan'!F13*(1+IF(IF(IF(IF(ISERROR('RC Customers by plan'!G5<=8),'RC Customers by plan'!G5<=8,IF('RC Customers by plan'!G5="","",'RC Customers by plan'!G5<=8))="",FALSE,IF(ISERROR('RC Customers by plan'!G5<=8),'RC Customers by plan'!G5<=8,IF('RC Customers by plan'!G5="","",'RC Customers by plan'!G5<=8))),IF('Model inputs'!AG52="","",'Model inputs'!AG52),IF('Model inputs'!AG48="","",'Model inputs'!AG48))="",0,IF(IF(IF(ISERROR('RC Customers by plan'!G5<=8),'RC Customers by plan'!G5<=8,IF('RC Customers by plan'!G5="","",'RC Customers by plan'!G5<=8))="",FALSE,IF(ISERROR('RC Customers by plan'!G5<=8),'RC Customers by plan'!G5<=8,IF('RC Customers by plan'!G5="","",'RC Customers by plan'!G5<=8))),IF('Model inputs'!AG52="","",'Model inputs'!AG52),IF('Model inputs'!AG48="","",'Model inputs'!AG48)))))) -> 4.3923 | H13: =IF(IF(IF(ISERROR('RC Customers by plan'!H5<1),'RC Customers by plan'!H5<1,IF('RC Customers by plan'!H5="","",'RC Customers by plan'!H5<1))="",FALSE,IF(ISERROR('RC Customers by plan'!H5<1),'RC Customers by plan'!H5<1,IF('RC Customers by plan'!H5="","",'RC Customers by plan'!H5<1))),0,IF(IF(IF(ISERROR('RC Customers by plan'!H5=1),'RC Customers by plan'!H5=1,IF('RC Customers by plan'!H5="","",'RC Customers by plan'!H5=1))="",FALSE,IF(ISERROR('RC Customers by plan'!H5=1),'RC Customers by plan'!H5=1,IF('RC Customers by plan'!H5="","",'RC Customers by plan'!H5=1))),IF('Model inputs'!AG71="","",'Model inputs'!AG71),'RC Customers by plan'!G13*(1+IF(IF(IF(IF(ISERROR('RC Customers by plan'!H5<=8),'RC Customers by plan'!H5<=8,IF('RC Customers by plan'!H5="","",'RC Customers by plan'!H5<=8))="",FALSE,IF(ISERROR('RC Customers by plan'!H5<=8),'RC Customers by plan'!H5<=8,IF('RC Customers by plan'!H5="","",'RC Customers by plan'!H5<=8))),IF('Model inputs'!AG52="","",'Model inputs'!AG52),IF('Model inputs'!AG48="","",'Model inputs'!AG48))="",0,IF(IF(IF(ISERROR('RC Customers by plan'!H5<=8),'RC Customers by plan'!H5<=8,IF('RC Customers by plan'!H5="","",'RC Customers by plan'!H5<=8))="",FALSE,IF(ISERROR('RC Customers by plan'!H5<=8),'RC Customers by plan'!H5<=8,IF('RC Customers by plan'!H5="","",'RC Customers by plan'!H5<=8))),IF('Model inputs'!AG52="","",'Model inputs'!AG52),IF('Model inputs'!AG48="","",'Model inputs'!AG48)))))) -> 4.83153 | I13: =IF(IF(IF(ISERROR('RC Customers by plan'!I5<1),'RC Customers by plan'!I5<1,IF('RC Customers by plan'!I5="","",'RC Customers by plan'!I5<1))="",FALSE,IF(ISERROR('RC Customers by plan'!I5<1),'RC Customers by plan'!I5<1,IF('RC Customers by plan'!I5="","",'RC Customers by plan'!I5<1))),0,IF(IF(IF(ISERROR('RC Customers by plan'!I5=1),'RC Customers by plan'!I5=1,IF('RC Customers by plan'!I5="","",'RC Customers by plan'!I5=1))="",FALSE,IF(ISERROR('RC Customers by plan'!I5=1),'RC Customers by plan'!I5=1,IF('RC Customers by plan'!I5="","",'RC Customers by plan'!I5=1))),IF('Model inputs'!AG71="","",'Model inputs'!AG71),'RC Customers by plan'!H13*(1+IF(IF(IF(IF(ISERROR('RC Customers by plan'!I5<=8),'RC Customers by plan'!I5<=8,IF('RC Customers by plan'!I5="","",'RC Customers by plan'!I5<=8))="",FALSE,IF(ISERROR('RC Customers by plan'!I5<=8),'RC Customers by plan'!I5<=8,IF('RC Customers by plan'!I5="","",'RC Customers by plan'!I5<=8))),IF('Model inputs'!AG52="","",'Model inputs'!AG52),IF('Model inputs'!AG48="","",'Model inputs'!AG48))="",0,IF(IF(IF(ISERROR('RC Customers by plan'!I5<=8),'RC Customers by plan'!I5<=8,IF('RC Customers by plan'!I5="","",'RC Customers by plan'!I5<=8))="",FALSE,IF(ISERROR('RC Customers by plan'!I5<=8),'RC Customers by plan'!I5<=8,IF('RC Customers by plan'!I5="","",'RC Customers by plan'!I5<=8))),IF('Model inputs'!AG52="","",'Model inputs'!AG52),IF('Model inputs'!AG48="","",'Model inputs'!AG48)))))) -> 5.314683 | J13: =IF(IF(IF(ISERROR('RC Customers by plan'!J5<1),'RC Customers by plan'!J5<1,IF('RC Customers by plan'!J5="","",'RC Customers by plan'!J5<1))="",FALSE,IF(ISERROR('RC Customers by plan'!J5<1),'RC Customers by plan'!J5<1,IF('RC Customers by plan'!J5="","",'RC Customers by plan'!J5<1))),0,IF(IF(IF(ISERROR('RC Customers by plan'!J5=1),'RC Customers by plan'!J5=1,IF('RC Customers by plan'!J5="","",'RC Customers by plan'!J5=1))="",FALSE,IF(ISERROR('RC Customers by plan'!J5=1),'RC Customers by plan'!J5=1,IF('RC Customers by plan'!J5="","",'RC Customers by plan'!J5=1))),IF('Model inputs'!AG71="","",'Model inputs'!AG71),'RC Customers by plan'!I13*(1+IF(IF(IF(IF(ISERROR('RC Customers by plan'!J5<=8),'RC Customers by plan'!J5<=8,IF('RC Customers by plan'!J5="","",'RC Customers by plan'!J5<=8))="",FALSE,IF(ISERROR('RC Customers by plan'!J5<=8),'RC Customers by plan'!J5<=8,IF('RC Customers by plan'!J5="","",'RC Customers by plan'!J5<=8))),IF('Model inputs'!AG52="","",'Model inputs'!AG52),IF('Model inputs'!AG48="","",'Model inputs'!AG48))="",0,IF(IF(IF(ISERROR('RC Customers by plan'!J5<=8),'RC Customers by plan'!J5<=8,IF('RC Customers by plan'!J5="","",'RC Customers by plan'!J5<=8))="",FALSE,IF(ISERROR('RC Customers by plan'!J5<=8),'RC Customers by plan'!J5<=8,IF('RC Customers by plan'!J5="","",'RC Customers by plan'!J5<=8))),IF('Model inputs'!AG52="","",'Model inputs'!AG52),IF('Model inputs'!AG48="","",'Model inputs'!AG48)))))) -> 5.8461513 | K13: =IF(IF(IF(ISERROR('RC Customers by plan'!K5<1),'RC Customers by plan'!K5<1,IF('RC Customers by plan'!K5="","",'RC Customers by plan'!K5<1))="",FALSE,IF(ISERROR('RC Customers by plan'!K5<1),'RC Customers by plan'!K5<1,IF('RC Customers by plan'!K5="","",'RC Customers by plan'!K5<1))),0,IF(IF(IF(ISERROR('RC Customers by plan'!K5=1),'RC Customers by plan'!K5=1,IF('RC Customers by plan'!K5="","",'RC Customers by plan'!K5=1))="",FALSE,IF(ISERROR('RC Customers by plan'!K5=1),'RC Customers by plan'!K5=1,IF('RC Customers by plan'!K5="","",'RC Customers by plan'!K5=1))),IF('Model inputs'!AG71="","",'Model inputs'!AG71),'RC Customers by plan'!J13*(1+IF(IF(IF(IF(ISERROR('RC Customers by plan'!K5<=8),'RC Customers by plan'!K5<=8,IF('RC Customers by plan'!K5="","",'RC Customers by plan'!K5<=8))="",FALSE,IF(ISERROR('RC Customers by plan'!K5<=8),'RC Customers by plan'!K5<=8,IF('RC Customers by plan'!K5="","",'RC Customers by plan'!K5<=8))),IF('Model inputs'!AG52="","",'Model inputs'!AG52),IF('Model inputs'!AG48="","",'Model inputs'!AG48))="",0,IF(IF(IF(ISERROR('RC Customers by plan'!K5<=8),'RC Customers by plan'!K5<=8,IF('RC Customers by plan'!K5="","",'RC Customers by plan'!K5<=8))="",FALSE,IF(ISERROR('RC Customers by plan'!K5<=8),'RC Customers by plan'!K5<=8,IF('RC Customers by plan'!K5="","",'RC Customers by plan'!K5<=8))),IF('Model inputs'!AG52="","",'Model inputs'!AG52),IF('Model inputs'!AG48="","",'Model inputs'!AG48)))))) -> 6.0799974 | L13: =IF(IF(IF(ISERROR('RC Customers by plan'!L5<1),'RC Customers by plan'!L5<1,IF('RC Customers by plan'!L5="","",'RC Customers by plan'!L5<1))="",FALSE,IF(ISERROR('RC Customers by plan'!L5<1),'RC Customers by plan'!L5<1,IF('RC Customers by plan'!L5="","",'RC Customers by plan'!L5<1))),0,IF(IF(IF(ISERROR('RC Customers by plan'!L5=1),'RC Customers by plan'!L5=1,IF('RC Customers by plan'!L5="","",'RC Customers by plan'!L5=1))="",FALSE,IF(ISERROR('RC Customers by plan'!L5=1),'RC Customers by plan'!L5=1,IF('RC Customers by plan'!L5="","",'RC Customers by plan'!L5=1))),IF('Model inputs'!AG71="","",'Model inputs'!AG71),'RC Customers by plan'!K13*(1+IF(IF(IF(IF(ISERROR('RC Customers by plan'!L5<=8),'RC Customers by plan'!L5<=8,IF('RC Customers by plan'!L5="","",'RC Customers by plan'!L5<=8))="",FALSE,IF(ISERROR('RC Customers by plan'!L5<=8),'RC Customers by plan'!L5<=8,IF('RC Customers by plan'!L5="","",'RC Customers by plan'!L5<=8))),IF('Model inputs'!AG52="","",'Model inputs'!AG52),IF('Model inputs'!AG48="","",'Model inputs'!AG48))="",0,IF(IF(IF(ISERROR('RC Customers by plan'!L5<=8),'RC Customers by plan'!L5<=8,IF('RC Customers by plan'!L5="","",'RC Customers by plan'!L5<=8))="",FALSE,IF(ISERROR('RC Customers by plan'!L5<=8),'RC Customers by plan'!L5<=8,IF('RC Customers by plan'!L5="","",'RC Customers by plan'!L5<=8))),IF('Model inputs'!AG52="","",'Model inputs'!AG52),IF('Model inputs'!AG48="","",'Model inputs'!AG48)))))) -> 6.3231972 | M13: =IF(IF(IF(ISERROR('RC Customers by plan'!M5<1),'RC Customers by plan'!M5<1,IF('RC Customers by plan'!M5="","",'RC Customers by plan'!M5<1))="",FALSE,IF(ISERROR('RC Customers by plan'!M5<1),'RC Customers by plan'!M5<1,IF('RC Customers by plan'!M5="","",'RC Customers by plan'!M5<1))),0,IF(IF(IF(ISERROR('RC Customers by plan'!M5=1),'RC Customers by plan'!M5=1,IF('RC Customers by plan'!M5="","",'RC Customers by plan'!M5=1))="",FALSE,IF(ISERROR('RC Customers by plan'!M5=1),'RC Customers by plan'!M5=1,IF('RC Customers by plan'!M5="","",'RC Customers by plan'!M5=1))),IF('Model inputs'!AG71="","",'Model inputs'!AG71),'RC Customers by plan'!L13*(1+IF(IF(IF(IF(ISERROR('RC Customers by plan'!M5<=8),'RC Customers by plan'!M5<=8,IF('RC Customers by plan'!M5="","",'RC Customers by plan'!M5<=8))="",FALSE,IF(ISERROR('RC Customers by plan'!M5<=8),'RC Customers by plan'!M5<=8,IF('RC Customers by plan'!M5="","",'RC Customers by plan'!M5<=8))),IF('Model inputs'!AG52="","",'Model inputs'!AG52),IF('Model inputs'!AG48="","",'Model inputs'!AG48))="",0,IF(IF(IF(ISERROR('RC Customers by plan'!M5<=8),'RC Customers by plan'!M5<=8,IF('RC Customers by plan'!M5="","",'RC Customers by plan'!M5<=8))="",FALSE,IF(ISERROR('RC Customers by plan'!M5<=8),'RC Customers by plan'!M5<=8,IF('RC Customers by plan'!M5="","",'RC Customers by plan'!M5<=8))),IF('Model inputs'!AG52="","",'Model inputs'!AG52),IF('Model inputs'!AG48="","",'Model inputs'!AG48)))))) -> 6.5761251 | N13: =IF(IF(IF(ISERROR('RC Customers by plan'!N5<1),'RC Customers by plan'!N5<1,IF('RC Customers by plan'!N5="","",'RC Customers by plan'!N5<1))="",FALSE,IF(ISERROR('RC Customers by plan'!N5<1),'RC Customers by plan'!N5<1,IF('RC Customers by plan'!N5="","",'RC Customers by plan'!N5<1))),0,IF(IF(IF(ISERROR('RC Customers by plan'!N5=1),'RC Customers by plan'!N5=1,IF('RC Customers by plan'!N5="","",'RC Customers by plan'!N5=1))="",FALSE,IF(ISERROR('RC Customers by plan'!N5=1),'RC Customers by plan'!N5=1,IF('RC Customers by plan'!N5="","",'RC Customers by plan'!N5=1))),IF('Model inputs'!AG71="","",'Model inputs'!AG71),'RC Customers by plan'!M13*(1+IF(IF(IF(IF(ISERROR('RC Customers by plan'!N5<=8),'RC Customers by plan'!N5<=8,IF('RC Customers by plan'!N5="","",'RC Customers by plan'!N5<=8))="",FALSE,IF(ISERROR('RC Customers by plan'!N5<=8),'RC Customers by plan'!N5<=8,IF('RC Customers by plan'!N5="","",'RC Customers by plan'!N5<=8))),IF('Model inputs'!AG52="","",'Model inputs'!AG52),IF('Model inputs'!AG48="","",'Model inputs'!AG48))="",0,IF(IF(IF(ISERROR('RC Customers by plan'!N5<=8),'RC Customers by plan'!N5<=8,IF('RC Customers by plan'!N5="","",'RC Customers by plan'!N5<=8))="",FALSE,IF(ISERROR('RC Customers by plan'!N5<=8),'RC Customers by plan'!N5<=8,IF('RC Customers by plan'!N5="","",'RC Customers by plan'!N5<=8))),IF('Model inputs'!AG52="","",'Model inputs'!AG52),IF('Model inputs'!AG48="","",'Model inputs'!AG48)))))) -> 6.8391701 | O13: =IF(IF(IF(ISERROR('RC Customers by plan'!O5<1),'RC Customers by plan'!O5<1,IF('RC Customers by plan'!O5="","",'RC Customers by plan'!O5<1))="",FALSE,IF(ISERROR('RC Customers by plan'!O5<1),'RC Customers by plan'!O5<1,IF('RC Customers by plan'!O5="","",'RC Customers by plan'!O5<1))),0,IF(IF(IF(ISERROR('RC Customers by plan'!O5=1),'RC Customers by plan'!O5=1,IF('RC Customers by plan'!O5="","",'RC Customers by plan'!O5=1))="",FALSE,IF(ISERROR('RC Customers by plan'!O5=1),'RC Customers by plan'!O5=1,IF('RC Customers by plan'!O5="","",'RC Customers by plan'!O5=1))),IF('Model inputs'!AG71="","",'Model inputs'!AG71),'RC Customers by plan'!N13*(1+IF(IF(IF(IF(ISERROR('RC Customers by plan'!O5<=8),'RC Customers by plan'!O5<=8,IF('RC Customers by plan'!O5="","",'RC Customers by plan'!O5<=8))="",FALSE,IF(ISERROR('RC Customers by plan'!O5<=8),'RC Customers by plan'!O5<=8,IF('RC Customers by plan'!O5="","",'RC Customers by plan'!O5<=8))),IF('Model inputs'!AG52="","",'Model inputs'!AG52),IF('Model inputs'!AG48="","",'Model inputs'!AG48))="",0,IF(IF(IF(ISERROR('RC Customers by plan'!O5<=8),'RC Customers by plan'!O5<=8,IF('RC Customers by plan'!O5="","",'RC Customers by plan'!O5<=8))="",FALSE,IF(ISERROR('RC Customers by plan'!O5<=8),'RC Customers by plan'!O5<=8,IF('RC Customers by plan'!O5="","",'RC Customers by plan'!O5<=8))),IF('Model inputs'!AG52="","",'Model inputs'!AG52),IF('Model inputs'!AG48="","",'Model inputs'!AG48)))))) -> 7.1127369 | P13: =IF(IF(IF(ISERROR('RC Customers by plan'!P5<1),'RC Customers by plan'!P5<1,IF('RC Customers by plan'!P5="","",'RC Customers by plan'!P5<1))="",FALSE,IF(ISERROR('RC Customers by plan'!P5<1),'RC Customers by plan'!P5<1,IF('RC Customers by plan'!P5="","",'RC Customers by plan'!P5<1))),0,IF(IF(IF(ISERROR('RC Customers by plan'!P5=1),'RC Customers by plan'!P5=1,IF('RC Customers by plan'!P5="","",'RC Customers by plan'!P5=1))="",FALSE,IF(ISERROR('RC Customers by plan'!P5=1),'RC Customers by plan'!P5=1,IF('RC Customers by plan'!P5="","",'RC Customers by plan'!P5=1))),IF('Model inputs'!AG71="","",'Model inputs'!AG71),'RC Customers by plan'!O13*(1+IF(IF(IF(IF(ISERROR('RC Customers by plan'!P5<=8),'RC Customers by plan'!P5<=8,IF('RC Customers by plan'!P5="","",'RC Customers by plan'!P5<=8))="",FALSE,IF(ISERROR('RC Customers by plan'!P5<=8),'RC Customers by plan'!P5<=8,IF('RC Customers by plan'!P5="","",'RC Customers by plan'!P5<=8))),IF('Model inputs'!AG52="","",'Model inputs'!AG52),IF('Model inputs'!AG48="","",'Model inputs'!AG48))="",0,IF(IF(IF(ISERROR('RC Customers by plan'!P5<=8),'RC Customers by plan'!P5<=8,IF('RC Customers by plan'!P5="","",'RC Customers by plan'!P5<=8))="",FALSE,IF(ISERROR('RC Customers by plan'!P5<=8),'RC Customers by plan'!P5<=8,IF('RC Customers by plan'!P5="","",'RC Customers by plan'!P5<=8))),IF('Model inputs'!AG52="","",'Model inputs'!AG52),IF('Model inputs'!AG48="","",'Model inputs'!AG48)))))) -> 7.3972464 | Q13: =IF(IF(IF(ISERROR('RC Customers by plan'!Q5<1),'RC Customers by plan'!Q5<1,IF('RC Customers by plan'!Q5="","",'RC Customers by plan'!Q5<1))="",FALSE,IF(ISERROR('RC Customers by plan'!Q5<1),'RC Customers by plan'!Q5<1,IF('RC Customers by plan'!Q5="","",'RC Customers by plan'!Q5<1))),0,IF(IF(IF(ISERROR('RC Customers by plan'!Q5=1),'RC Customers by plan'!Q5=1,IF('RC Customers by plan'!Q5="","",'RC Customers by plan'!Q5=1))="",FALSE,IF(ISERROR('RC Customers by plan'!Q5=1),'RC Customers by plan'!Q5=1,IF('RC Customers by plan'!Q5="","",'RC Customers by plan'!Q5=1))),IF('Model inputs'!AG71="","",'Model inputs'!AG71),'RC Customers by plan'!P13*(1+IF(IF(IF(IF(ISERROR('RC Customers by plan'!Q5<=8),'RC Customers by plan'!Q5<=8,IF('RC Customers by plan'!Q5="","",'RC Customers by plan'!Q5<=8))="",FALSE,IF(ISERROR('RC Customers by plan'!Q5<=8),'RC Customers by plan'!Q5<=8,IF('RC Customers by plan'!Q5="","",'RC Customers by plan'!Q5<=8))),IF('Model inputs'!AG52="","",'Model inputs'!AG52),IF('Model inputs'!AG48="","",'Model inputs'!AG48))="",0,IF(IF(IF(ISERROR('RC Customers by plan'!Q5<=8),'RC Customers by plan'!Q5<=8,IF('RC Customers by plan'!Q5="","",'RC Customers by plan'!Q5<=8))="",FALSE,IF(ISERROR('RC Customers by plan'!Q5<=8),'RC Customers by plan'!Q5<=8,IF('RC Customers by plan'!Q5="","",'RC Customers by plan'!Q5<=8))),IF('Model inputs'!AG52="","",'Model inputs'!AG52),IF('Model inputs'!AG48="","",'Model inputs'!AG48)))))) -> 7.6931363 | R13: =IF(IF(IF(ISERROR('RC Customers by plan'!R5<1),'RC Customers by plan'!R5<1,IF('RC Customers by plan'!R5="","",'RC Customers by plan'!R5<1))="",FALSE,IF(ISERROR('RC Customers by plan'!R5<1),'RC Customers by plan'!R5<1,IF('RC Customers by plan'!R5="","",'RC Customers by plan'!R5<1))),0,IF(IF(IF(ISERROR('RC Customers by plan'!R5=1),'RC Customers by plan'!R5=1,IF('RC Customers by plan'!R5="","",'RC Customers by plan'!R5=1))="",FALSE,IF(ISERROR('RC Customers by plan'!R5=1),'RC Customers by plan'!R5=1,IF('RC Customers by plan'!R5="","",'RC Customers by plan'!R5=1))),IF('Model inputs'!AG71="","",'Model inputs'!AG71),'RC Customers by plan'!Q13*(1+IF(IF(IF(IF(ISERROR('RC Customers by plan'!R5<=8),'RC Customers by plan'!R5<=8,IF('RC Customers by plan'!R5="","",'RC Customers by plan'!R5<=8))="",FALSE,IF(ISERROR('RC Customers by plan'!R5<=8),'RC Customers by plan'!R5<=8,IF('RC Customers by plan'!R5="","",'RC Customers by plan'!R5<=8))),IF('Model inputs'!AG52="","",'Model inputs'!AG52),IF('Model inputs'!AG48="","",'Model inputs'!AG48))="",0,IF(IF(IF(ISERROR('RC Customers by plan'!R5<=8),'RC Customers by plan'!R5<=8,IF('RC Customers by plan'!R5="","",'RC Customers by plan'!R5<=8))="",FALSE,IF(ISERROR('RC Customers by plan'!R5<=8),'RC Customers by plan'!R5<=8,IF('RC Customers by plan'!R5="","",'RC Customers by plan'!R5<=8))),IF('Model inputs'!AG52="","",'Model inputs'!AG52),IF('Model inputs'!AG48="","",'Model inputs'!AG48)))))) -> 8.0008617 | S13: =IF(IF(IF(ISERROR('RC Customers by plan'!S5<1),'RC Customers by plan'!S5<1,IF('RC Customers by plan'!S5="","",'RC Customers by plan'!S5<1))="",FALSE,IF(ISERROR('RC Customers by plan'!S5<1),'RC Customers by plan'!S5<1,IF('RC Customers by plan'!S5="","",'RC Customers by plan'!S5<1))),0,IF(IF(IF(ISERROR('RC Customers by plan'!S5=1),'RC Customers by plan'!S5=1,IF('RC Customers by plan'!S5="","",'RC Customers by plan'!S5=1))="",FALSE,IF(ISERROR('RC Customers by plan'!S5=1),'RC Customers by plan'!S5=1,IF('RC Customers by plan'!S5="","",'RC Customers by plan'!S5=1))),IF('Model inputs'!AG71="","",'Model inputs'!AG71),'RC Customers by plan'!R13*(1+IF(IF(IF(IF(ISERROR('RC Customers by plan'!S5<=8),'RC Customers by plan'!S5<=8,IF('RC Customers by plan'!S5="","",'RC Customers by plan'!S5<=8))="",FALSE,IF(ISERROR('RC Customers by plan'!S5<=8),'RC Customers by plan'!S5<=8,IF('RC Customers by plan'!S5="","",'RC Customers by plan'!S5<=8))),IF('Model inputs'!AG52="","",'Model inputs'!AG52),IF('Model inputs'!AG48="","",'Model inputs'!AG48))="",0,IF(IF(IF(ISERROR('RC Customers by plan'!S5<=8),'RC Customers by plan'!S5<=8,IF('RC Customers by plan'!S5="","",'RC Customers by plan'!S5<=8))="",FALSE,IF(ISERROR('RC Customers by plan'!S5<=8),'RC Customers by plan'!S5<=8,IF('RC Customers by plan'!S5="","",'RC Customers by plan'!S5<=8))),IF('Model inputs'!AG52="","",'Model inputs'!AG52),IF('Model inputs'!AG48="","",'Model inputs'!AG48)))))) -> 8.3208962
A14: Waitlist new logos | B14: =SUM('RC Customers by plan'!B15,'RC Customers by plan'!B16,'RC Customers by plan'!B17) -> 0 | C14: =SUM('RC Customers by plan'!C15,'RC Customers by plan'!C16,'RC Customers by plan'!C17) -> 12 | D14: =SUM('RC Customers by plan'!D15,'RC Customers by plan'!D16,'RC Customers by plan'!D17) -> 0 | E14: =SUM('RC Customers by plan'!E15,'RC Customers by plan'!E16,'RC Customers by plan'!E17) -> 0 | F14: =SUM('RC Customers by plan'!F15,'RC Customers by plan'!F16,'RC Customers by plan'!F17) -> 0 | G14: =SUM('RC Customers by plan'!G15,'RC Customers by plan'!G16,'RC Customers by plan'!G17) -> 0 | H14: =SUM('RC Customers by plan'!H15,'RC Customers by plan'!H16,'RC Customers by plan'!H17) -> 0 | I14: =SUM('RC Customers by plan'!I15,'RC Customers by plan'!I16,'RC Customers by plan'!I17) -> 0 | ... S14: =SUM('RC Customers by plan'!S15,'RC Customers by plan'!S16,'RC Customers by plan'!S17) -> 0
A15: Indie | B15: =IF(IF(IF(ISERROR('RC Customers by plan'!B5=1),'RC Customers by plan'!B5=1,IF('RC Customers by plan'!B5="","",'RC Customers by plan'!B5=1))="",FALSE,IF(ISERROR('RC Customers by plan'!B5=1),'RC Customers by plan'!B5=1,IF('RC Customers by plan'!B5="","",'RC Customers by plan'!B5=1))),IF('Model inputs'!AG98="","",'Model inputs'!AG98),0) -> 0 | C15: =IF(IF(IF(ISERROR('RC Customers by plan'!C5=1),'RC Customers by plan'!C5=1,IF('RC Customers by plan'!C5="","",'RC Customers by plan'!C5=1))="",FALSE,IF(ISERROR('RC Customers by plan'!C5=1),'RC Customers by plan'!C5=1,IF('RC Customers by plan'!C5="","",'RC Customers by plan'!C5=1))),IF('Model inputs'!AG98="","",'Model inputs'!AG98),0) -> 12 | D15: =IF(IF(IF(ISERROR('RC Customers by plan'!D5=1),'RC Customers by plan'!D5=1,IF('RC Customers by plan'!D5="","",'RC Customers by plan'!D5=1))="",FALSE,IF(ISERROR('RC Customers by plan'!D5=1),'RC Customers by plan'!D5=1,IF('RC Customers by plan'!D5="","",'RC Customers by plan'!D5=1))),IF('Model inputs'!AG98="","",'Model inputs'!AG98),0) -> 0 | E15: =IF(IF(IF(ISERROR('RC Customers by plan'!E5=1),'RC Customers by plan'!E5=1,IF('RC Customers by plan'!E5="","",'RC Customers by plan'!E5=1))="",FALSE,IF(ISERROR('RC Customers by plan'!E5=1),'RC Customers by plan'!E5=1,IF('RC Customers by plan'!E5="","",'RC Customers by plan'!E5=1))),IF('Model inputs'!AG98="","",'Model inputs'!AG98),0) -> 0 | F15: =IF(IF(IF(ISERROR('RC Customers by plan'!F5=1),'RC Customers by plan'!F5=1,IF('RC Customers by plan'!F5="","",'RC Customers by plan'!F5=1))="",FALSE,IF(ISERROR('RC Customers by plan'!F5=1),'RC Customers by plan'!F5=1,IF('RC Customers by plan'!F5="","",'RC Customers by plan'!F5=1))),IF('Model inputs'!AG98="","",'Model inputs'!AG98),0) -> 0 | G15: =IF(IF(IF(ISERROR('RC Customers by plan'!G5=1),'RC Customers by plan'!G5=1,IF('RC Customers by plan'!G5="","",'RC Customers by plan'!G5=1))="",FALSE,IF(ISERROR('RC Customers by plan'!G5=1),'RC Customers by plan'!G5=1,IF('RC Customers by plan'!G5="","",'RC Customers by plan'!G5=1))),IF('Model inputs'!AG98="","",'Model inputs'!AG98),0) -> 0 | H15: =IF(IF(IF(ISERROR('RC Customers by plan'!H5=1),'RC Customers by plan'!H5=1,IF('RC Customers by plan'!H5="","",'RC Customers by plan'!H5=1))="",FALSE,IF(ISERROR('RC Customers by plan'!H5=1),'RC Customers by plan'!H5=1,IF('RC Customers by plan'!H5="","",'RC Customers by plan'!H5=1))),IF('Model inputs'!AG98="","",'Model inputs'!AG98),0) -> 0 | I15: =IF(IF(IF(ISERROR('RC Customers by plan'!I5=1),'RC Customers by plan'!I5=1,IF('RC Customers by plan'!I5="","",'RC Customers by plan'!I5=1))="",FALSE,IF(ISERROR('RC Customers by plan'!I5=1),'RC Customers by plan'!I5=1,IF('RC Customers by plan'!I5="","",'RC Customers by plan'!I5=1))),IF('Model inputs'!AG98="","",'Model inputs'!AG98),0) -> 0 | J15: =IF(IF(IF(ISERROR('RC Customers by plan'!J5=1),'RC Customers by plan'!J5=1,IF('RC Customers by plan'!J5="","",'RC Customers by plan'!J5=1))="",FALSE,IF(ISERROR('RC Customers by plan'!J5=1),'RC Customers by plan'!J5=1,IF('RC Customers by plan'!J5="","",'RC Customers by plan'!J5=1))),IF('Model inputs'!AG98="","",'Model inputs'!AG98),0) -> 0 | K15: =IF(IF(IF(ISERROR('RC Customers by plan'!K5=1),'RC Customers by plan'!K5=1,IF('RC Customers by plan'!K5="","",'RC Customers by plan'!K5=1))="",FALSE,IF(ISERROR('RC Customers by plan'!K5=1),'RC Customers by plan'!K5=1,IF('RC Customers by plan'!K5="","",'RC Customers by plan'!K5=1))),IF('Model inputs'!AG98="","",'Model inputs'!AG98),0) -> 0 | L15: =IF(IF(IF(ISERROR('RC Customers by plan'!L5=1),'RC Customers by plan'!L5=1,IF('RC Customers by plan'!L5="","",'RC Customers by plan'!L5=1))="",FALSE,IF(ISERROR('RC Customers by plan'!L5=1),'RC Customers by plan'!L5=1,IF('RC Customers by plan'!L5="","",'RC Customers by plan'!L5=1))),IF('Model inputs'!AG98="","",'Model inputs'!AG98),0) -> 0 | M15: =IF(IF(IF(ISERROR('RC Customers by plan'!M5=1),'RC Customers by plan'!M5=1,IF('RC Customers by plan'!M5="","",'RC Customers by plan'!M5=1))="",FALSE,IF(ISERROR('RC Customers by plan'!M5=1),'RC Customers by plan'!M5=1,IF('RC Customers by plan'!M5="","",'RC Customers by plan'!M5=1))),IF('Model inputs'!AG98="","",'Model inputs'!AG98),0) -> 0 | N15: =IF(IF(IF(ISERROR('RC Customers by plan'!N5=1),'RC Customers by plan'!N5=1,IF('RC Customers by plan'!N5="","",'RC Customers by plan'!N5=1))="",FALSE,IF(ISERROR('RC Customers by plan'!N5=1),'RC Customers by plan'!N5=1,IF('RC Customers by plan'!N5="","",'RC Customers by plan'!N5=1))),IF('Model inputs'!AG98="","",'Model inputs'!AG98),0) -> 0 | O15: =IF(IF(IF(ISERROR('RC Customers by plan'!O5=1),'RC Customers by plan'!O5=1,IF('RC Customers by plan'!O5="","",'RC Customers by plan'!O5=1))="",FALSE,IF(ISERROR('RC Customers by plan'!O5=1),'RC Customers by plan'!O5=1,IF('RC Customers by plan'!O5="","",'RC Customers by plan'!O5=1))),IF('Model inputs'!AG98="","",'Model inputs'!AG98),0) -> 0 | P15: =IF(IF(IF(ISERROR('RC Customers by plan'!P5=1),'RC Customers by plan'!P5=1,IF('RC Customers by plan'!P5="","",'RC Customers by plan'!P5=1))="",FALSE,IF(ISERROR('RC Customers by plan'!P5=1),'RC Customers by plan'!P5=1,IF('RC Customers by plan'!P5="","",'RC Customers by plan'!P5=1))),IF('Model inputs'!AG98="","",'Model inputs'!AG98),0) -> 0 | Q15: =IF(IF(IF(ISERROR('RC Customers by plan'!Q5=1),'RC Customers by plan'!Q5=1,IF('RC Customers by plan'!Q5="","",'RC Customers by plan'!Q5=1))="",FALSE,IF(ISERROR('RC Customers by plan'!Q5=1),'RC Customers by plan'!Q5=1,IF('RC Customers by plan'!Q5="","",'RC Customers by plan'!Q5=1))),IF('Model inputs'!AG98="","",'Model inputs'!AG98),0) -> 0 | R15: =IF(IF(IF(ISERROR('RC Customers by plan'!R5=1),'RC Customers by plan'!R5=1,IF('RC Customers by plan'!R5="","",'RC Customers by plan'!R5=1))="",FALSE,IF(ISERROR('RC Customers by plan'!R5=1),'RC Customers by plan'!R5=1,IF('RC Customers by plan'!R5="","",'RC Customers by plan'!R5=1))),IF('Model inputs'!AG98="","",'Model inputs'!AG98),0) -> 0 | S15: =IF(IF(IF(ISERROR('RC Customers by plan'!S5=1),'RC Customers by plan'!S5=1,IF('RC Customers by plan'!S5="","",'RC Customers by plan'!S5=1))="",FALSE,IF(ISERROR('RC Customers by plan'!S5=1),'RC Customers by plan'!S5=1,IF('RC Customers by plan'!S5="","",'RC Customers by plan'!S5=1))),IF('Model inputs'!AG98="","",'Model inputs'!AG98),0) -> 0
A16: Launch | B16: =IF(IF(IF(ISERROR('RC Customers by plan'!B5=1),'RC Customers by plan'!B5=1,IF('RC Customers by plan'!B5="","",'RC Customers by plan'!B5=1))="",FALSE,IF(ISERROR('RC Customers by plan'!B5=1),'RC Customers by plan'!B5=1,IF('RC Customers by plan'!B5="","",'RC Customers by plan'!B5=1))),IF('Model inputs'!AG99="","",'Model inputs'!AG99),0) -> 0 | C16: =IF(IF(IF(ISERROR('RC Customers by plan'!C5=1),'RC Customers by plan'!C5=1,IF('RC Customers by plan'!C5="","",'RC Customers by plan'!C5=1))="",FALSE,IF(ISERROR('RC Customers by plan'!C5=1),'RC Customers by plan'!C5=1,IF('RC Customers by plan'!C5="","",'RC Customers by plan'!C5=1))),IF('Model inputs'!AG99="","",'Model inputs'!AG99),0) -> 0 | D16: =IF(IF(IF(ISERROR('RC Customers by plan'!D5=1),'RC Customers by plan'!D5=1,IF('RC Customers by plan'!D5="","",'RC Customers by plan'!D5=1))="",FALSE,IF(ISERROR('RC Customers by plan'!D5=1),'RC Customers by plan'!D5=1,IF('RC Customers by plan'!D5="","",'RC Customers by plan'!D5=1))),IF('Model inputs'!AG99="","",'Model inputs'!AG99),0) -> 0 | E16: =IF(IF(IF(ISERROR('RC Customers by plan'!E5=1),'RC Customers by plan'!E5=1,IF('RC Customers by plan'!E5="","",'RC Customers by plan'!E5=1))="",FALSE,IF(ISERROR('RC Customers by plan'!E5=1),'RC Customers by plan'!E5=1,IF('RC Customers by plan'!E5="","",'RC Customers by plan'!E5=1))),IF('Model inputs'!AG99="","",'Model inputs'!AG99),0) -> 0 | F16: =IF(IF(IF(ISERROR('RC Customers by plan'!F5=1),'RC Customers by plan'!F5=1,IF('RC Customers by plan'!F5="","",'RC Customers by plan'!F5=1))="",FALSE,IF(ISERROR('RC Customers by plan'!F5=1),'RC Customers by plan'!F5=1,IF('RC Customers by plan'!F5="","",'RC Customers by plan'!F5=1))),IF('Model inputs'!AG99="","",'Model inputs'!AG99),0) -> 0 | G16: =IF(IF(IF(ISERROR('RC Customers by plan'!G5=1),'RC Customers by plan'!G5=1,IF('RC Customers by plan'!G5="","",'RC Customers by plan'!G5=1))="",FALSE,IF(ISERROR('RC Customers by plan'!G5=1),'RC Customers by plan'!G5=1,IF('RC Customers by plan'!G5="","",'RC Customers by plan'!G5=1))),IF('Model inputs'!AG99="","",'Model inputs'!AG99),0) -> 0 | H16: =IF(IF(IF(ISERROR('RC Customers by plan'!H5=1),'RC Customers by plan'!H5=1,IF('RC Customers by plan'!H5="","",'RC Customers by plan'!H5=1))="",FALSE,IF(ISERROR('RC Customers by plan'!H5=1),'RC Customers by plan'!H5=1,IF('RC Customers by plan'!H5="","",'RC Customers by plan'!H5=1))),IF('Model inputs'!AG99="","",'Model inputs'!AG99),0) -> 0 | I16: =IF(IF(IF(ISERROR('RC Customers by plan'!I5=1),'RC Customers by plan'!I5=1,IF('RC Customers by plan'!I5="","",'RC Customers by plan'!I5=1))="",FALSE,IF(ISERROR('RC Customers by plan'!I5=1),'RC Customers by plan'!I5=1,IF('RC Customers by plan'!I5="","",'RC Customers by plan'!I5=1))),IF('Model inputs'!AG99="","",'Model inputs'!AG99),0) -> 0 | J16: =IF(IF(IF(ISERROR('RC Customers by plan'!J5=1),'RC Customers by plan'!J5=1,IF('RC Customers by plan'!J5="","",'RC Customers by plan'!J5=1))="",FALSE,IF(ISERROR('RC Customers by plan'!J5=1),'RC Customers by plan'!J5=1,IF('RC Customers by plan'!J5="","",'RC Customers by plan'!J5=1))),IF('Model inputs'!AG99="","",'Model inputs'!AG99),0) -> 0 | K16: =IF(IF(IF(ISERROR('RC Customers by plan'!K5=1),'RC Customers by plan'!K5=1,IF('RC Customers by plan'!K5="","",'RC Customers by plan'!K5=1))="",FALSE,IF(ISERROR('RC Customers by plan'!K5=1),'RC Customers by plan'!K5=1,IF('RC Customers by plan'!K5="","",'RC Customers by plan'!K5=1))),IF('Model inputs'!AG99="","",'Model inputs'!AG99),0) -> 0 | L16: =IF(IF(IF(ISERROR('RC Customers by plan'!L5=1),'RC Customers by plan'!L5=1,IF('RC Customers by plan'!L5="","",'RC Customers by plan'!L5=1))="",FALSE,IF(ISERROR('RC Customers by plan'!L5=1),'RC Customers by plan'!L5=1,IF('RC Customers by plan'!L5="","",'RC Customers by plan'!L5=1))),IF('Model inputs'!AG99="","",'Model inputs'!AG99),0) -> 0 | M16: =IF(IF(IF(ISERROR('RC Customers by plan'!M5=1),'RC Customers by plan'!M5=1,IF('RC Customers by plan'!M5="","",'RC Customers by plan'!M5=1))="",FALSE,IF(ISERROR('RC Customers by plan'!M5=1),'RC Customers by plan'!M5=1,IF('RC Customers by plan'!M5="","",'RC Customers by plan'!M5=1))),IF('Model inputs'!AG99="","",'Model inputs'!AG99),0) -> 0 | N16: =IF(IF(IF(ISERROR('RC Customers by plan'!N5=1),'RC Customers by plan'!N5=1,IF('RC Customers by plan'!N5="","",'RC Customers by plan'!N5=1))="",FALSE,IF(ISERROR('RC Customers by plan'!N5=1),'RC Customers by plan'!N5=1,IF('RC Customers by plan'!N5="","",'RC Customers by plan'!N5=1))),IF('Model inputs'!AG99="","",'Model inputs'!AG99),0) -> 0 | O16: =IF(IF(IF(ISERROR('RC Customers by plan'!O5=1),'RC Customers by plan'!O5=1,IF('RC Customers by plan'!O5="","",'RC Customers by plan'!O5=1))="",FALSE,IF(ISERROR('RC Customers by plan'!O5=1),'RC Customers by plan'!O5=1,IF('RC Customers by plan'!O5="","",'RC Customers by plan'!O5=1))),IF('Model inputs'!AG99="","",'Model inputs'!AG99),0) -> 0 | P16: =IF(IF(IF(ISERROR('RC Customers by plan'!P5=1),'RC Customers by plan'!P5=1,IF('RC Customers by plan'!P5="","",'RC Customers by plan'!P5=1))="",FALSE,IF(ISERROR('RC Customers by plan'!P5=1),'RC Customers by plan'!P5=1,IF('RC Customers by plan'!P5="","",'RC Customers by plan'!P5=1))),IF('Model inputs'!AG99="","",'Model inputs'!AG99),0) -> 0 | Q16: =IF(IF(IF(ISERROR('RC Customers by plan'!Q5=1),'RC Customers by plan'!Q5=1,IF('RC Customers by plan'!Q5="","",'RC Customers by plan'!Q5=1))="",FALSE,IF(ISERROR('RC Customers by plan'!Q5=1),'RC Customers by plan'!Q5=1,IF('RC Customers by plan'!Q5="","",'RC Customers by plan'!Q5=1))),IF('Model inputs'!AG99="","",'Model inputs'!AG99),0) -> 0 | R16: =IF(IF(IF(ISERROR('RC Customers by plan'!R5=1),'RC Customers by plan'!R5=1,IF('RC Customers by plan'!R5="","",'RC Customers by plan'!R5=1))="",FALSE,IF(ISERROR('RC Customers by plan'!R5=1),'RC Customers by plan'!R5=1,IF('RC Customers by plan'!R5="","",'RC Customers by plan'!R5=1))),IF('Model inputs'!AG99="","",'Model inputs'!AG99),0) -> 0 | S16: =IF(IF(IF(ISERROR('RC Customers by plan'!S5=1),'RC Customers by plan'!S5=1,IF('RC Customers by plan'!S5="","",'RC Customers by plan'!S5=1))="",FALSE,IF(ISERROR('RC Customers by plan'!S5=1),'RC Customers by plan'!S5=1,IF('RC Customers by plan'!S5="","",'RC Customers by plan'!S5=1))),IF('Model inputs'!AG99="","",'Model inputs'!AG99),0) -> 0
A17: Team | B17: =IF(IF(IF(ISERROR('RC Customers by plan'!B5=1),'RC Customers by plan'!B5=1,IF('RC Customers by plan'!B5="","",'RC Customers by plan'!B5=1))="",FALSE,IF(ISERROR('RC Customers by plan'!B5=1),'RC Customers by plan'!B5=1,IF('RC Customers by plan'!B5="","",'RC Customers by plan'!B5=1))),IF('Model inputs'!AG100="","",'Model inputs'!AG100),0) -> 0 | C17: =IF(IF(IF(ISERROR('RC Customers by plan'!C5=1),'RC Customers by plan'!C5=1,IF('RC Customers by plan'!C5="","",'RC Customers by plan'!C5=1))="",FALSE,IF(ISERROR('RC Customers by plan'!C5=1),'RC Customers by plan'!C5=1,IF('RC Customers by plan'!C5="","",'RC Customers by plan'!C5=1))),IF('Model inputs'!AG100="","",'Model inputs'!AG100),0) -> 0 | D17: =IF(IF(IF(ISERROR('RC Customers by plan'!D5=1),'RC Customers by plan'!D5=1,IF('RC Customers by plan'!D5="","",'RC Customers by plan'!D5=1))="",FALSE,IF(ISERROR('RC Customers by plan'!D5=1),'RC Customers by plan'!D5=1,IF('RC Customers by plan'!D5="","",'RC Customers by plan'!D5=1))),IF('Model inputs'!AG100="","",'Model inputs'!AG100),0) -> 0 | E17: =IF(IF(IF(ISERROR('RC Customers by plan'!E5=1),'RC Customers by plan'!E5=1,IF('RC Customers by plan'!E5="","",'RC Customers by plan'!E5=1))="",FALSE,IF(ISERROR('RC Customers by plan'!E5=1),'RC Customers by plan'!E5=1,IF('RC Customers by plan'!E5="","",'RC Customers by plan'!E5=1))),IF('Model inputs'!AG100="","",'Model inputs'!AG100),0) -> 0 | F17: =IF(IF(IF(ISERROR('RC Customers by plan'!F5=1),'RC Customers by plan'!F5=1,IF('RC Customers by plan'!F5="","",'RC Customers by plan'!F5=1))="",FALSE,IF(ISERROR('RC Customers by plan'!F5=1),'RC Customers by plan'!F5=1,IF('RC Customers by plan'!F5="","",'RC Customers by plan'!F5=1))),IF('Model inputs'!AG100="","",'Model inputs'!AG100),0) -> 0 | G17: =IF(IF(IF(ISERROR('RC Customers by plan'!G5=1),'RC Customers by plan'!G5=1,IF('RC Customers by plan'!G5="","",'RC Customers by plan'!G5=1))="",FALSE,IF(ISERROR('RC Customers by plan'!G5=1),'RC Customers by plan'!G5=1,IF('RC Customers by plan'!G5="","",'RC Customers by plan'!G5=1))),IF('Model inputs'!AG100="","",'Model inputs'!AG100),0) -> 0 | H17: =IF(IF(IF(ISERROR('RC Customers by plan'!H5=1),'RC Customers by plan'!H5=1,IF('RC Customers by plan'!H5="","",'RC Customers by plan'!H5=1))="",FALSE,IF(ISERROR('RC Customers by plan'!H5=1),'RC Customers by plan'!H5=1,IF('RC Customers by plan'!H5="","",'RC Customers by plan'!H5=1))),IF('Model inputs'!AG100="","",'Model inputs'!AG100),0) -> 0 | I17: =IF(IF(IF(ISERROR('RC Customers by plan'!I5=1),'RC Customers by plan'!I5=1,IF('RC Customers by plan'!I5="","",'RC Customers by plan'!I5=1))="",FALSE,IF(ISERROR('RC Customers by plan'!I5=1),'RC Customers by plan'!I5=1,IF('RC Customers by plan'!I5="","",'RC Customers by plan'!I5=1))),IF('Model inputs'!AG100="","",'Model inputs'!AG100),0) -> 0 | J17: =IF(IF(IF(ISERROR('RC Customers by plan'!J5=1),'RC Customers by plan'!J5=1,IF('RC Customers by plan'!J5="","",'RC Customers by plan'!J5=1))="",FALSE,IF(ISERROR('RC Customers by plan'!J5=1),'RC Customers by plan'!J5=1,IF('RC Customers by plan'!J5="","",'RC Customers by plan'!J5=1))),IF('Model inputs'!AG100="","",'Model inputs'!AG100),0) -> 0 | K17: =IF(IF(IF(ISERROR('RC Customers by plan'!K5=1),'RC Customers by plan'!K5=1,IF('RC Customers by plan'!K5="","",'RC Customers by plan'!K5=1))="",FALSE,IF(ISERROR('RC Customers by plan'!K5=1),'RC Customers by plan'!K5=1,IF('RC Customers by plan'!K5="","",'RC Customers by plan'!K5=1))),IF('Model inputs'!AG100="","",'Model inputs'!AG100),0) -> 0 | L17: =IF(IF(IF(ISERROR('RC Customers by plan'!L5=1),'RC Customers by plan'!L5=1,IF('RC Customers by plan'!L5="","",'RC Customers by plan'!L5=1))="",FALSE,IF(ISERROR('RC Customers by plan'!L5=1),'RC Customers by plan'!L5=1,IF('RC Customers by plan'!L5="","",'RC Customers by plan'!L5=1))),IF('Model inputs'!AG100="","",'Model inputs'!AG100),0) -> 0 | M17: =IF(IF(IF(ISERROR('RC Customers by plan'!M5=1),'RC Customers by plan'!M5=1,IF('RC Customers by plan'!M5="","",'RC Customers by plan'!M5=1))="",FALSE,IF(ISERROR('RC Customers by plan'!M5=1),'RC Customers by plan'!M5=1,IF('RC Customers by plan'!M5="","",'RC Customers by plan'!M5=1))),IF('Model inputs'!AG100="","",'Model inputs'!AG100),0) -> 0 | N17: =IF(IF(IF(ISERROR('RC Customers by plan'!N5=1),'RC Customers by plan'!N5=1,IF('RC Customers by plan'!N5="","",'RC Customers by plan'!N5=1))="",FALSE,IF(ISERROR('RC Customers by plan'!N5=1),'RC Customers by plan'!N5=1,IF('RC Customers by plan'!N5="","",'RC Customers by plan'!N5=1))),IF('Model inputs'!AG100="","",'Model inputs'!AG100),0) -> 0 | O17: =IF(IF(IF(ISERROR('RC Customers by plan'!O5=1),'RC Customers by plan'!O5=1,IF('RC Customers by plan'!O5="","",'RC Customers by plan'!O5=1))="",FALSE,IF(ISERROR('RC Customers by plan'!O5=1),'RC Customers by plan'!O5=1,IF('RC Customers by plan'!O5="","",'RC Customers by plan'!O5=1))),IF('Model inputs'!AG100="","",'Model inputs'!AG100),0) -> 0 | P17: =IF(IF(IF(ISERROR('RC Customers by plan'!P5=1),'RC Customers by plan'!P5=1,IF('RC Customers by plan'!P5="","",'RC Customers by plan'!P5=1))="",FALSE,IF(ISERROR('RC Customers by plan'!P5=1),'RC Customers by plan'!P5=1,IF('RC Customers by plan'!P5="","",'RC Customers by plan'!P5=1))),IF('Model inputs'!AG100="","",'Model inputs'!AG100),0) -> 0 | Q17: =IF(IF(IF(ISERROR('RC Customers by plan'!Q5=1),'RC Customers by plan'!Q5=1,IF('RC Customers by plan'!Q5="","",'RC Customers by plan'!Q5=1))="",FALSE,IF(ISERROR('RC Customers by plan'!Q5=1),'RC Customers by plan'!Q5=1,IF('RC Customers by plan'!Q5="","",'RC Customers by plan'!Q5=1))),IF('Model inputs'!AG100="","",'Model inputs'!AG100),0) -> 0 | R17: =IF(IF(IF(ISERROR('RC Customers by plan'!R5=1),'RC Customers by plan'!R5=1,IF('RC Customers by plan'!R5="","",'RC Customers by plan'!R5=1))="",FALSE,IF(ISERROR('RC Customers by plan'!R5=1),'RC Customers by plan'!R5=1,IF('RC Customers by plan'!R5="","",'RC Customers by plan'!R5=1))),IF('Model inputs'!AG100="","",'Model inputs'!AG100),0) -> 0 | S17: =IF(IF(IF(ISERROR('RC Customers by plan'!S5=1),'RC Customers by plan'!S5=1,IF('RC Customers by plan'!S5="","",'RC Customers by plan'!S5=1))="",FALSE,IF(ISERROR('RC Customers by plan'!S5=1),'RC Customers by plan'!S5=1,IF('RC Customers by plan'!S5="","",'RC Customers by plan'!S5=1))),IF('Model inputs'!AG100="","",'Model inputs'!AG100),0) -> 0
A18: Upgrades in | B18: =SUM('RC Customers by plan'!B19,'RC Customers by plan'!B20,'RC Customers by plan'!B21) -> 0 | C18: =SUM('RC Customers by plan'!C19,'RC Customers by plan'!C20,'RC Customers by plan'!C21) -> 0.29166667 | D18: =SUM('RC Customers by plan'!D19,'RC Customers by plan'!D20,'RC Customers by plan'!D21) -> 0.5333125 | E18: =SUM('RC Customers by plan'!E19,'RC Customers by plan'!E20,'RC Customers by plan'!E21) -> 0.69480025 | F18: =SUM('RC Customers by plan'!F19,'RC Customers by plan'!F20,'RC Customers by plan'!F21) -> 0.86238155 | G18: =SUM('RC Customers by plan'!G19,'RC Customers by plan'!G20,'RC Customers by plan'!G21) -> 1.0370073 | H18: =SUM('RC Customers by plan'!H19,'RC Customers by plan'!H20,'RC Customers by plan'!H21) -> 1.2196779 | I18: =SUM('RC Customers by plan'!I19,'RC Customers by plan'!I20,'RC Customers by plan'!I21) -> 1.4114492 | ... S18: =SUM('RC Customers by plan'!S19,'RC Customers by plan'!S20,'RC Customers by plan'!S21) -> 3.5695543
A19: Indie | B19: =IF(EXACT("Indie","Team"),IF('RC Customers by plan'!B27="","",'RC Customers by plan'!B27),IF(EXACT("Indie","Launch"),IF('RC Customers by plan'!B29="","",'RC Customers by plan'!B29),0)) -> 0 | C19: =IF(EXACT("Indie","Team"),IF('RC Customers by plan'!C27="","",'RC Customers by plan'!C27),IF(EXACT("Indie","Launch"),IF('RC Customers by plan'!C29="","",'RC Customers by plan'!C29),0)) -> 0 | D19: =IF(EXACT("Indie","Team"),IF('RC Customers by plan'!D27="","",'RC Customers by plan'!D27),IF(EXACT("Indie","Launch"),IF('RC Customers by plan'!D29="","",'RC Customers by plan'!D29),0)) -> 0 | E19: =IF(EXACT("Indie","Team"),IF('RC Customers by plan'!E27="","",'RC Customers by plan'!E27),IF(EXACT("Indie","Launch"),IF('RC Customers by plan'!E29="","",'RC Customers by plan'!E29),0)) -> 0 | F19: =IF(EXACT("Indie","Team"),IF('RC Customers by plan'!F27="","",'RC Customers by plan'!F27),IF(EXACT("Indie","Launch"),IF('RC Customers by plan'!F29="","",'RC Customers by plan'!F29),0)) -> 0 | G19: =IF(EXACT("Indie","Team"),IF('RC Customers by plan'!G27="","",'RC Customers by plan'!G27),IF(EXACT("Indie","Launch"),IF('RC Customers by plan'!G29="","",'RC Customers by plan'!G29),0)) -> 0 | H19: =IF(EXACT("Indie","Team"),IF('RC Customers by plan'!H27="","",'RC Customers by plan'!H27),IF(EXACT("Indie","Launch"),IF('RC Customers by plan'!H29="","",'RC Customers by plan'!H29),0)) -> 0 | I19: =IF(EXACT("Indie","Team"),IF('RC Customers by plan'!I27="","",'RC Customers by plan'!I27),IF(EXACT("Indie","Launch"),IF('RC Customers by plan'!I29="","",'RC Customers by plan'!I29),0)) -> 0 | ... S19: =IF(EXACT("Indie","Team"),IF('RC Customers by plan'!S27="","",'RC Customers by plan'!S27),IF(EXACT("Indie","Launch"),IF('RC Customers by plan'!S29="","",'RC Customers by plan'!S29),0)) -> 0
A20: Launch | B20: =IF(EXACT("Launch","Team"),IF('RC Customers by plan'!B27="","",'RC Customers by plan'!B27),IF(EXACT("Launch","Launch"),IF('RC Customers by plan'!B29="","",'RC Customers by plan'!B29),0)) -> 0 | C20: =IF(EXACT("Launch","Team"),IF('RC Customers by plan'!C27="","",'RC Customers by plan'!C27),IF(EXACT("Launch","Launch"),IF('RC Customers by plan'!C29="","",'RC Customers by plan'!C29),0)) -> 0.025 | D20: =IF(EXACT("Launch","Team"),IF('RC Customers by plan'!D27="","",'RC Customers by plan'!D27),IF(EXACT("Launch","Launch"),IF('RC Customers by plan'!D29="","",'RC Customers by plan'!D29),0)) -> 0.037756944 | E20: =IF(EXACT("Launch","Team"),IF('RC Customers by plan'!E27="","",'RC Customers by plan'!E27),IF(EXACT("Launch","Launch"),IF('RC Customers by plan'!E29="","",'RC Customers by plan'!E29),0)) -> 0.05228173 | F20: =IF(EXACT("Launch","Team"),IF('RC Customers by plan'!F27="","",'RC Customers by plan'!F27),IF(EXACT("Launch","Launch"),IF('RC Customers by plan'!F29="","",'RC Customers by plan'!F29),0)) -> 0.068297598 | G20: =IF(EXACT("Launch","Team"),IF('RC Customers by plan'!G27="","",'RC Customers by plan'!G27),IF(EXACT("Launch","Launch"),IF('RC Customers by plan'!G29="","",'RC Customers by plan'!G29),0)) -> 0.08591028 | H20: =IF(EXACT("Launch","Team"),IF('RC Customers by plan'!H27="","",'RC Customers by plan'!H27),IF(EXACT("Launch","Launch"),IF('RC Customers by plan'!H29="","",'RC Customers by plan'!H29),0)) -> 0.10523917 | I20: =IF(EXACT("Launch","Team"),IF('RC Customers by plan'!I27="","",'RC Customers by plan'!I27),IF(EXACT("Launch","Launch"),IF('RC Customers by plan'!I29="","",'RC Customers by plan'!I29),0)) -> 0.12641836 | ... S20: =IF(EXACT("Launch","Team"),IF('RC Customers by plan'!S27="","",'RC Customers by plan'!S27),IF(EXACT("Launch","Launch"),IF('RC Customers by plan'!S29="","",'RC Customers by plan'!S29),0)) -> 0.41059681
A21: Team | B21: =IF(EXACT("Team","Team"),IF('RC Customers by plan'!B27="","",'RC Customers by plan'!B27),IF(EXACT("Team","Launch"),IF('RC Customers by plan'!B29="","",'RC Customers by plan'!B29),0)) -> 0 | C21: =IF(EXACT("Team","Team"),IF('RC Customers by plan'!C27="","",'RC Customers by plan'!C27),IF(EXACT("Team","Launch"),IF('RC Customers by plan'!C29="","",'RC Customers by plan'!C29),0)) -> 0.26666667 | D21: =IF(EXACT("Team","Team"),IF('RC Customers by plan'!D27="","",'RC Customers by plan'!D27),IF(EXACT("Team","Launch"),IF('RC Customers by plan'!D29="","",'RC Customers by plan'!D29),0)) -> 0.49555556 | E21: =IF(EXACT("Team","Team"),IF('RC Customers by plan'!E27="","",'RC Customers by plan'!E27),IF(EXACT("Team","Launch"),IF('RC Customers by plan'!E29="","",'RC Customers by plan'!E29),0)) -> 0.64251852 | F21: =IF(EXACT("Team","Team"),IF('RC Customers by plan'!F27="","",'RC Customers by plan'!F27),IF(EXACT("Team","Launch"),IF('RC Customers by plan'!F29="","",'RC Customers by plan'!F29),0)) -> 0.79408395 | G21: =IF(EXACT("Team","Team"),IF('RC Customers by plan'!G27="","",'RC Customers by plan'!G27),IF(EXACT("Team","Launch"),IF('RC Customers by plan'!G29="","",'RC Customers by plan'!G29),0)) -> 0.95109702 | H21: =IF(EXACT("Team","Team"),IF('RC Customers by plan'!H27="","",'RC Customers by plan'!H27),IF(EXACT("Team","Launch"),IF('RC Customers by plan'!H29="","",'RC Customers by plan'!H29),0)) -> 1.1144387 | I21: =IF(EXACT("Team","Team"),IF('RC Customers by plan'!I27="","",'RC Customers by plan'!I27),IF(EXACT("Team","Launch"),IF('RC Customers by plan'!I29="","",'RC Customers by plan'!I29),0)) -> 1.2850308 | ... S21: =IF(EXACT("Team","Team"),IF('RC Customers by plan'!S27="","",'RC Customers by plan'!S27),IF(EXACT("Team","Launch"),IF('RC Customers by plan'!S29="","",'RC Customers by plan'!S29),0)) -> 3.1589575
A22: Churned customers | B22: =SUM('RC Customers by plan'!B23,'RC Customers by plan'!B24,'RC Customers by plan'!B25) -> 0 | C22: =SUM('RC Customers by plan'!C23,'RC Customers by plan'!C24,'RC Customers by plan'!C25) -> 2.595 | D22: =SUM('RC Customers by plan'!D23,'RC Customers by plan'!D24,'RC Customers by plan'!D25) -> 4.7545 | E22: =SUM('RC Customers by plan'!E23,'RC Customers by plan'!E24,'RC Customers by plan'!E25) -> 6.1894717 | F22: =SUM('RC Customers by plan'!F23,'RC Customers by plan'!F24,'RC Customers by plan'!F25) -> 7.6767034 | G22: =SUM('RC Customers by plan'!G23,'RC Customers by plan'!G24,'RC Customers by plan'!G25) -> 9.2245838 | H22: =SUM('RC Customers by plan'!H23,'RC Customers by plan'!H24,'RC Customers by plan'!H25) -> 10.841923 | I22: =SUM('RC Customers by plan'!I23,'RC Customers by plan'!I24,'RC Customers by plan'!I25) -> 12.538007 | ... S22: =SUM('RC Customers by plan'!S23,'RC Customers by plan'!S24,'RC Customers by plan'!S25) -> 31.54581
A23: Indie | B23: =IF(IF(IF(ISERROR('RC Customers by plan'!B5<1),'RC Customers by plan'!B5<1,IF('RC Customers by plan'!B5="","",'RC Customers by plan'!B5<1))="",FALSE,IF(ISERROR('RC Customers by plan'!B5<1),'RC Customers by plan'!B5<1,IF('RC Customers by plan'!B5="","",'RC Customers by plan'!B5<1))),0,'RC Customers by plan'!B7*'Model inputs'!AG57) -> 0 | C23: =IF(IF(IF(ISERROR('RC Customers by plan'!C5<1),'RC Customers by plan'!C5<1,IF('RC Customers by plan'!C5="","",'RC Customers by plan'!C5<1))="",FALSE,IF(ISERROR('RC Customers by plan'!C5<1),'RC Customers by plan'!C5<1,IF('RC Customers by plan'!C5="","",'RC Customers by plan'!C5<1))),0,'RC Customers by plan'!C7*'Model inputs'!AG57) -> 2.4 | D23: =IF(IF(IF(ISERROR('RC Customers by plan'!D5<1),'RC Customers by plan'!D5<1,IF('RC Customers by plan'!D5="","",'RC Customers by plan'!D5<1))="",FALSE,IF(ISERROR('RC Customers by plan'!D5<1),'RC Customers by plan'!D5<1,IF('RC Customers by plan'!D5="","",'RC Customers by plan'!D5<1))),0,'RC Customers by plan'!D7*'Model inputs'!AG57) -> 4.46 | E23: =IF(IF(IF(ISERROR('RC Customers by plan'!E5<1),'RC Customers by plan'!E5<1,IF('RC Customers by plan'!E5="","",'RC Customers by plan'!E5<1))="",FALSE,IF(ISERROR('RC Customers by plan'!E5<1),'RC Customers by plan'!E5<1,IF('RC Customers by plan'!E5="","",'RC Customers by plan'!E5<1))),0,'RC Customers by plan'!E7*'Model inputs'!AG57) -> 5.7826667 | F23: =IF(IF(IF(ISERROR('RC Customers by plan'!F5<1),'RC Customers by plan'!F5<1,IF('RC Customers by plan'!F5="","",'RC Customers by plan'!F5<1))="",FALSE,IF(ISERROR('RC Customers by plan'!F5<1),'RC Customers by plan'!F5<1,IF('RC Customers by plan'!F5="","",'RC Customers by plan'!F5<1))),0,'RC Customers by plan'!F7*'Model inputs'!AG57) -> 7.1467556 | G23: =IF(IF(IF(ISERROR('RC Customers by plan'!G5<1),'RC Customers by plan'!G5<1,IF('RC Customers by plan'!G5="","",'RC Customers by plan'!G5<1))="",FALSE,IF(ISERROR('RC Customers by plan'!G5<1),'RC Customers by plan'!G5<1,IF('RC Customers by plan'!G5="","",'RC Customers by plan'!G5<1))),0,'RC Customers by plan'!G7*'Model inputs'!AG57) -> 8.5598732 | H23: =IF(IF(IF(ISERROR('RC Customers by plan'!H5<1),'RC Customers by plan'!H5<1,IF('RC Customers by plan'!H5="","",'RC Customers by plan'!H5<1))="",FALSE,IF(ISERROR('RC Customers by plan'!H5<1),'RC Customers by plan'!H5<1,IF('RC Customers by plan'!H5="","",'RC Customers by plan'!H5<1))),0,'RC Customers by plan'!H7*'Model inputs'!AG57) -> 10.029948 | I23: =IF(IF(IF(ISERROR('RC Customers by plan'!I5<1),'RC Customers by plan'!I5<1,IF('RC Customers by plan'!I5="","",'RC Customers by plan'!I5<1))="",FALSE,IF(ISERROR('RC Customers by plan'!I5<1),'RC Customers by plan'!I5<1,IF('RC Customers by plan'!I5="","",'RC Customers by plan'!I5<1))),0,'RC Customers by plan'!I7*'Model inputs'!AG57) -> 11.565277 | J23: =IF(IF(IF(ISERROR('RC Customers by plan'!J5<1),'RC Customers by plan'!J5<1,IF('RC Customers by plan'!J5="","",'RC Customers by plan'!J5<1))="",FALSE,IF(ISERROR('RC Customers by plan'!J5<1),'RC Customers by plan'!J5<1,IF('RC Customers by plan'!J5="","",'RC Customers by plan'!J5<1))),0,'RC Customers by plan'!J7*'Model inputs'!AG57) -> 13.17457 | K23: =IF(IF(IF(ISERROR('RC Customers by plan'!K5<1),'RC Customers by plan'!K5<1,IF('RC Customers by plan'!K5="","",'RC Customers by plan'!K5<1))="",FALSE,IF(ISERROR('RC Customers by plan'!K5<1),'RC Customers by plan'!K5<1,IF('RC Customers by plan'!K5="","",'RC Customers by plan'!K5<1))),0,'RC Customers by plan'!K7*'Model inputs'!AG57) -> 14.867002 | L23: =IF(IF(IF(ISERROR('RC Customers by plan'!L5<1),'RC Customers by plan'!L5<1,IF('RC Customers by plan'!L5="","",'RC Customers by plan'!L5<1))="",FALSE,IF(ISERROR('RC Customers by plan'!L5<1),'RC Customers by plan'!L5<1,IF('RC Customers by plan'!L5="","",'RC Customers by plan'!L5<1))),0,'RC Customers by plan'!L7*'Model inputs'!AG57) -> 16.549434 | M23: =IF(IF(IF(ISERROR('RC Customers by plan'!M5<1),'RC Customers by plan'!M5<1,IF('RC Customers by plan'!M5="","",'RC Customers by plan'!M5<1))="",FALSE,IF(ISERROR('RC Customers by plan'!M5<1),'RC Customers by plan'!M5<1,IF('RC Customers by plan'!M5="","",'RC Customers by plan'!M5<1))),0,'RC Customers by plan'!M7*'Model inputs'!AG57) -> 18.226647 | N23: =IF(IF(IF(ISERROR('RC Customers by plan'!N5<1),'RC Customers by plan'!N5<1,IF('RC Customers by plan'!N5="","",'RC Customers by plan'!N5<1))="",FALSE,IF(ISERROR('RC Customers by plan'!N5<1),'RC Customers by plan'!N5<1,IF('RC Customers by plan'!N5="","",'RC Customers by plan'!N5<1))),0,'RC Customers by plan'!N7*'Model inputs'!AG57) -> 19.903266 | O23: =IF(IF(IF(ISERROR('RC Customers by plan'!O5<1),'RC Customers by plan'!O5<1,IF('RC Customers by plan'!O5="","",'RC Customers by plan'!O5<1))="",FALSE,IF(ISERROR('RC Customers by plan'!O5<1),'RC Customers by plan'!O5<1,IF('RC Customers by plan'!O5="","",'RC Customers by plan'!O5<1))),0,'RC Customers by plan'!O7*'Model inputs'!AG57) -> 21.58378 | P23: =IF(IF(IF(ISERROR('RC Customers by plan'!P5<1),'RC Customers by plan'!P5<1,IF('RC Customers by plan'!P5="","",'RC Customers by plan'!P5<1))="",FALSE,IF(ISERROR('RC Customers by plan'!P5<1),'RC Customers by plan'!P5<1,IF('RC Customers by plan'!P5="","",'RC Customers by plan'!P5<1))),0,'RC Customers by plan'!P7*'Model inputs'!AG57) -> 23.272555 | Q23: =IF(IF(IF(ISERROR('RC Customers by plan'!Q5<1),'RC Customers by plan'!Q5<1,IF('RC Customers by plan'!Q5="","",'RC Customers by plan'!Q5<1))="",FALSE,IF(ISERROR('RC Customers by plan'!Q5<1),'RC Customers by plan'!Q5<1,IF('RC Customers by plan'!Q5="","",'RC Customers by plan'!Q5<1))),0,'RC Customers by plan'!Q7*'Model inputs'!AG57) -> 24.973853 | R23: =IF(IF(IF(ISERROR('RC Customers by plan'!R5<1),'RC Customers by plan'!R5<1,IF('RC Customers by plan'!R5="","",'RC Customers by plan'!R5<1))="",FALSE,IF(ISERROR('RC Customers by plan'!R5<1),'RC Customers by plan'!R5<1,IF('RC Customers by plan'!R5="","",'RC Customers by plan'!R5<1))),0,'RC Customers by plan'!R7*'Model inputs'!AG57) -> 26.691843 | S23: =IF(IF(IF(ISERROR('RC Customers by plan'!S5<1),'RC Customers by plan'!S5<1,IF('RC Customers by plan'!S5="","",'RC Customers by plan'!S5<1))="",FALSE,IF(ISERROR('RC Customers by plan'!S5<1),'RC Customers by plan'!S5<1,IF('RC Customers by plan'!S5="","",'RC Customers by plan'!S5<1))),0,'RC Customers by plan'!S7*'Model inputs'!AG57) -> 28.430617
A24: Launch | B24: =IF(IF(IF(ISERROR('RC Customers by plan'!B5<1),'RC Customers by plan'!B5<1,IF('RC Customers by plan'!B5="","",'RC Customers by plan'!B5<1))="",FALSE,IF(ISERROR('RC Customers by plan'!B5<1),'RC Customers by plan'!B5<1,IF('RC Customers by plan'!B5="","",'RC Customers by plan'!B5<1))),0,'RC Customers by plan'!B8*'Model inputs'!AG58) -> 0 | C24: =IF(IF(IF(ISERROR('RC Customers by plan'!C5<1),'RC Customers by plan'!C5<1,IF('RC Customers by plan'!C5="","",'RC Customers by plan'!C5<1))="",FALSE,IF(ISERROR('RC Customers by plan'!C5<1),'RC Customers by plan'!C5<1,IF('RC Customers by plan'!C5="","",'RC Customers by plan'!C5<1))),0,'RC Customers by plan'!C8*'Model inputs'!AG58) -> 0.015 | D24: =IF(IF(IF(ISERROR('RC Customers by plan'!D5<1),'RC Customers by plan'!D5<1,IF('RC Customers by plan'!D5="","",'RC Customers by plan'!D5<1))="",FALSE,IF(ISERROR('RC Customers by plan'!D5<1),'RC Customers by plan'!D5<1,IF('RC Customers by plan'!D5="","",'RC Customers by plan'!D5<1))),0,'RC Customers by plan'!D8*'Model inputs'!AG58) -> 0.02265 | E24: =IF(IF(IF(ISERROR('RC Customers by plan'!E5<1),'RC Customers by plan'!E5<1,IF('RC Customers by plan'!E5="","",'RC Customers by plan'!E5<1))="",FALSE,IF(ISERROR('RC Customers by plan'!E5<1),'RC Customers by plan'!E5<1,IF('RC Customers by plan'!E5="","",'RC Customers by plan'!E5<1))),0,'RC Customers by plan'!E8*'Model inputs'!AG58) -> 0.030376604 | F24: =IF(IF(IF(ISERROR('RC Customers by plan'!F5<1),'RC Customers by plan'!F5<1,IF('RC Customers by plan'!F5="","",'RC Customers by plan'!F5<1))="",FALSE,IF(ISERROR('RC Customers by plan'!F5<1),'RC Customers by plan'!F5<1,IF('RC Customers by plan'!F5="","",'RC Customers by plan'!F5<1))),0,'RC Customers by plan'!F8*'Model inputs'!AG58) -> 0.038205181 | G24: =IF(IF(IF(ISERROR('RC Customers by plan'!G5<1),'RC Customers by plan'!G5<1,IF('RC Customers by plan'!G5="","",'RC Customers by plan'!G5<1))="",FALSE,IF(ISERROR('RC Customers by plan'!G5<1),'RC Customers by plan'!G5<1,IF('RC Customers by plan'!G5="","",'RC Customers by plan'!G5<1))),0,'RC Customers by plan'!G8*'Model inputs'!AG58) -> 0.046156567 | H24: =IF(IF(IF(ISERROR('RC Customers by plan'!H5<1),'RC Customers by plan'!H5<1,IF('RC Customers by plan'!H5="","",'RC Customers by plan'!H5<1))="",FALSE,IF(ISERROR('RC Customers by plan'!H5<1),'RC Customers by plan'!H5<1,IF('RC Customers by plan'!H5="","",'RC Customers by plan'!H5<1))),0,'RC Customers by plan'!H8*'Model inputs'!AG58) -> 0.054252873 | I24: =IF(IF(IF(ISERROR('RC Customers by plan'!I5<1),'RC Customers by plan'!I5<1,IF('RC Customers by plan'!I5="","",'RC Customers by plan'!I5<1))="",FALSE,IF(ISERROR('RC Customers by plan'!I5<1),'RC Customers by plan'!I5<1,IF('RC Customers by plan'!I5="","",'RC Customers by plan'!I5<1))),0,'RC Customers by plan'!I8*'Model inputs'!AG58) -> 0.062517667 | J24: =IF(IF(IF(ISERROR('RC Customers by plan'!J5<1),'RC Customers by plan'!J5<1,IF('RC Customers by plan'!J5="","",'RC Customers by plan'!J5<1))="",FALSE,IF(ISERROR('RC Customers by plan'!J5<1),'RC Customers by plan'!J5<1,IF('RC Customers by plan'!J5="","",'RC Customers by plan'!J5<1))),0,'RC Customers by plan'!J8*'Model inputs'!AG58) -> 0.070976178 | K24: =IF(IF(IF(ISERROR('RC Customers by plan'!K5<1),'RC Customers by plan'!K5<1,IF('RC Customers by plan'!K5="","",'RC Customers by plan'!K5<1))="",FALSE,IF(ISERROR('RC Customers by plan'!K5<1),'RC Customers by plan'!K5<1,IF('RC Customers by plan'!K5="","",'RC Customers by plan'!K5<1))),0,'RC Customers by plan'!K8*'Model inputs'!AG58) -> 0.079655503 | L24: =IF(IF(IF(ISERROR('RC Customers by plan'!L5<1),'RC Customers by plan'!L5<1,IF('RC Customers by plan'!L5="","",'RC Customers by plan'!L5<1))="",FALSE,IF(ISERROR('RC Customers by plan'!L5<1),'RC Customers by plan'!L5<1,IF('RC Customers by plan'!L5="","",'RC Customers by plan'!L5<1))),0,'RC Customers by plan'!L8*'Model inputs'!AG58) -> 0.088584845 | M24: =IF(IF(IF(ISERROR('RC Customers by plan'!M5<1),'RC Customers by plan'!M5<1,IF('RC Customers by plan'!M5="","",'RC Customers by plan'!M5<1))="",FALSE,IF(ISERROR('RC Customers by plan'!M5<1),'RC Customers by plan'!M5<1,IF('RC Customers by plan'!M5="","",'RC Customers by plan'!M5<1))),0,'RC Customers by plan'!M8*'Model inputs'!AG58) -> 0.097773829 | N24: =IF(IF(IF(ISERROR('RC Customers by plan'!N5<1),'RC Customers by plan'!N5<1,IF('RC Customers by plan'!N5="","",'RC Customers by plan'!N5<1))="",FALSE,IF(ISERROR('RC Customers by plan'!N5<1),'RC Customers by plan'!N5<1,IF('RC Customers by plan'!N5="","",'RC Customers by plan'!N5<1))),0,'RC Customers by plan'!N8*'Model inputs'!AG58) -> 0.107232 | O24: =IF(IF(IF(ISERROR('RC Customers by plan'!O5<1),'RC Customers by plan'!O5<1,IF('RC Customers by plan'!O5="","",'RC Customers by plan'!O5<1))="",FALSE,IF(ISERROR('RC Customers by plan'!O5<1),'RC Customers by plan'!O5<1,IF('RC Customers by plan'!O5="","",'RC Customers by plan'!O5<1))),0,'RC Customers by plan'!O8*'Model inputs'!AG58) -> 0.11696886 | P24: =IF(IF(IF(ISERROR('RC Customers by plan'!P5<1),'RC Customers by plan'!P5<1,IF('RC Customers by plan'!P5="","",'RC Customers by plan'!P5<1))="",FALSE,IF(ISERROR('RC Customers by plan'!P5<1),'RC Customers by plan'!P5<1,IF('RC Customers by plan'!P5="","",'RC Customers by plan'!P5<1))),0,'RC Customers by plan'!P8*'Model inputs'!AG58) -> 0.12699396 | Q24: =IF(IF(IF(ISERROR('RC Customers by plan'!Q5<1),'RC Customers by plan'!Q5<1,IF('RC Customers by plan'!Q5="","",'RC Customers by plan'!Q5<1))="",FALSE,IF(ISERROR('RC Customers by plan'!Q5<1),'RC Customers by plan'!Q5<1,IF('RC Customers by plan'!Q5="","",'RC Customers by plan'!Q5<1))),0,'RC Customers by plan'!Q8*'Model inputs'!AG58) -> 0.13731689 | R24: =IF(IF(IF(ISERROR('RC Customers by plan'!R5<1),'RC Customers by plan'!R5<1,IF('RC Customers by plan'!R5="","",'RC Customers by plan'!R5<1))="",FALSE,IF(ISERROR('RC Customers by plan'!R5<1),'RC Customers by plan'!R5<1,IF('RC Customers by plan'!R5="","",'RC Customers by plan'!R5<1))),0,'RC Customers by plan'!R8*'Model inputs'!AG58) -> 0.14794739 | S24: =IF(IF(IF(ISERROR('RC Customers by plan'!S5<1),'RC Customers by plan'!S5<1,IF('RC Customers by plan'!S5="","",'RC Customers by plan'!S5<1))="",FALSE,IF(ISERROR('RC Customers by plan'!S5<1),'RC Customers by plan'!S5<1,IF('RC Customers by plan'!S5="","",'RC Customers by plan'!S5<1))),0,'RC Customers by plan'!S8*'Model inputs'!AG58) -> 0.15889534
A25: Team | B25: =IF(IF(IF(ISERROR('RC Customers by plan'!B5<1),'RC Customers by plan'!B5<1,IF('RC Customers by plan'!B5="","",'RC Customers by plan'!B5<1))="",FALSE,IF(ISERROR('RC Customers by plan'!B5<1),'RC Customers by plan'!B5<1,IF('RC Customers by plan'!B5="","",'RC Customers by plan'!B5<1))),0,'RC Customers by plan'!B9*'Model inputs'!AG59) -> 0 | C25: =IF(IF(IF(ISERROR('RC Customers by plan'!C5<1),'RC Customers by plan'!C5<1,IF('RC Customers by plan'!C5="","",'RC Customers by plan'!C5<1))="",FALSE,IF(ISERROR('RC Customers by plan'!C5<1),'RC Customers by plan'!C5<1,IF('RC Customers by plan'!C5="","",'RC Customers by plan'!C5<1))),0,'RC Customers by plan'!C9*'Model inputs'!AG59) -> 0.18 | D25: =IF(IF(IF(ISERROR('RC Customers by plan'!D5<1),'RC Customers by plan'!D5<1,IF('RC Customers by plan'!D5="","",'RC Customers by plan'!D5<1))="",FALSE,IF(ISERROR('RC Customers by plan'!D5<1),'RC Customers by plan'!D5<1,IF('RC Customers by plan'!D5="","",'RC Customers by plan'!D5<1))),0,'RC Customers by plan'!D9*'Model inputs'!AG59) -> 0.27185 | E25: =IF(IF(IF(ISERROR('RC Customers by plan'!E5<1),'RC Customers by plan'!E5<1,IF('RC Customers by plan'!E5="","",'RC Customers by plan'!E5<1))="",FALSE,IF(ISERROR('RC Customers by plan'!E5<1),'RC Customers by plan'!E5<1,IF('RC Customers by plan'!E5="","",'RC Customers by plan'!E5<1))),0,'RC Customers by plan'!E9*'Model inputs'!AG59) -> 0.37642846 | F25: =IF(IF(IF(ISERROR('RC Customers by plan'!F5<1),'RC Customers by plan'!F5<1,IF('RC Customers by plan'!F5="","",'RC Customers by plan'!F5<1))="",FALSE,IF(ISERROR('RC Customers by plan'!F5<1),'RC Customers by plan'!F5<1,IF('RC Customers by plan'!F5="","",'RC Customers by plan'!F5<1))),0,'RC Customers by plan'!F9*'Model inputs'!AG59) -> 0.49174271 | G25: =IF(IF(IF(ISERROR('RC Customers by plan'!G5<1),'RC Customers by plan'!G5<1,IF('RC Customers by plan'!G5="","",'RC Customers by plan'!G5<1))="",FALSE,IF(ISERROR('RC Customers by plan'!G5<1),'RC Customers by plan'!G5<1,IF('RC Customers by plan'!G5="","",'RC Customers by plan'!G5<1))),0,'RC Customers by plan'!G9*'Model inputs'!AG59) -> 0.61855402 | H25: =IF(IF(IF(ISERROR('RC Customers by plan'!H5<1),'RC Customers by plan'!H5<1,IF('RC Customers by plan'!H5="","",'RC Customers by plan'!H5<1))="",FALSE,IF(ISERROR('RC Customers by plan'!H5<1),'RC Customers by plan'!H5<1,IF('RC Customers by plan'!H5="","",'RC Customers by plan'!H5<1))),0,'RC Customers by plan'!H9*'Model inputs'!AG59) -> 0.757722 | I25: =IF(IF(IF(ISERROR('RC Customers by plan'!I5<1),'RC Customers by plan'!I5<1,IF('RC Customers by plan'!I5="","",'RC Customers by plan'!I5<1))="",FALSE,IF(ISERROR('RC Customers by plan'!I5<1),'RC Customers by plan'!I5<1,IF('RC Customers by plan'!I5="","",'RC Customers by plan'!I5<1))),0,'RC Customers by plan'!I9*'Model inputs'!AG59) -> 0.91021223 | J25: =IF(IF(IF(ISERROR('RC Customers by plan'!J5<1),'RC Customers by plan'!J5<1,IF('RC Customers by plan'!J5="","",'RC Customers by plan'!J5<1))="",FALSE,IF(ISERROR('RC Customers by plan'!J5<1),'RC Customers by plan'!J5<1,IF('RC Customers by plan'!J5="","",'RC Customers by plan'!J5<1))),0,'RC Customers by plan'!J9*'Model inputs'!AG59) -> 1.0771047 | K25: =IF(IF(IF(ISERROR('RC Customers by plan'!K5<1),'RC Customers by plan'!K5<1,IF('RC Customers by plan'!K5="","",'RC Customers by plan'!K5<1))="",FALSE,IF(ISERROR('RC Customers by plan'!K5<1),'RC Customers by plan'!K5<1,IF('RC Customers by plan'!K5="","",'RC Customers by plan'!K5<1))),0,'RC Customers by plan'!K9*'Model inputs'!AG59) -> 1.2596034 | L25: =IF(IF(IF(ISERROR('RC Customers by plan'!L5<1),'RC Customers by plan'!L5<1,IF('RC Customers by plan'!L5="","",'RC Customers by plan'!L5<1))="",FALSE,IF(ISERROR('RC Customers by plan'!L5<1),'RC Customers by plan'!L5<1,IF('RC Customers by plan'!L5="","",'RC Customers by plan'!L5<1))),0,'RC Customers by plan'!L9*'Model inputs'!AG59) -> 1.4485236 | M25: =IF(IF(IF(ISERROR('RC Customers by plan'!M5<1),'RC Customers by plan'!M5<1,IF('RC Customers by plan'!M5="","",'RC Customers by plan'!M5<1))="",FALSE,IF(ISERROR('RC Customers by plan'!M5<1),'RC Customers by plan'!M5<1,IF('RC Customers by plan'!M5="","",'RC Customers by plan'!M5<1))),0,'RC Customers by plan'!M9*'Model inputs'!AG59) -> 1.643893 | N25: =IF(IF(IF(ISERROR('RC Customers by plan'!N5<1),'RC Customers by plan'!N5<1,IF('RC Customers by plan'!N5="","",'RC Customers by plan'!N5<1))="",FALSE,IF(ISERROR('RC Customers by plan'!N5<1),'RC Customers by plan'!N5<1,IF('RC Customers by plan'!N5="","",'RC Customers by plan'!N5<1))),0,'RC Customers by plan'!N9*'Model inputs'!AG59) -> 1.8457659 | O25: =IF(IF(IF(ISERROR('RC Customers by plan'!O5<1),'RC Customers by plan'!O5<1,IF('RC Customers by plan'!O5="","",'RC Customers by plan'!O5<1))="",FALSE,IF(ISERROR('RC Customers by plan'!O5<1),'RC Customers by plan'!O5<1,IF('RC Customers by plan'!O5="","",'RC Customers by plan'!O5<1))),0,'RC Customers by plan'!O9*'Model inputs'!AG59) -> 2.0542216 | P25: =IF(IF(IF(ISERROR('RC Customers by plan'!P5<1),'RC Customers by plan'!P5<1,IF('RC Customers by plan'!P5="","",'RC Customers by plan'!P5<1))="",FALSE,IF(ISERROR('RC Customers by plan'!P5<1),'RC Customers by plan'!P5<1,IF('RC Customers by plan'!P5="","",'RC Customers by plan'!P5<1))),0,'RC Customers by plan'!P9*'Model inputs'!AG59) -> 2.2693637 | Q25: =IF(IF(IF(ISERROR('RC Customers by plan'!Q5<1),'RC Customers by plan'!Q5<1,IF('RC Customers by plan'!Q5="","",'RC Customers by plan'!Q5<1))="",FALSE,IF(ISERROR('RC Customers by plan'!Q5<1),'RC Customers by plan'!Q5<1,IF('RC Customers by plan'!Q5="","",'RC Customers by plan'!Q5<1))),0,'RC Customers by plan'!Q9*'Model inputs'!AG59) -> 2.4913197 | R25: =IF(IF(IF(ISERROR('RC Customers by plan'!R5<1),'RC Customers by plan'!R5<1,IF('RC Customers by plan'!R5="","",'RC Customers by plan'!R5<1))="",FALSE,IF(ISERROR('RC Customers by plan'!R5<1),'RC Customers by plan'!R5<1,IF('RC Customers by plan'!R5="","",'RC Customers by plan'!R5<1))),0,'RC Customers by plan'!R9*'Model inputs'!AG59) -> 2.7202399 | S25: =IF(IF(IF(ISERROR('RC Customers by plan'!S5<1),'RC Customers by plan'!S5<1,IF('RC Customers by plan'!S5="","",'RC Customers by plan'!S5<1))="",FALSE,IF(ISERROR('RC Customers by plan'!S5<1),'RC Customers by plan'!S5<1,IF('RC Customers by plan'!S5="","",'RC Customers by plan'!S5<1))),0,'RC Customers by plan'!S9*'Model inputs'!AG59) -> 2.956297
A26: Upgrades out | B26: =SUM('RC Customers by plan'!B27,'RC Customers by plan'!B28,'RC Customers by plan'!B29) -> 0 | C26: =SUM('RC Customers by plan'!C27,'RC Customers by plan'!C28,'RC Customers by plan'!C29) -> 0.29166667 | D26: =SUM('RC Customers by plan'!D27,'RC Customers by plan'!D28,'RC Customers by plan'!D29) -> 0.5333125 | E26: =SUM('RC Customers by plan'!E27,'RC Customers by plan'!E28,'RC Customers by plan'!E29) -> 0.69480025 | F26: =SUM('RC Customers by plan'!F27,'RC Customers by plan'!F28,'RC Customers by plan'!F29) -> 0.86238155 | G26: =SUM('RC Customers by plan'!G27,'RC Customers by plan'!G28,'RC Customers by plan'!G29) -> 1.0370073 | H26: =SUM('RC Customers by plan'!H27,'RC Customers by plan'!H28,'RC Customers by plan'!H29) -> 1.2196779 | I26: =SUM('RC Customers by plan'!I27,'RC Customers by plan'!I28,'RC Customers by plan'!I29) -> 1.4114492 | ... S26: =SUM('RC Customers by plan'!S27,'RC Customers by plan'!S28,'RC Customers by plan'!S29) -> 3.5695543
A27: Indie | B27: =IF(IF(IF(ISERROR('RC Customers by plan'!B5<1),'RC Customers by plan'!B5<1,IF('RC Customers by plan'!B5="","",'RC Customers by plan'!B5<1))="",FALSE,IF(ISERROR('RC Customers by plan'!B5<1),'RC Customers by plan'!B5<1,IF('RC Customers by plan'!B5="","",'RC Customers by plan'!B5<1))),0,'RC Customers by plan'!B7*'Model inputs'!AG19/12) -> 0 | C27: =IF(IF(IF(ISERROR('RC Customers by plan'!C5<1),'RC Customers by plan'!C5<1,IF('RC Customers by plan'!C5="","",'RC Customers by plan'!C5<1))="",FALSE,IF(ISERROR('RC Customers by plan'!C5<1),'RC Customers by plan'!C5<1,IF('RC Customers by plan'!C5="","",'RC Customers by plan'!C5<1))),0,'RC Customers by plan'!C7*'Model inputs'!AG19/12) -> 0.26666667 | D27: =IF(IF(IF(ISERROR('RC Customers by plan'!D5<1),'RC Customers by plan'!D5<1,IF('RC Customers by plan'!D5="","",'RC Customers by plan'!D5<1))="",FALSE,IF(ISERROR('RC Customers by plan'!D5<1),'RC Customers by plan'!D5<1,IF('RC Customers by plan'!D5="","",'RC Customers by plan'!D5<1))),0,'RC Customers by plan'!D7*'Model inputs'!AG19/12) -> 0.49555556 | E27: =IF(IF(IF(ISERROR('RC Customers by plan'!E5<1),'RC Customers by plan'!E5<1,IF('RC Customers by plan'!E5="","",'RC Customers by plan'!E5<1))="",FALSE,IF(ISERROR('RC Customers by plan'!E5<1),'RC Customers by plan'!E5<1,IF('RC Customers by plan'!E5="","",'RC Customers by plan'!E5<1))),0,'RC Customers by plan'!E7*'Model inputs'!AG19/12) -> 0.64251852 | F27: =IF(IF(IF(ISERROR('RC Customers by plan'!F5<1),'RC Customers by plan'!F5<1,IF('RC Customers by plan'!F5="","",'RC Customers by plan'!F5<1))="",FALSE,IF(ISERROR('RC Customers by plan'!F5<1),'RC Customers by plan'!F5<1,IF('RC Customers by plan'!F5="","",'RC Customers by plan'!F5<1))),0,'RC Customers by plan'!F7*'Model inputs'!AG19/12) -> 0.79408395 | G27: =IF(IF(IF(ISERROR('RC Customers by plan'!G5<1),'RC Customers by plan'!G5<1,IF('RC Customers by plan'!G5="","",'RC Customers by plan'!G5<1))="",FALSE,IF(ISERROR('RC Customers by plan'!G5<1),'RC Customers by plan'!G5<1,IF('RC Customers by plan'!G5="","",'RC Customers by plan'!G5<1))),0,'RC Customers by plan'!G7*'Model inputs'!AG19/12) -> 0.95109702 | H27: =IF(IF(IF(ISERROR('RC Customers by plan'!H5<1),'RC Customers by plan'!H5<1,IF('RC Customers by plan'!H5="","",'RC Customers by plan'!H5<1))="",FALSE,IF(ISERROR('RC Customers by plan'!H5<1),'RC Customers by plan'!H5<1,IF('RC Customers by plan'!H5="","",'RC Customers by plan'!H5<1))),0,'RC Customers by plan'!H7*'Model inputs'!AG19/12) -> 1.1144387 | I27: =IF(IF(IF(ISERROR('RC Customers by plan'!I5<1),'RC Customers by plan'!I5<1,IF('RC Customers by plan'!I5="","",'RC Customers by plan'!I5<1))="",FALSE,IF(ISERROR('RC Customers by plan'!I5<1),'RC Customers by plan'!I5<1,IF('RC Customers by plan'!I5="","",'RC Customers by plan'!I5<1))),0,'RC Customers by plan'!I7*'Model inputs'!AG19/12) -> 1.2850308 | J27: =IF(IF(IF(ISERROR('RC Customers by plan'!J5<1),'RC Customers by plan'!J5<1,IF('RC Customers by plan'!J5="","",'RC Customers by plan'!J5<1))="",FALSE,IF(ISERROR('RC Customers by plan'!J5<1),'RC Customers by plan'!J5<1,IF('RC Customers by plan'!J5="","",'RC Customers by plan'!J5<1))),0,'RC Customers by plan'!J7*'Model inputs'!AG19/12) -> 1.4638411 | K27: =IF(IF(IF(ISERROR('RC Customers by plan'!K5<1),'RC Customers by plan'!K5<1,IF('RC Customers by plan'!K5="","",'RC Customers by plan'!K5<1))="",FALSE,IF(ISERROR('RC Customers by plan'!K5<1),'RC Customers by plan'!K5<1,IF('RC Customers by plan'!K5="","",'RC Customers by plan'!K5<1))),0,'RC Customers by plan'!K7*'Model inputs'!AG19/12) -> 1.6518891 | L27: =IF(IF(IF(ISERROR('RC Customers by plan'!L5<1),'RC Customers by plan'!L5<1,IF('RC Customers by plan'!L5="","",'RC Customers by plan'!L5<1))="",FALSE,IF(ISERROR('RC Customers by plan'!L5<1),'RC Customers by plan'!L5<1,IF('RC Customers by plan'!L5="","",'RC Customers by plan'!L5<1))),0,'RC Customers by plan'!L7*'Model inputs'!AG19/12) -> 1.838826 | M27: =IF(IF(IF(ISERROR('RC Customers by plan'!M5<1),'RC Customers by plan'!M5<1,IF('RC Customers by plan'!M5="","",'RC Customers by plan'!M5<1))="",FALSE,IF(ISERROR('RC Customers by plan'!M5<1),'RC Customers by plan'!M5<1,IF('RC Customers by plan'!M5="","",'RC Customers by plan'!M5<1))),0,'RC Customers by plan'!M7*'Model inputs'!AG19/12) -> 2.025183 | N27: =IF(IF(IF(ISERROR('RC Customers by plan'!N5<1),'RC Customers by plan'!N5<1,IF('RC Customers by plan'!N5="","",'RC Customers by plan'!N5<1))="",FALSE,IF(ISERROR('RC Customers by plan'!N5<1),'RC Customers by plan'!N5<1,IF('RC Customers by plan'!N5="","",'RC Customers by plan'!N5<1))),0,'RC Customers by plan'!N7*'Model inputs'!AG19/12) -> 2.211474 | O27: =IF(IF(IF(ISERROR('RC Customers by plan'!O5<1),'RC Customers by plan'!O5<1,IF('RC Customers by plan'!O5="","",'RC Customers by plan'!O5<1))="",FALSE,IF(ISERROR('RC Customers by plan'!O5<1),'RC Customers by plan'!O5<1,IF('RC Customers by plan'!O5="","",'RC Customers by plan'!O5<1))),0,'RC Customers by plan'!O7*'Model inputs'!AG19/12) -> 2.3981978 | P27: =IF(IF(IF(ISERROR('RC Customers by plan'!P5<1),'RC Customers by plan'!P5<1,IF('RC Customers by plan'!P5="","",'RC Customers by plan'!P5<1))="",FALSE,IF(ISERROR('RC Customers by plan'!P5<1),'RC Customers by plan'!P5<1,IF('RC Customers by plan'!P5="","",'RC Customers by plan'!P5<1))),0,'RC Customers by plan'!P7*'Model inputs'!AG19/12) -> 2.5858395 | Q27: =IF(IF(IF(ISERROR('RC Customers by plan'!Q5<1),'RC Customers by plan'!Q5<1,IF('RC Customers by plan'!Q5="","",'RC Customers by plan'!Q5<1))="",FALSE,IF(ISERROR('RC Customers by plan'!Q5<1),'RC Customers by plan'!Q5<1,IF('RC Customers by plan'!Q5="","",'RC Customers by plan'!Q5<1))),0,'RC Customers by plan'!Q7*'Model inputs'!AG19/12) -> 2.7748726 | R27: =IF(IF(IF(ISERROR('RC Customers by plan'!R5<1),'RC Customers by plan'!R5<1,IF('RC Customers by plan'!R5="","",'RC Customers by plan'!R5<1))="",FALSE,IF(ISERROR('RC Customers by plan'!R5<1),'RC Customers by plan'!R5<1,IF('RC Customers by plan'!R5="","",'RC Customers by plan'!R5<1))),0,'RC Customers by plan'!R7*'Model inputs'!AG19/12) -> 2.9657604 | S27: =IF(IF(IF(ISERROR('RC Customers by plan'!S5<1),'RC Customers by plan'!S5<1,IF('RC Customers by plan'!S5="","",'RC Customers by plan'!S5<1))="",FALSE,IF(ISERROR('RC Customers by plan'!S5<1),'RC Customers by plan'!S5<1,IF('RC Customers by plan'!S5="","",'RC Customers by plan'!S5<1))),0,'RC Customers by plan'!S7*'Model inputs'!AG19/12) -> 3.1589575
A28: Launch | B28: =IF(IF(IF(ISERROR('RC Customers by plan'!B5<1),'RC Customers by plan'!B5<1,IF('RC Customers by plan'!B5="","",'RC Customers by plan'!B5<1))="",FALSE,IF(ISERROR('RC Customers by plan'!B5<1),'RC Customers by plan'!B5<1,IF('RC Customers by plan'!B5="","",'RC Customers by plan'!B5<1))),0,'RC Customers by plan'!B8*'Model inputs'!AG20/12) -> 0 | C28: =IF(IF(IF(ISERROR('RC Customers by plan'!C5<1),'RC Customers by plan'!C5<1,IF('RC Customers by plan'!C5="","",'RC Customers by plan'!C5<1))="",FALSE,IF(ISERROR('RC Customers by plan'!C5<1),'RC Customers by plan'!C5<1,IF('RC Customers by plan'!C5="","",'RC Customers by plan'!C5<1))),0,'RC Customers by plan'!C8*'Model inputs'!AG20/12) -> 0 | D28: =IF(IF(IF(ISERROR('RC Customers by plan'!D5<1),'RC Customers by plan'!D5<1,IF('RC Customers by plan'!D5="","",'RC Customers by plan'!D5<1))="",FALSE,IF(ISERROR('RC Customers by plan'!D5<1),'RC Customers by plan'!D5<1,IF('RC Customers by plan'!D5="","",'RC Customers by plan'!D5<1))),0,'RC Customers by plan'!D8*'Model inputs'!AG20/12) -> 0 | E28: =IF(IF(IF(ISERROR('RC Customers by plan'!E5<1),'RC Customers by plan'!E5<1,IF('RC Customers by plan'!E5="","",'RC Customers by plan'!E5<1))="",FALSE,IF(ISERROR('RC Customers by plan'!E5<1),'RC Customers by plan'!E5<1,IF('RC Customers by plan'!E5="","",'RC Customers by plan'!E5<1))),0,'RC Customers by plan'!E8*'Model inputs'!AG20/12) -> 0 | F28: =IF(IF(IF(ISERROR('RC Customers by plan'!F5<1),'RC Customers by plan'!F5<1,IF('RC Customers by plan'!F5="","",'RC Customers by plan'!F5<1))="",FALSE,IF(ISERROR('RC Customers by plan'!F5<1),'RC Customers by plan'!F5<1,IF('RC Customers by plan'!F5="","",'RC Customers by plan'!F5<1))),0,'RC Customers by plan'!F8*'Model inputs'!AG20/12) -> 0 | G28: =IF(IF(IF(ISERROR('RC Customers by plan'!G5<1),'RC Customers by plan'!G5<1,IF('RC Customers by plan'!G5="","",'RC Customers by plan'!G5<1))="",FALSE,IF(ISERROR('RC Customers by plan'!G5<1),'RC Customers by plan'!G5<1,IF('RC Customers by plan'!G5="","",'RC Customers by plan'!G5<1))),0,'RC Customers by plan'!G8*'Model inputs'!AG20/12) -> 0 | H28: =IF(IF(IF(ISERROR('RC Customers by plan'!H5<1),'RC Customers by plan'!H5<1,IF('RC Customers by plan'!H5="","",'RC Customers by plan'!H5<1))="",FALSE,IF(ISERROR('RC Customers by plan'!H5<1),'RC Customers by plan'!H5<1,IF('RC Customers by plan'!H5="","",'RC Customers by plan'!H5<1))),0,'RC Customers by plan'!H8*'Model inputs'!AG20/12) -> 0 | I28: =IF(IF(IF(ISERROR('RC Customers by plan'!I5<1),'RC Customers by plan'!I5<1,IF('RC Customers by plan'!I5="","",'RC Customers by plan'!I5<1))="",FALSE,IF(ISERROR('RC Customers by plan'!I5<1),'RC Customers by plan'!I5<1,IF('RC Customers by plan'!I5="","",'RC Customers by plan'!I5<1))),0,'RC Customers by plan'!I8*'Model inputs'!AG20/12) -> 0 | J28: =IF(IF(IF(ISERROR('RC Customers by plan'!J5<1),'RC Customers by plan'!J5<1,IF('RC Customers by plan'!J5="","",'RC Customers by plan'!J5<1))="",FALSE,IF(ISERROR('RC Customers by plan'!J5<1),'RC Customers by plan'!J5<1,IF('RC Customers by plan'!J5="","",'RC Customers by plan'!J5<1))),0,'RC Customers by plan'!J8*'Model inputs'!AG20/12) -> 0 | K28: =IF(IF(IF(ISERROR('RC Customers by plan'!K5<1),'RC Customers by plan'!K5<1,IF('RC Customers by plan'!K5="","",'RC Customers by plan'!K5<1))="",FALSE,IF(ISERROR('RC Customers by plan'!K5<1),'RC Customers by plan'!K5<1,IF('RC Customers by plan'!K5="","",'RC Customers by plan'!K5<1))),0,'RC Customers by plan'!K8*'Model inputs'!AG20/12) -> 0 | L28: =IF(IF(IF(ISERROR('RC Customers by plan'!L5<1),'RC Customers by plan'!L5<1,IF('RC Customers by plan'!L5="","",'RC Customers by plan'!L5<1))="",FALSE,IF(ISERROR('RC Customers by plan'!L5<1),'RC Customers by plan'!L5<1,IF('RC Customers by plan'!L5="","",'RC Customers by plan'!L5<1))),0,'RC Customers by plan'!L8*'Model inputs'!AG20/12) -> 0 | M28: =IF(IF(IF(ISERROR('RC Customers by plan'!M5<1),'RC Customers by plan'!M5<1,IF('RC Customers by plan'!M5="","",'RC Customers by plan'!M5<1))="",FALSE,IF(ISERROR('RC Customers by plan'!M5<1),'RC Customers by plan'!M5<1,IF('RC Customers by plan'!M5="","",'RC Customers by plan'!M5<1))),0,'RC Customers by plan'!M8*'Model inputs'!AG20/12) -> 0 | N28: =IF(IF(IF(ISERROR('RC Customers by plan'!N5<1),'RC Customers by plan'!N5<1,IF('RC Customers by plan'!N5="","",'RC Customers by plan'!N5<1))="",FALSE,IF(ISERROR('RC Customers by plan'!N5<1),'RC Customers by plan'!N5<1,IF('RC Customers by plan'!N5="","",'RC Customers by plan'!N5<1))),0,'RC Customers by plan'!N8*'Model inputs'!AG20/12) -> 0 | O28: =IF(IF(IF(ISERROR('RC Customers by plan'!O5<1),'RC Customers by plan'!O5<1,IF('RC Customers by plan'!O5="","",'RC Customers by plan'!O5<1))="",FALSE,IF(ISERROR('RC Customers by plan'!O5<1),'RC Customers by plan'!O5<1,IF('RC Customers by plan'!O5="","",'RC Customers by plan'!O5<1))),0,'RC Customers by plan'!O8*'Model inputs'!AG20/12) -> 0 | P28: =IF(IF(IF(ISERROR('RC Customers by plan'!P5<1),'RC Customers by plan'!P5<1,IF('RC Customers by plan'!P5="","",'RC Customers by plan'!P5<1))="",FALSE,IF(ISERROR('RC Customers by plan'!P5<1),'RC Customers by plan'!P5<1,IF('RC Customers by plan'!P5="","",'RC Customers by plan'!P5<1))),0,'RC Customers by plan'!P8*'Model inputs'!AG20/12) -> 0 | Q28: =IF(IF(IF(ISERROR('RC Customers by plan'!Q5<1),'RC Customers by plan'!Q5<1,IF('RC Customers by plan'!Q5="","",'RC Customers by plan'!Q5<1))="",FALSE,IF(ISERROR('RC Customers by plan'!Q5<1),'RC Customers by plan'!Q5<1,IF('RC Customers by plan'!Q5="","",'RC Customers by plan'!Q5<1))),0,'RC Customers by plan'!Q8*'Model inputs'!AG20/12) -> 0 | R28: =IF(IF(IF(ISERROR('RC Customers by plan'!R5<1),'RC Customers by plan'!R5<1,IF('RC Customers by plan'!R5="","",'RC Customers by plan'!R5<1))="",FALSE,IF(ISERROR('RC Customers by plan'!R5<1),'RC Customers by plan'!R5<1,IF('RC Customers by plan'!R5="","",'RC Customers by plan'!R5<1))),0,'RC Customers by plan'!R8*'Model inputs'!AG20/12) -> 0 | S28: =IF(IF(IF(ISERROR('RC Customers by plan'!S5<1),'RC Customers by plan'!S5<1,IF('RC Customers by plan'!S5="","",'RC Customers by plan'!S5<1))="",FALSE,IF(ISERROR('RC Customers by plan'!S5<1),'RC Customers by plan'!S5<1,IF('RC Customers by plan'!S5="","",'RC Customers by plan'!S5<1))),0,'RC Customers by plan'!S8*'Model inputs'!AG20/12) -> 0
A29: Team | B29: =IF(IF(IF(ISERROR('RC Customers by plan'!B5<1),'RC Customers by plan'!B5<1,IF('RC Customers by plan'!B5="","",'RC Customers by plan'!B5<1))="",FALSE,IF(ISERROR('RC Customers by plan'!B5<1),'RC Customers by plan'!B5<1,IF('RC Customers by plan'!B5="","",'RC Customers by plan'!B5<1))),0,'RC Customers by plan'!B9*'Model inputs'!AG21/12) -> 0 | C29: =IF(IF(IF(ISERROR('RC Customers by plan'!C5<1),'RC Customers by plan'!C5<1,IF('RC Customers by plan'!C5="","",'RC Customers by plan'!C5<1))="",FALSE,IF(ISERROR('RC Customers by plan'!C5<1),'RC Customers by plan'!C5<1,IF('RC Customers by plan'!C5="","",'RC Customers by plan'!C5<1))),0,'RC Customers by plan'!C9*'Model inputs'!AG21/12) -> 0.025 | D29: =IF(IF(IF(ISERROR('RC Customers by plan'!D5<1),'RC Customers by plan'!D5<1,IF('RC Customers by plan'!D5="","",'RC Customers by plan'!D5<1))="",FALSE,IF(ISERROR('RC Customers by plan'!D5<1),'RC Customers by plan'!D5<1,IF('RC Customers by plan'!D5="","",'RC Customers by plan'!D5<1))),0,'RC Customers by plan'!D9*'Model inputs'!AG21/12) -> 0.037756944 | E29: =IF(IF(IF(ISERROR('RC Customers by plan'!E5<1),'RC Customers by plan'!E5<1,IF('RC Customers by plan'!E5="","",'RC Customers by plan'!E5<1))="",FALSE,IF(ISERROR('RC Customers by plan'!E5<1),'RC Customers by plan'!E5<1,IF('RC Customers by plan'!E5="","",'RC Customers by plan'!E5<1))),0,'RC Customers by plan'!E9*'Model inputs'!AG21/12) -> 0.05228173 | F29: =IF(IF(IF(ISERROR('RC Customers by plan'!F5<1),'RC Customers by plan'!F5<1,IF('RC Customers by plan'!F5="","",'RC Customers by plan'!F5<1))="",FALSE,IF(ISERROR('RC Customers by plan'!F5<1),'RC Customers by plan'!F5<1,IF('RC Customers by plan'!F5="","",'RC Customers by plan'!F5<1))),0,'RC Customers by plan'!F9*'Model inputs'!AG21/12) -> 0.068297598 | G29: =IF(IF(IF(ISERROR('RC Customers by plan'!G5<1),'RC Customers by plan'!G5<1,IF('RC Customers by plan'!G5="","",'RC Customers by plan'!G5<1))="",FALSE,IF(ISERROR('RC Customers by plan'!G5<1),'RC Customers by plan'!G5<1,IF('RC Customers by plan'!G5="","",'RC Customers by plan'!G5<1))),0,'RC Customers by plan'!G9*'Model inputs'!AG21/12) -> 0.08591028 | H29: =IF(IF(IF(ISERROR('RC Customers by plan'!H5<1),'RC Customers by plan'!H5<1,IF('RC Customers by plan'!H5="","",'RC Customers by plan'!H5<1))="",FALSE,IF(ISERROR('RC Customers by plan'!H5<1),'RC Customers by plan'!H5<1,IF('RC Customers by plan'!H5="","",'RC Customers by plan'!H5<1))),0,'RC Customers by plan'!H9*'Model inputs'!AG21/12) -> 0.10523917 | I29: =IF(IF(IF(ISERROR('RC Customers by plan'!I5<1),'RC Customers by plan'!I5<1,IF('RC Customers by plan'!I5="","",'RC Customers by plan'!I5<1))="",FALSE,IF(ISERROR('RC Customers by plan'!I5<1),'RC Customers by plan'!I5<1,IF('RC Customers by plan'!I5="","",'RC Customers by plan'!I5<1))),0,'RC Customers by plan'!I9*'Model inputs'!AG21/12) -> 0.12641836 | J29: =IF(IF(IF(ISERROR('RC Customers by plan'!J5<1),'RC Customers by plan'!J5<1,IF('RC Customers by plan'!J5="","",'RC Customers by plan'!J5<1))="",FALSE,IF(ISERROR('RC Customers by plan'!J5<1),'RC Customers by plan'!J5<1,IF('RC Customers by plan'!J5="","",'RC Customers by plan'!J5<1))),0,'RC Customers by plan'!J9*'Model inputs'!AG21/12) -> 0.14959788 | K29: =IF(IF(IF(ISERROR('RC Customers by plan'!K5<1),'RC Customers by plan'!K5<1,IF('RC Customers by plan'!K5="","",'RC Customers by plan'!K5<1))="",FALSE,IF(ISERROR('RC Customers by plan'!K5<1),'RC Customers by plan'!K5<1,IF('RC Customers by plan'!K5="","",'RC Customers by plan'!K5<1))),0,'RC Customers by plan'!K9*'Model inputs'!AG21/12) -> 0.17494492 | L29: =IF(IF(IF(ISERROR('RC Customers by plan'!L5<1),'RC Customers by plan'!L5<1,IF('RC Customers by plan'!L5="","",'RC Customers by plan'!L5<1))="",FALSE,IF(ISERROR('RC Customers by plan'!L5<1),'RC Customers by plan'!L5<1,IF('RC Customers by plan'!L5="","",'RC Customers by plan'!L5<1))),0,'RC Customers by plan'!L9*'Model inputs'!AG21/12) -> 0.20118383 | M29: =IF(IF(IF(ISERROR('RC Customers by plan'!M5<1),'RC Customers by plan'!M5<1,IF('RC Customers by plan'!M5="","",'RC Customers by plan'!M5<1))="",FALSE,IF(ISERROR('RC Customers by plan'!M5<1),'RC Customers by plan'!M5<1,IF('RC Customers by plan'!M5="","",'RC Customers by plan'!M5<1))),0,'RC Customers by plan'!M9*'Model inputs'!AG21/12) -> 0.22831848 | N29: =IF(IF(IF(ISERROR('RC Customers by plan'!N5<1),'RC Customers by plan'!N5<1,IF('RC Customers by plan'!N5="","",'RC Customers by plan'!N5<1))="",FALSE,IF(ISERROR('RC Customers by plan'!N5<1),'RC Customers by plan'!N5<1,IF('RC Customers by plan'!N5="","",'RC Customers by plan'!N5<1))),0,'RC Customers by plan'!N9*'Model inputs'!AG21/12) -> 0.25635638 | O29: =IF(IF(IF(ISERROR('RC Customers by plan'!O5<1),'RC Customers by plan'!O5<1,IF('RC Customers by plan'!O5="","",'RC Customers by plan'!O5<1))="",FALSE,IF(ISERROR('RC Customers by plan'!O5<1),'RC Customers by plan'!O5<1,IF('RC Customers by plan'!O5="","",'RC Customers by plan'!O5<1))),0,'RC Customers by plan'!O9*'Model inputs'!AG21/12) -> 0.28530855 | P29: =IF(IF(IF(ISERROR('RC Customers by plan'!P5<1),'RC Customers by plan'!P5<1,IF('RC Customers by plan'!P5="","",'RC Customers by plan'!P5<1))="",FALSE,IF(ISERROR('RC Customers by plan'!P5<1),'RC Customers by plan'!P5<1,IF('RC Customers by plan'!P5="","",'RC Customers by plan'!P5<1))),0,'RC Customers by plan'!P9*'Model inputs'!AG21/12) -> 0.31518941 | Q29: =IF(IF(IF(ISERROR('RC Customers by plan'!Q5<1),'RC Customers by plan'!Q5<1,IF('RC Customers by plan'!Q5="","",'RC Customers by plan'!Q5<1))="",FALSE,IF(ISERROR('RC Customers by plan'!Q5<1),'RC Customers by plan'!Q5<1,IF('RC Customers by plan'!Q5="","",'RC Customers by plan'!Q5<1))),0,'RC Customers by plan'!Q9*'Model inputs'!AG21/12) -> 0.34601663 | R29: =IF(IF(IF(ISERROR('RC Customers by plan'!R5<1),'RC Customers by plan'!R5<1,IF('RC Customers by plan'!R5="","",'RC Customers by plan'!R5<1))="",FALSE,IF(ISERROR('RC Customers by plan'!R5<1),'RC Customers by plan'!R5<1,IF('RC Customers by plan'!R5="","",'RC Customers by plan'!R5<1))),0,'RC Customers by plan'!R9*'Model inputs'!AG21/12) -> 0.3778111 | S29: =IF(IF(IF(ISERROR('RC Customers by plan'!S5<1),'RC Customers by plan'!S5<1,IF('RC Customers by plan'!S5="","",'RC Customers by plan'!S5<1))="",FALSE,IF(ISERROR('RC Customers by plan'!S5<1),'RC Customers by plan'!S5<1,IF('RC Customers by plan'!S5="","",'RC Customers by plan'!S5<1))),0,'RC Customers by plan'!S9*'Model inputs'!AG21/12) -> 0.41059681
A30: Ending customers | B30: =SUM('RC Customers by plan'!B31,'RC Customers by plan'!B32,'RC Customers by plan'!B33) -> 47 | C30: =SUM('RC Customers by plan'!C31,'RC Customers by plan'!C32,'RC Customers by plan'!C33) -> 84.905 | D30: =SUM('RC Customers by plan'!D31,'RC Customers by plan'!D32,'RC Customers by plan'!D33) -> 110.9505 | E30: =SUM('RC Customers by plan'!E31,'RC Customers by plan'!E32,'RC Customers by plan'!E33) -> 138.05103 | F30: =SUM('RC Customers by plan'!F31,'RC Customers by plan'!F32,'RC Customers by plan'!F33) -> 166.36012 | G30: =SUM('RC Customers by plan'!G31,'RC Customers by plan'!G32,'RC Customers by plan'!G33) -> 196.04007 | H30: =SUM('RC Customers by plan'!H31,'RC Customers by plan'!H32,'RC Customers by plan'!H33) -> 227.26287 | I30: =SUM('RC Customers by plan'!I31,'RC Customers by plan'!I32,'RC Customers by plan'!I33) -> 260.21141 | ... S30: =SUM('RC Customers by plan'!S31,'RC Customers by plan'!S32,'RC Customers by plan'!S33) -> 621.23762
A31: Indie | B31: ='RC Customers by plan'!B7+'RC Customers by plan'!B11+'RC Customers by plan'!B15+'RC Customers by plan'!B19-'RC Customers by plan'!B23-'RC Customers by plan'!B27 -> 40 | C31: ='RC Customers by plan'!C7+'RC Customers by plan'!C11+'RC Customers by plan'!C15+'RC Customers by plan'!C19-'RC Customers by plan'!C23-'RC Customers by plan'!C27 -> 74.333333 | D31: ='RC Customers by plan'!D7+'RC Customers by plan'!D11+'RC Customers by plan'!D15+'RC Customers by plan'!D19-'RC Customers by plan'!D23-'RC Customers by plan'!D27 -> 96.377778 | E31: ='RC Customers by plan'!E7+'RC Customers by plan'!E11+'RC Customers by plan'!E15+'RC Customers by plan'!E19-'RC Customers by plan'!E23-'RC Customers by plan'!E27 -> 119.11259 | F31: ='RC Customers by plan'!F7+'RC Customers by plan'!F11+'RC Customers by plan'!F15+'RC Customers by plan'!F19-'RC Customers by plan'!F23-'RC Customers by plan'!F27 -> 142.66455 | G31: ='RC Customers by plan'!G7+'RC Customers by plan'!G11+'RC Customers by plan'!G15+'RC Customers by plan'!G19-'RC Customers by plan'!G23-'RC Customers by plan'!G27 -> 167.16581 | H31: ='RC Customers by plan'!H7+'RC Customers by plan'!H11+'RC Customers by plan'!H15+'RC Customers by plan'!H19-'RC Customers by plan'!H23-'RC Customers by plan'!H27 -> 192.75462 | I31: ='RC Customers by plan'!I7+'RC Customers by plan'!I11+'RC Customers by plan'!I15+'RC Customers by plan'!I19-'RC Customers by plan'!I23-'RC Customers by plan'!I27 -> 219.57617 | ... S31: ='RC Customers by plan'!S7+'RC Customers by plan'!S11+'RC Customers by plan'!S15+'RC Customers by plan'!S19-'RC Customers by plan'!S23-'RC Customers by plan'!S27 -> 503.23671
A32: Launch | B32: ='RC Customers by plan'!B8+'RC Customers by plan'!B12+'RC Customers by plan'!B16+'RC Customers by plan'!B20-'RC Customers by plan'!B24-'RC Customers by plan'!B28 -> 1 | C32: ='RC Customers by plan'!C8+'RC Customers by plan'!C12+'RC Customers by plan'!C16+'RC Customers by plan'!C20-'RC Customers by plan'!C24-'RC Customers by plan'!C28 -> 1.51 | D32: ='RC Customers by plan'!D8+'RC Customers by plan'!D12+'RC Customers by plan'!D16+'RC Customers by plan'!D20-'RC Customers by plan'!D24-'RC Customers by plan'!D28 -> 2.0251069 | E32: ='RC Customers by plan'!E8+'RC Customers by plan'!E12+'RC Customers by plan'!E16+'RC Customers by plan'!E20-'RC Customers by plan'!E24-'RC Customers by plan'!E28 -> 2.5470121 | F32: ='RC Customers by plan'!F8+'RC Customers by plan'!F12+'RC Customers by plan'!F16+'RC Customers by plan'!F20-'RC Customers by plan'!F24-'RC Customers by plan'!F28 -> 3.0771045 | G32: ='RC Customers by plan'!G8+'RC Customers by plan'!G12+'RC Customers by plan'!G16+'RC Customers by plan'!G20-'RC Customers by plan'!G24-'RC Customers by plan'!G28 -> 3.6168582 | H32: ='RC Customers by plan'!H8+'RC Customers by plan'!H12+'RC Customers by plan'!H16+'RC Customers by plan'!H20-'RC Customers by plan'!H24-'RC Customers by plan'!H28 -> 4.1678445 | I32: ='RC Customers by plan'!I8+'RC Customers by plan'!I12+'RC Customers by plan'!I16+'RC Customers by plan'!I20-'RC Customers by plan'!I24-'RC Customers by plan'!I28 -> 4.7317452 | ... S32: ='RC Customers by plan'!S8+'RC Customers by plan'!S12+'RC Customers by plan'!S16+'RC Customers by plan'!S20-'RC Customers by plan'!S24-'RC Customers by plan'!S28 -> 11.344724
A33: Team | B33: ='RC Customers by plan'!B9+'RC Customers by plan'!B13+'RC Customers by plan'!B17+'RC Customers by plan'!B21-'RC Customers by plan'!B25-'RC Customers by plan'!B29 -> 6 | C33: ='RC Customers by plan'!C9+'RC Customers by plan'!C13+'RC Customers by plan'!C17+'RC Customers by plan'!C21-'RC Customers by plan'!C25-'RC Customers by plan'!C29 -> 9.0616667 | D33: ='RC Customers by plan'!D9+'RC Customers by plan'!D13+'RC Customers by plan'!D17+'RC Customers by plan'!D21-'RC Customers by plan'!D25-'RC Customers by plan'!D29 -> 12.547615 | E33: ='RC Customers by plan'!E9+'RC Customers by plan'!E13+'RC Customers by plan'!E17+'RC Customers by plan'!E21-'RC Customers by plan'!E25-'RC Customers by plan'!E29 -> 16.391424 | F33: ='RC Customers by plan'!F9+'RC Customers by plan'!F13+'RC Customers by plan'!F17+'RC Customers by plan'!F21-'RC Customers by plan'!F25-'RC Customers by plan'!F29 -> 20.618467 | G33: ='RC Customers by plan'!G9+'RC Customers by plan'!G13+'RC Customers by plan'!G17+'RC Customers by plan'!G21-'RC Customers by plan'!G25-'RC Customers by plan'!G29 -> 25.2574 | H33: ='RC Customers by plan'!H9+'RC Customers by plan'!H13+'RC Customers by plan'!H17+'RC Customers by plan'!H21-'RC Customers by plan'!H25-'RC Customers by plan'!H29 -> 30.340408 | I33: ='RC Customers by plan'!I9+'RC Customers by plan'!I13+'RC Customers by plan'!I17+'RC Customers by plan'!I21-'RC Customers by plan'!I25-'RC Customers by plan'!I29 -> 35.903491 | ... S33: ='RC Customers by plan'!S9+'RC Customers by plan'!S13+'RC Customers by plan'!S17+'RC Customers by plan'!S21-'RC Customers by plan'!S25-'RC Customers by plan'!S29 -> 106.65619

Sheet RC Revenue & billing by plan
A1: RC Revenue & billing by plan
A2: RC Customers & revenue · Main Scenario
A4: Variable / dimension | B4: 2026-11 | C4: 2026-12 | D4: 2027-01 | E4: 2027-02 | F4: 2027-03 | G4: 2027-04 | H4: 2027-05 | I4: 2027-06 | J4: 2027-07 | K4: 2027-08 | L4: 2027-09 | M4: 2027-10 | N4: 2027-11 | O4: 2027-12 | P4: 2028-01 | Q4: 2028-02 | R4: 2028-03 | S4: 2028-04
A5: Annual-pay share | B5: =IFERROR('RC Revenue & billing by plan'!B9/'RC Customers by plan'!B30,0) -> 0 | C5: =IFERROR('RC Revenue & billing by plan'!C9/'RC Customers by plan'!C30,0) -> 0.007263183 | D5: =IFERROR('RC Revenue & billing by plan'!D9/'RC Customers by plan'!D30,0) -> 0.015323508 | E5: =IFERROR('RC Revenue & billing by plan'!E9/'RC Customers by plan'!E30,0) -> 0.024007255 | F5: =IFERROR('RC Revenue & billing by plan'!F9/'RC Customers by plan'!F30,0) -> 0.033234928 | G5: =IFERROR('RC Revenue & billing by plan'!G9/'RC Customers by plan'!G30,0) -> 0.042958865 | H5: =IFERROR('RC Revenue & billing by plan'!H9/'RC Customers by plan'!H30,0) -> 0.053145012 | I5: =IFERROR('RC Revenue & billing by plan'!I9/'RC Customers by plan'!I30,0) -> 0.054656837 | ... S5: =IFERROR('RC Revenue & billing by plan'!S9/'RC Customers by plan'!S30,0) -> 0.066480715
A6: Indie | B6: =IF(IF(IF(ISERROR('RC Customers by plan'!B5<=0),'RC Customers by plan'!B5<=0,IF('RC Customers by plan'!B5="","",'RC Customers by plan'!B5<=0))="",FALSE,IF(ISERROR('RC Customers by plan'!B5<=0),'RC Customers by plan'!B5<=0,IF('RC Customers by plan'!B5="","",'RC Customers by plan'!B5<=0))),0,'Model inputs'!AG28*MIN('RC Customers by plan'!B5/'Model inputs'!AG22,1)) -> 0 | C6: =IF(IF(IF(ISERROR('RC Customers by plan'!C5<=0),'RC Customers by plan'!C5<=0,IF('RC Customers by plan'!C5="","",'RC Customers by plan'!C5<=0))="",FALSE,IF(ISERROR('RC Customers by plan'!C5<=0),'RC Customers by plan'!C5<=0,IF('RC Customers by plan'!C5="","",'RC Customers by plan'!C5<=0))),0,'Model inputs'!AG28*MIN('RC Customers by plan'!C5/'Model inputs'!AG22,1)) -> 0 | D6: =IF(IF(IF(ISERROR('RC Customers by plan'!D5<=0),'RC Customers by plan'!D5<=0,IF('RC Customers by plan'!D5="","",'RC Customers by plan'!D5<=0))="",FALSE,IF(ISERROR('RC Customers by plan'!D5<=0),'RC Customers by plan'!D5<=0,IF('RC Customers by plan'!D5="","",'RC Customers by plan'!D5<=0))),0,'Model inputs'!AG28*MIN('RC Customers by plan'!D5/'Model inputs'!AG22,1)) -> 0 | E6: =IF(IF(IF(ISERROR('RC Customers by plan'!E5<=0),'RC Customers by plan'!E5<=0,IF('RC Customers by plan'!E5="","",'RC Customers by plan'!E5<=0))="",FALSE,IF(ISERROR('RC Customers by plan'!E5<=0),'RC Customers by plan'!E5<=0,IF('RC Customers by plan'!E5="","",'RC Customers by plan'!E5<=0))),0,'Model inputs'!AG28*MIN('RC Customers by plan'!E5/'Model inputs'!AG22,1)) -> 0 | F6: =IF(IF(IF(ISERROR('RC Customers by plan'!F5<=0),'RC Customers by plan'!F5<=0,IF('RC Customers by plan'!F5="","",'RC Customers by plan'!F5<=0))="",FALSE,IF(ISERROR('RC Customers by plan'!F5<=0),'RC Customers by plan'!F5<=0,IF('RC Customers by plan'!F5="","",'RC Customers by plan'!F5<=0))),0,'Model inputs'!AG28*MIN('RC Customers by plan'!F5/'Model inputs'!AG22,1)) -> 0 | G6: =IF(IF(IF(ISERROR('RC Customers by plan'!G5<=0),'RC Customers by plan'!G5<=0,IF('RC Customers by plan'!G5="","",'RC Customers by plan'!G5<=0))="",FALSE,IF(ISERROR('RC Customers by plan'!G5<=0),'RC Customers by plan'!G5<=0,IF('RC Customers by plan'!G5="","",'RC Customers by plan'!G5<=0))),0,'Model inputs'!AG28*MIN('RC Customers by plan'!G5/'Model inputs'!AG22,1)) -> 0 | H6: =IF(IF(IF(ISERROR('RC Customers by plan'!H5<=0),'RC Customers by plan'!H5<=0,IF('RC Customers by plan'!H5="","",'RC Customers by plan'!H5<=0))="",FALSE,IF(ISERROR('RC Customers by plan'!H5<=0),'RC Customers by plan'!H5<=0,IF('RC Customers by plan'!H5="","",'RC Customers by plan'!H5<=0))),0,'Model inputs'!AG28*MIN('RC Customers by plan'!H5/'Model inputs'!AG22,1)) -> 0 | I6: =IF(IF(IF(ISERROR('RC Customers by plan'!I5<=0),'RC Customers by plan'!I5<=0,IF('RC Customers by plan'!I5="","",'RC Customers by plan'!I5<=0))="",FALSE,IF(ISERROR('RC Customers by plan'!I5<=0),'RC Customers by plan'!I5<=0,IF('RC Customers by plan'!I5="","",'RC Customers by plan'!I5<=0))),0,'Model inputs'!AG28*MIN('RC Customers by plan'!I5/'Model inputs'!AG22,1)) -> 0 | J6: =IF(IF(IF(ISERROR('RC Customers by plan'!J5<=0),'RC Customers by plan'!J5<=0,IF('RC Customers by plan'!J5="","",'RC Customers by plan'!J5<=0))="",FALSE,IF(ISERROR('RC Customers by plan'!J5<=0),'RC Customers by plan'!J5<=0,IF('RC Customers by plan'!J5="","",'RC Customers by plan'!J5<=0))),0,'Model inputs'!AG28*MIN('RC Customers by plan'!J5/'Model inputs'!AG22,1)) -> 0 | K6: =IF(IF(IF(ISERROR('RC Customers by plan'!K5<=0),'RC Customers by plan'!K5<=0,IF('RC Customers by plan'!K5="","",'RC Customers by plan'!K5<=0))="",FALSE,IF(ISERROR('RC Customers by plan'!K5<=0),'RC Customers by plan'!K5<=0,IF('RC Customers by plan'!K5="","",'RC Customers by plan'!K5<=0))),0,'Model inputs'!AG28*MIN('RC Customers by plan'!K5/'Model inputs'!AG22,1)) -> 0 | L6: =IF(IF(IF(ISERROR('RC Customers by plan'!L5<=0),'RC Customers by plan'!L5<=0,IF('RC Customers by plan'!L5="","",'RC Customers by plan'!L5<=0))="",FALSE,IF(ISERROR('RC Customers by plan'!L5<=0),'RC Customers by plan'!L5<=0,IF('RC Customers by plan'!L5="","",'RC Customers by plan'!L5<=0))),0,'Model inputs'!AG28*MIN('RC Customers by plan'!L5/'Model inputs'!AG22,1)) -> 0 | M6: =IF(IF(IF(ISERROR('RC Customers by plan'!M5<=0),'RC Customers by plan'!M5<=0,IF('RC Customers by plan'!M5="","",'RC Customers by plan'!M5<=0))="",FALSE,IF(ISERROR('RC Customers by plan'!M5<=0),'RC Customers by plan'!M5<=0,IF('RC Customers by plan'!M5="","",'RC Customers by plan'!M5<=0))),0,'Model inputs'!AG28*MIN('RC Customers by plan'!M5/'Model inputs'!AG22,1)) -> 0 | N6: =IF(IF(IF(ISERROR('RC Customers by plan'!N5<=0),'RC Customers by plan'!N5<=0,IF('RC Customers by plan'!N5="","",'RC Customers by plan'!N5<=0))="",FALSE,IF(ISERROR('RC Customers by plan'!N5<=0),'RC Customers by plan'!N5<=0,IF('RC Customers by plan'!N5="","",'RC Customers by plan'!N5<=0))),0,'Model inputs'!AG28*MIN('RC Customers by plan'!N5/'Model inputs'!AG22,1)) -> 0 | O6: =IF(IF(IF(ISERROR('RC Customers by plan'!O5<=0),'RC Customers by plan'!O5<=0,IF('RC Customers by plan'!O5="","",'RC Customers by plan'!O5<=0))="",FALSE,IF(ISERROR('RC Customers by plan'!O5<=0),'RC Customers by plan'!O5<=0,IF('RC Customers by plan'!O5="","",'RC Customers by plan'!O5<=0))),0,'Model inputs'!AG28*MIN('RC Customers by plan'!O5/'Model inputs'!AG22,1)) -> 0 | P6: =IF(IF(IF(ISERROR('RC Customers by plan'!P5<=0),'RC Customers by plan'!P5<=0,IF('RC Customers by plan'!P5="","",'RC Customers by plan'!P5<=0))="",FALSE,IF(ISERROR('RC Customers by plan'!P5<=0),'RC Customers by plan'!P5<=0,IF('RC Customers by plan'!P5="","",'RC Customers by plan'!P5<=0))),0,'Model inputs'!AG28*MIN('RC Customers by plan'!P5/'Model inputs'!AG22,1)) -> 0 | Q6: =IF(IF(IF(ISERROR('RC Customers by plan'!Q5<=0),'RC Customers by plan'!Q5<=0,IF('RC Customers by plan'!Q5="","",'RC Customers by plan'!Q5<=0))="",FALSE,IF(ISERROR('RC Customers by plan'!Q5<=0),'RC Customers by plan'!Q5<=0,IF('RC Customers by plan'!Q5="","",'RC Customers by plan'!Q5<=0))),0,'Model inputs'!AG28*MIN('RC Customers by plan'!Q5/'Model inputs'!AG22,1)) -> 0 | R6: =IF(IF(IF(ISERROR('RC Customers by plan'!R5<=0),'RC Customers by plan'!R5<=0,IF('RC Customers by plan'!R5="","",'RC Customers by plan'!R5<=0))="",FALSE,IF(ISERROR('RC Customers by plan'!R5<=0),'RC Customers by plan'!R5<=0,IF('RC Customers by plan'!R5="","",'RC Customers by plan'!R5<=0))),0,'Model inputs'!AG28*MIN('RC Customers by plan'!R5/'Model inputs'!AG22,1)) -> 0 | S6: =IF(IF(IF(ISERROR('RC Customers by plan'!S5<=0),'RC Customers by plan'!S5<=0,IF('RC Customers by plan'!S5="","",'RC Customers by plan'!S5<=0))="",FALSE,IF(ISERROR('RC Customers by plan'!S5<=0),'RC Customers by plan'!S5<=0,IF('RC Customers by plan'!S5="","",'RC Customers by plan'!S5<=0))),0,'Model inputs'!AG28*MIN('RC Customers by plan'!S5/'Model inputs'!AG22,1)) -> 0
A7: Launch | B7: =IF(IF(IF(ISERROR('RC Customers by plan'!B5<=0),'RC Customers by plan'!B5<=0,IF('RC Customers by plan'!B5="","",'RC Customers by plan'!B5<=0))="",FALSE,IF(ISERROR('RC Customers by plan'!B5<=0),'RC Customers by plan'!B5<=0,IF('RC Customers by plan'!B5="","",'RC Customers by plan'!B5<=0))),0,'Model inputs'!AG29*MIN('RC Customers by plan'!B5/'Model inputs'!AG22,1)) -> 0 | C7: =IF(IF(IF(ISERROR('RC Customers by plan'!C5<=0),'RC Customers by plan'!C5<=0,IF('RC Customers by plan'!C5="","",'RC Customers by plan'!C5<=0))="",FALSE,IF(ISERROR('RC Customers by plan'!C5<=0),'RC Customers by plan'!C5<=0,IF('RC Customers by plan'!C5="","",'RC Customers by plan'!C5<=0))),0,'Model inputs'!AG29*MIN('RC Customers by plan'!C5/'Model inputs'!AG22,1)) -> 0.058333333 | D7: =IF(IF(IF(ISERROR('RC Customers by plan'!D5<=0),'RC Customers by plan'!D5<=0,IF('RC Customers by plan'!D5="","",'RC Customers by plan'!D5<=0))="",FALSE,IF(ISERROR('RC Customers by plan'!D5<=0),'RC Customers by plan'!D5<=0,IF('RC Customers by plan'!D5="","",'RC Customers by plan'!D5<=0))),0,'Model inputs'!AG29*MIN('RC Customers by plan'!D5/'Model inputs'!AG22,1)) -> 0.11666667 | E7: =IF(IF(IF(ISERROR('RC Customers by plan'!E5<=0),'RC Customers by plan'!E5<=0,IF('RC Customers by plan'!E5="","",'RC Customers by plan'!E5<=0))="",FALSE,IF(ISERROR('RC Customers by plan'!E5<=0),'RC Customers by plan'!E5<=0,IF('RC Customers by plan'!E5="","",'RC Customers by plan'!E5<=0))),0,'Model inputs'!AG29*MIN('RC Customers by plan'!E5/'Model inputs'!AG22,1)) -> 0.175 | F7: =IF(IF(IF(ISERROR('RC Customers by plan'!F5<=0),'RC Customers by plan'!F5<=0,IF('RC Customers by plan'!F5="","",'RC Customers by plan'!F5<=0))="",FALSE,IF(ISERROR('RC Customers by plan'!F5<=0),'RC Customers by plan'!F5<=0,IF('RC Customers by plan'!F5="","",'RC Customers by plan'!F5<=0))),0,'Model inputs'!AG29*MIN('RC Customers by plan'!F5/'Model inputs'!AG22,1)) -> 0.23333333 | G7: =IF(IF(IF(ISERROR('RC Customers by plan'!G5<=0),'RC Customers by plan'!G5<=0,IF('RC Customers by plan'!G5="","",'RC Customers by plan'!G5<=0))="",FALSE,IF(ISERROR('RC Customers by plan'!G5<=0),'RC Customers by plan'!G5<=0,IF('RC Customers by plan'!G5="","",'RC Customers by plan'!G5<=0))),0,'Model inputs'!AG29*MIN('RC Customers by plan'!G5/'Model inputs'!AG22,1)) -> 0.29166667 | H7: =IF(IF(IF(ISERROR('RC Customers by plan'!H5<=0),'RC Customers by plan'!H5<=0,IF('RC Customers by plan'!H5="","",'RC Customers by plan'!H5<=0))="",FALSE,IF(ISERROR('RC Customers by plan'!H5<=0),'RC Customers by plan'!H5<=0,IF('RC Customers by plan'!H5="","",'RC Customers by plan'!H5<=0))),0,'Model inputs'!AG29*MIN('RC Customers by plan'!H5/'Model inputs'!AG22,1)) -> 0.35 | I7: =IF(IF(IF(ISERROR('RC Customers by plan'!I5<=0),'RC Customers by plan'!I5<=0,IF('RC Customers by plan'!I5="","",'RC Customers by plan'!I5<=0))="",FALSE,IF(ISERROR('RC Customers by plan'!I5<=0),'RC Customers by plan'!I5<=0,IF('RC Customers by plan'!I5="","",'RC Customers by plan'!I5<=0))),0,'Model inputs'!AG29*MIN('RC Customers by plan'!I5/'Model inputs'!AG22,1)) -> 0.35 | J7: =IF(IF(IF(ISERROR('RC Customers by plan'!J5<=0),'RC Customers by plan'!J5<=0,IF('RC Customers by plan'!J5="","",'RC Customers by plan'!J5<=0))="",FALSE,IF(ISERROR('RC Customers by plan'!J5<=0),'RC Customers by plan'!J5<=0,IF('RC Customers by plan'!J5="","",'RC Customers by plan'!J5<=0))),0,'Model inputs'!AG29*MIN('RC Customers by plan'!J5/'Model inputs'!AG22,1)) -> 0.35 | K7: =IF(IF(IF(ISERROR('RC Customers by plan'!K5<=0),'RC Customers by plan'!K5<=0,IF('RC Customers by plan'!K5="","",'RC Customers by plan'!K5<=0))="",FALSE,IF(ISERROR('RC Customers by plan'!K5<=0),'RC Customers by plan'!K5<=0,IF('RC Customers by plan'!K5="","",'RC Customers by plan'!K5<=0))),0,'Model inputs'!AG29*MIN('RC Customers by plan'!K5/'Model inputs'!AG22,1)) -> 0.35 | L7: =IF(IF(IF(ISERROR('RC Customers by plan'!L5<=0),'RC Customers by plan'!L5<=0,IF('RC Customers by plan'!L5="","",'RC Customers by plan'!L5<=0))="",FALSE,IF(ISERROR('RC Customers by plan'!L5<=0),'RC Customers by plan'!L5<=0,IF('RC Customers by plan'!L5="","",'RC Customers by plan'!L5<=0))),0,'Model inputs'!AG29*MIN('RC Customers by plan'!L5/'Model inputs'!AG22,1)) -> 0.35 | M7: =IF(IF(IF(ISERROR('RC Customers by plan'!M5<=0),'RC Customers by plan'!M5<=0,IF('RC Customers by plan'!M5="","",'RC Customers by plan'!M5<=0))="",FALSE,IF(ISERROR('RC Customers by plan'!M5<=0),'RC Customers by plan'!M5<=0,IF('RC Customers by plan'!M5="","",'RC Customers by plan'!M5<=0))),0,'Model inputs'!AG29*MIN('RC Customers by plan'!M5/'Model inputs'!AG22,1)) -> 0.35 | N7: =IF(IF(IF(ISERROR('RC Customers by plan'!N5<=0),'RC Customers by plan'!N5<=0,IF('RC Customers by plan'!N5="","",'RC Customers by plan'!N5<=0))="",FALSE,IF(ISERROR('RC Customers by plan'!N5<=0),'RC Customers by plan'!N5<=0,IF('RC Customers by plan'!N5="","",'RC Customers by plan'!N5<=0))),0,'Model inputs'!AG29*MIN('RC Customers by plan'!N5/'Model inputs'!AG22,1)) -> 0.35 | O7: =IF(IF(IF(ISERROR('RC Customers by plan'!O5<=0),'RC Customers by plan'!O5<=0,IF('RC Customers by plan'!O5="","",'RC Customers by plan'!O5<=0))="",FALSE,IF(ISERROR('RC Customers by plan'!O5<=0),'RC Customers by plan'!O5<=0,IF('RC Customers by plan'!O5="","",'RC Customers by plan'!O5<=0))),0,'Model inputs'!AG29*MIN('RC Customers by plan'!O5/'Model inputs'!AG22,1)) -> 0.35 | P7: =IF(IF(IF(ISERROR('RC Customers by plan'!P5<=0),'RC Customers by plan'!P5<=0,IF('RC Customers by plan'!P5="","",'RC Customers by plan'!P5<=0))="",FALSE,IF(ISERROR('RC Customers by plan'!P5<=0),'RC Customers by plan'!P5<=0,IF('RC Customers by plan'!P5="","",'RC Customers by plan'!P5<=0))),0,'Model inputs'!AG29*MIN('RC Customers by plan'!P5/'Model inputs'!AG22,1)) -> 0.35 | Q7: =IF(IF(IF(ISERROR('RC Customers by plan'!Q5<=0),'RC Customers by plan'!Q5<=0,IF('RC Customers by plan'!Q5="","",'RC Customers by plan'!Q5<=0))="",FALSE,IF(ISERROR('RC Customers by plan'!Q5<=0),'RC Customers by plan'!Q5<=0,IF('RC Customers by plan'!Q5="","",'RC Customers by plan'!Q5<=0))),0,'Model inputs'!AG29*MIN('RC Customers by plan'!Q5/'Model inputs'!AG22,1)) -> 0.35 | R7: =IF(IF(IF(ISERROR('RC Customers by plan'!R5<=0),'RC Customers by plan'!R5<=0,IF('RC Customers by plan'!R5="","",'RC Customers by plan'!R5<=0))="",FALSE,IF(ISERROR('RC Customers by plan'!R5<=0),'RC Customers by plan'!R5<=0,IF('RC Customers by plan'!R5="","",'RC Customers by plan'!R5<=0))),0,'Model inputs'!AG29*MIN('RC Customers by plan'!R5/'Model inputs'!AG22,1)) -> 0.35 | S7: =IF(IF(IF(ISERROR('RC Customers by plan'!S5<=0),'RC Customers by plan'!S5<=0,IF('RC Customers by plan'!S5="","",'RC Customers by plan'!S5<=0))="",FALSE,IF(ISERROR('RC Customers by plan'!S5<=0),'RC Customers by plan'!S5<=0,IF('RC Customers by plan'!S5="","",'RC Customers by plan'!S5<=0))),0,'Model inputs'!AG29*MIN('RC Customers by plan'!S5/'Model inputs'!AG22,1)) -> 0.35
A8: Team | B8: =IF(IF(IF(ISERROR('RC Customers by plan'!B5<=0),'RC Customers by plan'!B5<=0,IF('RC Customers by plan'!B5="","",'RC Customers by plan'!B5<=0))="",FALSE,IF(ISERROR('RC Customers by plan'!B5<=0),'RC Customers by plan'!B5<=0,IF('RC Customers by plan'!B5="","",'RC Customers by plan'!B5<=0))),0,'Model inputs'!AG30*MIN('RC Customers by plan'!B5/'Model inputs'!AG22,1)) -> 0 | C8: =IF(IF(IF(ISERROR('RC Customers by plan'!C5<=0),'RC Customers by plan'!C5<=0,IF('RC Customers by plan'!C5="","",'RC Customers by plan'!C5<=0))="",FALSE,IF(ISERROR('RC Customers by plan'!C5<=0),'RC Customers by plan'!C5<=0,IF('RC Customers by plan'!C5="","",'RC Customers by plan'!C5<=0))),0,'Model inputs'!AG30*MIN('RC Customers by plan'!C5/'Model inputs'!AG22,1)) -> 0.058333333 | D8: =IF(IF(IF(ISERROR('RC Customers by plan'!D5<=0),'RC Customers by plan'!D5<=0,IF('RC Customers by plan'!D5="","",'RC Customers by plan'!D5<=0))="",FALSE,IF(ISERROR('RC Customers by plan'!D5<=0),'RC Customers by plan'!D5<=0,IF('RC Customers by plan'!D5="","",'RC Customers by plan'!D5<=0))),0,'Model inputs'!AG30*MIN('RC Customers by plan'!D5/'Model inputs'!AG22,1)) -> 0.11666667 | E8: =IF(IF(IF(ISERROR('RC Customers by plan'!E5<=0),'RC Customers by plan'!E5<=0,IF('RC Customers by plan'!E5="","",'RC Customers by plan'!E5<=0))="",FALSE,IF(ISERROR('RC Customers by plan'!E5<=0),'RC Customers by plan'!E5<=0,IF('RC Customers by plan'!E5="","",'RC Customers by plan'!E5<=0))),0,'Model inputs'!AG30*MIN('RC Customers by plan'!E5/'Model inputs'!AG22,1)) -> 0.175 | F8: =IF(IF(IF(ISERROR('RC Customers by plan'!F5<=0),'RC Customers by plan'!F5<=0,IF('RC Customers by plan'!F5="","",'RC Customers by plan'!F5<=0))="",FALSE,IF(ISERROR('RC Customers by plan'!F5<=0),'RC Customers by plan'!F5<=0,IF('RC Customers by plan'!F5="","",'RC Customers by plan'!F5<=0))),0,'Model inputs'!AG30*MIN('RC Customers by plan'!F5/'Model inputs'!AG22,1)) -> 0.23333333 | G8: =IF(IF(IF(ISERROR('RC Customers by plan'!G5<=0),'RC Customers by plan'!G5<=0,IF('RC Customers by plan'!G5="","",'RC Customers by plan'!G5<=0))="",FALSE,IF(ISERROR('RC Customers by plan'!G5<=0),'RC Customers by plan'!G5<=0,IF('RC Customers by plan'!G5="","",'RC Customers by plan'!G5<=0))),0,'Model inputs'!AG30*MIN('RC Customers by plan'!G5/'Model inputs'!AG22,1)) -> 0.29166667 | H8: =IF(IF(IF(ISERROR('RC Customers by plan'!H5<=0),'RC Customers by plan'!H5<=0,IF('RC Customers by plan'!H5="","",'RC Customers by plan'!H5<=0))="",FALSE,IF(ISERROR('RC Customers by plan'!H5<=0),'RC Customers by plan'!H5<=0,IF('RC Customers by plan'!H5="","",'RC Customers by plan'!H5<=0))),0,'Model inputs'!AG30*MIN('RC Customers by plan'!H5/'Model inputs'!AG22,1)) -> 0.35 | I8: =IF(IF(IF(ISERROR('RC Customers by plan'!I5<=0),'RC Customers by plan'!I5<=0,IF('RC Customers by plan'!I5="","",'RC Customers by plan'!I5<=0))="",FALSE,IF(ISERROR('RC Customers by plan'!I5<=0),'RC Customers by plan'!I5<=0,IF('RC Customers by plan'!I5="","",'RC Customers by plan'!I5<=0))),0,'Model inputs'!AG30*MIN('RC Customers by plan'!I5/'Model inputs'!AG22,1)) -> 0.35 | J8: =IF(IF(IF(ISERROR('RC Customers by plan'!J5<=0),'RC Customers by plan'!J5<=0,IF('RC Customers by plan'!J5="","",'RC Customers by plan'!J5<=0))="",FALSE,IF(ISERROR('RC Customers by plan'!J5<=0),'RC Customers by plan'!J5<=0,IF('RC Customers by plan'!J5="","",'RC Customers by plan'!J5<=0))),0,'Model inputs'!AG30*MIN('RC Customers by plan'!J5/'Model inputs'!AG22,1)) -> 0.35 | K8: =IF(IF(IF(ISERROR('RC Customers by plan'!K5<=0),'RC Customers by plan'!K5<=0,IF('RC Customers by plan'!K5="","",'RC Customers by plan'!K5<=0))="",FALSE,IF(ISERROR('RC Customers by plan'!K5<=0),'RC Customers by plan'!K5<=0,IF('RC Customers by plan'!K5="","",'RC Customers by plan'!K5<=0))),0,'Model inputs'!AG30*MIN('RC Customers by plan'!K5/'Model inputs'!AG22,1)) -> 0.35 | L8: =IF(IF(IF(ISERROR('RC Customers by plan'!L5<=0),'RC Customers by plan'!L5<=0,IF('RC Customers by plan'!L5="","",'RC Customers by plan'!L5<=0))="",FALSE,IF(ISERROR('RC Customers by plan'!L5<=0),'RC Customers by plan'!L5<=0,IF('RC Customers by plan'!L5="","",'RC Customers by plan'!L5<=0))),0,'Model inputs'!AG30*MIN('RC Customers by plan'!L5/'Model inputs'!AG22,1)) -> 0.35 | M8: =IF(IF(IF(ISERROR('RC Customers by plan'!M5<=0),'RC Customers by plan'!M5<=0,IF('RC Customers by plan'!M5="","",'RC Customers by plan'!M5<=0))="",FALSE,IF(ISERROR('RC Customers by plan'!M5<=0),'RC Customers by plan'!M5<=0,IF('RC Customers by plan'!M5="","",'RC Customers by plan'!M5<=0))),0,'Model inputs'!AG30*MIN('RC Customers by plan'!M5/'Model inputs'!AG22,1)) -> 0.35 | N8: =IF(IF(IF(ISERROR('RC Customers by plan'!N5<=0),'RC Customers by plan'!N5<=0,IF('RC Customers by plan'!N5="","",'RC Customers by plan'!N5<=0))="",FALSE,IF(ISERROR('RC Customers by plan'!N5<=0),'RC Customers by plan'!N5<=0,IF('RC Customers by plan'!N5="","",'RC Customers by plan'!N5<=0))),0,'Model inputs'!AG30*MIN('RC Customers by plan'!N5/'Model inputs'!AG22,1)) -> 0.35 | O8: =IF(IF(IF(ISERROR('RC Customers by plan'!O5<=0),'RC Customers by plan'!O5<=0,IF('RC Customers by plan'!O5="","",'RC Customers by plan'!O5<=0))="",FALSE,IF(ISERROR('RC Customers by plan'!O5<=0),'RC Customers by plan'!O5<=0,IF('RC Customers by plan'!O5="","",'RC Customers by plan'!O5<=0))),0,'Model inputs'!AG30*MIN('RC Customers by plan'!O5/'Model inputs'!AG22,1)) -> 0.35 | P8: =IF(IF(IF(ISERROR('RC Customers by plan'!P5<=0),'RC Customers by plan'!P5<=0,IF('RC Customers by plan'!P5="","",'RC Customers by plan'!P5<=0))="",FALSE,IF(ISERROR('RC Customers by plan'!P5<=0),'RC Customers by plan'!P5<=0,IF('RC Customers by plan'!P5="","",'RC Customers by plan'!P5<=0))),0,'Model inputs'!AG30*MIN('RC Customers by plan'!P5/'Model inputs'!AG22,1)) -> 0.35 | Q8: =IF(IF(IF(ISERROR('RC Customers by plan'!Q5<=0),'RC Customers by plan'!Q5<=0,IF('RC Customers by plan'!Q5="","",'RC Customers by plan'!Q5<=0))="",FALSE,IF(ISERROR('RC Customers by plan'!Q5<=0),'RC Customers by plan'!Q5<=0,IF('RC Customers by plan'!Q5="","",'RC Customers by plan'!Q5<=0))),0,'Model inputs'!AG30*MIN('RC Customers by plan'!Q5/'Model inputs'!AG22,1)) -> 0.35 | R8: =IF(IF(IF(ISERROR('RC Customers by plan'!R5<=0),'RC Customers by plan'!R5<=0,IF('RC Customers by plan'!R5="","",'RC Customers by plan'!R5<=0))="",FALSE,IF(ISERROR('RC Customers by plan'!R5<=0),'RC Customers by plan'!R5<=0,IF('RC Customers by plan'!R5="","",'RC Customers by plan'!R5<=0))),0,'Model inputs'!AG30*MIN('RC Customers by plan'!R5/'Model inputs'!AG22,1)) -> 0.35 | S8: =IF(IF(IF(ISERROR('RC Customers by plan'!S5<=0),'RC Customers by plan'!S5<=0,IF('RC Customers by plan'!S5="","",'RC Customers by plan'!S5<=0))="",FALSE,IF(ISERROR('RC Customers by plan'!S5<=0),'RC Customers by plan'!S5<=0,IF('RC Customers by plan'!S5="","",'RC Customers by plan'!S5<=0))),0,'Model inputs'!AG30*MIN('RC Customers by plan'!S5/'Model inputs'!AG22,1)) -> 0.35
A9: Annual payers | B9: =SUM('RC Revenue & billing by plan'!B10,'RC Revenue & billing by plan'!B11,'RC Revenue & billing by plan'!B12) -> 0 | C9: =SUM('RC Revenue & billing by plan'!C10,'RC Revenue & billing by plan'!C11,'RC Revenue & billing by plan'!C12) -> 0.61668056 | D9: =SUM('RC Revenue & billing by plan'!D10,'RC Revenue & billing by plan'!D11,'RC Revenue & billing by plan'!D12) -> 1.7001509 | E9: =SUM('RC Revenue & billing by plan'!E10,'RC Revenue & billing by plan'!E11,'RC Revenue & billing by plan'!E12) -> 3.3142262 | F9: =SUM('RC Revenue & billing by plan'!F10,'RC Revenue & billing by plan'!F11,'RC Revenue & billing by plan'!F12) -> 5.5289667 | G9: =SUM('RC Revenue & billing by plan'!G10,'RC Revenue & billing by plan'!G11,'RC Revenue & billing by plan'!G12) -> 8.4216586 | H9: =SUM('RC Revenue & billing by plan'!H10,'RC Revenue & billing by plan'!H11,'RC Revenue & billing by plan'!H12) -> 12.077888 | I9: =SUM('RC Revenue & billing by plan'!I10,'RC Revenue & billing by plan'!I11,'RC Revenue & billing by plan'!I12) -> 14.222333 | ... S9: =SUM('RC Revenue & billing by plan'!S10,'RC Revenue & billing by plan'!S11,'RC Revenue & billing by plan'!S12) -> 41.300321
