Workbook

Sheet RC P&L, cash & runway
A1: RC P&L, cash & runway
A2: RC P&L, cash & runway · Main Scenario
A4: Variable / dimension | B4: 2026-11 | C4: 2026-12 | D4: 2027-01 | E4: 2027-02 | F4: 2027-03 | G4: 2027-04 | H4: 2027-05 | I4: 2027-06 | J4: 2027-07 | K4: 2027-08 | L4: 2027-09 | M4: 2027-10 | N4: 2027-11 | O4: 2027-12 | P4: 2028-01 | Q4: 2028-02 | R4: 2028-03 | S4: 2028-04
A5: Subscription revenue | B5: =SUM('Model inputs'!E69,'Model inputs'!E70,'Model inputs'!E71) -> 2553 | C5: =SUM('Model inputs'!F69,'Model inputs'!F70,'Model inputs'!F71) -> 4238.8926 | D5: =SUM('Model inputs'!G69,'Model inputs'!G70,'Model inputs'!G71) -> 5619.0762 | E5: =SUM('Model inputs'!H69,'Model inputs'!H70,'Model inputs'!H71) -> 7059.2423 | F5: =SUM('Model inputs'!I69,'Model inputs'!I70,'Model inputs'!I71) -> 8565.7133 | G5: =SUM('Model inputs'!J69,'Model inputs'!J70,'Model inputs'!J71) -> 10145.299 | H5: =SUM('Model inputs'!K69,'Model inputs'!K70,'Model inputs'!K71) -> 11805.331 | I5: =SUM('Model inputs'!L69,'Model inputs'!L70,'Model inputs'!L71) -> 13628.676 | ... S5: =SUM('Model inputs'!V69,'Model inputs'!V70,'Model inputs'!V71) -> 34889.409
A6: Overage revenue | B6: =SUM('Model inputs'!E59,'Model inputs'!E60,'Model inputs'!E61) -> 95 | C6: =SUM('Model inputs'!F59,'Model inputs'!F60,'Model inputs'!F61) -> 160.875 | D6: =SUM('Model inputs'!G59,'Model inputs'!G60,'Model inputs'!G61) -> 213.5869 | E6: =SUM('Model inputs'!H59,'Model inputs'!H60,'Model inputs'!H61) -> 269.05304 | F6: =SUM('Model inputs'!I59,'Model inputs'!I60,'Model inputs'!I61) -> 327.57959 | G6: =SUM('Model inputs'!J59,'Model inputs'!J60,'Model inputs'!J61) -> 389.49713 | H6: =SUM('Model inputs'!K59,'Model inputs'!K60,'Model inputs'!K61) -> 455.16298 | I6: =SUM('Model inputs'!L59,'Model inputs'!L60,'Model inputs'!L61) -> 524.96385 | ... S6: =SUM('Model inputs'!V59,'Model inputs'!V60,'Model inputs'!V61) -> 1332.4977
A7: Long-trailer revenue | B7: =SUM('Model inputs'!E29,'Model inputs'!E30,'Model inputs'!E31) -> 49.68 | C7: =SUM('Model inputs'!F29,'Model inputs'!F30,'Model inputs'!F31) -> 82.1275 | D7: =SUM('Model inputs'!G29,'Model inputs'!G30,'Model inputs'!G31) -> 109.56726 | E7: =SUM('Model inputs'!H29,'Model inputs'!H30,'Model inputs'!H31) -> 138.45231 | F7: =SUM('Model inputs'!I29,'Model inputs'!I30,'Model inputs'!I31) -> 168.93601 | G7: =SUM('Model inputs'!J29,'Model inputs'!J30,'Model inputs'!J31) -> 201.1848 | H7: =SUM('Model inputs'!K29,'Model inputs'!K30,'Model inputs'!K31) -> 235.37936 | I7: =SUM('Model inputs'!L29,'Model inputs'!L30,'Model inputs'!L31) -> 271.71606 | ... S7: =SUM('Model inputs'!V29,'Model inputs'!V30,'Model inputs'!V31) -> 697.64198
A8: Total revenue | B8: =SUM('Model inputs'!E73,'Model inputs'!E74,'Model inputs'!E75) -> 2697.68 | C8: =SUM('Model inputs'!F73,'Model inputs'!F74,'Model inputs'!F75) -> 4481.8951 | D8: =SUM('Model inputs'!G73,'Model inputs'!G74,'Model inputs'!G75) -> 5942.2304 | E8: =SUM('Model inputs'!H73,'Model inputs'!H74,'Model inputs'!H75) -> 7466.7476 | F8: =SUM('Model inputs'!I73,'Model inputs'!I74,'Model inputs'!I75) -> 9062.2289 | G8: =SUM('Model inputs'!J73,'Model inputs'!J74,'Model inputs'!J75) -> 10735.98 | H8: =SUM('Model inputs'!K73,'Model inputs'!K74,'Model inputs'!K75) -> 12495.874 | I8: =SUM('Model inputs'!L73,'Model inputs'!L74,'Model inputs'!L75) -> 14425.355 | ... S8: =SUM('Model inputs'!V73,'Model inputs'!V74,'Model inputs'!V75) -> 36919.548
A9: Kit COGS | B9: =SUM('Model inputs'!E25,'Model inputs'!E26,'Model inputs'!E27) -> 198.72 | C9: =SUM('Model inputs'!F25,'Model inputs'!F26,'Model inputs'!F27) -> 328.51 | D9: =SUM('Model inputs'!G25,'Model inputs'!G26,'Model inputs'!G27) -> 438.26905 | E9: =SUM('Model inputs'!H25,'Model inputs'!H26,'Model inputs'!H27) -> 553.80922 | F9: =SUM('Model inputs'!I25,'Model inputs'!I26,'Model inputs'!I27) -> 675.74404 | G9: =SUM('Model inputs'!J25,'Model inputs'!J26,'Model inputs'!J27) -> 804.73919 | H9: =SUM('Model inputs'!K25,'Model inputs'!K26,'Model inputs'!K27) -> 941.51746 | I9: =SUM('Model inputs'!L25,'Model inputs'!L26,'Model inputs'!L27) -> 1086.8642 | ... S9: =SUM('Model inputs'!V25,'Model inputs'!V26,'Model inputs'!V27) -> 2790.5679
A10: Kit gross profit | B10: ='RC P&L, cash & runway'!B8-'RC P&L, cash & runway'!B9 -> 2498.96 | C10: ='RC P&L, cash & runway'!C8-'RC P&L, cash & runway'!C9 -> 4153.3851 | D10: ='RC P&L, cash & runway'!D8-'RC P&L, cash & runway'!D9 -> 5503.9613 | E10: ='RC P&L, cash & runway'!E8-'RC P&L, cash & runway'!E9 -> 6912.9384 | F10: ='RC P&L, cash & runway'!F8-'RC P&L, cash & runway'!F9 -> 8386.4849 | G10: ='RC P&L, cash & runway'!G8-'RC P&L, cash & runway'!G9 -> 9931.2413 | H10: ='RC P&L, cash & runway'!H8-'RC P&L, cash & runway'!H9 -> 11554.356 | I10: ='RC P&L, cash & runway'!I8-'RC P&L, cash & runway'!I9 -> 13338.491 | ... S10: ='RC P&L, cash & runway'!S8-'RC P&L, cash & runway'!S9 -> 34128.98
A11: Gross margin % | B11: =IFERROR('RC P&L, cash & runway'!B10/'RC P&L, cash & runway'!B8,"") -> 0.9263367 | C11: =IFERROR('RC P&L, cash & runway'!C10/'RC P&L, cash & runway'!C8,"") -> 0.92670288 | D11: =IFERROR('RC P&L, cash & runway'!D10/'RC P&L, cash & runway'!D8,"") -> 0.92624502 | E11: =IFERROR('RC P&L, cash & runway'!E10/'RC P&L, cash & runway'!E8,"") -> 0.92582993 | F11: =IFERROR('RC P&L, cash & runway'!F10/'RC P&L, cash & runway'!F8,"") -> 0.92543291 | G11: =IFERROR('RC P&L, cash & runway'!G10/'RC P&L, cash & runway'!G8,"") -> 0.92504279 | H11: =IFERROR('RC P&L, cash & runway'!H10/'RC P&L, cash & runway'!H8,"") -> 0.92465373 | I11: =IFERROR('RC P&L, cash & runway'!I10/'RC P&L, cash & runway'!I8,"") -> 0.92465598 | ... S11: =IFERROR('RC P&L, cash & runway'!S10/'RC P&L, cash & runway'!S8,"") -> 0.9244149
A12: Payment fees | B12: =SUM('Model inputs'!E63,'Model inputs'!E64,'Model inputs'!E65) -> 92.33272 | C12: =SUM('Model inputs'!F63,'Model inputs'!F64,'Model inputs'!F65) -> 188.06808 | D12: =SUM('Model inputs'!G63,'Model inputs'!G64,'Model inputs'!G65) -> 260.04299 | E12: =SUM('Model inputs'!H63,'Model inputs'!H64,'Model inputs'!H65) -> 335.16643 | F12: =SUM('Model inputs'!I63,'Model inputs'!I64,'Model inputs'!I65) -> 413.78401 | G12: =SUM('Model inputs'!J63,'Model inputs'!J64,'Model inputs'!J65) -> 496.28164 | H12: =SUM('Model inputs'!K63,'Model inputs'!K64,'Model inputs'!K65) -> 583.08838 | I12: =SUM('Model inputs'!L63,'Model inputs'!L64,'Model inputs'!L65) -> 557.28335 | ... S12: =SUM('Model inputs'!V63,'Model inputs'!V64,'Model inputs'!V65) -> 1400.7014
A13: Contribution | B13: =SUM('Model inputs'!E16,'Model inputs'!E17,'Model inputs'!E18) -> 2406.6273 | C13: =SUM('Model inputs'!F16,'Model inputs'!F17,'Model inputs'!F18) -> 3965.317 | D13: =SUM('Model inputs'!G16,'Model inputs'!G17,'Model inputs'!G18) -> 5243.9183 | E13: =SUM('Model inputs'!H16,'Model inputs'!H17,'Model inputs'!H18) -> 6577.772 | F13: =SUM('Model inputs'!I16,'Model inputs'!I17,'Model inputs'!I18) -> 7972.7009 | G13: =SUM('Model inputs'!J16,'Model inputs'!J17,'Model inputs'!J18) -> 9434.9597 | H13: =SUM('Model inputs'!K16,'Model inputs'!K17,'Model inputs'!K18) -> 10971.268 | I13: =SUM('Model inputs'!L16,'Model inputs'!L17,'Model inputs'!L18) -> 12781.208 | ... S13: =SUM('Model inputs'!V16,'Model inputs'!V17,'Model inputs'!V18) -> 32728.279
A14: Contribution margin % | B14: =IFERROR('RC P&L, cash & runway'!B13/'RC P&L, cash & runway'!B8,"") -> 0.89210999 | C14: =IFERROR('RC P&L, cash & runway'!C13/'RC P&L, cash & runway'!C8,"") -> 0.88474115 | D14: =IFERROR('RC P&L, cash & runway'!D13/'RC P&L, cash & runway'!D8,"") -> 0.88248318 | E14: =IFERROR('RC P&L, cash & runway'!E13/'RC P&L, cash & runway'!E8,"") -> 0.88094205 | F14: =IFERROR('RC P&L, cash & runway'!F13/'RC P&L, cash & runway'!F8,"") -> 0.87977262 | G14: =IFERROR('RC P&L, cash & runway'!G13/'RC P&L, cash & runway'!G8,"") -> 0.87881677 | H14: =IFERROR('RC P&L, cash & runway'!H13/'RC P&L, cash & runway'!H8,"") -> 0.87799126 | I14: =IFERROR('RC P&L, cash & runway'!I13/'RC P&L, cash & runway'!I8,"") -> 0.88602377 | ... S14: =IFERROR('RC P&L, cash & runway'!S13/'RC P&L, cash & runway'!S8,"") -> 0.88647561
A15: Opex | B15: =SUM('Model inputs'!E35,'Model inputs'!E36,'Model inputs'!E37,'Model inputs'!E38,'Model inputs'!E39,'Model inputs'!E40,'Model inputs'!E41,'Model inputs'!E42,'Model inputs'!E43,'Model inputs'!E44,'Model inputs'!E45) -> 5245 | C15: =SUM('Model inputs'!F35,'Model inputs'!F36,'Model inputs'!F37,'Model inputs'!F38,'Model inputs'!F39,'Model inputs'!F40,'Model inputs'!F41,'Model inputs'!F42,'Model inputs'!F43,'Model inputs'!F44,'Model inputs'!F45) -> 5595 | D15: =SUM('Model inputs'!G35,'Model inputs'!G36,'Model inputs'!G37,'Model inputs'!G38,'Model inputs'!G39,'Model inputs'!G40,'Model inputs'!G41,'Model inputs'!G42,'Model inputs'!G43,'Model inputs'!G44,'Model inputs'!G45) -> 5595 | E15: =SUM('Model inputs'!H35,'Model inputs'!H36,'Model inputs'!H37,'Model inputs'!H38,'Model inputs'!H39,'Model inputs'!H40,'Model inputs'!H41,'Model inputs'!H42,'Model inputs'!H43,'Model inputs'!H44,'Model inputs'!H45) -> 7245 | F15: =SUM('Model inputs'!I35,'Model inputs'!I36,'Model inputs'!I37,'Model inputs'!I38,'Model inputs'!I39,'Model inputs'!I40,'Model inputs'!I41,'Model inputs'!I42,'Model inputs'!I43,'Model inputs'!I44,'Model inputs'!I45) -> 7445 | G15: =SUM('Model inputs'!J35,'Model inputs'!J36,'Model inputs'!J37,'Model inputs'!J38,'Model inputs'!J39,'Model inputs'!J40,'Model inputs'!J41,'Model inputs'!J42,'Model inputs'!J43,'Model inputs'!J44,'Model inputs'!J45) -> 7445 | H15: =SUM('Model inputs'!K35,'Model inputs'!K36,'Model inputs'!K37,'Model inputs'!K38,'Model inputs'!K39,'Model inputs'!K40,'Model inputs'!K41,'Model inputs'!K42,'Model inputs'!K43,'Model inputs'!K44,'Model inputs'!K45) -> 11445 | I15: =SUM('Model inputs'!L35,'Model inputs'!L36,'Model inputs'!L37,'Model inputs'!L38,'Model inputs'!L39,'Model inputs'!L40,'Model inputs'!L41,'Model inputs'!L42,'Model inputs'!L43,'Model inputs'!L44,'Model inputs'!L45) -> 11445 | ... S15: =SUM('Model inputs'!V35,'Model inputs'!V36,'Model inputs'!V37,'Model inputs'!V38,'Model inputs'!V39,'Model inputs'!V40,'Model inputs'!V41,'Model inputs'!V42,'Model inputs'!V43,'Model inputs'!V44,'Model inputs'!V45) -> 11445
A16: Net income | B16: ='RC P&L, cash & runway'!B13-'RC P&L, cash & runway'!B15 -> -2838.3727 | C16: ='RC P&L, cash & runway'!C13-'RC P&L, cash & runway'!C15 -> -1629.683 | D16: ='RC P&L, cash & runway'!D13-'RC P&L, cash & runway'!D15 -> -351.08167 | E16: ='RC P&L, cash & runway'!E13-'RC P&L, cash & runway'!E15 -> -667.22802 | F16: ='RC P&L, cash & runway'!F13-'RC P&L, cash & runway'!F15 -> 527.70086 | G16: ='RC P&L, cash & runway'!G13-'RC P&L, cash & runway'!G15 -> 1989.9597 | H16: ='RC P&L, cash & runway'!H13-'RC P&L, cash & runway'!H15 -> -473.73205 | I16: ='RC P&L, cash & runway'!I13-'RC P&L, cash & runway'!I15 -> 1336.2079 | ... S16: ='RC P&L, cash & runway'!S13-'RC P&L, cash & runway'!S15 -> 21283.279
A18: Cash collected | B18: =SUM('Model inputs'!E10,'Model inputs'!E11,'Model inputs'!E12) -> 2697.68 | C18: =SUM('Model inputs'!F10,'Model inputs'!F11,'Model inputs'!F12) -> 5606.7786 | D18: =SUM('Model inputs'!G10,'Model inputs'!G11,'Model inputs'!G12) -> 7825.4376 | E18: =SUM('Model inputs'!H10,'Model inputs'!H11,'Model inputs'!H12) -> 10146.446 | F18: =SUM('Model inputs'!I10,'Model inputs'!I11,'Model inputs'!I12) -> 12580.773 | G18: =SUM('Model inputs'!J10,'Model inputs'!J11,'Model inputs'!J12) -> 15140.751 | H18: =SUM('Model inputs'!K10,'Model inputs'!K11,'Model inputs'!K12) -> 17840.171 | I18: =SUM('Model inputs'!L10,'Model inputs'!L11,'Model inputs'!L12) -> 16646.247 | ... S18: =SUM('Model inputs'!V10,'Model inputs'!V11,'Model inputs'!V12) -> 42234.94
A19: Opex cash paid | B19: =SUM('Model inputs'!E47,'Model inputs'!E48,'Model inputs'!E49,'Model inputs'!E50,'Model inputs'!E51,'Model inputs'!E52,'Model inputs'!E53,'Model inputs'!E54,'Model inputs'!E55,'Model inputs'!E56,'Model inputs'!E57) -> 9370 | C19: =SUM('Model inputs'!F47,'Model inputs'!F48,'Model inputs'!F49,'Model inputs'!F50,'Model inputs'!F51,'Model inputs'!F52,'Model inputs'!F53,'Model inputs'!F54,'Model inputs'!F55,'Model inputs'!F56,'Model inputs'!F57) -> 5220 | D19: =SUM('Model inputs'!G47,'Model inputs'!G48,'Model inputs'!G49,'Model inputs'!G50,'Model inputs'!G51,'Model inputs'!G52,'Model inputs'!G53,'Model inputs'!G54,'Model inputs'!G55,'Model inputs'!G56,'Model inputs'!G57) -> 5220 | E19: =SUM('Model inputs'!H47,'Model inputs'!H48,'Model inputs'!H49,'Model inputs'!H50,'Model inputs'!H51,'Model inputs'!H52,'Model inputs'!H53,'Model inputs'!H54,'Model inputs'!H55,'Model inputs'!H56,'Model inputs'!H57) -> 6870 | F19: =SUM('Model inputs'!I47,'Model inputs'!I48,'Model inputs'!I49,'Model inputs'!I50,'Model inputs'!I51,'Model inputs'!I52,'Model inputs'!I53,'Model inputs'!I54,'Model inputs'!I55,'Model inputs'!I56,'Model inputs'!I57) -> 7070 | G19: =SUM('Model inputs'!J47,'Model inputs'!J48,'Model inputs'!J49,'Model inputs'!J50,'Model inputs'!J51,'Model inputs'!J52,'Model inputs'!J53,'Model inputs'!J54,'Model inputs'!J55,'Model inputs'!J56,'Model inputs'!J57) -> 7070 | H19: =SUM('Model inputs'!K47,'Model inputs'!K48,'Model inputs'!K49,'Model inputs'!K50,'Model inputs'!K51,'Model inputs'!K52,'Model inputs'!K53,'Model inputs'!K54,'Model inputs'!K55,'Model inputs'!K56,'Model inputs'!K57) -> 11070 | I19: =SUM('Model inputs'!L47,'Model inputs'!L48,'Model inputs'!L49,'Model inputs'!L50,'Model inputs'!L51,'Model inputs'!L52,'Model inputs'!L53,'Model inputs'!L54,'Model inputs'!L55,'Model inputs'!L56,'Model inputs'!L57) -> 11070 | ... S19: =SUM('Model inputs'!V47,'Model inputs'!V48,'Model inputs'!V49,'Model inputs'!V50,'Model inputs'!V51,'Model inputs'!V52,'Model inputs'!V53,'Model inputs'!V54,'Model inputs'!V55,'Model inputs'!V56,'Model inputs'!V57) -> 11070
A20: Equity raised | B20: =IF(IF(IF(IFERROR(IF(ISERROR('Model inputs'!B8=1),'Model inputs'!B8=1,IF('Model inputs'!B8="","",'Model inputs'!B8=1))=FALSE,FALSE),FALSE,IF(IFERROR('Model inputs'!B358=FALSE,FALSE),FALSE,IF(IFERROR('Model inputs'!B359=FALSE,FALSE),FALSE,IF(OR(IF(ISERROR('Model inputs'!B8=1),'Model inputs'!B8=1,IF('Model inputs'!B8="","",'Model inputs'!B8=1))="",'Model inputs'!B358="",'Model inputs'!B359=""),"",AND(IF(ISERROR('Model inputs'!B8=1),'Model inputs'!B8=1,IF('Model inputs'!B8="","",'Model inputs'!B8=1)),'Model inputs'!B358,'Model inputs'!B359)))))="",FALSE,IF(IFERROR(IF(ISERROR('Model inputs'!B8=1),'Model inputs'!B8=1,IF('Model inputs'!B8="","",'Model inputs'!B8=1))=FALSE,FALSE),FALSE,IF(IFERROR('Model inputs'!B358=FALSE,FALSE),FALSE,IF(IFERROR('Model inputs'!B359=FALSE,FALSE),FALSE,IF(OR(IF(ISERROR('Model inputs'!B8=1),'Model inputs'!B8=1,IF('Model inputs'!B8="","",'Model inputs'!B8=1))="",'Model inputs'!B358="",'Model inputs'!B359=""),"",AND(IF(ISERROR('Model inputs'!B8=1),'Model inputs'!B8=1,IF('Model inputs'!B8="","",'Model inputs'!B8=1)),'Model inputs'!B358,'Model inputs'!B359)))))),IF('Model inputs'!B6="","",'Model inputs'!B6),0) -> 0 | C20: =IF(IF(IF(IFERROR(IF(ISERROR('Model inputs'!B8=1),'Model inputs'!B8=1,IF('Model inputs'!B8="","",'Model inputs'!B8=1))=FALSE,FALSE),FALSE,IF(IFERROR('Model inputs'!B360=FALSE,FALSE),FALSE,IF(IFERROR('Model inputs'!B361=FALSE,FALSE),FALSE,IF(OR(IF(ISERROR('Model inputs'!B8=1),'Model inputs'!B8=1,IF('Model inputs'!B8="","",'Model inputs'!B8=1))="",'Model inputs'!B360="",'Model inputs'!B361=""),"",AND(IF(ISERROR('Model inputs'!B8=1),'Model inputs'!B8=1,IF('Model inputs'!B8="","",'Model inputs'!B8=1)),'Model inputs'!B360,'Model inputs'!B361)))))="",FALSE,IF(IFERROR(IF(ISERROR('Model inputs'!B8=1),'Model inputs'!B8=1,IF('Model inputs'!B8="","",'Model inputs'!B8=1))=FALSE,FALSE),FALSE,IF(IFERROR('Model inputs'!B360=FALSE,FALSE),FALSE,IF(IFERROR('Model inputs'!B361=FALSE,FALSE),FALSE,IF(OR(IF(ISERROR('Model inputs'!B8=1),'Model inputs'!B8=1,IF('Model inputs'!B8="","",'Model inputs'!B8=1))="",'Model inputs'!B360="",'Model inputs'!B361=""),"",AND(IF(ISERROR('Model inputs'!B8=1),'Model inputs'!B8=1,IF('Model inputs'!B8="","",'Model inputs'!B8=1)),'Model inputs'!B360,'Model inputs'!B361)))))),IF('Model inputs'!B6="","",'Model inputs'!B6),0) -> 0 | D20: =IF(IF(IF(IFERROR(IF(ISERROR('Model inputs'!B8=1),'Model inputs'!B8=1,IF('Model inputs'!B8="","",'Model inputs'!B8=1))=FALSE,FALSE),FALSE,IF(IFERROR('Model inputs'!B362=FALSE,FALSE),FALSE,IF(IFERROR('Model inputs'!B363=FALSE,FALSE),FALSE,IF(OR(IF(ISERROR('Model inputs'!B8=1),'Model inputs'!B8=1,IF('Model inputs'!B8="","",'Model inputs'!B8=1))="",'Model inputs'!B362="",'Model inputs'!B363=""),"",AND(IF(ISERROR('Model inputs'!B8=1),'Model inputs'!B8=1,IF('Model inputs'!B8="","",'Model inputs'!B8=1)),'Model inputs'!B362,'Model inputs'!B363)))))="",FALSE,IF(IFERROR(IF(ISERROR('Model inputs'!B8=1),'Model inputs'!B8=1,IF('Model inputs'!B8="","",'Model inputs'!B8=1))=FALSE,FALSE),FALSE,IF(IFERROR('Model inputs'!B362=FALSE,FALSE),FALSE,IF(IFERROR('Model inputs'!B363=FALSE,FALSE),FALSE,IF(OR(IF(ISERROR('Model inputs'!B8=1),'Model inputs'!B8=1,IF('Model inputs'!B8="","",'Model inputs'!B8=1))="",'Model inputs'!B362="",'Model inputs'!B363=""),"",AND(IF(ISERROR('Model inputs'!B8=1),'Model inputs'!B8=1,IF('Model inputs'!B8="","",'Model inputs'!B8=1)),'Model inputs'!B362,'Model inputs'!B363)))))),IF('Model inputs'!B6="","",'Model inputs'!B6),0) -> 0 | E20: =IF(IF(IF(IFERROR(IF(ISERROR('Model inputs'!B8=1),'Model inputs'!B8=1,IF('Model inputs'!B8="","",'Model inputs'!B8=1))=FALSE,FALSE),FALSE,IF(IFERROR('Model inputs'!B364=FALSE,FALSE),FALSE,IF(IFERROR('Model inputs'!B365=FALSE,FALSE),FALSE,IF(OR(IF(ISERROR('Model inputs'!B8=1),'Model inputs'!B8=1,IF('Model inputs'!B8="","",'Model inputs'!B8=1))="",'Model inputs'!B364="",'Model inputs'!B365=""),"",AND(IF(ISERROR('Model inputs'!B8=1),'Model inputs'!B8=1,IF('Model inputs'!B8="","",'Model inputs'!B8=1)),'Model inputs'!B364,'Model inputs'!B365)))))="",FALSE,IF(IFERROR(IF(ISERROR('Model inputs'!B8=1),'Model inputs'!B8=1,IF('Model inputs'!B8="","",'Model inputs'!B8=1))=FALSE,FALSE),FALSE,IF(IFERROR('Model inputs'!B364=FALSE,FALSE),FALSE,IF(IFERROR('Model inputs'!B365=FALSE,FALSE),FALSE,IF(OR(IF(ISERROR('Model inputs'!B8=1),'Model inputs'!B8=1,IF('Model inputs'!B8="","",'Model inputs'!B8=1))="",'Model inputs'!B364="",'Model inputs'!B365=""),"",AND(IF(ISERROR('Model inputs'!B8=1),'Model inputs'!B8=1,IF('Model inputs'!B8="","",'Model inputs'!B8=1)),'Model inputs'!B364,'Model inputs'!B365)))))),IF('Model inputs'!B6="","",'Model inputs'!B6),0) -> 0 | F20: =IF(IF(IF(IFERROR(IF(ISERROR('Model inputs'!B8=1),'Model inputs'!B8=1,IF('Model inputs'!B8="","",'Model inputs'!B8=1))=FALSE,FALSE),FALSE,IF(IFERROR('Model inputs'!B366=FALSE,FALSE),FALSE,IF(IFERROR('Model inputs'!B367=FALSE,FALSE),FALSE,IF(OR(IF(ISERROR('Model inputs'!B8=1),'Model inputs'!B8=1,IF('Model inputs'!B8="","",'Model inputs'!B8=1))="",'Model inputs'!B366="",'Model inputs'!B367=""),"",AND(IF(ISERROR('Model inputs'!B8=1),'Model inputs'!B8=1,IF('Model inputs'!B8="","",'Model inputs'!B8=1)),'Model inputs'!B366,'Model inputs'!B367)))))="",FALSE,IF(IFERROR(IF(ISERROR('Model inputs'!B8=1),'Model inputs'!B8=1,IF('Model inputs'!B8="","",'Model inputs'!B8=1))=FALSE,FALSE),FALSE,IF(IFERROR('Model inputs'!B366=FALSE,FALSE),FALSE,IF(IFERROR('Model inputs'!B367=FALSE,FALSE),FALSE,IF(OR(IF(ISERROR('Model inputs'!B8=1),'Model inputs'!B8=1,IF('Model inputs'!B8="","",'Model inputs'!B8=1))="",'Model inputs'!B366="",'Model inputs'!B367=""),"",AND(IF(ISERROR('Model inputs'!B8=1),'Model inputs'!B8=1,IF('Model inputs'!B8="","",'Model inputs'!B8=1)),'Model inputs'!B366,'Model inputs'!B367)))))),IF('Model inputs'!B6="","",'Model inputs'!B6),0) -> 0 | G20: =IF(IF(IF(IFERROR(IF(ISERROR('Model inputs'!B8=1),'Model inputs'!B8=1,IF('Model inputs'!B8="","",'Model inputs'!B8=1))=FALSE,FALSE),FALSE,IF(IFERROR('Model inputs'!B368=FALSE,FALSE),FALSE,IF(IFERROR('Model inputs'!B369=FALSE,FALSE),FALSE,IF(OR(IF(ISERROR('Model inputs'!B8=1),'Model inputs'!B8=1,IF('Model inputs'!B8="","",'Model inputs'!B8=1))="",'Model inputs'!B368="",'Model inputs'!B369=""),"",AND(IF(ISERROR('Model inputs'!B8=1),'Model inputs'!B8=1,IF('Model inputs'!B8="","",'Model inputs'!B8=1)),'Model inputs'!B368,'Model inputs'!B369)))))="",FALSE,IF(IFERROR(IF(ISERROR('Model inputs'!B8=1),'Model inputs'!B8=1,IF('Model inputs'!B8="","",'Model inputs'!B8=1))=FALSE,FALSE),FALSE,IF(IFERROR('Model inputs'!B368=FALSE,FALSE),FALSE,IF(IFERROR('Model inputs'!B369=FALSE,FALSE),FALSE,IF(OR(IF(ISERROR('Model inputs'!B8=1),'Model inputs'!B8=1,IF('Model inputs'!B8="","",'Model inputs'!B8=1))="",'Model inputs'!B368="",'Model inputs'!B369=""),"",AND(IF(ISERROR('Model inputs'!B8=1),'Model inputs'!B8=1,IF('Model inputs'!B8="","",'Model inputs'!B8=1)),'Model inputs'!B368,'Model inputs'!B369)))))),IF('Model inputs'!B6="","",'Model inputs'!B6),0) -> 0 | H20: =IF(IF(IF(IFERROR(IF(ISERROR('Model inputs'!B8=1),'Model inputs'!B8=1,IF('Model inputs'!B8="","",'Model inputs'!B8=1))=FALSE,FALSE),FALSE,IF(IFERROR('Model inputs'!B370=FALSE,FALSE),FALSE,IF(IFERROR('Model inputs'!B371=FALSE,FALSE),FALSE,IF(OR(IF(ISERROR('Model inputs'!B8=1),'Model inputs'!B8=1,IF('Model inputs'!B8="","",'Model inputs'!B8=1))="",'Model inputs'!B370="",'Model inputs'!B371=""),"",AND(IF(ISERROR('Model inputs'!B8=1),'Model inputs'!B8=1,IF('Model inputs'!B8="","",'Model inputs'!B8=1)),'Model inputs'!B370,'Model inputs'!B371)))))="",FALSE,IF(IFERROR(IF(ISERROR('Model inputs'!B8=1),'Model inputs'!B8=1,IF('Model inputs'!B8="","",'Model inputs'!B8=1))=FALSE,FALSE),FALSE,IF(IFERROR('Model inputs'!B370=FALSE,FALSE),FALSE,IF(IFERROR('Model inputs'!B371=FALSE,FALSE),FALSE,IF(OR(IF(ISERROR('Model inputs'!B8=1),'Model inputs'!B8=1,IF('Model inputs'!B8="","",'Model inputs'!B8=1))="",'Model inputs'!B370="",'Model inputs'!B371=""),"",AND(IF(ISERROR('Model inputs'!B8=1),'Model inputs'!B8=1,IF('Model inputs'!B8="","",'Model inputs'!B8=1)),'Model inputs'!B370,'Model inputs'!B371)))))),IF('Model inputs'!B6="","",'Model inputs'!B6),0) -> 0 | I20: =IF(IF(IF(IFERROR(IF(ISERROR('Model inputs'!B8=1),'Model inputs'!B8=1,IF('Model inputs'!B8="","",'Model inputs'!B8=1))=FALSE,FALSE),FALSE,IF(IFERROR('Model inputs'!B372=FALSE,FALSE),FALSE,IF(IFERROR('Model inputs'!B373=FALSE,FALSE),FALSE,IF(OR(IF(ISERROR('Model inputs'!B8=1),'Model inputs'!B8=1,IF('Model inputs'!B8="","",'Model inputs'!B8=1))="",'Model inputs'!B372="",'Model inputs'!B373=""),"",AND(IF(ISERROR('Model inputs'!B8=1),'Model inputs'!B8=1,IF('Model inputs'!B8="","",'Model inputs'!B8=1)),'Model inputs'!B372,'Model inputs'!B373)))))="",FALSE,IF(IFERROR(IF(ISERROR('Model inputs'!B8=1),'Model inputs'!B8=1,IF('Model inputs'!B8="","",'Model inputs'!B8=1))=FALSE,FALSE),FALSE,IF(IFERROR('Model inputs'!B372=FALSE,FALSE),FALSE,IF(IFERROR('Model inputs'!B373=FALSE,FALSE),FALSE,IF(OR(IF(ISERROR('Model inputs'!B8=1),'Model inputs'!B8=1,IF('Model inputs'!B8="","",'Model inputs'!B8=1))="",'Model inputs'!B372="",'Model inputs'!B373=""),"",AND(IF(ISERROR('Model inputs'!B8=1),'Model inputs'!B8=1,IF('Model inputs'!B8="","",'Model inputs'!B8=1)),'Model inputs'!B372,'Model inputs'!B373)))))),IF('Model inputs'!B6="","",'Model inputs'!B6),0) -> 0 | J20: =IF(IF(IF(IFERROR(IF(ISERROR('Model inputs'!B8=1),'Model inputs'!B8=1,IF('Model inputs'!B8="","",'Model inputs'!B8=1))=FALSE,FALSE),FALSE,IF(IFERROR('Model inputs'!B374=FALSE,FALSE),FALSE,IF(IFERROR('Model inputs'!B375=FALSE,FALSE),FALSE,IF(OR(IF(ISERROR('Model inputs'!B8=1),'Model inputs'!B8=1,IF('Model inputs'!B8="","",'Model inputs'!B8=1))="",'Model inputs'!B374="",'Model inputs'!B375=""),"",AND(IF(ISERROR('Model inputs'!B8=1),'Model inputs'!B8=1,IF('Model inputs'!B8="","",'Model inputs'!B8=1)),'Model inputs'!B374,'Model inputs'!B375)))))="",FALSE,IF(IFERROR(IF(ISERROR('Model inputs'!B8=1),'Model inputs'!B8=1,IF('Model inputs'!B8="","",'Model inputs'!B8=1))=FALSE,FALSE),FALSE,IF(IFERROR('Model inputs'!B374=FALSE,FALSE),FALSE,IF(IFERROR('Model inputs'!B375=FALSE,FALSE),FALSE,IF(OR(IF(ISERROR('Model inputs'!B8=1),'Model inputs'!B8=1,IF('Model inputs'!B8="","",'Model inputs'!B8=1))="",'Model inputs'!B374="",'Model inputs'!B375=""),"",AND(IF(ISERROR('Model inputs'!B8=1),'Model inputs'!B8=1,IF('Model inputs'!B8="","",'Model inputs'!B8=1)),'Model inputs'!B374,'Model inputs'!B375)))))),IF('Model inputs'!B6="","",'Model inputs'!B6),0) -> 0 | K20: =IF(IF(IF(IFERROR(IF(ISERROR('Model inputs'!B8=1),'Model inputs'!B8=1,IF('Model inputs'!B8="","",'Model inputs'!B8=1))=FALSE,FALSE),FALSE,IF(IFERROR('Model inputs'!B376=FALSE,FALSE),FALSE,IF(IFERROR('Model inputs'!B377=FALSE,FALSE),FALSE,IF(OR(IF(ISERROR('Model inputs'!B8=1),'Model inputs'!B8=1,IF('Model inputs'!B8="","",'Model inputs'!B8=1))="",'Model inputs'!B376="",'Model inputs'!B377=""),"",AND(IF(ISERROR('Model inputs'!B8=1),'Model inputs'!B8=1,IF('Model inputs'!B8="","",'Model inputs'!B8=1)),'Model inputs'!B376,'Model inputs'!B377)))))="",FALSE,IF(IFERROR(IF(ISERROR('Model inputs'!B8=1),'Model inputs'!B8=1,IF('Model inputs'!B8="","",'Model inputs'!B8=1))=FALSE,FALSE),FALSE,IF(IFERROR('Model inputs'!B376=FALSE,FALSE),FALSE,IF(IFERROR('Model inputs'!B377=FALSE,FALSE),FALSE,IF(OR(IF(ISERROR('Model inputs'!B8=1),'Model inputs'!B8=1,IF('Model inputs'!B8="","",'Model inputs'!B8=1))="",'Model inputs'!B376="",'Model inputs'!B377=""),"",AND(IF(ISERROR('Model inputs'!B8=1),'Model inputs'!B8=1,IF('Model inputs'!B8="","",'Model inputs'!B8=1)),'Model inputs'!B376,'Model inputs'!B377)))))),IF('Model inputs'!B6="","",'Model inputs'!B6),0) -> 0 | L20: =IF(IF(IF(IFERROR(IF(ISERROR('Model inputs'!B8=1),'Model inputs'!B8=1,IF('Model inputs'!B8="","",'Model inputs'!B8=1))=FALSE,FALSE),FALSE,IF(IFERROR('Model inputs'!B378=FALSE,FALSE),FALSE,IF(IFERROR('Model inputs'!B379=FALSE,FALSE),FALSE,IF(OR(IF(ISERROR('Model inputs'!B8=1),'Model inputs'!B8=1,IF('Model inputs'!B8="","",'Model inputs'!B8=1))="",'Model inputs'!B378="",'Model inputs'!B379=""),"",AND(IF(ISERROR('Model inputs'!B8=1),'Model inputs'!B8=1,IF('Model inputs'!B8="","",'Model inputs'!B8=1)),'Model inputs'!B378,'Model inputs'!B379)))))="",FALSE,IF(IFERROR(IF(ISERROR('Model inputs'!B8=1),'Model inputs'!B8=1,IF('Model inputs'!B8="","",'Model inputs'!B8=1))=FALSE,FALSE),FALSE,IF(IFERROR('Model inputs'!B378=FALSE,FALSE),FALSE,IF(IFERROR('Model inputs'!B379=FALSE,FALSE),FALSE,IF(OR(IF(ISERROR('Model inputs'!B8=1),'Model inputs'!B8=1,IF('Model inputs'!B8="","",'Model inputs'!B8=1))="",'Model inputs'!B378="",'Model inputs'!B379=""),"",AND(IF(ISERROR('Model inputs'!B8=1),'Model inputs'!B8=1,IF('Model inputs'!B8="","",'Model inputs'!B8=1)),'Model inputs'!B378,'Model inputs'!B379)))))),IF('Model inputs'!B6="","",'Model inputs'!B6),0) -> 0 | M20: =IF(IF(IF(IFERROR(IF(ISERROR('Model inputs'!B8=1),'Model inputs'!B8=1,IF('Model inputs'!B8="","",'Model inputs'!B8=1))=FALSE,FALSE),FALSE,IF(IFERROR('Model inputs'!B380=FALSE,FALSE),FALSE,IF(IFERROR('Model inputs'!B381=FALSE,FALSE),FALSE,IF(OR(IF(ISERROR('Model inputs'!B8=1),'Model inputs'!B8=1,IF('Model inputs'!B8="","",'Model inputs'!B8=1))="",'Model inputs'!B380="",'Model inputs'!B381=""),"",AND(IF(ISERROR('Model inputs'!B8=1),'Model inputs'!B8=1,IF('Model inputs'!B8="","",'Model inputs'!B8=1)),'Model inputs'!B380,'Model inputs'!B381)))))="",FALSE,IF(IFERROR(IF(ISERROR('Model inputs'!B8=1),'Model inputs'!B8=1,IF('Model inputs'!B8="","",'Model inputs'!B8=1))=FALSE,FALSE),FALSE,IF(IFERROR('Model inputs'!B380=FALSE,FALSE),FALSE,IF(IFERROR('Model inputs'!B381=FALSE,FALSE),FALSE,IF(OR(IF(ISERROR('Model inputs'!B8=1),'Model inputs'!B8=1,IF('Model inputs'!B8="","",'Model inputs'!B8=1))="",'Model inputs'!B380="",'Model inputs'!B381=""),"",AND(IF(ISERROR('Model inputs'!B8=1),'Model inputs'!B8=1,IF('Model inputs'!B8="","",'Model inputs'!B8=1)),'Model inputs'!B380,'Model inputs'!B381)))))),IF('Model inputs'!B6="","",'Model inputs'!B6),0) -> 0 | N20: =IF(IF(IF(IFERROR(IF(ISERROR('Model inputs'!B8=1),'Model inputs'!B8=1,IF('Model inputs'!B8="","",'Model inputs'!B8=1))=FALSE,FALSE),FALSE,IF(IFERROR('Model inputs'!B382=FALSE,FALSE),FALSE,IF(IFERROR('Model inputs'!B383=FALSE,FALSE),FALSE,IF(OR(IF(ISERROR('Model inputs'!B8=1),'Model inputs'!B8=1,IF('Model inputs'!B8="","",'Model inputs'!B8=1))="",'Model inputs'!B382="",'Model inputs'!B383=""),"",AND(IF(ISERROR('Model inputs'!B8=1),'Model inputs'!B8=1,IF('Model inputs'!B8="","",'Model inputs'!B8=1)),'Model inputs'!B382,'Model inputs'!B383)))))="",FALSE,IF(IFERROR(IF(ISERROR('Model inputs'!B8=1),'Model inputs'!B8=1,IF('Model inputs'!B8="","",'Model inputs'!B8=1))=FALSE,FALSE),FALSE,IF(IFERROR('Model inputs'!B382=FALSE,FALSE),FALSE,IF(IFERROR('Model inputs'!B383=FALSE,FALSE),FALSE,IF(OR(IF(ISERROR('Model inputs'!B8=1),'Model inputs'!B8=1,IF('Model inputs'!B8="","",'Model inputs'!B8=1))="",'Model inputs'!B382="",'Model inputs'!B383=""),"",AND(IF(ISERROR('Model inputs'!B8=1),'Model inputs'!B8=1,IF('Model inputs'!B8="","",'Model inputs'!B8=1)),'Model inputs'!B382,'Model inputs'!B383)))))),IF('Model inputs'!B6="","",'Model inputs'!B6),0) -> 0 | O20: =IF(IF(IF(IFERROR(IF(ISERROR('Model inputs'!B8=1),'Model inputs'!B8=1,IF('Model inputs'!B8="","",'Model inputs'!B8=1))=FALSE,FALSE),FALSE,IF(IFERROR('Model inputs'!B384=FALSE,FALSE),FALSE,IF(IFERROR('Model inputs'!B385=FALSE,FALSE),FALSE,IF(OR(IF(ISERROR('Model inputs'!B8=1),'Model inputs'!B8=1,IF('Model inputs'!B8="","",'Model inputs'!B8=1))="",'Model inputs'!B384="",'Model inputs'!B385=""),"",AND(IF(ISERROR('Model inputs'!B8=1),'Model inputs'!B8=1,IF('Model inputs'!B8="","",'Model inputs'!B8=1)),'Model inputs'!B384,'Model inputs'!B385)))))="",FALSE,IF(IFERROR(IF(ISERROR('Model inputs'!B8=1),'Model inputs'!B8=1,IF('Model inputs'!B8="","",'Model inputs'!B8=1))=FALSE,FALSE),FALSE,IF(IFERROR('Model inputs'!B384=FALSE,FALSE),FALSE,IF(IFERROR('Model inputs'!B385=FALSE,FALSE),FALSE,IF(OR(IF(ISERROR('Model inputs'!B8=1),'Model inputs'!B8=1,IF('Model inputs'!B8="","",'Model inputs'!B8=1))="",'Model inputs'!B384="",'Model inputs'!B385=""),"",AND(IF(ISERROR('Model inputs'!B8=1),'Model inputs'!B8=1,IF('Model inputs'!B8="","",'Model inputs'!B8=1)),'Model inputs'!B384,'Model inputs'!B385)))))),IF('Model inputs'!B6="","",'Model inputs'!B6),0) -> 0 | P20: =IF(IF(IF(IFERROR(IF(ISERROR('Model inputs'!B8=1),'Model inputs'!B8=1,IF('Model inputs'!B8="","",'Model inputs'!B8=1))=FALSE,FALSE),FALSE,IF(IFERROR('Model inputs'!B386=FALSE,FALSE),FALSE,IF(IFERROR('Model inputs'!B387=FALSE,FALSE),FALSE,IF(OR(IF(ISERROR('Model inputs'!B8=1),'Model inputs'!B8=1,IF('Model inputs'!B8="","",'Model inputs'!B8=1))="",'Model inputs'!B386="",'Model inputs'!B387=""),"",AND(IF(ISERROR('Model inputs'!B8=1),'Model inputs'!B8=1,IF('Model inputs'!B8="","",'Model inputs'!B8=1)),'Model inputs'!B386,'Model inputs'!B387)))))="",FALSE,IF(IFERROR(IF(ISERROR('Model inputs'!B8=1),'Model inputs'!B8=1,IF('Model inputs'!B8="","",'Model inputs'!B8=1))=FALSE,FALSE),FALSE,IF(IFERROR('Model inputs'!B386=FALSE,FALSE),FALSE,IF(IFERROR('Model inputs'!B387=FALSE,FALSE),FALSE,IF(OR(IF(ISERROR('Model inputs'!B8=1),'Model inputs'!B8=1,IF('Model inputs'!B8="","",'Model inputs'!B8=1))="",'Model inputs'!B386="",'Model inputs'!B387=""),"",AND(IF(ISERROR('Model inputs'!B8=1),'Model inputs'!B8=1,IF('Model inputs'!B8="","",'Model inputs'!B8=1)),'Model inputs'!B386,'Model inputs'!B387)))))),IF('Model inputs'!B6="","",'Model inputs'!B6),0) -> 0 | Q20: =IF(IF(IF(IFERROR(IF(ISERROR('Model inputs'!B8=1),'Model inputs'!B8=1,IF('Model inputs'!B8="","",'Model inputs'!B8=1))=FALSE,FALSE),FALSE,IF(IFERROR('Model inputs'!B388=FALSE,FALSE),FALSE,IF(IFERROR('Model inputs'!B389=FALSE,FALSE),FALSE,IF(OR(IF(ISERROR('Model inputs'!B8=1),'Model inputs'!B8=1,IF('Model inputs'!B8="","",'Model inputs'!B8=1))="",'Model inputs'!B388="",'Model inputs'!B389=""),"",AND(IF(ISERROR('Model inputs'!B8=1),'Model inputs'!B8=1,IF('Model inputs'!B8="","",'Model inputs'!B8=1)),'Model inputs'!B388,'Model inputs'!B389)))))="",FALSE,IF(IFERROR(IF(ISERROR('Model inputs'!B8=1),'Model inputs'!B8=1,IF('Model inputs'!B8="","",'Model inputs'!B8=1))=FALSE,FALSE),FALSE,IF(IFERROR('Model inputs'!B388=FALSE,FALSE),FALSE,IF(IFERROR('Model inputs'!B389=FALSE,FALSE),FALSE,IF(OR(IF(ISERROR('Model inputs'!B8=1),'Model inputs'!B8=1,IF('Model inputs'!B8="","",'Model inputs'!B8=1))="",'Model inputs'!B388="",'Model inputs'!B389=""),"",AND(IF(ISERROR('Model inputs'!B8=1),'Model inputs'!B8=1,IF('Model inputs'!B8="","",'Model inputs'!B8=1)),'Model inputs'!B388,'Model inputs'!B389)))))),IF('Model inputs'!B6="","",'Model inputs'!B6),0) -> 0 | R20: =IF(IF(IF(IFERROR(IF(ISERROR('Model inputs'!B8=1),'Model inputs'!B8=1,IF('Model inputs'!B8="","",'Model inputs'!B8=1))=FALSE,FALSE),FALSE,IF(IFERROR('Model inputs'!B390=FALSE,FALSE),FALSE,IF(IFERROR('Model inputs'!B391=FALSE,FALSE),FALSE,IF(OR(IF(ISERROR('Model inputs'!B8=1),'Model inputs'!B8=1,IF('Model inputs'!B8="","",'Model inputs'!B8=1))="",'Model inputs'!B390="",'Model inputs'!B391=""),"",AND(IF(ISERROR('Model inputs'!B8=1),'Model inputs'!B8=1,IF('Model inputs'!B8="","",'Model inputs'!B8=1)),'Model inputs'!B390,'Model inputs'!B391)))))="",FALSE,IF(IFERROR(IF(ISERROR('Model inputs'!B8=1),'Model inputs'!B8=1,IF('Model inputs'!B8="","",'Model inputs'!B8=1))=FALSE,FALSE),FALSE,IF(IFERROR('Model inputs'!B390=FALSE,FALSE),FALSE,IF(IFERROR('Model inputs'!B391=FALSE,FALSE),FALSE,IF(OR(IF(ISERROR('Model inputs'!B8=1),'Model inputs'!B8=1,IF('Model inputs'!B8="","",'Model inputs'!B8=1))="",'Model inputs'!B390="",'Model inputs'!B391=""),"",AND(IF(ISERROR('Model inputs'!B8=1),'Model inputs'!B8=1,IF('Model inputs'!B8="","",'Model inputs'!B8=1)),'Model inputs'!B390,'Model inputs'!B391)))))),IF('Model inputs'!B6="","",'Model inputs'!B6),0) -> 0 | S20: =IF(IF(IF(IFERROR(IF(ISERROR('Model inputs'!B8=1),'Model inputs'!B8=1,IF('Model inputs'!B8="","",'Model inputs'!B8=1))=FALSE,FALSE),FALSE,IF(IFERROR('Model inputs'!B392=FALSE,FALSE),FALSE,IF(IFERROR('Model inputs'!B393=FALSE,FALSE),FALSE,IF(OR(IF(ISERROR('Model inputs'!B8=1),'Model inputs'!B8=1,IF('Model inputs'!B8="","",'Model inputs'!B8=1))="",'Model inputs'!B392="",'Model inputs'!B393=""),"",AND(IF(ISERROR('Model inputs'!B8=1),'Model inputs'!B8=1,IF('Model inputs'!B8="","",'Model inputs'!B8=1)),'Model inputs'!B392,'Model inputs'!B393)))))="",FALSE,IF(IFERROR(IF(ISERROR('Model inputs'!B8=1),'Model inputs'!B8=1,IF('Model inputs'!B8="","",'Model inputs'!B8=1))=FALSE,FALSE),FALSE,IF(IFERROR('Model inputs'!B392=FALSE,FALSE),FALSE,IF(IFERROR('Model inputs'!B393=FALSE,FALSE),FALSE,IF(OR(IF(ISERROR('Model inputs'!B8=1),'Model inputs'!B8=1,IF('Model inputs'!B8="","",'Model inputs'!B8=1))="",'Model inputs'!B392="",'Model inputs'!B393=""),"",AND(IF(ISERROR('Model inputs'!B8=1),'Model inputs'!B8=1,IF('Model inputs'!B8="","",'Model inputs'!B8=1)),'Model inputs'!B392,'Model inputs'!B393)))))),IF('Model inputs'!B6="","",'Model inputs'!B6),0) -> 0
A21: Net cash change | B21: ='RC P&L, cash & runway'!B18-'RC P&L, cash & runway'!B9-'RC P&L, cash & runway'!B12-'RC P&L, cash & runway'!B19+'RC P&L, cash & runway'!B20 -> -6963.3727 | C21: ='RC P&L, cash & runway'!C18-'RC P&L, cash & runway'!C9-'RC P&L, cash & runway'!C12-'RC P&L, cash & runway'!C19+'RC P&L, cash & runway'!C20 -> -129.79946 | D21: ='RC P&L, cash & runway'!D18-'RC P&L, cash & runway'!D9-'RC P&L, cash & runway'!D12-'RC P&L, cash & runway'!D19+'RC P&L, cash & runway'!D20 -> 1907.1256 | E21: ='RC P&L, cash & runway'!E18-'RC P&L, cash & runway'!E9-'RC P&L, cash & runway'!E12-'RC P&L, cash & runway'!E19+'RC P&L, cash & runway'!E20 -> 2387.4703 | F21: ='RC P&L, cash & runway'!F18-'RC P&L, cash & runway'!F9-'RC P&L, cash & runway'!F12-'RC P&L, cash & runway'!F19+'RC P&L, cash & runway'!F20 -> 4421.2451 | G21: ='RC P&L, cash & runway'!G18-'RC P&L, cash & runway'!G9-'RC P&L, cash & runway'!G12-'RC P&L, cash & runway'!G19+'RC P&L, cash & runway'!G20 -> 6769.7302 | H21: ='RC P&L, cash & runway'!H18-'RC P&L, cash & runway'!H9-'RC P&L, cash & runway'!H12-'RC P&L, cash & runway'!H19+'RC P&L, cash & runway'!H20 -> 5245.5654 | I21: ='RC P&L, cash & runway'!I18-'RC P&L, cash & runway'!I9-'RC P&L, cash & runway'!I12-'RC P&L, cash & runway'!I19+'RC P&L, cash & runway'!I20 -> 3932.0992 | ... S21: ='RC P&L, cash & runway'!S18-'RC P&L, cash & runway'!S9-'RC P&L, cash & runway'!S12-'RC P&L, cash & runway'!S19+'RC P&L, cash & runway'!S20 -> 26973.67
A22: Cash on hand | B22: =IF(IF(IF(ISERROR('Model inputs'!E32=0),'Model inputs'!E32=0,IF('Model inputs'!E32="","",'Model inputs'!E32=0))="",FALSE,IF(ISERROR('Model inputs'!E32=0),'Model inputs'!E32=0,IF('Model inputs'!E32="","",'Model inputs'!E32=0))),'Model inputs'!B67+'RC P&L, cash & runway'!B21,'Model inputs'!D14+'RC P&L, cash & runway'!B21) -> 5036.6273 | C22: =IF(IF(IF(ISERROR('Model inputs'!F32=0),'Model inputs'!F32=0,IF('Model inputs'!F32="","",'Model inputs'!F32=0))="",FALSE,IF(ISERROR('Model inputs'!F32=0),'Model inputs'!F32=0,IF('Model inputs'!F32="","",'Model inputs'!F32=0))),'Model inputs'!B67+'RC P&L, cash & runway'!C21,'RC P&L, cash & runway'!B22+'RC P&L, cash & runway'!C21) -> 4906.8278 | D22: =IF(IF(IF(ISERROR('Model inputs'!G32=0),'Model inputs'!G32=0,IF('Model inputs'!G32="","",'Model inputs'!G32=0))="",FALSE,IF(ISERROR('Model inputs'!G32=0),'Model inputs'!G32=0,IF('Model inputs'!G32="","",'Model inputs'!G32=0))),'Model inputs'!B67+'RC P&L, cash & runway'!D21,'RC P&L, cash & runway'!C22+'RC P&L, cash & runway'!D21) -> 6813.9534 | E22: =IF(IF(IF(ISERROR('Model inputs'!H32=0),'Model inputs'!H32=0,IF('Model inputs'!H32="","",'Model inputs'!H32=0))="",FALSE,IF(ISERROR('Model inputs'!H32=0),'Model inputs'!H32=0,IF('Model inputs'!H32="","",'Model inputs'!H32=0))),'Model inputs'!B67+'RC P&L, cash & runway'!E21,'RC P&L, cash & runway'!D22+'RC P&L, cash & runway'!E21) -> 9201.4237 | F22: =IF(IF(IF(ISERROR('Model inputs'!I32=0),'Model inputs'!I32=0,IF('Model inputs'!I32="","",'Model inputs'!I32=0))="",FALSE,IF(ISERROR('Model inputs'!I32=0),'Model inputs'!I32=0,IF('Model inputs'!I32="","",'Model inputs'!I32=0))),'Model inputs'!B67+'RC P&L, cash & runway'!F21,'RC P&L, cash & runway'!E22+'RC P&L, cash & runway'!F21) -> 13622.669 | G22: =IF(IF(IF(ISERROR('Model inputs'!J32=0),'Model inputs'!J32=0,IF('Model inputs'!J32="","",'Model inputs'!J32=0))="",FALSE,IF(ISERROR('Model inputs'!J32=0),'Model inputs'!J32=0,IF('Model inputs'!J32="","",'Model inputs'!J32=0))),'Model inputs'!B67+'RC P&L, cash & runway'!G21,'RC P&L, cash & runway'!F22+'RC P&L, cash & runway'!G21) -> 20392.399 | H22: =IF(IF(IF(ISERROR('Model inputs'!K32=0),'Model inputs'!K32=0,IF('Model inputs'!K32="","",'Model inputs'!K32=0))="",FALSE,IF(ISERROR('Model inputs'!K32=0),'Model inputs'!K32=0,IF('Model inputs'!K32="","",'Model inputs'!K32=0))),'Model inputs'!B67+'RC P&L, cash & runway'!H21,'RC P&L, cash & runway'!G22+'RC P&L, cash & runway'!H21) -> 25637.964 | I22: =IF(IF(IF(ISERROR('Model inputs'!L32=0),'Model inputs'!L32=0,IF('Model inputs'!L32="","",'Model inputs'!L32=0))="",FALSE,IF(ISERROR('Model inputs'!L32=0),'Model inputs'!L32=0,IF('Model inputs'!L32="","",'Model inputs'!L32=0))),'Model inputs'!B67+'RC P&L, cash & runway'!I21,'RC P&L, cash & runway'!H22+'RC P&L, cash & runway'!I21) -> 29570.064 | J22: =IF(IF(IF(ISERROR('Model inputs'!M32=0),'Model inputs'!M32=0,IF('Model inputs'!M32="","",'Model inputs'!M32=0))="",FALSE,IF(ISERROR('Model inputs'!M32=0),'Model inputs'!M32=0,IF('Model inputs'!M32="","",'Model inputs'!M32=0))),'Model inputs'!B67+'RC P&L, cash & runway'!J21,'RC P&L, cash & runway'!I22+'RC P&L, cash & runway'!J21) -> 35383.167 | K22: =IF(IF(IF(ISERROR('Model inputs'!N32=0),'Model inputs'!N32=0,IF('Model inputs'!N32="","",'Model inputs'!N32=0))="",FALSE,IF(ISERROR('Model inputs'!N32=0),'Model inputs'!N32=0,IF('Model inputs'!N32="","",'Model inputs'!N32=0))),'Model inputs'!B67+'RC P&L, cash & runway'!K21,'RC P&L, cash & runway'!J22+'RC P&L, cash & runway'!K21) -> 42953.427 | L22: =IF(IF(IF(ISERROR('Model inputs'!O32=0),'Model inputs'!O32=0,IF('Model inputs'!O32="","",'Model inputs'!O32=0))="",FALSE,IF(ISERROR('Model inputs'!O32=0),'Model inputs'!O32=0,IF('Model inputs'!O32="","",'Model inputs'!O32=0))),'Model inputs'!B67+'RC P&L, cash & runway'!L21,'RC P&L, cash & runway'!K22+'RC P&L, cash & runway'!L21) -> 52308.118 | M22: =IF(IF(IF(ISERROR('Model inputs'!P32=0),'Model inputs'!P32=0,IF('Model inputs'!P32="","",'Model inputs'!P32=0))="",FALSE,IF(ISERROR('Model inputs'!P32=0),'Model inputs'!P32=0,IF('Model inputs'!P32="","",'Model inputs'!P32=0))),'Model inputs'!B67+'RC P&L, cash & runway'!M21,'RC P&L, cash & runway'!L22+'RC P&L, cash & runway'!M21) -> 63477.448 | N22: =IF(IF(IF(ISERROR('Model inputs'!Q32=0),'Model inputs'!Q32=0,IF('Model inputs'!Q32="","",'Model inputs'!Q32=0))="",FALSE,IF(ISERROR('Model inputs'!Q32=0),'Model inputs'!Q32=0,IF('Model inputs'!Q32="","",'Model inputs'!Q32=0))),'Model inputs'!B67+'RC P&L, cash & runway'!N21,'RC P&L, cash & runway'!M22+'RC P&L, cash & runway'!N21) -> 71994.571 | O22: =IF(IF(IF(ISERROR('Model inputs'!R32=0),'Model inputs'!R32=0,IF('Model inputs'!R32="","",'Model inputs'!R32=0))="",FALSE,IF(ISERROR('Model inputs'!R32=0),'Model inputs'!R32=0,IF('Model inputs'!R32="","",'Model inputs'!R32=0))),'Model inputs'!B67+'RC P&L, cash & runway'!O21,'RC P&L, cash & runway'!N22+'RC P&L, cash & runway'!O21) -> 87782.111 | P22: =IF(IF(IF(ISERROR('Model inputs'!S32=0),'Model inputs'!S32=0,IF('Model inputs'!S32="","",'Model inputs'!S32=0))="",FALSE,IF(ISERROR('Model inputs'!S32=0),'Model inputs'!S32=0,IF('Model inputs'!S32="","",'Model inputs'!S32=0))),'Model inputs'!B67+'RC P&L, cash & runway'!P21,'RC P&L, cash & runway'!O22+'RC P&L, cash & runway'!P21) -> 106165 | Q22: =IF(IF(IF(ISERROR('Model inputs'!T32=0),'Model inputs'!T32=0,IF('Model inputs'!T32="","",'Model inputs'!T32=0))="",FALSE,IF(ISERROR('Model inputs'!T32=0),'Model inputs'!T32=0,IF('Model inputs'!T32="","",'Model inputs'!T32=0))),'Model inputs'!B67+'RC P&L, cash & runway'!Q21,'RC P&L, cash & runway'!P22+'RC P&L, cash & runway'!Q21) -> 127268.95 | R22: =IF(IF(IF(ISERROR('Model inputs'!U32=0),'Model inputs'!U32=0,IF('Model inputs'!U32="","",'Model inputs'!U32=0))="",FALSE,IF(ISERROR('Model inputs'!U32=0),'Model inputs'!U32=0,IF('Model inputs'!U32="","",'Model inputs'!U32=0))),'Model inputs'!B67+'RC P&L, cash & runway'!R21,'RC P&L, cash & runway'!Q22+'RC P&L, cash & runway'!R21) -> 151231.95 | S22: =IF(IF(IF(ISERROR('Model inputs'!V32=0),'Model inputs'!V32=0,IF('Model inputs'!V32="","",'Model inputs'!V32=0))="",FALSE,IF(ISERROR('Model inputs'!V32=0),'Model inputs'!V32=0,IF('Model inputs'!V32="","",'Model inputs'!V32=0))),'Model inputs'!B67+'RC P&L, cash & runway'!S21,'RC P&L, cash & runway'!R22+'RC P&L, cash & runway'!S21) -> 178205.62
A23: Net burn | B23: =MAX('RC P&L, cash & runway'!B20-'RC P&L, cash & runway'!B21,0) -> 6963.3727 | C23: =MAX('RC P&L, cash & runway'!C20-'RC P&L, cash & runway'!C21,0) -> 129.79946 | D23: =MAX('RC P&L, cash & runway'!D20-'RC P&L, cash & runway'!D21,0) -> 0 | E23: =MAX('RC P&L, cash & runway'!E20-'RC P&L, cash & runway'!E21,0) -> 0 | F23: =MAX('RC P&L, cash & runway'!F20-'RC P&L, cash & runway'!F21,0) -> 0 | G23: =MAX('RC P&L, cash & runway'!G20-'RC P&L, cash & runway'!G21,0) -> 0 | H23: =MAX('RC P&L, cash & runway'!H20-'RC P&L, cash & runway'!H21,0) -> 0 | I23: =MAX('RC P&L, cash & runway'!I20-'RC P&L, cash & runway'!I21,0) -> 0 | ... S23: =MAX('RC P&L, cash & runway'!S20-'RC P&L, cash & runway'!S21,0) -> 0
A24: Runway (months) | B24: =IFERROR(IF(IF(IF(ISERROR('RC P&L, cash & runway'!B22<=0),'RC P&L, cash & runway'!B22<=0,IF('RC P&L, cash & runway'!B22="","",'RC P&L, cash & runway'!B22<=0))="",FALSE,IF(ISERROR('RC P&L, cash & runway'!B22<=0),'RC P&L, cash & runway'!B22<=0,IF('RC P&L, cash & runway'!B22="","",'RC P&L, cash & runway'!B22<=0))),0,IF(IF(IF(ISERROR('RC P&L, cash & runway'!B23>0),'RC P&L, cash & runway'!B23>0,IF('RC P&L, cash & runway'!B23="","",'RC P&L, cash & runway'!B23>0))="",FALSE,IF(ISERROR('RC P&L, cash & runway'!B23>0),'RC P&L, cash & runway'!B23>0,IF('RC P&L, cash & runway'!B23="","",'RC P&L, cash & runway'!B23>0))),'RC P&L, cash & runway'!B22/'RC P&L, cash & runway'!B23,"")),"") -> 0.72330284 | C24: =IFERROR(IF(IF(IF(ISERROR('RC P&L, cash & runway'!C22<=0),'RC P&L, cash & runway'!C22<=0,IF('RC P&L, cash & runway'!C22="","",'RC P&L, cash & runway'!C22<=0))="",FALSE,IF(ISERROR('RC P&L, cash & runway'!C22<=0),'RC P&L, cash & runway'!C22<=0,IF('RC P&L, cash & runway'!C22="","",'RC P&L, cash & runway'!C22<=0))),0,IF(IF(IF(ISERROR('RC P&L, cash & runway'!C23>0),'RC P&L, cash & runway'!C23>0,IF('RC P&L, cash & runway'!C23="","",'RC P&L, cash & runway'!C23>0))="",FALSE,IF(ISERROR('RC P&L, cash & runway'!C23>0),'RC P&L, cash & runway'!C23>0,IF('RC P&L, cash & runway'!C23="","",'RC P&L, cash & runway'!C23>0))),'RC P&L, cash & runway'!C22/'RC P&L, cash & runway'!C23,"")),"") -> 37.803147 | D24: =IFERROR(IF(IF(IF(ISERROR('RC P&L, cash & runway'!D22<=0),'RC P&L, cash & runway'!D22<=0,IF('RC P&L, cash & runway'!D22="","",'RC P&L, cash & runway'!D22<=0))="",FALSE,IF(ISERROR('RC P&L, cash & runway'!D22<=0),'RC P&L, cash & runway'!D22<=0,IF('RC P&L, cash & runway'!D22="","",'RC P&L, cash & runway'!D22<=0))),0,IF(IF(IF(ISERROR('RC P&L, cash & runway'!D23>0),'RC P&L, cash & runway'!D23>0,IF('RC P&L, cash & runway'!D23="","",'RC P&L, cash & runway'!D23>0))="",FALSE,IF(ISERROR('RC P&L, cash & runway'!D23>0),'RC P&L, cash & runway'!D23>0,IF('RC P&L, cash & runway'!D23="","",'RC P&L, cash & runway'!D23>0))),'RC P&L, cash & runway'!D22/'RC P&L, cash & runway'!D23,"")),"") | E24: =IFERROR(IF(IF(IF(ISERROR('RC P&L, cash & runway'!E22<=0),'RC P&L, cash & runway'!E22<=0,IF('RC P&L, cash & runway'!E22="","",'RC P&L, cash & runway'!E22<=0))="",FALSE,IF(ISERROR('RC P&L, cash & runway'!E22<=0),'RC P&L, cash & runway'!E22<=0,IF('RC P&L, cash & runway'!E22="","",'RC P&L, cash & runway'!E22<=0))),0,IF(IF(IF(ISERROR('RC P&L, cash & runway'!E23>0),'RC P&L, cash & runway'!E23>0,IF('RC P&L, cash & runway'!E23="","",'RC P&L, cash & runway'!E23>0))="",FALSE,IF(ISERROR('RC P&L, cash & runway'!E23>0),'RC P&L, cash & runway'!E23>0,IF('RC P&L, cash & runway'!E23="","",'RC P&L, cash & runway'!E23>0))),'RC P&L, cash & runway'!E22/'RC P&L, cash & runway'!E23,"")),"") | F24: =IFERROR(IF(IF(IF(ISERROR('RC P&L, cash & runway'!F22<=0),'RC P&L, cash & runway'!F22<=0,IF('RC P&L, cash & runway'!F22="","",'RC P&L, cash & runway'!F22<=0))="",FALSE,IF(ISERROR('RC P&L, cash & runway'!F22<=0),'RC P&L, cash & runway'!F22<=0,IF('RC P&L, cash & runway'!F22="","",'RC P&L, cash & runway'!F22<=0))),0,IF(IF(IF(ISERROR('RC P&L, cash & runway'!F23>0),'RC P&L, cash & runway'!F23>0,IF('RC P&L, cash & runway'!F23="","",'RC P&L, cash & runway'!F23>0))="",FALSE,IF(ISERROR('RC P&L, cash & runway'!F23>0),'RC P&L, cash & runway'!F23>0,IF('RC P&L, cash & runway'!F23="","",'RC P&L, cash & runway'!F23>0))),'RC P&L, cash & runway'!F22/'RC P&L, cash & runway'!F23,"")),"") | G24: =IFERROR(IF(IF(IF(ISERROR('RC P&L, cash & runway'!G22<=0),'RC P&L, cash & runway'!G22<=0,IF('RC P&L, cash & runway'!G22="","",'RC P&L, cash & runway'!G22<=0))="",FALSE,IF(ISERROR('RC P&L, cash & runway'!G22<=0),'RC P&L, cash & runway'!G22<=0,IF('RC P&L, cash & runway'!G22="","",'RC P&L, cash & runway'!G22<=0))),0,IF(IF(IF(ISERROR('RC P&L, cash & runway'!G23>0),'RC P&L, cash & runway'!G23>0,IF('RC P&L, cash & runway'!G23="","",'RC P&L, cash & runway'!G23>0))="",FALSE,IF(ISERROR('RC P&L, cash & runway'!G23>0),'RC P&L, cash & runway'!G23>0,IF('RC P&L, cash & runway'!G23="","",'RC P&L, cash & runway'!G23>0))),'RC P&L, cash & runway'!G22/'RC P&L, cash & runway'!G23,"")),"") | H24: =IFERROR(IF(IF(IF(ISERROR('RC P&L, cash & runway'!H22<=0),'RC P&L, cash & runway'!H22<=0,IF('RC P&L, cash & runway'!H22="","",'RC P&L, cash & runway'!H22<=0))="",FALSE,IF(ISERROR('RC P&L, cash & runway'!H22<=0),'RC P&L, cash & runway'!H22<=0,IF('RC P&L, cash & runway'!H22="","",'RC P&L, cash & runway'!H22<=0))),0,IF(IF(IF(ISERROR('RC P&L, cash & runway'!H23>0),'RC P&L, cash & runway'!H23>0,IF('RC P&L, cash & runway'!H23="","",'RC P&L, cash & runway'!H23>0))="",FALSE,IF(ISERROR('RC P&L, cash & runway'!H23>0),'RC P&L, cash & runway'!H23>0,IF('RC P&L, cash & runway'!H23="","",'RC P&L, cash & runway'!H23>0))),'RC P&L, cash & runway'!H22/'RC P&L, cash & runway'!H23,"")),"") | I24: =IFERROR(IF(IF(IF(ISERROR('RC P&L, cash & runway'!I22<=0),'RC P&L, cash & runway'!I22<=0,IF('RC P&L, cash & runway'!I22="","",'RC P&L, cash & runway'!I22<=0))="",FALSE,IF(ISERROR('RC P&L, cash & runway'!I22<=0),'RC P&L, cash & runway'!I22<=0,IF('RC P&L, cash & runway'!I22="","",'RC P&L, cash & runway'!I22<=0))),0,IF(IF(IF(ISERROR('RC P&L, cash & runway'!I23>0),'RC P&L, cash & runway'!I23>0,IF('RC P&L, cash & runway'!I23="","",'RC P&L, cash & runway'!I23>0))="",FALSE,IF(ISERROR('RC P&L, cash & runway'!I23>0),'RC P&L, cash & runway'!I23>0,IF('RC P&L, cash & runway'!I23="","",'RC P&L, cash & runway'!I23>0))),'RC P&L, cash & runway'!I22/'RC P&L, cash & runway'!I23,"")),"") | ... S24: =IFERROR(IF(IF(IF(ISERROR('RC P&L, cash & runway'!S22<=0),'RC P&L, cash & runway'!S22<=0,IF('RC P&L, cash & runway'!S22="","",'RC P&L, cash & runway'!S22<=0))="",FALSE,IF(ISERROR('RC P&L, cash & runway'!S22<=0),'RC P&L, cash & runway'!S22<=0,IF('RC P&L, cash & runway'!S22="","",'RC P&L, cash & runway'!S22<=0))),0,IF(IF(IF(ISERROR('RC P&L, cash & runway'!S23>0),'RC P&L, cash & runway'!S23>0,IF('RC P&L, cash & runway'!S23="","",'RC P&L, cash & runway'!S23>0))="",FALSE,IF(ISERROR('RC P&L, cash & runway'!S23>0),'RC P&L, cash & runway'!S23>0,IF('RC P&L, cash & runway'!S23="","",'RC P&L, cash & runway'!S23>0))),'RC P&L, cash & runway'!S22/'RC P&L, cash & runway'!S23,"")),"")
A25: Months of opex in cash | B25: =IFERROR('RC P&L, cash & runway'!B22/'RC P&L, cash & runway'!B15,"") -> 0.96027212 | C25: =IFERROR('RC P&L, cash & runway'!C22/'RC P&L, cash & runway'!C15,"") -> 0.87700229 | D25: =IFERROR('RC P&L, cash & runway'!D22/'RC P&L, cash & runway'!D15,"") -> 1.2178648 | E25: =IFERROR('RC P&L, cash & runway'!E22/'RC P&L, cash & runway'!E15,"") -> 1.2700378 | F25: =IFERROR('RC P&L, cash & runway'!F22/'RC P&L, cash & runway'!F15,"") -> 1.8297742 | G25: =IFERROR('RC P&L, cash & runway'!G22/'RC P&L, cash & runway'!G15,"") -> 2.7390731 | H25: =IFERROR('RC P&L, cash & runway'!H22/'RC P&L, cash & runway'!H15,"") -> 2.2401017 | I25: =IFERROR('RC P&L, cash & runway'!I22/'RC P&L, cash & runway'!I15,"") -> 2.5836665 | ... S25: =IFERROR('RC P&L, cash & runway'!S22/'RC P&L, cash & runway'!S15,"") -> 15.570609
A26: Below 4-month cash floor | B26: =IF(IF(IF(ISERROR('RC P&L, cash & runway'!B22<'Model inputs'!B13*'RC P&L, cash & runway'!B15),'RC P&L, cash & runway'!B22<'Model inputs'!B13*'RC P&L, cash & runway'!B15,IF('RC P&L, cash & runway'!B22="","",'RC P&L, cash & runway'!B22<'Model inputs'!B13*'RC P&L, cash & runway'!B15))="",FALSE,IF(ISERROR('RC P&L, cash & runway'!B22<'Model inputs'!B13*'RC P&L, cash & runway'!B15),'RC P&L, cash & runway'!B22<'Model inputs'!B13*'RC P&L, cash & runway'!B15,IF('RC P&L, cash & runway'!B22="","",'RC P&L, cash & runway'!B22<'Model inputs'!B13*'RC P&L, cash & runway'!B15))),1,0) -> 1 | C26: =IF(IF(IF(ISERROR('RC P&L, cash & runway'!C22<'Model inputs'!B13*'RC P&L, cash & runway'!C15),'RC P&L, cash & runway'!C22<'Model inputs'!B13*'RC P&L, cash & runway'!C15,IF('RC P&L, cash & runway'!C22="","",'RC P&L, cash & runway'!C22<'Model inputs'!B13*'RC P&L, cash & runway'!C15))="",FALSE,IF(ISERROR('RC P&L, cash & runway'!C22<'Model inputs'!B13*'RC P&L, cash & runway'!C15),'RC P&L, cash & runway'!C22<'Model inputs'!B13*'RC P&L, cash & runway'!C15,IF('RC P&L, cash & runway'!C22="","",'RC P&L, cash & runway'!C22<'Model inputs'!B13*'RC P&L, cash & runway'!C15))),1,0) -> 1 | D26: =IF(IF(IF(ISERROR('RC P&L, cash & runway'!D22<'Model inputs'!B13*'RC P&L, cash & runway'!D15),'RC P&L, cash & runway'!D22<'Model inputs'!B13*'RC P&L, cash & runway'!D15,IF('RC P&L, cash & runway'!D22="","",'RC P&L, cash & runway'!D22<'Model inputs'!B13*'RC P&L, cash & runway'!D15))="",FALSE,IF(ISERROR('RC P&L, cash & runway'!D22<'Model inputs'!B13*'RC P&L, cash & runway'!D15),'RC P&L, cash & runway'!D22<'Model inputs'!B13*'RC P&L, cash & runway'!D15,IF('RC P&L, cash & runway'!D22="","",'RC P&L, cash & runway'!D22<'Model inputs'!B13*'RC P&L, cash & runway'!D15))),1,0) -> 1 | E26: =IF(IF(IF(ISERROR('RC P&L, cash & runway'!E22<'Model inputs'!B13*'RC P&L, cash & runway'!E15),'RC P&L, cash & runway'!E22<'Model inputs'!B13*'RC P&L, cash & runway'!E15,IF('RC P&L, cash & runway'!E22="","",'RC P&L, cash & runway'!E22<'Model inputs'!B13*'RC P&L, cash & runway'!E15))="",FALSE,IF(ISERROR('RC P&L, cash & runway'!E22<'Model inputs'!B13*'RC P&L, cash & runway'!E15),'RC P&L, cash & runway'!E22<'Model inputs'!B13*'RC P&L, cash & runway'!E15,IF('RC P&L, cash & runway'!E22="","",'RC P&L, cash & runway'!E22<'Model inputs'!B13*'RC P&L, cash & runway'!E15))),1,0) -> 1 | F26: =IF(IF(IF(ISERROR('RC P&L, cash & runway'!F22<'Model inputs'!B13*'RC P&L, cash & runway'!F15),'RC P&L, cash & runway'!F22<'Model inputs'!B13*'RC P&L, cash & runway'!F15,IF('RC P&L, cash & runway'!F22="","",'RC P&L, cash & runway'!F22<'Model inputs'!B13*'RC P&L, cash & runway'!F15))="",FALSE,IF(ISERROR('RC P&L, cash & runway'!F22<'Model inputs'!B13*'RC P&L, cash & runway'!F15),'RC P&L, cash & runway'!F22<'Model inputs'!B13*'RC P&L, cash & runway'!F15,IF('RC P&L, cash & runway'!F22="","",'RC P&L, cash & runway'!F22<'Model inputs'!B13*'RC P&L, cash & runway'!F15))),1,0) -> 1 | G26: =IF(IF(IF(ISERROR('RC P&L, cash & runway'!G22<'Model inputs'!B13*'RC P&L, cash & runway'!G15),'RC P&L, cash & runway'!G22<'Model inputs'!B13*'RC P&L, cash & runway'!G15,IF('RC P&L, cash & runway'!G22="","",'RC P&L, cash & runway'!G22<'Model inputs'!B13*'RC P&L, cash & runway'!G15))="",FALSE,IF(ISERROR('RC P&L, cash & runway'!G22<'Model inputs'!B13*'RC P&L, cash & runway'!G15),'RC P&L, cash & runway'!G22<'Model inputs'!B13*'RC P&L, cash & runway'!G15,IF('RC P&L, cash & runway'!G22="","",'RC P&L, cash & runway'!G22<'Model inputs'!B13*'RC P&L, cash & runway'!G15))),1,0) -> 1 | H26: =IF(IF(IF(ISERROR('RC P&L, cash & runway'!H22<'Model inputs'!B13*'RC P&L, cash & runway'!H15),'RC P&L, cash & runway'!H22<'Model inputs'!B13*'RC P&L, cash & runway'!H15,IF('RC P&L, cash & runway'!H22="","",'RC P&L, cash & runway'!H22<'Model inputs'!B13*'RC P&L, cash & runway'!H15))="",FALSE,IF(ISERROR('RC P&L, cash & runway'!H22<'Model inputs'!B13*'RC P&L, cash & runway'!H15),'RC P&L, cash & runway'!H22<'Model inputs'!B13*'RC P&L, cash & runway'!H15,IF('RC P&L, cash & runway'!H22="","",'RC P&L, cash & runway'!H22<'Model inputs'!B13*'RC P&L, cash & runway'!H15))),1,0) -> 1 | I26: =IF(IF(IF(ISERROR('RC P&L, cash & runway'!I22<'Model inputs'!B13*'RC P&L, cash & runway'!I15),'RC P&L, cash & runway'!I22<'Model inputs'!B13*'RC P&L, cash & runway'!I15,IF('RC P&L, cash & runway'!I22="","",'RC P&L, cash & runway'!I22<'Model inputs'!B13*'RC P&L, cash & runway'!I15))="",FALSE,IF(ISERROR('RC P&L, cash & runway'!I22<'Model inputs'!B13*'RC P&L, cash & runway'!I15),'RC P&L, cash & runway'!I22<'Model inputs'!B13*'RC P&L, cash & runway'!I15,IF('RC P&L, cash & runway'!I22="","",'RC P&L, cash & runway'!I22<'Model inputs'!B13*'RC P&L, cash & runway'!I15))),1,0) -> 1 | J26: =IF(IF(IF(ISERROR('RC P&L, cash & runway'!J22<'Model inputs'!B13*'RC P&L, cash & runway'!J15),'RC P&L, cash & runway'!J22<'Model inputs'!B13*'RC P&L, cash & runway'!J15,IF('RC P&L, cash & runway'!J22="","",'RC P&L, cash & runway'!J22<'Model inputs'!B13*'RC P&L, cash & runway'!J15))="",FALSE,IF(ISERROR('RC P&L, cash & runway'!J22<'Model inputs'!B13*'RC P&L, cash & runway'!J15),'RC P&L, cash & runway'!J22<'Model inputs'!B13*'RC P&L, cash & runway'!J15,IF('RC P&L, cash & runway'!J22="","",'RC P&L, cash & runway'!J22<'Model inputs'!B13*'RC P&L, cash & runway'!J15))),1,0) -> 1 | K26: =IF(IF(IF(ISERROR('RC P&L, cash & runway'!K22<'Model inputs'!B13*'RC P&L, cash & runway'!K15),'RC P&L, cash & runway'!K22<'Model inputs'!B13*'RC P&L, cash & runway'!K15,IF('RC P&L, cash & runway'!K22="","",'RC P&L, cash & runway'!K22<'Model inputs'!B13*'RC P&L, cash & runway'!K15))="",FALSE,IF(ISERROR('RC P&L, cash & runway'!K22<'Model inputs'!B13*'RC P&L, cash & runway'!K15),'RC P&L, cash & runway'!K22<'Model inputs'!B13*'RC P&L, cash & runway'!K15,IF('RC P&L, cash & runway'!K22="","",'RC P&L, cash & runway'!K22<'Model inputs'!B13*'RC P&L, cash & runway'!K15))),1,0) -> 1 | L26: =IF(IF(IF(ISERROR('RC P&L, cash & runway'!L22<'Model inputs'!B13*'RC P&L, cash & runway'!L15),'RC P&L, cash & runway'!L22<'Model inputs'!B13*'RC P&L, cash & runway'!L15,IF('RC P&L, cash & runway'!L22="","",'RC P&L, cash & runway'!L22<'Model inputs'!B13*'RC P&L, cash & runway'!L15))="",FALSE,IF(ISERROR('RC P&L, cash & runway'!L22<'Model inputs'!B13*'RC P&L, cash & runway'!L15),'RC P&L, cash & runway'!L22<'Model inputs'!B13*'RC P&L, cash & runway'!L15,IF('RC P&L, cash & runway'!L22="","",'RC P&L, cash & runway'!L22<'Model inputs'!B13*'RC P&L, cash & runway'!L15))),1,0) -> 0 | M26: =IF(IF(IF(ISERROR('RC P&L, cash & runway'!M22<'Model inputs'!B13*'RC P&L, cash & runway'!M15),'RC P&L, cash & runway'!M22<'Model inputs'!B13*'RC P&L, cash & runway'!M15,IF('RC P&L, cash & runway'!M22="","",'RC P&L, cash & runway'!M22<'Model inputs'!B13*'RC P&L, cash & runway'!M15))="",FALSE,IF(ISERROR('RC P&L, cash & runway'!M22<'Model inputs'!B13*'RC P&L, cash & runway'!M15),'RC P&L, cash & runway'!M22<'Model inputs'!B13*'RC P&L, cash & runway'!M15,IF('RC P&L, cash & runway'!M22="","",'RC P&L, cash & runway'!M22<'Model inputs'!B13*'RC P&L, cash & runway'!M15))),1,0) -> 0 | N26: =IF(IF(IF(ISERROR('RC P&L, cash & runway'!N22<'Model inputs'!B13*'RC P&L, cash & runway'!N15),'RC P&L, cash & runway'!N22<'Model inputs'!B13*'RC P&L, cash & runway'!N15,IF('RC P&L, cash & runway'!N22="","",'RC P&L, cash & runway'!N22<'Model inputs'!B13*'RC P&L, cash & runway'!N15))="",FALSE,IF(ISERROR('RC P&L, cash & runway'!N22<'Model inputs'!B13*'RC P&L, cash & runway'!N15),'RC P&L, cash & runway'!N22<'Model inputs'!B13*'RC P&L, cash & runway'!N15,IF('RC P&L, cash & runway'!N22="","",'RC P&L, cash & runway'!N22<'Model inputs'!B13*'RC P&L, cash & runway'!N15))),1,0) -> 0 | O26: =IF(IF(IF(ISERROR('RC P&L, cash & runway'!O22<'Model inputs'!B13*'RC P&L, cash & runway'!O15),'RC P&L, cash & runway'!O22<'Model inputs'!B13*'RC P&L, cash & runway'!O15,IF('RC P&L, cash & runway'!O22="","",'RC P&L, cash & runway'!O22<'Model inputs'!B13*'RC P&L, cash & runway'!O15))="",FALSE,IF(ISERROR('RC P&L, cash & runway'!O22<'Model inputs'!B13*'RC P&L, cash & runway'!O15),'RC P&L, cash & runway'!O22<'Model inputs'!B13*'RC P&L, cash & runway'!O15,IF('RC P&L, cash & runway'!O22="","",'RC P&L, cash & runway'!O22<'Model inputs'!B13*'RC P&L, cash & runway'!O15))),1,0) -> 0 | P26: =IF(IF(IF(ISERROR('RC P&L, cash & runway'!P22<'Model inputs'!B13*'RC P&L, cash & runway'!P15),'RC P&L, cash & runway'!P22<'Model inputs'!B13*'RC P&L, cash & runway'!P15,IF('RC P&L, cash & runway'!P22="","",'RC P&L, cash & runway'!P22<'Model inputs'!B13*'RC P&L, cash & runway'!P15))="",FALSE,IF(ISERROR('RC P&L, cash & runway'!P22<'Model inputs'!B13*'RC P&L, cash & runway'!P15),'RC P&L, cash & runway'!P22<'Model inputs'!B13*'RC P&L, cash & runway'!P15,IF('RC P&L, cash & runway'!P22="","",'RC P&L, cash & runway'!P22<'Model inputs'!B13*'RC P&L, cash & runway'!P15))),1,0) -> 0 | Q26: =IF(IF(IF(ISERROR('RC P&L, cash & runway'!Q22<'Model inputs'!B13*'RC P&L, cash & runway'!Q15),'RC P&L, cash & runway'!Q22<'Model inputs'!B13*'RC P&L, cash & runway'!Q15,IF('RC P&L, cash & runway'!Q22="","",'RC P&L, cash & runway'!Q22<'Model inputs'!B13*'RC P&L, cash & runway'!Q15))="",FALSE,IF(ISERROR('RC P&L, cash & runway'!Q22<'Model inputs'!B13*'RC P&L, cash & runway'!Q15),'RC P&L, cash & runway'!Q22<'Model inputs'!B13*'RC P&L, cash & runway'!Q15,IF('RC P&L, cash & runway'!Q22="","",'RC P&L, cash & runway'!Q22<'Model inputs'!B13*'RC P&L, cash & runway'!Q15))),1,0) -> 0 | R26: =IF(IF(IF(ISERROR('RC P&L, cash & runway'!R22<'Model inputs'!B13*'RC P&L, cash & runway'!R15),'RC P&L, cash & runway'!R22<'Model inputs'!B13*'RC P&L, cash & runway'!R15,IF('RC P&L, cash & runway'!R22="","",'RC P&L, cash & runway'!R22<'Model inputs'!B13*'RC P&L, cash & runway'!R15))="",FALSE,IF(ISERROR('RC P&L, cash & runway'!R22<'Model inputs'!B13*'RC P&L, cash & runway'!R15),'RC P&L, cash & runway'!R22<'Model inputs'!B13*'RC P&L, cash & runway'!R15,IF('RC P&L, cash & runway'!R22="","",'RC P&L, cash & runway'!R22<'Model inputs'!B13*'RC P&L, cash & runway'!R15))),1,0) -> 0 | S26: =IF(IF(IF(ISERROR('RC P&L, cash & runway'!S22<'Model inputs'!B13*'RC P&L, cash & runway'!S15),'RC P&L, cash & runway'!S22<'Model inputs'!B13*'RC P&L, cash & runway'!S15,IF('RC P&L, cash & runway'!S22="","",'RC P&L, cash & runway'!S22<'Model inputs'!B13*'RC P&L, cash & runway'!S15))="",FALSE,IF(ISERROR('RC P&L, cash & runway'!S22<'Model inputs'!B13*'RC P&L, cash & runway'!S15),'RC P&L, cash & runway'!S22<'Model inputs'!B13*'RC P&L, cash & runway'!S15,IF('RC P&L, cash & runway'!S22="","",'RC P&L, cash & runway'!S22<'Model inputs'!B13*'RC P&L, cash & runway'!S15))),1,0) -> 0

Sheet Model inputs
A1: Model inputs
A2: Integration values are aggregated snapshots; raw source records are not included.
A4: Variables
A5: Variable / segment | B5: Value | C5: 2026-09 | D5: 2026-10 | E5: 2026-11 | F5: 2026-12 | G5: 2027-01 | H5: 2027-02 | I5: 2027-03 | J5: 2027-04 | K5: 2027-05 | L5: 2027-06 | M5: 2027-07 | N5: 2027-08 | O5: 2027-09 | P5: 2027-10 | Q5: 2027-11 | R5: 2027-12 | S5: 2028-01 | T5: 2028-02 | U5: 2028-03 | V5: 2028-04 | W5: 2025-10 | X5: 2025-11 | Y5: 2025-12 | Z5: 2026-01 | AA5: 2026-02 | AB5: 2026-03 | AC5: 2026-04 | AD5: 2026-05 | AE5: 2026-06 | AF5: 2026-07 | AG5: 2026-08
A6: Angel raise amount | B6: =150000 -> 150000
A7: Angel raise month | B7: =5 -> 5
A8: Angel raise on | B8: =0 -> 0
A9: Cash collected | C9: =SUM('Model inputs'!C10,'Model inputs'!C11,'Model inputs'!C12) -> 0 | D9: =SUM('Model inputs'!D10,'Model inputs'!D11,'Model inputs'!D12) -> 0 | E9: =SUM('Model inputs'!E10,'Model inputs'!E11,'Model inputs'!E12) -> 2697.68 | F9: =SUM('Model inputs'!F10,'Model inputs'!F11,'Model inputs'!F12) -> 5606.7786 | G9: =SUM('Model inputs'!G10,'Model inputs'!G11,'Model inputs'!G12) -> 7825.4376 | H9: =SUM('Model inputs'!H10,'Model inputs'!H11,'Model inputs'!H12) -> 10146.446 | I9: =SUM('Model inputs'!I10,'Model inputs'!I11,'Model inputs'!I12) -> 12580.773 | J9: =SUM('Model inputs'!J10,'Model inputs'!J11,'Model inputs'!J12) -> 15140.751 | ... V9: =SUM('Model inputs'!V10,'Model inputs'!V11,'Model inputs'!V12) -> 42234.94
A10: Cash collected > Indie | C10: ='Model inputs'!C167*'Model inputs'!B171+('Model inputs'!C175+'Model inputs'!C85)*'Model inputs'!B81+'Model inputs'!C59+'Model inputs'!C29 -> 0 | D10: ='Model inputs'!D167*'Model inputs'!B171+('Model inputs'!D175+'Model inputs'!D85)*'Model inputs'!B81+'Model inputs'!D59+'Model inputs'!D29 -> 0 | E10: ='Model inputs'!E167*'Model inputs'!B171+('Model inputs'!E175+'Model inputs'!E85)*'Model inputs'!B81+'Model inputs'!E59+'Model inputs'!E29 -> 1230.4 | F10: ='Model inputs'!F167*'Model inputs'!B171+('Model inputs'!F175+'Model inputs'!F85)*'Model inputs'!B81+'Model inputs'!F59+'Model inputs'!F29 -> 2286.4933 | G10: ='Model inputs'!G167*'Model inputs'!B171+('Model inputs'!G175+'Model inputs'!G85)*'Model inputs'!B81+'Model inputs'!G59+'Model inputs'!G29 -> 2964.5804 | H10: ='Model inputs'!H167*'Model inputs'!B171+('Model inputs'!H175+'Model inputs'!H85)*'Model inputs'!B81+'Model inputs'!H59+'Model inputs'!H29 -> 3663.9033 | I10: ='Model inputs'!I167*'Model inputs'!B171+('Model inputs'!I175+'Model inputs'!I85)*'Model inputs'!B81+'Model inputs'!I59+'Model inputs'!I29 -> 4388.3617 | J10: ='Model inputs'!J167*'Model inputs'!B171+('Model inputs'!J175+'Model inputs'!J85)*'Model inputs'!B81+'Model inputs'!J59+'Model inputs'!J29 -> 5142.0202 | K10: ='Model inputs'!K167*'Model inputs'!B171+('Model inputs'!K175+'Model inputs'!K85)*'Model inputs'!B81+'Model inputs'!K59+'Model inputs'!K29 -> 5929.1322 | L10: ='Model inputs'!L167*'Model inputs'!B171+('Model inputs'!L175+'Model inputs'!L85)*'Model inputs'!B81+'Model inputs'!L59+'Model inputs'!L29 -> 6754.163 | M10: ='Model inputs'!M167*'Model inputs'!B171+('Model inputs'!M175+'Model inputs'!M85)*'Model inputs'!B81+'Model inputs'!M59+'Model inputs'!M29 -> 7621.8164 | N10: ='Model inputs'!N167*'Model inputs'!B171+('Model inputs'!N175+'Model inputs'!N85)*'Model inputs'!B81+'Model inputs'!N59+'Model inputs'!N29 -> 8484.3434 | O10: ='Model inputs'!O167*'Model inputs'!B171+('Model inputs'!O175+'Model inputs'!O85)*'Model inputs'!B81+'Model inputs'!O59+'Model inputs'!O29 -> 9344.1945 | P10: ='Model inputs'!P167*'Model inputs'!B171+('Model inputs'!P175+'Model inputs'!P85)*'Model inputs'!B81+'Model inputs'!P59+'Model inputs'!P29 -> 10203.741 | Q10: ='Model inputs'!Q167*'Model inputs'!B171+('Model inputs'!Q175+'Model inputs'!Q85)*'Model inputs'!B81+'Model inputs'!Q59+'Model inputs'!Q29 -> 11065.284 | R10: ='Model inputs'!R167*'Model inputs'!B171+('Model inputs'!R175+'Model inputs'!R85)*'Model inputs'!B81+'Model inputs'!R59+'Model inputs'!R29 -> 11931.063 | S10: ='Model inputs'!S167*'Model inputs'!B171+('Model inputs'!S175+'Model inputs'!S85)*'Model inputs'!B81+'Model inputs'!S59+'Model inputs'!S29 -> 12803.262 | T10: ='Model inputs'!T167*'Model inputs'!B171+('Model inputs'!T175+'Model inputs'!T85)*'Model inputs'!B81+'Model inputs'!T59+'Model inputs'!T29 -> 13684.018 | U10: ='Model inputs'!U167*'Model inputs'!B171+('Model inputs'!U175+'Model inputs'!U85)*'Model inputs'!B81+'Model inputs'!U59+'Model inputs'!U29 -> 14575.43 | V10: ='Model inputs'!V167*'Model inputs'!B171+('Model inputs'!V175+'Model inputs'!V85)*'Model inputs'!B81+'Model inputs'!V59+'Model inputs'!V29 -> 15479.561
A11: Cash collected > Launch | C11: ='Model inputs'!C168*'Model inputs'!B172+('Model inputs'!C176+'Model inputs'!C86)*'Model inputs'!B82+'Model inputs'!C60+'Model inputs'!C30 -> 0 | D11: ='Model inputs'!D168*'Model inputs'!B172+('Model inputs'!D176+'Model inputs'!D86)*'Model inputs'!B82+'Model inputs'!D60+'Model inputs'!D30 -> 0 | E11: ='Model inputs'!E168*'Model inputs'!B172+('Model inputs'!E176+'Model inputs'!E86)*'Model inputs'!B82+'Model inputs'!E60+'Model inputs'!E30 -> 526.36 | F11: ='Model inputs'!F168*'Model inputs'!B172+('Model inputs'!F176+'Model inputs'!F86)*'Model inputs'!B82+'Model inputs'!F60+'Model inputs'!F30 -> 1190.3858 | G11: ='Model inputs'!G168*'Model inputs'!B172+('Model inputs'!G176+'Model inputs'!G86)*'Model inputs'!B82+'Model inputs'!G60+'Model inputs'!G30 -> 1694.0473 | H11: ='Model inputs'!H168*'Model inputs'!B172+('Model inputs'!H176+'Model inputs'!H86)*'Model inputs'!B82+'Model inputs'!H60+'Model inputs'!H30 -> 2181.1402 | I11: ='Model inputs'!I168*'Model inputs'!B172+('Model inputs'!I176+'Model inputs'!I86)*'Model inputs'!B82+'Model inputs'!I60+'Model inputs'!I30 -> 2653.3469 | J11: ='Model inputs'!J168*'Model inputs'!B172+('Model inputs'!J176+'Model inputs'!J86)*'Model inputs'!B82+'Model inputs'!J60+'Model inputs'!J30 -> 3112.3679 | K11: ='Model inputs'!K168*'Model inputs'!B172+('Model inputs'!K176+'Model inputs'!K86)*'Model inputs'!B82+'Model inputs'!K60+'Model inputs'!K30 -> 3559.9378 | L11: ='Model inputs'!L168*'Model inputs'!B172+('Model inputs'!L176+'Model inputs'!L86)*'Model inputs'!B82+'Model inputs'!L60+'Model inputs'!L30 -> 2758.2418 | M11: ='Model inputs'!M168*'Model inputs'!B172+('Model inputs'!M176+'Model inputs'!M86)*'Model inputs'!B82+'Model inputs'!M60+'Model inputs'!M30 -> 3002.2318 | N11: ='Model inputs'!N168*'Model inputs'!B172+('Model inputs'!N176+'Model inputs'!N86)*'Model inputs'!B82+'Model inputs'!N60+'Model inputs'!N30 -> 3255.8697 | O11: ='Model inputs'!O168*'Model inputs'!B172+('Model inputs'!O176+'Model inputs'!O86)*'Model inputs'!B82+'Model inputs'!O60+'Model inputs'!O30 -> 3517.1531 | P11: ='Model inputs'!P168*'Model inputs'!B172+('Model inputs'!P176+'Model inputs'!P86)*'Model inputs'!B82+'Model inputs'!P60+'Model inputs'!P30 -> 3786.3126 | Q11: ='Model inputs'!Q168*'Model inputs'!B172+('Model inputs'!Q176+'Model inputs'!Q86)*'Model inputs'!B82+'Model inputs'!Q60+'Model inputs'!Q30 -> 4063.5844 | R11: ='Model inputs'!R168*'Model inputs'!B172+('Model inputs'!R176+'Model inputs'!R86)*'Model inputs'!B82+'Model inputs'!R60+'Model inputs'!R30 -> 4715.842 | S11: ='Model inputs'!S168*'Model inputs'!B172+('Model inputs'!S176+'Model inputs'!S86)*'Model inputs'!B82+'Model inputs'!S60+'Model inputs'!S30 -> 5265.7115 | T11: ='Model inputs'!T168*'Model inputs'!B172+('Model inputs'!T176+'Model inputs'!T86)*'Model inputs'!B82+'Model inputs'!T60+'Model inputs'!T30 -> 5833.1493 | U11: ='Model inputs'!U168*'Model inputs'!B172+('Model inputs'!U176+'Model inputs'!U86)*'Model inputs'!B82+'Model inputs'!U60+'Model inputs'!U30 -> 6419.8473 | V11: ='Model inputs'!V168*'Model inputs'!B172+('Model inputs'!V176+'Model inputs'!V86)*'Model inputs'!B82+'Model inputs'!V60+'Model inputs'!V30 -> 7027.631
A12: Cash collected > Team | C12: ='Model inputs'!C169*'Model inputs'!B173+('Model inputs'!C177+'Model inputs'!C87)*'Model inputs'!B83+'Model inputs'!C61+'Model inputs'!C31 -> 0 | D12: ='Model inputs'!D169*'Model inputs'!B173+('Model inputs'!D177+'Model inputs'!D87)*'Model inputs'!B83+'Model inputs'!D61+'Model inputs'!D31 -> 0 | E12: ='Model inputs'!E169*'Model inputs'!B173+('Model inputs'!E177+'Model inputs'!E87)*'Model inputs'!B83+'Model inputs'!E61+'Model inputs'!E31 -> 940.92 | F12: ='Model inputs'!F169*'Model inputs'!B173+('Model inputs'!F177+'Model inputs'!F87)*'Model inputs'!B83+'Model inputs'!F61+'Model inputs'!F31 -> 2129.8994 | G12: ='Model inputs'!G169*'Model inputs'!B173+('Model inputs'!G177+'Model inputs'!G87)*'Model inputs'!B83+'Model inputs'!G61+'Model inputs'!G31 -> 3166.8099 | H12: ='Model inputs'!H169*'Model inputs'!B173+('Model inputs'!H177+'Model inputs'!H87)*'Model inputs'!B83+'Model inputs'!H61+'Model inputs'!H31 -> 4301.4024 | I12: ='Model inputs'!I169*'Model inputs'!B173+('Model inputs'!I177+'Model inputs'!I87)*'Model inputs'!B83+'Model inputs'!I61+'Model inputs'!I31 -> 5539.0646 | J12: ='Model inputs'!J169*'Model inputs'!B173+('Model inputs'!J177+'Model inputs'!J87)*'Model inputs'!B83+'Model inputs'!J61+'Model inputs'!J31 -> 6886.3629 | K12: ='Model inputs'!K169*'Model inputs'!B173+('Model inputs'!K177+'Model inputs'!K87)*'Model inputs'!B83+'Model inputs'!K61+'Model inputs'!K31 -> 8351.1013 | L12: ='Model inputs'!L169*'Model inputs'!B173+('Model inputs'!L177+'Model inputs'!L87)*'Model inputs'!B83+'Model inputs'!L61+'Model inputs'!L31 -> 7133.842 | M12: ='Model inputs'!M169*'Model inputs'!B173+('Model inputs'!M177+'Model inputs'!M87)*'Model inputs'!B83+'Model inputs'!M61+'Model inputs'!M31 -> 8128.9021 | N12: ='Model inputs'!N169*'Model inputs'!B173+('Model inputs'!N177+'Model inputs'!N87)*'Model inputs'!B83+'Model inputs'!N61+'Model inputs'!N31 -> 8994.8437 | O12: ='Model inputs'!O169*'Model inputs'!B173+('Model inputs'!O177+'Model inputs'!O87)*'Model inputs'!B83+'Model inputs'!O61+'Model inputs'!O31 -> 9887.1206 | P12: ='Model inputs'!P169*'Model inputs'!B173+('Model inputs'!P177+'Model inputs'!P87)*'Model inputs'!B83+'Model inputs'!P61+'Model inputs'!P31 -> 10806.391 | Q12: ='Model inputs'!Q169*'Model inputs'!B173+('Model inputs'!Q177+'Model inputs'!Q87)*'Model inputs'!B83+'Model inputs'!Q61+'Model inputs'!Q31 -> 11753.4 | R12: ='Model inputs'!R169*'Model inputs'!B173+('Model inputs'!R177+'Model inputs'!R87)*'Model inputs'!B83+'Model inputs'!R61+'Model inputs'!R31 -> 13275.451 | S12: ='Model inputs'!S169*'Model inputs'!B173+('Model inputs'!S177+'Model inputs'!S87)*'Model inputs'!B83+'Model inputs'!S61+'Model inputs'!S31 -> 14717.344 | T12: ='Model inputs'!T169*'Model inputs'!B173+('Model inputs'!T177+'Model inputs'!T87)*'Model inputs'!B83+'Model inputs'!T61+'Model inputs'!T31 -> 16267.06 | U12: ='Model inputs'!U169*'Model inputs'!B173+('Model inputs'!U177+'Model inputs'!U87)*'Model inputs'!B83+'Model inputs'!U61+'Model inputs'!U31 -> 17933.732 | V12: ='Model inputs'!V169*'Model inputs'!B173+('Model inputs'!V177+'Model inputs'!V87)*'Model inputs'!B83+'Model inputs'!V61+'Model inputs'!V31 -> 19727.748
A13: Cash floor (months of opex) | B13: =4 -> 4
A14: Cash on hand | C14: =IF(IF(IF(ISERROR('Model inputs'!C32=0),'Model inputs'!C32=0,IF('Model inputs'!C32="","",'Model inputs'!C32=0))="",FALSE,IF(ISERROR('Model inputs'!C32=0),'Model inputs'!C32=0,IF('Model inputs'!C32="","",'Model inputs'!C32=0))),'Model inputs'!B67+'Model inputs'!C33,'Model inputs'!AG106+'Model inputs'!C33) -> 0 | D14: =IF(IF(IF(ISERROR('Model inputs'!D32=0),'Model inputs'!D32=0,IF('Model inputs'!D32="","",'Model inputs'!D32=0))="",FALSE,IF(ISERROR('Model inputs'!D32=0),'Model inputs'!D32=0,IF('Model inputs'!D32="","",'Model inputs'!D32=0))),'Model inputs'!B67+'Model inputs'!D33,'Model inputs'!C14+'Model inputs'!D33) -> 0 | E14: =IF(IF(IF(ISERROR('Model inputs'!E32=0),'Model inputs'!E32=0,IF('Model inputs'!E32="","",'Model inputs'!E32=0))="",FALSE,IF(ISERROR('Model inputs'!E32=0),'Model inputs'!E32=0,IF('Model inputs'!E32="","",'Model inputs'!E32=0))),'Model inputs'!B67+'Model inputs'!E33,'Model inputs'!D14+'Model inputs'!E33) -> 5036.6273 | F14: =IF(IF(IF(ISERROR('Model inputs'!F32=0),'Model inputs'!F32=0,IF('Model inputs'!F32="","",'Model inputs'!F32=0))="",FALSE,IF(ISERROR('Model inputs'!F32=0),'Model inputs'!F32=0,IF('Model inputs'!F32="","",'Model inputs'!F32=0))),'Model inputs'!B67+'Model inputs'!F33,'Model inputs'!E14+'Model inputs'!F33) -> 4906.8278 | G14: =IF(IF(IF(ISERROR('Model inputs'!G32=0),'Model inputs'!G32=0,IF('Model inputs'!G32="","",'Model inputs'!G32=0))="",FALSE,IF(ISERROR('Model inputs'!G32=0),'Model inputs'!G32=0,IF('Model inputs'!G32="","",'Model inputs'!G32=0))),'Model inputs'!B67+'Model inputs'!G33,'Model inputs'!F14+'Model inputs'!G33) -> 6813.9534 | H14: =IF(IF(IF(ISERROR('Model inputs'!H32=0),'Model inputs'!H32=0,IF('Model inputs'!H32="","",'Model inputs'!H32=0))="",FALSE,IF(ISERROR('Model inputs'!H32=0),'Model inputs'!H32=0,IF('Model inputs'!H32="","",'Model inputs'!H32=0))),'Model inputs'!B67+'Model inputs'!H33,'Model inputs'!G14+'Model inputs'!H33) -> 9201.4237 | I14: =IF(IF(IF(ISERROR('Model inputs'!I32=0),'Model inputs'!I32=0,IF('Model inputs'!I32="","",'Model inputs'!I32=0))="",FALSE,IF(ISERROR('Model inputs'!I32=0),'Model inputs'!I32=0,IF('Model inputs'!I32="","",'Model inputs'!I32=0))),'Model inputs'!B67+'Model inputs'!I33,'Model inputs'!H14+'Model inputs'!I33) -> 13622.669 | J14: =IF(IF(IF(ISERROR('Model inputs'!J32=0),'Model inputs'!J32=0,IF('Model inputs'!J32="","",'Model inputs'!J32=0))="",FALSE,IF(ISERROR('Model inputs'!J32=0),'Model inputs'!J32=0,IF('Model inputs'!J32="","",'Model inputs'!J32=0))),'Model inputs'!B67+'Model inputs'!J33,'Model inputs'!I14+'Model inputs'!J33) -> 20392.399 | K14: =IF(IF(IF(ISERROR('Model inputs'!K32=0),'Model inputs'!K32=0,IF('Model inputs'!K32="","",'Model inputs'!K32=0))="",FALSE,IF(ISERROR('Model inputs'!K32=0),'Model inputs'!K32=0,IF('Model inputs'!K32="","",'Model inputs'!K32=0))),'Model inputs'!B67+'Model inputs'!K33,'Model inputs'!J14+'Model inputs'!K33) -> 25637.964 | L14: =IF(IF(IF(ISERROR('Model inputs'!L32=0),'Model inputs'!L32=0,IF('Model inputs'!L32="","",'Model inputs'!L32=0))="",FALSE,IF(ISERROR('Model inputs'!L32=0),'Model inputs'!L32=0,IF('Model inputs'!L32="","",'Model inputs'!L32=0))),'Model inputs'!B67+'Model inputs'!L33,'Model inputs'!K14+'Model inputs'!L33) -> 29570.064 | M14: =IF(IF(IF(ISERROR('Model inputs'!M32=0),'Model inputs'!M32=0,IF('Model inputs'!M32="","",'Model inputs'!M32=0))="",FALSE,IF(ISERROR('Model inputs'!M32=0),'Model inputs'!M32=0,IF('Model inputs'!M32="","",'Model inputs'!M32=0))),'Model inputs'!B67+'Model inputs'!M33,'Model inputs'!L14+'Model inputs'!M33) -> 35383.167 | N14: =IF(IF(IF(ISERROR('Model inputs'!N32=0),'Model inputs'!N32=0,IF('Model inputs'!N32="","",'Model inputs'!N32=0))="",FALSE,IF(ISERROR('Model inputs'!N32=0),'Model inputs'!N32=0,IF('Model inputs'!N32="","",'Model inputs'!N32=0))),'Model inputs'!B67+'Model inputs'!N33,'Model inputs'!M14+'Model inputs'!N33) -> 42953.427 | O14: =IF(IF(IF(ISERROR('Model inputs'!O32=0),'Model inputs'!O32=0,IF('Model inputs'!O32="","",'Model inputs'!O32=0))="",FALSE,IF(ISERROR('Model inputs'!O32=0),'Model inputs'!O32=0,IF('Model inputs'!O32="","",'Model inputs'!O32=0))),'Model inputs'!B67+'Model inputs'!O33,'Model inputs'!N14+'Model inputs'!O33) -> 52308.118 | P14: =IF(IF(IF(ISERROR('Model inputs'!P32=0),'Model inputs'!P32=0,IF('Model inputs'!P32="","",'Model inputs'!P32=0))="",FALSE,IF(ISERROR('Model inputs'!P32=0),'Model inputs'!P32=0,IF('Model inputs'!P32="","",'Model inputs'!P32=0))),'Model inputs'!B67+'Model inputs'!P33,'Model inputs'!O14+'Model inputs'!P33) -> 63477.448 | Q14: =IF(IF(IF(ISERROR('Model inputs'!Q32=0),'Model inputs'!Q32=0,IF('Model inputs'!Q32="","",'Model inputs'!Q32=0))="",FALSE,IF(ISERROR('Model inputs'!Q32=0),'Model inputs'!Q32=0,IF('Model inputs'!Q32="","",'Model inputs'!Q32=0))),'Model inputs'!B67+'Model inputs'!Q33,'Model inputs'!P14+'Model inputs'!Q33) -> 71994.571 | R14: =IF(IF(IF(ISERROR('Model inputs'!R32=0),'Model inputs'!R32=0,IF('Model inputs'!R32="","",'Model inputs'!R32=0))="",FALSE,IF(ISERROR('Model inputs'!R32=0),'Model inputs'!R32=0,IF('Model inputs'!R32="","",'Model inputs'!R32=0))),'Model inputs'!B67+'Model inputs'!R33,'Model inputs'!Q14+'Model inputs'!R33) -> 87782.111 | S14: =IF(IF(IF(ISERROR('Model inputs'!S32=0),'Model inputs'!S32=0,IF('Model inputs'!S32="","",'Model inputs'!S32=0))="",FALSE,IF(ISERROR('Model inputs'!S32=0),'Model inputs'!S32=0,IF('Model inputs'!S32="","",'Model inputs'!S32=0))),'Model inputs'!B67+'Model inputs'!S33,'Model inputs'!R14+'Model inputs'!S33) -> 106165 | T14: =IF(IF(IF(ISERROR('Model inputs'!T32=0),'Model inputs'!T32=0,IF('Model inputs'!T32="","",'Model inputs'!T32=0))="",FALSE,IF(ISERROR('Model inputs'!T32=0),'Model inputs'!T32=0,IF('Model inputs'!T32="","",'Model inputs'!T32=0))),'Model inputs'!B67+'Model inputs'!T33,'Model inputs'!S14+'Model inputs'!T33) -> 127268.95 | U14: =IF(IF(IF(ISERROR('Model inputs'!U32=0),'Model inputs'!U32=0,IF('Model inputs'!U32="","",'Model inputs'!U32=0))="",FALSE,IF(ISERROR('Model inputs'!U32=0),'Model inputs'!U32=0,IF('Model inputs'!U32="","",'Model inputs'!U32=0))),'Model inputs'!B67+'Model inputs'!U33,'Model inputs'!T14+'Model inputs'!U33) -> 151231.95 | V14: =IF(IF(IF(ISERROR('Model inputs'!V32=0),'Model inputs'!V32=0,IF('Model inputs'!V32="","",'Model inputs'!V32=0))="",FALSE,IF(ISERROR('Model inputs'!V32=0),'Model inputs'!V32=0,IF('Model inputs'!V32="","",'Model inputs'!V32=0))),'Model inputs'!B67+'Model inputs'!V33,'Model inputs'!U14+'Model inputs'!V33) -> 178205.62
A15: Contribution | E15: =SUM('Model inputs'!E16,'Model inputs'!E17,'Model inputs'!E18) -> 2406.6273 | F15: =SUM('Model inputs'!F16,'Model inputs'!F17,'Model inputs'!F18) -> 3965.317 | G15: =SUM('Model inputs'!G16,'Model inputs'!G17,'Model inputs'!G18) -> 5243.9183 | H15: =SUM('Model inputs'!H16,'Model inputs'!H17,'Model inputs'!H18) -> 6577.772 | I15: =SUM('Model inputs'!I16,'Model inputs'!I17,'Model inputs'!I18) -> 7972.7009 | J15: =SUM('Model inputs'!J16,'Model inputs'!J17,'Model inputs'!J18) -> 9434.9597 | K15: =SUM('Model inputs'!K16,'Model inputs'!K17,'Model inputs'!K18) -> 10971.268 | L15: =SUM('Model inputs'!L16,'Model inputs'!L17,'Model inputs'!L18) -> 12781.208 | ... V15: =SUM('Model inputs'!V16,'Model inputs'!V17,'Model inputs'!V18) -> 32728.279
A16: Contribution > Indie | E16: ='Model inputs'!E73-'Model inputs'!E25-'Model inputs'!E63 -> 1101.1184 | F16: ='Model inputs'!F73-'Model inputs'!F25-'Model inputs'!F63 -> 2046.245 | G16: ='Model inputs'!G73-'Model inputs'!G25-'Model inputs'!G63 -> 2653.0836 | H16: ='Model inputs'!H73-'Model inputs'!H25-'Model inputs'!H63 -> 3278.9267 | I16: ='Model inputs'!I73-'Model inputs'!I25-'Model inputs'!I63 -> 3927.2641 | J16: ='Model inputs'!J73-'Model inputs'!J25-'Model inputs'!J63 -> 4601.7336 | K16: ='Model inputs'!K73-'Model inputs'!K25-'Model inputs'!K63 -> 5306.1415 | L16: ='Model inputs'!L73-'Model inputs'!L25-'Model inputs'!L63 -> 6044.4841 | ... V16: ='Model inputs'!V73-'Model inputs'!V25-'Model inputs'!V63 -> 13853.08
A17: Contribution > Launch | E17: ='Model inputs'!E74-'Model inputs'!E26-'Model inputs'!E64 -> 461.35556 | F17: ='Model inputs'!F74-'Model inputs'!F26-'Model inputs'!F64 -> 677.84941 | G17: ='Model inputs'!G74-'Model inputs'!G26-'Model inputs'!G64 -> 896.45597 | H17: ='Model inputs'!H74-'Model inputs'!H26-'Model inputs'!H64 -> 1113.704 | I17: ='Model inputs'!I74-'Model inputs'!I26-'Model inputs'!I64 -> 1330.0813 | J17: ='Model inputs'!J74-'Model inputs'!J26-'Model inputs'!J64 -> 1546.0865 | K17: ='Model inputs'!K74-'Model inputs'!K26-'Model inputs'!K64 -> 1762.2326 | L17: ='Model inputs'!L74-'Model inputs'!L26-'Model inputs'!L64 -> 2037.9532 | ... V17: ='Model inputs'!V74-'Model inputs'!V26-'Model inputs'!V64 -> 4874.1038
A18: Contribution > Team | E18: ='Model inputs'!E75-'Model inputs'!E27-'Model inputs'!E65 -> 844.15332 | F18: ='Model inputs'!F75-'Model inputs'!F27-'Model inputs'!F65 -> 1241.2226 | G18: ='Model inputs'!G75-'Model inputs'!G27-'Model inputs'!G65 -> 1694.3787 | H18: ='Model inputs'!H75-'Model inputs'!H27-'Model inputs'!H65 -> 2185.1413 | I18: ='Model inputs'!I75-'Model inputs'!I27-'Model inputs'!I65 -> 2715.3555 | J18: ='Model inputs'!J75-'Model inputs'!J27-'Model inputs'!J65 -> 3287.1395 | K18: ='Model inputs'!K75-'Model inputs'!K27-'Model inputs'!K65 -> 3902.8939 | L18: ='Model inputs'!L75-'Model inputs'!L27-'Model inputs'!L65 -> 4698.7706 | ... V18: ='Model inputs'!V75-'Model inputs'!V27-'Model inputs'!V65 -> 14001.095
A19: Ending customers | C19: =SUM('Model inputs'!C20,'Model inputs'!C21,'Model inputs'!C22) -> 0 | D19: =SUM('Model inputs'!D20,'Model inputs'!D21,'Model inputs'!D22) -> 0 | E19: =SUM('Model inputs'!E20,'Model inputs'!E21,'Model inputs'!E22) -> 47 | F19: =SUM('Model inputs'!F20,'Model inputs'!F21,'Model inputs'!F22) -> 84.905 | G19: =SUM('Model inputs'!G20,'Model inputs'!G21,'Model inputs'!G22) -> 110.9505 | H19: =SUM('Model inputs'!H20,'Model inputs'!H21,'Model inputs'!H22) -> 138.05103 | I19: =SUM('Model inputs'!I20,'Model inputs'!I21,'Model inputs'!I22) -> 166.36012 | J19: =SUM('Model inputs'!J20,'Model inputs'!J21,'Model inputs'!J22) -> 196.04007 | ... V19: =SUM('Model inputs'!V20,'Model inputs'!V21,'Model inputs'!V22) -> 621.23762
A20: Ending customers > Indie | C20: ='Model inputs'!C179+'Model inputs'!C183+'Model inputs'!C200+'Model inputs'!C192-'Model inputs'!C108-'Model inputs'!C196 -> 0 | D20: ='Model inputs'!D179+'Model inputs'!D183+'Model inputs'!D200+'Model inputs'!D192-'Model inputs'!D108-'Model inputs'!D196 -> 0 | E20: ='Model inputs'!E179+'Model inputs'!E183+'Model inputs'!E200+'Model inputs'!E192-'Model inputs'!E108-'Model inputs'!E196 -> 40 | F20: ='Model inputs'!F179+'Model inputs'!F183+'Model inputs'!F200+'Model inputs'!F192-'Model inputs'!F108-'Model inputs'!F196 -> 74.333333 | G20: ='Model inputs'!G179+'Model inputs'!G183+'Model inputs'!G200+'Model inputs'!G192-'Model inputs'!G108-'Model inputs'!G196 -> 96.377778 | H20: ='Model inputs'!H179+'Model inputs'!H183+'Model inputs'!H200+'Model inputs'!H192-'Model inputs'!H108-'Model inputs'!H196 -> 119.11259 | I20: ='Model inputs'!I179+'Model inputs'!I183+'Model inputs'!I200+'Model inputs'!I192-'Model inputs'!I108-'Model inputs'!I196 -> 142.66455 | J20: ='Model inputs'!J179+'Model inputs'!J183+'Model inputs'!J200+'Model inputs'!J192-'Model inputs'!J108-'Model inputs'!J196 -> 167.16581 | ... V20: ='Model inputs'!V179+'Model inputs'!V183+'Model inputs'!V200+'Model inputs'!V192-'Model inputs'!V108-'Model inputs'!V196 -> 503.23671
A21: Ending customers > Launch | C21: ='Model inputs'!C180+'Model inputs'!C184+'Model inputs'!C201+'Model inputs'!C193-'Model inputs'!C109-'Model inputs'!C197 -> 0 | D21: ='Model inputs'!D180+'Model inputs'!D184+'Model inputs'!D201+'Model inputs'!D193-'Model inputs'!D109-'Model inputs'!D197 -> 0 | E21: ='Model inputs'!E180+'Model inputs'!E184+'Model inputs'!E201+'Model inputs'!E193-'Model inputs'!E109-'Model inputs'!E197 -> 1 | F21: ='Model inputs'!F180+'Model inputs'!F184+'Model inputs'!F201+'Model inputs'!F193-'Model inputs'!F109-'Model inputs'!F197 -> 1.51 | G21: ='Model inputs'!G180+'Model inputs'!G184+'Model inputs'!G201+'Model inputs'!G193-'Model inputs'!G109-'Model inputs'!G197 -> 2.0251069 | H21: ='Model inputs'!H180+'Model inputs'!H184+'Model inputs'!H201+'Model inputs'!H193-'Model inputs'!H109-'Model inputs'!H197 -> 2.5470121 | I21: ='Model inputs'!I180+'Model inputs'!I184+'Model inputs'!I201+'Model inputs'!I193-'Model inputs'!I109-'Model inputs'!I197 -> 3.0771045 | J21: ='Model inputs'!J180+'Model inputs'!J184+'Model inputs'!J201+'Model inputs'!J193-'Model inputs'!J109-'Model inputs'!J197 -> 3.6168582 | ... V21: ='Model inputs'!V180+'Model inputs'!V184+'Model inputs'!V201+'Model inputs'!V193-'Model inputs'!V109-'Model inputs'!V197 -> 11.344724
A22: Ending customers > Team | C22: ='Model inputs'!C181+'Model inputs'!C185+'Model inputs'!C202+'Model inputs'!C194-'Model inputs'!C110-'Model inputs'!C198 -> 0 | D22: ='Model inputs'!D181+'Model inputs'!D185+'Model inputs'!D202+'Model inputs'!D194-'Model inputs'!D110-'Model inputs'!D198 -> 0 | E22: ='Model inputs'!E181+'Model inputs'!E185+'Model inputs'!E202+'Model inputs'!E194-'Model inputs'!E110-'Model inputs'!E198 -> 6 | F22: ='Model inputs'!F181+'Model inputs'!F185+'Model inputs'!F202+'Model inputs'!F194-'Model inputs'!F110-'Model inputs'!F198 -> 9.0616667 | G22: ='Model inputs'!G181+'Model inputs'!G185+'Model inputs'!G202+'Model inputs'!G194-'Model inputs'!G110-'Model inputs'!G198 -> 12.547615 | H22: ='Model inputs'!H181+'Model inputs'!H185+'Model inputs'!H202+'Model inputs'!H194-'Model inputs'!H110-'Model inputs'!H198 -> 16.391424 | I22: ='Model inputs'!I181+'Model inputs'!I185+'Model inputs'!I202+'Model inputs'!I194-'Model inputs'!I110-'Model inputs'!I198 -> 20.618467 | J22: ='Model inputs'!J181+'Model inputs'!J185+'Model inputs'!J202+'Model inputs'!J194-'Model inputs'!J110-'Model inputs'!J198 -> 25.2574 | ... V22: ='Model inputs'!V181+'Model inputs'!V185+'Model inputs'!V202+'Model inputs'!V194-'Model inputs'!V110-'Model inputs'!V198 -> 106.65619
A23: Equity raised | C23: =IF(IF(IF(IFERROR(IF(ISERROR('Model inputs'!B8=1),'Model inputs'!B8=1,IF('Model inputs'!B8="","",'Model inputs'!B8=1))=FALSE,FALSE),FALSE,IF(IFERROR('Model inputs'!B394=FALSE,FALSE),FALSE,IF(IFERROR('Model inputs'!B395=FALSE,FALSE),FALSE,IF(OR(IF(ISERROR('Model inputs'!B8=1),'Model inputs'!B8=1,IF('Model inputs'!B8="","",'Model inputs'!B8=1))="",'Model inputs'!B394="",'Model inputs'!B395=""),"",AND(IF(ISERROR('Model inputs'!B8=1),'Model inputs'!B8=1,IF('Model inputs'!B8="","",'Model inputs'!B8=1)),'Model inputs'!B394,'Model inputs'!B395)))))="",FALSE,IF(IFERROR(IF(ISERROR('Model inputs'!B8=1),'Model inputs'!B8=1,IF('Model inputs'!B8="","",'Model inputs'!B8=1))=FALSE,FALSE),FALSE,IF(IFERROR('Model inputs'!B394=FALSE,FALSE),FALSE,IF(IFERROR('Model inputs'!B395=FALSE,FALSE),FALSE,IF(OR(IF(ISERROR('Model inputs'!B8=1),'Model inputs'!B8=1,IF('Model inputs'!B8="","",'Model inputs'!B8=1))="",'Model inputs'!B394="",'Model inputs'!B395=""),"",AND(IF(ISERROR('Model inputs'!B8=1),'Model inputs'!B8=1,IF('Model inputs'!B8="","",'Model inputs'!B8=1)),'Model inputs'!B394,'Model inputs'!B395)))))),IF('Model inputs'!B6="","",'Model inputs'!B6),0) -> 0 | D23: =IF(IF(IF(IFERROR(IF(ISERROR('Model inputs'!B8=1),'Model inputs'!B8=1,IF('Model inputs'!B8="","",'Model inputs'!B8=1))=FALSE,FALSE),FALSE,IF(IFERROR('Model inputs'!B396=FALSE,FALSE),FALSE,IF(IFERROR('Model inputs'!B397=FALSE,FALSE),FALSE,IF(OR(IF(ISERROR('Model inputs'!B8=1),'Model inputs'!B8=1,IF('Model inputs'!B8="","",'Model inputs'!B8=1))="",'Model inputs'!B396="",'Model inputs'!B397=""),"",AND(IF(ISERROR('Model inputs'!B8=1),'Model inputs'!B8=1,IF('Model inputs'!B8="","",'Model inputs'!B8=1)),'Model inputs'!B396,'Model inputs'!B397)))))="",FALSE,IF(IFERROR(IF(ISERROR('Model inputs'!B8=1),'Model inputs'!B8=1,IF('Model inputs'!B8="","",'Model inputs'!B8=1))=FALSE,FALSE),FALSE,IF(IFERROR('Model inputs'!B396=FALSE,FALSE),FALSE,IF(IFERROR('Model inputs'!B397=FALSE,FALSE),FALSE,IF(OR(IF(ISERROR('Model inputs'!B8=1),'Model inputs'!B8=1,IF('Model inputs'!B8="","",'Model inputs'!B8=1))="",'Model inputs'!B396="",'Model inputs'!B397=""),"",AND(IF(ISERROR('Model inputs'!B8=1),'Model inputs'!B8=1,IF('Model inputs'!B8="","",'Model inputs'!B8=1)),'Model inputs'!B396,'Model inputs'!B397)))))),IF('Model inputs'!B6="","",'Model inputs'!B6),0) -> 0 | E23: =IF(IF(IF(IFERROR(IF(ISERROR('Model inputs'!B8=1),'Model inputs'!B8=1,IF('Model inputs'!B8="","",'Model inputs'!B8=1))=FALSE,FALSE),FALSE,IF(IFERROR('Model inputs'!B358=FALSE,FALSE),FALSE,IF(IFERROR('Model inputs'!B359=FALSE,FALSE),FALSE,IF(OR(IF(ISERROR('Model inputs'!B8=1),'Model inputs'!B8=1,IF('Model inputs'!B8="","",'Model inputs'!B8=1))="",'Model inputs'!B358="",'Model inputs'!B359=""),"",AND(IF(ISERROR('Model inputs'!B8=1),'Model inputs'!B8=1,IF('Model inputs'!B8="","",'Model inputs'!B8=1)),'Model inputs'!B358,'Model inputs'!B359)))))="",FALSE,IF(IFERROR(IF(ISERROR('Model inputs'!B8=1),'Model inputs'!B8=1,IF('Model inputs'!B8="","",'Model inputs'!B8=1))=FALSE,FALSE),FALSE,IF(IFERROR('Model inputs'!B358=FALSE,FALSE),FALSE,IF(IFERROR('Model inputs'!B359=FALSE,FALSE),FALSE,IF(OR(IF(ISERROR('Model inputs'!B8=1),'Model inputs'!B8=1,IF('Model inputs'!B8="","",'Model inputs'!B8=1))="",'Model inputs'!B358="",'Model inputs'!B359=""),"",AND(IF(ISERROR('Model inputs'!B8=1),'Model inputs'!B8=1,IF('Model inputs'!B8="","",'Model inputs'!B8=1)),'Model inputs'!B358,'Model inputs'!B359)))))),IF('Model inputs'!B6="","",'Model inputs'!B6),0) -> 0 | F23: =IF(IF(IF(IFERROR(IF(ISERROR('Model inputs'!B8=1),'Model inputs'!B8=1,IF('Model inputs'!B8="","",'Model inputs'!B8=1))=FALSE,FALSE),FALSE,IF(IFERROR('Model inputs'!B360=FALSE,FALSE),FALSE,IF(IFERROR('Model inputs'!B361=FALSE,FALSE),FALSE,IF(OR(IF(ISERROR('Model inputs'!B8=1),'Model inputs'!B8=1,IF('Model inputs'!B8="","",'Model inputs'!B8=1))="",'Model inputs'!B360="",'Model inputs'!B361=""),"",AND(IF(ISERROR('Model inputs'!B8=1),'Model inputs'!B8=1,IF('Model inputs'!B8="","",'Model inputs'!B8=1)),'Model inputs'!B360,'Model inputs'!B361)))))="",FALSE,IF(IFERROR(IF(ISERROR('Model inputs'!B8=1),'Model inputs'!B8=1,IF('Model inputs'!B8="","",'Model inputs'!B8=1))=FALSE,FALSE),FALSE,IF(IFERROR('Model inputs'!B360=FALSE,FALSE),FALSE,IF(IFERROR('Model inputs'!B361=FALSE,FALSE),FALSE,IF(OR(IF(ISERROR('Model inputs'!B8=1),'Model inputs'!B8=1,IF('Model inputs'!B8="","",'Model inputs'!B8=1))="",'Model inputs'!B360="",'Model inputs'!B361=""),"",AND(IF(ISERROR('Model inputs'!B8=1),'Model inputs'!B8=1,IF('Model inputs'!B8="","",'Model inputs'!B8=1)),'Model inputs'!B360,'Model inputs'!B361)))))),IF('Model inputs'!B6="","",'Model inputs'!B6),0) -> 0 | G23: =IF(IF(IF(IFERROR(IF(ISERROR('Model inputs'!B8=1),'Model inputs'!B8=1,IF('Model inputs'!B8="","",'Model inputs'!B8=1))=FALSE,FALSE),FALSE,IF(IFERROR('Model inputs'!B362=FALSE,FALSE),FALSE,IF(IFERROR('Model inputs'!B363=FALSE,FALSE),FALSE,IF(OR(IF(ISERROR('Model inputs'!B8=1),'Model inputs'!B8=1,IF('Model inputs'!B8="","",'Model inputs'!B8=1))="",'Model inputs'!B362="",'Model inputs'!B363=""),"",AND(IF(ISERROR('Model inputs'!B8=1),'Model inputs'!B8=1,IF('Model inputs'!B8="","",'Model inputs'!B8=1)),'Model inputs'!B362,'Model inputs'!B363)))))="",FALSE,IF(IFERROR(IF(ISERROR('Model inputs'!B8=1),'Model inputs'!B8=1,IF('Model inputs'!B8="","",'Model inputs'!B8=1))=FALSE,FALSE),FALSE,IF(IFERROR('Model inputs'!B362=FALSE,FALSE),FALSE,IF(IFERROR('Model inputs'!B363=FALSE,FALSE),FALSE,IF(OR(IF(ISERROR('Model inputs'!B8=1),'Model inputs'!B8=1,IF('Model inputs'!B8="","",'Model inputs'!B8=1))="",'Model inputs'!B362="",'Model inputs'!B363=""),"",AND(IF(ISERROR('Model inputs'!B8=1),'Model inputs'!B8=1,IF('Model inputs'!B8="","",'Model inputs'!B8=1)),'Model inputs'!B362,'Model inputs'!B363)))))),IF('Model inputs'!B6="","",'Model inputs'!B6),0) -> 0 | H23: =IF(IF(IF(IFERROR(IF(ISERROR('Model inputs'!B8=1),'Model inputs'!B8=1,IF('Model inputs'!B8="","",'Model inputs'!B8=1))=FALSE,FALSE),FALSE,IF(IFERROR('Model inputs'!B364=FALSE,FALSE),FALSE,IF(IFERROR('Model inputs'!B365=FALSE,FALSE),FALSE,IF(OR(IF(ISERROR('Model inputs'!B8=1),'Model inputs'!B8=1,IF('Model inputs'!B8="","",'Model inputs'!B8=1))="",'Model inputs'!B364="",'Model inputs'!B365=""),"",AND(IF(ISERROR('Model inputs'!B8=1),'Model inputs'!B8=1,IF('Model inputs'!B8="","",'Model inputs'!B8=1)),'Model inputs'!B364,'Model inputs'!B365)))))="",FALSE,IF(IFERROR(IF(ISERROR('Model inputs'!B8=1),'Model inputs'!B8=1,IF('Model inputs'!B8="","",'Model inputs'!B8=1))=FALSE,FALSE),FALSE,IF(IFERROR('Model inputs'!B364=FALSE,FALSE),FALSE,IF(IFERROR('Model inputs'!B365=FALSE,FALSE),FALSE,IF(OR(IF(ISERROR('Model inputs'!B8=1),'Model inputs'!B8=1,IF('Model inputs'!B8="","",'Model inputs'!B8=1))="",'Model inputs'!B364="",'Model inputs'!B365=""),"",AND(IF(ISERROR('Model inputs'!B8=1),'Model inputs'!B8=1,IF('Model inputs'!B8="","",'Model inputs'!B8=1)),'Model inputs'!B364,'Model inputs'!B365)))))),IF('Model inputs'!B6="","",'Model inputs'!B6),0) -> 0 | I23: =IF(IF(IF(IFERROR(IF(ISERROR('Model inputs'!B8=1),'Model inputs'!B8=1,IF('Model inputs'!B8="","",'Model inputs'!B8=1))=FALSE,FALSE),FALSE,IF(IFERROR('Model inputs'!B366=FALSE,FALSE),FALSE,IF(IFERROR('Model inputs'!B367=FALSE,FALSE),FALSE,IF(OR(IF(ISERROR('Model inputs'!B8=1),'Model inputs'!B8=1,IF('Model inputs'!B8="","",'Model inputs'!B8=1))="",'Model inputs'!B366="",'Model inputs'!B367=""),"",AND(IF(ISERROR('Model inputs'!B8=1),'Model inputs'!B8=1,IF('Model inputs'!B8="","",'Model inputs'!B8=1)),'Model inputs'!B366,'Model inputs'!B367)))))="",FALSE,IF(IFERROR(IF(ISERROR('Model inputs'!B8=1),'Model inputs'!B8=1,IF('Model inputs'!B8="","",'Model inputs'!B8=1))=FALSE,FALSE),FALSE,IF(IFERROR('Model inputs'!B366=FALSE,FALSE),FALSE,IF(IFERROR('Model inputs'!B367=FALSE,FALSE),FALSE,IF(OR(IF(ISERROR('Model inputs'!B8=1),'Model inputs'!B8=1,IF('Model inputs'!B8="","",'Model inputs'!B8=1))="",'Model inputs'!B366="",'Model inputs'!B367=""),"",AND(IF(ISERROR('Model inputs'!B8=1),'Model inputs'!B8=1,IF('Model inputs'!B8="","",'Model inputs'!B8=1)),'Model inputs'!B366,'Model inputs'!B367)))))),IF('Model inputs'!B6="","",'Model inputs'!B6),0) -> 0 | J23: =IF(IF(IF(IFERROR(IF(ISERROR('Model inputs'!B8=1),'Model inputs'!B8=1,IF('Model inputs'!B8="","",'Model inputs'!B8=1))=FALSE,FALSE),FALSE,IF(IFERROR('Model inputs'!B368=FALSE,FALSE),FALSE,IF(IFERROR('Model inputs'!B369=FALSE,FALSE),FALSE,IF(OR(IF(ISERROR('Model inputs'!B8=1),'Model inputs'!B8=1,IF('Model inputs'!B8="","",'Model inputs'!B8=1))="",'Model inputs'!B368="",'Model inputs'!B369=""),"",AND(IF(ISERROR('Model inputs'!B8=1),'Model inputs'!B8=1,IF('Model inputs'!B8="","",'Model inputs'!B8=1)),'Model inputs'!B368,'Model inputs'!B369)))))="",FALSE,IF(IFERROR(IF(ISERROR('Model inputs'!B8=1),'Model inputs'!B8=1,IF('Model inputs'!B8="","",'Model inputs'!B8=1))=FALSE,FALSE),FALSE,IF(IFERROR('Model inputs'!B368=FALSE,FALSE),FALSE,IF(IFERROR('Model inputs'!B369=FALSE,FALSE),FALSE,IF(OR(IF(ISERROR('Model inputs'!B8=1),'Model inputs'!B8=1,IF('Model inputs'!B8="","",'Model inputs'!B8=1))="",'Model inputs'!B368="",'Model inputs'!B369=""),"",AND(IF(ISERROR('Model inputs'!B8=1),'Model inputs'!B8=1,IF('Model inputs'!B8="","",'Model inputs'!B8=1)),'Model inputs'!B368,'Model inputs'!B369)))))),IF('Model inputs'!B6="","",'Model inputs'!B6),0) -> 0 | K23: =IF(IF(IF(IFERROR(IF(ISERROR('Model inputs'!B8=1),'Model inputs'!B8=1,IF('Model inputs'!B8="","",'Model inputs'!B8=1))=FALSE,FALSE),FALSE,IF(IFERROR('Model inputs'!B370=FALSE,FALSE),FALSE,IF(IFERROR('Model inputs'!B371=FALSE,FALSE),FALSE,IF(OR(IF(ISERROR('Model inputs'!B8=1),'Model inputs'!B8=1,IF('Model inputs'!B8="","",'Model inputs'!B8=1))="",'Model inputs'!B370="",'Model inputs'!B371=""),"",AND(IF(ISERROR('Model inputs'!B8=1),'Model inputs'!B8=1,IF('Model inputs'!B8="","",'Model inputs'!B8=1)),'Model inputs'!B370,'Model inputs'!B371)))))="",FALSE,IF(IFERROR(IF(ISERROR('Model inputs'!B8=1),'Model inputs'!B8=1,IF('Model inputs'!B8="","",'Model inputs'!B8=1))=FALSE,FALSE),FALSE,IF(IFERROR('Model inputs'!B370=FALSE,FALSE),FALSE,IF(IFERROR('Model inputs'!B371=FALSE,FALSE),FALSE,IF(OR(IF(ISERROR('Model inputs'!B8=1),'Model inputs'!B8=1,IF('Model inputs'!B8="","",'Model inputs'!B8=1))="",'Model inputs'!B370="",'Model inputs'!B371=""),"",AND(IF(ISERROR('Model inputs'!B8=1),'Model inputs'!B8=1,IF('Model inputs'!B8="","",'Model inputs'!B8=1)),'Model inputs'!B370,'Model inputs'!B371)))))),IF('Model inputs'!B6="","",'Model inputs'!B6),0) -> 0 | L23: =IF(IF(IF(IFERROR(IF(ISERROR('Model inputs'!B8=1),'Model inputs'!B8=1,IF('Model inputs'!B8="","",'Model inputs'!B8=1))=FALSE,FALSE),FALSE,IF(IFERROR('Model inputs'!B372=FALSE,FALSE),FALSE,IF(IFERROR('Model inputs'!B373=FALSE,FALSE),FALSE,IF(OR(IF(ISERROR('Model inputs'!B8=1),'Model inputs'!B8=1,IF('Model inputs'!B8="","",'Model inputs'!B8=1))="",'Model inputs'!B372="",'Model inputs'!B373=""),"",AND(IF(ISERROR('Model inputs'!B8=1),'Model inputs'!B8=1,IF('Model inputs'!B8="","",'Model inputs'!B8=1)),'Model inputs'!B372,'Model inputs'!B373)))))="",FALSE,IF(IFERROR(IF(ISERROR('Model inputs'!B8=1),'Model inputs'!B8=1,IF('Model inputs'!B8="","",'Model inputs'!B8=1))=FALSE,FALSE),FALSE,IF(IFERROR('Model inputs'!B372=FALSE,FALSE),FALSE,IF(IFERROR('Model inputs'!B373=FALSE,FALSE),FALSE,IF(OR(IF(ISERROR('Model inputs'!B8=1),'Model inputs'!B8=1,IF('Model inputs'!B8="","",'Model inputs'!B8=1))="",'Model inputs'!B372="",'Model inputs'!B373=""),"",AND(IF(ISERROR('Model inputs'!B8=1),'Model inputs'!B8=1,IF('Model inputs'!B8="","",'Model inputs'!B8=1)),'Model inputs'!B372,'Model inputs'!B373)))))),IF('Model inputs'!B6="","",'Model inputs'!B6),0) -> 0 | M23: =IF(IF(IF(IFERROR(IF(ISERROR('Model inputs'!B8=1),'Model inputs'!B8=1,IF('Model inputs'!B8="","",'Model inputs'!B8=1))=FALSE,FALSE),FALSE,IF(IFERROR('Model inputs'!B374=FALSE,FALSE),FALSE,IF(IFERROR('Model inputs'!B375=FALSE,FALSE),FALSE,IF(OR(IF(ISERROR('Model inputs'!B8=1),'Model inputs'!B8=1,IF('Model inputs'!B8="","",'Model inputs'!B8=1))="",'Model inputs'!B374="",'Model inputs'!B375=""),"",AND(IF(ISERROR('Model inputs'!B8=1),'Model inputs'!B8=1,IF('Model inputs'!B8="","",'Model inputs'!B8=1)),'Model inputs'!B374,'Model inputs'!B375)))))="",FALSE,IF(IFERROR(IF(ISERROR('Model inputs'!B8=1),'Model inputs'!B8=1,IF('Model inputs'!B8="","",'Model inputs'!B8=1))=FALSE,FALSE),FALSE,IF(IFERROR('Model inputs'!B374=FALSE,FALSE),FALSE,IF(IFERROR('Model inputs'!B375=FALSE,FALSE),FALSE,IF(OR(IF(ISERROR('Model inputs'!B8=1),'Model inputs'!B8=1,IF('Model inputs'!B8="","",'Model inputs'!B8=1))="",'Model inputs'!B374="",'Model inputs'!B375=""),"",AND(IF(ISERROR('Model inputs'!B8=1),'Model inputs'!B8=1,IF('Model inputs'!B8="","",'Model inputs'!B8=1)),'Model inputs'!B374,'Model inputs'!B375)))))),IF('Model inputs'!B6="","",'Model inputs'!B6),0) -> 0 | N23: =IF(IF(IF(IFERROR(IF(ISERROR('Model inputs'!B8=1),'Model inputs'!B8=1,IF('Model inputs'!B8="","",'Model inputs'!B8=1))=FALSE,FALSE),FALSE,IF(IFERROR('Model inputs'!B376=FALSE,FALSE),FALSE,IF(IFERROR('Model inputs'!B377=FALSE,FALSE),FALSE,IF(OR(IF(ISERROR('Model inputs'!B8=1),'Model inputs'!B8=1,IF('Model inputs'!B8="","",'Model inputs'!B8=1))="",'Model inputs'!B376="",'Model inputs'!B377=""),"",AND(IF(ISERROR('Model inputs'!B8=1),'Model inputs'!B8=1,IF('Model inputs'!B8="","",'Model inputs'!B8=1)),'Model inputs'!B376,'Model inputs'!B377)))))="",FALSE,IF(IFERROR(IF(ISERROR('Model inputs'!B8=1),'Model inputs'!B8=1,IF('Model inputs'!B8="","",'Model inputs'!B8=1))=FALSE,FALSE),FALSE,IF(IFERROR('Model inputs'!B376=FALSE,FALSE),FALSE,IF(IFERROR('Model inputs'!B377=FALSE,FALSE),FALSE,IF(OR(IF(ISERROR('Model inputs'!B8=1),'Model inputs'!B8=1,IF('Model inputs'!B8="","",'Model inputs'!B8=1))="",'Model inputs'!B376="",'Model inputs'!B377=""),"",AND(IF(ISERROR('Model inputs'!B8=1),'Model inputs'!B8=1,IF('Model inputs'!B8="","",'Model inputs'!B8=1)),'Model inputs'!B376,'Model inputs'!B377)))))),IF('Model inputs'!B6="","",'Model inputs'!B6),0) -> 0 | O23: =IF(IF(IF(IFERROR(IF(ISERROR('Model inputs'!B8=1),'Model inputs'!B8=1,IF('Model inputs'!B8="","",'Model inputs'!B8=1))=FALSE,FALSE),FALSE,IF(IFERROR('Model inputs'!B378=FALSE,FALSE),FALSE,IF(IFERROR('Model inputs'!B379=FALSE,FALSE),FALSE,IF(OR(IF(ISERROR('Model inputs'!B8=1),'Model inputs'!B8=1,IF('Model inputs'!B8="","",'Model inputs'!B8=1))="",'Model inputs'!B378="",'Model inputs'!B379=""),"",AND(IF(ISERROR('Model inputs'!B8=1),'Model inputs'!B8=1,IF('Model inputs'!B8="","",'Model inputs'!B8=1)),'Model inputs'!B378,'Model inputs'!B379)))))="",FALSE,IF(IFERROR(IF(ISERROR('Model inputs'!B8=1),'Model inputs'!B8=1,IF('Model inputs'!B8="","",'Model inputs'!B8=1))=FALSE,FALSE),FALSE,IF(IFERROR('Model inputs'!B378=FALSE,FALSE),FALSE,IF(IFERROR('Model inputs'!B379=FALSE,FALSE),FALSE,IF(OR(IF(ISERROR('Model inputs'!B8=1),'Model inputs'!B8=1,IF('Model inputs'!B8="","",'Model inputs'!B8=1))="",'Model inputs'!B378="",'Model inputs'!B379=""),"",AND(IF(ISERROR('Model inputs'!B8=1),'Model inputs'!B8=1,IF('Model inputs'!B8="","",'Model inputs'!B8=1)),'Model inputs'!B378,'Model inputs'!B379)))))),IF('Model inputs'!B6="","",'Model inputs'!B6),0) -> 0 | P23: =IF(IF(IF(IFERROR(IF(ISERROR('Model inputs'!B8=1),'Model inputs'!B8=1,IF('Model inputs'!B8="","",'Model inputs'!B8=1))=FALSE,FALSE),FALSE,IF(IFERROR('Model inputs'!B380=FALSE,FALSE),FALSE,IF(IFERROR('Model inputs'!B381=FALSE,FALSE),FALSE,IF(OR(IF(ISERROR('Model inputs'!B8=1),'Model inputs'!B8=1,IF('Model inputs'!B8="","",'Model inputs'!B8=1))="",'Model inputs'!B380="",'Model inputs'!B381=""),"",AND(IF(ISERROR('Model inputs'!B8=1),'Model inputs'!B8=1,IF('Model inputs'!B8="","",'Model inputs'!B8=1)),'Model inputs'!B380,'Model inputs'!B381)))))="",FALSE,IF(IFERROR(IF(ISERROR('Model inputs'!B8=1),'Model inputs'!B8=1,IF('Model inputs'!B8="","",'Model inputs'!B8=1))=FALSE,FALSE),FALSE,IF(IFERROR('Model inputs'!B380=FALSE,FALSE),FALSE,IF(IFERROR('Model inputs'!B381=FALSE,FALSE),FALSE,IF(OR(IF(ISERROR('Model inputs'!B8=1),'Model inputs'!B8=1,IF('Model inputs'!B8="","",'Model inputs'!B8=1))="",'Model inputs'!B380="",'Model inputs'!B381=""),"",AND(IF(ISERROR('Model inputs'!B8=1),'Model inputs'!B8=1,IF('Model inputs'!B8="","",'Model inputs'!B8=1)),'Model inputs'!B380,'Model inputs'!B381)))))),IF('Model inputs'!B6="","",'Model inputs'!B6),0) -> 0 | Q23: =IF(IF(IF(IFERROR(IF(ISERROR('Model inputs'!B8=1),'Model inputs'!B8=1,IF('Model inputs'!B8="","",'Model inputs'!B8=1))=FALSE,FALSE),FALSE,IF(IFERROR('Model inputs'!B382=FALSE,FALSE),FALSE,IF(IFERROR('Model inputs'!B383=FALSE,FALSE),FALSE,IF(OR(IF(ISERROR('Model inputs'!B8=1),'Model inputs'!B8=1,IF('Model inputs'!B8="","",'Model inputs'!B8=1))="",'Model inputs'!B382="",'Model inputs'!B383=""),"",AND(IF(ISERROR('Model inputs'!B8=1),'Model inputs'!B8=1,IF('Model inputs'!B8="","",'Model inputs'!B8=1)),'Model inputs'!B382,'Model inputs'!B383)))))="",FALSE,IF(IFERROR(IF(ISERROR('Model inputs'!B8=1),'Model inputs'!B8=1,IF('Model inputs'!B8="","",'Model inputs'!B8=1))=FALSE,FALSE),FALSE,IF(IFERROR('Model inputs'!B382=FALSE,FALSE),FALSE,IF(IFERROR('Model inputs'!B383=FALSE,FALSE),FALSE,IF(OR(IF(ISERROR('Model inputs'!B8=1),'Model inputs'!B8=1,IF('Model inputs'!B8="","",'Model inputs'!B8=1))="",'Model inputs'!B382="",'Model inputs'!B383=""),"",AND(IF(ISERROR('Model inputs'!B8=1),'Model inputs'!B8=1,IF('Model inputs'!B8="","",'Model inputs'!B8=1)),'Model inputs'!B382,'Model inputs'!B383)))))),IF('Model inputs'!B6="","",'Model inputs'!B6),0) -> 0 | R23: =IF(IF(IF(IFERROR(IF(ISERROR('Model inputs'!B8=1),'Model inputs'!B8=1,IF('Model inputs'!B8="","",'Model inputs'!B8=1))=FALSE,FALSE),FALSE,IF(IFERROR('Model inputs'!B384=FALSE,FALSE),FALSE,IF(IFERROR('Model inputs'!B385=FALSE,FALSE),FALSE,IF(OR(IF(ISERROR('Model inputs'!B8=1),'Model inputs'!B8=1,IF('Model inputs'!B8="","",'Model inputs'!B8=1))="",'Model inputs'!B384="",'Model inputs'!B385=""),"",AND(IF(ISERROR('Model inputs'!B8=1),'Model inputs'!B8=1,IF('Model inputs'!B8="","",'Model inputs'!B8=1)),'Model inputs'!B384,'Model inputs'!B385)))))="",FALSE,IF(IFERROR(IF(ISERROR('Model inputs'!B8=1),'Model inputs'!B8=1,IF('Model inputs'!B8="","",'Model inputs'!B8=1))=FALSE,FALSE),FALSE,IF(IFERROR('Model inputs'!B384=FALSE,FALSE),FALSE,IF(IFERROR('Model inputs'!B385=FALSE,FALSE),FALSE,IF(OR(IF(ISERROR('Model inputs'!B8=1),'Model inputs'!B8=1,IF('Model inputs'!B8="","",'Model inputs'!B8=1))="",'Model inputs'!B384="",'Model inputs'!B385=""),"",AND(IF(ISERROR('Model inputs'!B8=1),'Model inputs'!B8=1,IF('Model inputs'!B8="","",'Model inputs'!B8=1)),'Model inputs'!B384,'Model inputs'!B385)))))),IF('Model inputs'!B6="","",'Model inputs'!B6),0) -> 0 | S23: =IF(IF(IF(IFERROR(IF(ISERROR('Model inputs'!B8=1),'Model inputs'!B8=1,IF('Model inputs'!B8="","",'Model inputs'!B8=1))=FALSE,FALSE),FALSE,IF(IFERROR('Model inputs'!B386=FALSE,FALSE),FALSE,IF(IFERROR('Model inputs'!B387=FALSE,FALSE),FALSE,IF(OR(IF(ISERROR('Model inputs'!B8=1),'Model inputs'!B8=1,IF('Model inputs'!B8="","",'Model inputs'!B8=1))="",'Model inputs'!B386="",'Model inputs'!B387=""),"",AND(IF(ISERROR('Model inputs'!B8=1),'Model inputs'!B8=1,IF('Model inputs'!B8="","",'Model inputs'!B8=1)),'Model inputs'!B386,'Model inputs'!B387)))))="",FALSE,IF(IFERROR(IF(ISERROR('Model inputs'!B8=1),'Model inputs'!B8=1,IF('Model inputs'!B8="","",'Model inputs'!B8=1))=FALSE,FALSE),FALSE,IF(IFERROR('Model inputs'!B386=FALSE,FALSE),FALSE,IF(IFERROR('Model inputs'!B387=FALSE,FALSE),FALSE,IF(OR(IF(ISERROR('Model inputs'!B8=1),'Model inputs'!B8=1,IF('Model inputs'!B8="","",'Model inputs'!B8=1))="",'Model inputs'!B386="",'Model inputs'!B387=""),"",AND(IF(ISERROR('Model inputs'!B8=1),'Model inputs'!B8=1,IF('Model inputs'!B8="","",'Model inputs'!B8=1)),'Model inputs'!B386,'Model inputs'!B387)))))),IF('Model inputs'!B6="","",'Model inputs'!B6),0) -> 0 | T23: =IF(IF(IF(IFERROR(IF(ISERROR('Model inputs'!B8=1),'Model inputs'!B8=1,IF('Model inputs'!B8="","",'Model inputs'!B8=1))=FALSE,FALSE),FALSE,IF(IFERROR('Model inputs'!B388=FALSE,FALSE),FALSE,IF(IFERROR('Model inputs'!B389=FALSE,FALSE),FALSE,IF(OR(IF(ISERROR('Model inputs'!B8=1),'Model inputs'!B8=1,IF('Model inputs'!B8="","",'Model inputs'!B8=1))="",'Model inputs'!B388="",'Model inputs'!B389=""),"",AND(IF(ISERROR('Model inputs'!B8=1),'Model inputs'!B8=1,IF('Model inputs'!B8="","",'Model inputs'!B8=1)),'Model inputs'!B388,'Model inputs'!B389)))))="",FALSE,IF(IFERROR(IF(ISERROR('Model inputs'!B8=1),'Model inputs'!B8=1,IF('Model inputs'!B8="","",'Model inputs'!B8=1))=FALSE,FALSE),FALSE,IF(IFERROR('Model inputs'!B388=FALSE,FALSE),FALSE,IF(IFERROR('Model inputs'!B389=FALSE,FALSE),FALSE,IF(OR(IF(ISERROR('Model inputs'!B8=1),'Model inputs'!B8=1,IF('Model inputs'!B8="","",'Model inputs'!B8=1))="",'Model inputs'!B388="",'Model inputs'!B389=""),"",AND(IF(ISERROR('Model inputs'!B8=1),'Model inputs'!B8=1,IF('Model inputs'!B8="","",'Model inputs'!B8=1)),'Model inputs'!B388,'Model inputs'!B389)))))),IF('Model inputs'!B6="","",'Model inputs'!B6),0) -> 0 | U23: =IF(IF(IF(IFERROR(IF(ISERROR('Model inputs'!B8=1),'Model inputs'!B8=1,IF('Model inputs'!B8="","",'Model inputs'!B8=1))=FALSE,FALSE),FALSE,IF(IFERROR('Model inputs'!B390=FALSE,FALSE),FALSE,IF(IFERROR('Model inputs'!B391=FALSE,FALSE),FALSE,IF(OR(IF(ISERROR('Model inputs'!B8=1),'Model inputs'!B8=1,IF('Model inputs'!B8="","",'Model inputs'!B8=1))="",'Model inputs'!B390="",'Model inputs'!B391=""),"",AND(IF(ISERROR('Model inputs'!B8=1),'Model inputs'!B8=1,IF('Model inputs'!B8="","",'Model inputs'!B8=1)),'Model inputs'!B390,'Model inputs'!B391)))))="",FALSE,IF(IFERROR(IF(ISERROR('Model inputs'!B8=1),'Model inputs'!B8=1,IF('Model inputs'!B8="","",'Model inputs'!B8=1))=FALSE,FALSE),FALSE,IF(IFERROR('Model inputs'!B390=FALSE,FALSE),FALSE,IF(IFERROR('Model inputs'!B391=FALSE,FALSE),FALSE,IF(OR(IF(ISERROR('Model inputs'!B8=1),'Model inputs'!B8=1,IF('Model inputs'!B8="","",'Model inputs'!B8=1))="",'Model inputs'!B390="",'Model inputs'!B391=""),"",AND(IF(ISERROR('Model inputs'!B8=1),'Model inputs'!B8=1,IF('Model inputs'!B8="","",'Model inputs'!B8=1)),'Model inputs'!B390,'Model inputs'!B391)))))),IF('Model inputs'!B6="","",'Model inputs'!B6),0) -> 0 | V23: =IF(IF(IF(IFERROR(IF(ISERROR('Model inputs'!B8=1),'Model inputs'!B8=1,IF('Model inputs'!B8="","",'Model inputs'!B8=1))=FALSE,FALSE),FALSE,IF(IFERROR('Model inputs'!B392=FALSE,FALSE),FALSE,IF(IFERROR('Model inputs'!B393=FALSE,FALSE),FALSE,IF(OR(IF(ISERROR('Model inputs'!B8=1),'Model inputs'!B8=1,IF('Model inputs'!B8="","",'Model inputs'!B8=1))="",'Model inputs'!B392="",'Model inputs'!B393=""),"",AND(IF(ISERROR('Model inputs'!B8=1),'Model inputs'!B8=1,IF('Model inputs'!B8="","",'Model inputs'!B8=1)),'Model inputs'!B392,'Model inputs'!B393)))))="",FALSE,IF(IFERROR(IF(ISERROR('Model inputs'!B8=1),'Model inputs'!B8=1,IF('Model inputs'!B8="","",'Model inputs'!B8=1))=FALSE,FALSE),FALSE,IF(IFERROR('Model inputs'!B392=FALSE,FALSE),FALSE,IF(IFERROR('Model inputs'!B393=FALSE,FALSE),FALSE,IF(OR(IF(ISERROR('Model inputs'!B8=1),'Model inputs'!B8=1,IF('Model inputs'!B8="","",'Model inputs'!B8=1))="",'Model inputs'!B392="",'Model inputs'!B393=""),"",AND(IF(ISERROR('Model inputs'!B8=1),'Model inputs'!B8=1,IF('Model inputs'!B8="","",'Model inputs'!B8=1)),'Model inputs'!B392,'Model inputs'!B393)))))),IF('Model inputs'!B6="","",'Model inputs'!B6),0) -> 0
A24: Kit COGS | C24: =SUM('Model inputs'!C25,'Model inputs'!C26,'Model inputs'!C27) -> 0 | D24: =SUM('Model inputs'!D25,'Model inputs'!D26,'Model inputs'!D27) -> 0 | E24: =SUM('Model inputs'!E25,'Model inputs'!E26,'Model inputs'!E27) -> 198.72 | F24: =SUM('Model inputs'!F25,'Model inputs'!F26,'Model inputs'!F27) -> 328.51 | G24: =SUM('Model inputs'!G25,'Model inputs'!G26,'Model inputs'!G27) -> 438.26905 | H24: =SUM('Model inputs'!H25,'Model inputs'!H26,'Model inputs'!H27) -> 553.80922 | I24: =SUM('Model inputs'!I25,'Model inputs'!I26,'Model inputs'!I27) -> 675.74404 | J24: =SUM('Model inputs'!J25,'Model inputs'!J26,'Model inputs'!J27) -> 804.73919 | ... V24: =SUM('Model inputs'!V25,'Model inputs'!V26,'Model inputs'!V27) -> 2790.5679
A25: Kit COGS > Indie | C25: ='Model inputs'!C113*'Model inputs'!C111 -> 0 | D25: ='Model inputs'!D113*'Model inputs'!D111 -> 0 | E25: ='Model inputs'!E113*'Model inputs'!E111 -> 81.6 | F25: ='Model inputs'!F113*'Model inputs'!F111 -> 151.64 | G25: ='Model inputs'!G113*'Model inputs'!G111 -> 196.61067 | H25: ='Model inputs'!H113*'Model inputs'!H111 -> 242.98969 | I25: ='Model inputs'!I113*'Model inputs'!I111 -> 291.03569 | J25: ='Model inputs'!J113*'Model inputs'!J111 -> 341.01825 | ... V25: ='Model inputs'!V113*'Model inputs'!V111 -> 1026.6029
A26: Kit COGS > Launch | C26: ='Model inputs'!C114*'Model inputs'!C111 -> 0 | D26: ='Model inputs'!D114*'Model inputs'!D111 -> 0 | E26: ='Model inputs'!E114*'Model inputs'!E111 -> 49.44 | F26: ='Model inputs'!F114*'Model inputs'!F111 -> 74.6544 | G26: ='Model inputs'!G114*'Model inputs'!G111 -> 100.12129 | H26: ='Model inputs'!H114*'Model inputs'!H111 -> 125.92428 | I26: ='Model inputs'!I114*'Model inputs'!I111 -> 152.13205 | J26: ='Model inputs'!J114*'Model inputs'!J111 -> 178.81747 | ... V26: ='Model inputs'!V114*'Model inputs'!V111 -> 560.88317
A27: Kit COGS > Team | C27: ='Model inputs'!C115*'Model inputs'!C111 -> 0 | D27: ='Model inputs'!D115*'Model inputs'!D111 -> 0 | E27: ='Model inputs'!E115*'Model inputs'!E111 -> 67.68 | F27: ='Model inputs'!F115*'Model inputs'!F111 -> 102.2156 | G27: ='Model inputs'!G115*'Model inputs'!G111 -> 141.5371 | H27: ='Model inputs'!H115*'Model inputs'!H111 -> 184.89526 | I27: ='Model inputs'!I115*'Model inputs'!I111 -> 232.57631 | J27: ='Model inputs'!J115*'Model inputs'!J111 -> 284.90347 | ... V27: ='Model inputs'!V115*'Model inputs'!V111 -> 1203.0819
A28: Long-trailer revenue | C28: =SUM('Model inputs'!C29,'Model inputs'!C30,'Model inputs'!C31) -> 0 | D28: =SUM('Model inputs'!D29,'Model inputs'!D30,'Model inputs'!D31) -> 0 | E28: =SUM('Model inputs'!E29,'Model inputs'!E30,'Model inputs'!E31) -> 49.68 | F28: =SUM('Model inputs'!F29,'Model inputs'!F30,'Model inputs'!F31) -> 82.1275 | G28: =SUM('Model inputs'!G29,'Model inputs'!G30,'Model inputs'!G31) -> 109.56726 | H28: =SUM('Model inputs'!H29,'Model inputs'!H30,'Model inputs'!H31) -> 138.45231 | I28: =SUM('Model inputs'!I29,'Model inputs'!I30,'Model inputs'!I31) -> 168.93601 | J28: =SUM('Model inputs'!J29,'Model inputs'!J30,'Model inputs'!J31) -> 201.1848 | ... V28: =SUM('Model inputs'!V29,'Model inputs'!V30,'Model inputs'!V31) -> 697.64198
A29: Long-trailer revenue > Indie | C29: ='Model inputs'!C113*'Model inputs'!B165*'Model inputs'!B164 -> 0 | D29: ='Model inputs'!D113*'Model inputs'!B165*'Model inputs'!B164 -> 0 | E29: ='Model inputs'!E113*'Model inputs'!B165*'Model inputs'!B164 -> 20.4 | F29: ='Model inputs'!F113*'Model inputs'!B165*'Model inputs'!B164 -> 37.91 | G29: ='Model inputs'!G113*'Model inputs'!B165*'Model inputs'!B164 -> 49.152667 | H29: ='Model inputs'!H113*'Model inputs'!B165*'Model inputs'!B164 -> 60.747422 | I29: ='Model inputs'!I113*'Model inputs'!B165*'Model inputs'!B164 -> 72.758922 | J29: ='Model inputs'!J113*'Model inputs'!B165*'Model inputs'!B164 -> 85.254562 | K29: ='Model inputs'!K113*'Model inputs'!B165*'Model inputs'!B164 -> 98.304857 | L29: ='Model inputs'!L113*'Model inputs'!B165*'Model inputs'!B164 -> 111.98385 | M29: ='Model inputs'!M113*'Model inputs'!B165*'Model inputs'!B164 -> 126.36952 | N29: ='Model inputs'!N113*'Model inputs'!B165*'Model inputs'!B164 -> 140.67019 | O29: ='Model inputs'!O113*'Model inputs'!B165*'Model inputs'!B164 -> 154.9265 | P29: ='Model inputs'!P113*'Model inputs'!B165*'Model inputs'!B164 -> 169.17776 | Q29: ='Model inputs'!Q113*'Model inputs'!B165*'Model inputs'!B164 -> 183.46213 | R29: ='Model inputs'!R113*'Model inputs'!B165*'Model inputs'!B164 -> 197.81672 | S29: ='Model inputs'!S113*'Model inputs'!B165*'Model inputs'!B164 -> 212.27775 | T29: ='Model inputs'!T113*'Model inputs'!B165*'Model inputs'!B164 -> 226.88067 | U29: ='Model inputs'!U113*'Model inputs'!B165*'Model inputs'!B164 -> 241.66025 | V29: ='Model inputs'!V113*'Model inputs'!B165*'Model inputs'!B164 -> 256.65072
A30: Long-trailer revenue > Launch | C30: ='Model inputs'!C114*'Model inputs'!B165*'Model inputs'!B164 -> 0 | D30: ='Model inputs'!D114*'Model inputs'!B165*'Model inputs'!B164 -> 0 | E30: ='Model inputs'!E114*'Model inputs'!B165*'Model inputs'!B164 -> 12.36 | F30: ='Model inputs'!F114*'Model inputs'!B165*'Model inputs'!B164 -> 18.6636 | G30: ='Model inputs'!G114*'Model inputs'!B165*'Model inputs'!B164 -> 25.030322 | H30: ='Model inputs'!H114*'Model inputs'!B165*'Model inputs'!B164 -> 31.481069 | I30: ='Model inputs'!I114*'Model inputs'!B165*'Model inputs'!B164 -> 38.033011 | J30: ='Model inputs'!J114*'Model inputs'!B165*'Model inputs'!B164 -> 44.704367 | K30: ='Model inputs'!K114*'Model inputs'!B165*'Model inputs'!B164 -> 51.514558 | L30: ='Model inputs'!L114*'Model inputs'!B165*'Model inputs'!B164 -> 58.484371 | M30: ='Model inputs'!M114*'Model inputs'!B165*'Model inputs'!B164 -> 65.636135 | N30: ='Model inputs'!N114*'Model inputs'!B165*'Model inputs'!B164 -> 72.993912 | O30: ='Model inputs'!O114*'Model inputs'!B165*'Model inputs'!B164 -> 80.565635 | P30: ='Model inputs'!P114*'Model inputs'!B165*'Model inputs'!B164 -> 88.359167 | Q30: ='Model inputs'!Q114*'Model inputs'!B165*'Model inputs'!B164 -> 96.382345 | R30: ='Model inputs'!R114*'Model inputs'!B165*'Model inputs'!B164 -> 104.64302 | S30: ='Model inputs'!S114*'Model inputs'!B165*'Model inputs'!B164 -> 113.14912 | T30: ='Model inputs'!T114*'Model inputs'!B165*'Model inputs'!B164 -> 121.90865 | U30: ='Model inputs'!U114*'Model inputs'!B165*'Model inputs'!B164 -> 130.92976 | V30: ='Model inputs'!V114*'Model inputs'!B165*'Model inputs'!B164 -> 140.22079
A31: Long-trailer revenue > Team | C31: ='Model inputs'!C115*'Model inputs'!B165*'Model inputs'!B164 -> 0 | D31: ='Model inputs'!D115*'Model inputs'!B165*'Model inputs'!B164 -> 0 | E31: ='Model inputs'!E115*'Model inputs'!B165*'Model inputs'!B164 -> 16.92 | F31: ='Model inputs'!F115*'Model inputs'!B165*'Model inputs'!B164 -> 25.5539 | G31: ='Model inputs'!G115*'Model inputs'!B165*'Model inputs'!B164 -> 35.384275 | H31: ='Model inputs'!H115*'Model inputs'!B165*'Model inputs'!B164 -> 46.223815 | I31: ='Model inputs'!I115*'Model inputs'!B165*'Model inputs'!B164 -> 58.144078 | J31: ='Model inputs'!J115*'Model inputs'!B165*'Model inputs'!B164 -> 71.225868 | K31: ='Model inputs'!K115*'Model inputs'!B165*'Model inputs'!B164 -> 85.559949 | L31: ='Model inputs'!L115*'Model inputs'!B165*'Model inputs'!B164 -> 101.24784 | M31: ='Model inputs'!M115*'Model inputs'!B165*'Model inputs'!B164 -> 118.40272 | N31: ='Model inputs'!N115*'Model inputs'!B165*'Model inputs'!B164 -> 136.16121 | O31: ='Model inputs'!O115*'Model inputs'!B165*'Model inputs'!B164 -> 154.52595 | P31: ='Model inputs'!P115*'Model inputs'!B165*'Model inputs'!B164 -> 173.502 | Q31: ='Model inputs'!Q115*'Model inputs'!B165*'Model inputs'!B164 -> 193.09683 | R31: ='Model inputs'!R115*'Model inputs'!B165*'Model inputs'!B164 -> 213.32019 | S31: ='Model inputs'!S115*'Model inputs'!B165*'Model inputs'!B164 -> 234.18405 | T31: ='Model inputs'!T115*'Model inputs'!B165*'Model inputs'!B164 -> 255.70255 | U31: ='Model inputs'!U115*'Model inputs'!B165*'Model inputs'!B164 -> 277.89192 | V31: ='Model inputs'!V115*'Model inputs'!B165*'Model inputs'!B164 -> 300.77047
A32: Model month | C32: =(YEAR(DATE(2026,9,1))-2026)*12+MONTH(DATE(2026,9,1))-11 -> -2 | D32: =(YEAR(DATE(2026,10,1))-2026)*12+MONTH(DATE(2026,10,1))-11 -> -1 | E32: =(YEAR(DATE(2026,11,1))-2026)*12+MONTH(DATE(2026,11,1))-11 -> 0 | F32: =(YEAR(DATE(2026,12,1))-2026)*12+MONTH(DATE(2026,12,1))-11 -> 1 | G32: =(YEAR(DATE(2027,1,1))-2026)*12+MONTH(DATE(2027,1,1))-11 -> 2 | H32: =(YEAR(DATE(2027,2,1))-2026)*12+MONTH(DATE(2027,2,1))-11 -> 3 | I32: =(YEAR(DATE(2027,3,1))-2026)*12+MONTH(DATE(2027,3,1))-11 -> 4 | J32: =(YEAR(DATE(2027,4,1))-2026)*12+MONTH(DATE(2027,4,1))-11 -> 5 | K32: =(YEAR(DATE(2027,5,1))-2026)*12+MONTH(DATE(2027,5,1))-11 -> 6 | L32: =(YEAR(DATE(2027,6,1))-2026)*12+MONTH(DATE(2027,6,1))-11 -> 7 | M32: =(YEAR(DATE(2027,7,1))-2026)*12+MONTH(DATE(2027,7,1))-11 -> 8 | N32: =(YEAR(DATE(2027,8,1))-2026)*12+MONTH(DATE(2027,8,1))-11 -> 9 | O32: =(YEAR(DATE(2027,9,1))-2026)*12+MONTH(DATE(2027,9,1))-11 -> 10 | P32: =(YEAR(DATE(2027,10,1))-2026)*12+MONTH(DATE(2027,10,1))-11 -> 11 | Q32: =(YEAR(DATE(2027,11,1))-2026)*12+MONTH(DATE(2027,11,1))-11 -> 12 | R32: =(YEAR(DATE(2027,12,1))-2026)*12+MONTH(DATE(2027,12,1))-11 -> 13 | S32: =(YEAR(DATE(2028,1,1))-2026)*12+MONTH(DATE(2028,1,1))-11 -> 14 | T32: =(YEAR(DATE(2028,2,1))-2026)*12+MONTH(DATE(2028,2,1))-11 -> 15 | U32: =(YEAR(DATE(2028,3,1))-2026)*12+MONTH(DATE(2028,3,1))-11 -> 16 | V32: =(YEAR(DATE(2028,4,1))-2026)*12+MONTH(DATE(2028,4,1))-11 -> 17
A33: Net cash change | C33: ='Model inputs'!C9-'Model inputs'!C24-'Model inputs'!C62-'Model inputs'!C46+'Model inputs'!C23 -> 0 | D33: ='Model inputs'!D9-'Model inputs'!D24-'Model inputs'!D62-'Model inputs'!D46+'Model inputs'!D23 -> 0 | E33: ='Model inputs'!E9-'Model inputs'!E24-'Model inputs'!E62-'Model inputs'!E46+'Model inputs'!E23 -> -6963.3727 | F33: ='Model inputs'!F9-'Model inputs'!F24-'Model inputs'!F62-'Model inputs'!F46+'Model inputs'!F23 -> -129.79946 | G33: ='Model inputs'!G9-'Model inputs'!G24-'Model inputs'!G62-'Model inputs'!G46+'Model inputs'!G23 -> 1907.1256 | H33: ='Model inputs'!H9-'Model inputs'!H24-'Model inputs'!H62-'Model inputs'!H46+'Model inputs'!H23 -> 2387.4703 | I33: ='Model inputs'!I9-'Model inputs'!I24-'Model inputs'!I62-'Model inputs'!I46+'Model inputs'!I23 -> 4421.2451 | J33: ='Model inputs'!J9-'Model inputs'!J24-'Model inputs'!J62-'Model inputs'!J46+'Model inputs'!J23 -> 6769.7302 | ... V33: ='Model inputs'!V9-'Model inputs'!V24-'Model inputs'!V62-'Model inputs'!V46+'Model inputs'!V23 -> 26973.67
A34: Opex | C34: =SUM('Model inputs'!C35,'Model inputs'!C36,'Model inputs'!C37,'Model inputs'!C38,'Model inputs'!C39,'Model inputs'!C40,'Model inputs'!C41,'Model inputs'!C42,'Model inputs'!C43,'Model inputs'!C44,'Model inputs'!C45) -> 0 | D34: =SUM('Model inputs'!D35,'Model inputs'!D36,'Model inputs'!D37,'Model inputs'!D38,'Model inputs'!D39,'Model inputs'!D40,'Model inputs'!D41,'Model inputs'!D42,'Model inputs'!D43,'Model inputs'!D44,'Model inputs'!D45) -> 0 | E34: =SUM('Model inputs'!E35,'Model inputs'!E36,'Model inputs'!E37,'Model inputs'!E38,'Model inputs'!E39,'Model inputs'!E40,'Model inputs'!E41,'Model inputs'!E42,'Model inputs'!E43,'Model inputs'!E44,'Model inputs'!E45) -> 5245 | F34: =SUM('Model inputs'!F35,'Model inputs'!F36,'Model inputs'!F37,'Model inputs'!F38,'Model inputs'!F39,'Model inputs'!F40,'Model inputs'!F41,'Model inputs'!F42,'Model inputs'!F43,'Model inputs'!F44,'Model inputs'!F45) -> 5595 | G34: =SUM('Model inputs'!G35,'Model inputs'!G36,'Model inputs'!G37,'Model inputs'!G38,'Model inputs'!G39,'Model inputs'!G40,'Model inputs'!G41,'Model inputs'!G42,'Model inputs'!G43,'Model inputs'!G44,'Model inputs'!G45) -> 5595 | H34: =SUM('Model inputs'!H35,'Model inputs'!H36,'Model inputs'!H37,'Model inputs'!H38,'Model inputs'!H39,'Model inputs'!H40,'Model inputs'!H41,'Model inputs'!H42,'Model inputs'!H43,'Model inputs'!H44,'Model inputs'!H45) -> 7245 | I34: =SUM('Model inputs'!I35,'Model inputs'!I36,'Model inputs'!I37,'Model inputs'!I38,'Model inputs'!I39,'Model inputs'!I40,'Model inputs'!I41,'Model inputs'!I42,'Model inputs'!I43,'Model inputs'!I44,'Model inputs'!I45) -> 7445 | J34: =SUM('Model inputs'!J35,'Model inputs'!J36,'Model inputs'!J37,'Model inputs'!J38,'Model inputs'!J39,'Model inputs'!J40,'Model inputs'!J41,'Model inputs'!J42,'Model inputs'!J43,'Model inputs'!J44,'Model inputs'!J45) -> 7445 | ... V34: =SUM('Model inputs'!V35,'Model inputs'!V36,'Model inputs'!V37,'Model inputs'!V38,'Model inputs'!V39,'Model inputs'!V40,'Model inputs'!V41,'Model inputs'!V42,'Model inputs'!V43,'Model inputs'!V44,'Model inputs'!V45) -> 11445
A35: Opex > Domain, email, extras | C35: ='Model inputs'!B129*IF(IF(IF(IF(IFERROR('Model inputs'!B399=FALSE,FALSE),FALSE,IF(IFERROR('Model inputs'!B400=FALSE,FALSE),FALSE,IF(OR('Model inputs'!B399="",'Model inputs'!B400=""),"",AND('Model inputs'!B399,'Model inputs'!B400))))="",FALSE,IF(IFERROR('Model inputs'!B399=FALSE,FALSE),FALSE,IF(IFERROR('Model inputs'!B400=FALSE,FALSE),FALSE,IF(OR('Model inputs'!B399="",'Model inputs'!B400=""),"",AND('Model inputs'!B399,'Model inputs'!B400))))),IF('Model inputs'!B141="","",'Model inputs'!B141),0)="",0,IF(IF(IF(IFERROR('Model inputs'!B399=FALSE,FALSE),FALSE,IF(IFERROR('Model inputs'!B400=FALSE,FALSE),FALSE,IF(OR('Model inputs'!B399="",'Model inputs'!B400=""),"",AND('Model inputs'!B399,'Model inputs'!B400))))="",FALSE,IF(IFERROR('Model inputs'!B399=FALSE,FALSE),FALSE,IF(IFERROR('Model inputs'!B400=FALSE,FALSE),FALSE,IF(OR('Model inputs'!B399="",'Model inputs'!B400=""),"",AND('Model inputs'!B399,'Model inputs'!B400))))),IF('Model inputs'!B141="","",'Model inputs'!B141),0)) -> 0 | D35: ='Model inputs'!B129*IF(IF(IF(IF(IFERROR('Model inputs'!B402=FALSE,FALSE),FALSE,IF(IFERROR('Model inputs'!B403=FALSE,FALSE),FALSE,IF(OR('Model inputs'!B402="",'Model inputs'!B403=""),"",AND('Model inputs'!B402,'Model inputs'!B403))))="",FALSE,IF(IFERROR('Model inputs'!B402=FALSE,FALSE),FALSE,IF(IFERROR('Model inputs'!B403=FALSE,FALSE),FALSE,IF(OR('Model inputs'!B402="",'Model inputs'!B403=""),"",AND('Model inputs'!B402,'Model inputs'!B403))))),IF('Model inputs'!B141="","",'Model inputs'!B141),0)="",0,IF(IF(IF(IFERROR('Model inputs'!B402=FALSE,FALSE),FALSE,IF(IFERROR('Model inputs'!B403=FALSE,FALSE),FALSE,IF(OR('Model inputs'!B402="",'Model inputs'!B403=""),"",AND('Model inputs'!B402,'Model inputs'!B403))))="",FALSE,IF(IFERROR('Model inputs'!B402=FALSE,FALSE),FALSE,IF(IFERROR('Model inputs'!B403=FALSE,FALSE),FALSE,IF(OR('Model inputs'!B402="",'Model inputs'!B403=""),"",AND('Model inputs'!B402,'Model inputs'!B403))))),IF('Model inputs'!B141="","",'Model inputs'!B141),0)) -> 0 | E35: ='Model inputs'!B129*IF(IF(IF(IF(IFERROR('Model inputs'!B405=FALSE,FALSE),FALSE,IF(IFERROR('Model inputs'!B406=FALSE,FALSE),FALSE,IF(OR('Model inputs'!B405="",'Model inputs'!B406=""),"",AND('Model inputs'!B405,'Model inputs'!B406))))="",FALSE,IF(IFERROR('Model inputs'!B405=FALSE,FALSE),FALSE,IF(IFERROR('Model inputs'!B406=FALSE,FALSE),FALSE,IF(OR('Model inputs'!B405="",'Model inputs'!B406=""),"",AND('Model inputs'!B405,'Model inputs'!B406))))),IF('Model inputs'!B141="","",'Model inputs'!B141),0)="",0,IF(IF(IF(IFERROR('Model inputs'!B405=FALSE,FALSE),FALSE,IF(IFERROR('Model inputs'!B406=FALSE,FALSE),FALSE,IF(OR('Model inputs'!B405="",'Model inputs'!B406=""),"",AND('Model inputs'!B405,'Model inputs'!B406))))="",FALSE,IF(IFERROR('Model inputs'!B405=FALSE,FALSE),FALSE,IF(IFERROR('Model inputs'!B406=FALSE,FALSE),FALSE,IF(OR('Model inputs'!B405="",'Model inputs'!B406=""),"",AND('Model inputs'!B405,'Model inputs'!B406))))),IF('Model inputs'!B141="","",'Model inputs'!B141),0)) -> 40 | F35: ='Model inputs'!B129*IF(IF(IF(IF(IFERROR('Model inputs'!B408=FALSE,FALSE),FALSE,IF(IFERROR('Model inputs'!B409=FALSE,FALSE),FALSE,IF(OR('Model inputs'!B408="",'Model inputs'!B409=""),"",AND('Model inputs'!B408,'Model inputs'!B409))))="",FALSE,IF(IFERROR('Model inputs'!B408=FALSE,FALSE),FALSE,IF(IFERROR('Model inputs'!B409=FALSE,FALSE),FALSE,IF(OR('Model inputs'!B408="",'Model inputs'!B409=""),"",AND('Model inputs'!B408,'Model inputs'!B409))))),IF('Model inputs'!B141="","",'Model inputs'!B141),0)="",0,IF(IF(IF(IFERROR('Model inputs'!B408=FALSE,FALSE),FALSE,IF(IFERROR('Model inputs'!B409=FALSE,FALSE),FALSE,IF(OR('Model inputs'!B408="",'Model inputs'!B409=""),"",AND('Model inputs'!B408,'Model inputs'!B409))))="",FALSE,IF(IFERROR('Model inputs'!B408=FALSE,FALSE),FALSE,IF(IFERROR('Model inputs'!B409=FALSE,FALSE),FALSE,IF(OR('Model inputs'!B408="",'Model inputs'!B409=""),"",AND('Model inputs'!B408,'Model inputs'!B409))))),IF('Model inputs'!B141="","",'Model inputs'!B141),0)) -> 40 | G35: ='Model inputs'!B129*IF(IF(IF(IF(IFERROR('Model inputs'!B411=FALSE,FALSE),FALSE,IF(IFERROR('Model inputs'!B412=FALSE,FALSE),FALSE,IF(OR('Model inputs'!B411="",'Model inputs'!B412=""),"",AND('Model inputs'!B411,'Model inputs'!B412))))="",FALSE,IF(IFERROR('Model inputs'!B411=FALSE,FALSE),FALSE,IF(IFERROR('Model inputs'!B412=FALSE,FALSE),FALSE,IF(OR('Model inputs'!B411="",'Model inputs'!B412=""),"",AND('Model inputs'!B411,'Model inputs'!B412))))),IF('Model inputs'!B141="","",'Model inputs'!B141),0)="",0,IF(IF(IF(IFERROR('Model inputs'!B411=FALSE,FALSE),FALSE,IF(IFERROR('Model inputs'!B412=FALSE,FALSE),FALSE,IF(OR('Model inputs'!B411="",'Model inputs'!B412=""),"",AND('Model inputs'!B411,'Model inputs'!B412))))="",FALSE,IF(IFERROR('Model inputs'!B411=FALSE,FALSE),FALSE,IF(IFERROR('Model inputs'!B412=FALSE,FALSE),FALSE,IF(OR('Model inputs'!B411="",'Model inputs'!B412=""),"",AND('Model inputs'!B411,'Model inputs'!B412))))),IF('Model inputs'!B141="","",'Model inputs'!B141),0)) -> 40 | H35: ='Model inputs'!B129*IF(IF(IF(IF(IFERROR('Model inputs'!B414=FALSE,FALSE),FALSE,IF(IFERROR('Model inputs'!B415=FALSE,FALSE),FALSE,IF(OR('Model inputs'!B414="",'Model inputs'!B415=""),"",AND('Model inputs'!B414,'Model inputs'!B415))))="",FALSE,IF(IFERROR('Model inputs'!B414=FALSE,FALSE),FALSE,IF(IFERROR('Model inputs'!B415=FALSE,FALSE),FALSE,IF(OR('Model inputs'!B414="",'Model inputs'!B415=""),"",AND('Model inputs'!B414,'Model inputs'!B415))))),IF('Model inputs'!B141="","",'Model inputs'!B141),0)="",0,IF(IF(IF(IFERROR('Model inputs'!B414=FALSE,FALSE),FALSE,IF(IFERROR('Model inputs'!B415=FALSE,FALSE),FALSE,IF(OR('Model inputs'!B414="",'Model inputs'!B415=""),"",AND('Model inputs'!B414,'Model inputs'!B415))))="",FALSE,IF(IFERROR('Model inputs'!B414=FALSE,FALSE),FALSE,IF(IFERROR('Model inputs'!B415=FALSE,FALSE),FALSE,IF(OR('Model inputs'!B414="",'Model inputs'!B415=""),"",AND('Model inputs'!B414,'Model inputs'!B415))))),IF('Model inputs'!B141="","",'Model inputs'!B141),0)) -> 40 | I35: ='Model inputs'!B129*IF(IF(IF(IF(IFERROR('Model inputs'!B417=FALSE,FALSE),FALSE,IF(IFERROR('Model inputs'!B418=FALSE,FALSE),FALSE,IF(OR('Model inputs'!B417="",'Model inputs'!B418=""),"",AND('Model inputs'!B417,'Model inputs'!B418))))="",FALSE,IF(IFERROR('Model inputs'!B417=FALSE,FALSE),FALSE,IF(IFERROR('Model inputs'!B418=FALSE,FALSE),FALSE,IF(OR('Model inputs'!B417="",'Model inputs'!B418=""),"",AND('Model inputs'!B417,'Model inputs'!B418))))),IF('Model inputs'!B141="","",'Model inputs'!B141),0)="",0,IF(IF(IF(IFERROR('Model inputs'!B417=FALSE,FALSE),FALSE,IF(IFERROR('Model inputs'!B418=FALSE,FALSE),FALSE,IF(OR('Model inputs'!B417="",'Model inputs'!B418=""),"",AND('Model inputs'!B417,'Model inputs'!B418))))="",FALSE,IF(IFERROR('Model inputs'!B417=FALSE,FALSE),FALSE,IF(IFERROR('Model inputs'!B418=FALSE,FALSE),FALSE,IF(OR('Model inputs'!B417="",'Model inputs'!B418=""),"",AND('Model inputs'!B417,'Model inputs'!B418))))),IF('Model inputs'!B141="","",'Model inputs'!B141),0)) -> 40 | J35: ='Model inputs'!B129*IF(IF(IF(IF(IFERROR('Model inputs'!B420=FALSE,FALSE),FALSE,IF(IFERROR('Model inputs'!B421=FALSE,FALSE),FALSE,IF(OR('Model inputs'!B420="",'Model inputs'!B421=""),"",AND('Model inputs'!B420,'Model inputs'!B421))))="",FALSE,IF(IFERROR('Model inputs'!B420=FALSE,FALSE),FALSE,IF(IFERROR('Model inputs'!B421=FALSE,FALSE),FALSE,IF(OR('Model inputs'!B420="",'Model inputs'!B421=""),"",AND('Model inputs'!B420,'Model inputs'!B421))))),IF('Model inputs'!B141="","",'Model inputs'!B141),0)="",0,IF(IF(IF(IFERROR('Model inputs'!B420=FALSE,FALSE),FALSE,IF(IFERROR('Model inputs'!B421=FALSE,FALSE),FALSE,IF(OR('Model inputs'!B420="",'Model inputs'!B421=""),"",AND('Model inputs'!B420,'Model inputs'!B421))))="",FALSE,IF(IFERROR('Model inputs'!B420=FALSE,FALSE),FALSE,IF(IFERROR('Model inputs'!B421=FALSE,FALSE),FALSE,IF(OR('Model inputs'!B420="",'Model inputs'!B421=""),"",AND('Model inputs'!B420,'Model inputs'!B421))))),IF('Model inputs'!B141="","",'Model inputs'!B141),0)) -> 40 | K35: ='Model inputs'!B129*IF(IF(IF(IF(IFERROR('Model inputs'!B423=FALSE,FALSE),FALSE,IF(IFERROR('Model inputs'!B424=FALSE,FALSE),FALSE,IF(OR('Model inputs'!B423="",'Model inputs'!B424=""),"",AND('Model inputs'!B423,'Model inputs'!B424))))="",FALSE,IF(IFERROR('Model inputs'!B423=FALSE,FALSE),FALSE,IF(IFERROR('Model inputs'!B424=FALSE,FALSE),FALSE,IF(OR('Model inputs'!B423="",'Model inputs'!B424=""),"",AND('Model inputs'!B423,'Model inputs'!B424))))),IF('Model inputs'!B141="","",'Model inputs'!B141),0)="",0,IF(IF(IF(IFERROR('Model inputs'!B423=FALSE,FALSE),FALSE,IF(IFERROR('Model inputs'!B424=FALSE,FALSE),FALSE,IF(OR('Model inputs'!B423="",'Model inputs'!B424=""),"",AND('Model inputs'!B423,'Model inputs'!B424))))="",FALSE,IF(IFERROR('Model inputs'!B423=FALSE,FALSE),FALSE,IF(IFERROR('Model inputs'!B424=FALSE,FALSE),FALSE,IF(OR('Model inputs'!B423="",'Model inputs'!B424=""),"",AND('Model inputs'!B423,'Model inputs'!B424))))),IF('Model inputs'!B141="","",'Model inputs'!B141),0)) -> 40 | L35: ='Model inputs'!B129*IF(IF(IF(IF(IFERROR('Model inputs'!B426=FALSE,FALSE),FALSE,IF(IFERROR('Model inputs'!B427=FALSE,FALSE),FALSE,IF(OR('Model inputs'!B426="",'Model inputs'!B427=""),"",AND('Model inputs'!B426,'Model inputs'!B427))))="",FALSE,IF(IFERROR('Model inputs'!B426=FALSE,FALSE),FALSE,IF(IFERROR('Model inputs'!B427=FALSE,FALSE),FALSE,IF(OR('Model inputs'!B426="",'Model inputs'!B427=""),"",AND('Model inputs'!B426,'Model inputs'!B427))))),IF('Model inputs'!B141="","",'Model inputs'!B141),0)="",0,IF(IF(IF(IFERROR('Model inputs'!B426=FALSE,FALSE),FALSE,IF(IFERROR('Model inputs'!B427=FALSE,FALSE),FALSE,IF(OR('Model inputs'!B426="",'Model inputs'!B427=""),"",AND('Model inputs'!B426,'Model inputs'!B427))))="",FALSE,IF(IFERROR('Model inputs'!B426=FALSE,FALSE),FALSE,IF(IFERROR('Model inputs'!B427=FALSE,FALSE),FALSE,IF(OR('Model inputs'!B426="",'Model inputs'!B427=""),"",AND('Model inputs'!B426,'Model inputs'!B427))))),IF('Model inputs'!B141="","",'Model inputs'!B141),0)) -> 40 | M35: ='Model inputs'!B129*IF(IF(IF(IF(IFERROR('Model inputs'!B429=FALSE,FALSE),FALSE,IF(IFERROR('Model inputs'!B430=FALSE,FALSE),FALSE,IF(OR('Model inputs'!B429="",'Model inputs'!B430=""),"",AND('Model inputs'!B429,'Model inputs'!B430))))="",FALSE,IF(IFERROR('Model inputs'!B429=FALSE,FALSE),FALSE,IF(IFERROR('Model inputs'!B430=FALSE,FALSE),FALSE,IF(OR('Model inputs'!B429="",'Model inputs'!B430=""),"",AND('Model inputs'!B429,'Model inputs'!B430))))),IF('Model inputs'!B141="","",'Model inputs'!B141),0)="",0,IF(IF(IF(IFERROR('Model inputs'!B429=FALSE,FALSE),FALSE,IF(IFERROR('Model inputs'!B430=FALSE,FALSE),FALSE,IF(OR('Model inputs'!B429="",'Model inputs'!B430=""),"",AND('Model inputs'!B429,'Model inputs'!B430))))="",FALSE,IF(IFERROR('Model inputs'!B429=FALSE,FALSE),FALSE,IF(IFERROR('Model inputs'!B430=FALSE,FALSE),FALSE,IF(OR('Model inputs'!B429="",'Model inputs'!B430=""),"",AND('Model inputs'!B429,'Model inputs'!B430))))),IF('Model inputs'!B141="","",'Model inputs'!B141),0)) -> 40 | N35: ='Model inputs'!B129*IF(IF(IF(IF(IFERROR('Model inputs'!B432=FALSE,FALSE),FALSE,IF(IFERROR('Model inputs'!B433=FALSE,FALSE),FALSE,IF(OR('Model inputs'!B432="",'Model inputs'!B433=""),"",AND('Model inputs'!B432,'Model inputs'!B433))))="",FALSE,IF(IFERROR('Model inputs'!B432=FALSE,FALSE),FALSE,IF(IFERROR('Model inputs'!B433=FALSE,FALSE),FALSE,IF(OR('Model inputs'!B432="",'Model inputs'!B433=""),"",AND('Model inputs'!B432,'Model inputs'!B433))))),IF('Model inputs'!B141="","",'Model inputs'!B141),0)="",0,IF(IF(IF(IFERROR('Model inputs'!B432=FALSE,FALSE),FALSE,IF(IFERROR('Model inputs'!B433=FALSE,FALSE),FALSE,IF(OR('Model inputs'!B432="",'Model inputs'!B433=""),"",AND('Model inputs'!B432,'Model inputs'!B433))))="",FALSE,IF(IFERROR('Model inputs'!B432=FALSE,FALSE),FALSE,IF(IFERROR('Model inputs'!B433=FALSE,FALSE),FALSE,IF(OR('Model inputs'!B432="",'Model inputs'!B433=""),"",AND('Model inputs'!B432,'Model inputs'!B433))))),IF('Model inputs'!B141="","",'Model inputs'!B141),0)) -> 40 | O35: ='Model inputs'!B129*IF(IF(IF(IF(IFERROR('Model inputs'!B435=FALSE,FALSE),FALSE,IF(IFERROR('Model inputs'!B436=FALSE,FALSE),FALSE,IF(OR('Model inputs'!B435="",'Model inputs'!B436=""),"",AND('Model inputs'!B435,'Model inputs'!B436))))="",FALSE,IF(IFERROR('Model inputs'!B435=FALSE,FALSE),FALSE,IF(IFERROR('Model inputs'!B436=FALSE,FALSE),FALSE,IF(OR('Model inputs'!B435="",'Model inputs'!B436=""),"",AND('Model inputs'!B435,'Model inputs'!B436))))),IF('Model inputs'!B141="","",'Model inputs'!B141),0)="",0,IF(IF(IF(IFERROR('Model inputs'!B435=FALSE,FALSE),FALSE,IF(IFERROR('Model inputs'!B436=FALSE,FALSE),FALSE,IF(OR('Model inputs'!B435="",'Model inputs'!B436=""),"",AND('Model inputs'!B435,'Model inputs'!B436))))="",FALSE,IF(IFERROR('Model inputs'!B435=FALSE,FALSE),FALSE,IF(IFERROR('Model inputs'!B436=FALSE,FALSE),FALSE,IF(OR('Model inputs'!B435="",'Model inputs'!B436=""),"",AND('Model inputs'!B435,'Model inputs'!B436))))),IF('Model inputs'!B141="","",'Model inputs'!B141),0)) -> 40 | P35: ='Model inputs'!B129*IF(IF(IF(IF(IFERROR('Model inputs'!B438=FALSE,FALSE),FALSE,IF(IFERROR('Model inputs'!B439=FALSE,FALSE),FALSE,IF(OR('Model inputs'!B438="",'Model inputs'!B439=""),"",AND('Model inputs'!B438,'Model inputs'!B439))))="",FALSE,IF(IFERROR('Model inputs'!B438=FALSE,FALSE),FALSE,IF(IFERROR('Model inputs'!B439=FALSE,FALSE),FALSE,IF(OR('Model inputs'!B438="",'Model inputs'!B439=""),"",AND('Model inputs'!B438,'Model inputs'!B439))))),IF('Model inputs'!B141="","",'Model inputs'!B141),0)="",0,IF(IF(IF(IFERROR('Model inputs'!B438=FALSE,FALSE),FALSE,IF(IFERROR('Model inputs'!B439=FALSE,FALSE),FALSE,IF(OR('Model inputs'!B438="",'Model inputs'!B439=""),"",AND('Model inputs'!B438,'Model inputs'!B439))))="",FALSE,IF(IFERROR('Model inputs'!B438=FALSE,FALSE),FALSE,IF(IFERROR('Model inputs'!B439=FALSE,FALSE),FALSE,IF(OR('Model inputs'!B438="",'Model inputs'!B439=""),"",AND('Model inputs'!B438,'Model inputs'!B439))))),IF('Model inputs'!B141="","",'Model inputs'!B141),0)) -> 40 | Q35: ='Model inputs'!B129*IF(IF(IF(IF(IFERROR('Model inputs'!B441=FALSE,FALSE),FALSE,IF(IFERROR('Model inputs'!B442=FALSE,FALSE),FALSE,IF(OR('Model inputs'!B441="",'Model inputs'!B442=""),"",AND('Model inputs'!B441,'Model inputs'!B442))))="",FALSE,IF(IFERROR('Model inputs'!B441=FALSE,FALSE),FALSE,IF(IFERROR('Model inputs'!B442=FALSE,FALSE),FALSE,IF(OR('Model inputs'!B441="",'Model inputs'!B442=""),"",AND('Model inputs'!B441,'Model inputs'!B442))))),IF('Model inputs'!B141="","",'Model inputs'!B141),0)="",0,IF(IF(IF(IFERROR('Model inputs'!B441=FALSE,FALSE),FALSE,IF(IFERROR('Model inputs'!B442=FALSE,FALSE),FALSE,IF(OR('Model inputs'!B441="",'Model inputs'!B442=""),"",AND('Model inputs'!B441,'Model inputs'!B442))))="",FALSE,IF(IFERROR('Model inputs'!B441=FALSE,FALSE),FALSE,IF(IFERROR('Model inputs'!B442=FALSE,FALSE),FALSE,IF(OR('Model inputs'!B441="",'Model inputs'!B442=""),"",AND('Model inputs'!B441,'Model inputs'!B442))))),IF('Model inputs'!B141="","",'Model inputs'!B141),0)) -> 40 | R35: ='Model inputs'!B129*IF(IF(IF(IF(IFERROR('Model inputs'!B444=FALSE,FALSE),FALSE,IF(IFERROR('Model inputs'!B445=FALSE,FALSE),FALSE,IF(OR('Model inputs'!B444="",'Model inputs'!B445=""),"",AND('Model inputs'!B444,'Model inputs'!B445))))="",FALSE,IF(IFERROR('Model inputs'!B444=FALSE,FALSE),FALSE,IF(IFERROR('Model inputs'!B445=FALSE,FALSE),FALSE,IF(OR('Model inputs'!B444="",'Model inputs'!B445=""),"",AND('Model inputs'!B444,'Model inputs'!B445))))),IF('Model inputs'!B141="","",'Model inputs'!B141),0)="",0,IF(IF(IF(IFERROR('Model inputs'!B444=FALSE,FALSE),FALSE,IF(IFERROR('Model inputs'!B445=FALSE,FALSE),FALSE,IF(OR('Model inputs'!B444="",'Model inputs'!B445=""),"",AND('Model inputs'!B444,'Model inputs'!B445))))="",FALSE,IF(IFERROR('Model inputs'!B444=FALSE,FALSE),FALSE,IF(IFERROR('Model inputs'!B445=FALSE,FALSE),FALSE,IF(OR('Model inputs'!B444="",'Model inputs'!B445=""),"",AND('Model inputs'!B444,'Model inputs'!B445))))),IF('Model inputs'!B141="","",'Model inputs'!B141),0)) -> 40 | S35: ='Model inputs'!B129*IF(IF(IF(IF(IFERROR('Model inputs'!B447=FALSE,FALSE),FALSE,IF(IFERROR('Model inputs'!B448=FALSE,FALSE),FALSE,IF(OR('Model inputs'!B447="",'Model inputs'!B448=""),"",AND('Model inputs'!B447,'Model inputs'!B448))))="",FALSE,IF(IFERROR('Model inputs'!B447=FALSE,FALSE),FALSE,IF(IFERROR('Model inputs'!B448=FALSE,FALSE),FALSE,IF(OR('Model inputs'!B447="",'Model inputs'!B448=""),"",AND('Model inputs'!B447,'Model inputs'!B448))))),IF('Model inputs'!B141="","",'Model inputs'!B141),0)="",0,IF(IF(IF(IFERROR('Model inputs'!B447=FALSE,FALSE),FALSE,IF(IFERROR('Model inputs'!B448=FALSE,FALSE),FALSE,IF(OR('Model inputs'!B447="",'Model inputs'!B448=""),"",AND('Model inputs'!B447,'Model inputs'!B448))))="",FALSE,IF(IFERROR('Model inputs'!B447=FALSE,FALSE),FALSE,IF(IFERROR('Model inputs'!B448=FALSE,FALSE),FALSE,IF(OR('Model inputs'!B447="",'Model inputs'!B448=""),"",AND('Model inputs'!B447,'Model inputs'!B448))))),IF('Model inputs'!B141="","",'Model inputs'!B141),0)) -> 40 | T35: ='Model inputs'!B129*IF(IF(IF(IF(IFERROR('Model inputs'!B450=FALSE,FALSE),FALSE,IF(IFERROR('Model inputs'!B451=FALSE,FALSE),FALSE,IF(OR('Model inputs'!B450="",'Model inputs'!B451=""),"",AND('Model inputs'!B450,'Model inputs'!B451))))="",FALSE,IF(IFERROR('Model inputs'!B450=FALSE,FALSE),FALSE,IF(IFERROR('Model inputs'!B451=FALSE,FALSE),FALSE,IF(OR('Model inputs'!B450="",'Model inputs'!B451=""),"",AND('Model inputs'!B450,'Model inputs'!B451))))),IF('Model inputs'!B141="","",'Model inputs'!B141),0)="",0,IF(IF(IF(IFERROR('Model inputs'!B450=FALSE,FALSE),FALSE,IF(IFERROR('Model inputs'!B451=FALSE,FALSE),FALSE,IF(OR('Model inputs'!B450="",'Model inputs'!B451=""),"",AND('Model inputs'!B450,'Model inputs'!B451))))="",FALSE,IF(IFERROR('Model inputs'!B450=FALSE,FALSE),FALSE,IF(IFERROR('Model inputs'!B451=FALSE,FALSE),FALSE,IF(OR('Model inputs'!B450="",'Model inputs'!B451=""),"",AND('Model inputs'!B450,'Model inputs'!B451))))),IF('Model inputs'!B141="","",'Model inputs'!B141),0)) -> 40 | U35: ='Model inputs'!B129*IF(IF(IF(IF(IFERROR('Model inputs'!B453=FALSE,FALSE),FALSE,IF(IFERROR('Model inputs'!B454=FALSE,FALSE),FALSE,IF(OR('Model inputs'!B453="",'Model inputs'!B454=""),"",AND('Model inputs'!B453,'Model inputs'!B454))))="",FALSE,IF(IFERROR('Model inputs'!B453=FALSE,FALSE),FALSE,IF(IFERROR('Model inputs'!B454=FALSE,FALSE),FALSE,IF(OR('Model inputs'!B453="",'Model inputs'!B454=""),"",AND('Model inputs'!B453,'Model inputs'!B454))))),IF('Model inputs'!B141="","",'Model inputs'!B141),0)="",0,IF(IF(IF(IFERROR('Model inputs'!B453=FALSE,FALSE),FALSE,IF(IFERROR('Model inputs'!B454=FALSE,FALSE),FALSE,IF(OR('Model inputs'!B453="",'Model inputs'!B454=""),"",AND('Model inputs'!B453,'Model inputs'!B454))))="",FALSE,IF(IFERROR('Model inputs'!B453=FALSE,FALSE),FALSE,IF(IFERROR('Model inputs'!B454=FALSE,FALSE),FALSE,IF(OR('Model inputs'!B453="",'Model inputs'!B454=""),"",AND('Model inputs'!B453,'Model inputs'!B454))))),IF('Model inputs'!B141="","",'Model inputs'!B141),0)) -> 40 | V35: ='Model inputs'!B129*IF(IF(IF(IF(IFERROR('Model inputs'!B456=FALSE,FALSE),FALSE,IF(IFERROR('Model inputs'!B457=FALSE,FALSE),FALSE,IF(OR('Model inputs'!B456="",'Model inputs'!B457=""),"",AND('Model inputs'!B456,'Model inputs'!B457))))="",FALSE,IF(IFERROR('Model inputs'!B456=FALSE,FALSE),FALSE,IF(IFERROR('Model inputs'!B457=FALSE,FALSE),FALSE,IF(OR('Model inputs'!B456="",'Model inputs'!B457=""),"",AND('Model inputs'!B456,'Model inputs'!B457))))),IF('Model inputs'!B141="","",'Model inputs'!B141),0)="",0,IF(IF(IF(IFERROR('Model inputs'!B456=FALSE,FALSE),FALSE,IF(IFERROR('Model inputs'!B457=FALSE,FALSE),FALSE,IF(OR('Model inputs'!B456="",'Model inputs'!B457=""),"",AND('Model inputs'!B456,'Model inputs'!B457))))="",FALSE,IF(IFERROR('Model inputs'!B456=FALSE,FALSE),FALSE,IF(IFERROR('Model inputs'!B457=FALSE,FALSE),FALSE,IF(OR('Model inputs'!B456="",'Model inputs'!B457=""),"",AND('Model inputs'!B456,'Model inputs'!B457))))),IF('Model inputs'!B141="","",'Model inputs'!B141),0)) -> 40
A36: Opex > Entire cloud workspace | C36: ='Model inputs'!B130*IF(IF(IF(IF(IFERROR('Model inputs'!B459=FALSE,FALSE),FALSE,IF(IFERROR('Model inputs'!B460=FALSE,FALSE),FALSE,IF(OR('Model inputs'!B459="",'Model inputs'!B460=""),"",AND('Model inputs'!B459,'Model inputs'!B460))))="",FALSE,IF(IFERROR('Model inputs'!B459=FALSE,FALSE),FALSE,IF(IFERROR('Model inputs'!B460=FALSE,FALSE),FALSE,IF(OR('Model inputs'!B459="",'Model inputs'!B460=""),"",AND('Model inputs'!B459,'Model inputs'!B460))))),IF('Model inputs'!B142="","",'Model inputs'!B142),0)="",0,IF(IF(IF(IFERROR('Model inputs'!B459=FALSE,FALSE),FALSE,IF(IFERROR('Model inputs'!B460=FALSE,FALSE),FALSE,IF(OR('Model inputs'!B459="",'Model inputs'!B460=""),"",AND('Model inputs'!B459,'Model inputs'!B460))))="",FALSE,IF(IFERROR('Model inputs'!B459=FALSE,FALSE),FALSE,IF(IFERROR('Model inputs'!B460=FALSE,FALSE),FALSE,IF(OR('Model inputs'!B459="",'Model inputs'!B460=""),"",AND('Model inputs'!B459,'Model inputs'!B460))))),IF('Model inputs'!B142="","",'Model inputs'!B142),0)) -> 0 | D36: ='Model inputs'!B130*IF(IF(IF(IF(IFERROR('Model inputs'!B462=FALSE,FALSE),FALSE,IF(IFERROR('Model inputs'!B463=FALSE,FALSE),FALSE,IF(OR('Model inputs'!B462="",'Model inputs'!B463=""),"",AND('Model inputs'!B462,'Model inputs'!B463))))="",FALSE,IF(IFERROR('Model inputs'!B462=FALSE,FALSE),FALSE,IF(IFERROR('Model inputs'!B463=FALSE,FALSE),FALSE,IF(OR('Model inputs'!B462="",'Model inputs'!B463=""),"",AND('Model inputs'!B462,'Model inputs'!B463))))),IF('Model inputs'!B142="","",'Model inputs'!B142),0)="",0,IF(IF(IF(IFERROR('Model inputs'!B462=FALSE,FALSE),FALSE,IF(IFERROR('Model inputs'!B463=FALSE,FALSE),FALSE,IF(OR('Model inputs'!B462="",'Model inputs'!B463=""),"",AND('Model inputs'!B462,'Model inputs'!B463))))="",FALSE,IF(IFERROR('Model inputs'!B462=FALSE,FALSE),FALSE,IF(IFERROR('Model inputs'!B463=FALSE,FALSE),FALSE,IF(OR('Model inputs'!B462="",'Model inputs'!B463=""),"",AND('Model inputs'!B462,'Model inputs'!B463))))),IF('Model inputs'!B142="","",'Model inputs'!B142),0)) -> 0 | E36: ='Model inputs'!B130*IF(IF(IF(IF(IFERROR('Model inputs'!B465=FALSE,FALSE),FALSE,IF(IFERROR('Model inputs'!B466=FALSE,FALSE),FALSE,IF(OR('Model inputs'!B465="",'Model inputs'!B466=""),"",AND('Model inputs'!B465,'Model inputs'!B466))))="",FALSE,IF(IFERROR('Model inputs'!B465=FALSE,FALSE),FALSE,IF(IFERROR('Model inputs'!B466=FALSE,FALSE),FALSE,IF(OR('Model inputs'!B465="",'Model inputs'!B466=""),"",AND('Model inputs'!B465,'Model inputs'!B466))))),IF('Model inputs'!B142="","",'Model inputs'!B142),0)="",0,IF(IF(IF(IFERROR('Model inputs'!B465=FALSE,FALSE),FALSE,IF(IFERROR('Model inputs'!B466=FALSE,FALSE),FALSE,IF(OR('Model inputs'!B465="",'Model inputs'!B466=""),"",AND('Model inputs'!B465,'Model inputs'!B466))))="",FALSE,IF(IFERROR('Model inputs'!B465=FALSE,FALSE),FALSE,IF(IFERROR('Model inputs'!B466=FALSE,FALSE),FALSE,IF(OR('Model inputs'!B465="",'Model inputs'!B466=""),"",AND('Model inputs'!B465,'Model inputs'!B466))))),IF('Model inputs'!B142="","",'Model inputs'!B142),0)) -> 0 | F36: ='Model inputs'!B130*IF(IF(IF(IF(IFERROR('Model inputs'!B468=FALSE,FALSE),FALSE,IF(IFERROR('Model inputs'!B469=FALSE,FALSE),FALSE,IF(OR('Model inputs'!B468="",'Model inputs'!B469=""),"",AND('Model inputs'!B468,'Model inputs'!B469))))="",FALSE,IF(IFERROR('Model inputs'!B468=FALSE,FALSE),FALSE,IF(IFERROR('Model inputs'!B469=FALSE,FALSE),FALSE,IF(OR('Model inputs'!B468="",'Model inputs'!B469=""),"",AND('Model inputs'!B468,'Model inputs'!B469))))),IF('Model inputs'!B142="","",'Model inputs'!B142),0)="",0,IF(IF(IF(IFERROR('Model inputs'!B468=FALSE,FALSE),FALSE,IF(IFERROR('Model inputs'!B469=FALSE,FALSE),FALSE,IF(OR('Model inputs'!B468="",'Model inputs'!B469=""),"",AND('Model inputs'!B468,'Model inputs'!B469))))="",FALSE,IF(IFERROR('Model inputs'!B468=FALSE,FALSE),FALSE,IF(IFERROR('Model inputs'!B469=FALSE,FALSE),FALSE,IF(OR('Model inputs'!B468="",'Model inputs'!B469=""),"",AND('Model inputs'!B468,'Model inputs'!B469))))),IF('Model inputs'!B142="","",'Model inputs'!B142),0)) -> 0 | G36: ='Model inputs'!B130*IF(IF(IF(IF(IFERROR('Model inputs'!B471=FALSE,FALSE),FALSE,IF(IFERROR('Model inputs'!B472=FALSE,FALSE),FALSE,IF(OR('Model inputs'!B471="",'Model inputs'!B472=""),"",AND('Model inputs'!B471,'Model inputs'!B472))))="",FALSE,IF(IFERROR('Model inputs'!B471=FALSE,FALSE),FALSE,IF(IFERROR('Model inputs'!B472=FALSE,FALSE),FALSE,IF(OR('Model inputs'!B471="",'Model inputs'!B472=""),"",AND('Model inputs'!B471,'Model inputs'!B472))))),IF('Model inputs'!B142="","",'Model inputs'!B142),0)="",0,IF(IF(IF(IFERROR('Model inputs'!B471=FALSE,FALSE),FALSE,IF(IFERROR('Model inputs'!B472=FALSE,FALSE),FALSE,IF(OR('Model inputs'!B471="",'Model inputs'!B472=""),"",AND('Model inputs'!B471,'Model inputs'!B472))))="",FALSE,IF(IFERROR('Model inputs'!B471=FALSE,FALSE),FALSE,IF(IFERROR('Model inputs'!B472=FALSE,FALSE),FALSE,IF(OR('Model inputs'!B471="",'Model inputs'!B472=""),"",AND('Model inputs'!B471,'Model inputs'!B472))))),IF('Model inputs'!B142="","",'Model inputs'!B142),0)) -> 0 | H36: ='Model inputs'!B130*IF(IF(IF(IF(IFERROR('Model inputs'!B474=FALSE,FALSE),FALSE,IF(IFERROR('Model inputs'!B475=FALSE,FALSE),FALSE,IF(OR('Model inputs'!B474="",'Model inputs'!B475=""),"",AND('Model inputs'!B474,'Model inputs'!B475))))="",FALSE,IF(IFERROR('Model inputs'!B474=FALSE,FALSE),FALSE,IF(IFERROR('Model inputs'!B475=FALSE,FALSE),FALSE,IF(OR('Model inputs'!B474="",'Model inputs'!B475=""),"",AND('Model inputs'!B474,'Model inputs'!B475))))),IF('Model inputs'!B142="","",'Model inputs'!B142),0)="",0,IF(IF(IF(IFERROR('Model inputs'!B474=FALSE,FALSE),FALSE,IF(IFERROR('Model inputs'!B475=FALSE,FALSE),FALSE,IF(OR('Model inputs'!B474="",'Model inputs'!B475=""),"",AND('Model inputs'!B474,'Model inputs'!B475))))="",FALSE,IF(IFERROR('Model inputs'!B474=FALSE,FALSE),FALSE,IF(IFERROR('Model inputs'!B475=FALSE,FALSE),FALSE,IF(OR('Model inputs'!B474="",'Model inputs'!B475=""),"",AND('Model inputs'!B474,'Model inputs'!B475))))),IF('Model inputs'!B142="","",'Model inputs'!B142),0)) -> 0 | I36: ='Model inputs'!B130*IF(IF(IF(IF(IFERROR('Model inputs'!B477=FALSE,FALSE),FALSE,IF(IFERROR('Model inputs'!B478=FALSE,FALSE),FALSE,IF(OR('Model inputs'!B477="",'Model inputs'!B478=""),"",AND('Model inputs'!B477,'Model inputs'!B478))))="",FALSE,IF(IFERROR('Model inputs'!B477=FALSE,FALSE),FALSE,IF(IFERROR('Model inputs'!B478=FALSE,FALSE),FALSE,IF(OR('Model inputs'!B477="",'Model inputs'!B478=""),"",AND('Model inputs'!B477,'Model inputs'!B478))))),IF('Model inputs'!B142="","",'Model inputs'!B142),0)="",0,IF(IF(IF(IFERROR('Model inputs'!B477=FALSE,FALSE),FALSE,IF(IFERROR('Model inputs'!B478=FALSE,FALSE),FALSE,IF(OR('Model inputs'!B477="",'Model inputs'!B478=""),"",AND('Model inputs'!B477,'Model inputs'!B478))))="",FALSE,IF(IFERROR('Model inputs'!B477=FALSE,FALSE),FALSE,IF(IFERROR('Model inputs'!B478=FALSE,FALSE),FALSE,IF(OR('Model inputs'!B477="",'Model inputs'!B478=""),"",AND('Model inputs'!B477,'Model inputs'!B478))))),IF('Model inputs'!B142="","",'Model inputs'!B142),0)) -> 200 | J36: ='Model inputs'!B130*IF(IF(IF(IF(IFERROR('Model inputs'!B480=FALSE,FALSE),FALSE,IF(IFERROR('Model inputs'!B481=FALSE,FALSE),FALSE,IF(OR('Model inputs'!B480="",'Model inputs'!B481=""),"",AND('Model inputs'!B480,'Model inputs'!B481))))="",FALSE,IF(IFERROR('Model inputs'!B480=FALSE,FALSE),FALSE,IF(IFERROR('Model inputs'!B481=FALSE,FALSE),FALSE,IF(OR('Model inputs'!B480="",'Model inputs'!B481=""),"",AND('Model inputs'!B480,'Model inputs'!B481))))),IF('Model inputs'!B142="","",'Model inputs'!B142),0)="",0,IF(IF(IF(IFERROR('Model inputs'!B480=FALSE,FALSE),FALSE,IF(IFERROR('Model inputs'!B481=FALSE,FALSE),FALSE,IF(OR('Model inputs'!B480="",'Model inputs'!B481=""),"",AND('Model inputs'!B480,'Model inputs'!B481))))="",FALSE,IF(IFERROR('Model inputs'!B480=FALSE,FALSE),FALSE,IF(IFERROR('Model inputs'!B481=FALSE,FALSE),FALSE,IF(OR('Model inputs'!B480="",'Model inputs'!B481=""),"",AND('Model inputs'!B480,'Model inputs'!B481))))),IF('Model inputs'!B142="","",'Model inputs'!B142),0)) -> 200 | K36: ='Model inputs'!B130*IF(IF(IF(IF(IFERROR('Model inputs'!B483=FALSE,FALSE),FALSE,IF(IFERROR('Model inputs'!B484=FALSE,FALSE),FALSE,IF(OR('Model inputs'!B483="",'Model inputs'!B484=""),"",AND('Model inputs'!B483,'Model inputs'!B484))))="",FALSE,IF(IFERROR('Model inputs'!B483=FALSE,FALSE),FALSE,IF(IFERROR('Model inputs'!B484=FALSE,FALSE),FALSE,IF(OR('Model inputs'!B483="",'Model inputs'!B484=""),"",AND('Model inputs'!B483,'Model inputs'!B484))))),IF('Model inputs'!B142="","",'Model inputs'!B142),0)="",0,IF(IF(IF(IFERROR('Model inputs'!B483=FALSE,FALSE),FALSE,IF(IFERROR('Model inputs'!B484=FALSE,FALSE),FALSE,IF(OR('Model inputs'!B483="",'Model inputs'!B484=""),"",AND('Model inputs'!B483,'Model inputs'!B484))))="",FALSE,IF(IFERROR('Model inputs'!B483=FALSE,FALSE),FALSE,IF(IFERROR('Model inputs'!B484=FALSE,FALSE),FALSE,IF(OR('Model inputs'!B483="",'Model inputs'!B484=""),"",AND('Model inputs'!B483,'Model inputs'!B484))))),IF('Model inputs'!B142="","",'Model inputs'!B142),0)) -> 200 | L36: ='Model inputs'!B130*IF(IF(IF(IF(IFERROR('Model inputs'!B486=FALSE,FALSE),FALSE,IF(IFERROR('Model inputs'!B487=FALSE,FALSE),FALSE,IF(OR('Model inputs'!B486="",'Model inputs'!B487=""),"",AND('Model inputs'!B486,'Model inputs'!B487))))="",FALSE,IF(IFERROR('Model inputs'!B486=FALSE,FALSE),FALSE,IF(IFERROR('Model inputs'!B487=FALSE,FALSE),FALSE,IF(OR('Model inputs'!B486="",'Model inputs'!B487=""),"",AND('Model inputs'!B486,'Model inputs'!B487))))),IF('Model inputs'!B142="","",'Model inputs'!B142),0)="",0,IF(IF(IF(IFERROR('Model inputs'!B486=FALSE,FALSE),FALSE,IF(IFERROR('Model inputs'!B487=FALSE,FALSE),FALSE,IF(OR('Model inputs'!B486="",'Model inputs'!B487=""),"",AND('Model inputs'!B486,'Model inputs'!B487))))="",FALSE,IF(IFERROR('Model inputs'!B486=FALSE,FALSE),FALSE,IF(IFERROR('Model inputs'!B487=FALSE,FALSE),FALSE,IF(OR('Model inputs'!B486="",'Model inputs'!B487=""),"",AND('Model inputs'!B486,'Model inputs'!B487))))),IF('Model inputs'!B142="","",'Model inputs'!B142),0)) -> 200 | M36: ='Model inputs'!B130*IF(IF(IF(IF(IFERROR('Model inputs'!B489=FALSE,FALSE),FALSE,IF(IFERROR('Model inputs'!B490=FALSE,FALSE),FALSE,IF(OR('Model inputs'!B489="",'Model inputs'!B490=""),"",AND('Model inputs'!B489,'Model inputs'!B490))))="",FALSE,IF(IFERROR('Model inputs'!B489=FALSE,FALSE),FALSE,IF(IFERROR('Model inputs'!B490=FALSE,FALSE),FALSE,IF(OR('Model inputs'!B489="",'Model inputs'!B490=""),"",AND('Model inputs'!B489,'Model inputs'!B490))))),IF('Model inputs'!B142="","",'Model inputs'!B142),0)="",0,IF(IF(IF(IFERROR('Model inputs'!B489=FALSE,FALSE),FALSE,IF(IFERROR('Model inputs'!B490=FALSE,FALSE),FALSE,IF(OR('Model inputs'!B489="",'Model inputs'!B490=""),"",AND('Model inputs'!B489,'Model inputs'!B490))))="",FALSE,IF(IFERROR('Model inputs'!B489=FALSE,FALSE),FALSE,IF(IFERROR('Model inputs'!B490=FALSE,FALSE),FALSE,IF(OR('Model inputs'!B489="",'Model inputs'!B490=""),"",AND('Model inputs'!B489,'Model inputs'!B490))))),IF('Model inputs'!B142="","",'Model inputs'!B142),0)) -> 200 | N36: ='Model inputs'!B130*IF(IF(IF(IF(IFERROR('Model inputs'!B492=FALSE,FALSE),FALSE,IF(IFERROR('Model inputs'!B493=FALSE,FALSE),FALSE,IF(OR('Model inputs'!B492="",'Model inputs'!B493=""),"",AND('Model inputs'!B492,'Model inputs'!B493))))="",FALSE,IF(IFERROR('Model inputs'!B492=FALSE,FALSE),FALSE,IF(IFERROR('Model inputs'!B493=FALSE,FALSE),FALSE,IF(OR('Model inputs'!B492="",'Model inputs'!B493=""),"",AND('Model inputs'!B492,'Model inputs'!B493))))),IF('Model inputs'!B142="","",'Model inputs'!B142),0)="",0,IF(IF(IF(IFERROR('Model inputs'!B492=FALSE,FALSE),FALSE,IF(IFERROR('Model inputs'!B493=FALSE,FALSE),FALSE,IF(OR('Model inputs'!B492="",'Model inputs'!B493=""),"",AND('Model inputs'!B492,'Model inputs'!B493))))="",FALSE,IF(IFERROR('Model inputs'!B492=FALSE,FALSE),FALSE,IF(IFERROR('Model inputs'!B493=FALSE,FALSE),FALSE,IF(OR('Model inputs'!B492="",'Model inputs'!B493=""),"",AND('Model inputs'!B492,'Model inputs'!B493))))),IF('Model inputs'!B142="","",'Model inputs'!B142),0)) -> 200 | O36: ='Model inputs'!B130*IF(IF(IF(IF(IFERROR('Model inputs'!B495=FALSE,FALSE),FALSE,IF(IFERROR('Model inputs'!B496=FALSE,FALSE),FALSE,IF(OR('Model inputs'!B495="",'Model inputs'!B496=""),"",AND('Model inputs'!B495,'Model inputs'!B496))))="",FALSE,IF(IFERROR('Model inputs'!B495=FALSE,FALSE),FALSE,IF(IFERROR('Model inputs'!B496=FALSE,FALSE),FALSE,IF(OR('Model inputs'!B495="",'Model inputs'!B496=""),"",AND('Model inputs'!B495,'Model inputs'!B496))))),IF('Model inputs'!B142="","",'Model inputs'!B142),0)="",0,IF(IF(IF(IFERROR('Model inputs'!B495=FALSE,FALSE),FALSE,IF(IFERROR('Model inputs'!B496=FALSE,FALSE),FALSE,IF(OR('Model inputs'!B495="",'Model inputs'!B496=""),"",AND('Model inputs'!B495,'Model inputs'!B496))))="",FALSE,IF(IFERROR('Model inputs'!B495=FALSE,FALSE),FALSE,IF(IFERROR('Model inputs'!B496=FALSE,FALSE),FALSE,IF(OR('Model inputs'!B495="",'Model inputs'!B496=""),"",AND('Model inputs'!B495,'Model inputs'!B496))))),IF('Model inputs'!B142="","",'Model inputs'!B142),0)) -> 200 | P36: ='Model inputs'!B130*IF(IF(IF(IF(IFERROR('Model inputs'!B498=FALSE,FALSE),FALSE,IF(IFERROR('Model inputs'!B499=FALSE,FALSE),FALSE,IF(OR('Model inputs'!B498="",'Model inputs'!B499=""),"",AND('Model inputs'!B498,'Model inputs'!B499))))="",FALSE,IF(IFERROR('Model inputs'!B498=FALSE,FALSE),FALSE,IF(IFERROR('Model inputs'!B499=FALSE,FALSE),FALSE,IF(OR('Model inputs'!B498="",'Model inputs'!B499=""),"",AND('Model inputs'!B498,'Model inputs'!B499))))),IF('Model inputs'!B142="","",'Model inputs'!B142),0)="",0,IF(IF(IF(IFERROR('Model inputs'!B498=FALSE,FALSE),FALSE,IF(IFERROR('Model inputs'!B499=FALSE,FALSE),FALSE,IF(OR('Model inputs'!B498="",'Model inputs'!B499=""),"",AND('Model inputs'!B498,'Model inputs'!B499))))="",FALSE,IF(IFERROR('Model inputs'!B498=FALSE,FALSE),FALSE,IF(IFERROR('Model inputs'!B499=FALSE,FALSE),FALSE,IF(OR('Model inputs'!B498="",'Model inputs'!B499=""),"",AND('Model inputs'!B498,'Model inputs'!B499))))),IF('Model inputs'!B142="","",'Model inputs'!B142),0)) -> 200 | Q36: ='Model inputs'!B130*IF(IF(IF(IF(IFERROR('Model inputs'!B501=FALSE,FALSE),FALSE,IF(IFERROR('Model inputs'!B502=FALSE,FALSE),FALSE,IF(OR('Model inputs'!B501="",'Model inputs'!B502=""),"",AND('Model inputs'!B501,'Model inputs'!B502))))="",FALSE,IF(IFERROR('Model inputs'!B501=FALSE,FALSE),FALSE,IF(IFERROR('Model inputs'!B502=FALSE,FALSE),FALSE,IF(OR('Model inputs'!B501="",'Model inputs'!B502=""),"",AND('Model inputs'!B501,'Model inputs'!B502))))),IF('Model inputs'!B142="","",'Model inputs'!B142),0)="",0,IF(IF(IF(IFERROR('Model inputs'!B501=FALSE,FALSE),FALSE,IF(IFERROR('Model inputs'!B502=FALSE,FALSE),FALSE,IF(OR('Model inputs'!B501="",'Model inputs'!B502=""),"",AND('Model inputs'!B501,'Model inputs'!B502))))="",FALSE,IF(IFERROR('Model inputs'!B501=FALSE,FALSE),FALSE,IF(IFERROR('Model inputs'!B502=FALSE,FALSE),FALSE,IF(OR('Model inputs'!B501="",'Model inputs'!B502=""),"",AND('Model inputs'!B501,'Model inputs'!B502))))),IF('Model inputs'!B142="","",'Model inputs'!B142),0)) -> 200 | R36: ='Model inputs'!B130*IF(IF(IF(IF(IFERROR('Model inputs'!B504=FALSE,FALSE),FALSE,IF(IFERROR('Model inputs'!B505=FALSE,FALSE),FALSE,IF(OR('Model inputs'!B504="",'Model inputs'!B505=""),"",AND('Model inputs'!B504,'Model inputs'!B505))))="",FALSE,IF(IFERROR('Model inputs'!B504=FALSE,FALSE),FALSE,IF(IFERROR('Model inputs'!B505=FALSE,FALSE),FALSE,IF(OR('Model inputs'!B504="",'Model inputs'!B505=""),"",AND('Model inputs'!B504,'Model inputs'!B505))))),IF('Model inputs'!B142="","",'Model inputs'!B142),0)="",0,IF(IF(IF(IFERROR('Model inputs'!B504=FALSE,FALSE),FALSE,IF(IFERROR('Model inputs'!B505=FALSE,FALSE),FALSE,IF(OR('Model inputs'!B504="",'Model inputs'!B505=""),"",AND('Model inputs'!B504,'Model inputs'!B505))))="",FALSE,IF(IFERROR('Model inputs'!B504=FALSE,FALSE),FALSE,IF(IFERROR('Model inputs'!B505=FALSE,FALSE),FALSE,IF(OR('Model inputs'!B504="",'Model inputs'!B505=""),"",AND('Model inputs'!B504,'Model inputs'!B505))))),IF('Model inputs'!B142="","",'Model inputs'!B142),0)) -> 200 | S36: ='Model inputs'!B130*IF(IF(IF(IF(IFERROR('Model inputs'!B507=FALSE,FALSE),FALSE,IF(IFERROR('Model inputs'!B508=FALSE,FALSE),FALSE,IF(OR('Model inputs'!B507="",'Model inputs'!B508=""),"",AND('Model inputs'!B507,'Model inputs'!B508))))="",FALSE,IF(IFERROR('Model inputs'!B507=FALSE,FALSE),FALSE,IF(IFERROR('Model inputs'!B508=FALSE,FALSE),FALSE,IF(OR('Model inputs'!B507="",'Model inputs'!B508=""),"",AND('Model inputs'!B507,'Model inputs'!B508))))),IF('Model inputs'!B142="","",'Model inputs'!B142),0)="",0,IF(IF(IF(IFERROR('Model inputs'!B507=FALSE,FALSE),FALSE,IF(IFERROR('Model inputs'!B508=FALSE,FALSE),FALSE,IF(OR('Model inputs'!B507="",'Model inputs'!B508=""),"",AND('Model inputs'!B507,'Model inputs'!B508))))="",FALSE,IF(IFERROR('Model inputs'!B507=FALSE,FALSE),FALSE,IF(IFERROR('Model inputs'!B508=FALSE,FALSE),FALSE,IF(OR('Model inputs'!B507="",'Model inputs'!B508=""),"",AND('Model inputs'!B507,'Model inputs'!B508))))),IF('Model inputs'!B142="","",'Model inputs'!B142),0)) -> 200 | T36: ='Model inputs'!B130*IF(IF(IF(IF(IFERROR('Model inputs'!B510=FALSE,FALSE),FALSE,IF(IFERROR('Model inputs'!B511=FALSE,FALSE),FALSE,IF(OR('Model inputs'!B510="",'Model inputs'!B511=""),"",AND('Model inputs'!B510,'Model inputs'!B511))))="",FALSE,IF(IFERROR('Model inputs'!B510=FALSE,FALSE),FALSE,IF(IFERROR('Model inputs'!B511=FALSE,FALSE),FALSE,IF(OR('Model inputs'!B510="",'Model inputs'!B511=""),"",AND('Model inputs'!B510,'Model inputs'!B511))))),IF('Model inputs'!B142="","",'Model inputs'!B142),0)="",0,IF(IF(IF(IFERROR('Model inputs'!B510=FALSE,FALSE),FALSE,IF(IFERROR('Model inputs'!B511=FALSE,FALSE),FALSE,IF(OR('Model inputs'!B510="",'Model inputs'!B511=""),"",AND('Model inputs'!B510,'Model inputs'!B511))))="",FALSE,IF(IFERROR('Model inputs'!B510=FALSE,FALSE),FALSE,IF(IFERROR('Model inputs'!B511=FALSE,FALSE),FALSE,IF(OR('Model inputs'!B510="",'Model inputs'!B511=""),"",AND('Model inputs'!B510,'Model inputs'!B511))))),IF('Model inputs'!B142="","",'Model inputs'!B142),0)) -> 200 | U36: ='Model inputs'!B130*IF(IF(IF(IF(IFERROR('Model inputs'!B513=FALSE,FALSE),FALSE,IF(IFERROR('Model inputs'!B514=FALSE,FALSE),FALSE,IF(OR('Model inputs'!B513="",'Model inputs'!B514=""),"",AND('Model inputs'!B513,'Model inputs'!B514))))="",FALSE,IF(IFERROR('Model inputs'!B513=FALSE,FALSE),FALSE,IF(IFERROR('Model inputs'!B514=FALSE,FALSE),FALSE,IF(OR('Model inputs'!B513="",'Model inputs'!B514=""),"",AND('Model inputs'!B513,'Model inputs'!B514))))),IF('Model inputs'!B142="","",'Model inputs'!B142),0)="",0,IF(IF(IF(IFERROR('Model inputs'!B513=FALSE,FALSE),FALSE,IF(IFERROR('Model inputs'!B514=FALSE,FALSE),FALSE,IF(OR('Model inputs'!B513="",'Model inputs'!B514=""),"",AND('Model inputs'!B513,'Model inputs'!B514))))="",FALSE,IF(IFERROR('Model inputs'!B513=FALSE,FALSE),FALSE,IF(IFERROR('Model inputs'!B514=FALSE,FALSE),FALSE,IF(OR('Model inputs'!B513="",'Model inputs'!B514=""),"",AND('Model inputs'!B513,'Model inputs'!B514))))),IF('Model inputs'!B142="","",'Model inputs'!B142),0)) -> 200 | V36: ='Model inputs'!B130*IF(IF(IF(IF(IFERROR('Model inputs'!B516=FALSE,FALSE),FALSE,IF(IFERROR('Model inputs'!B517=FALSE,FALSE),FALSE,IF(OR('Model inputs'!B516="",'Model inputs'!B517=""),"",AND('Model inputs'!B516,'Model inputs'!B517))))="",FALSE,IF(IFERROR('Model inputs'!B516=FALSE,FALSE),FALSE,IF(IFERROR('Model inputs'!B517=FALSE,FALSE),FALSE,IF(OR('Model inputs'!B516="",'Model inputs'!B517=""),"",AND('Model inputs'!B516,'Model inputs'!B517))))),IF('Model inputs'!B142="","",'Model inputs'!B142),0)="",0,IF(IF(IF(IFERROR('Model inputs'!B516=FALSE,FALSE),FALSE,IF(IFERROR('Model inputs'!B517=FALSE,FALSE),FALSE,IF(OR('Model inputs'!B516="",'Model inputs'!B517=""),"",AND('Model inputs'!B516,'Model inputs'!B517))))="",FALSE,IF(IFERROR('Model inputs'!B516=FALSE,FALSE),FALSE,IF(IFERROR('Model inputs'!B517=FALSE,FALSE),FALSE,IF(OR('Model inputs'!B516="",'Model inputs'!B517=""),"",AND('Model inputs'!B516,'Model inputs'!B517))))),IF('Model inputs'!B142="","",'Model inputs'!B142),0)) -> 200
A37: Opex > First engineer (loaded) | C37: ='Model inputs'!B131*IF(IF(IF(IF(IFERROR('Model inputs'!B519=FALSE,FALSE),FALSE,IF(IFERROR('Model inputs'!B520=FALSE,FALSE),FALSE,IF(OR('Model inputs'!B519="",'Model inputs'!B520=""),"",AND('Model inputs'!B519,'Model inputs'!B520))))="",FALSE,IF(IFERROR('Model inputs'!B519=FALSE,FALSE),FALSE,IF(IFERROR('Model inputs'!B520=FALSE,FALSE),FALSE,IF(OR('Model inputs'!B519="",'Model inputs'!B520=""),"",AND('Model inputs'!B519,'Model inputs'!B520))))),IF('Model inputs'!B143="","",'Model inputs'!B143),0)="",0,IF(IF(IF(IFERROR('Model inputs'!B519=FALSE,FALSE),FALSE,IF(IFERROR('Model inputs'!B520=FALSE,FALSE),FALSE,IF(OR('Model inputs'!B519="",'Model inputs'!B520=""),"",AND('Model inputs'!B519,'Model inputs'!B520))))="",FALSE,IF(IFERROR('Model inputs'!B519=FALSE,FALSE),FALSE,IF(IFERROR('Model inputs'!B520=FALSE,FALSE),FALSE,IF(OR('Model inputs'!B519="",'Model inputs'!B520=""),"",AND('Model inputs'!B519,'Model inputs'!B520))))),IF('Model inputs'!B143="","",'Model inputs'!B143),0)) -> 0 | D37: ='Model inputs'!B131*IF(IF(IF(IF(IFERROR('Model inputs'!B522=FALSE,FALSE),FALSE,IF(IFERROR('Model inputs'!B523=FALSE,FALSE),FALSE,IF(OR('Model inputs'!B522="",'Model inputs'!B523=""),"",AND('Model inputs'!B522,'Model inputs'!B523))))="",FALSE,IF(IFERROR('Model inputs'!B522=FALSE,FALSE),FALSE,IF(IFERROR('Model inputs'!B523=FALSE,FALSE),FALSE,IF(OR('Model inputs'!B522="",'Model inputs'!B523=""),"",AND('Model inputs'!B522,'Model inputs'!B523))))),IF('Model inputs'!B143="","",'Model inputs'!B143),0)="",0,IF(IF(IF(IFERROR('Model inputs'!B522=FALSE,FALSE),FALSE,IF(IFERROR('Model inputs'!B523=FALSE,FALSE),FALSE,IF(OR('Model inputs'!B522="",'Model inputs'!B523=""),"",AND('Model inputs'!B522,'Model inputs'!B523))))="",FALSE,IF(IFERROR('Model inputs'!B522=FALSE,FALSE),FALSE,IF(IFERROR('Model inputs'!B523=FALSE,FALSE),FALSE,IF(OR('Model inputs'!B522="",'Model inputs'!B523=""),"",AND('Model inputs'!B522,'Model inputs'!B523))))),IF('Model inputs'!B143="","",'Model inputs'!B143),0)) -> 0 | E37: ='Model inputs'!B131*IF(IF(IF(IF(IFERROR('Model inputs'!B525=FALSE,FALSE),FALSE,IF(IFERROR('Model inputs'!B526=FALSE,FALSE),FALSE,IF(OR('Model inputs'!B525="",'Model inputs'!B526=""),"",AND('Model inputs'!B525,'Model inputs'!B526))))="",FALSE,IF(IFERROR('Model inputs'!B525=FALSE,FALSE),FALSE,IF(IFERROR('Model inputs'!B526=FALSE,FALSE),FALSE,IF(OR('Model inputs'!B525="",'Model inputs'!B526=""),"",AND('Model inputs'!B525,'Model inputs'!B526))))),IF('Model inputs'!B143="","",'Model inputs'!B143),0)="",0,IF(IF(IF(IFERROR('Model inputs'!B525=FALSE,FALSE),FALSE,IF(IFERROR('Model inputs'!B526=FALSE,FALSE),FALSE,IF(OR('Model inputs'!B525="",'Model inputs'!B526=""),"",AND('Model inputs'!B525,'Model inputs'!B526))))="",FALSE,IF(IFERROR('Model inputs'!B525=FALSE,FALSE),FALSE,IF(IFERROR('Model inputs'!B526=FALSE,FALSE),FALSE,IF(OR('Model inputs'!B525="",'Model inputs'!B526=""),"",AND('Model inputs'!B525,'Model inputs'!B526))))),IF('Model inputs'!B143="","",'Model inputs'!B143),0)) -> 0 | F37: ='Model inputs'!B131*IF(IF(IF(IF(IFERROR('Model inputs'!B528=FALSE,FALSE),FALSE,IF(IFERROR('Model inputs'!B529=FALSE,FALSE),FALSE,IF(OR('Model inputs'!B528="",'Model inputs'!B529=""),"",AND('Model inputs'!B528,'Model inputs'!B529))))="",FALSE,IF(IFERROR('Model inputs'!B528=FALSE,FALSE),FALSE,IF(IFERROR('Model inputs'!B529=FALSE,FALSE),FALSE,IF(OR('Model inputs'!B528="",'Model inputs'!B529=""),"",AND('Model inputs'!B528,'Model inputs'!B529))))),IF('Model inputs'!B143="","",'Model inputs'!B143),0)="",0,IF(IF(IF(IFERROR('Model inputs'!B528=FALSE,FALSE),FALSE,IF(IFERROR('Model inputs'!B529=FALSE,FALSE),FALSE,IF(OR('Model inputs'!B528="",'Model inputs'!B529=""),"",AND('Model inputs'!B528,'Model inputs'!B529))))="",FALSE,IF(IFERROR('Model inputs'!B528=FALSE,FALSE),FALSE,IF(IFERROR('Model inputs'!B529=FALSE,FALSE),FALSE,IF(OR('Model inputs'!B528="",'Model inputs'!B529=""),"",AND('Model inputs'!B528,'Model inputs'!B529))))),IF('Model inputs'!B143="","",'Model inputs'!B143),0)) -> 0 | G37: ='Model inputs'!B131*IF(IF(IF(IF(IFERROR('Model inputs'!B531=FALSE,FALSE),FALSE,IF(IFERROR('Model inputs'!B532=FALSE,FALSE),FALSE,IF(OR('Model inputs'!B531="",'Model inputs'!B532=""),"",AND('Model inputs'!B531,'Model inputs'!B532))))="",FALSE,IF(IFERROR('Model inputs'!B531=FALSE,FALSE),FALSE,IF(IFERROR('Model inputs'!B532=FALSE,FALSE),FALSE,IF(OR('Model inputs'!B531="",'Model inputs'!B532=""),"",AND('Model inputs'!B531,'Model inputs'!B532))))),IF('Model inputs'!B143="","",'Model inputs'!B143),0)="",0,IF(IF(IF(IFERROR('Model inputs'!B531=FALSE,FALSE),FALSE,IF(IFERROR('Model inputs'!B532=FALSE,FALSE),FALSE,IF(OR('Model inputs'!B531="",'Model inputs'!B532=""),"",AND('Model inputs'!B531,'Model inputs'!B532))))="",FALSE,IF(IFERROR('Model inputs'!B531=FALSE,FALSE),FALSE,IF(IFERROR('Model inputs'!B532=FALSE,FALSE),FALSE,IF(OR('Model inputs'!B531="",'Model inputs'!B532=""),"",AND('Model inputs'!B531,'Model inputs'!B532))))),IF('Model inputs'!B143="","",'Model inputs'!B143),0)) -> 0 | H37: ='Model inputs'!B131*IF(IF(IF(IF(IFERROR('Model inputs'!B534=FALSE,FALSE),FALSE,IF(IFERROR('Model inputs'!B535=FALSE,FALSE),FALSE,IF(OR('Model inputs'!B534="",'Model inputs'!B535=""),"",AND('Model inputs'!B534,'Model inputs'!B535))))="",FALSE,IF(IFERROR('Model inputs'!B534=FALSE,FALSE),FALSE,IF(IFERROR('Model inputs'!B535=FALSE,FALSE),FALSE,IF(OR('Model inputs'!B534="",'Model inputs'!B535=""),"",AND('Model inputs'!B534,'Model inputs'!B535))))),IF('Model inputs'!B143="","",'Model inputs'!B143),0)="",0,IF(IF(IF(IFERROR('Model inputs'!B534=FALSE,FALSE),FALSE,IF(IFERROR('Model inputs'!B535=FALSE,FALSE),FALSE,IF(OR('Model inputs'!B534="",'Model inputs'!B535=""),"",AND('Model inputs'!B534,'Model inputs'!B535))))="",FALSE,IF(IFERROR('Model inputs'!B534=FALSE,FALSE),FALSE,IF(IFERROR('Model inputs'!B535=FALSE,FALSE),FALSE,IF(OR('Model inputs'!B534="",'Model inputs'!B535=""),"",AND('Model inputs'!B534,'Model inputs'!B535))))),IF('Model inputs'!B143="","",'Model inputs'!B143),0)) -> 0 | I37: ='Model inputs'!B131*IF(IF(IF(IF(IFERROR('Model inputs'!B537=FALSE,FALSE),FALSE,IF(IFERROR('Model inputs'!B538=FALSE,FALSE),FALSE,IF(OR('Model inputs'!B537="",'Model inputs'!B538=""),"",AND('Model inputs'!B537,'Model inputs'!B538))))="",FALSE,IF(IFERROR('Model inputs'!B537=FALSE,FALSE),FALSE,IF(IFERROR('Model inputs'!B538=FALSE,FALSE),FALSE,IF(OR('Model inputs'!B537="",'Model inputs'!B538=""),"",AND('Model inputs'!B537,'Model inputs'!B538))))),IF('Model inputs'!B143="","",'Model inputs'!B143),0)="",0,IF(IF(IF(IFERROR('Model inputs'!B537=FALSE,FALSE),FALSE,IF(IFERROR('Model inputs'!B538=FALSE,FALSE),FALSE,IF(OR('Model inputs'!B537="",'Model inputs'!B538=""),"",AND('Model inputs'!B537,'Model inputs'!B538))))="",FALSE,IF(IFERROR('Model inputs'!B537=FALSE,FALSE),FALSE,IF(IFERROR('Model inputs'!B538=FALSE,FALSE),FALSE,IF(OR('Model inputs'!B537="",'Model inputs'!B538=""),"",AND('Model inputs'!B537,'Model inputs'!B538))))),IF('Model inputs'!B143="","",'Model inputs'!B143),0)) -> 0 | J37: ='Model inputs'!B131*IF(IF(IF(IF(IFERROR('Model inputs'!B540=FALSE,FALSE),FALSE,IF(IFERROR('Model inputs'!B541=FALSE,FALSE),FALSE,IF(OR('Model inputs'!B540="",'Model inputs'!B541=""),"",AND('Model inputs'!B540,'Model inputs'!B541))))="",FALSE,IF(IFERROR('Model inputs'!B540=FALSE,FALSE),FALSE,IF(IFERROR('Model inputs'!B541=FALSE,FALSE),FALSE,IF(OR('Model inputs'!B540="",'Model inputs'!B541=""),"",AND('Model inputs'!B540,'Model inputs'!B541))))),IF('Model inputs'!B143="","",'Model inputs'!B143),0)="",0,IF(IF(IF(IFERROR('Model inputs'!B540=FALSE,FALSE),FALSE,IF(IFERROR('Model inputs'!B541=FALSE,FALSE),FALSE,IF(OR('Model inputs'!B540="",'Model inputs'!B541=""),"",AND('Model inputs'!B540,'Model inputs'!B541))))="",FALSE,IF(IFERROR('Model inputs'!B540=FALSE,FALSE),FALSE,IF(IFERROR('Model inputs'!B541=FALSE,FALSE),FALSE,IF(OR('Model inputs'!B540="",'Model inputs'!B541=""),"",AND('Model inputs'!B540,'Model inputs'!B541))))),IF('Model inputs'!B143="","",'Model inputs'!B143),0)) -> 0 | K37: ='Model inputs'!B131*IF(IF(IF(IF(IFERROR('Model inputs'!B543=FALSE,FALSE),FALSE,IF(IFERROR('Model inputs'!B544=FALSE,FALSE),FALSE,IF(OR('Model inputs'!B543="",'Model inputs'!B544=""),"",AND('Model inputs'!B543,'Model inputs'!B544))))="",FALSE,IF(IFERROR('Model inputs'!B543=FALSE,FALSE),FALSE,IF(IFERROR('Model inputs'!B544=FALSE,FALSE),FALSE,IF(OR('Model inputs'!B543="",'Model inputs'!B544=""),"",AND('Model inputs'!B543,'Model inputs'!B544))))),IF('Model inputs'!B143="","",'Model inputs'!B143),0)="",0,IF(IF(IF(IFERROR('Model inputs'!B543=FALSE,FALSE),FALSE,IF(IFERROR('Model inputs'!B544=FALSE,FALSE),FALSE,IF(OR('Model inputs'!B543="",'Model inputs'!B544=""),"",AND('Model inputs'!B543,'Model inputs'!B544))))="",FALSE,IF(IFERROR('Model inputs'!B543=FALSE,FALSE),FALSE,IF(IFERROR('Model inputs'!B544=FALSE,FALSE),FALSE,IF(OR('Model inputs'!B543="",'Model inputs'!B544=""),"",AND('Model inputs'!B543,'Model inputs'!B544))))),IF('Model inputs'!B143="","",'Model inputs'!B143),0)) -> 0 | L37: ='Model inputs'!B131*IF(IF(IF(IF(IFERROR('Model inputs'!B546=FALSE,FALSE),FALSE,IF(IFERROR('Model inputs'!B547=FALSE,FALSE),FALSE,IF(OR('Model inputs'!B546="",'Model inputs'!B547=""),"",AND('Model inputs'!B546,'Model inputs'!B547))))="",FALSE,IF(IFERROR('Model inputs'!B546=FALSE,FALSE),FALSE,IF(IFERROR('Model inputs'!B547=FALSE,FALSE),FALSE,IF(OR('Model inputs'!B546="",'Model inputs'!B547=""),"",AND('Model inputs'!B546,'Model inputs'!B547))))),IF('Model inputs'!B143="","",'Model inputs'!B143),0)="",0,IF(IF(IF(IFERROR('Model inputs'!B546=FALSE,FALSE),FALSE,IF(IFERROR('Model inputs'!B547=FALSE,FALSE),FALSE,IF(OR('Model inputs'!B546="",'Model inputs'!B547=""),"",AND('Model inputs'!B546,'Model inputs'!B547))))="",FALSE,IF(IFERROR('Model inputs'!B546=FALSE,FALSE),FALSE,IF(IFERROR('Model inputs'!B547=FALSE,FALSE),FALSE,IF(OR('Model inputs'!B546="",'Model inputs'!B547=""),"",AND('Model inputs'!B546,'Model inputs'!B547))))),IF('Model inputs'!B143="","",'Model inputs'!B143),0)) -> 0 | M37: ='Model inputs'!B131*IF(IF(IF(IF(IFERROR('Model inputs'!B549=FALSE,FALSE),FALSE,IF(IFERROR('Model inputs'!B550=FALSE,FALSE),FALSE,IF(OR('Model inputs'!B549="",'Model inputs'!B550=""),"",AND('Model inputs'!B549,'Model inputs'!B550))))="",FALSE,IF(IFERROR('Model inputs'!B549=FALSE,FALSE),FALSE,IF(IFERROR('Model inputs'!B550=FALSE,FALSE),FALSE,IF(OR('Model inputs'!B549="",'Model inputs'!B550=""),"",AND('Model inputs'!B549,'Model inputs'!B550))))),IF('Model inputs'!B143="","",'Model inputs'!B143),0)="",0,IF(IF(IF(IFERROR('Model inputs'!B549=FALSE,FALSE),FALSE,IF(IFERROR('Model inputs'!B550=FALSE,FALSE),FALSE,IF(OR('Model inputs'!B549="",'Model inputs'!B550=""),"",AND('Model inputs'!B549,'Model inputs'!B550))))="",FALSE,IF(IFERROR('Model inputs'!B549=FALSE,FALSE),FALSE,IF(IFERROR('Model inputs'!B550=FALSE,FALSE),FALSE,IF(OR('Model inputs'!B549="",'Model inputs'!B550=""),"",AND('Model inputs'!B549,'Model inputs'!B550))))),IF('Model inputs'!B143="","",'Model inputs'!B143),0)) -> 0 | N37: ='Model inputs'!B131*IF(IF(IF(IF(IFERROR('Model inputs'!B552=FALSE,FALSE),FALSE,IF(IFERROR('Model inputs'!B553=FALSE,FALSE),FALSE,IF(OR('Model inputs'!B552="",'Model inputs'!B553=""),"",AND('Model inputs'!B552,'Model inputs'!B553))))="",FALSE,IF(IFERROR('Model inputs'!B552=FALSE,FALSE),FALSE,IF(IFERROR('Model inputs'!B553=FALSE,FALSE),FALSE,IF(OR('Model inputs'!B552="",'Model inputs'!B553=""),"",AND('Model inputs'!B552,'Model inputs'!B553))))),IF('Model inputs'!B143="","",'Model inputs'!B143),0)="",0,IF(IF(IF(IFERROR('Model inputs'!B552=FALSE,FALSE),FALSE,IF(IFERROR('Model inputs'!B553=FALSE,FALSE),FALSE,IF(OR('Model inputs'!B552="",'Model inputs'!B553=""),"",AND('Model inputs'!B552,'Model inputs'!B553))))="",FALSE,IF(IFERROR('Model inputs'!B552=FALSE,FALSE),FALSE,IF(IFERROR('Model inputs'!B553=FALSE,FALSE),FALSE,IF(OR('Model inputs'!B552="",'Model inputs'!B553=""),"",AND('Model inputs'!B552,'Model inputs'!B553))))),IF('Model inputs'!B143="","",'Model inputs'!B143),0)) -> 0 | O37: ='Model inputs'!B131*IF(IF(IF(IF(IFERROR('Model inputs'!B555=FALSE,FALSE),FALSE,IF(IFERROR('Model inputs'!B556=FALSE,FALSE),FALSE,IF(OR('Model inputs'!B555="",'Model inputs'!B556=""),"",AND('Model inputs'!B555,'Model inputs'!B556))))="",FALSE,IF(IFERROR('Model inputs'!B555=FALSE,FALSE),FALSE,IF(IFERROR('Model inputs'!B556=FALSE,FALSE),FALSE,IF(OR('Model inputs'!B555="",'Model inputs'!B556=""),"",AND('Model inputs'!B555,'Model inputs'!B556))))),IF('Model inputs'!B143="","",'Model inputs'!B143),0)="",0,IF(IF(IF(IFERROR('Model inputs'!B555=FALSE,FALSE),FALSE,IF(IFERROR('Model inputs'!B556=FALSE,FALSE),FALSE,IF(OR('Model inputs'!B555="",'Model inputs'!B556=""),"",AND('Model inputs'!B555,'Model inputs'!B556))))="",FALSE,IF(IFERROR('Model inputs'!B555=FALSE,FALSE),FALSE,IF(IFERROR('Model inputs'!B556=FALSE,FALSE),FALSE,IF(OR('Model inputs'!B555="",'Model inputs'!B556=""),"",AND('Model inputs'!B555,'Model inputs'!B556))))),IF('Model inputs'!B143="","",'Model inputs'!B143),0)) -> 0 | P37: ='Model inputs'!B131*IF(IF(IF(IF(IFERROR('Model inputs'!B558=FALSE,FALSE),FALSE,IF(IFERROR('Model inputs'!B559=FALSE,FALSE),FALSE,IF(OR('Model inputs'!B558="",'Model inputs'!B559=""),"",AND('Model inputs'!B558,'Model inputs'!B559))))="",FALSE,IF(IFERROR('Model inputs'!B558=FALSE,FALSE),FALSE,IF(IFERROR('Model inputs'!B559=FALSE,FALSE),FALSE,IF(OR('Model inputs'!B558="",'Model inputs'!B559=""),"",AND('Model inputs'!B558,'Model inputs'!B559))))),IF('Model inputs'!B143="","",'Model inputs'!B143),0)="",0,IF(IF(IF(IFERROR('Model inputs'!B558=FALSE,FALSE),FALSE,IF(IFERROR('Model inputs'!B559=FALSE,FALSE),FALSE,IF(OR('Model inputs'!B558="",'Model inputs'!B559=""),"",AND('Model inputs'!B558,'Model inputs'!B559))))="",FALSE,IF(IFERROR('Model inputs'!B558=FALSE,FALSE),FALSE,IF(IFERROR('Model inputs'!B559=FALSE,FALSE),FALSE,IF(OR('Model inputs'!B558="",'Model inputs'!B559=""),"",AND('Model inputs'!B558,'Model inputs'!B559))))),IF('Model inputs'!B143="","",'Model inputs'!B143),0)) -> 0 | Q37: ='Model inputs'!B131*IF(IF(IF(IF(IFERROR('Model inputs'!B561=FALSE,FALSE),FALSE,IF(IFERROR('Model inputs'!B562=FALSE,FALSE),FALSE,IF(OR('Model inputs'!B561="",'Model inputs'!B562=""),"",AND('Model inputs'!B561,'Model inputs'!B562))))="",FALSE,IF(IFERROR('Model inputs'!B561=FALSE,FALSE),FALSE,IF(IFERROR('Model inputs'!B562=FALSE,FALSE),FALSE,IF(OR('Model inputs'!B561="",'Model inputs'!B562=""),"",AND('Model inputs'!B561,'Model inputs'!B562))))),IF('Model inputs'!B143="","",'Model inputs'!B143),0)="",0,IF(IF(IF(IFERROR('Model inputs'!B561=FALSE,FALSE),FALSE,IF(IFERROR('Model inputs'!B562=FALSE,FALSE),FALSE,IF(OR('Model inputs'!B561="",'Model inputs'!B562=""),"",AND('Model inputs'!B561,'Model inputs'!B562))))="",FALSE,IF(IFERROR('Model inputs'!B561=FALSE,FALSE),FALSE,IF(IFERROR('Model inputs'!B562=FALSE,FALSE),FALSE,IF(OR('Model inputs'!B561="",'Model inputs'!B562=""),"",AND('Model inputs'!B561,'Model inputs'!B562))))),IF('Model inputs'!B143="","",'Model inputs'!B143),0)) -> 0 | R37: ='Model inputs'!B131*IF(IF(IF(IF(IFERROR('Model inputs'!B564=FALSE,FALSE),FALSE,IF(IFERROR('Model inputs'!B565=FALSE,FALSE),FALSE,IF(OR('Model inputs'!B564="",'Model inputs'!B565=""),"",AND('Model inputs'!B564,'Model inputs'!B565))))="",FALSE,IF(IFERROR('Model inputs'!B564=FALSE,FALSE),FALSE,IF(IFERROR('Model inputs'!B565=FALSE,FALSE),FALSE,IF(OR('Model inputs'!B564="",'Model inputs'!B565=""),"",AND('Model inputs'!B564,'Model inputs'!B565))))),IF('Model inputs'!B143="","",'Model inputs'!B143),0)="",0,IF(IF(IF(IFERROR('Model inputs'!B564=FALSE,FALSE),FALSE,IF(IFERROR('Model inputs'!B565=FALSE,FALSE),FALSE,IF(OR('Model inputs'!B564="",'Model inputs'!B565=""),"",AND('Model inputs'!B564,'Model inputs'!B565))))="",FALSE,IF(IFERROR('Model inputs'!B564=FALSE,FALSE),FALSE,IF(IFERROR('Model inputs'!B565=FALSE,FALSE),FALSE,IF(OR('Model inputs'!B564="",'Model inputs'!B565=""),"",AND('Model inputs'!B564,'Model inputs'!B565))))),IF('Model inputs'!B143="","",'Model inputs'!B143),0)) -> 0 | S37: ='Model inputs'!B131*IF(IF(IF(IF(IFERROR('Model inputs'!B567=FALSE,FALSE),FALSE,IF(IFERROR('Model inputs'!B568=FALSE,FALSE),FALSE,IF(OR('Model inputs'!B567="",'Model inputs'!B568=""),"",AND('Model inputs'!B567,'Model inputs'!B568))))="",FALSE,IF(IFERROR('Model inputs'!B567=FALSE,FALSE),FALSE,IF(IFERROR('Model inputs'!B568=FALSE,FALSE),FALSE,IF(OR('Model inputs'!B567="",'Model inputs'!B568=""),"",AND('Model inputs'!B567,'Model inputs'!B568))))),IF('Model inputs'!B143="","",'Model inputs'!B143),0)="",0,IF(IF(IF(IFERROR('Model inputs'!B567=FALSE,FALSE),FALSE,IF(IFERROR('Model inputs'!B568=FALSE,FALSE),FALSE,IF(OR('Model inputs'!B567="",'Model inputs'!B568=""),"",AND('Model inputs'!B567,'Model inputs'!B568))))="",FALSE,IF(IFERROR('Model inputs'!B567=FALSE,FALSE),FALSE,IF(IFERROR('Model inputs'!B568=FALSE,FALSE),FALSE,IF(OR('Model inputs'!B567="",'Model inputs'!B568=""),"",AND('Model inputs'!B567,'Model inputs'!B568))))),IF('Model inputs'!B143="","",'Model inputs'!B143),0)) -> 0 | T37: ='Model inputs'!B131*IF(IF(IF(IF(IFERROR('Model inputs'!B570=FALSE,FALSE),FALSE,IF(IFERROR('Model inputs'!B571=FALSE,FALSE),FALSE,IF(OR('Model inputs'!B570="",'Model inputs'!B571=""),"",AND('Model inputs'!B570,'Model inputs'!B571))))="",FALSE,IF(IFERROR('Model inputs'!B570=FALSE,FALSE),FALSE,IF(IFERROR('Model inputs'!B571=FALSE,FALSE),FALSE,IF(OR('Model inputs'!B570="",'Model inputs'!B571=""),"",AND('Model inputs'!B570,'Model inputs'!B571))))),IF('Model inputs'!B143="","",'Model inputs'!B143),0)="",0,IF(IF(IF(IFERROR('Model inputs'!B570=FALSE,FALSE),FALSE,IF(IFERROR('Model inputs'!B571=FALSE,FALSE),FALSE,IF(OR('Model inputs'!B570="",'Model inputs'!B571=""),"",AND('Model inputs'!B570,'Model inputs'!B571))))="",FALSE,IF(IFERROR('Model inputs'!B570=FALSE,FALSE),FALSE,IF(IFERROR('Model inputs'!B571=FALSE,FALSE),FALSE,IF(OR('Model inputs'!B570="",'Model inputs'!B571=""),"",AND('Model inputs'!B570,'Model inputs'!B571))))),IF('Model inputs'!B143="","",'Model inputs'!B143),0)) -> 0 | U37: ='Model inputs'!B131*IF(IF(IF(IF(IFERROR('Model inputs'!B573=FALSE,FALSE),FALSE,IF(IFERROR('Model inputs'!B574=FALSE,FALSE),FALSE,IF(OR('Model inputs'!B573="",'Model inputs'!B574=""),"",AND('Model inputs'!B573,'Model inputs'!B574))))="",FALSE,IF(IFERROR('Model inputs'!B573=FALSE,FALSE),FALSE,IF(IFERROR('Model inputs'!B574=FALSE,FALSE),FALSE,IF(OR('Model inputs'!B573="",'Model inputs'!B574=""),"",AND('Model inputs'!B573,'Model inputs'!B574))))),IF('Model inputs'!B143="","",'Model inputs'!B143),0)="",0,IF(IF(IF(IFERROR('Model inputs'!B573=FALSE,FALSE),FALSE,IF(IFERROR('Model inputs'!B574=FALSE,FALSE),FALSE,IF(OR('Model inputs'!B573="",'Model inputs'!B574=""),"",AND('Model inputs'!B573,'Model inputs'!B574))))="",FALSE,IF(IFERROR('Model inputs'!B573=FALSE,FALSE),FALSE,IF(IFERROR('Model inputs'!B574=FALSE,FALSE),FALSE,IF(OR('Model inputs'!B573="",'Model inputs'!B574=""),"",AND('Model inputs'!B573,'Model inputs'!B574))))),IF('Model inputs'!B143="","",'Model inputs'!B143),0)) -> 0 | V37: ='Model inputs'!B131*IF(IF(IF(IF(IFERROR('Model inputs'!B576=FALSE,FALSE),FALSE,IF(IFERROR('Model inputs'!B577=FALSE,FALSE),FALSE,IF(OR('Model inputs'!B576="",'Model inputs'!B577=""),"",AND('Model inputs'!B576,'Model inputs'!B577))))="",FALSE,IF(IFERROR('Model inputs'!B576=FALSE,FALSE),FALSE,IF(IFERROR('Model inputs'!B577=FALSE,FALSE),FALSE,IF(OR('Model inputs'!B576="",'Model inputs'!B577=""),"",AND('Model inputs'!B576,'Model inputs'!B577))))),IF('Model inputs'!B143="","",'Model inputs'!B143),0)="",0,IF(IF(IF(IFERROR('Model inputs'!B576=FALSE,FALSE),FALSE,IF(IFERROR('Model inputs'!B577=FALSE,FALSE),FALSE,IF(OR('Model inputs'!B576="",'Model inputs'!B577=""),"",AND('Model inputs'!B576,'Model inputs'!B577))))="",FALSE,IF(IFERROR('Model inputs'!B576=FALSE,FALSE),FALSE,IF(IFERROR('Model inputs'!B577=FALSE,FALSE),FALSE,IF(OR('Model inputs'!B576="",'Model inputs'!B577=""),"",AND('Model inputs'!B576,'Model inputs'!B577))))),IF('Model inputs'!B143="","",'Model inputs'!B143),0)) -> 0
