Workbook

Sheet RC Unit economics
A1: RC Unit economics
A2: RC Unit economics · Main Scenario
A4: Variable / dimension | B4: 2026-11 | C4: 2026-12 | D4: 2027-01 | E4: 2027-02 | F4: 2027-03 | G4: 2027-04 | H4: 2027-05 | I4: 2027-06 | J4: 2027-07 | K4: 2027-08 | L4: 2027-09 | M4: 2027-10 | N4: 2027-11 | O4: 2027-12 | P4: 2028-01 | Q4: 2028-02 | R4: 2028-03 | S4: 2028-04
A5: Ending customers | B5: =SUM('RC Unit economics'!B6,'RC Unit economics'!B7,'RC Unit economics'!B8) -> 47 | C5: =SUM('RC Unit economics'!C6,'RC Unit economics'!C7,'RC Unit economics'!C8) -> 84.905 | D5: =SUM('RC Unit economics'!D6,'RC Unit economics'!D7,'RC Unit economics'!D8) -> 110.9505 | E5: =SUM('RC Unit economics'!E6,'RC Unit economics'!E7,'RC Unit economics'!E8) -> 138.05103 | F5: =SUM('RC Unit economics'!F6,'RC Unit economics'!F7,'RC Unit economics'!F8) -> 166.36012 | G5: =SUM('RC Unit economics'!G6,'RC Unit economics'!G7,'RC Unit economics'!G8) -> 196.04007 | H5: =SUM('RC Unit economics'!H6,'RC Unit economics'!H7,'RC Unit economics'!H8) -> 227.26287 | I5: =SUM('RC Unit economics'!I6,'RC Unit economics'!I7,'RC Unit economics'!I8) -> 260.21141 | ... S5: =SUM('RC Unit economics'!S6,'RC Unit economics'!S7,'RC Unit economics'!S8) -> 621.23762
A6: Indie | B6: ='Model inputs'!C43+'Model inputs'!C48+'Model inputs'!C68+'Model inputs'!C60-'Model inputs'!C11-'Model inputs'!C64 -> 40 | C6: ='Model inputs'!D43+'Model inputs'!D48+'Model inputs'!D68+'Model inputs'!D60-'Model inputs'!D11-'Model inputs'!D64 -> 74.333333 | D6: ='Model inputs'!E43+'Model inputs'!E48+'Model inputs'!E68+'Model inputs'!E60-'Model inputs'!E11-'Model inputs'!E64 -> 96.377778 | E6: ='Model inputs'!F43+'Model inputs'!F48+'Model inputs'!F68+'Model inputs'!F60-'Model inputs'!F11-'Model inputs'!F64 -> 119.11259 | F6: ='Model inputs'!G43+'Model inputs'!G48+'Model inputs'!G68+'Model inputs'!G60-'Model inputs'!G11-'Model inputs'!G64 -> 142.66455 | G6: ='Model inputs'!H43+'Model inputs'!H48+'Model inputs'!H68+'Model inputs'!H60-'Model inputs'!H11-'Model inputs'!H64 -> 167.16581 | H6: ='Model inputs'!I43+'Model inputs'!I48+'Model inputs'!I68+'Model inputs'!I60-'Model inputs'!I11-'Model inputs'!I64 -> 192.75462 | I6: ='Model inputs'!J43+'Model inputs'!J48+'Model inputs'!J68+'Model inputs'!J60-'Model inputs'!J11-'Model inputs'!J64 -> 219.57617 | ... S6: ='Model inputs'!T43+'Model inputs'!T48+'Model inputs'!T68+'Model inputs'!T60-'Model inputs'!T11-'Model inputs'!T64 -> 503.23671
A7: Launch | B7: ='Model inputs'!C44+'Model inputs'!C49+'Model inputs'!C69+'Model inputs'!C61-'Model inputs'!C12-'Model inputs'!C65 -> 1 | C7: ='Model inputs'!D44+'Model inputs'!D49+'Model inputs'!D69+'Model inputs'!D61-'Model inputs'!D12-'Model inputs'!D65 -> 1.51 | D7: ='Model inputs'!E44+'Model inputs'!E49+'Model inputs'!E69+'Model inputs'!E61-'Model inputs'!E12-'Model inputs'!E65 -> 2.0251069 | E7: ='Model inputs'!F44+'Model inputs'!F49+'Model inputs'!F69+'Model inputs'!F61-'Model inputs'!F12-'Model inputs'!F65 -> 2.5470121 | F7: ='Model inputs'!G44+'Model inputs'!G49+'Model inputs'!G69+'Model inputs'!G61-'Model inputs'!G12-'Model inputs'!G65 -> 3.0771045 | G7: ='Model inputs'!H44+'Model inputs'!H49+'Model inputs'!H69+'Model inputs'!H61-'Model inputs'!H12-'Model inputs'!H65 -> 3.6168582 | H7: ='Model inputs'!I44+'Model inputs'!I49+'Model inputs'!I69+'Model inputs'!I61-'Model inputs'!I12-'Model inputs'!I65 -> 4.1678445 | I7: ='Model inputs'!J44+'Model inputs'!J49+'Model inputs'!J69+'Model inputs'!J61-'Model inputs'!J12-'Model inputs'!J65 -> 4.7317452 | ... S7: ='Model inputs'!T44+'Model inputs'!T49+'Model inputs'!T69+'Model inputs'!T61-'Model inputs'!T12-'Model inputs'!T65 -> 11.344724
A8: Team | B8: ='Model inputs'!C45+'Model inputs'!C50+'Model inputs'!C70+'Model inputs'!C62-'Model inputs'!C13-'Model inputs'!C66 -> 6 | C8: ='Model inputs'!D45+'Model inputs'!D50+'Model inputs'!D70+'Model inputs'!D62-'Model inputs'!D13-'Model inputs'!D66 -> 9.0616667 | D8: ='Model inputs'!E45+'Model inputs'!E50+'Model inputs'!E70+'Model inputs'!E62-'Model inputs'!E13-'Model inputs'!E66 -> 12.547615 | E8: ='Model inputs'!F45+'Model inputs'!F50+'Model inputs'!F70+'Model inputs'!F62-'Model inputs'!F13-'Model inputs'!F66 -> 16.391424 | F8: ='Model inputs'!G45+'Model inputs'!G50+'Model inputs'!G70+'Model inputs'!G62-'Model inputs'!G13-'Model inputs'!G66 -> 20.618467 | G8: ='Model inputs'!H45+'Model inputs'!H50+'Model inputs'!H70+'Model inputs'!H62-'Model inputs'!H13-'Model inputs'!H66 -> 25.2574 | H8: ='Model inputs'!I45+'Model inputs'!I50+'Model inputs'!I70+'Model inputs'!I62-'Model inputs'!I13-'Model inputs'!I66 -> 30.340408 | I8: ='Model inputs'!J45+'Model inputs'!J50+'Model inputs'!J70+'Model inputs'!J62-'Model inputs'!J13-'Model inputs'!J66 -> 35.903491 | ... S8: ='Model inputs'!T45+'Model inputs'!T50+'Model inputs'!T70+'Model inputs'!T62-'Model inputs'!T13-'Model inputs'!T66 -> 106.65619
A9: ARPU | B9: =IFERROR('Model inputs'!C55/'RC Unit economics'!B5,"") -> 57.397447 | C9: =IFERROR('Model inputs'!D55/'RC Unit economics'!C5,"") -> 52.787175 | D9: =IFERROR('Model inputs'!E55/'RC Unit economics'!D5,"") -> 53.557491 | E9: =IFERROR('Model inputs'!F55/'RC Unit economics'!E5,"") -> 54.086867 | F9: =IFERROR('Model inputs'!G55/'RC Unit economics'!F5,"") -> 54.473564 | G9: =IFERROR('Model inputs'!H55/'RC Unit economics'!G5,"") -> 54.764216 | H9: =IFERROR('Model inputs'!I55/'RC Unit economics'!H5,"") -> 54.984229 | I9: =IFERROR('Model inputs'!J55/'RC Unit economics'!I5,"") -> 55.43706 | ... S9: =IFERROR('Model inputs'!T55/'RC Unit economics'!S5,"") -> 59.429028
A10: Indie | B10: =IFERROR('Model inputs'!C56/'RC Unit economics'!B6,"") -> 30.76 | C10: =IFERROR('Model inputs'!D56/'RC Unit economics'!C6,"") -> 30.76 | D10: =IFERROR('Model inputs'!E56/'RC Unit economics'!D6,"") -> 30.76 | E10: =IFERROR('Model inputs'!F56/'RC Unit economics'!E6,"") -> 30.76 | F10: =IFERROR('Model inputs'!G56/'RC Unit economics'!F6,"") -> 30.76 | G10: =IFERROR('Model inputs'!H56/'RC Unit economics'!G6,"") -> 30.76 | H10: =IFERROR('Model inputs'!I56/'RC Unit economics'!H6,"") -> 30.76 | I10: =IFERROR('Model inputs'!J56/'RC Unit economics'!I6,"") -> 30.76 | ... S10: =IFERROR('Model inputs'!T56/'RC Unit economics'!S6,"") -> 30.76
A11: Launch | B11: =IFERROR('Model inputs'!C57/'RC Unit economics'!B7,"") -> 526.36 | C11: =IFERROR('Model inputs'!D57/'RC Unit economics'!C7,"") -> 521.50861 | D11: =IFERROR('Model inputs'!E57/'RC Unit economics'!D7,"") -> 516.65722 | E11: =IFERROR('Model inputs'!F57/'RC Unit economics'!E7,"") -> 511.80583 | F11: =IFERROR('Model inputs'!G57/'RC Unit economics'!F7,"") -> 506.95444 | G11: =IFERROR('Model inputs'!H57/'RC Unit economics'!G7,"") -> 502.10306 | H11: =IFERROR('Model inputs'!I57/'RC Unit economics'!H7,"") -> 497.25167 | I11: =IFERROR('Model inputs'!J57/'RC Unit economics'!I7,"") -> 497.25167 | ... S11: =IFERROR('Model inputs'!T57/'RC Unit economics'!S7,"") -> 497.25167
A12: Team | B12: =IFERROR('Model inputs'!C58/'RC Unit economics'!B8,"") -> 156.82 | C12: =IFERROR('Model inputs'!D58/'RC Unit economics'!C8,"") -> 155.37139 | D12: =IFERROR('Model inputs'!E58/'RC Unit economics'!D8,"") -> 153.92278 | E12: =IFERROR('Model inputs'!F58/'RC Unit economics'!E8,"") -> 152.47417 | F12: =IFERROR('Model inputs'!G58/'RC Unit economics'!F8,"") -> 151.02556 | G12: =IFERROR('Model inputs'!H58/'RC Unit economics'!G8,"") -> 149.57694 | H12: =IFERROR('Model inputs'!I58/'RC Unit economics'!H8,"") -> 148.12833 | I12: =IFERROR('Model inputs'!J58/'RC Unit economics'!I8,"") -> 148.12833 | ... S12: =IFERROR('Model inputs'!T58/'RC Unit economics'!S8,"") -> 148.12833
A13: Kits per customer | B13: =IFERROR('Model inputs'!C20/'RC Unit economics'!B5,"") -> 17.617021 | C13: =IFERROR('Model inputs'!D20/'RC Unit economics'!C5,"") -> 16.121449 | D13: =IFERROR('Model inputs'!E20/'RC Unit economics'!D5,"") -> 16.458881 | E13: =IFERROR('Model inputs'!F20/'RC Unit economics'!E5,"") -> 16.715112 | F13: =IFERROR('Model inputs'!G20/'RC Unit economics'!F5,"") -> 16.92473 | G13: =IFERROR('Model inputs'!H20/'RC Unit economics'!G5,"") -> 17.104054 | H13: =IFERROR('Model inputs'!I20/'RC Unit economics'!H5,"") -> 17.261902 | I13: =IFERROR('Model inputs'!J20/'RC Unit economics'!I5,"") -> 17.403545 | ... S13: =IFERROR('Model inputs'!T20/'RC Unit economics'!S5,"") -> 18.716455
A14: Indie | B14: =IFERROR('Model inputs'!C21/'RC Unit economics'!B6,"") -> 8.5 | C14: =IFERROR('Model inputs'!D21/'RC Unit economics'!C6,"") -> 8.5 | D14: =IFERROR('Model inputs'!E21/'RC Unit economics'!D6,"") -> 8.5 | E14: =IFERROR('Model inputs'!F21/'RC Unit economics'!E6,"") -> 8.5 | F14: =IFERROR('Model inputs'!G21/'RC Unit economics'!F6,"") -> 8.5 | G14: =IFERROR('Model inputs'!H21/'RC Unit economics'!G6,"") -> 8.5 | H14: =IFERROR('Model inputs'!I21/'RC Unit economics'!H6,"") -> 8.5 | I14: =IFERROR('Model inputs'!J21/'RC Unit economics'!I6,"") -> 8.5 | ... S14: =IFERROR('Model inputs'!T21/'RC Unit economics'!S6,"") -> 8.5
A15: Launch | B15: =IFERROR('Model inputs'!C22/'RC Unit economics'!B7,"") -> 206 | C15: =IFERROR('Model inputs'!D22/'RC Unit economics'!C7,"") -> 206 | D15: =IFERROR('Model inputs'!E22/'RC Unit economics'!D7,"") -> 206 | E15: =IFERROR('Model inputs'!F22/'RC Unit economics'!E7,"") -> 206 | F15: =IFERROR('Model inputs'!G22/'RC Unit economics'!F7,"") -> 206 | G15: =IFERROR('Model inputs'!H22/'RC Unit economics'!G7,"") -> 206 | H15: =IFERROR('Model inputs'!I22/'RC Unit economics'!H7,"") -> 206 | I15: =IFERROR('Model inputs'!J22/'RC Unit economics'!I7,"") -> 206 | ... S15: =IFERROR('Model inputs'!T22/'RC Unit economics'!S7,"") -> 206
A16: Team | B16: =IFERROR('Model inputs'!C23/'RC Unit economics'!B8,"") -> 47 | C16: =IFERROR('Model inputs'!D23/'RC Unit economics'!C8,"") -> 47 | D16: =IFERROR('Model inputs'!E23/'RC Unit economics'!D8,"") -> 47 | E16: =IFERROR('Model inputs'!F23/'RC Unit economics'!E8,"") -> 47 | F16: =IFERROR('Model inputs'!G23/'RC Unit economics'!F8,"") -> 47 | G16: =IFERROR('Model inputs'!H23/'RC Unit economics'!G8,"") -> 47 | H16: =IFERROR('Model inputs'!I23/'RC Unit economics'!H8,"") -> 47 | I16: =IFERROR('Model inputs'!J23/'RC Unit economics'!I8,"") -> 47 | ... S16: =IFERROR('Model inputs'!T23/'RC Unit economics'!S8,"") -> 47
A17: COGS per kit | B17: =IF(IF(IF(IFERROR(IF(ISERROR('Model inputs'!B19=1),'Model inputs'!B19=1,IF('Model inputs'!B19="","",'Model inputs'!B19=1))=FALSE,FALSE),FALSE,IF(IFERROR('Model inputs'!B214=FALSE,FALSE),FALSE,IF(OR(IF(ISERROR('Model inputs'!B19=1),'Model inputs'!B19=1,IF('Model inputs'!B19="","",'Model inputs'!B19=1))="",'Model inputs'!B214=""),"",AND(IF(ISERROR('Model inputs'!B19=1),'Model inputs'!B19=1,IF('Model inputs'!B19="","",'Model inputs'!B19=1)),'Model inputs'!B214))))="",FALSE,IF(IFERROR(IF(ISERROR('Model inputs'!B19=1),'Model inputs'!B19=1,IF('Model inputs'!B19="","",'Model inputs'!B19=1))=FALSE,FALSE),FALSE,IF(IFERROR('Model inputs'!B214=FALSE,FALSE),FALSE,IF(OR(IF(ISERROR('Model inputs'!B19=1),'Model inputs'!B19=1,IF('Model inputs'!B19="","",'Model inputs'!B19=1))="",'Model inputs'!B214=""),"",AND(IF(ISERROR('Model inputs'!B19=1),'Model inputs'!B19=1,IF('Model inputs'!B19="","",'Model inputs'!B19=1)),'Model inputs'!B214))))),IF('Model inputs'!B46="","",'Model inputs'!B46),IF('Model inputs'!B36="","",'Model inputs'!B36)) -> 0.24 | C17: =IF(IF(IF(IFERROR(IF(ISERROR('Model inputs'!B19=1),'Model inputs'!B19=1,IF('Model inputs'!B19="","",'Model inputs'!B19=1))=FALSE,FALSE),FALSE,IF(IFERROR('Model inputs'!B215=FALSE,FALSE),FALSE,IF(OR(IF(ISERROR('Model inputs'!B19=1),'Model inputs'!B19=1,IF('Model inputs'!B19="","",'Model inputs'!B19=1))="",'Model inputs'!B215=""),"",AND(IF(ISERROR('Model inputs'!B19=1),'Model inputs'!B19=1,IF('Model inputs'!B19="","",'Model inputs'!B19=1)),'Model inputs'!B215))))="",FALSE,IF(IFERROR(IF(ISERROR('Model inputs'!B19=1),'Model inputs'!B19=1,IF('Model inputs'!B19="","",'Model inputs'!B19=1))=FALSE,FALSE),FALSE,IF(IFERROR('Model inputs'!B215=FALSE,FALSE),FALSE,IF(OR(IF(ISERROR('Model inputs'!B19=1),'Model inputs'!B19=1,IF('Model inputs'!B19="","",'Model inputs'!B19=1))="",'Model inputs'!B215=""),"",AND(IF(ISERROR('Model inputs'!B19=1),'Model inputs'!B19=1,IF('Model inputs'!B19="","",'Model inputs'!B19=1)),'Model inputs'!B215))))),IF('Model inputs'!B46="","",'Model inputs'!B46),IF('Model inputs'!B36="","",'Model inputs'!B36)) -> 0.24 | D17: =IF(IF(IF(IFERROR(IF(ISERROR('Model inputs'!B19=1),'Model inputs'!B19=1,IF('Model inputs'!B19="","",'Model inputs'!B19=1))=FALSE,FALSE),FALSE,IF(IFERROR('Model inputs'!B216=FALSE,FALSE),FALSE,IF(OR(IF(ISERROR('Model inputs'!B19=1),'Model inputs'!B19=1,IF('Model inputs'!B19="","",'Model inputs'!B19=1))="",'Model inputs'!B216=""),"",AND(IF(ISERROR('Model inputs'!B19=1),'Model inputs'!B19=1,IF('Model inputs'!B19="","",'Model inputs'!B19=1)),'Model inputs'!B216))))="",FALSE,IF(IFERROR(IF(ISERROR('Model inputs'!B19=1),'Model inputs'!B19=1,IF('Model inputs'!B19="","",'Model inputs'!B19=1))=FALSE,FALSE),FALSE,IF(IFERROR('Model inputs'!B216=FALSE,FALSE),FALSE,IF(OR(IF(ISERROR('Model inputs'!B19=1),'Model inputs'!B19=1,IF('Model inputs'!B19="","",'Model inputs'!B19=1))="",'Model inputs'!B216=""),"",AND(IF(ISERROR('Model inputs'!B19=1),'Model inputs'!B19=1,IF('Model inputs'!B19="","",'Model inputs'!B19=1)),'Model inputs'!B216))))),IF('Model inputs'!B46="","",'Model inputs'!B46),IF('Model inputs'!B36="","",'Model inputs'!B36)) -> 0.24 | E17: =IF(IF(IF(IFERROR(IF(ISERROR('Model inputs'!B19=1),'Model inputs'!B19=1,IF('Model inputs'!B19="","",'Model inputs'!B19=1))=FALSE,FALSE),FALSE,IF(IFERROR('Model inputs'!B217=FALSE,FALSE),FALSE,IF(OR(IF(ISERROR('Model inputs'!B19=1),'Model inputs'!B19=1,IF('Model inputs'!B19="","",'Model inputs'!B19=1))="",'Model inputs'!B217=""),"",AND(IF(ISERROR('Model inputs'!B19=1),'Model inputs'!B19=1,IF('Model inputs'!B19="","",'Model inputs'!B19=1)),'Model inputs'!B217))))="",FALSE,IF(IFERROR(IF(ISERROR('Model inputs'!B19=1),'Model inputs'!B19=1,IF('Model inputs'!B19="","",'Model inputs'!B19=1))=FALSE,FALSE),FALSE,IF(IFERROR('Model inputs'!B217=FALSE,FALSE),FALSE,IF(OR(IF(ISERROR('Model inputs'!B19=1),'Model inputs'!B19=1,IF('Model inputs'!B19="","",'Model inputs'!B19=1))="",'Model inputs'!B217=""),"",AND(IF(ISERROR('Model inputs'!B19=1),'Model inputs'!B19=1,IF('Model inputs'!B19="","",'Model inputs'!B19=1)),'Model inputs'!B217))))),IF('Model inputs'!B46="","",'Model inputs'!B46),IF('Model inputs'!B36="","",'Model inputs'!B36)) -> 0.24 | F17: =IF(IF(IF(IFERROR(IF(ISERROR('Model inputs'!B19=1),'Model inputs'!B19=1,IF('Model inputs'!B19="","",'Model inputs'!B19=1))=FALSE,FALSE),FALSE,IF(IFERROR('Model inputs'!B218=FALSE,FALSE),FALSE,IF(OR(IF(ISERROR('Model inputs'!B19=1),'Model inputs'!B19=1,IF('Model inputs'!B19="","",'Model inputs'!B19=1))="",'Model inputs'!B218=""),"",AND(IF(ISERROR('Model inputs'!B19=1),'Model inputs'!B19=1,IF('Model inputs'!B19="","",'Model inputs'!B19=1)),'Model inputs'!B218))))="",FALSE,IF(IFERROR(IF(ISERROR('Model inputs'!B19=1),'Model inputs'!B19=1,IF('Model inputs'!B19="","",'Model inputs'!B19=1))=FALSE,FALSE),FALSE,IF(IFERROR('Model inputs'!B218=FALSE,FALSE),FALSE,IF(OR(IF(ISERROR('Model inputs'!B19=1),'Model inputs'!B19=1,IF('Model inputs'!B19="","",'Model inputs'!B19=1))="",'Model inputs'!B218=""),"",AND(IF(ISERROR('Model inputs'!B19=1),'Model inputs'!B19=1,IF('Model inputs'!B19="","",'Model inputs'!B19=1)),'Model inputs'!B218))))),IF('Model inputs'!B46="","",'Model inputs'!B46),IF('Model inputs'!B36="","",'Model inputs'!B36)) -> 0.24 | G17: =IF(IF(IF(IFERROR(IF(ISERROR('Model inputs'!B19=1),'Model inputs'!B19=1,IF('Model inputs'!B19="","",'Model inputs'!B19=1))=FALSE,FALSE),FALSE,IF(IFERROR('Model inputs'!B219=FALSE,FALSE),FALSE,IF(OR(IF(ISERROR('Model inputs'!B19=1),'Model inputs'!B19=1,IF('Model inputs'!B19="","",'Model inputs'!B19=1))="",'Model inputs'!B219=""),"",AND(IF(ISERROR('Model inputs'!B19=1),'Model inputs'!B19=1,IF('Model inputs'!B19="","",'Model inputs'!B19=1)),'Model inputs'!B219))))="",FALSE,IF(IFERROR(IF(ISERROR('Model inputs'!B19=1),'Model inputs'!B19=1,IF('Model inputs'!B19="","",'Model inputs'!B19=1))=FALSE,FALSE),FALSE,IF(IFERROR('Model inputs'!B219=FALSE,FALSE),FALSE,IF(OR(IF(ISERROR('Model inputs'!B19=1),'Model inputs'!B19=1,IF('Model inputs'!B19="","",'Model inputs'!B19=1))="",'Model inputs'!B219=""),"",AND(IF(ISERROR('Model inputs'!B19=1),'Model inputs'!B19=1,IF('Model inputs'!B19="","",'Model inputs'!B19=1)),'Model inputs'!B219))))),IF('Model inputs'!B46="","",'Model inputs'!B46),IF('Model inputs'!B36="","",'Model inputs'!B36)) -> 0.24 | H17: =IF(IF(IF(IFERROR(IF(ISERROR('Model inputs'!B19=1),'Model inputs'!B19=1,IF('Model inputs'!B19="","",'Model inputs'!B19=1))=FALSE,FALSE),FALSE,IF(IFERROR('Model inputs'!B220=FALSE,FALSE),FALSE,IF(OR(IF(ISERROR('Model inputs'!B19=1),'Model inputs'!B19=1,IF('Model inputs'!B19="","",'Model inputs'!B19=1))="",'Model inputs'!B220=""),"",AND(IF(ISERROR('Model inputs'!B19=1),'Model inputs'!B19=1,IF('Model inputs'!B19="","",'Model inputs'!B19=1)),'Model inputs'!B220))))="",FALSE,IF(IFERROR(IF(ISERROR('Model inputs'!B19=1),'Model inputs'!B19=1,IF('Model inputs'!B19="","",'Model inputs'!B19=1))=FALSE,FALSE),FALSE,IF(IFERROR('Model inputs'!B220=FALSE,FALSE),FALSE,IF(OR(IF(ISERROR('Model inputs'!B19=1),'Model inputs'!B19=1,IF('Model inputs'!B19="","",'Model inputs'!B19=1))="",'Model inputs'!B220=""),"",AND(IF(ISERROR('Model inputs'!B19=1),'Model inputs'!B19=1,IF('Model inputs'!B19="","",'Model inputs'!B19=1)),'Model inputs'!B220))))),IF('Model inputs'!B46="","",'Model inputs'!B46),IF('Model inputs'!B36="","",'Model inputs'!B36)) -> 0.24 | I17: =IF(IF(IF(IFERROR(IF(ISERROR('Model inputs'!B19=1),'Model inputs'!B19=1,IF('Model inputs'!B19="","",'Model inputs'!B19=1))=FALSE,FALSE),FALSE,IF(IFERROR('Model inputs'!B221=FALSE,FALSE),FALSE,IF(OR(IF(ISERROR('Model inputs'!B19=1),'Model inputs'!B19=1,IF('Model inputs'!B19="","",'Model inputs'!B19=1))="",'Model inputs'!B221=""),"",AND(IF(ISERROR('Model inputs'!B19=1),'Model inputs'!B19=1,IF('Model inputs'!B19="","",'Model inputs'!B19=1)),'Model inputs'!B221))))="",FALSE,IF(IFERROR(IF(ISERROR('Model inputs'!B19=1),'Model inputs'!B19=1,IF('Model inputs'!B19="","",'Model inputs'!B19=1))=FALSE,FALSE),FALSE,IF(IFERROR('Model inputs'!B221=FALSE,FALSE),FALSE,IF(OR(IF(ISERROR('Model inputs'!B19=1),'Model inputs'!B19=1,IF('Model inputs'!B19="","",'Model inputs'!B19=1))="",'Model inputs'!B221=""),"",AND(IF(ISERROR('Model inputs'!B19=1),'Model inputs'!B19=1,IF('Model inputs'!B19="","",'Model inputs'!B19=1)),'Model inputs'!B221))))),IF('Model inputs'!B46="","",'Model inputs'!B46),IF('Model inputs'!B36="","",'Model inputs'!B36)) -> 0.24 | J17: =IF(IF(IF(IFERROR(IF(ISERROR('Model inputs'!B19=1),'Model inputs'!B19=1,IF('Model inputs'!B19="","",'Model inputs'!B19=1))=FALSE,FALSE),FALSE,IF(IFERROR('Model inputs'!B222=FALSE,FALSE),FALSE,IF(OR(IF(ISERROR('Model inputs'!B19=1),'Model inputs'!B19=1,IF('Model inputs'!B19="","",'Model inputs'!B19=1))="",'Model inputs'!B222=""),"",AND(IF(ISERROR('Model inputs'!B19=1),'Model inputs'!B19=1,IF('Model inputs'!B19="","",'Model inputs'!B19=1)),'Model inputs'!B222))))="",FALSE,IF(IFERROR(IF(ISERROR('Model inputs'!B19=1),'Model inputs'!B19=1,IF('Model inputs'!B19="","",'Model inputs'!B19=1))=FALSE,FALSE),FALSE,IF(IFERROR('Model inputs'!B222=FALSE,FALSE),FALSE,IF(OR(IF(ISERROR('Model inputs'!B19=1),'Model inputs'!B19=1,IF('Model inputs'!B19="","",'Model inputs'!B19=1))="",'Model inputs'!B222=""),"",AND(IF(ISERROR('Model inputs'!B19=1),'Model inputs'!B19=1,IF('Model inputs'!B19="","",'Model inputs'!B19=1)),'Model inputs'!B222))))),IF('Model inputs'!B46="","",'Model inputs'!B46),IF('Model inputs'!B36="","",'Model inputs'!B36)) -> 0.24 | K17: =IF(IF(IF(IFERROR(IF(ISERROR('Model inputs'!B19=1),'Model inputs'!B19=1,IF('Model inputs'!B19="","",'Model inputs'!B19=1))=FALSE,FALSE),FALSE,IF(IFERROR('Model inputs'!B223=FALSE,FALSE),FALSE,IF(OR(IF(ISERROR('Model inputs'!B19=1),'Model inputs'!B19=1,IF('Model inputs'!B19="","",'Model inputs'!B19=1))="",'Model inputs'!B223=""),"",AND(IF(ISERROR('Model inputs'!B19=1),'Model inputs'!B19=1,IF('Model inputs'!B19="","",'Model inputs'!B19=1)),'Model inputs'!B223))))="",FALSE,IF(IFERROR(IF(ISERROR('Model inputs'!B19=1),'Model inputs'!B19=1,IF('Model inputs'!B19="","",'Model inputs'!B19=1))=FALSE,FALSE),FALSE,IF(IFERROR('Model inputs'!B223=FALSE,FALSE),FALSE,IF(OR(IF(ISERROR('Model inputs'!B19=1),'Model inputs'!B19=1,IF('Model inputs'!B19="","",'Model inputs'!B19=1))="",'Model inputs'!B223=""),"",AND(IF(ISERROR('Model inputs'!B19=1),'Model inputs'!B19=1,IF('Model inputs'!B19="","",'Model inputs'!B19=1)),'Model inputs'!B223))))),IF('Model inputs'!B46="","",'Model inputs'!B46),IF('Model inputs'!B36="","",'Model inputs'!B36)) -> 0.24 | L17: =IF(IF(IF(IFERROR(IF(ISERROR('Model inputs'!B19=1),'Model inputs'!B19=1,IF('Model inputs'!B19="","",'Model inputs'!B19=1))=FALSE,FALSE),FALSE,IF(IFERROR('Model inputs'!B224=FALSE,FALSE),FALSE,IF(OR(IF(ISERROR('Model inputs'!B19=1),'Model inputs'!B19=1,IF('Model inputs'!B19="","",'Model inputs'!B19=1))="",'Model inputs'!B224=""),"",AND(IF(ISERROR('Model inputs'!B19=1),'Model inputs'!B19=1,IF('Model inputs'!B19="","",'Model inputs'!B19=1)),'Model inputs'!B224))))="",FALSE,IF(IFERROR(IF(ISERROR('Model inputs'!B19=1),'Model inputs'!B19=1,IF('Model inputs'!B19="","",'Model inputs'!B19=1))=FALSE,FALSE),FALSE,IF(IFERROR('Model inputs'!B224=FALSE,FALSE),FALSE,IF(OR(IF(ISERROR('Model inputs'!B19=1),'Model inputs'!B19=1,IF('Model inputs'!B19="","",'Model inputs'!B19=1))="",'Model inputs'!B224=""),"",AND(IF(ISERROR('Model inputs'!B19=1),'Model inputs'!B19=1,IF('Model inputs'!B19="","",'Model inputs'!B19=1)),'Model inputs'!B224))))),IF('Model inputs'!B46="","",'Model inputs'!B46),IF('Model inputs'!B36="","",'Model inputs'!B36)) -> 0.24 | M17: =IF(IF(IF(IFERROR(IF(ISERROR('Model inputs'!B19=1),'Model inputs'!B19=1,IF('Model inputs'!B19="","",'Model inputs'!B19=1))=FALSE,FALSE),FALSE,IF(IFERROR('Model inputs'!B225=FALSE,FALSE),FALSE,IF(OR(IF(ISERROR('Model inputs'!B19=1),'Model inputs'!B19=1,IF('Model inputs'!B19="","",'Model inputs'!B19=1))="",'Model inputs'!B225=""),"",AND(IF(ISERROR('Model inputs'!B19=1),'Model inputs'!B19=1,IF('Model inputs'!B19="","",'Model inputs'!B19=1)),'Model inputs'!B225))))="",FALSE,IF(IFERROR(IF(ISERROR('Model inputs'!B19=1),'Model inputs'!B19=1,IF('Model inputs'!B19="","",'Model inputs'!B19=1))=FALSE,FALSE),FALSE,IF(IFERROR('Model inputs'!B225=FALSE,FALSE),FALSE,IF(OR(IF(ISERROR('Model inputs'!B19=1),'Model inputs'!B19=1,IF('Model inputs'!B19="","",'Model inputs'!B19=1))="",'Model inputs'!B225=""),"",AND(IF(ISERROR('Model inputs'!B19=1),'Model inputs'!B19=1,IF('Model inputs'!B19="","",'Model inputs'!B19=1)),'Model inputs'!B225))))),IF('Model inputs'!B46="","",'Model inputs'!B46),IF('Model inputs'!B36="","",'Model inputs'!B36)) -> 0.24 | N17: =IF(IF(IF(IFERROR(IF(ISERROR('Model inputs'!B19=1),'Model inputs'!B19=1,IF('Model inputs'!B19="","",'Model inputs'!B19=1))=FALSE,FALSE),FALSE,IF(IFERROR('Model inputs'!B226=FALSE,FALSE),FALSE,IF(OR(IF(ISERROR('Model inputs'!B19=1),'Model inputs'!B19=1,IF('Model inputs'!B19="","",'Model inputs'!B19=1))="",'Model inputs'!B226=""),"",AND(IF(ISERROR('Model inputs'!B19=1),'Model inputs'!B19=1,IF('Model inputs'!B19="","",'Model inputs'!B19=1)),'Model inputs'!B226))))="",FALSE,IF(IFERROR(IF(ISERROR('Model inputs'!B19=1),'Model inputs'!B19=1,IF('Model inputs'!B19="","",'Model inputs'!B19=1))=FALSE,FALSE),FALSE,IF(IFERROR('Model inputs'!B226=FALSE,FALSE),FALSE,IF(OR(IF(ISERROR('Model inputs'!B19=1),'Model inputs'!B19=1,IF('Model inputs'!B19="","",'Model inputs'!B19=1))="",'Model inputs'!B226=""),"",AND(IF(ISERROR('Model inputs'!B19=1),'Model inputs'!B19=1,IF('Model inputs'!B19="","",'Model inputs'!B19=1)),'Model inputs'!B226))))),IF('Model inputs'!B46="","",'Model inputs'!B46),IF('Model inputs'!B36="","",'Model inputs'!B36)) -> 0.24 | O17: =IF(IF(IF(IFERROR(IF(ISERROR('Model inputs'!B19=1),'Model inputs'!B19=1,IF('Model inputs'!B19="","",'Model inputs'!B19=1))=FALSE,FALSE),FALSE,IF(IFERROR('Model inputs'!B227=FALSE,FALSE),FALSE,IF(OR(IF(ISERROR('Model inputs'!B19=1),'Model inputs'!B19=1,IF('Model inputs'!B19="","",'Model inputs'!B19=1))="",'Model inputs'!B227=""),"",AND(IF(ISERROR('Model inputs'!B19=1),'Model inputs'!B19=1,IF('Model inputs'!B19="","",'Model inputs'!B19=1)),'Model inputs'!B227))))="",FALSE,IF(IFERROR(IF(ISERROR('Model inputs'!B19=1),'Model inputs'!B19=1,IF('Model inputs'!B19="","",'Model inputs'!B19=1))=FALSE,FALSE),FALSE,IF(IFERROR('Model inputs'!B227=FALSE,FALSE),FALSE,IF(OR(IF(ISERROR('Model inputs'!B19=1),'Model inputs'!B19=1,IF('Model inputs'!B19="","",'Model inputs'!B19=1))="",'Model inputs'!B227=""),"",AND(IF(ISERROR('Model inputs'!B19=1),'Model inputs'!B19=1,IF('Model inputs'!B19="","",'Model inputs'!B19=1)),'Model inputs'!B227))))),IF('Model inputs'!B46="","",'Model inputs'!B46),IF('Model inputs'!B36="","",'Model inputs'!B36)) -> 0.24 | P17: =IF(IF(IF(IFERROR(IF(ISERROR('Model inputs'!B19=1),'Model inputs'!B19=1,IF('Model inputs'!B19="","",'Model inputs'!B19=1))=FALSE,FALSE),FALSE,IF(IFERROR('Model inputs'!B228=FALSE,FALSE),FALSE,IF(OR(IF(ISERROR('Model inputs'!B19=1),'Model inputs'!B19=1,IF('Model inputs'!B19="","",'Model inputs'!B19=1))="",'Model inputs'!B228=""),"",AND(IF(ISERROR('Model inputs'!B19=1),'Model inputs'!B19=1,IF('Model inputs'!B19="","",'Model inputs'!B19=1)),'Model inputs'!B228))))="",FALSE,IF(IFERROR(IF(ISERROR('Model inputs'!B19=1),'Model inputs'!B19=1,IF('Model inputs'!B19="","",'Model inputs'!B19=1))=FALSE,FALSE),FALSE,IF(IFERROR('Model inputs'!B228=FALSE,FALSE),FALSE,IF(OR(IF(ISERROR('Model inputs'!B19=1),'Model inputs'!B19=1,IF('Model inputs'!B19="","",'Model inputs'!B19=1))="",'Model inputs'!B228=""),"",AND(IF(ISERROR('Model inputs'!B19=1),'Model inputs'!B19=1,IF('Model inputs'!B19="","",'Model inputs'!B19=1)),'Model inputs'!B228))))),IF('Model inputs'!B46="","",'Model inputs'!B46),IF('Model inputs'!B36="","",'Model inputs'!B36)) -> 0.24 | Q17: =IF(IF(IF(IFERROR(IF(ISERROR('Model inputs'!B19=1),'Model inputs'!B19=1,IF('Model inputs'!B19="","",'Model inputs'!B19=1))=FALSE,FALSE),FALSE,IF(IFERROR('Model inputs'!B229=FALSE,FALSE),FALSE,IF(OR(IF(ISERROR('Model inputs'!B19=1),'Model inputs'!B19=1,IF('Model inputs'!B19="","",'Model inputs'!B19=1))="",'Model inputs'!B229=""),"",AND(IF(ISERROR('Model inputs'!B19=1),'Model inputs'!B19=1,IF('Model inputs'!B19="","",'Model inputs'!B19=1)),'Model inputs'!B229))))="",FALSE,IF(IFERROR(IF(ISERROR('Model inputs'!B19=1),'Model inputs'!B19=1,IF('Model inputs'!B19="","",'Model inputs'!B19=1))=FALSE,FALSE),FALSE,IF(IFERROR('Model inputs'!B229=FALSE,FALSE),FALSE,IF(OR(IF(ISERROR('Model inputs'!B19=1),'Model inputs'!B19=1,IF('Model inputs'!B19="","",'Model inputs'!B19=1))="",'Model inputs'!B229=""),"",AND(IF(ISERROR('Model inputs'!B19=1),'Model inputs'!B19=1,IF('Model inputs'!B19="","",'Model inputs'!B19=1)),'Model inputs'!B229))))),IF('Model inputs'!B46="","",'Model inputs'!B46),IF('Model inputs'!B36="","",'Model inputs'!B36)) -> 0.24 | R17: =IF(IF(IF(IFERROR(IF(ISERROR('Model inputs'!B19=1),'Model inputs'!B19=1,IF('Model inputs'!B19="","",'Model inputs'!B19=1))=FALSE,FALSE),FALSE,IF(IFERROR('Model inputs'!B230=FALSE,FALSE),FALSE,IF(OR(IF(ISERROR('Model inputs'!B19=1),'Model inputs'!B19=1,IF('Model inputs'!B19="","",'Model inputs'!B19=1))="",'Model inputs'!B230=""),"",AND(IF(ISERROR('Model inputs'!B19=1),'Model inputs'!B19=1,IF('Model inputs'!B19="","",'Model inputs'!B19=1)),'Model inputs'!B230))))="",FALSE,IF(IFERROR(IF(ISERROR('Model inputs'!B19=1),'Model inputs'!B19=1,IF('Model inputs'!B19="","",'Model inputs'!B19=1))=FALSE,FALSE),FALSE,IF(IFERROR('Model inputs'!B230=FALSE,FALSE),FALSE,IF(OR(IF(ISERROR('Model inputs'!B19=1),'Model inputs'!B19=1,IF('Model inputs'!B19="","",'Model inputs'!B19=1))="",'Model inputs'!B230=""),"",AND(IF(ISERROR('Model inputs'!B19=1),'Model inputs'!B19=1,IF('Model inputs'!B19="","",'Model inputs'!B19=1)),'Model inputs'!B230))))),IF('Model inputs'!B46="","",'Model inputs'!B46),IF('Model inputs'!B36="","",'Model inputs'!B36)) -> 0.24 | S17: =IF(IF(IF(IFERROR(IF(ISERROR('Model inputs'!B19=1),'Model inputs'!B19=1,IF('Model inputs'!B19="","",'Model inputs'!B19=1))=FALSE,FALSE),FALSE,IF(IFERROR('Model inputs'!B231=FALSE,FALSE),FALSE,IF(OR(IF(ISERROR('Model inputs'!B19=1),'Model inputs'!B19=1,IF('Model inputs'!B19="","",'Model inputs'!B19=1))="",'Model inputs'!B231=""),"",AND(IF(ISERROR('Model inputs'!B19=1),'Model inputs'!B19=1,IF('Model inputs'!B19="","",'Model inputs'!B19=1)),'Model inputs'!B231))))="",FALSE,IF(IFERROR(IF(ISERROR('Model inputs'!B19=1),'Model inputs'!B19=1,IF('Model inputs'!B19="","",'Model inputs'!B19=1))=FALSE,FALSE),FALSE,IF(IFERROR('Model inputs'!B231=FALSE,FALSE),FALSE,IF(OR(IF(ISERROR('Model inputs'!B19=1),'Model inputs'!B19=1,IF('Model inputs'!B19="","",'Model inputs'!B19=1))="",'Model inputs'!B231=""),"",AND(IF(ISERROR('Model inputs'!B19=1),'Model inputs'!B19=1,IF('Model inputs'!B19="","",'Model inputs'!B19=1)),'Model inputs'!B231))))),IF('Model inputs'!B46="","",'Model inputs'!B46),IF('Model inputs'!B36="","",'Model inputs'!B36)) -> 0.24
A18: Payment fees per customer | B18: =IFERROR('Model inputs'!C51/'RC Unit economics'!B5,"") -> 1.964526 | C18: =IFERROR('Model inputs'!D51/'RC Unit economics'!C5,"") -> 2.2150413 | D18: =IFERROR('Model inputs'!E51/'RC Unit economics'!D5,"") -> 2.3437748 | E18: =IFERROR('Model inputs'!F51/'RC Unit economics'!E5,"") -> 2.4278445 | F18: =IFERROR('Model inputs'!G51/'RC Unit economics'!F5,"") -> 2.4872788 | G18: =IFERROR('Model inputs'!H51/'RC Unit economics'!G5,"") -> 2.5315317 | H18: =IFERROR('Model inputs'!I51/'RC Unit economics'!H5,"") -> 2.5657001 | I18: =IFERROR('Model inputs'!J51/'RC Unit economics'!I5,"") -> 2.1416561 | ... S18: =IFERROR('Model inputs'!T51/'RC Unit economics'!S5,"") -> 2.254695
A19: Indie | B19: =IFERROR('Model inputs'!C52/'RC Unit economics'!B6,"") -> 1.19204 | C19: =IFERROR('Model inputs'!D52/'RC Unit economics'!C6,"") -> 1.19204 | D19: =IFERROR('Model inputs'!E52/'RC Unit economics'!D6,"") -> 1.19204 | E19: =IFERROR('Model inputs'!F52/'RC Unit economics'!E6,"") -> 1.19204 | F19: =IFERROR('Model inputs'!G52/'RC Unit economics'!F6,"") -> 1.19204 | G19: =IFERROR('Model inputs'!H52/'RC Unit economics'!G6,"") -> 1.19204 | H19: =IFERROR('Model inputs'!I52/'RC Unit economics'!H6,"") -> 1.19204 | I19: =IFERROR('Model inputs'!J52/'RC Unit economics'!I6,"") -> 1.19204 | ... S19: =IFERROR('Model inputs'!T52/'RC Unit economics'!S6,"") -> 1.19204
A20: Launch | B20: =IFERROR('Model inputs'!C53/'RC Unit economics'!B7,"") -> 15.56444 | C20: =IFERROR('Model inputs'!D53/'RC Unit economics'!C7,"") -> 23.161715 | D20: =IFERROR('Model inputs'!E53/'RC Unit economics'!D7,"") -> 24.546296 | E20: =IFERROR('Model inputs'!F53/'RC Unit economics'!E7,"") -> 25.106813 | F20: =IFERROR('Model inputs'!G53/'RC Unit economics'!F7,"") -> 25.263516 | G20: =IFERROR('Model inputs'!H53/'RC Unit economics'!G7,"") -> 25.196332 | H20: =IFERROR('Model inputs'!I53/'RC Unit economics'!H7,"") -> 24.995372 | I20: =IFERROR('Model inputs'!J53/'RC Unit economics'!I7,"") -> 17.113659 | ... S20: =IFERROR('Model inputs'!T53/'RC Unit economics'!S7,"") -> 18.175509
A21: Team | B21: =IFERROR('Model inputs'!C54/'RC Unit economics'!B8,"") -> 4.84778 | C21: =IFERROR('Model inputs'!D54/'RC Unit economics'!C8,"") -> 7.116305 | D21: =IFERROR('Model inputs'!E54/'RC Unit economics'!D8,"") -> 7.6068597 | E21: =IFERROR('Model inputs'!F54/'RC Unit economics'!E8,"") -> 7.8841294 | F21: =IFERROR('Model inputs'!G54/'RC Unit economics'!F8,"") -> 8.0502435 | G21: =IFERROR('Model inputs'!H54/'RC Unit economics'!G8,"") -> 8.1513437 | H21: =IFERROR('Model inputs'!I54/'RC Unit economics'!H8,"") -> 8.2115027 | I21: =IFERROR('Model inputs'!J54/'RC Unit economics'!I8,"") -> 5.9760845 | ... S21: =IFERROR('Model inputs'!T54/'RC Unit economics'!S8,"") -> 5.575175
A22: Contribution per customer | B22: =IFERROR('Model inputs'!C14/'RC Unit economics'!B5,"") -> 51.204836 | C22: =IFERROR('Model inputs'!D14/'RC Unit economics'!C5,"") -> 46.702986 | D22: =IFERROR('Model inputs'!E14/'RC Unit economics'!D5,"") -> 47.263584 | E22: =IFERROR('Model inputs'!F14/'RC Unit economics'!E5,"") -> 47.647396 | F22: =IFERROR('Model inputs'!G14/'RC Unit economics'!F5,"") -> 47.92435 | G22: =IFERROR('Model inputs'!H14/'RC Unit economics'!G5,"") -> 48.127711 | H22: =IFERROR('Model inputs'!I14/'RC Unit economics'!H5,"") -> 48.275672 | I22: =IFERROR('Model inputs'!J14/'RC Unit economics'!I5,"") -> 49.118553 | ... S22: =IFERROR('Model inputs'!T14/'RC Unit economics'!S5,"") -> 52.682384
A23: Indie | B23: =IFERROR('Model inputs'!C15/'RC Unit economics'!B6,"") -> 27.52796 | C23: =IFERROR('Model inputs'!D15/'RC Unit economics'!C6,"") -> 27.52796 | D23: =IFERROR('Model inputs'!E15/'RC Unit economics'!D6,"") -> 27.52796 | E23: =IFERROR('Model inputs'!F15/'RC Unit economics'!E6,"") -> 27.52796 | F23: =IFERROR('Model inputs'!G15/'RC Unit economics'!F6,"") -> 27.52796 | G23: =IFERROR('Model inputs'!H15/'RC Unit economics'!G6,"") -> 27.52796 | H23: =IFERROR('Model inputs'!I15/'RC Unit economics'!H6,"") -> 27.52796 | I23: =IFERROR('Model inputs'!J15/'RC Unit economics'!I6,"") -> 27.52796 | ... S23: =IFERROR('Model inputs'!T15/'RC Unit economics'!S6,"") -> 27.52796
A24: Launch | B24: =IFERROR('Model inputs'!C16/'RC Unit economics'!B7,"") -> 461.35556 | C24: =IFERROR('Model inputs'!D16/'RC Unit economics'!C7,"") -> 448.9069 | D24: =IFERROR('Model inputs'!E16/'RC Unit economics'!D7,"") -> 442.67093 | E24: =IFERROR('Model inputs'!F16/'RC Unit economics'!E7,"") -> 437.25902 | F24: =IFERROR('Model inputs'!G16/'RC Unit economics'!F7,"") -> 432.25093 | G24: =IFERROR('Model inputs'!H16/'RC Unit economics'!G7,"") -> 427.46672 | H24: =IFERROR('Model inputs'!I16/'RC Unit economics'!H7,"") -> 422.81629 | I24: =IFERROR('Model inputs'!J16/'RC Unit economics'!I7,"") -> 430.69801 | ... S24: =IFERROR('Model inputs'!T16/'RC Unit economics'!S7,"") -> 429.63616
A25: Team | B25: =IFERROR('Model inputs'!C17/'RC Unit economics'!B8,"") -> 140.69222 | C25: =IFERROR('Model inputs'!D17/'RC Unit economics'!C8,"") -> 136.97508 | D25: =IFERROR('Model inputs'!E17/'RC Unit economics'!D8,"") -> 135.03592 | E25: =IFERROR('Model inputs'!F17/'RC Unit economics'!E8,"") -> 133.31004 | F25: =IFERROR('Model inputs'!G17/'RC Unit economics'!F8,"") -> 131.69531 | G25: =IFERROR('Model inputs'!H17/'RC Unit economics'!G8,"") -> 130.1456 | H25: =IFERROR('Model inputs'!I17/'RC Unit economics'!H8,"") -> 128.63683 | I25: =IFERROR('Model inputs'!J17/'RC Unit economics'!I8,"") -> 130.87225 | ... S25: =IFERROR('Model inputs'!T17/'RC Unit economics'!S8,"") -> 131.27316
A26: Contribution margin % | B26: =IFERROR('Model inputs'!C14/'Model inputs'!C55,"") -> 0.89210999 | C26: =IFERROR('Model inputs'!D14/'Model inputs'!D55,"") -> 0.88474115 | D26: =IFERROR('Model inputs'!E14/'Model inputs'!E55,"") -> 0.88248318 | E26: =IFERROR('Model inputs'!F14/'Model inputs'!F55,"") -> 0.88094205 | F26: =IFERROR('Model inputs'!G14/'Model inputs'!G55,"") -> 0.87977262 | G26: =IFERROR('Model inputs'!H14/'Model inputs'!H55,"") -> 0.87881677 | H26: =IFERROR('Model inputs'!I14/'Model inputs'!I55,"") -> 0.87799126 | I26: =IFERROR('Model inputs'!J14/'Model inputs'!J55,"") -> 0.88602377 | ... S26: =IFERROR('Model inputs'!T14/'Model inputs'!T55,"") -> 0.88647561
A27: Indie | B27: =IFERROR('Model inputs'!C15/'Model inputs'!C56,"") -> 0.89492718 | C27: =IFERROR('Model inputs'!D15/'Model inputs'!D56,"") -> 0.89492718 | D27: =IFERROR('Model inputs'!E15/'Model inputs'!E56,"") -> 0.89492718 | E27: =IFERROR('Model inputs'!F15/'Model inputs'!F56,"") -> 0.89492718 | F27: =IFERROR('Model inputs'!G15/'Model inputs'!G56,"") -> 0.89492718 | G27: =IFERROR('Model inputs'!H15/'Model inputs'!H56,"") -> 0.89492718 | H27: =IFERROR('Model inputs'!I15/'Model inputs'!I56,"") -> 0.89492718 | I27: =IFERROR('Model inputs'!J15/'Model inputs'!J56,"") -> 0.89492718 | ... S27: =IFERROR('Model inputs'!T15/'Model inputs'!T56,"") -> 0.89492718
A28: Launch | B28: =IFERROR('Model inputs'!C16/'Model inputs'!C57,"") -> 0.87650194 | C28: =IFERROR('Model inputs'!D16/'Model inputs'!D57,"") -> 0.8607852 | D28: =IFERROR('Model inputs'!E16/'Model inputs'!E57,"") -> 0.8567981 | E28: =IFERROR('Model inputs'!F16/'Model inputs'!F57,"") -> 0.85434552 | F28: =IFERROR('Model inputs'!G16/'Model inputs'!G57,"") -> 0.85264255 | G28: =IFERROR('Model inputs'!H16/'Model inputs'!H57,"") -> 0.85135256 | H28: =IFERROR('Model inputs'!I16/'Model inputs'!I57,"") -> 0.85030644 | I28: =IFERROR('Model inputs'!J16/'Model inputs'!J57,"") -> 0.86615699 | ... S28: =IFERROR('Model inputs'!T16/'Model inputs'!T57,"") -> 0.86402155
A29: Team | B29: =IFERROR('Model inputs'!C17/'Model inputs'!C58,"") -> 0.89715738 | C29: =IFERROR('Model inputs'!D17/'Model inputs'!D58,"") -> 0.88159786 | D29: =IFERROR('Model inputs'!E17/'Model inputs'!E58,"") -> 0.87729653 | E29: =IFERROR('Model inputs'!F17/'Model inputs'!F58,"") -> 0.87431229 | F29: =IFERROR('Model inputs'!G17/'Model inputs'!G58,"") -> 0.8720068 | G29: =IFERROR('Model inputs'!H17/'Model inputs'!H58,"") -> 0.87009132 | H29: =IFERROR('Model inputs'!I17/'Model inputs'!I58,"") -> 0.86841476 | I29: =IFERROR('Model inputs'!J17/'Model inputs'!J58,"") -> 0.88350585 | ... S29: =IFERROR('Model inputs'!T17/'Model inputs'!T58,"") -> 0.88621235
A30: LTV (24-month) | B30: =IFERROR('RC Unit economics'!B22*(1-(1-IF(IF(SUM(IF(IF('Model inputs'!B232="",0,1)="",0,IF('Model inputs'!B232="",0,1)),IF(IF('Model inputs'!B233="",0,1)="",0,IF('Model inputs'!B233="",0,1)),IF(IF('Model inputs'!B234="",0,1)="",0,IF('Model inputs'!B234="",0,1)))=0,"",SUM('Model inputs'!B232,'Model inputs'!B233,'Model inputs'!B234))="",0,IF(SUM(IF(IF('Model inputs'!B232="",0,1)="",0,IF('Model inputs'!B232="",0,1)),IF(IF('Model inputs'!B233="",0,1)="",0,IF('Model inputs'!B233="",0,1)),IF(IF('Model inputs'!B234="",0,1)="",0,IF('Model inputs'!B234="",0,1)))=0,"",SUM('Model inputs'!B232,'Model inputs'!B233,'Model inputs'!B234))))^24)/IF(IF(SUM(IF(IF('Model inputs'!B232="",0,1)="",0,IF('Model inputs'!B232="",0,1)),IF(IF('Model inputs'!B233="",0,1)="",0,IF('Model inputs'!B233="",0,1)),IF(IF('Model inputs'!B234="",0,1)="",0,IF('Model inputs'!B234="",0,1)))=0,"",SUM('Model inputs'!B232,'Model inputs'!B233,'Model inputs'!B234))="",0,IF(SUM(IF(IF('Model inputs'!B232="",0,1)="",0,IF('Model inputs'!B232="",0,1)),IF(IF('Model inputs'!B233="",0,1)="",0,IF('Model inputs'!B233="",0,1)),IF(IF('Model inputs'!B234="",0,1)="",0,IF('Model inputs'!B234="",0,1)))=0,"",SUM('Model inputs'!B232,'Model inputs'!B233,'Model inputs'!B234))),"") | C30: =IFERROR('RC Unit economics'!C22*(1-(1-IF(IF(SUM(IF(IF('Model inputs'!B232="",0,1)="",0,IF('Model inputs'!B232="",0,1)),IF(IF('Model inputs'!B233="",0,1)="",0,IF('Model inputs'!B233="",0,1)),IF(IF('Model inputs'!B234="",0,1)="",0,IF('Model inputs'!B234="",0,1)))=0,"",SUM('Model inputs'!B232,'Model inputs'!B233,'Model inputs'!B234))="",0,IF(SUM(IF(IF('Model inputs'!B232="",0,1)="",0,IF('Model inputs'!B232="",0,1)),IF(IF('Model inputs'!B233="",0,1)="",0,IF('Model inputs'!B233="",0,1)),IF(IF('Model inputs'!B234="",0,1)="",0,IF('Model inputs'!B234="",0,1)))=0,"",SUM('Model inputs'!B232,'Model inputs'!B233,'Model inputs'!B234))))^24)/IF(IF(SUM(IF(IF('Model inputs'!B232="",0,1)="",0,IF('Model inputs'!B232="",0,1)),IF(IF('Model inputs'!B233="",0,1)="",0,IF('Model inputs'!B233="",0,1)),IF(IF('Model inputs'!B234="",0,1)="",0,IF('Model inputs'!B234="",0,1)))=0,"",SUM('Model inputs'!B232,'Model inputs'!B233,'Model inputs'!B234))="",0,IF(SUM(IF(IF('Model inputs'!B232="",0,1)="",0,IF('Model inputs'!B232="",0,1)),IF(IF('Model inputs'!B233="",0,1)="",0,IF('Model inputs'!B233="",0,1)),IF(IF('Model inputs'!B234="",0,1)="",0,IF('Model inputs'!B234="",0,1)))=0,"",SUM('Model inputs'!B232,'Model inputs'!B233,'Model inputs'!B234))),"") | D30: =IFERROR('RC Unit economics'!D22*(1-(1-IF(IF(SUM(IF(IF('Model inputs'!B232="",0,1)="",0,IF('Model inputs'!B232="",0,1)),IF(IF('Model inputs'!B233="",0,1)="",0,IF('Model inputs'!B233="",0,1)),IF(IF('Model inputs'!B234="",0,1)="",0,IF('Model inputs'!B234="",0,1)))=0,"",SUM('Model inputs'!B232,'Model inputs'!B233,'Model inputs'!B234))="",0,IF(SUM(IF(IF('Model inputs'!B232="",0,1)="",0,IF('Model inputs'!B232="",0,1)),IF(IF('Model inputs'!B233="",0,1)="",0,IF('Model inputs'!B233="",0,1)),IF(IF('Model inputs'!B234="",0,1)="",0,IF('Model inputs'!B234="",0,1)))=0,"",SUM('Model inputs'!B232,'Model inputs'!B233,'Model inputs'!B234))))^24)/IF(IF(SUM(IF(IF('Model inputs'!B232="",0,1)="",0,IF('Model inputs'!B232="",0,1)),IF(IF('Model inputs'!B233="",0,1)="",0,IF('Model inputs'!B233="",0,1)),IF(IF('Model inputs'!B234="",0,1)="",0,IF('Model inputs'!B234="",0,1)))=0,"",SUM('Model inputs'!B232,'Model inputs'!B233,'Model inputs'!B234))="",0,IF(SUM(IF(IF('Model inputs'!B232="",0,1)="",0,IF('Model inputs'!B232="",0,1)),IF(IF('Model inputs'!B233="",0,1)="",0,IF('Model inputs'!B233="",0,1)),IF(IF('Model inputs'!B234="",0,1)="",0,IF('Model inputs'!B234="",0,1)))=0,"",SUM('Model inputs'!B232,'Model inputs'!B233,'Model inputs'!B234))),"") | E30: =IFERROR('RC Unit economics'!E22*(1-(1-IF(IF(SUM(IF(IF('Model inputs'!B232="",0,1)="",0,IF('Model inputs'!B232="",0,1)),IF(IF('Model inputs'!B233="",0,1)="",0,IF('Model inputs'!B233="",0,1)),IF(IF('Model inputs'!B234="",0,1)="",0,IF('Model inputs'!B234="",0,1)))=0,"",SUM('Model inputs'!B232,'Model inputs'!B233,'Model inputs'!B234))="",0,IF(SUM(IF(IF('Model inputs'!B232="",0,1)="",0,IF('Model inputs'!B232="",0,1)),IF(IF('Model inputs'!B233="",0,1)="",0,IF('Model inputs'!B233="",0,1)),IF(IF('Model inputs'!B234="",0,1)="",0,IF('Model inputs'!B234="",0,1)))=0,"",SUM('Model inputs'!B232,'Model inputs'!B233,'Model inputs'!B234))))^24)/IF(IF(SUM(IF(IF('Model inputs'!B232="",0,1)="",0,IF('Model inputs'!B232="",0,1)),IF(IF('Model inputs'!B233="",0,1)="",0,IF('Model inputs'!B233="",0,1)),IF(IF('Model inputs'!B234="",0,1)="",0,IF('Model inputs'!B234="",0,1)))=0,"",SUM('Model inputs'!B232,'Model inputs'!B233,'Model inputs'!B234))="",0,IF(SUM(IF(IF('Model inputs'!B232="",0,1)="",0,IF('Model inputs'!B232="",0,1)),IF(IF('Model inputs'!B233="",0,1)="",0,IF('Model inputs'!B233="",0,1)),IF(IF('Model inputs'!B234="",0,1)="",0,IF('Model inputs'!B234="",0,1)))=0,"",SUM('Model inputs'!B232,'Model inputs'!B233,'Model inputs'!B234))),"") | F30: =IFERROR('RC Unit economics'!F22*(1-(1-IF(IF(SUM(IF(IF('Model inputs'!B232="",0,1)="",0,IF('Model inputs'!B232="",0,1)),IF(IF('Model inputs'!B233="",0,1)="",0,IF('Model inputs'!B233="",0,1)),IF(IF('Model inputs'!B234="",0,1)="",0,IF('Model inputs'!B234="",0,1)))=0,"",SUM('Model inputs'!B232,'Model inputs'!B233,'Model inputs'!B234))="",0,IF(SUM(IF(IF('Model inputs'!B232="",0,1)="",0,IF('Model inputs'!B232="",0,1)),IF(IF('Model inputs'!B233="",0,1)="",0,IF('Model inputs'!B233="",0,1)),IF(IF('Model inputs'!B234="",0,1)="",0,IF('Model inputs'!B234="",0,1)))=0,"",SUM('Model inputs'!B232,'Model inputs'!B233,'Model inputs'!B234))))^24)/IF(IF(SUM(IF(IF('Model inputs'!B232="",0,1)="",0,IF('Model inputs'!B232="",0,1)),IF(IF('Model inputs'!B233="",0,1)="",0,IF('Model inputs'!B233="",0,1)),IF(IF('Model inputs'!B234="",0,1)="",0,IF('Model inputs'!B234="",0,1)))=0,"",SUM('Model inputs'!B232,'Model inputs'!B233,'Model inputs'!B234))="",0,IF(SUM(IF(IF('Model inputs'!B232="",0,1)="",0,IF('Model inputs'!B232="",0,1)),IF(IF('Model inputs'!B233="",0,1)="",0,IF('Model inputs'!B233="",0,1)),IF(IF('Model inputs'!B234="",0,1)="",0,IF('Model inputs'!B234="",0,1)))=0,"",SUM('Model inputs'!B232,'Model inputs'!B233,'Model inputs'!B234))),"") | G30: =IFERROR('RC Unit economics'!G22*(1-(1-IF(IF(SUM(IF(IF('Model inputs'!B232="",0,1)="",0,IF('Model inputs'!B232="",0,1)),IF(IF('Model inputs'!B233="",0,1)="",0,IF('Model inputs'!B233="",0,1)),IF(IF('Model inputs'!B234="",0,1)="",0,IF('Model inputs'!B234="",0,1)))=0,"",SUM('Model inputs'!B232,'Model inputs'!B233,'Model inputs'!B234))="",0,IF(SUM(IF(IF('Model inputs'!B232="",0,1)="",0,IF('Model inputs'!B232="",0,1)),IF(IF('Model inputs'!B233="",0,1)="",0,IF('Model inputs'!B233="",0,1)),IF(IF('Model inputs'!B234="",0,1)="",0,IF('Model inputs'!B234="",0,1)))=0,"",SUM('Model inputs'!B232,'Model inputs'!B233,'Model inputs'!B234))))^24)/IF(IF(SUM(IF(IF('Model inputs'!B232="",0,1)="",0,IF('Model inputs'!B232="",0,1)),IF(IF('Model inputs'!B233="",0,1)="",0,IF('Model inputs'!B233="",0,1)),IF(IF('Model inputs'!B234="",0,1)="",0,IF('Model inputs'!B234="",0,1)))=0,"",SUM('Model inputs'!B232,'Model inputs'!B233,'Model inputs'!B234))="",0,IF(SUM(IF(IF('Model inputs'!B232="",0,1)="",0,IF('Model inputs'!B232="",0,1)),IF(IF('Model inputs'!B233="",0,1)="",0,IF('Model inputs'!B233="",0,1)),IF(IF('Model inputs'!B234="",0,1)="",0,IF('Model inputs'!B234="",0,1)))=0,"",SUM('Model inputs'!B232,'Model inputs'!B233,'Model inputs'!B234))),"") | H30: =IFERROR('RC Unit economics'!H22*(1-(1-IF(IF(SUM(IF(IF('Model inputs'!B232="",0,1)="",0,IF('Model inputs'!B232="",0,1)),IF(IF('Model inputs'!B233="",0,1)="",0,IF('Model inputs'!B233="",0,1)),IF(IF('Model inputs'!B234="",0,1)="",0,IF('Model inputs'!B234="",0,1)))=0,"",SUM('Model inputs'!B232,'Model inputs'!B233,'Model inputs'!B234))="",0,IF(SUM(IF(IF('Model inputs'!B232="",0,1)="",0,IF('Model inputs'!B232="",0,1)),IF(IF('Model inputs'!B233="",0,1)="",0,IF('Model inputs'!B233="",0,1)),IF(IF('Model inputs'!B234="",0,1)="",0,IF('Model inputs'!B234="",0,1)))=0,"",SUM('Model inputs'!B232,'Model inputs'!B233,'Model inputs'!B234))))^24)/IF(IF(SUM(IF(IF('Model inputs'!B232="",0,1)="",0,IF('Model inputs'!B232="",0,1)),IF(IF('Model inputs'!B233="",0,1)="",0,IF('Model inputs'!B233="",0,1)),IF(IF('Model inputs'!B234="",0,1)="",0,IF('Model inputs'!B234="",0,1)))=0,"",SUM('Model inputs'!B232,'Model inputs'!B233,'Model inputs'!B234))="",0,IF(SUM(IF(IF('Model inputs'!B232="",0,1)="",0,IF('Model inputs'!B232="",0,1)),IF(IF('Model inputs'!B233="",0,1)="",0,IF('Model inputs'!B233="",0,1)),IF(IF('Model inputs'!B234="",0,1)="",0,IF('Model inputs'!B234="",0,1)))=0,"",SUM('Model inputs'!B232,'Model inputs'!B233,'Model inputs'!B234))),"") | I30: =IFERROR('RC Unit economics'!I22*(1-(1-IF(IF(SUM(IF(IF('Model inputs'!B232="",0,1)="",0,IF('Model inputs'!B232="",0,1)),IF(IF('Model inputs'!B233="",0,1)="",0,IF('Model inputs'!B233="",0,1)),IF(IF('Model inputs'!B234="",0,1)="",0,IF('Model inputs'!B234="",0,1)))=0,"",SUM('Model inputs'!B232,'Model inputs'!B233,'Model inputs'!B234))="",0,IF(SUM(IF(IF('Model inputs'!B232="",0,1)="",0,IF('Model inputs'!B232="",0,1)),IF(IF('Model inputs'!B233="",0,1)="",0,IF('Model inputs'!B233="",0,1)),IF(IF('Model inputs'!B234="",0,1)="",0,IF('Model inputs'!B234="",0,1)))=0,"",SUM('Model inputs'!B232,'Model inputs'!B233,'Model inputs'!B234))))^24)/IF(IF(SUM(IF(IF('Model inputs'!B232="",0,1)="",0,IF('Model inputs'!B232="",0,1)),IF(IF('Model inputs'!B233="",0,1)="",0,IF('Model inputs'!B233="",0,1)),IF(IF('Model inputs'!B234="",0,1)="",0,IF('Model inputs'!B234="",0,1)))=0,"",SUM('Model inputs'!B232,'Model inputs'!B233,'Model inputs'!B234))="",0,IF(SUM(IF(IF('Model inputs'!B232="",0,1)="",0,IF('Model inputs'!B232="",0,1)),IF(IF('Model inputs'!B233="",0,1)="",0,IF('Model inputs'!B233="",0,1)),IF(IF('Model inputs'!B234="",0,1)="",0,IF('Model inputs'!B234="",0,1)))=0,"",SUM('Model inputs'!B232,'Model inputs'!B233,'Model inputs'!B234))),"") | J30: =IFERROR('RC Unit economics'!J22*(1-(1-IF(IF(SUM(IF(IF('Model inputs'!B232="",0,1)="",0,IF('Model inputs'!B232="",0,1)),IF(IF('Model inputs'!B233="",0,1)="",0,IF('Model inputs'!B233="",0,1)),IF(IF('Model inputs'!B234="",0,1)="",0,IF('Model inputs'!B234="",0,1)))=0,"",SUM('Model inputs'!B232,'Model inputs'!B233,'Model inputs'!B234))="",0,IF(SUM(IF(IF('Model inputs'!B232="",0,1)="",0,IF('Model inputs'!B232="",0,1)),IF(IF('Model inputs'!B233="",0,1)="",0,IF('Model inputs'!B233="",0,1)),IF(IF('Model inputs'!B234="",0,1)="",0,IF('Model inputs'!B234="",0,1)))=0,"",SUM('Model inputs'!B232,'Model inputs'!B233,'Model inputs'!B234))))^24)/IF(IF(SUM(IF(IF('Model inputs'!B232="",0,1)="",0,IF('Model inputs'!B232="",0,1)),IF(IF('Model inputs'!B233="",0,1)="",0,IF('Model inputs'!B233="",0,1)),IF(IF('Model inputs'!B234="",0,1)="",0,IF('Model inputs'!B234="",0,1)))=0,"",SUM('Model inputs'!B232,'Model inputs'!B233,'Model inputs'!B234))="",0,IF(SUM(IF(IF('Model inputs'!B232="",0,1)="",0,IF('Model inputs'!B232="",0,1)),IF(IF('Model inputs'!B233="",0,1)="",0,IF('Model inputs'!B233="",0,1)),IF(IF('Model inputs'!B234="",0,1)="",0,IF('Model inputs'!B234="",0,1)))=0,"",SUM('Model inputs'!B232,'Model inputs'!B233,'Model inputs'!B234))),"") | K30: =IFERROR('RC Unit economics'!K22*(1-(1-IF(IF(SUM(IF(IF('Model inputs'!B232="",0,1)="",0,IF('Model inputs'!B232="",0,1)),IF(IF('Model inputs'!B233="",0,1)="",0,IF('Model inputs'!B233="",0,1)),IF(IF('Model inputs'!B234="",0,1)="",0,IF('Model inputs'!B234="",0,1)))=0,"",SUM('Model inputs'!B232,'Model inputs'!B233,'Model inputs'!B234))="",0,IF(SUM(IF(IF('Model inputs'!B232="",0,1)="",0,IF('Model inputs'!B232="",0,1)),IF(IF('Model inputs'!B233="",0,1)="",0,IF('Model inputs'!B233="",0,1)),IF(IF('Model inputs'!B234="",0,1)="",0,IF('Model inputs'!B234="",0,1)))=0,"",SUM('Model inputs'!B232,'Model inputs'!B233,'Model inputs'!B234))))^24)/IF(IF(SUM(IF(IF('Model inputs'!B232="",0,1)="",0,IF('Model inputs'!B232="",0,1)),IF(IF('Model inputs'!B233="",0,1)="",0,IF('Model inputs'!B233="",0,1)),IF(IF('Model inputs'!B234="",0,1)="",0,IF('Model inputs'!B234="",0,1)))=0,"",SUM('Model inputs'!B232,'Model inputs'!B233,'Model inputs'!B234))="",0,IF(SUM(IF(IF('Model inputs'!B232="",0,1)="",0,IF('Model inputs'!B232="",0,1)),IF(IF('Model inputs'!B233="",0,1)="",0,IF('Model inputs'!B233="",0,1)),IF(IF('Model inputs'!B234="",0,1)="",0,IF('Model inputs'!B234="",0,1)))=0,"",SUM('Model inputs'!B232,'Model inputs'!B233,'Model inputs'!B234))),"") | L30: =IFERROR('RC Unit economics'!L22*(1-(1-IF(IF(SUM(IF(IF('Model inputs'!B232="",0,1)="",0,IF('Model inputs'!B232="",0,1)),IF(IF('Model inputs'!B233="",0,1)="",0,IF('Model inputs'!B233="",0,1)),IF(IF('Model inputs'!B234="",0,1)="",0,IF('Model inputs'!B234="",0,1)))=0,"",SUM('Model inputs'!B232,'Model inputs'!B233,'Model inputs'!B234))="",0,IF(SUM(IF(IF('Model inputs'!B232="",0,1)="",0,IF('Model inputs'!B232="",0,1)),IF(IF('Model inputs'!B233="",0,1)="",0,IF('Model inputs'!B233="",0,1)),IF(IF('Model inputs'!B234="",0,1)="",0,IF('Model inputs'!B234="",0,1)))=0,"",SUM('Model inputs'!B232,'Model inputs'!B233,'Model inputs'!B234))))^24)/IF(IF(SUM(IF(IF('Model inputs'!B232="",0,1)="",0,IF('Model inputs'!B232="",0,1)),IF(IF('Model inputs'!B233="",0,1)="",0,IF('Model inputs'!B233="",0,1)),IF(IF('Model inputs'!B234="",0,1)="",0,IF('Model inputs'!B234="",0,1)))=0,"",SUM('Model inputs'!B232,'Model inputs'!B233,'Model inputs'!B234))="",0,IF(SUM(IF(IF('Model inputs'!B232="",0,1)="",0,IF('Model inputs'!B232="",0,1)),IF(IF('Model inputs'!B233="",0,1)="",0,IF('Model inputs'!B233="",0,1)),IF(IF('Model inputs'!B234="",0,1)="",0,IF('Model inputs'!B234="",0,1)))=0,"",SUM('Model inputs'!B232,'Model inputs'!B233,'Model inputs'!B234))),"") | M30: =IFERROR('RC Unit economics'!M22*(1-(1-IF(IF(SUM(IF(IF('Model inputs'!B232="",0,1)="",0,IF('Model inputs'!B232="",0,1)),IF(IF('Model inputs'!B233="",0,1)="",0,IF('Model inputs'!B233="",0,1)),IF(IF('Model inputs'!B234="",0,1)="",0,IF('Model inputs'!B234="",0,1)))=0,"",SUM('Model inputs'!B232,'Model inputs'!B233,'Model inputs'!B234))="",0,IF(SUM(IF(IF('Model inputs'!B232="",0,1)="",0,IF('Model inputs'!B232="",0,1)),IF(IF('Model inputs'!B233="",0,1)="",0,IF('Model inputs'!B233="",0,1)),IF(IF('Model inputs'!B234="",0,1)="",0,IF('Model inputs'!B234="",0,1)))=0,"",SUM('Model inputs'!B232,'Model inputs'!B233,'Model inputs'!B234))))^24)/IF(IF(SUM(IF(IF('Model inputs'!B232="",0,1)="",0,IF('Model inputs'!B232="",0,1)),IF(IF('Model inputs'!B233="",0,1)="",0,IF('Model inputs'!B233="",0,1)),IF(IF('Model inputs'!B234="",0,1)="",0,IF('Model inputs'!B234="",0,1)))=0,"",SUM('Model inputs'!B232,'Model inputs'!B233,'Model inputs'!B234))="",0,IF(SUM(IF(IF('Model inputs'!B232="",0,1)="",0,IF('Model inputs'!B232="",0,1)),IF(IF('Model inputs'!B233="",0,1)="",0,IF('Model inputs'!B233="",0,1)),IF(IF('Model inputs'!B234="",0,1)="",0,IF('Model inputs'!B234="",0,1)))=0,"",SUM('Model inputs'!B232,'Model inputs'!B233,'Model inputs'!B234))),"") | N30: =IFERROR('RC Unit economics'!N22*(1-(1-IF(IF(SUM(IF(IF('Model inputs'!B232="",0,1)="",0,IF('Model inputs'!B232="",0,1)),IF(IF('Model inputs'!B233="",0,1)="",0,IF('Model inputs'!B233="",0,1)),IF(IF('Model inputs'!B234="",0,1)="",0,IF('Model inputs'!B234="",0,1)))=0,"",SUM('Model inputs'!B232,'Model inputs'!B233,'Model inputs'!B234))="",0,IF(SUM(IF(IF('Model inputs'!B232="",0,1)="",0,IF('Model inputs'!B232="",0,1)),IF(IF('Model inputs'!B233="",0,1)="",0,IF('Model inputs'!B233="",0,1)),IF(IF('Model inputs'!B234="",0,1)="",0,IF('Model inputs'!B234="",0,1)))=0,"",SUM('Model inputs'!B232,'Model inputs'!B233,'Model inputs'!B234))))^24)/IF(IF(SUM(IF(IF('Model inputs'!B232="",0,1)="",0,IF('Model inputs'!B232="",0,1)),IF(IF('Model inputs'!B233="",0,1)="",0,IF('Model inputs'!B233="",0,1)),IF(IF('Model inputs'!B234="",0,1)="",0,IF('Model inputs'!B234="",0,1)))=0,"",SUM('Model inputs'!B232,'Model inputs'!B233,'Model inputs'!B234))="",0,IF(SUM(IF(IF('Model inputs'!B232="",0,1)="",0,IF('Model inputs'!B232="",0,1)),IF(IF('Model inputs'!B233="",0,1)="",0,IF('Model inputs'!B233="",0,1)),IF(IF('Model inputs'!B234="",0,1)="",0,IF('Model inputs'!B234="",0,1)))=0,"",SUM('Model inputs'!B232,'Model inputs'!B233,'Model inputs'!B234))),"") | O30: =IFERROR('RC Unit economics'!O22*(1-(1-IF(IF(SUM(IF(IF('Model inputs'!B232="",0,1)="",0,IF('Model inputs'!B232="",0,1)),IF(IF('Model inputs'!B233="",0,1)="",0,IF('Model inputs'!B233="",0,1)),IF(IF('Model inputs'!B234="",0,1)="",0,IF('Model inputs'!B234="",0,1)))=0,"",SUM('Model inputs'!B232,'Model inputs'!B233,'Model inputs'!B234))="",0,IF(SUM(IF(IF('Model inputs'!B232="",0,1)="",0,IF('Model inputs'!B232="",0,1)),IF(IF('Model inputs'!B233="",0,1)="",0,IF('Model inputs'!B233="",0,1)),IF(IF('Model inputs'!B234="",0,1)="",0,IF('Model inputs'!B234="",0,1)))=0,"",SUM('Model inputs'!B232,'Model inputs'!B233,'Model inputs'!B234))))^24)/IF(IF(SUM(IF(IF('Model inputs'!B232="",0,1)="",0,IF('Model inputs'!B232="",0,1)),IF(IF('Model inputs'!B233="",0,1)="",0,IF('Model inputs'!B233="",0,1)),IF(IF('Model inputs'!B234="",0,1)="",0,IF('Model inputs'!B234="",0,1)))=0,"",SUM('Model inputs'!B232,'Model inputs'!B233,'Model inputs'!B234))="",0,IF(SUM(IF(IF('Model inputs'!B232="",0,1)="",0,IF('Model inputs'!B232="",0,1)),IF(IF('Model inputs'!B233="",0,1)="",0,IF('Model inputs'!B233="",0,1)),IF(IF('Model inputs'!B234="",0,1)="",0,IF('Model inputs'!B234="",0,1)))=0,"",SUM('Model inputs'!B232,'Model inputs'!B233,'Model inputs'!B234))),"") | P30: =IFERROR('RC Unit economics'!P22*(1-(1-IF(IF(SUM(IF(IF('Model inputs'!B232="",0,1)="",0,IF('Model inputs'!B232="",0,1)),IF(IF('Model inputs'!B233="",0,1)="",0,IF('Model inputs'!B233="",0,1)),IF(IF('Model inputs'!B234="",0,1)="",0,IF('Model inputs'!B234="",0,1)))=0,"",SUM('Model inputs'!B232,'Model inputs'!B233,'Model inputs'!B234))="",0,IF(SUM(IF(IF('Model inputs'!B232="",0,1)="",0,IF('Model inputs'!B232="",0,1)),IF(IF('Model inputs'!B233="",0,1)="",0,IF('Model inputs'!B233="",0,1)),IF(IF('Model inputs'!B234="",0,1)="",0,IF('Model inputs'!B234="",0,1)))=0,"",SUM('Model inputs'!B232,'Model inputs'!B233,'Model inputs'!B234))))^24)/IF(IF(SUM(IF(IF('Model inputs'!B232="",0,1)="",0,IF('Model inputs'!B232="",0,1)),IF(IF('Model inputs'!B233="",0,1)="",0,IF('Model inputs'!B233="",0,1)),IF(IF('Model inputs'!B234="",0,1)="",0,IF('Model inputs'!B234="",0,1)))=0,"",SUM('Model inputs'!B232,'Model inputs'!B233,'Model inputs'!B234))="",0,IF(SUM(IF(IF('Model inputs'!B232="",0,1)="",0,IF('Model inputs'!B232="",0,1)),IF(IF('Model inputs'!B233="",0,1)="",0,IF('Model inputs'!B233="",0,1)),IF(IF('Model inputs'!B234="",0,1)="",0,IF('Model inputs'!B234="",0,1)))=0,"",SUM('Model inputs'!B232,'Model inputs'!B233,'Model inputs'!B234))),"") | Q30: =IFERROR('RC Unit economics'!Q22*(1-(1-IF(IF(SUM(IF(IF('Model inputs'!B232="",0,1)="",0,IF('Model inputs'!B232="",0,1)),IF(IF('Model inputs'!B233="",0,1)="",0,IF('Model inputs'!B233="",0,1)),IF(IF('Model inputs'!B234="",0,1)="",0,IF('Model inputs'!B234="",0,1)))=0,"",SUM('Model inputs'!B232,'Model inputs'!B233,'Model inputs'!B234))="",0,IF(SUM(IF(IF('Model inputs'!B232="",0,1)="",0,IF('Model inputs'!B232="",0,1)),IF(IF('Model inputs'!B233="",0,1)="",0,IF('Model inputs'!B233="",0,1)),IF(IF('Model inputs'!B234="",0,1)="",0,IF('Model inputs'!B234="",0,1)))=0,"",SUM('Model inputs'!B232,'Model inputs'!B233,'Model inputs'!B234))))^24)/IF(IF(SUM(IF(IF('Model inputs'!B232="",0,1)="",0,IF('Model inputs'!B232="",0,1)),IF(IF('Model inputs'!B233="",0,1)="",0,IF('Model inputs'!B233="",0,1)),IF(IF('Model inputs'!B234="",0,1)="",0,IF('Model inputs'!B234="",0,1)))=0,"",SUM('Model inputs'!B232,'Model inputs'!B233,'Model inputs'!B234))="",0,IF(SUM(IF(IF('Model inputs'!B232="",0,1)="",0,IF('Model inputs'!B232="",0,1)),IF(IF('Model inputs'!B233="",0,1)="",0,IF('Model inputs'!B233="",0,1)),IF(IF('Model inputs'!B234="",0,1)="",0,IF('Model inputs'!B234="",0,1)))=0,"",SUM('Model inputs'!B232,'Model inputs'!B233,'Model inputs'!B234))),"") | R30: =IFERROR('RC Unit economics'!R22*(1-(1-IF(IF(SUM(IF(IF('Model inputs'!B232="",0,1)="",0,IF('Model inputs'!B232="",0,1)),IF(IF('Model inputs'!B233="",0,1)="",0,IF('Model inputs'!B233="",0,1)),IF(IF('Model inputs'!B234="",0,1)="",0,IF('Model inputs'!B234="",0,1)))=0,"",SUM('Model inputs'!B232,'Model inputs'!B233,'Model inputs'!B234))="",0,IF(SUM(IF(IF('Model inputs'!B232="",0,1)="",0,IF('Model inputs'!B232="",0,1)),IF(IF('Model inputs'!B233="",0,1)="",0,IF('Model inputs'!B233="",0,1)),IF(IF('Model inputs'!B234="",0,1)="",0,IF('Model inputs'!B234="",0,1)))=0,"",SUM('Model inputs'!B232,'Model inputs'!B233,'Model inputs'!B234))))^24)/IF(IF(SUM(IF(IF('Model inputs'!B232="",0,1)="",0,IF('Model inputs'!B232="",0,1)),IF(IF('Model inputs'!B233="",0,1)="",0,IF('Model inputs'!B233="",0,1)),IF(IF('Model inputs'!B234="",0,1)="",0,IF('Model inputs'!B234="",0,1)))=0,"",SUM('Model inputs'!B232,'Model inputs'!B233,'Model inputs'!B234))="",0,IF(SUM(IF(IF('Model inputs'!B232="",0,1)="",0,IF('Model inputs'!B232="",0,1)),IF(IF('Model inputs'!B233="",0,1)="",0,IF('Model inputs'!B233="",0,1)),IF(IF('Model inputs'!B234="",0,1)="",0,IF('Model inputs'!B234="",0,1)))=0,"",SUM('Model inputs'!B232,'Model inputs'!B233,'Model inputs'!B234))),"") | S30: =IFERROR('RC Unit economics'!S22*(1-(1-IF(IF(SUM(IF(IF('Model inputs'!B232="",0,1)="",0,IF('Model inputs'!B232="",0,1)),IF(IF('Model inputs'!B233="",0,1)="",0,IF('Model inputs'!B233="",0,1)),IF(IF('Model inputs'!B234="",0,1)="",0,IF('Model inputs'!B234="",0,1)))=0,"",SUM('Model inputs'!B232,'Model inputs'!B233,'Model inputs'!B234))="",0,IF(SUM(IF(IF('Model inputs'!B232="",0,1)="",0,IF('Model inputs'!B232="",0,1)),IF(IF('Model inputs'!B233="",0,1)="",0,IF('Model inputs'!B233="",0,1)),IF(IF('Model inputs'!B234="",0,1)="",0,IF('Model inputs'!B234="",0,1)))=0,"",SUM('Model inputs'!B232,'Model inputs'!B233,'Model inputs'!B234))))^24)/IF(IF(SUM(IF(IF('Model inputs'!B232="",0,1)="",0,IF('Model inputs'!B232="",0,1)),IF(IF('Model inputs'!B233="",0,1)="",0,IF('Model inputs'!B233="",0,1)),IF(IF('Model inputs'!B234="",0,1)="",0,IF('Model inputs'!B234="",0,1)))=0,"",SUM('Model inputs'!B232,'Model inputs'!B233,'Model inputs'!B234))="",0,IF(SUM(IF(IF('Model inputs'!B232="",0,1)="",0,IF('Model inputs'!B232="",0,1)),IF(IF('Model inputs'!B233="",0,1)="",0,IF('Model inputs'!B233="",0,1)),IF(IF('Model inputs'!B234="",0,1)="",0,IF('Model inputs'!B234="",0,1)))=0,"",SUM('Model inputs'!B232,'Model inputs'!B233,'Model inputs'!B234))),"")
A31: Indie | B31: =IFERROR('RC Unit economics'!B23*(1-(1-'Model inputs'!B39)^24)/'Model inputs'!B39,"") -> 354.88122 | C31: =IFERROR('RC Unit economics'!C23*(1-(1-'Model inputs'!B39)^24)/'Model inputs'!B39,"") -> 354.88122 | D31: =IFERROR('RC Unit economics'!D23*(1-(1-'Model inputs'!B39)^24)/'Model inputs'!B39,"") -> 354.88122 | E31: =IFERROR('RC Unit economics'!E23*(1-(1-'Model inputs'!B39)^24)/'Model inputs'!B39,"") -> 354.88122 | F31: =IFERROR('RC Unit economics'!F23*(1-(1-'Model inputs'!B39)^24)/'Model inputs'!B39,"") -> 354.88122 | G31: =IFERROR('RC Unit economics'!G23*(1-(1-'Model inputs'!B39)^24)/'Model inputs'!B39,"") -> 354.88122 | H31: =IFERROR('RC Unit economics'!H23*(1-(1-'Model inputs'!B39)^24)/'Model inputs'!B39,"") -> 354.88122 | I31: =IFERROR('RC Unit economics'!I23*(1-(1-'Model inputs'!B39)^24)/'Model inputs'!B39,"") -> 354.88122 | J31: =IFERROR('RC Unit economics'!J23*(1-(1-'Model inputs'!B39)^24)/'Model inputs'!B39,"") -> 354.88122 | K31: =IFERROR('RC Unit economics'!K23*(1-(1-'Model inputs'!B39)^24)/'Model inputs'!B39,"") -> 354.88122 | L31: =IFERROR('RC Unit economics'!L23*(1-(1-'Model inputs'!B39)^24)/'Model inputs'!B39,"") -> 354.88122 | M31: =IFERROR('RC Unit economics'!M23*(1-(1-'Model inputs'!B39)^24)/'Model inputs'!B39,"") -> 354.88122 | N31: =IFERROR('RC Unit economics'!N23*(1-(1-'Model inputs'!B39)^24)/'Model inputs'!B39,"") -> 354.88122 | O31: =IFERROR('RC Unit economics'!O23*(1-(1-'Model inputs'!B39)^24)/'Model inputs'!B39,"") -> 354.88122 | P31: =IFERROR('RC Unit economics'!P23*(1-(1-'Model inputs'!B39)^24)/'Model inputs'!B39,"") -> 354.88122 | Q31: =IFERROR('RC Unit economics'!Q23*(1-(1-'Model inputs'!B39)^24)/'Model inputs'!B39,"") -> 354.88122 | R31: =IFERROR('RC Unit economics'!R23*(1-(1-'Model inputs'!B39)^24)/'Model inputs'!B39,"") -> 354.88122 | S31: =IFERROR('RC Unit economics'!S23*(1-(1-'Model inputs'!B39)^24)/'Model inputs'!B39,"") -> 354.88122
A32: Launch | B32: =IFERROR('RC Unit economics'!B24*(1-(1-'Model inputs'!B40)^24)/'Model inputs'!B40,"") -> 9357.0246 | C32: =IFERROR('RC Unit economics'!C24*(1-(1-'Model inputs'!B40)^24)/'Model inputs'!B40,"") -> 9104.5459 | D32: =IFERROR('RC Unit economics'!D24*(1-(1-'Model inputs'!B40)^24)/'Model inputs'!B40,"") -> 8978.0705 | E32: =IFERROR('RC Unit economics'!E24*(1-(1-'Model inputs'!B40)^24)/'Model inputs'!B40,"") -> 8868.3085 | F32: =IFERROR('RC Unit economics'!F24*(1-(1-'Model inputs'!B40)^24)/'Model inputs'!B40,"") -> 8766.7364 | G32: =IFERROR('RC Unit economics'!G24*(1-(1-'Model inputs'!B40)^24)/'Model inputs'!B40,"") -> 8669.7051 | H32: =IFERROR('RC Unit economics'!H24*(1-(1-'Model inputs'!B40)^24)/'Model inputs'!B40,"") -> 8575.387 | I32: =IFERROR('RC Unit economics'!I24*(1-(1-'Model inputs'!B40)^24)/'Model inputs'!B40,"") -> 8735.2407 | J32: =IFERROR('RC Unit economics'!J24*(1-(1-'Model inputs'!B40)^24)/'Model inputs'!B40,"") -> 8745.596 | K32: =IFERROR('RC Unit economics'!K24*(1-(1-'Model inputs'!B40)^24)/'Model inputs'!B40,"") -> 8753.8705 | L32: =IFERROR('RC Unit economics'!L24*(1-(1-'Model inputs'!B40)^24)/'Model inputs'!B40,"") -> 8760.7833 | M32: =IFERROR('RC Unit economics'!M24*(1-(1-'Model inputs'!B40)^24)/'Model inputs'!B40,"") -> 8766.6429 | N32: =IFERROR('RC Unit economics'!N24*(1-(1-'Model inputs'!B40)^24)/'Model inputs'!B40,"") -> 8771.6716 | O32: =IFERROR('RC Unit economics'!O24*(1-(1-'Model inputs'!B40)^24)/'Model inputs'!B40,"") -> 8750.5099 | P32: =IFERROR('RC Unit economics'!P24*(1-(1-'Model inputs'!B40)^24)/'Model inputs'!B40,"") -> 8739.788 | Q32: =IFERROR('RC Unit economics'!Q24*(1-(1-'Model inputs'!B40)^24)/'Model inputs'!B40,"") -> 8730.2397 | R32: =IFERROR('RC Unit economics'!R24*(1-(1-'Model inputs'!B40)^24)/'Model inputs'!B40,"") -> 8721.6128 | S32: =IFERROR('RC Unit economics'!S24*(1-(1-'Model inputs'!B40)^24)/'Model inputs'!B40,"") -> 8713.7047
A33: Team | B33: =IFERROR('RC Unit economics'!B25*(1-(1-'Model inputs'!B41)^24)/'Model inputs'!B41,"") -> 2432.0187 | C33: =IFERROR('RC Unit economics'!C25*(1-(1-'Model inputs'!B41)^24)/'Model inputs'!B41,"") -> 2367.764 | D33: =IFERROR('RC Unit economics'!D25*(1-(1-'Model inputs'!B41)^24)/'Model inputs'!B41,"") -> 2334.2434 | E33: =IFERROR('RC Unit economics'!E25*(1-(1-'Model inputs'!B41)^24)/'Model inputs'!B41,"") -> 2304.4096 | F33: =IFERROR('RC Unit economics'!F25*(1-(1-'Model inputs'!B41)^24)/'Model inputs'!B41,"") -> 2276.4974 | G33: =IFERROR('RC Unit economics'!G25*(1-(1-'Model inputs'!B41)^24)/'Model inputs'!B41,"") -> 2249.7089 | H33: =IFERROR('RC Unit economics'!H25*(1-(1-'Model inputs'!B41)^24)/'Model inputs'!B41,"") -> 2223.6282 | I33: =IFERROR('RC Unit economics'!I25*(1-(1-'Model inputs'!B41)^24)/'Model inputs'!B41,"") -> 2262.2698 | J33: =IFERROR('RC Unit economics'!J25*(1-(1-'Model inputs'!B41)^24)/'Model inputs'!B41,"") -> 2264.8385 | K33: =IFERROR('RC Unit economics'!K25*(1-(1-'Model inputs'!B41)^24)/'Model inputs'!B41,"") -> 2268.5316 | L33: =IFERROR('RC Unit economics'!L25*(1-(1-'Model inputs'!B41)^24)/'Model inputs'!B41,"") -> 2271.4877 | M33: =IFERROR('RC Unit economics'!M25*(1-(1-'Model inputs'!B41)^24)/'Model inputs'!B41,"") -> 2273.907 | N33: =IFERROR('RC Unit economics'!N25*(1-(1-'Model inputs'!B41)^24)/'Model inputs'!B41,"") -> 2275.9227 | O33: =IFERROR('RC Unit economics'!O25*(1-(1-'Model inputs'!B41)^24)/'Model inputs'!B41,"") -> 2273.9803 | P33: =IFERROR('RC Unit economics'!P25*(1-(1-'Model inputs'!B41)^24)/'Model inputs'!B41,"") -> 2273.1081 | Q33: =IFERROR('RC Unit economics'!Q25*(1-(1-'Model inputs'!B41)^24)/'Model inputs'!B41,"") -> 2272.0093 | R33: =IFERROR('RC Unit economics'!R25*(1-(1-'Model inputs'!B41)^24)/'Model inputs'!B41,"") -> 2270.7029 | S33: =IFERROR('RC Unit economics'!S25*(1-(1-'Model inputs'!B41)^24)/'Model inputs'!B41,"") -> 2269.2
A34: LTV:CAC | B34: =IFERROR(IF('RC Unit economics'!B30="",0,'RC Unit economics'!B30)/IF(IF(SUM(IF(IF('Model inputs'!B235="",0,1)="",0,IF('Model inputs'!B235="",0,1)),IF(IF('Model inputs'!B236="",0,1)="",0,IF('Model inputs'!B236="",0,1)),IF(IF('Model inputs'!B237="",0,1)="",0,IF('Model inputs'!B237="",0,1)))=0,"",SUM('Model inputs'!B235,'Model inputs'!B236,'Model inputs'!B237))="",0,IF(SUM(IF(IF('Model inputs'!B235="",0,1)="",0,IF('Model inputs'!B235="",0,1)),IF(IF('Model inputs'!B236="",0,1)="",0,IF('Model inputs'!B236="",0,1)),IF(IF('Model inputs'!B237="",0,1)="",0,IF('Model inputs'!B237="",0,1)))=0,"",SUM('Model inputs'!B235,'Model inputs'!B236,'Model inputs'!B237))),"") | C34: =IFERROR(IF('RC Unit economics'!C30="",0,'RC Unit economics'!C30)/IF(IF(SUM(IF(IF('Model inputs'!B235="",0,1)="",0,IF('Model inputs'!B235="",0,1)),IF(IF('Model inputs'!B236="",0,1)="",0,IF('Model inputs'!B236="",0,1)),IF(IF('Model inputs'!B237="",0,1)="",0,IF('Model inputs'!B237="",0,1)))=0,"",SUM('Model inputs'!B235,'Model inputs'!B236,'Model inputs'!B237))="",0,IF(SUM(IF(IF('Model inputs'!B235="",0,1)="",0,IF('Model inputs'!B235="",0,1)),IF(IF('Model inputs'!B236="",0,1)="",0,IF('Model inputs'!B236="",0,1)),IF(IF('Model inputs'!B237="",0,1)="",0,IF('Model inputs'!B237="",0,1)))=0,"",SUM('Model inputs'!B235,'Model inputs'!B236,'Model inputs'!B237))),"") | D34: =IFERROR(IF('RC Unit economics'!D30="",0,'RC Unit economics'!D30)/IF(IF(SUM(IF(IF('Model inputs'!B235="",0,1)="",0,IF('Model inputs'!B235="",0,1)),IF(IF('Model inputs'!B236="",0,1)="",0,IF('Model inputs'!B236="",0,1)),IF(IF('Model inputs'!B237="",0,1)="",0,IF('Model inputs'!B237="",0,1)))=0,"",SUM('Model inputs'!B235,'Model inputs'!B236,'Model inputs'!B237))="",0,IF(SUM(IF(IF('Model inputs'!B235="",0,1)="",0,IF('Model inputs'!B235="",0,1)),IF(IF('Model inputs'!B236="",0,1)="",0,IF('Model inputs'!B236="",0,1)),IF(IF('Model inputs'!B237="",0,1)="",0,IF('Model inputs'!B237="",0,1)))=0,"",SUM('Model inputs'!B235,'Model inputs'!B236,'Model inputs'!B237))),"") | E34: =IFERROR(IF('RC Unit economics'!E30="",0,'RC Unit economics'!E30)/IF(IF(SUM(IF(IF('Model inputs'!B235="",0,1)="",0,IF('Model inputs'!B235="",0,1)),IF(IF('Model inputs'!B236="",0,1)="",0,IF('Model inputs'!B236="",0,1)),IF(IF('Model inputs'!B237="",0,1)="",0,IF('Model inputs'!B237="",0,1)))=0,"",SUM('Model inputs'!B235,'Model inputs'!B236,'Model inputs'!B237))="",0,IF(SUM(IF(IF('Model inputs'!B235="",0,1)="",0,IF('Model inputs'!B235="",0,1)),IF(IF('Model inputs'!B236="",0,1)="",0,IF('Model inputs'!B236="",0,1)),IF(IF('Model inputs'!B237="",0,1)="",0,IF('Model inputs'!B237="",0,1)))=0,"",SUM('Model inputs'!B235,'Model inputs'!B236,'Model inputs'!B237))),"") | F34: =IFERROR(IF('RC Unit economics'!F30="",0,'RC Unit economics'!F30)/IF(IF(SUM(IF(IF('Model inputs'!B235="",0,1)="",0,IF('Model inputs'!B235="",0,1)),IF(IF('Model inputs'!B236="",0,1)="",0,IF('Model inputs'!B236="",0,1)),IF(IF('Model inputs'!B237="",0,1)="",0,IF('Model inputs'!B237="",0,1)))=0,"",SUM('Model inputs'!B235,'Model inputs'!B236,'Model inputs'!B237))="",0,IF(SUM(IF(IF('Model inputs'!B235="",0,1)="",0,IF('Model inputs'!B235="",0,1)),IF(IF('Model inputs'!B236="",0,1)="",0,IF('Model inputs'!B236="",0,1)),IF(IF('Model inputs'!B237="",0,1)="",0,IF('Model inputs'!B237="",0,1)))=0,"",SUM('Model inputs'!B235,'Model inputs'!B236,'Model inputs'!B237))),"") | G34: =IFERROR(IF('RC Unit economics'!G30="",0,'RC Unit economics'!G30)/IF(IF(SUM(IF(IF('Model inputs'!B235="",0,1)="",0,IF('Model inputs'!B235="",0,1)),IF(IF('Model inputs'!B236="",0,1)="",0,IF('Model inputs'!B236="",0,1)),IF(IF('Model inputs'!B237="",0,1)="",0,IF('Model inputs'!B237="",0,1)))=0,"",SUM('Model inputs'!B235,'Model inputs'!B236,'Model inputs'!B237))="",0,IF(SUM(IF(IF('Model inputs'!B235="",0,1)="",0,IF('Model inputs'!B235="",0,1)),IF(IF('Model inputs'!B236="",0,1)="",0,IF('Model inputs'!B236="",0,1)),IF(IF('Model inputs'!B237="",0,1)="",0,IF('Model inputs'!B237="",0,1)))=0,"",SUM('Model inputs'!B235,'Model inputs'!B236,'Model inputs'!B237))),"") | H34: =IFERROR(IF('RC Unit economics'!H30="",0,'RC Unit economics'!H30)/IF(IF(SUM(IF(IF('Model inputs'!B235="",0,1)="",0,IF('Model inputs'!B235="",0,1)),IF(IF('Model inputs'!B236="",0,1)="",0,IF('Model inputs'!B236="",0,1)),IF(IF('Model inputs'!B237="",0,1)="",0,IF('Model inputs'!B237="",0,1)))=0,"",SUM('Model inputs'!B235,'Model inputs'!B236,'Model inputs'!B237))="",0,IF(SUM(IF(IF('Model inputs'!B235="",0,1)="",0,IF('Model inputs'!B235="",0,1)),IF(IF('Model inputs'!B236="",0,1)="",0,IF('Model inputs'!B236="",0,1)),IF(IF('Model inputs'!B237="",0,1)="",0,IF('Model inputs'!B237="",0,1)))=0,"",SUM('Model inputs'!B235,'Model inputs'!B236,'Model inputs'!B237))),"") | I34: =IFERROR(IF('RC Unit economics'!I30="",0,'RC Unit economics'!I30)/IF(IF(SUM(IF(IF('Model inputs'!B235="",0,1)="",0,IF('Model inputs'!B235="",0,1)),IF(IF('Model inputs'!B236="",0,1)="",0,IF('Model inputs'!B236="",0,1)),IF(IF('Model inputs'!B237="",0,1)="",0,IF('Model inputs'!B237="",0,1)))=0,"",SUM('Model inputs'!B235,'Model inputs'!B236,'Model inputs'!B237))="",0,IF(SUM(IF(IF('Model inputs'!B235="",0,1)="",0,IF('Model inputs'!B235="",0,1)),IF(IF('Model inputs'!B236="",0,1)="",0,IF('Model inputs'!B236="",0,1)),IF(IF('Model inputs'!B237="",0,1)="",0,IF('Model inputs'!B237="",0,1)))=0,"",SUM('Model inputs'!B235,'Model inputs'!B236,'Model inputs'!B237))),"") | J34: =IFERROR(IF('RC Unit economics'!J30="",0,'RC Unit economics'!J30)/IF(IF(SUM(IF(IF('Model inputs'!B235="",0,1)="",0,IF('Model inputs'!B235="",0,1)),IF(IF('Model inputs'!B236="",0,1)="",0,IF('Model inputs'!B236="",0,1)),IF(IF('Model inputs'!B237="",0,1)="",0,IF('Model inputs'!B237="",0,1)))=0,"",SUM('Model inputs'!B235,'Model inputs'!B236,'Model inputs'!B237))="",0,IF(SUM(IF(IF('Model inputs'!B235="",0,1)="",0,IF('Model inputs'!B235="",0,1)),IF(IF('Model inputs'!B236="",0,1)="",0,IF('Model inputs'!B236="",0,1)),IF(IF('Model inputs'!B237="",0,1)="",0,IF('Model inputs'!B237="",0,1)))=0,"",SUM('Model inputs'!B235,'Model inputs'!B236,'Model inputs'!B237))),"") | K34: =IFERROR(IF('RC Unit economics'!K30="",0,'RC Unit economics'!K30)/IF(IF(SUM(IF(IF('Model inputs'!B235="",0,1)="",0,IF('Model inputs'!B235="",0,1)),IF(IF('Model inputs'!B236="",0,1)="",0,IF('Model inputs'!B236="",0,1)),IF(IF('Model inputs'!B237="",0,1)="",0,IF('Model inputs'!B237="",0,1)))=0,"",SUM('Model inputs'!B235,'Model inputs'!B236,'Model inputs'!B237))="",0,IF(SUM(IF(IF('Model inputs'!B235="",0,1)="",0,IF('Model inputs'!B235="",0,1)),IF(IF('Model inputs'!B236="",0,1)="",0,IF('Model inputs'!B236="",0,1)),IF(IF('Model inputs'!B237="",0,1)="",0,IF('Model inputs'!B237="",0,1)))=0,"",SUM('Model inputs'!B235,'Model inputs'!B236,'Model inputs'!B237))),"") | L34: =IFERROR(IF('RC Unit economics'!L30="",0,'RC Unit economics'!L30)/IF(IF(SUM(IF(IF('Model inputs'!B235="",0,1)="",0,IF('Model inputs'!B235="",0,1)),IF(IF('Model inputs'!B236="",0,1)="",0,IF('Model inputs'!B236="",0,1)),IF(IF('Model inputs'!B237="",0,1)="",0,IF('Model inputs'!B237="",0,1)))=0,"",SUM('Model inputs'!B235,'Model inputs'!B236,'Model inputs'!B237))="",0,IF(SUM(IF(IF('Model inputs'!B235="",0,1)="",0,IF('Model inputs'!B235="",0,1)),IF(IF('Model inputs'!B236="",0,1)="",0,IF('Model inputs'!B236="",0,1)),IF(IF('Model inputs'!B237="",0,1)="",0,IF('Model inputs'!B237="",0,1)))=0,"",SUM('Model inputs'!B235,'Model inputs'!B236,'Model inputs'!B237))),"") | M34: =IFERROR(IF('RC Unit economics'!M30="",0,'RC Unit economics'!M30)/IF(IF(SUM(IF(IF('Model inputs'!B235="",0,1)="",0,IF('Model inputs'!B235="",0,1)),IF(IF('Model inputs'!B236="",0,1)="",0,IF('Model inputs'!B236="",0,1)),IF(IF('Model inputs'!B237="",0,1)="",0,IF('Model inputs'!B237="",0,1)))=0,"",SUM('Model inputs'!B235,'Model inputs'!B236,'Model inputs'!B237))="",0,IF(SUM(IF(IF('Model inputs'!B235="",0,1)="",0,IF('Model inputs'!B235="",0,1)),IF(IF('Model inputs'!B236="",0,1)="",0,IF('Model inputs'!B236="",0,1)),IF(IF('Model inputs'!B237="",0,1)="",0,IF('Model inputs'!B237="",0,1)))=0,"",SUM('Model inputs'!B235,'Model inputs'!B236,'Model inputs'!B237))),"") | N34: =IFERROR(IF('RC Unit economics'!N30="",0,'RC Unit economics'!N30)/IF(IF(SUM(IF(IF('Model inputs'!B235="",0,1)="",0,IF('Model inputs'!B235="",0,1)),IF(IF('Model inputs'!B236="",0,1)="",0,IF('Model inputs'!B236="",0,1)),IF(IF('Model inputs'!B237="",0,1)="",0,IF('Model inputs'!B237="",0,1)))=0,"",SUM('Model inputs'!B235,'Model inputs'!B236,'Model inputs'!B237))="",0,IF(SUM(IF(IF('Model inputs'!B235="",0,1)="",0,IF('Model inputs'!B235="",0,1)),IF(IF('Model inputs'!B236="",0,1)="",0,IF('Model inputs'!B236="",0,1)),IF(IF('Model inputs'!B237="",0,1)="",0,IF('Model inputs'!B237="",0,1)))=0,"",SUM('Model inputs'!B235,'Model inputs'!B236,'Model inputs'!B237))),"") | O34: =IFERROR(IF('RC Unit economics'!O30="",0,'RC Unit economics'!O30)/IF(IF(SUM(IF(IF('Model inputs'!B235="",0,1)="",0,IF('Model inputs'!B235="",0,1)),IF(IF('Model inputs'!B236="",0,1)="",0,IF('Model inputs'!B236="",0,1)),IF(IF('Model inputs'!B237="",0,1)="",0,IF('Model inputs'!B237="",0,1)))=0,"",SUM('Model inputs'!B235,'Model inputs'!B236,'Model inputs'!B237))="",0,IF(SUM(IF(IF('Model inputs'!B235="",0,1)="",0,IF('Model inputs'!B235="",0,1)),IF(IF('Model inputs'!B236="",0,1)="",0,IF('Model inputs'!B236="",0,1)),IF(IF('Model inputs'!B237="",0,1)="",0,IF('Model inputs'!B237="",0,1)))=0,"",SUM('Model inputs'!B235,'Model inputs'!B236,'Model inputs'!B237))),"") | P34: =IFERROR(IF('RC Unit economics'!P30="",0,'RC Unit economics'!P30)/IF(IF(SUM(IF(IF('Model inputs'!B235="",0,1)="",0,IF('Model inputs'!B235="",0,1)),IF(IF('Model inputs'!B236="",0,1)="",0,IF('Model inputs'!B236="",0,1)),IF(IF('Model inputs'!B237="",0,1)="",0,IF('Model inputs'!B237="",0,1)))=0,"",SUM('Model inputs'!B235,'Model inputs'!B236,'Model inputs'!B237))="",0,IF(SUM(IF(IF('Model inputs'!B235="",0,1)="",0,IF('Model inputs'!B235="",0,1)),IF(IF('Model inputs'!B236="",0,1)="",0,IF('Model inputs'!B236="",0,1)),IF(IF('Model inputs'!B237="",0,1)="",0,IF('Model inputs'!B237="",0,1)))=0,"",SUM('Model inputs'!B235,'Model inputs'!B236,'Model inputs'!B237))),"") | Q34: =IFERROR(IF('RC Unit economics'!Q30="",0,'RC Unit economics'!Q30)/IF(IF(SUM(IF(IF('Model inputs'!B235="",0,1)="",0,IF('Model inputs'!B235="",0,1)),IF(IF('Model inputs'!B236="",0,1)="",0,IF('Model inputs'!B236="",0,1)),IF(IF('Model inputs'!B237="",0,1)="",0,IF('Model inputs'!B237="",0,1)))=0,"",SUM('Model inputs'!B235,'Model inputs'!B236,'Model inputs'!B237))="",0,IF(SUM(IF(IF('Model inputs'!B235="",0,1)="",0,IF('Model inputs'!B235="",0,1)),IF(IF('Model inputs'!B236="",0,1)="",0,IF('Model inputs'!B236="",0,1)),IF(IF('Model inputs'!B237="",0,1)="",0,IF('Model inputs'!B237="",0,1)))=0,"",SUM('Model inputs'!B235,'Model inputs'!B236,'Model inputs'!B237))),"") | R34: =IFERROR(IF('RC Unit economics'!R30="",0,'RC Unit economics'!R30)/IF(IF(SUM(IF(IF('Model inputs'!B235="",0,1)="",0,IF('Model inputs'!B235="",0,1)),IF(IF('Model inputs'!B236="",0,1)="",0,IF('Model inputs'!B236="",0,1)),IF(IF('Model inputs'!B237="",0,1)="",0,IF('Model inputs'!B237="",0,1)))=0,"",SUM('Model inputs'!B235,'Model inputs'!B236,'Model inputs'!B237))="",0,IF(SUM(IF(IF('Model inputs'!B235="",0,1)="",0,IF('Model inputs'!B235="",0,1)),IF(IF('Model inputs'!B236="",0,1)="",0,IF('Model inputs'!B236="",0,1)),IF(IF('Model inputs'!B237="",0,1)="",0,IF('Model inputs'!B237="",0,1)))=0,"",SUM('Model inputs'!B235,'Model inputs'!B236,'Model inputs'!B237))),"") | S34: =IFERROR(IF('RC Unit economics'!S30="",0,'RC Unit economics'!S30)/IF(IF(SUM(IF(IF('Model inputs'!B235="",0,1)="",0,IF('Model inputs'!B235="",0,1)),IF(IF('Model inputs'!B236="",0,1)="",0,IF('Model inputs'!B236="",0,1)),IF(IF('Model inputs'!B237="",0,1)="",0,IF('Model inputs'!B237="",0,1)))=0,"",SUM('Model inputs'!B235,'Model inputs'!B236,'Model inputs'!B237))="",0,IF(SUM(IF(IF('Model inputs'!B235="",0,1)="",0,IF('Model inputs'!B235="",0,1)),IF(IF('Model inputs'!B236="",0,1)="",0,IF('Model inputs'!B236="",0,1)),IF(IF('Model inputs'!B237="",0,1)="",0,IF('Model inputs'!B237="",0,1)))=0,"",SUM('Model inputs'!B235,'Model inputs'!B236,'Model inputs'!B237))),"")
A35: Indie | B35: =IFERROR('RC Unit economics'!B31/'Model inputs'!B7,"") -> 8.8720304 | C35: =IFERROR('RC Unit economics'!C31/'Model inputs'!B7,"") -> 8.8720304 | D35: =IFERROR('RC Unit economics'!D31/'Model inputs'!B7,"") -> 8.8720304 | E35: =IFERROR('RC Unit economics'!E31/'Model inputs'!B7,"") -> 8.8720304 | F35: =IFERROR('RC Unit economics'!F31/'Model inputs'!B7,"") -> 8.8720304 | G35: =IFERROR('RC Unit economics'!G31/'Model inputs'!B7,"") -> 8.8720304 | H35: =IFERROR('RC Unit economics'!H31/'Model inputs'!B7,"") -> 8.8720304 | I35: =IFERROR('RC Unit economics'!I31/'Model inputs'!B7,"") -> 8.8720304 | J35: =IFERROR('RC Unit economics'!J31/'Model inputs'!B7,"") -> 8.8720304 | K35: =IFERROR('RC Unit economics'!K31/'Model inputs'!B7,"") -> 8.8720304 | L35: =IFERROR('RC Unit economics'!L31/'Model inputs'!B7,"") -> 8.8720304 | M35: =IFERROR('RC Unit economics'!M31/'Model inputs'!B7,"") -> 8.8720304 | N35: =IFERROR('RC Unit economics'!N31/'Model inputs'!B7,"") -> 8.8720304 | O35: =IFERROR('RC Unit economics'!O31/'Model inputs'!B7,"") -> 8.8720304 | P35: =IFERROR('RC Unit economics'!P31/'Model inputs'!B7,"") -> 8.8720304 | Q35: =IFERROR('RC Unit economics'!Q31/'Model inputs'!B7,"") -> 8.8720304 | R35: =IFERROR('RC Unit economics'!R31/'Model inputs'!B7,"") -> 8.8720304 | S35: =IFERROR('RC Unit economics'!S31/'Model inputs'!B7,"") -> 8.8720304
A36: Launch | B36: =IFERROR('RC Unit economics'!B32/'Model inputs'!B8,"") -> 10.396694 | C36: =IFERROR('RC Unit economics'!C32/'Model inputs'!B8,"") -> 10.116162 | D36: =IFERROR('RC Unit economics'!D32/'Model inputs'!B8,"") -> 9.9756339 | E36: =IFERROR('RC Unit economics'!E32/'Model inputs'!B8,"") -> 9.8536761 | F36: =IFERROR('RC Unit economics'!F32/'Model inputs'!B8,"") -> 9.7408182 | G36: =IFERROR('RC Unit economics'!G32/'Model inputs'!B8,"") -> 9.6330057 | H36: =IFERROR('RC Unit economics'!H32/'Model inputs'!B8,"") -> 9.5282078 | I36: =IFERROR('RC Unit economics'!I32/'Model inputs'!B8,"") -> 9.705823 | J36: =IFERROR('RC Unit economics'!J32/'Model inputs'!B8,"") -> 9.7173289 | K36: =IFERROR('RC Unit economics'!K32/'Model inputs'!B8,"") -> 9.7265228 | L36: =IFERROR('RC Unit economics'!L32/'Model inputs'!B8,"") -> 9.7342036 | M36: =IFERROR('RC Unit economics'!M32/'Model inputs'!B8,"") -> 9.7407143 | N36: =IFERROR('RC Unit economics'!N32/'Model inputs'!B8,"") -> 9.7463018 | O36: =IFERROR('RC Unit economics'!O32/'Model inputs'!B8,"") -> 9.7227888 | P36: =IFERROR('RC Unit economics'!P32/'Model inputs'!B8,"") -> 9.7108756 | Q36: =IFERROR('RC Unit economics'!Q32/'Model inputs'!B8,"") -> 9.7002663 | R36: =IFERROR('RC Unit economics'!R32/'Model inputs'!B8,"") -> 9.6906809 | S36: =IFERROR('RC Unit economics'!S32/'Model inputs'!B8,"") -> 9.6818941
A37: Team | B37: =IFERROR('RC Unit economics'!B33/'Model inputs'!B9,"") -> 11.054631 | C37: =IFERROR('RC Unit economics'!C33/'Model inputs'!B9,"") -> 10.762564 | D37: =IFERROR('RC Unit economics'!D33/'Model inputs'!B9,"") -> 10.610197 | E37: =IFERROR('RC Unit economics'!E33/'Model inputs'!B9,"") -> 10.474589 | F37: =IFERROR('RC Unit economics'!F33/'Model inputs'!B9,"") -> 10.347715 | G37: =IFERROR('RC Unit economics'!G33/'Model inputs'!B9,"") -> 10.22595 | H37: =IFERROR('RC Unit economics'!H33/'Model inputs'!B9,"") -> 10.107401 | I37: =IFERROR('RC Unit economics'!I33/'Model inputs'!B9,"") -> 10.283045 | J37: =IFERROR('RC Unit economics'!J33/'Model inputs'!B9,"") -> 10.29472 | K37: =IFERROR('RC Unit economics'!K33/'Model inputs'!B9,"") -> 10.311507 | L37: =IFERROR('RC Unit economics'!L33/'Model inputs'!B9,"") -> 10.324944 | M37: =IFERROR('RC Unit economics'!M33/'Model inputs'!B9,"") -> 10.335941 | N37: =IFERROR('RC Unit economics'!N33/'Model inputs'!B9,"") -> 10.345103 | O37: =IFERROR('RC Unit economics'!O33/'Model inputs'!B9,"") -> 10.336274 | P37: =IFERROR('RC Unit economics'!P33/'Model inputs'!B9,"") -> 10.33231 | Q37: =IFERROR('RC Unit economics'!Q33/'Model inputs'!B9,"") -> 10.327315 | R37: =IFERROR('RC Unit economics'!R33/'Model inputs'!B9,"") -> 10.321377 | S37: =IFERROR('RC Unit economics'!S33/'Model inputs'!B9,"") -> 10.314545
A38: CAC payback (months) | B38: =IFERROR(IF(IF(SUM(IF(IF('Model inputs'!B235="",0,1)="",0,IF('Model inputs'!B235="",0,1)),IF(IF('Model inputs'!B236="",0,1)="",0,IF('Model inputs'!B236="",0,1)),IF(IF('Model inputs'!B237="",0,1)="",0,IF('Model inputs'!B237="",0,1)))=0,"",SUM('Model inputs'!B235,'Model inputs'!B236,'Model inputs'!B237))="",0,IF(SUM(IF(IF('Model inputs'!B235="",0,1)="",0,IF('Model inputs'!B235="",0,1)),IF(IF('Model inputs'!B236="",0,1)="",0,IF('Model inputs'!B236="",0,1)),IF(IF('Model inputs'!B237="",0,1)="",0,IF('Model inputs'!B237="",0,1)))=0,"",SUM('Model inputs'!B235,'Model inputs'!B236,'Model inputs'!B237)))/'RC Unit economics'!B22,"") -> 0 | C38: =IFERROR(IF(IF(SUM(IF(IF('Model inputs'!B235="",0,1)="",0,IF('Model inputs'!B235="",0,1)),IF(IF('Model inputs'!B236="",0,1)="",0,IF('Model inputs'!B236="",0,1)),IF(IF('Model inputs'!B237="",0,1)="",0,IF('Model inputs'!B237="",0,1)))=0,"",SUM('Model inputs'!B235,'Model inputs'!B236,'Model inputs'!B237))="",0,IF(SUM(IF(IF('Model inputs'!B235="",0,1)="",0,IF('Model inputs'!B235="",0,1)),IF(IF('Model inputs'!B236="",0,1)="",0,IF('Model inputs'!B236="",0,1)),IF(IF('Model inputs'!B237="",0,1)="",0,IF('Model inputs'!B237="",0,1)))=0,"",SUM('Model inputs'!B235,'Model inputs'!B236,'Model inputs'!B237)))/'RC Unit economics'!C22,"") -> 0 | D38: =IFERROR(IF(IF(SUM(IF(IF('Model inputs'!B235="",0,1)="",0,IF('Model inputs'!B235="",0,1)),IF(IF('Model inputs'!B236="",0,1)="",0,IF('Model inputs'!B236="",0,1)),IF(IF('Model inputs'!B237="",0,1)="",0,IF('Model inputs'!B237="",0,1)))=0,"",SUM('Model inputs'!B235,'Model inputs'!B236,'Model inputs'!B237))="",0,IF(SUM(IF(IF('Model inputs'!B235="",0,1)="",0,IF('Model inputs'!B235="",0,1)),IF(IF('Model inputs'!B236="",0,1)="",0,IF('Model inputs'!B236="",0,1)),IF(IF('Model inputs'!B237="",0,1)="",0,IF('Model inputs'!B237="",0,1)))=0,"",SUM('Model inputs'!B235,'Model inputs'!B236,'Model inputs'!B237)))/'RC Unit economics'!D22,"") -> 0 | E38: =IFERROR(IF(IF(SUM(IF(IF('Model inputs'!B235="",0,1)="",0,IF('Model inputs'!B235="",0,1)),IF(IF('Model inputs'!B236="",0,1)="",0,IF('Model inputs'!B236="",0,1)),IF(IF('Model inputs'!B237="",0,1)="",0,IF('Model inputs'!B237="",0,1)))=0,"",SUM('Model inputs'!B235,'Model inputs'!B236,'Model inputs'!B237))="",0,IF(SUM(IF(IF('Model inputs'!B235="",0,1)="",0,IF('Model inputs'!B235="",0,1)),IF(IF('Model inputs'!B236="",0,1)="",0,IF('Model inputs'!B236="",0,1)),IF(IF('Model inputs'!B237="",0,1)="",0,IF('Model inputs'!B237="",0,1)))=0,"",SUM('Model inputs'!B235,'Model inputs'!B236,'Model inputs'!B237)))/'RC Unit economics'!E22,"") -> 0 | F38: =IFERROR(IF(IF(SUM(IF(IF('Model inputs'!B235="",0,1)="",0,IF('Model inputs'!B235="",0,1)),IF(IF('Model inputs'!B236="",0,1)="",0,IF('Model inputs'!B236="",0,1)),IF(IF('Model inputs'!B237="",0,1)="",0,IF('Model inputs'!B237="",0,1)))=0,"",SUM('Model inputs'!B235,'Model inputs'!B236,'Model inputs'!B237))="",0,IF(SUM(IF(IF('Model inputs'!B235="",0,1)="",0,IF('Model inputs'!B235="",0,1)),IF(IF('Model inputs'!B236="",0,1)="",0,IF('Model inputs'!B236="",0,1)),IF(IF('Model inputs'!B237="",0,1)="",0,IF('Model inputs'!B237="",0,1)))=0,"",SUM('Model inputs'!B235,'Model inputs'!B236,'Model inputs'!B237)))/'RC Unit economics'!F22,"") -> 0 | G38: =IFERROR(IF(IF(SUM(IF(IF('Model inputs'!B235="",0,1)="",0,IF('Model inputs'!B235="",0,1)),IF(IF('Model inputs'!B236="",0,1)="",0,IF('Model inputs'!B236="",0,1)),IF(IF('Model inputs'!B237="",0,1)="",0,IF('Model inputs'!B237="",0,1)))=0,"",SUM('Model inputs'!B235,'Model inputs'!B236,'Model inputs'!B237))="",0,IF(SUM(IF(IF('Model inputs'!B235="",0,1)="",0,IF('Model inputs'!B235="",0,1)),IF(IF('Model inputs'!B236="",0,1)="",0,IF('Model inputs'!B236="",0,1)),IF(IF('Model inputs'!B237="",0,1)="",0,IF('Model inputs'!B237="",0,1)))=0,"",SUM('Model inputs'!B235,'Model inputs'!B236,'Model inputs'!B237)))/'RC Unit economics'!G22,"") -> 0 | H38: =IFERROR(IF(IF(SUM(IF(IF('Model inputs'!B235="",0,1)="",0,IF('Model inputs'!B235="",0,1)),IF(IF('Model inputs'!B236="",0,1)="",0,IF('Model inputs'!B236="",0,1)),IF(IF('Model inputs'!B237="",0,1)="",0,IF('Model inputs'!B237="",0,1)))=0,"",SUM('Model inputs'!B235,'Model inputs'!B236,'Model inputs'!B237))="",0,IF(SUM(IF(IF('Model inputs'!B235="",0,1)="",0,IF('Model inputs'!B235="",0,1)),IF(IF('Model inputs'!B236="",0,1)="",0,IF('Model inputs'!B236="",0,1)),IF(IF('Model inputs'!B237="",0,1)="",0,IF('Model inputs'!B237="",0,1)))=0,"",SUM('Model inputs'!B235,'Model inputs'!B236,'Model inputs'!B237)))/'RC Unit economics'!H22,"") -> 0 | I38: =IFERROR(IF(IF(SUM(IF(IF('Model inputs'!B235="",0,1)="",0,IF('Model inputs'!B235="",0,1)),IF(IF('Model inputs'!B236="",0,1)="",0,IF('Model inputs'!B236="",0,1)),IF(IF('Model inputs'!B237="",0,1)="",0,IF('Model inputs'!B237="",0,1)))=0,"",SUM('Model inputs'!B235,'Model inputs'!B236,'Model inputs'!B237))="",0,IF(SUM(IF(IF('Model inputs'!B235="",0,1)="",0,IF('Model inputs'!B235="",0,1)),IF(IF('Model inputs'!B236="",0,1)="",0,IF('Model inputs'!B236="",0,1)),IF(IF('Model inputs'!B237="",0,1)="",0,IF('Model inputs'!B237="",0,1)))=0,"",SUM('Model inputs'!B235,'Model inputs'!B236,'Model inputs'!B237)))/'RC Unit economics'!I22,"") -> 0 | J38: =IFERROR(IF(IF(SUM(IF(IF('Model inputs'!B235="",0,1)="",0,IF('Model inputs'!B235="",0,1)),IF(IF('Model inputs'!B236="",0,1)="",0,IF('Model inputs'!B236="",0,1)),IF(IF('Model inputs'!B237="",0,1)="",0,IF('Model inputs'!B237="",0,1)))=0,"",SUM('Model inputs'!B235,'Model inputs'!B236,'Model inputs'!B237))="",0,IF(SUM(IF(IF('Model inputs'!B235="",0,1)="",0,IF('Model inputs'!B235="",0,1)),IF(IF('Model inputs'!B236="",0,1)="",0,IF('Model inputs'!B236="",0,1)),IF(IF('Model inputs'!B237="",0,1)="",0,IF('Model inputs'!B237="",0,1)))=0,"",SUM('Model inputs'!B235,'Model inputs'!B236,'Model inputs'!B237)))/'RC Unit economics'!J22,"") -> 0 | K38: =IFERROR(IF(IF(SUM(IF(IF('Model inputs'!B235="",0,1)="",0,IF('Model inputs'!B235="",0,1)),IF(IF('Model inputs'!B236="",0,1)="",0,IF('Model inputs'!B236="",0,1)),IF(IF('Model inputs'!B237="",0,1)="",0,IF('Model inputs'!B237="",0,1)))=0,"",SUM('Model inputs'!B235,'Model inputs'!B236,'Model inputs'!B237))="",0,IF(SUM(IF(IF('Model inputs'!B235="",0,1)="",0,IF('Model inputs'!B235="",0,1)),IF(IF('Model inputs'!B236="",0,1)="",0,IF('Model inputs'!B236="",0,1)),IF(IF('Model inputs'!B237="",0,1)="",0,IF('Model inputs'!B237="",0,1)))=0,"",SUM('Model inputs'!B235,'Model inputs'!B236,'Model inputs'!B237)))/'RC Unit economics'!K22,"") -> 0 | L38: =IFERROR(IF(IF(SUM(IF(IF('Model inputs'!B235="",0,1)="",0,IF('Model inputs'!B235="",0,1)),IF(IF('Model inputs'!B236="",0,1)="",0,IF('Model inputs'!B236="",0,1)),IF(IF('Model inputs'!B237="",0,1)="",0,IF('Model inputs'!B237="",0,1)))=0,"",SUM('Model inputs'!B235,'Model inputs'!B236,'Model inputs'!B237))="",0,IF(SUM(IF(IF('Model inputs'!B235="",0,1)="",0,IF('Model inputs'!B235="",0,1)),IF(IF('Model inputs'!B236="",0,1)="",0,IF('Model inputs'!B236="",0,1)),IF(IF('Model inputs'!B237="",0,1)="",0,IF('Model inputs'!B237="",0,1)))=0,"",SUM('Model inputs'!B235,'Model inputs'!B236,'Model inputs'!B237)))/'RC Unit economics'!L22,"") -> 0 | M38: =IFERROR(IF(IF(SUM(IF(IF('Model inputs'!B235="",0,1)="",0,IF('Model inputs'!B235="",0,1)),IF(IF('Model inputs'!B236="",0,1)="",0,IF('Model inputs'!B236="",0,1)),IF(IF('Model inputs'!B237="",0,1)="",0,IF('Model inputs'!B237="",0,1)))=0,"",SUM('Model inputs'!B235,'Model inputs'!B236,'Model inputs'!B237))="",0,IF(SUM(IF(IF('Model inputs'!B235="",0,1)="",0,IF('Model inputs'!B235="",0,1)),IF(IF('Model inputs'!B236="",0,1)="",0,IF('Model inputs'!B236="",0,1)),IF(IF('Model inputs'!B237="",0,1)="",0,IF('Model inputs'!B237="",0,1)))=0,"",SUM('Model inputs'!B235,'Model inputs'!B236,'Model inputs'!B237)))/'RC Unit economics'!M22,"") -> 0 | N38: =IFERROR(IF(IF(SUM(IF(IF('Model inputs'!B235="",0,1)="",0,IF('Model inputs'!B235="",0,1)),IF(IF('Model inputs'!B236="",0,1)="",0,IF('Model inputs'!B236="",0,1)),IF(IF('Model inputs'!B237="",0,1)="",0,IF('Model inputs'!B237="",0,1)))=0,"",SUM('Model inputs'!B235,'Model inputs'!B236,'Model inputs'!B237))="",0,IF(SUM(IF(IF('Model inputs'!B235="",0,1)="",0,IF('Model inputs'!B235="",0,1)),IF(IF('Model inputs'!B236="",0,1)="",0,IF('Model inputs'!B236="",0,1)),IF(IF('Model inputs'!B237="",0,1)="",0,IF('Model inputs'!B237="",0,1)))=0,"",SUM('Model inputs'!B235,'Model inputs'!B236,'Model inputs'!B237)))/'RC Unit economics'!N22,"") -> 0 | O38: =IFERROR(IF(IF(SUM(IF(IF('Model inputs'!B235="",0,1)="",0,IF('Model inputs'!B235="",0,1)),IF(IF('Model inputs'!B236="",0,1)="",0,IF('Model inputs'!B236="",0,1)),IF(IF('Model inputs'!B237="",0,1)="",0,IF('Model inputs'!B237="",0,1)))=0,"",SUM('Model inputs'!B235,'Model inputs'!B236,'Model inputs'!B237))="",0,IF(SUM(IF(IF('Model inputs'!B235="",0,1)="",0,IF('Model inputs'!B235="",0,1)),IF(IF('Model inputs'!B236="",0,1)="",0,IF('Model inputs'!B236="",0,1)),IF(IF('Model inputs'!B237="",0,1)="",0,IF('Model inputs'!B237="",0,1)))=0,"",SUM('Model inputs'!B235,'Model inputs'!B236,'Model inputs'!B237)))/'RC Unit economics'!O22,"") -> 0 | P38: =IFERROR(IF(IF(SUM(IF(IF('Model inputs'!B235="",0,1)="",0,IF('Model inputs'!B235="",0,1)),IF(IF('Model inputs'!B236="",0,1)="",0,IF('Model inputs'!B236="",0,1)),IF(IF('Model inputs'!B237="",0,1)="",0,IF('Model inputs'!B237="",0,1)))=0,"",SUM('Model inputs'!B235,'Model inputs'!B236,'Model inputs'!B237))="",0,IF(SUM(IF(IF('Model inputs'!B235="",0,1)="",0,IF('Model inputs'!B235="",0,1)),IF(IF('Model inputs'!B236="",0,1)="",0,IF('Model inputs'!B236="",0,1)),IF(IF('Model inputs'!B237="",0,1)="",0,IF('Model inputs'!B237="",0,1)))=0,"",SUM('Model inputs'!B235,'Model inputs'!B236,'Model inputs'!B237)))/'RC Unit economics'!P22,"") -> 0 | Q38: =IFERROR(IF(IF(SUM(IF(IF('Model inputs'!B235="",0,1)="",0,IF('Model inputs'!B235="",0,1)),IF(IF('Model inputs'!B236="",0,1)="",0,IF('Model inputs'!B236="",0,1)),IF(IF('Model inputs'!B237="",0,1)="",0,IF('Model inputs'!B237="",0,1)))=0,"",SUM('Model inputs'!B235,'Model inputs'!B236,'Model inputs'!B237))="",0,IF(SUM(IF(IF('Model inputs'!B235="",0,1)="",0,IF('Model inputs'!B235="",0,1)),IF(IF('Model inputs'!B236="",0,1)="",0,IF('Model inputs'!B236="",0,1)),IF(IF('Model inputs'!B237="",0,1)="",0,IF('Model inputs'!B237="",0,1)))=0,"",SUM('Model inputs'!B235,'Model inputs'!B236,'Model inputs'!B237)))/'RC Unit economics'!Q22,"") -> 0 | R38: =IFERROR(IF(IF(SUM(IF(IF('Model inputs'!B235="",0,1)="",0,IF('Model inputs'!B235="",0,1)),IF(IF('Model inputs'!B236="",0,1)="",0,IF('Model inputs'!B236="",0,1)),IF(IF('Model inputs'!B237="",0,1)="",0,IF('Model inputs'!B237="",0,1)))=0,"",SUM('Model inputs'!B235,'Model inputs'!B236,'Model inputs'!B237))="",0,IF(SUM(IF(IF('Model inputs'!B235="",0,1)="",0,IF('Model inputs'!B235="",0,1)),IF(IF('Model inputs'!B236="",0,1)="",0,IF('Model inputs'!B236="",0,1)),IF(IF('Model inputs'!B237="",0,1)="",0,IF('Model inputs'!B237="",0,1)))=0,"",SUM('Model inputs'!B235,'Model inputs'!B236,'Model inputs'!B237)))/'RC Unit economics'!R22,"") -> 0 | S38: =IFERROR(IF(IF(SUM(IF(IF('Model inputs'!B235="",0,1)="",0,IF('Model inputs'!B235="",0,1)),IF(IF('Model inputs'!B236="",0,1)="",0,IF('Model inputs'!B236="",0,1)),IF(IF('Model inputs'!B237="",0,1)="",0,IF('Model inputs'!B237="",0,1)))=0,"",SUM('Model inputs'!B235,'Model inputs'!B236,'Model inputs'!B237))="",0,IF(SUM(IF(IF('Model inputs'!B235="",0,1)="",0,IF('Model inputs'!B235="",0,1)),IF(IF('Model inputs'!B236="",0,1)="",0,IF('Model inputs'!B236="",0,1)),IF(IF('Model inputs'!B237="",0,1)="",0,IF('Model inputs'!B237="",0,1)))=0,"",SUM('Model inputs'!B235,'Model inputs'!B236,'Model inputs'!B237)))/'RC Unit economics'!S22,"") -> 0
A39: Indie | B39: =IFERROR('Model inputs'!B7/'RC Unit economics'!B23,"") -> 1.4530681 | C39: =IFERROR('Model inputs'!B7/'RC Unit economics'!C23,"") -> 1.4530681 | D39: =IFERROR('Model inputs'!B7/'RC Unit economics'!D23,"") -> 1.4530681 | E39: =IFERROR('Model inputs'!B7/'RC Unit economics'!E23,"") -> 1.4530681 | F39: =IFERROR('Model inputs'!B7/'RC Unit economics'!F23,"") -> 1.4530681 | G39: =IFERROR('Model inputs'!B7/'RC Unit economics'!G23,"") -> 1.4530681 | H39: =IFERROR('Model inputs'!B7/'RC Unit economics'!H23,"") -> 1.4530681 | I39: =IFERROR('Model inputs'!B7/'RC Unit economics'!I23,"") -> 1.4530681 | J39: =IFERROR('Model inputs'!B7/'RC Unit economics'!J23,"") -> 1.4530681 | K39: =IFERROR('Model inputs'!B7/'RC Unit economics'!K23,"") -> 1.4530681 | L39: =IFERROR('Model inputs'!B7/'RC Unit economics'!L23,"") -> 1.4530681 | M39: =IFERROR('Model inputs'!B7/'RC Unit economics'!M23,"") -> 1.4530681 | N39: =IFERROR('Model inputs'!B7/'RC Unit economics'!N23,"") -> 1.4530681 | O39: =IFERROR('Model inputs'!B7/'RC Unit economics'!O23,"") -> 1.4530681 | P39: =IFERROR('Model inputs'!B7/'RC Unit economics'!P23,"") -> 1.4530681 | Q39: =IFERROR('Model inputs'!B7/'RC Unit economics'!Q23,"") -> 1.4530681 | R39: =IFERROR('Model inputs'!B7/'RC Unit economics'!R23,"") -> 1.4530681 | S39: =IFERROR('Model inputs'!B7/'RC Unit economics'!S23,"") -> 1.4530681
A40: Launch | B40: =IFERROR('Model inputs'!B8/'RC Unit economics'!B24,"") -> 1.9507731 | C40: =IFERROR('Model inputs'!B8/'RC Unit economics'!C24,"") -> 2.0048701 | D40: =IFERROR('Model inputs'!B8/'RC Unit economics'!D24,"") -> 2.033113 | E40: =IFERROR('Model inputs'!B8/'RC Unit economics'!E24,"") -> 2.0582766 | F40: =IFERROR('Model inputs'!B8/'RC Unit economics'!F24,"") -> 2.0821239 | G40: =IFERROR('Model inputs'!B8/'RC Unit economics'!G24,"") -> 2.105427 | H40: =IFERROR('Model inputs'!B8/'RC Unit economics'!H24,"") -> 2.128584 | I40: =IFERROR('Model inputs'!B8/'RC Unit economics'!I24,"") -> 2.0896312 | J40: =IFERROR('Model inputs'!B8/'RC Unit economics'!J24,"") -> 2.087157 | K40: =IFERROR('Model inputs'!B8/'RC Unit economics'!K24,"") -> 2.0851841 | L40: =IFERROR('Model inputs'!B8/'RC Unit economics'!L24,"") -> 2.0835388 | M40: =IFERROR('Model inputs'!B8/'RC Unit economics'!M24,"") -> 2.0821461 | N40: =IFERROR('Model inputs'!B8/'RC Unit economics'!N24,"") -> 2.0809525 | O40: =IFERROR('Model inputs'!B8/'RC Unit economics'!O24,"") -> 2.0859849 | P40: =IFERROR('Model inputs'!B8/'RC Unit economics'!P24,"") -> 2.088544 | Q40: =IFERROR('Model inputs'!B8/'RC Unit economics'!Q24,"") -> 2.0908282 | R40: =IFERROR('Model inputs'!B8/'RC Unit economics'!R24,"") -> 2.0928963 | S40: =IFERROR('Model inputs'!B8/'RC Unit economics'!S24,"") -> 2.0947958
A41: Team | B41: =IFERROR('Model inputs'!B9/'RC Unit economics'!B25,"") -> 1.563697 | C41: =IFERROR('Model inputs'!B9/'RC Unit economics'!C25,"") -> 1.6061315 | D41: =IFERROR('Model inputs'!B9/'RC Unit economics'!D25,"") -> 1.6291962 | E41: =IFERROR('Model inputs'!B9/'RC Unit economics'!E25,"") -> 1.6502883 | F41: =IFERROR('Model inputs'!B9/'RC Unit economics'!F25,"") -> 1.6705226 | G41: =IFERROR('Model inputs'!B9/'RC Unit economics'!G25,"") -> 1.6904144 | H41: =IFERROR('Model inputs'!B9/'RC Unit economics'!H25,"") -> 1.7102411 | I41: =IFERROR('Model inputs'!B9/'RC Unit economics'!I25,"") -> 1.6810287 | J41: =IFERROR('Model inputs'!B9/'RC Unit economics'!J25,"") -> 1.6791221 | K41: =IFERROR('Model inputs'!B9/'RC Unit economics'!K25,"") -> 1.6763885 | L41: =IFERROR('Model inputs'!B9/'RC Unit economics'!L25,"") -> 1.6742069 | M41: =IFERROR('Model inputs'!B9/'RC Unit economics'!M25,"") -> 1.6724256 | N41: =IFERROR('Model inputs'!B9/'RC Unit economics'!N25,"") -> 1.6709444 | O41: =IFERROR('Model inputs'!B9/'RC Unit economics'!O25,"") -> 1.6723718 | P41: =IFERROR('Model inputs'!B9/'RC Unit economics'!P25,"") -> 1.6730134 | Q41: =IFERROR('Model inputs'!B9/'RC Unit economics'!Q25,"") -> 1.6738225 | R41: =IFERROR('Model inputs'!B9/'RC Unit economics'!R25,"") -> 1.6747856 | S41: =IFERROR('Model inputs'!B9/'RC Unit economics'!S25,"") -> 1.6758948
A42: Team logos to fund engineer | B42: =IFERROR('Model inputs'!B27/'RC Unit economics'!B25,"") -> 85.292563 | C42: =IFERROR('Model inputs'!B27/'RC Unit economics'!C25,"") -> 87.607174 | D42: =IFERROR('Model inputs'!B27/'RC Unit economics'!D25,"") -> 88.865245 | E42: =IFERROR('Model inputs'!B27/'RC Unit economics'!E25,"") -> 90.015728 | F42: =IFERROR('Model inputs'!B27/'RC Unit economics'!F25,"") -> 91.119417 | G42: =IFERROR('Model inputs'!B27/'RC Unit economics'!G25,"") -> 92.204423 | H42: =IFERROR('Model inputs'!B27/'RC Unit economics'!H25,"") -> 93.28588 | I42: =IFERROR('Model inputs'!B27/'RC Unit economics'!I25,"") -> 91.692472 | J42: =IFERROR('Model inputs'!B27/'RC Unit economics'!J25,"") -> 91.588479 | K42: =IFERROR('Model inputs'!B27/'RC Unit economics'!K25,"") -> 91.439375 | L42: =IFERROR('Model inputs'!B27/'RC Unit economics'!L25,"") -> 91.320376 | M42: =IFERROR('Model inputs'!B27/'RC Unit economics'!M25,"") -> 91.223216 | N42: =IFERROR('Model inputs'!B27/'RC Unit economics'!N25,"") -> 91.142422 | O42: =IFERROR('Model inputs'!B27/'RC Unit economics'!O25,"") -> 91.220278 | P42: =IFERROR('Model inputs'!B27/'RC Unit economics'!P25,"") -> 91.255277 | Q42: =IFERROR('Model inputs'!B27/'RC Unit economics'!Q25,"") -> 91.299411 | R42: =IFERROR('Model inputs'!B27/'RC Unit economics'!R25,"") -> 91.35194 | S42: =IFERROR('Model inputs'!B27/'RC Unit economics'!S25,"") -> 91.412442

Sheet Model inputs
A1: Model inputs
A2: Integration values are aggregated snapshots; raw source records are not included.
A4: Variables
A5: Variable / segment | B5: Value | C5: 2026-11 | D5: 2026-12 | E5: 2027-01 | F5: 2027-02 | G5: 2027-03 | H5: 2027-04 | I5: 2027-05 | J5: 2027-06 | K5: 2027-07 | L5: 2027-08 | M5: 2027-09 | N5: 2027-10 | O5: 2027-11 | P5: 2027-12 | Q5: 2028-01 | R5: 2028-02 | S5: 2028-03 | T5: 2028-04 | U5: 2025-10 | V5: 2025-11 | W5: 2025-12 | X5: 2026-01 | Y5: 2026-02 | Z5: 2026-03 | AA5: 2026-04 | AB5: 2026-05 | AC5: 2026-06 | AD5: 2026-07 | AE5: 2026-08 | AF5: 2026-09 | AG5: 2026-10
A6: CAC | B6: 0
A7: CAC > Indie | B7: =40 -> 40
A8: CAC > Launch | B8: =900 -> 900
A9: CAC > Team | B9: =220 -> 220
A10: Churned customers | C10: =SUM('Model inputs'!C11,'Model inputs'!C12,'Model inputs'!C13) -> 0 | D10: =SUM('Model inputs'!D11,'Model inputs'!D12,'Model inputs'!D13) -> 2.595 | E10: =SUM('Model inputs'!E11,'Model inputs'!E12,'Model inputs'!E13) -> 4.7545 | F10: =SUM('Model inputs'!F11,'Model inputs'!F12,'Model inputs'!F13) -> 6.1894717 | G10: =SUM('Model inputs'!G11,'Model inputs'!G12,'Model inputs'!G13) -> 7.6767034 | H10: =SUM('Model inputs'!H11,'Model inputs'!H12,'Model inputs'!H13) -> 9.2245838 | I10: =SUM('Model inputs'!I11,'Model inputs'!I12,'Model inputs'!I13) -> 10.841923 | J10: =SUM('Model inputs'!J11,'Model inputs'!J12,'Model inputs'!J13) -> 12.538007 | ... T10: =SUM('Model inputs'!T11,'Model inputs'!T12,'Model inputs'!T13) -> 31.54581
A11: Churned customers > Indie | C11: =IF(IF(IF(ISERROR('Model inputs'!C37<1),'Model inputs'!C37<1,IF('Model inputs'!C37="","",'Model inputs'!C37<1))="",FALSE,IF(ISERROR('Model inputs'!C37<1),'Model inputs'!C37<1,IF('Model inputs'!C37="","",'Model inputs'!C37<1))),0,'Model inputs'!C43*'Model inputs'!B39) -> 0 | D11: =IF(IF(IF(ISERROR('Model inputs'!D37<1),'Model inputs'!D37<1,IF('Model inputs'!D37="","",'Model inputs'!D37<1))="",FALSE,IF(ISERROR('Model inputs'!D37<1),'Model inputs'!D37<1,IF('Model inputs'!D37="","",'Model inputs'!D37<1))),0,'Model inputs'!D43*'Model inputs'!B39) -> 2.4 | E11: =IF(IF(IF(ISERROR('Model inputs'!E37<1),'Model inputs'!E37<1,IF('Model inputs'!E37="","",'Model inputs'!E37<1))="",FALSE,IF(ISERROR('Model inputs'!E37<1),'Model inputs'!E37<1,IF('Model inputs'!E37="","",'Model inputs'!E37<1))),0,'Model inputs'!E43*'Model inputs'!B39) -> 4.46 | F11: =IF(IF(IF(ISERROR('Model inputs'!F37<1),'Model inputs'!F37<1,IF('Model inputs'!F37="","",'Model inputs'!F37<1))="",FALSE,IF(ISERROR('Model inputs'!F37<1),'Model inputs'!F37<1,IF('Model inputs'!F37="","",'Model inputs'!F37<1))),0,'Model inputs'!F43*'Model inputs'!B39) -> 5.7826667 | G11: =IF(IF(IF(ISERROR('Model inputs'!G37<1),'Model inputs'!G37<1,IF('Model inputs'!G37="","",'Model inputs'!G37<1))="",FALSE,IF(ISERROR('Model inputs'!G37<1),'Model inputs'!G37<1,IF('Model inputs'!G37="","",'Model inputs'!G37<1))),0,'Model inputs'!G43*'Model inputs'!B39) -> 7.1467556 | H11: =IF(IF(IF(ISERROR('Model inputs'!H37<1),'Model inputs'!H37<1,IF('Model inputs'!H37="","",'Model inputs'!H37<1))="",FALSE,IF(ISERROR('Model inputs'!H37<1),'Model inputs'!H37<1,IF('Model inputs'!H37="","",'Model inputs'!H37<1))),0,'Model inputs'!H43*'Model inputs'!B39) -> 8.5598732 | I11: =IF(IF(IF(ISERROR('Model inputs'!I37<1),'Model inputs'!I37<1,IF('Model inputs'!I37="","",'Model inputs'!I37<1))="",FALSE,IF(ISERROR('Model inputs'!I37<1),'Model inputs'!I37<1,IF('Model inputs'!I37="","",'Model inputs'!I37<1))),0,'Model inputs'!I43*'Model inputs'!B39) -> 10.029948 | J11: =IF(IF(IF(ISERROR('Model inputs'!J37<1),'Model inputs'!J37<1,IF('Model inputs'!J37="","",'Model inputs'!J37<1))="",FALSE,IF(ISERROR('Model inputs'!J37<1),'Model inputs'!J37<1,IF('Model inputs'!J37="","",'Model inputs'!J37<1))),0,'Model inputs'!J43*'Model inputs'!B39) -> 11.565277 | K11: =IF(IF(IF(ISERROR('Model inputs'!K37<1),'Model inputs'!K37<1,IF('Model inputs'!K37="","",'Model inputs'!K37<1))="",FALSE,IF(ISERROR('Model inputs'!K37<1),'Model inputs'!K37<1,IF('Model inputs'!K37="","",'Model inputs'!K37<1))),0,'Model inputs'!K43*'Model inputs'!B39) -> 13.17457 | L11: =IF(IF(IF(ISERROR('Model inputs'!L37<1),'Model inputs'!L37<1,IF('Model inputs'!L37="","",'Model inputs'!L37<1))="",FALSE,IF(ISERROR('Model inputs'!L37<1),'Model inputs'!L37<1,IF('Model inputs'!L37="","",'Model inputs'!L37<1))),0,'Model inputs'!L43*'Model inputs'!B39) -> 14.867002 | M11: =IF(IF(IF(ISERROR('Model inputs'!M37<1),'Model inputs'!M37<1,IF('Model inputs'!M37="","",'Model inputs'!M37<1))="",FALSE,IF(ISERROR('Model inputs'!M37<1),'Model inputs'!M37<1,IF('Model inputs'!M37="","",'Model inputs'!M37<1))),0,'Model inputs'!M43*'Model inputs'!B39) -> 16.549434 | N11: =IF(IF(IF(ISERROR('Model inputs'!N37<1),'Model inputs'!N37<1,IF('Model inputs'!N37="","",'Model inputs'!N37<1))="",FALSE,IF(ISERROR('Model inputs'!N37<1),'Model inputs'!N37<1,IF('Model inputs'!N37="","",'Model inputs'!N37<1))),0,'Model inputs'!N43*'Model inputs'!B39) -> 18.226647 | O11: =IF(IF(IF(ISERROR('Model inputs'!O37<1),'Model inputs'!O37<1,IF('Model inputs'!O37="","",'Model inputs'!O37<1))="",FALSE,IF(ISERROR('Model inputs'!O37<1),'Model inputs'!O37<1,IF('Model inputs'!O37="","",'Model inputs'!O37<1))),0,'Model inputs'!O43*'Model inputs'!B39) -> 19.903266 | P11: =IF(IF(IF(ISERROR('Model inputs'!P37<1),'Model inputs'!P37<1,IF('Model inputs'!P37="","",'Model inputs'!P37<1))="",FALSE,IF(ISERROR('Model inputs'!P37<1),'Model inputs'!P37<1,IF('Model inputs'!P37="","",'Model inputs'!P37<1))),0,'Model inputs'!P43*'Model inputs'!B39) -> 21.58378 | Q11: =IF(IF(IF(ISERROR('Model inputs'!Q37<1),'Model inputs'!Q37<1,IF('Model inputs'!Q37="","",'Model inputs'!Q37<1))="",FALSE,IF(ISERROR('Model inputs'!Q37<1),'Model inputs'!Q37<1,IF('Model inputs'!Q37="","",'Model inputs'!Q37<1))),0,'Model inputs'!Q43*'Model inputs'!B39) -> 23.272555 | R11: =IF(IF(IF(ISERROR('Model inputs'!R37<1),'Model inputs'!R37<1,IF('Model inputs'!R37="","",'Model inputs'!R37<1))="",FALSE,IF(ISERROR('Model inputs'!R37<1),'Model inputs'!R37<1,IF('Model inputs'!R37="","",'Model inputs'!R37<1))),0,'Model inputs'!R43*'Model inputs'!B39) -> 24.973853 | S11: =IF(IF(IF(ISERROR('Model inputs'!S37<1),'Model inputs'!S37<1,IF('Model inputs'!S37="","",'Model inputs'!S37<1))="",FALSE,IF(ISERROR('Model inputs'!S37<1),'Model inputs'!S37<1,IF('Model inputs'!S37="","",'Model inputs'!S37<1))),0,'Model inputs'!S43*'Model inputs'!B39) -> 26.691843 | T11: =IF(IF(IF(ISERROR('Model inputs'!T37<1),'Model inputs'!T37<1,IF('Model inputs'!T37="","",'Model inputs'!T37<1))="",FALSE,IF(ISERROR('Model inputs'!T37<1),'Model inputs'!T37<1,IF('Model inputs'!T37="","",'Model inputs'!T37<1))),0,'Model inputs'!T43*'Model inputs'!B39) -> 28.430617
A12: Churned customers > Launch | C12: =IF(IF(IF(ISERROR('Model inputs'!C37<1),'Model inputs'!C37<1,IF('Model inputs'!C37="","",'Model inputs'!C37<1))="",FALSE,IF(ISERROR('Model inputs'!C37<1),'Model inputs'!C37<1,IF('Model inputs'!C37="","",'Model inputs'!C37<1))),0,'Model inputs'!C44*'Model inputs'!B40) -> 0 | D12: =IF(IF(IF(ISERROR('Model inputs'!D37<1),'Model inputs'!D37<1,IF('Model inputs'!D37="","",'Model inputs'!D37<1))="",FALSE,IF(ISERROR('Model inputs'!D37<1),'Model inputs'!D37<1,IF('Model inputs'!D37="","",'Model inputs'!D37<1))),0,'Model inputs'!D44*'Model inputs'!B40) -> 0.015 | E12: =IF(IF(IF(ISERROR('Model inputs'!E37<1),'Model inputs'!E37<1,IF('Model inputs'!E37="","",'Model inputs'!E37<1))="",FALSE,IF(ISERROR('Model inputs'!E37<1),'Model inputs'!E37<1,IF('Model inputs'!E37="","",'Model inputs'!E37<1))),0,'Model inputs'!E44*'Model inputs'!B40) -> 0.02265 | F12: =IF(IF(IF(ISERROR('Model inputs'!F37<1),'Model inputs'!F37<1,IF('Model inputs'!F37="","",'Model inputs'!F37<1))="",FALSE,IF(ISERROR('Model inputs'!F37<1),'Model inputs'!F37<1,IF('Model inputs'!F37="","",'Model inputs'!F37<1))),0,'Model inputs'!F44*'Model inputs'!B40) -> 0.030376604 | G12: =IF(IF(IF(ISERROR('Model inputs'!G37<1),'Model inputs'!G37<1,IF('Model inputs'!G37="","",'Model inputs'!G37<1))="",FALSE,IF(ISERROR('Model inputs'!G37<1),'Model inputs'!G37<1,IF('Model inputs'!G37="","",'Model inputs'!G37<1))),0,'Model inputs'!G44*'Model inputs'!B40) -> 0.038205181 | H12: =IF(IF(IF(ISERROR('Model inputs'!H37<1),'Model inputs'!H37<1,IF('Model inputs'!H37="","",'Model inputs'!H37<1))="",FALSE,IF(ISERROR('Model inputs'!H37<1),'Model inputs'!H37<1,IF('Model inputs'!H37="","",'Model inputs'!H37<1))),0,'Model inputs'!H44*'Model inputs'!B40) -> 0.046156567 | I12: =IF(IF(IF(ISERROR('Model inputs'!I37<1),'Model inputs'!I37<1,IF('Model inputs'!I37="","",'Model inputs'!I37<1))="",FALSE,IF(ISERROR('Model inputs'!I37<1),'Model inputs'!I37<1,IF('Model inputs'!I37="","",'Model inputs'!I37<1))),0,'Model inputs'!I44*'Model inputs'!B40) -> 0.054252873 | J12: =IF(IF(IF(ISERROR('Model inputs'!J37<1),'Model inputs'!J37<1,IF('Model inputs'!J37="","",'Model inputs'!J37<1))="",FALSE,IF(ISERROR('Model inputs'!J37<1),'Model inputs'!J37<1,IF('Model inputs'!J37="","",'Model inputs'!J37<1))),0,'Model inputs'!J44*'Model inputs'!B40) -> 0.062517667 | K12: =IF(IF(IF(ISERROR('Model inputs'!K37<1),'Model inputs'!K37<1,IF('Model inputs'!K37="","",'Model inputs'!K37<1))="",FALSE,IF(ISERROR('Model inputs'!K37<1),'Model inputs'!K37<1,IF('Model inputs'!K37="","",'Model inputs'!K37<1))),0,'Model inputs'!K44*'Model inputs'!B40) -> 0.070976178 | L12: =IF(IF(IF(ISERROR('Model inputs'!L37<1),'Model inputs'!L37<1,IF('Model inputs'!L37="","",'Model inputs'!L37<1))="",FALSE,IF(ISERROR('Model inputs'!L37<1),'Model inputs'!L37<1,IF('Model inputs'!L37="","",'Model inputs'!L37<1))),0,'Model inputs'!L44*'Model inputs'!B40) -> 0.079655503 | M12: =IF(IF(IF(ISERROR('Model inputs'!M37<1),'Model inputs'!M37<1,IF('Model inputs'!M37="","",'Model inputs'!M37<1))="",FALSE,IF(ISERROR('Model inputs'!M37<1),'Model inputs'!M37<1,IF('Model inputs'!M37="","",'Model inputs'!M37<1))),0,'Model inputs'!M44*'Model inputs'!B40) -> 0.088584845 | N12: =IF(IF(IF(ISERROR('Model inputs'!N37<1),'Model inputs'!N37<1,IF('Model inputs'!N37="","",'Model inputs'!N37<1))="",FALSE,IF(ISERROR('Model inputs'!N37<1),'Model inputs'!N37<1,IF('Model inputs'!N37="","",'Model inputs'!N37<1))),0,'Model inputs'!N44*'Model inputs'!B40) -> 0.097773829 | O12: =IF(IF(IF(ISERROR('Model inputs'!O37<1),'Model inputs'!O37<1,IF('Model inputs'!O37="","",'Model inputs'!O37<1))="",FALSE,IF(ISERROR('Model inputs'!O37<1),'Model inputs'!O37<1,IF('Model inputs'!O37="","",'Model inputs'!O37<1))),0,'Model inputs'!O44*'Model inputs'!B40) -> 0.107232 | P12: =IF(IF(IF(ISERROR('Model inputs'!P37<1),'Model inputs'!P37<1,IF('Model inputs'!P37="","",'Model inputs'!P37<1))="",FALSE,IF(ISERROR('Model inputs'!P37<1),'Model inputs'!P37<1,IF('Model inputs'!P37="","",'Model inputs'!P37<1))),0,'Model inputs'!P44*'Model inputs'!B40) -> 0.11696886 | Q12: =IF(IF(IF(ISERROR('Model inputs'!Q37<1),'Model inputs'!Q37<1,IF('Model inputs'!Q37="","",'Model inputs'!Q37<1))="",FALSE,IF(ISERROR('Model inputs'!Q37<1),'Model inputs'!Q37<1,IF('Model inputs'!Q37="","",'Model inputs'!Q37<1))),0,'Model inputs'!Q44*'Model inputs'!B40) -> 0.12699396 | R12: =IF(IF(IF(ISERROR('Model inputs'!R37<1),'Model inputs'!R37<1,IF('Model inputs'!R37="","",'Model inputs'!R37<1))="",FALSE,IF(ISERROR('Model inputs'!R37<1),'Model inputs'!R37<1,IF('Model inputs'!R37="","",'Model inputs'!R37<1))),0,'Model inputs'!R44*'Model inputs'!B40) -> 0.13731689 | S12: =IF(IF(IF(ISERROR('Model inputs'!S37<1),'Model inputs'!S37<1,IF('Model inputs'!S37="","",'Model inputs'!S37<1))="",FALSE,IF(ISERROR('Model inputs'!S37<1),'Model inputs'!S37<1,IF('Model inputs'!S37="","",'Model inputs'!S37<1))),0,'Model inputs'!S44*'Model inputs'!B40) -> 0.14794739 | T12: =IF(IF(IF(ISERROR('Model inputs'!T37<1),'Model inputs'!T37<1,IF('Model inputs'!T37="","",'Model inputs'!T37<1))="",FALSE,IF(ISERROR('Model inputs'!T37<1),'Model inputs'!T37<1,IF('Model inputs'!T37="","",'Model inputs'!T37<1))),0,'Model inputs'!T44*'Model inputs'!B40) -> 0.15889534
A13: Churned customers > Team | C13: =IF(IF(IF(ISERROR('Model inputs'!C37<1),'Model inputs'!C37<1,IF('Model inputs'!C37="","",'Model inputs'!C37<1))="",FALSE,IF(ISERROR('Model inputs'!C37<1),'Model inputs'!C37<1,IF('Model inputs'!C37="","",'Model inputs'!C37<1))),0,'Model inputs'!C45*'Model inputs'!B41) -> 0 | D13: =IF(IF(IF(ISERROR('Model inputs'!D37<1),'Model inputs'!D37<1,IF('Model inputs'!D37="","",'Model inputs'!D37<1))="",FALSE,IF(ISERROR('Model inputs'!D37<1),'Model inputs'!D37<1,IF('Model inputs'!D37="","",'Model inputs'!D37<1))),0,'Model inputs'!D45*'Model inputs'!B41) -> 0.18 | E13: =IF(IF(IF(ISERROR('Model inputs'!E37<1),'Model inputs'!E37<1,IF('Model inputs'!E37="","",'Model inputs'!E37<1))="",FALSE,IF(ISERROR('Model inputs'!E37<1),'Model inputs'!E37<1,IF('Model inputs'!E37="","",'Model inputs'!E37<1))),0,'Model inputs'!E45*'Model inputs'!B41) -> 0.27185 | F13: =IF(IF(IF(ISERROR('Model inputs'!F37<1),'Model inputs'!F37<1,IF('Model inputs'!F37="","",'Model inputs'!F37<1))="",FALSE,IF(ISERROR('Model inputs'!F37<1),'Model inputs'!F37<1,IF('Model inputs'!F37="","",'Model inputs'!F37<1))),0,'Model inputs'!F45*'Model inputs'!B41) -> 0.37642846 | G13: =IF(IF(IF(ISERROR('Model inputs'!G37<1),'Model inputs'!G37<1,IF('Model inputs'!G37="","",'Model inputs'!G37<1))="",FALSE,IF(ISERROR('Model inputs'!G37<1),'Model inputs'!G37<1,IF('Model inputs'!G37="","",'Model inputs'!G37<1))),0,'Model inputs'!G45*'Model inputs'!B41) -> 0.49174271 | H13: =IF(IF(IF(ISERROR('Model inputs'!H37<1),'Model inputs'!H37<1,IF('Model inputs'!H37="","",'Model inputs'!H37<1))="",FALSE,IF(ISERROR('Model inputs'!H37<1),'Model inputs'!H37<1,IF('Model inputs'!H37="","",'Model inputs'!H37<1))),0,'Model inputs'!H45*'Model inputs'!B41) -> 0.61855402 | I13: =IF(IF(IF(ISERROR('Model inputs'!I37<1),'Model inputs'!I37<1,IF('Model inputs'!I37="","",'Model inputs'!I37<1))="",FALSE,IF(ISERROR('Model inputs'!I37<1),'Model inputs'!I37<1,IF('Model inputs'!I37="","",'Model inputs'!I37<1))),0,'Model inputs'!I45*'Model inputs'!B41) -> 0.757722 | J13: =IF(IF(IF(ISERROR('Model inputs'!J37<1),'Model inputs'!J37<1,IF('Model inputs'!J37="","",'Model inputs'!J37<1))="",FALSE,IF(ISERROR('Model inputs'!J37<1),'Model inputs'!J37<1,IF('Model inputs'!J37="","",'Model inputs'!J37<1))),0,'Model inputs'!J45*'Model inputs'!B41) -> 0.91021223 | K13: =IF(IF(IF(ISERROR('Model inputs'!K37<1),'Model inputs'!K37<1,IF('Model inputs'!K37="","",'Model inputs'!K37<1))="",FALSE,IF(ISERROR('Model inputs'!K37<1),'Model inputs'!K37<1,IF('Model inputs'!K37="","",'Model inputs'!K37<1))),0,'Model inputs'!K45*'Model inputs'!B41) -> 1.0771047 | L13: =IF(IF(IF(ISERROR('Model inputs'!L37<1),'Model inputs'!L37<1,IF('Model inputs'!L37="","",'Model inputs'!L37<1))="",FALSE,IF(ISERROR('Model inputs'!L37<1),'Model inputs'!L37<1,IF('Model inputs'!L37="","",'Model inputs'!L37<1))),0,'Model inputs'!L45*'Model inputs'!B41) -> 1.2596034 | M13: =IF(IF(IF(ISERROR('Model inputs'!M37<1),'Model inputs'!M37<1,IF('Model inputs'!M37="","",'Model inputs'!M37<1))="",FALSE,IF(ISERROR('Model inputs'!M37<1),'Model inputs'!M37<1,IF('Model inputs'!M37="","",'Model inputs'!M37<1))),0,'Model inputs'!M45*'Model inputs'!B41) -> 1.4485236 | N13: =IF(IF(IF(ISERROR('Model inputs'!N37<1),'Model inputs'!N37<1,IF('Model inputs'!N37="","",'Model inputs'!N37<1))="",FALSE,IF(ISERROR('Model inputs'!N37<1),'Model inputs'!N37<1,IF('Model inputs'!N37="","",'Model inputs'!N37<1))),0,'Model inputs'!N45*'Model inputs'!B41) -> 1.643893 | O13: =IF(IF(IF(ISERROR('Model inputs'!O37<1),'Model inputs'!O37<1,IF('Model inputs'!O37="","",'Model inputs'!O37<1))="",FALSE,IF(ISERROR('Model inputs'!O37<1),'Model inputs'!O37<1,IF('Model inputs'!O37="","",'Model inputs'!O37<1))),0,'Model inputs'!O45*'Model inputs'!B41) -> 1.8457659 | P13: =IF(IF(IF(ISERROR('Model inputs'!P37<1),'Model inputs'!P37<1,IF('Model inputs'!P37="","",'Model inputs'!P37<1))="",FALSE,IF(ISERROR('Model inputs'!P37<1),'Model inputs'!P37<1,IF('Model inputs'!P37="","",'Model inputs'!P37<1))),0,'Model inputs'!P45*'Model inputs'!B41) -> 2.0542216 | Q13: =IF(IF(IF(ISERROR('Model inputs'!Q37<1),'Model inputs'!Q37<1,IF('Model inputs'!Q37="","",'Model inputs'!Q37<1))="",FALSE,IF(ISERROR('Model inputs'!Q37<1),'Model inputs'!Q37<1,IF('Model inputs'!Q37="","",'Model inputs'!Q37<1))),0,'Model inputs'!Q45*'Model inputs'!B41) -> 2.2693637 | R13: =IF(IF(IF(ISERROR('Model inputs'!R37<1),'Model inputs'!R37<1,IF('Model inputs'!R37="","",'Model inputs'!R37<1))="",FALSE,IF(ISERROR('Model inputs'!R37<1),'Model inputs'!R37<1,IF('Model inputs'!R37="","",'Model inputs'!R37<1))),0,'Model inputs'!R45*'Model inputs'!B41) -> 2.4913197 | S13: =IF(IF(IF(ISERROR('Model inputs'!S37<1),'Model inputs'!S37<1,IF('Model inputs'!S37="","",'Model inputs'!S37<1))="",FALSE,IF(ISERROR('Model inputs'!S37<1),'Model inputs'!S37<1,IF('Model inputs'!S37="","",'Model inputs'!S37<1))),0,'Model inputs'!S45*'Model inputs'!B41) -> 2.7202399 | T13: =IF(IF(IF(ISERROR('Model inputs'!T37<1),'Model inputs'!T37<1,IF('Model inputs'!T37="","",'Model inputs'!T37<1))="",FALSE,IF(ISERROR('Model inputs'!T37<1),'Model inputs'!T37<1,IF('Model inputs'!T37="","",'Model inputs'!T37<1))),0,'Model inputs'!T45*'Model inputs'!B41) -> 2.956297
A14: Contribution | C14: =SUM('Model inputs'!C15,'Model inputs'!C16,'Model inputs'!C17) -> 2406.6273 | D14: =SUM('Model inputs'!D15,'Model inputs'!D16,'Model inputs'!D17) -> 3965.317 | E14: =SUM('Model inputs'!E15,'Model inputs'!E16,'Model inputs'!E17) -> 5243.9183 | F14: =SUM('Model inputs'!F15,'Model inputs'!F16,'Model inputs'!F17) -> 6577.772 | G14: =SUM('Model inputs'!G15,'Model inputs'!G16,'Model inputs'!G17) -> 7972.7009 | H14: =SUM('Model inputs'!H15,'Model inputs'!H16,'Model inputs'!H17) -> 9434.9597 | I14: =SUM('Model inputs'!I15,'Model inputs'!I16,'Model inputs'!I17) -> 10971.268 | J14: =SUM('Model inputs'!J15,'Model inputs'!J16,'Model inputs'!J17) -> 12781.208 | ... T14: =SUM('Model inputs'!T15,'Model inputs'!T16,'Model inputs'!T17) -> 32728.279
A15: Contribution > Indie | C15: ='Model inputs'!C56-'Model inputs'!C95-'Model inputs'!C52 -> 1101.1184 | D15: ='Model inputs'!D56-'Model inputs'!D95-'Model inputs'!D52 -> 2046.245 | E15: ='Model inputs'!E56-'Model inputs'!E95-'Model inputs'!E52 -> 2653.0836 | F15: ='Model inputs'!F56-'Model inputs'!F95-'Model inputs'!F52 -> 3278.9267 | G15: ='Model inputs'!G56-'Model inputs'!G95-'Model inputs'!G52 -> 3927.2641 | H15: ='Model inputs'!H56-'Model inputs'!H95-'Model inputs'!H52 -> 4601.7336 | I15: ='Model inputs'!I56-'Model inputs'!I95-'Model inputs'!I52 -> 5306.1415 | J15: ='Model inputs'!J56-'Model inputs'!J95-'Model inputs'!J52 -> 6044.4841 | ... T15: ='Model inputs'!T56-'Model inputs'!T95-'Model inputs'!T52 -> 13853.08
A16: Contribution > Launch | C16: ='Model inputs'!C57-'Model inputs'!C96-'Model inputs'!C53 -> 461.35556 | D16: ='Model inputs'!D57-'Model inputs'!D96-'Model inputs'!D53 -> 677.84941 | E16: ='Model inputs'!E57-'Model inputs'!E96-'Model inputs'!E53 -> 896.45597 | F16: ='Model inputs'!F57-'Model inputs'!F96-'Model inputs'!F53 -> 1113.704 | G16: ='Model inputs'!G57-'Model inputs'!G96-'Model inputs'!G53 -> 1330.0813 | H16: ='Model inputs'!H57-'Model inputs'!H96-'Model inputs'!H53 -> 1546.0865 | I16: ='Model inputs'!I57-'Model inputs'!I96-'Model inputs'!I53 -> 1762.2326 | J16: ='Model inputs'!J57-'Model inputs'!J96-'Model inputs'!J53 -> 2037.9532 | ... T16: ='Model inputs'!T57-'Model inputs'!T96-'Model inputs'!T53 -> 4874.1038
A17: Contribution > Team | C17: ='Model inputs'!C58-'Model inputs'!C97-'Model inputs'!C54 -> 844.15332 | D17: ='Model inputs'!D58-'Model inputs'!D97-'Model inputs'!D54 -> 1241.2226 | E17: ='Model inputs'!E58-'Model inputs'!E97-'Model inputs'!E54 -> 1694.3787 | F17: ='Model inputs'!F58-'Model inputs'!F97-'Model inputs'!F54 -> 2185.1413 | G17: ='Model inputs'!G58-'Model inputs'!G97-'Model inputs'!G54 -> 2715.3555 | H17: ='Model inputs'!H58-'Model inputs'!H97-'Model inputs'!H54 -> 3287.1395 | I17: ='Model inputs'!I58-'Model inputs'!I97-'Model inputs'!I54 -> 3902.8939 | J17: ='Model inputs'!J58-'Model inputs'!J97-'Model inputs'!J54 -> 4698.7706 | ... T17: ='Model inputs'!T58-'Model inputs'!T97-'Model inputs'!T54 -> 14001.095
A18: Cost optimization from month | B18: =7 -> 7
A19: Cost optimization on | B19: =0 -> 0
A20: Kits generated | C20: =SUM('Model inputs'!C21,'Model inputs'!C22,'Model inputs'!C23) -> 828 | D20: =SUM('Model inputs'!D21,'Model inputs'!D22,'Model inputs'!D23) -> 1368.7917 | E20: =SUM('Model inputs'!E21,'Model inputs'!E22,'Model inputs'!E23) -> 1826.1211 | F20: =SUM('Model inputs'!F21,'Model inputs'!F22,'Model inputs'!F23) -> 2307.5384 | G20: =SUM('Model inputs'!G21,'Model inputs'!G22,'Model inputs'!G23) -> 2815.6002 | H20: =SUM('Model inputs'!H21,'Model inputs'!H22,'Model inputs'!H23) -> 3353.0799 | I20: =SUM('Model inputs'!I21,'Model inputs'!I22,'Model inputs'!I23) -> 3922.9894 | J20: =SUM('Model inputs'!J21,'Model inputs'!J22,'Model inputs'!J23) -> 4528.601 | ... T20: =SUM('Model inputs'!T21,'Model inputs'!T22,'Model inputs'!T23) -> 11627.366
A21: Kits generated > Indie | C21: ='Model inputs'!C72*('Model inputs'!B100+'Model inputs'!B131) -> 340 | D21: ='Model inputs'!D72*('Model inputs'!B100+'Model inputs'!B131) -> 631.83333 | E21: ='Model inputs'!E72*('Model inputs'!B100+'Model inputs'!B131) -> 819.21111 | F21: ='Model inputs'!F72*('Model inputs'!B100+'Model inputs'!B131) -> 1012.457 | G21: ='Model inputs'!G72*('Model inputs'!B100+'Model inputs'!B131) -> 1212.6487 | H21: ='Model inputs'!H72*('Model inputs'!B100+'Model inputs'!B131) -> 1420.9094 | I21: ='Model inputs'!I72*('Model inputs'!B100+'Model inputs'!B131) -> 1638.4143 | J21: ='Model inputs'!J72*('Model inputs'!B100+'Model inputs'!B131) -> 1866.3975 | K21: ='Model inputs'!K72*('Model inputs'!B100+'Model inputs'!B131) -> 2106.1586 | L21: ='Model inputs'!L72*('Model inputs'!B100+'Model inputs'!B131) -> 2344.5032 | M21: ='Model inputs'!M72*('Model inputs'!B100+'Model inputs'!B131) -> 2582.1084 | N21: ='Model inputs'!N72*('Model inputs'!B100+'Model inputs'!B131) -> 2819.6294 | O21: ='Model inputs'!O72*('Model inputs'!B100+'Model inputs'!B131) -> 3057.7021 | P21: ='Model inputs'!P72*('Model inputs'!B100+'Model inputs'!B131) -> 3296.9453 | Q21: ='Model inputs'!Q72*('Model inputs'!B100+'Model inputs'!B131) -> 3537.9625 | R21: ='Model inputs'!R72*('Model inputs'!B100+'Model inputs'!B131) -> 3781.3445 | S21: ='Model inputs'!S72*('Model inputs'!B100+'Model inputs'!B131) -> 4027.6708 | T21: ='Model inputs'!T72*('Model inputs'!B100+'Model inputs'!B131) -> 4277.512
A22: Kits generated > Launch | C22: ='Model inputs'!C73*('Model inputs'!B101+'Model inputs'!B132) -> 206 | D22: ='Model inputs'!D73*('Model inputs'!B101+'Model inputs'!B132) -> 311.06 | E22: ='Model inputs'!E73*('Model inputs'!B101+'Model inputs'!B132) -> 417.17203 | F22: ='Model inputs'!F73*('Model inputs'!B101+'Model inputs'!B132) -> 524.68449 | G22: ='Model inputs'!G73*('Model inputs'!B101+'Model inputs'!B132) -> 633.88352 | H22: ='Model inputs'!H73*('Model inputs'!B101+'Model inputs'!B132) -> 745.07279 | I22: ='Model inputs'!I73*('Model inputs'!B101+'Model inputs'!B132) -> 858.57597 | J22: ='Model inputs'!J73*('Model inputs'!B101+'Model inputs'!B132) -> 974.73951 | K22: ='Model inputs'!K73*('Model inputs'!B101+'Model inputs'!B132) -> 1093.9356 | L22: ='Model inputs'!L73*('Model inputs'!B101+'Model inputs'!B132) -> 1216.5652 | M22: ='Model inputs'!M73*('Model inputs'!B101+'Model inputs'!B132) -> 1342.7606 | N22: ='Model inputs'!N73*('Model inputs'!B101+'Model inputs'!B132) -> 1472.6528 | O22: ='Model inputs'!O73*('Model inputs'!B101+'Model inputs'!B132) -> 1606.3724 | P22: ='Model inputs'!P73*('Model inputs'!B101+'Model inputs'!B132) -> 1744.0504 | Q22: ='Model inputs'!Q73*('Model inputs'!B101+'Model inputs'!B132) -> 1885.8186 | R22: ='Model inputs'!R73*('Model inputs'!B101+'Model inputs'!B132) -> 2031.8108 | S22: ='Model inputs'!S73*('Model inputs'!B101+'Model inputs'!B132) -> 2182.1627 | T22: ='Model inputs'!T73*('Model inputs'!B101+'Model inputs'!B132) -> 2337.0132
A23: Kits generated > Team | C23: ='Model inputs'!C74*('Model inputs'!B102+'Model inputs'!B133) -> 282 | D23: ='Model inputs'!D74*('Model inputs'!B102+'Model inputs'!B133) -> 425.89833 | E23: ='Model inputs'!E74*('Model inputs'!B102+'Model inputs'!B133) -> 589.73792 | F23: ='Model inputs'!F74*('Model inputs'!B102+'Model inputs'!B133) -> 770.39691 | G23: ='Model inputs'!G74*('Model inputs'!B102+'Model inputs'!B133) -> 969.06796 | H23: ='Model inputs'!H74*('Model inputs'!B102+'Model inputs'!B133) -> 1187.0978 | I23: ='Model inputs'!I74*('Model inputs'!B102+'Model inputs'!B133) -> 1425.9992 | J23: ='Model inputs'!J74*('Model inputs'!B102+'Model inputs'!B133) -> 1687.4641 | K23: ='Model inputs'!K74*('Model inputs'!B102+'Model inputs'!B133) -> 1973.3787 | L23: ='Model inputs'!L74*('Model inputs'!B102+'Model inputs'!B133) -> 2269.3536 | M23: ='Model inputs'!M74*('Model inputs'!B102+'Model inputs'!B133) -> 2575.4324 | N23: ='Model inputs'!N74*('Model inputs'!B102+'Model inputs'!B133) -> 2891.7 | O23: ='Model inputs'!O74*('Model inputs'!B102+'Model inputs'!B133) -> 3218.2805 | P23: ='Model inputs'!P74*('Model inputs'!B102+'Model inputs'!B133) -> 3555.3365 | Q23: ='Model inputs'!Q74*('Model inputs'!B102+'Model inputs'!B133) -> 3903.0675 | R23: ='Model inputs'!R74*('Model inputs'!B102+'Model inputs'!B133) -> 4261.7092 | S23: ='Model inputs'!S74*('Model inputs'!B102+'Model inputs'!B133) -> 4631.532 | T23: ='Model inputs'!T74*('Model inputs'!B102+'Model inputs'!B133) -> 5012.8411
A24: Line monthly cost | B24: 0
A25: Line monthly cost > Domain, email, extras | B25: =40 -> 40
A26: Line monthly cost > Entire cloud workspace | B26: =200 -> 200
A27: Line monthly cost > First engineer (loaded) | B27: =12000 -> 12000
A28: Line monthly cost > Founder full-time step-up | B28: =4000 -> 4000
A29: Line monthly cost > Founder salary (0.5 FTE) | B29: =4000 -> 4000
A30: Line monthly cost > Frontend contractor (0.25 FTE) | B30: =2000 -> 2000
A31: Line monthly cost > Hosting (Vercel + storage) | B31: =80 -> 80
A32: Line monthly cost > Marketing: always-on | B32: =250 -> 250
A33: Line monthly cost > Marketing: launch push | B33: =350 -> 350
A34: Line monthly cost > cfo.ai Startup | B34: =375 -> 375
A35: Line monthly cost > neatlogs Pro | B35: =500 -> 500
A36: Loaded COGS per kit | B36: ='Model inputs'!B103+'Model inputs'!B93+'Model inputs'!B138+'Model inputs'!B117+'Model inputs'!B98 -> 0.24
A37: Model month | C37: =(YEAR(DATE(2026,11,1))-2026)*12+MONTH(DATE(2026,11,1))-11 -> 0 | D37: =(YEAR(DATE(2026,12,1))-2026)*12+MONTH(DATE(2026,12,1))-11 -> 1 | E37: =(YEAR(DATE(2027,1,1))-2026)*12+MONTH(DATE(2027,1,1))-11 -> 2 | F37: =(YEAR(DATE(2027,2,1))-2026)*12+MONTH(DATE(2027,2,1))-11 -> 3 | G37: =(YEAR(DATE(2027,3,1))-2026)*12+MONTH(DATE(2027,3,1))-11 -> 4 | H37: =(YEAR(DATE(2027,4,1))-2026)*12+MONTH(DATE(2027,4,1))-11 -> 5 | I37: =(YEAR(DATE(2027,5,1))-2026)*12+MONTH(DATE(2027,5,1))-11 -> 6 | J37: =(YEAR(DATE(2027,6,1))-2026)*12+MONTH(DATE(2027,6,1))-11 -> 7 | K37: =(YEAR(DATE(2027,7,1))-2026)*12+MONTH(DATE(2027,7,1))-11 -> 8 | L37: =(YEAR(DATE(2027,8,1))-2026)*12+MONTH(DATE(2027,8,1))-11 -> 9 | M37: =(YEAR(DATE(2027,9,1))-2026)*12+MONTH(DATE(2027,9,1))-11 -> 10 | N37: =(YEAR(DATE(2027,10,1))-2026)*12+MONTH(DATE(2027,10,1))-11 -> 11 | O37: =(YEAR(DATE(2027,11,1))-2026)*12+MONTH(DATE(2027,11,1))-11 -> 12 | P37: =(YEAR(DATE(2027,12,1))-2026)*12+MONTH(DATE(2027,12,1))-11 -> 13 | Q37: =(YEAR(DATE(2028,1,1))-2026)*12+MONTH(DATE(2028,1,1))-11 -> 14 | R37: =(YEAR(DATE(2028,2,1))-2026)*12+MONTH(DATE(2028,2,1))-11 -> 15 | S37: =(YEAR(DATE(2028,3,1))-2026)*12+MONTH(DATE(2028,3,1))-11 -> 16 | T37: =(YEAR(DATE(2028,4,1))-2026)*12+MONTH(DATE(2028,4,1))-11 -> 17
A38: Monthly logo churn | B38: 0
A39: Monthly logo churn > Indie | B39: =0.06 -> 0.06
A40: Monthly logo churn > Launch | B40: =0.015 -> 0.015
A41: Monthly logo churn > Team | B41: =0.03 -> 0.03
A42: Opening customers | C42: =SUM('Model inputs'!C43,'Model inputs'!C44,'Model inputs'!C45) -> 47 | D42: =SUM('Model inputs'!D43,'Model inputs'!D44,'Model inputs'!D45) -> 47 | E42: =SUM('Model inputs'!E43,'Model inputs'!E44,'Model inputs'!E45) -> 84.905 | F42: =SUM('Model inputs'!F43,'Model inputs'!F44,'Model inputs'!F45) -> 110.9505 | G42: =SUM('Model inputs'!G43,'Model inputs'!G44,'Model inputs'!G45) -> 138.05103 | H42: =SUM('Model inputs'!H43,'Model inputs'!H44,'Model inputs'!H45) -> 166.36012 | I42: =SUM('Model inputs'!I43,'Model inputs'!I44,'Model inputs'!I45) -> 196.04007 | J42: =SUM('Model inputs'!J43,'Model inputs'!J44,'Model inputs'!J45) -> 227.26287 | ... T42: =SUM('Model inputs'!T43,'Model inputs'!T44,'Model inputs'!T45) -> 582.97988
A43: Opening customers > Indie | C43: =IF(IF(IF(ISERROR('Model inputs'!C37=0),'Model inputs'!C37=0,IF('Model inputs'!C37="","",'Model inputs'!C37=0))="",FALSE,IF(ISERROR('Model inputs'!C37=0),'Model inputs'!C37=0,IF('Model inputs'!C37="","",'Model inputs'!C37=0))),IF('Model inputs'!B140="","",'Model inputs'!B140),IF('Model inputs'!AG90="","",'Model inputs'!AG90)) -> 40 | D43: =IF(IF(IF(ISERROR('Model inputs'!D37=0),'Model inputs'!D37=0,IF('Model inputs'!D37="","",'Model inputs'!D37=0))="",FALSE,IF(ISERROR('Model inputs'!D37=0),'Model inputs'!D37=0,IF('Model inputs'!D37="","",'Model inputs'!D37=0))),IF('Model inputs'!B140="","",'Model inputs'!B140),IF('Model inputs'!C72="","",'Model inputs'!C72)) -> 40 | E43: =IF(IF(IF(ISERROR('Model inputs'!E37=0),'Model inputs'!E37=0,IF('Model inputs'!E37="","",'Model inputs'!E37=0))="",FALSE,IF(ISERROR('Model inputs'!E37=0),'Model inputs'!E37=0,IF('Model inputs'!E37="","",'Model inputs'!E37=0))),IF('Model inputs'!B140="","",'Model inputs'!B140),IF('Model inputs'!D72="","",'Model inputs'!D72)) -> 74.333333 | F43: =IF(IF(IF(ISERROR('Model inputs'!F37=0),'Model inputs'!F37=0,IF('Model inputs'!F37="","",'Model inputs'!F37=0))="",FALSE,IF(ISERROR('Model inputs'!F37=0),'Model inputs'!F37=0,IF('Model inputs'!F37="","",'Model inputs'!F37=0))),IF('Model inputs'!B140="","",'Model inputs'!B140),IF('Model inputs'!E72="","",'Model inputs'!E72)) -> 96.377778 | G43: =IF(IF(IF(ISERROR('Model inputs'!G37=0),'Model inputs'!G37=0,IF('Model inputs'!G37="","",'Model inputs'!G37=0))="",FALSE,IF(ISERROR('Model inputs'!G37=0),'Model inputs'!G37=0,IF('Model inputs'!G37="","",'Model inputs'!G37=0))),IF('Model inputs'!B140="","",'Model inputs'!B140),IF('Model inputs'!F72="","",'Model inputs'!F72)) -> 119.11259 | H43: =IF(IF(IF(ISERROR('Model inputs'!H37=0),'Model inputs'!H37=0,IF('Model inputs'!H37="","",'Model inputs'!H37=0))="",FALSE,IF(ISERROR('Model inputs'!H37=0),'Model inputs'!H37=0,IF('Model inputs'!H37="","",'Model inputs'!H37=0))),IF('Model inputs'!B140="","",'Model inputs'!B140),IF('Model inputs'!G72="","",'Model inputs'!G72)) -> 142.66455 | I43: =IF(IF(IF(ISERROR('Model inputs'!I37=0),'Model inputs'!I37=0,IF('Model inputs'!I37="","",'Model inputs'!I37=0))="",FALSE,IF(ISERROR('Model inputs'!I37=0),'Model inputs'!I37=0,IF('Model inputs'!I37="","",'Model inputs'!I37=0))),IF('Model inputs'!B140="","",'Model inputs'!B140),IF('Model inputs'!H72="","",'Model inputs'!H72)) -> 167.16581 | J43: =IF(IF(IF(ISERROR('Model inputs'!J37=0),'Model inputs'!J37=0,IF('Model inputs'!J37="","",'Model inputs'!J37=0))="",FALSE,IF(ISERROR('Model inputs'!J37=0),'Model inputs'!J37=0,IF('Model inputs'!J37="","",'Model inputs'!J37=0))),IF('Model inputs'!B140="","",'Model inputs'!B140),IF('Model inputs'!I72="","",'Model inputs'!I72)) -> 192.75462 | K43: =IF(IF(IF(ISERROR('Model inputs'!K37=0),'Model inputs'!K37=0,IF('Model inputs'!K37="","",'Model inputs'!K37=0))="",FALSE,IF(ISERROR('Model inputs'!K37=0),'Model inputs'!K37=0,IF('Model inputs'!K37="","",'Model inputs'!K37=0))),IF('Model inputs'!B140="","",'Model inputs'!B140),IF('Model inputs'!J72="","",'Model inputs'!J72)) -> 219.57617 | L43: =IF(IF(IF(ISERROR('Model inputs'!L37=0),'Model inputs'!L37=0,IF('Model inputs'!L37="","",'Model inputs'!L37=0))="",FALSE,IF(ISERROR('Model inputs'!L37=0),'Model inputs'!L37=0,IF('Model inputs'!L37="","",'Model inputs'!L37=0))),IF('Model inputs'!B140="","",'Model inputs'!B140),IF('Model inputs'!K72="","",'Model inputs'!K72)) -> 247.78337 | M43: =IF(IF(IF(ISERROR('Model inputs'!M37=0),'Model inputs'!M37=0,IF('Model inputs'!M37="","",'Model inputs'!M37=0))="",FALSE,IF(ISERROR('Model inputs'!M37=0),'Model inputs'!M37=0,IF('Model inputs'!M37="","",'Model inputs'!M37=0))),IF('Model inputs'!B140="","",'Model inputs'!B140),IF('Model inputs'!L72="","",'Model inputs'!L72)) -> 275.82391 | N43: =IF(IF(IF(ISERROR('Model inputs'!N37=0),'Model inputs'!N37=0,IF('Model inputs'!N37="","",'Model inputs'!N37=0))="",FALSE,IF(ISERROR('Model inputs'!N37=0),'Model inputs'!N37=0,IF('Model inputs'!N37="","",'Model inputs'!N37=0))),IF('Model inputs'!B140="","",'Model inputs'!B140),IF('Model inputs'!M72="","",'Model inputs'!M72)) -> 303.77745 | O43: =IF(IF(IF(ISERROR('Model inputs'!O37=0),'Model inputs'!O37=0,IF('Model inputs'!O37="","",'Model inputs'!O37=0))="",FALSE,IF(ISERROR('Model inputs'!O37=0),'Model inputs'!O37=0,IF('Model inputs'!O37="","",'Model inputs'!O37=0))),IF('Model inputs'!B140="","",'Model inputs'!B140),IF('Model inputs'!N72="","",'Model inputs'!N72)) -> 331.7211 | P43: =IF(IF(IF(ISERROR('Model inputs'!P37=0),'Model inputs'!P37=0,IF('Model inputs'!P37="","",'Model inputs'!P37=0))="",FALSE,IF(ISERROR('Model inputs'!P37=0),'Model inputs'!P37=0,IF('Model inputs'!P37="","",'Model inputs'!P37=0))),IF('Model inputs'!B140="","",'Model inputs'!B140),IF('Model inputs'!O72="","",'Model inputs'!O72)) -> 359.72966 | Q43: =IF(IF(IF(ISERROR('Model inputs'!Q37=0),'Model inputs'!Q37=0,IF('Model inputs'!Q37="","",'Model inputs'!Q37=0))="",FALSE,IF(ISERROR('Model inputs'!Q37=0),'Model inputs'!Q37=0,IF('Model inputs'!Q37="","",'Model inputs'!Q37=0))),IF('Model inputs'!B140="","",'Model inputs'!B140),IF('Model inputs'!P72="","",'Model inputs'!P72)) -> 387.87592 | R43: =IF(IF(IF(ISERROR('Model inputs'!R37=0),'Model inputs'!R37=0,IF('Model inputs'!R37="","",'Model inputs'!R37=0))="",FALSE,IF(ISERROR('Model inputs'!R37=0),'Model inputs'!R37=0,IF('Model inputs'!R37="","",'Model inputs'!R37=0))),IF('Model inputs'!B140="","",'Model inputs'!B140),IF('Model inputs'!Q72="","",'Model inputs'!Q72)) -> 416.23088 | S43: =IF(IF(IF(ISERROR('Model inputs'!S37=0),'Model inputs'!S37=0,IF('Model inputs'!S37="","",'Model inputs'!S37=0))="",FALSE,IF(ISERROR('Model inputs'!S37=0),'Model inputs'!S37=0,IF('Model inputs'!S37="","",'Model inputs'!S37=0))),IF('Model inputs'!B140="","",'Model inputs'!B140),IF('Model inputs'!R72="","",'Model inputs'!R72)) -> 444.86405 | T43: =IF(IF(IF(ISERROR('Model inputs'!T37=0),'Model inputs'!T37=0,IF('Model inputs'!T37="","",'Model inputs'!T37=0))="",FALSE,IF(ISERROR('Model inputs'!T37=0),'Model inputs'!T37=0,IF('Model inputs'!T37="","",'Model inputs'!T37=0))),IF('Model inputs'!B140="","",'Model inputs'!B140),IF('Model inputs'!S72="","",'Model inputs'!S72)) -> 473.84362
A44: Opening customers > Launch | C44: =IF(IF(IF(ISERROR('Model inputs'!C37=0),'Model inputs'!C37=0,IF('Model inputs'!C37="","",'Model inputs'!C37=0))="",FALSE,IF(ISERROR('Model inputs'!C37=0),'Model inputs'!C37=0,IF('Model inputs'!C37="","",'Model inputs'!C37=0))),IF('Model inputs'!B141="","",'Model inputs'!B141),IF('Model inputs'!AG91="","",'Model inputs'!AG91)) -> 1 | D44: =IF(IF(IF(ISERROR('Model inputs'!D37=0),'Model inputs'!D37=0,IF('Model inputs'!D37="","",'Model inputs'!D37=0))="",FALSE,IF(ISERROR('Model inputs'!D37=0),'Model inputs'!D37=0,IF('Model inputs'!D37="","",'Model inputs'!D37=0))),IF('Model inputs'!B141="","",'Model inputs'!B141),IF('Model inputs'!C73="","",'Model inputs'!C73)) -> 1 | E44: =IF(IF(IF(ISERROR('Model inputs'!E37=0),'Model inputs'!E37=0,IF('Model inputs'!E37="","",'Model inputs'!E37=0))="",FALSE,IF(ISERROR('Model inputs'!E37=0),'Model inputs'!E37=0,IF('Model inputs'!E37="","",'Model inputs'!E37=0))),IF('Model inputs'!B141="","",'Model inputs'!B141),IF('Model inputs'!D73="","",'Model inputs'!D73)) -> 1.51 | F44: =IF(IF(IF(ISERROR('Model inputs'!F37=0),'Model inputs'!F37=0,IF('Model inputs'!F37="","",'Model inputs'!F37=0))="",FALSE,IF(ISERROR('Model inputs'!F37=0),'Model inputs'!F37=0,IF('Model inputs'!F37="","",'Model inputs'!F37=0))),IF('Model inputs'!B141="","",'Model inputs'!B141),IF('Model inputs'!E73="","",'Model inputs'!E73)) -> 2.0251069 | G44: =IF(IF(IF(ISERROR('Model inputs'!G37=0),'Model inputs'!G37=0,IF('Model inputs'!G37="","",'Model inputs'!G37=0))="",FALSE,IF(ISERROR('Model inputs'!G37=0),'Model inputs'!G37=0,IF('Model inputs'!G37="","",'Model inputs'!G37=0))),IF('Model inputs'!B141="","",'Model inputs'!B141),IF('Model inputs'!F73="","",'Model inputs'!F73)) -> 2.5470121 | H44: =IF(IF(IF(ISERROR('Model inputs'!H37=0),'Model inputs'!H37=0,IF('Model inputs'!H37="","",'Model inputs'!H37=0))="",FALSE,IF(ISERROR('Model inputs'!H37=0),'Model inputs'!H37=0,IF('Model inputs'!H37="","",'Model inputs'!H37=0))),IF('Model inputs'!B141="","",'Model inputs'!B141),IF('Model inputs'!G73="","",'Model inputs'!G73)) -> 3.0771045 | I44: =IF(IF(IF(ISERROR('Model inputs'!I37=0),'Model inputs'!I37=0,IF('Model inputs'!I37="","",'Model inputs'!I37=0))="",FALSE,IF(ISERROR('Model inputs'!I37=0),'Model inputs'!I37=0,IF('Model inputs'!I37="","",'Model inputs'!I37=0))),IF('Model inputs'!B141="","",'Model inputs'!B141),IF('Model inputs'!H73="","",'Model inputs'!H73)) -> 3.6168582 | J44: =IF(IF(IF(ISERROR('Model inputs'!J37=0),'Model inputs'!J37=0,IF('Model inputs'!J37="","",'Model inputs'!J37=0))="",FALSE,IF(ISERROR('Model inputs'!J37=0),'Model inputs'!J37=0,IF('Model inputs'!J37="","",'Model inputs'!J37=0))),IF('Model inputs'!B141="","",'Model inputs'!B141),IF('Model inputs'!I73="","",'Model inputs'!I73)) -> 4.1678445 | K44: =IF(IF(IF(ISERROR('Model inputs'!K37=0),'Model inputs'!K37=0,IF('Model inputs'!K37="","",'Model inputs'!K37=0))="",FALSE,IF(ISERROR('Model inputs'!K37=0),'Model inputs'!K37=0,IF('Model inputs'!K37="","",'Model inputs'!K37=0))),IF('Model inputs'!B141="","",'Model inputs'!B141),IF('Model inputs'!J73="","",'Model inputs'!J73)) -> 4.7317452 | L44: =IF(IF(IF(ISERROR('Model inputs'!L37=0),'Model inputs'!L37=0,IF('Model inputs'!L37="","",'Model inputs'!L37=0))="",FALSE,IF(ISERROR('Model inputs'!L37=0),'Model inputs'!L37=0,IF('Model inputs'!L37="","",'Model inputs'!L37=0))),IF('Model inputs'!B141="","",'Model inputs'!B141),IF('Model inputs'!K73="","",'Model inputs'!K73)) -> 5.3103669 | M44: =IF(IF(IF(ISERROR('Model inputs'!M37=0),'Model inputs'!M37=0,IF('Model inputs'!M37="","",'Model inputs'!M37=0))="",FALSE,IF(ISERROR('Model inputs'!M37=0),'Model inputs'!M37=0,IF('Model inputs'!M37="","",'Model inputs'!M37=0))),IF('Model inputs'!B141="","",'Model inputs'!B141),IF('Model inputs'!L73="","",'Model inputs'!L73)) -> 5.9056563 | N44: =IF(IF(IF(ISERROR('Model inputs'!N37=0),'Model inputs'!N37=0,IF('Model inputs'!N37="","",'Model inputs'!N37=0))="",FALSE,IF(ISERROR('Model inputs'!N37=0),'Model inputs'!N37=0,IF('Model inputs'!N37="","",'Model inputs'!N37=0))),IF('Model inputs'!B141="","",'Model inputs'!B141),IF('Model inputs'!M73="","",'Model inputs'!M73)) -> 6.5182553 | O44: =IF(IF(IF(ISERROR('Model inputs'!O37=0),'Model inputs'!O37=0,IF('Model inputs'!O37="","",'Model inputs'!O37=0))="",FALSE,IF(ISERROR('Model inputs'!O37=0),'Model inputs'!O37=0,IF('Model inputs'!O37="","",'Model inputs'!O37=0))),IF('Model inputs'!B141="","",'Model inputs'!B141),IF('Model inputs'!N73="","",'Model inputs'!N73)) -> 7.1487999 | P44: =IF(IF(IF(ISERROR('Model inputs'!P37=0),'Model inputs'!P37=0,IF('Model inputs'!P37="","",'Model inputs'!P37=0))="",FALSE,IF(ISERROR('Model inputs'!P37=0),'Model inputs'!P37=0,IF('Model inputs'!P37="","",'Model inputs'!P37=0))),IF('Model inputs'!B141="","",'Model inputs'!B141),IF('Model inputs'!O73="","",'Model inputs'!O73)) -> 7.7979243 | Q44: =IF(IF(IF(ISERROR('Model inputs'!Q37=0),'Model inputs'!Q37=0,IF('Model inputs'!Q37="","",'Model inputs'!Q37=0))="",FALSE,IF(ISERROR('Model inputs'!Q37=0),'Model inputs'!Q37=0,IF('Model inputs'!Q37="","",'Model inputs'!Q37=0))),IF('Model inputs'!B141="","",'Model inputs'!B141),IF('Model inputs'!P73="","",'Model inputs'!P73)) -> 8.466264 | R44: =IF(IF(IF(ISERROR('Model inputs'!R37=0),'Model inputs'!R37=0,IF('Model inputs'!R37="","",'Model inputs'!R37=0))="",FALSE,IF(ISERROR('Model inputs'!R37=0),'Model inputs'!R37=0,IF('Model inputs'!R37="","",'Model inputs'!R37=0))),IF('Model inputs'!B141="","",'Model inputs'!B141),IF('Model inputs'!Q73="","",'Model inputs'!Q73)) -> 9.1544595 | S44: =IF(IF(IF(ISERROR('Model inputs'!S37=0),'Model inputs'!S37=0,IF('Model inputs'!S37="","",'Model inputs'!S37=0))="",FALSE,IF(ISERROR('Model inputs'!S37=0),'Model inputs'!S37=0,IF('Model inputs'!S37="","",'Model inputs'!S37=0))),IF('Model inputs'!B141="","",'Model inputs'!B141),IF('Model inputs'!R73="","",'Model inputs'!R73)) -> 9.8631592 | T44: =IF(IF(IF(ISERROR('Model inputs'!T37=0),'Model inputs'!T37=0,IF('Model inputs'!T37="","",'Model inputs'!T37=0))="",FALSE,IF(ISERROR('Model inputs'!T37=0),'Model inputs'!T37=0,IF('Model inputs'!T37="","",'Model inputs'!T37=0))),IF('Model inputs'!B141="","",'Model inputs'!B141),IF('Model inputs'!S73="","",'Model inputs'!S73)) -> 10.593023
A45: Opening customers > Team | C45: =IF(IF(IF(ISERROR('Model inputs'!C37=0),'Model inputs'!C37=0,IF('Model inputs'!C37="","",'Model inputs'!C37=0))="",FALSE,IF(ISERROR('Model inputs'!C37=0),'Model inputs'!C37=0,IF('Model inputs'!C37="","",'Model inputs'!C37=0))),IF('Model inputs'!B142="","",'Model inputs'!B142),IF('Model inputs'!AG92="","",'Model inputs'!AG92)) -> 6 | D45: =IF(IF(IF(ISERROR('Model inputs'!D37=0),'Model inputs'!D37=0,IF('Model inputs'!D37="","",'Model inputs'!D37=0))="",FALSE,IF(ISERROR('Model inputs'!D37=0),'Model inputs'!D37=0,IF('Model inputs'!D37="","",'Model inputs'!D37=0))),IF('Model inputs'!B142="","",'Model inputs'!B142),IF('Model inputs'!C74="","",'Model inputs'!C74)) -> 6 | E45: =IF(IF(IF(ISERROR('Model inputs'!E37=0),'Model inputs'!E37=0,IF('Model inputs'!E37="","",'Model inputs'!E37=0))="",FALSE,IF(ISERROR('Model inputs'!E37=0),'Model inputs'!E37=0,IF('Model inputs'!E37="","",'Model inputs'!E37=0))),IF('Model inputs'!B142="","",'Model inputs'!B142),IF('Model inputs'!D74="","",'Model inputs'!D74)) -> 9.0616667 | F45: =IF(IF(IF(ISERROR('Model inputs'!F37=0),'Model inputs'!F37=0,IF('Model inputs'!F37="","",'Model inputs'!F37=0))="",FALSE,IF(ISERROR('Model inputs'!F37=0),'Model inputs'!F37=0,IF('Model inputs'!F37="","",'Model inputs'!F37=0))),IF('Model inputs'!B142="","",'Model inputs'!B142),IF('Model inputs'!E74="","",'Model inputs'!E74)) -> 12.547615 | G45: =IF(IF(IF(ISERROR('Model inputs'!G37=0),'Model inputs'!G37=0,IF('Model inputs'!G37="","",'Model inputs'!G37=0))="",FALSE,IF(ISERROR('Model inputs'!G37=0),'Model inputs'!G37=0,IF('Model inputs'!G37="","",'Model inputs'!G37=0))),IF('Model inputs'!B142="","",'Model inputs'!B142),IF('Model inputs'!F74="","",'Model inputs'!F74)) -> 16.391424 | H45: =IF(IF(IF(ISERROR('Model inputs'!H37=0),'Model inputs'!H37=0,IF('Model inputs'!H37="","",'Model inputs'!H37=0))="",FALSE,IF(ISERROR('Model inputs'!H37=0),'Model inputs'!H37=0,IF('Model inputs'!H37="","",'Model inputs'!H37=0))),IF('Model inputs'!B142="","",'Model inputs'!B142),IF('Model inputs'!G74="","",'Model inputs'!G74)) -> 20.618467 | I45: =IF(IF(IF(ISERROR('Model inputs'!I37=0),'Model inputs'!I37=0,IF('Model inputs'!I37="","",'Model inputs'!I37=0))="",FALSE,IF(ISERROR('Model inputs'!I37=0),'Model inputs'!I37=0,IF('Model inputs'!I37="","",'Model inputs'!I37=0))),IF('Model inputs'!B142="","",'Model inputs'!B142),IF('Model inputs'!H74="","",'Model inputs'!H74)) -> 25.2574 | J45: =IF(IF(IF(ISERROR('Model inputs'!J37=0),'Model inputs'!J37=0,IF('Model inputs'!J37="","",'Model inputs'!J37=0))="",FALSE,IF(ISERROR('Model inputs'!J37=0),'Model inputs'!J37=0,IF('Model inputs'!J37="","",'Model inputs'!J37=0))),IF('Model inputs'!B142="","",'Model inputs'!B142),IF('Model inputs'!I74="","",'Model inputs'!I74)) -> 30.340408 | K45: =IF(IF(IF(ISERROR('Model inputs'!K37=0),'Model inputs'!K37=0,IF('Model inputs'!K37="","",'Model inputs'!K37=0))="",FALSE,IF(ISERROR('Model inputs'!K37=0),'Model inputs'!K37=0,IF('Model inputs'!K37="","",'Model inputs'!K37=0))),IF('Model inputs'!B142="","",'Model inputs'!B142),IF('Model inputs'!J74="","",'Model inputs'!J74)) -> 35.903491 | L45: =IF(IF(IF(ISERROR('Model inputs'!L37=0),'Model inputs'!L37=0,IF('Model inputs'!L37="","",'Model inputs'!L37=0))="",FALSE,IF(ISERROR('Model inputs'!L37=0),'Model inputs'!L37=0,IF('Model inputs'!L37="","",'Model inputs'!L37=0))),IF('Model inputs'!B142="","",'Model inputs'!B142),IF('Model inputs'!K74="","",'Model inputs'!K74)) -> 41.986781 | M45: =IF(IF(IF(ISERROR('Model inputs'!M37=0),'Model inputs'!M37=0,IF('Model inputs'!M37="","",'Model inputs'!M37=0))="",FALSE,IF(ISERROR('Model inputs'!M37=0),'Model inputs'!M37=0,IF('Model inputs'!M37="","",'Model inputs'!M37=0))),IF('Model inputs'!B142="","",'Model inputs'!B142),IF('Model inputs'!L74="","",'Model inputs'!L74)) -> 48.284119 | N45: =IF(IF(IF(ISERROR('Model inputs'!N37=0),'Model inputs'!N37=0,IF('Model inputs'!N37="","",'Model inputs'!N37=0))="",FALSE,IF(ISERROR('Model inputs'!N37=0),'Model inputs'!N37=0,IF('Model inputs'!N37="","",'Model inputs'!N37=0))),IF('Model inputs'!B142="","",'Model inputs'!B142),IF('Model inputs'!M74="","",'Model inputs'!M74)) -> 54.796435 | O45: =IF(IF(IF(ISERROR('Model inputs'!O37=0),'Model inputs'!O37=0,IF('Model inputs'!O37="","",'Model inputs'!O37=0))="",FALSE,IF(ISERROR('Model inputs'!O37=0),'Model inputs'!O37=0,IF('Model inputs'!O37="","",'Model inputs'!O37=0))),IF('Model inputs'!B142="","",'Model inputs'!B142),IF('Model inputs'!N74="","",'Model inputs'!N74)) -> 61.525531 | P45: =IF(IF(IF(ISERROR('Model inputs'!P37=0),'Model inputs'!P37=0,IF('Model inputs'!P37="","",'Model inputs'!P37=0))="",FALSE,IF(ISERROR('Model inputs'!P37=0),'Model inputs'!P37=0,IF('Model inputs'!P37="","",'Model inputs'!P37=0))),IF('Model inputs'!B142="","",'Model inputs'!B142),IF('Model inputs'!O74="","",'Model inputs'!O74)) -> 68.474053 | Q45: =IF(IF(IF(ISERROR('Model inputs'!Q37=0),'Model inputs'!Q37=0,IF('Model inputs'!Q37="","",'Model inputs'!Q37=0))="",FALSE,IF(ISERROR('Model inputs'!Q37=0),'Model inputs'!Q37=0,IF('Model inputs'!Q37="","",'Model inputs'!Q37=0))),IF('Model inputs'!B142="","",'Model inputs'!B142),IF('Model inputs'!P74="","",'Model inputs'!P74)) -> 75.645458 | R45: =IF(IF(IF(ISERROR('Model inputs'!R37=0),'Model inputs'!R37=0,IF('Model inputs'!R37="","",'Model inputs'!R37=0))="",FALSE,IF(ISERROR('Model inputs'!R37=0),'Model inputs'!R37=0,IF('Model inputs'!R37="","",'Model inputs'!R37=0))),IF('Model inputs'!B142="","",'Model inputs'!B142),IF('Model inputs'!Q74="","",'Model inputs'!Q74)) -> 83.04399 | S45: =IF(IF(IF(ISERROR('Model inputs'!S37=0),'Model inputs'!S37=0,IF('Model inputs'!S37="","",'Model inputs'!S37=0))="",FALSE,IF(ISERROR('Model inputs'!S37=0),'Model inputs'!S37=0,IF('Model inputs'!S37="","",'Model inputs'!S37=0))),IF('Model inputs'!B142="","",'Model inputs'!B142),IF('Model inputs'!R74="","",'Model inputs'!R74)) -> 90.674663 | T45: =IF(IF(IF(ISERROR('Model inputs'!T37=0),'Model inputs'!T37=0,IF('Model inputs'!T37="","",'Model inputs'!T37=0))="",FALSE,IF(ISERROR('Model inputs'!T37=0),'Model inputs'!T37=0,IF('Model inputs'!T37="","",'Model inputs'!T37=0))),IF('Model inputs'!B142="","",'Model inputs'!B142),IF('Model inputs'!S74="","",'Model inputs'!S74)) -> 98.543234
A46: Optimized COGS per kit | B46: =0.16 -> 0.16
A47: Organic new logos | C47: =SUM('Model inputs'!C48,'Model inputs'!C49,'Model inputs'!C50) -> 0 | D47: =SUM('Model inputs'!D48,'Model inputs'!D49,'Model inputs'!D50) -> 28.5 | E47: =SUM('Model inputs'!E48,'Model inputs'!E49,'Model inputs'!E50) -> 30.8 | F47: =SUM('Model inputs'!F48,'Model inputs'!F49,'Model inputs'!F50) -> 33.29 | G47: =SUM('Model inputs'!G48,'Model inputs'!G49,'Model inputs'!G50) -> 35.9858 | H47: =SUM('Model inputs'!H48,'Model inputs'!H49,'Model inputs'!H50) -> 38.904524 | I47: =SUM('Model inputs'!I48,'Model inputs'!I49,'Model inputs'!I50) -> 42.064732 | J47: =SUM('Model inputs'!J48,'Model inputs'!J49,'Model inputs'!J50) -> 45.486541 | ... T47: =SUM('Model inputs'!T48,'Model inputs'!T49,'Model inputs'!T50) -> 69.803554
A48: Organic new logos > Indie | C48: =IF(IF(IF(ISERROR('Model inputs'!C37<1),'Model inputs'!C37<1,IF('Model inputs'!C37="","",'Model inputs'!C37<1))="",FALSE,IF(ISERROR('Model inputs'!C37<1),'Model inputs'!C37<1,IF('Model inputs'!C37="","",'Model inputs'!C37<1))),0,IF(IF(IF(ISERROR('Model inputs'!C37=1),'Model inputs'!C37=1,IF('Model inputs'!C37="","",'Model inputs'!C37=1))="",FALSE,IF(ISERROR('Model inputs'!C37=1),'Model inputs'!C37=1,IF('Model inputs'!C37="","",'Model inputs'!C37=1))),IF('Model inputs'!B119="","",'Model inputs'!B119),'Model inputs'!AG127*(1+IF(IF(IF(IF(ISERROR('Model inputs'!C37<=8),'Model inputs'!C37<=8,IF('Model inputs'!C37="","",'Model inputs'!C37<=8))="",FALSE,IF(ISERROR('Model inputs'!C37<=8),'Model inputs'!C37<=8,IF('Model inputs'!C37="","",'Model inputs'!C37<=8))),IF('Model inputs'!B109="","",'Model inputs'!B109),IF('Model inputs'!B105="","",'Model inputs'!B105))="",0,IF(IF(IF(ISERROR('Model inputs'!C37<=8),'Model inputs'!C37<=8,IF('Model inputs'!C37="","",'Model inputs'!C37<=8))="",FALSE,IF(ISERROR('Model inputs'!C37<=8),'Model inputs'!C37<=8,IF('Model inputs'!C37="","",'Model inputs'!C37<=8))),IF('Model inputs'!B109="","",'Model inputs'!B109),IF('Model inputs'!B105="","",'Model inputs'!B105)))))) -> 0 | D48: =IF(IF(IF(ISERROR('Model inputs'!D37<1),'Model inputs'!D37<1,IF('Model inputs'!D37="","",'Model inputs'!D37<1))="",FALSE,IF(ISERROR('Model inputs'!D37<1),'Model inputs'!D37<1,IF('Model inputs'!D37="","",'Model inputs'!D37<1))),0,IF(IF(IF(ISERROR('Model inputs'!D37=1),'Model inputs'!D37=1,IF('Model inputs'!D37="","",'Model inputs'!D37=1))="",FALSE,IF(ISERROR('Model inputs'!D37=1),'Model inputs'!D37=1,IF('Model inputs'!D37="","",'Model inputs'!D37=1))),IF('Model inputs'!B119="","",'Model inputs'!B119),'Model inputs'!C48*(1+IF(IF(IF(IF(ISERROR('Model inputs'!D37<=8),'Model inputs'!D37<=8,IF('Model inputs'!D37="","",'Model inputs'!D37<=8))="",FALSE,IF(ISERROR('Model inputs'!D37<=8),'Model inputs'!D37<=8,IF('Model inputs'!D37="","",'Model inputs'!D37<=8))),IF('Model inputs'!B109="","",'Model inputs'!B109),IF('Model inputs'!B105="","",'Model inputs'!B105))="",0,IF(IF(IF(ISERROR('Model inputs'!D37<=8),'Model inputs'!D37<=8,IF('Model inputs'!D37="","",'Model inputs'!D37<=8))="",FALSE,IF(ISERROR('Model inputs'!D37<=8),'Model inputs'!D37<=8,IF('Model inputs'!D37="","",'Model inputs'!D37<=8))),IF('Model inputs'!B109="","",'Model inputs'!B109),IF('Model inputs'!B105="","",'Model inputs'!B105)))))) -> 25 | E48: =IF(IF(IF(ISERROR('Model inputs'!E37<1),'Model inputs'!E37<1,IF('Model inputs'!E37="","",'Model inputs'!E37<1))="",FALSE,IF(ISERROR('Model inputs'!E37<1),'Model inputs'!E37<1,IF('Model inputs'!E37="","",'Model inputs'!E37<1))),0,IF(IF(IF(ISERROR('Model inputs'!E37=1),'Model inputs'!E37=1,IF('Model inputs'!E37="","",'Model inputs'!E37=1))="",FALSE,IF(ISERROR('Model inputs'!E37=1),'Model inputs'!E37=1,IF('Model inputs'!E37="","",'Model inputs'!E37=1))),IF('Model inputs'!B119="","",'Model inputs'!B119),'Model inputs'!D48*(1+IF(IF(IF(IF(ISERROR('Model inputs'!E37<=8),'Model inputs'!E37<=8,IF('Model inputs'!E37="","",'Model inputs'!E37<=8))="",FALSE,IF(ISERROR('Model inputs'!E37<=8),'Model inputs'!E37<=8,IF('Model inputs'!E37="","",'Model inputs'!E37<=8))),IF('Model inputs'!B109="","",'Model inputs'!B109),IF('Model inputs'!B105="","",'Model inputs'!B105))="",0,IF(IF(IF(ISERROR('Model inputs'!E37<=8),'Model inputs'!E37<=8,IF('Model inputs'!E37="","",'Model inputs'!E37<=8))="",FALSE,IF(ISERROR('Model inputs'!E37<=8),'Model inputs'!E37<=8,IF('Model inputs'!E37="","",'Model inputs'!E37<=8))),IF('Model inputs'!B109="","",'Model inputs'!B109),IF('Model inputs'!B105="","",'Model inputs'!B105)))))) -> 27 | F48: =IF(IF(IF(ISERROR('Model inputs'!F37<1),'Model inputs'!F37<1,IF('Model inputs'!F37="","",'Model inputs'!F37<1))="",FALSE,IF(ISERROR('Model inputs'!F37<1),'Model inputs'!F37<1,IF('Model inputs'!F37="","",'Model inputs'!F37<1))),0,IF(IF(IF(ISERROR('Model inputs'!F37=1),'Model inputs'!F37=1,IF('Model inputs'!F37="","",'Model inputs'!F37=1))="",FALSE,IF(ISERROR('Model inputs'!F37=1),'Model inputs'!F37=1,IF('Model inputs'!F37="","",'Model inputs'!F37=1))),IF('Model inputs'!B119="","",'Model inputs'!B119),'Model inputs'!E48*(1+IF(IF(IF(IF(ISERROR('Model inputs'!F37<=8),'Model inputs'!F37<=8,IF('Model inputs'!F37="","",'Model inputs'!F37<=8))="",FALSE,IF(ISERROR('Model inputs'!F37<=8),'Model inputs'!F37<=8,IF('Model inputs'!F37="","",'Model inputs'!F37<=8))),IF('Model inputs'!B109="","",'Model inputs'!B109),IF('Model inputs'!B105="","",'Model inputs'!B105))="",0,IF(IF(IF(ISERROR('Model inputs'!F37<=8),'Model inputs'!F37<=8,IF('Model inputs'!F37="","",'Model inputs'!F37<=8))="",FALSE,IF(ISERROR('Model inputs'!F37<=8),'Model inputs'!F37<=8,IF('Model inputs'!F37="","",'Model inputs'!F37<=8))),IF('Model inputs'!B109="","",'Model inputs'!B109),IF('Model inputs'!B105="","",'Model inputs'!B105)))))) -> 29.16 | G48: =IF(IF(IF(ISERROR('Model inputs'!G37<1),'Model inputs'!G37<1,IF('Model inputs'!G37="","",'Model inputs'!G37<1))="",FALSE,IF(ISERROR('Model inputs'!G37<1),'Model inputs'!G37<1,IF('Model inputs'!G37="","",'Model inputs'!G37<1))),0,IF(IF(IF(ISERROR('Model inputs'!G37=1),'Model inputs'!G37=1,IF('Model inputs'!G37="","",'Model inputs'!G37=1))="",FALSE,IF(ISERROR('Model inputs'!G37=1),'Model inputs'!G37=1,IF('Model inputs'!G37="","",'Model inputs'!G37=1))),IF('Model inputs'!B119="","",'Model inputs'!B119),'Model inputs'!F48*(1+IF(IF(IF(IF(ISERROR('Model inputs'!G37<=8),'Model inputs'!G37<=8,IF('Model inputs'!G37="","",'Model inputs'!G37<=8))="",FALSE,IF(ISERROR('Model inputs'!G37<=8),'Model inputs'!G37<=8,IF('Model inputs'!G37="","",'Model inputs'!G37<=8))),IF('Model inputs'!B109="","",'Model inputs'!B109),IF('Model inputs'!B105="","",'Model inputs'!B105))="",0,IF(IF(IF(ISERROR('Model inputs'!G37<=8),'Model inputs'!G37<=8,IF('Model inputs'!G37="","",'Model inputs'!G37<=8))="",FALSE,IF(ISERROR('Model inputs'!G37<=8),'Model inputs'!G37<=8,IF('Model inputs'!G37="","",'Model inputs'!G37<=8))),IF('Model inputs'!B109="","",'Model inputs'!B109),IF('Model inputs'!B105="","",'Model inputs'!B105)))))) -> 31.4928 | H48: =IF(IF(IF(ISERROR('Model inputs'!H37<1),'Model inputs'!H37<1,IF('Model inputs'!H37="","",'Model inputs'!H37<1))="",FALSE,IF(ISERROR('Model inputs'!H37<1),'Model inputs'!H37<1,IF('Model inputs'!H37="","",'Model inputs'!H37<1))),0,IF(IF(IF(ISERROR('Model inputs'!H37=1),'Model inputs'!H37=1,IF('Model inputs'!H37="","",'Model inputs'!H37=1))="",FALSE,IF(ISERROR('Model inputs'!H37=1),'Model inputs'!H37=1,IF('Model inputs'!H37="","",'Model inputs'!H37=1))),IF('Model inputs'!B119="","",'Model inputs'!B119),'Model inputs'!G48*(1+IF(IF(IF(IF(ISERROR('Model inputs'!H37<=8),'Model inputs'!H37<=8,IF('Model inputs'!H37="","",'Model inputs'!H37<=8))="",FALSE,IF(ISERROR('Model inputs'!H37<=8),'Model inputs'!H37<=8,IF('Model inputs'!H37="","",'Model inputs'!H37<=8))),IF('Model inputs'!B109="","",'Model inputs'!B109),IF('Model inputs'!B105="","",'Model inputs'!B105))="",0,IF(IF(IF(ISERROR('Model inputs'!H37<=8),'Model inputs'!H37<=8,IF('Model inputs'!H37="","",'Model inputs'!H37<=8))="",FALSE,IF(ISERROR('Model inputs'!H37<=8),'Model inputs'!H37<=8,IF('Model inputs'!H37="","",'Model inputs'!H37<=8))),IF('Model inputs'!B109="","",'Model inputs'!B109),IF('Model inputs'!B105="","",'Model inputs'!B105)))))) -> 34.012224 | I48: =IF(IF(IF(ISERROR('Model inputs'!I37<1),'Model inputs'!I37<1,IF('Model inputs'!I37="","",'Model inputs'!I37<1))="",FALSE,IF(ISERROR('Model inputs'!I37<1),'Model inputs'!I37<1,IF('Model inputs'!I37="","",'Model inputs'!I37<1))),0,IF(IF(IF(ISERROR('Model inputs'!I37=1),'Model inputs'!I37=1,IF('Model inputs'!I37="","",'Model inputs'!I37=1))="",FALSE,IF(ISERROR('Model inputs'!I37=1),'Model inputs'!I37=1,IF('Model inputs'!I37="","",'Model inputs'!I37=1))),IF('Model inputs'!B119="","",'Model inputs'!B119),'Model inputs'!H48*(1+IF(IF(IF(IF(ISERROR('Model inputs'!I37<=8),'Model inputs'!I37<=8,IF('Model inputs'!I37="","",'Model inputs'!I37<=8))="",FALSE,IF(ISERROR('Model inputs'!I37<=8),'Model inputs'!I37<=8,IF('Model inputs'!I37="","",'Model inputs'!I37<=8))),IF('Model inputs'!B109="","",'Model inputs'!B109),IF('Model inputs'!B105="","",'Model inputs'!B105))="",0,IF(IF(IF(ISERROR('Model inputs'!I37<=8),'Model inputs'!I37<=8,IF('Model inputs'!I37="","",'Model inputs'!I37<=8))="",FALSE,IF(ISERROR('Model inputs'!I37<=8),'Model inputs'!I37<=8,IF('Model inputs'!I37="","",'Model inputs'!I37<=8))),IF('Model inputs'!B109="","",'Model inputs'!B109),IF('Model inputs'!B105="","",'Model inputs'!B105)))))) -> 36.733202 | J48: =IF(IF(IF(ISERROR('Model inputs'!J37<1),'Model inputs'!J37<1,IF('Model inputs'!J37="","",'Model inputs'!J37<1))="",FALSE,IF(ISERROR('Model inputs'!J37<1),'Model inputs'!J37<1,IF('Model inputs'!J37="","",'Model inputs'!J37<1))),0,IF(IF(IF(ISERROR('Model inputs'!J37=1),'Model inputs'!J37=1,IF('Model inputs'!J37="","",'Model inputs'!J37=1))="",FALSE,IF(ISERROR('Model inputs'!J37=1),'Model inputs'!J37=1,IF('Model inputs'!J37="","",'Model inputs'!J37=1))),IF('Model inputs'!B119="","",'Model inputs'!B119),'Model inputs'!I48*(1+IF(IF(IF(IF(ISERROR('Model inputs'!J37<=8),'Model inputs'!J37<=8,IF('Model inputs'!J37="","",'Model inputs'!J37<=8))="",FALSE,IF(ISERROR('Model inputs'!J37<=8),'Model inputs'!J37<=8,IF('Model inputs'!J37="","",'Model inputs'!J37<=8))),IF('Model inputs'!B109="","",'Model inputs'!B109),IF('Model inputs'!B105="","",'Model inputs'!B105))="",0,IF(IF(IF(ISERROR('Model inputs'!J37<=8),'Model inputs'!J37<=8,IF('Model inputs'!J37="","",'Model inputs'!J37<=8))="",FALSE,IF(ISERROR('Model inputs'!J37<=8),'Model inputs'!J37<=8,IF('Model inputs'!J37="","",'Model inputs'!J37<=8))),IF('Model inputs'!B109="","",'Model inputs'!B109),IF('Model inputs'!B105="","",'Model inputs'!B105)))))) -> 39.671858 | K48: =IF(IF(IF(ISERROR('Model inputs'!K37<1),'Model inputs'!K37<1,IF('Model inputs'!K37="","",'Model inputs'!K37<1))="",FALSE,IF(ISERROR('Model inputs'!K37<1),'Model inputs'!K37<1,IF('Model inputs'!K37="","",'Model inputs'!K37<1))),0,IF(IF(IF(ISERROR('Model inputs'!K37=1),'Model inputs'!K37=1,IF('Model inputs'!K37="","",'Model inputs'!K37=1))="",FALSE,IF(ISERROR('Model inputs'!K37=1),'Model inputs'!K37=1,IF('Model inputs'!K37="","",'Model inputs'!K37=1))),IF('Model inputs'!B119="","",'Model inputs'!B119),'Model inputs'!J48*(1+IF(IF(IF(IF(ISERROR('Model inputs'!K37<=8),'Model inputs'!K37<=8,IF('Model inputs'!K37="","",'Model inputs'!K37<=8))="",FALSE,IF(ISERROR('Model inputs'!K37<=8),'Model inputs'!K37<=8,IF('Model inputs'!K37="","",'Model inputs'!K37<=8))),IF('Model inputs'!B109="","",'Model inputs'!B109),IF('Model inputs'!B105="","",'Model inputs'!B105))="",0,IF(IF(IF(ISERROR('Model inputs'!K37<=8),'Model inputs'!K37<=8,IF('Model inputs'!K37="","",'Model inputs'!K37<=8))="",FALSE,IF(ISERROR('Model inputs'!K37<=8),'Model inputs'!K37<=8,IF('Model inputs'!K37="","",'Model inputs'!K37<=8))),IF('Model inputs'!B109="","",'Model inputs'!B109),IF('Model inputs'!B105="","",'Model inputs'!B105)))))) -> 42.845607 | L48: =IF(IF(IF(ISERROR('Model inputs'!L37<1),'Model inputs'!L37<1,IF('Model inputs'!L37="","",'Model inputs'!L37<1))="",FALSE,IF(ISERROR('Model inputs'!L37<1),'Model inputs'!L37<1,IF('Model inputs'!L37="","",'Model inputs'!L37<1))),0,IF(IF(IF(ISERROR('Model inputs'!L37=1),'Model inputs'!L37=1,IF('Model inputs'!L37="","",'Model inputs'!L37=1))="",FALSE,IF(ISERROR('Model inputs'!L37=1),'Model inputs'!L37=1,IF('Model inputs'!L37="","",'Model inputs'!L37=1))),IF('Model inputs'!B119="","",'Model inputs'!B119),'Model inputs'!K48*(1+IF(IF(IF(IF(ISERROR('Model inputs'!L37<=8),'Model inputs'!L37<=8,IF('Model inputs'!L37="","",'Model inputs'!L37<=8))="",FALSE,IF(ISERROR('Model inputs'!L37<=8),'Model inputs'!L37<=8,IF('Model inputs'!L37="","",'Model inputs'!L37<=8))),IF('Model inputs'!B109="","",'Model inputs'!B109),IF('Model inputs'!B105="","",'Model inputs'!B105))="",0,IF(IF(IF(ISERROR('Model inputs'!L37<=8),'Model inputs'!L37<=8,IF('Model inputs'!L37="","",'Model inputs'!L37<=8))="",FALSE,IF(ISERROR('Model inputs'!L37<=8),'Model inputs'!L37<=8,IF('Model inputs'!L37="","",'Model inputs'!L37<=8))),IF('Model inputs'!B109="","",'Model inputs'!B109),IF('Model inputs'!B105="","",'Model inputs'!B105)))))) -> 44.559431 | M48: =IF(IF(IF(ISERROR('Model inputs'!M37<1),'Model inputs'!M37<1,IF('Model inputs'!M37="","",'Model inputs'!M37<1))="",FALSE,IF(ISERROR('Model inputs'!M37<1),'Model inputs'!M37<1,IF('Model inputs'!M37="","",'Model inputs'!M37<1))),0,IF(IF(IF(ISERROR('Model inputs'!M37=1),'Model inputs'!M37=1,IF('Model inputs'!M37="","",'Model inputs'!M37=1))="",FALSE,IF(ISERROR('Model inputs'!M37=1),'Model inputs'!M37=1,IF('Model inputs'!M37="","",'Model inputs'!M37=1))),IF('Model inputs'!B119="","",'Model inputs'!B119),'Model inputs'!L48*(1+IF(IF(IF(IF(ISERROR('Model inputs'!M37<=8),'Model inputs'!M37<=8,IF('Model inputs'!M37="","",'Model inputs'!M37<=8))="",FALSE,IF(ISERROR('Model inputs'!M37<=8),'Model inputs'!M37<=8,IF('Model inputs'!M37="","",'Model inputs'!M37<=8))),IF('Model inputs'!B109="","",'Model inputs'!B109),IF('Model inputs'!B105="","",'Model inputs'!B105))="",0,IF(IF(IF(ISERROR('Model inputs'!M37<=8),'Model inputs'!M37<=8,IF('Model inputs'!M37="","",'Model inputs'!M37<=8))="",FALSE,IF(ISERROR('Model inputs'!M37<=8),'Model inputs'!M37<=8,IF('Model inputs'!M37="","",'Model inputs'!M37<=8))),IF('Model inputs'!B109="","",'Model inputs'!B109),IF('Model inputs'!B105="","",'Model inputs'!B105)))))) -> 46.341808 | N48: =IF(IF(IF(ISERROR('Model inputs'!N37<1),'Model inputs'!N37<1,IF('Model inputs'!N37="","",'Model inputs'!N37<1))="",FALSE,IF(ISERROR('Model inputs'!N37<1),'Model inputs'!N37<1,IF('Model inputs'!N37="","",'Model inputs'!N37<1))),0,IF(IF(IF(ISERROR('Model inputs'!N37=1),'Model inputs'!N37=1,IF('Model inputs'!N37="","",'Model inputs'!N37=1))="",FALSE,IF(ISERROR('Model inputs'!N37=1),'Model inputs'!N37=1,IF('Model inputs'!N37="","",'Model inputs'!N37=1))),IF('Model inputs'!B119="","",'Model inputs'!B119),'Model inputs'!M48*(1+IF(IF(IF(IF(ISERROR('Model inputs'!N37<=8),'Model inputs'!N37<=8,IF('Model inputs'!N37="","",'Model inputs'!N37<=8))="",FALSE,IF(ISERROR('Model inputs'!N37<=8),'Model inputs'!N37<=8,IF('Model inputs'!N37="","",'Model inputs'!N37<=8))),IF('Model inputs'!B109="","",'Model inputs'!B109),IF('Model inputs'!B105="","",'Model inputs'!B105))="",0,IF(IF(IF(ISERROR('Model inputs'!N37<=8),'Model inputs'!N37<=8,IF('Model inputs'!N37="","",'Model inputs'!N37<=8))="",FALSE,IF(ISERROR('Model inputs'!N37<=8),'Model inputs'!N37<=8,IF('Model inputs'!N37="","",'Model inputs'!N37<=8))),IF('Model inputs'!B109="","",'Model inputs'!B109),IF('Model inputs'!B105="","",'Model inputs'!B105)))))) -> 48.195481 | O48: =IF(IF(IF(ISERROR('Model inputs'!O37<1),'Model inputs'!O37<1,IF('Model inputs'!O37="","",'Model inputs'!O37<1))="",FALSE,IF(ISERROR('Model inputs'!O37<1),'Model inputs'!O37<1,IF('Model inputs'!O37="","",'Model inputs'!O37<1))),0,IF(IF(IF(ISERROR('Model inputs'!O37=1),'Model inputs'!O37=1,IF('Model inputs'!O37="","",'Model inputs'!O37=1))="",FALSE,IF(ISERROR('Model inputs'!O37=1),'Model inputs'!O37=1,IF('Model inputs'!O37="","",'Model inputs'!O37=1))),IF('Model inputs'!B119="","",'Model inputs'!B119),'Model inputs'!N48*(1+IF(IF(IF(IF(ISERROR('Model inputs'!O37<=8),'Model inputs'!O37<=8,IF('Model inputs'!O37="","",'Model inputs'!O37<=8))="",FALSE,IF(ISERROR('Model inputs'!O37<=8),'Model inputs'!O37<=8,IF('Model inputs'!O37="","",'Model inputs'!O37<=8))),IF('Model inputs'!B109="","",'Model inputs'!B109),IF('Model inputs'!B105="","",'Model inputs'!B105))="",0,IF(IF(IF(ISERROR('Model inputs'!O37<=8),'Model inputs'!O37<=8,IF('Model inputs'!O37="","",'Model inputs'!O37<=8))="",FALSE,IF(ISERROR('Model inputs'!O37<=8),'Model inputs'!O37<=8,IF('Model inputs'!O37="","",'Model inputs'!O37<=8))),IF('Model inputs'!B109="","",'Model inputs'!B109),IF('Model inputs'!B105="","",'Model inputs'!B105)))))) -> 50.1233 | P48: =IF(IF(IF(ISERROR('Model inputs'!P37<1),'Model inputs'!P37<1,IF('Model inputs'!P37="","",'Model inputs'!P37<1))="",FALSE,IF(ISERROR('Model inputs'!P37<1),'Model inputs'!P37<1,IF('Model inputs'!P37="","",'Model inputs'!P37<1))),0,IF(IF(IF(ISERROR('Model inputs'!P37=1),'Model inputs'!P37=1,IF('Model inputs'!P37="","",'Model inputs'!P37=1))="",FALSE,IF(ISERROR('Model inputs'!P37=1),'Model inputs'!P37=1,IF('Model inputs'!P37="","",'Model inputs'!P37=1))),IF('Model inputs'!B119="","",'Model inputs'!B119),'Model inputs'!O48*(1+IF(IF(IF(IF(ISERROR('Model inputs'!P37<=8),'Model inputs'!P37<=8,IF('Model inputs'!P37="","",'Model inputs'!P37<=8))="",FALSE,IF(ISERROR('Model inputs'!P37<=8),'Model inputs'!P37<=8,IF('Model inputs'!P37="","",'Model inputs'!P37<=8))),IF('Model inputs'!B109="","",'Model inputs'!B109),IF('Model inputs'!B105="","",'Model inputs'!B105))="",0,IF(IF(IF(ISERROR('Model inputs'!P37<=8),'Model inputs'!P37<=8,IF('Model inputs'!P37="","",'Model inputs'!P37<=8))="",FALSE,IF(ISERROR('Model inputs'!P37<=8),'Model inputs'!P37<=8,IF('Model inputs'!P37="","",'Model inputs'!P37<=8))),IF('Model inputs'!B109="","",'Model inputs'!B109),IF('Model inputs'!B105="","",'Model inputs'!B105)))))) -> 52.128232 | Q48: =IF(IF(IF(ISERROR('Model inputs'!Q37<1),'Model inputs'!Q37<1,IF('Model inputs'!Q37="","",'Model inputs'!Q37<1))="",FALSE,IF(ISERROR('Model inputs'!Q37<1),'Model inputs'!Q37<1,IF('Model inputs'!Q37="","",'Model inputs'!Q37<1))),0,IF(IF(IF(ISERROR('Model inputs'!Q37=1),'Model inputs'!Q37=1,IF('Model inputs'!Q37="","",'Model inputs'!Q37=1))="",FALSE,IF(ISERROR('Model inputs'!Q37=1),'Model inputs'!Q37=1,IF('Model inputs'!Q37="","",'Model inputs'!Q37=1))),IF('Model inputs'!B119="","",'Model inputs'!B119),'Model inputs'!P48*(1+IF(IF(IF(IF(ISERROR('Model inputs'!Q37<=8),'Model inputs'!Q37<=8,IF('Model inputs'!Q37="","",'Model inputs'!Q37<=8))="",FALSE,IF(ISERROR('Model inputs'!Q37<=8),'Model inputs'!Q37<=8,IF('Model inputs'!Q37="","",'Model inputs'!Q37<=8))),IF('Model inputs'!B109="","",'Model inputs'!B109),IF('Model inputs'!B105="","",'Model inputs'!B105))="",0,IF(IF(IF(ISERROR('Model inputs'!Q37<=8),'Model inputs'!Q37<=8,IF('Model inputs'!Q37="","",'Model inputs'!Q37<=8))="",FALSE,IF(ISERROR('Model inputs'!Q37<=8),'Model inputs'!Q37<=8,IF('Model inputs'!Q37="","",'Model inputs'!Q37<=8))),IF('Model inputs'!B109="","",'Model inputs'!B109),IF('Model inputs'!B105="","",'Model inputs'!B105)))))) -> 54.213361 | R48: =IF(IF(IF(ISERROR('Model inputs'!R37<1),'Model inputs'!R37<1,IF('Model inputs'!R37="","",'Model inputs'!R37<1))="",FALSE,IF(ISERROR('Model inputs'!R37<1),'Model inputs'!R37<1,IF('Model inputs'!R37="","",'Model inputs'!R37<1))),0,IF(IF(IF(ISERROR('Model inputs'!R37=1),'Model inputs'!R37=1,IF('Model inputs'!R37="","",'Model inputs'!R37=1))="",FALSE,IF(ISERROR('Model inputs'!R37=1),'Model inputs'!R37=1,IF('Model inputs'!R37="","",'Model inputs'!R37=1))),IF('Model inputs'!B119="","",'Model inputs'!B119),'Model inputs'!Q48*(1+IF(IF(IF(IF(ISERROR('Model inputs'!R37<=8),'Model inputs'!R37<=8,IF('Model inputs'!R37="","",'Model inputs'!R37<=8))="",FALSE,IF(ISERROR('Model inputs'!R37<=8),'Model inputs'!R37<=8,IF('Model inputs'!R37="","",'Model inputs'!R37<=8))),IF('Model inputs'!B109="","",'Model inputs'!B109),IF('Model inputs'!B105="","",'Model inputs'!B105))="",0,IF(IF(IF(ISERROR('Model inputs'!R37<=8),'Model inputs'!R37<=8,IF('Model inputs'!R37="","",'Model inputs'!R37<=8))="",FALSE,IF(ISERROR('Model inputs'!R37<=8),'Model inputs'!R37<=8,IF('Model inputs'!R37="","",'Model inputs'!R37<=8))),IF('Model inputs'!B109="","",'Model inputs'!B109),IF('Model inputs'!B105="","",'Model inputs'!B105)))))) -> 56.381895 | S48: =IF(IF(IF(ISERROR('Model inputs'!S37<1),'Model inputs'!S37<1,IF('Model inputs'!S37="","",'Model inputs'!S37<1))="",FALSE,IF(ISERROR('Model inputs'!S37<1),'Model inputs'!S37<1,IF('Model inputs'!S37="","",'Model inputs'!S37<1))),0,IF(IF(IF(ISERROR('Model inputs'!S37=1),'Model inputs'!S37=1,IF('Model inputs'!S37="","",'Model inputs'!S37=1))="",FALSE,IF(ISERROR('Model inputs'!S37=1),'Model inputs'!S37=1,IF('Model inputs'!S37="","",'Model inputs'!S37=1))),IF('Model inputs'!B119="","",'Model inputs'!B119),'Model inputs'!R48*(1+IF(IF(IF(IF(ISERROR('Model inputs'!S37<=8),'Model inputs'!S37<=8,IF('Model inputs'!S37="","",'Model inputs'!S37<=8))="",FALSE,IF(ISERROR('Model inputs'!S37<=8),'Model inputs'!S37<=8,IF('Model inputs'!S37="","",'Model inputs'!S37<=8))),IF('Model inputs'!B109="","",'Model inputs'!B109),IF('Model inputs'!B105="","",'Model inputs'!B105))="",0,IF(IF(IF(ISERROR('Model inputs'!S37<=8),'Model inputs'!S37<=8,IF('Model inputs'!S37="","",'Model inputs'!S37<=8))="",FALSE,IF(ISERROR('Model inputs'!S37<=8),'Model inputs'!S37<=8,IF('Model inputs'!S37="","",'Model inputs'!S37<=8))),IF('Model inputs'!B109="","",'Model inputs'!B109),IF('Model inputs'!B105="","",'Model inputs'!B105)))))) -> 58.637171 | T48: =IF(IF(IF(ISERROR('Model inputs'!T37<1),'Model inputs'!T37<1,IF('Model inputs'!T37="","",'Model inputs'!T37<1))="",FALSE,IF(ISERROR('Model inputs'!T37<1),'Model inputs'!T37<1,IF('Model inputs'!T37="","",'Model inputs'!T37<1))),0,IF(IF(IF(ISERROR('Model inputs'!T37=1),'Model inputs'!T37=1,IF('Model inputs'!T37="","",'Model inputs'!T37=1))="",FALSE,IF(ISERROR('Model inputs'!T37=1),'Model inputs'!T37=1,IF('Model inputs'!T37="","",'Model inputs'!T37=1))),IF('Model inputs'!B119="","",'Model inputs'!B119),'Model inputs'!S48*(1+IF(IF(IF(IF(ISERROR('Model inputs'!T37<=8),'Model inputs'!T37<=8,IF('Model inputs'!T37="","",'Model inputs'!T37<=8))="",FALSE,IF(ISERROR('Model inputs'!T37<=8),'Model inputs'!T37<=8,IF('Model inputs'!T37="","",'Model inputs'!T37<=8))),IF('Model inputs'!B109="","",'Model inputs'!B109),IF('Model inputs'!B105="","",'Model inputs'!B105))="",0,IF(IF(IF(ISERROR('Model inputs'!T37<=8),'Model inputs'!T37<=8,IF('Model inputs'!T37="","",'Model inputs'!T37<=8))="",FALSE,IF(ISERROR('Model inputs'!T37<=8),'Model inputs'!T37<=8,IF('Model inputs'!T37="","",'Model inputs'!T37<=8))),IF('Model inputs'!B109="","",'Model inputs'!B109),IF('Model inputs'!B105="","",'Model inputs'!B105)))))) -> 60.982658
A49: Organic new logos > Launch | C49: =IF(IF(IF(ISERROR('Model inputs'!C37<1),'Model inputs'!C37<1,IF('Model inputs'!C37="","",'Model inputs'!C37<1))="",FALSE,IF(ISERROR('Model inputs'!C37<1),'Model inputs'!C37<1,IF('Model inputs'!C37="","",'Model inputs'!C37<1))),0,IF(IF(IF(ISERROR('Model inputs'!C37=1),'Model inputs'!C37=1,IF('Model inputs'!C37="","",'Model inputs'!C37=1))="",FALSE,IF(ISERROR('Model inputs'!C37=1),'Model inputs'!C37=1,IF('Model inputs'!C37="","",'Model inputs'!C37=1))),IF('Model inputs'!B120="","",'Model inputs'!B120),'Model inputs'!AG128*(1+IF(IF(IF(IF(ISERROR('Model inputs'!C37<=8),'Model inputs'!C37<=8,IF('Model inputs'!C37="","",'Model inputs'!C37<=8))="",FALSE,IF(ISERROR('Model inputs'!C37<=8),'Model inputs'!C37<=8,IF('Model inputs'!C37="","",'Model inputs'!C37<=8))),IF('Model inputs'!B110="","",'Model inputs'!B110),IF('Model inputs'!B106="","",'Model inputs'!B106))="",0,IF(IF(IF(ISERROR('Model inputs'!C37<=8),'Model inputs'!C37<=8,IF('Model inputs'!C37="","",'Model inputs'!C37<=8))="",FALSE,IF(ISERROR('Model inputs'!C37<=8),'Model inputs'!C37<=8,IF('Model inputs'!C37="","",'Model inputs'!C37<=8))),IF('Model inputs'!B110="","",'Model inputs'!B110),IF('Model inputs'!B106="","",'Model inputs'!B106)))))) -> 0 | D49: =IF(IF(IF(ISERROR('Model inputs'!D37<1),'Model inputs'!D37<1,IF('Model inputs'!D37="","",'Model inputs'!D37<1))="",FALSE,IF(ISERROR('Model inputs'!D37<1),'Model inputs'!D37<1,IF('Model inputs'!D37="","",'Model inputs'!D37<1))),0,IF(IF(IF(ISERROR('Model inputs'!D37=1),'Model inputs'!D37=1,IF('Model inputs'!D37="","",'Model inputs'!D37=1))="",FALSE,IF(ISERROR('Model inputs'!D37=1),'Model inputs'!D37=1,IF('Model inputs'!D37="","",'Model inputs'!D37=1))),IF('Model inputs'!B120="","",'Model inputs'!B120),'Model inputs'!C49*(1+IF(IF(IF(IF(ISERROR('Model inputs'!D37<=8),'Model inputs'!D37<=8,IF('Model inputs'!D37="","",'Model inputs'!D37<=8))="",FALSE,IF(ISERROR('Model inputs'!D37<=8),'Model inputs'!D37<=8,IF('Model inputs'!D37="","",'Model inputs'!D37<=8))),IF('Model inputs'!B110="","",'Model inputs'!B110),IF('Model inputs'!B106="","",'Model inputs'!B106))="",0,IF(IF(IF(ISERROR('Model inputs'!D37<=8),'Model inputs'!D37<=8,IF('Model inputs'!D37="","",'Model inputs'!D37<=8))="",FALSE,IF(ISERROR('Model inputs'!D37<=8),'Model inputs'!D37<=8,IF('Model inputs'!D37="","",'Model inputs'!D37<=8))),IF('Model inputs'!B110="","",'Model inputs'!B110),IF('Model inputs'!B106="","",'Model inputs'!B106)))))) -> 0.5 | E49: =IF(IF(IF(ISERROR('Model inputs'!E37<1),'Model inputs'!E37<1,IF('Model inputs'!E37="","",'Model inputs'!E37<1))="",FALSE,IF(ISERROR('Model inputs'!E37<1),'Model inputs'!E37<1,IF('Model inputs'!E37="","",'Model inputs'!E37<1))),0,IF(IF(IF(ISERROR('Model inputs'!E37=1),'Model inputs'!E37=1,IF('Model inputs'!E37="","",'Model inputs'!E37=1))="",FALSE,IF(ISERROR('Model inputs'!E37=1),'Model inputs'!E37=1,IF('Model inputs'!E37="","",'Model inputs'!E37=1))),IF('Model inputs'!B120="","",'Model inputs'!B120),'Model inputs'!D49*(1+IF(IF(IF(IF(ISERROR('Model inputs'!E37<=8),'Model inputs'!E37<=8,IF('Model inputs'!E37="","",'Model inputs'!E37<=8))="",FALSE,IF(ISERROR('Model inputs'!E37<=8),'Model inputs'!E37<=8,IF('Model inputs'!E37="","",'Model inputs'!E37<=8))),IF('Model inputs'!B110="","",'Model inputs'!B110),IF('Model inputs'!B106="","",'Model inputs'!B106))="",0,IF(IF(IF(ISERROR('Model inputs'!E37<=8),'Model inputs'!E37<=8,IF('Model inputs'!E37="","",'Model inputs'!E37<=8))="",FALSE,IF(ISERROR('Model inputs'!E37<=8),'Model inputs'!E37<=8,IF('Model inputs'!E37="","",'Model inputs'!E37<=8))),IF('Model inputs'!B110="","",'Model inputs'!B110),IF('Model inputs'!B106="","",'Model inputs'!B106)))))) -> 0.5 | F49: =IF(IF(IF(ISERROR('Model inputs'!F37<1),'Model inputs'!F37<1,IF('Model inputs'!F37="","",'Model inputs'!F37<1))="",FALSE,IF(ISERROR('Model inputs'!F37<1),'Model inputs'!F37<1,IF('Model inputs'!F37="","",'Model inputs'!F37<1))),0,IF(IF(IF(ISERROR('Model inputs'!F37=1),'Model inputs'!F37=1,IF('Model inputs'!F37="","",'Model inputs'!F37=1))="",FALSE,IF(ISERROR('Model inputs'!F37=1),'Model inputs'!F37=1,IF('Model inputs'!F37="","",'Model inputs'!F37=1))),IF('Model inputs'!B120="","",'Model inputs'!B120),'Model inputs'!E49*(1+IF(IF(IF(IF(ISERROR('Model inputs'!F37<=8),'Model inputs'!F37<=8,IF('Model inputs'!F37="","",'Model inputs'!F37<=8))="",FALSE,IF(ISERROR('Model inputs'!F37<=8),'Model inputs'!F37<=8,IF('Model inputs'!F37="","",'Model inputs'!F37<=8))),IF('Model inputs'!B110="","",'Model inputs'!B110),IF('Model inputs'!B106="","",'Model inputs'!B106))="",0,IF(IF(IF(ISERROR('Model inputs'!F37<=8),'Model inputs'!F37<=8,IF('Model inputs'!F37="","",'Model inputs'!F37<=8))="",FALSE,IF(ISERROR('Model inputs'!F37<=8),'Model inputs'!F37<=8,IF('Model inputs'!F37="","",'Model inputs'!F37<=8))),IF('Model inputs'!B110="","",'Model inputs'!B110),IF('Model inputs'!B106="","",'Model inputs'!B106)))))) -> 0.5 | G49: =IF(IF(IF(ISERROR('Model inputs'!G37<1),'Model inputs'!G37<1,IF('Model inputs'!G37="","",'Model inputs'!G37<1))="",FALSE,IF(ISERROR('Model inputs'!G37<1),'Model inputs'!G37<1,IF('Model inputs'!G37="","",'Model inputs'!G37<1))),0,IF(IF(IF(ISERROR('Model inputs'!G37=1),'Model inputs'!G37=1,IF('Model inputs'!G37="","",'Model inputs'!G37=1))="",FALSE,IF(ISERROR('Model inputs'!G37=1),'Model inputs'!G37=1,IF('Model inputs'!G37="","",'Model inputs'!G37=1))),IF('Model inputs'!B120="","",'Model inputs'!B120),'Model inputs'!F49*(1+IF(IF(IF(IF(ISERROR('Model inputs'!G37<=8),'Model inputs'!G37<=8,IF('Model inputs'!G37="","",'Model inputs'!G37<=8))="",FALSE,IF(ISERROR('Model inputs'!G37<=8),'Model inputs'!G37<=8,IF('Model inputs'!G37="","",'Model inputs'!G37<=8))),IF('Model inputs'!B110="","",'Model inputs'!B110),IF('Model inputs'!B106="","",'Model inputs'!B106))="",0,IF(IF(IF(ISERROR('Model inputs'!G37<=8),'Model inputs'!G37<=8,IF('Model inputs'!G37="","",'Model inputs'!G37<=8))="",FALSE,IF(ISERROR('Model inputs'!G37<=8),'Model inputs'!G37<=8,IF('Model inputs'!G37="","",'Model inputs'!G37<=8))),IF('Model inputs'!B110="","",'Model inputs'!B110),IF('Model inputs'!B106="","",'Model inputs'!B106)))))) -> 0.5 | H49: =IF(IF(IF(ISERROR('Model inputs'!H37<1),'Model inputs'!H37<1,IF('Model inputs'!H37="","",'Model inputs'!H37<1))="",FALSE,IF(ISERROR('Model inputs'!H37<1),'Model inputs'!H37<1,IF('Model inputs'!H37="","",'Model inputs'!H37<1))),0,IF(IF(IF(ISERROR('Model inputs'!H37=1),'Model inputs'!H37=1,IF('Model inputs'!H37="","",'Model inputs'!H37=1))="",FALSE,IF(ISERROR('Model inputs'!H37=1),'Model inputs'!H37=1,IF('Model inputs'!H37="","",'Model inputs'!H37=1))),IF('Model inputs'!B120="","",'Model inputs'!B120),'Model inputs'!G49*(1+IF(IF(IF(IF(ISERROR('Model inputs'!H37<=8),'Model inputs'!H37<=8,IF('Model inputs'!H37="","",'Model inputs'!H37<=8))="",FALSE,IF(ISERROR('Model inputs'!H37<=8),'Model inputs'!H37<=8,IF('Model inputs'!H37="","",'Model inputs'!H37<=8))),IF('Model inputs'!B110="","",'Model inputs'!B110),IF('Model inputs'!B106="","",'Model inputs'!B106))="",0,IF(IF(IF(ISERROR('Model inputs'!H37<=8),'Model inputs'!H37<=8,IF('Model inputs'!H37="","",'Model inputs'!H37<=8))="",FALSE,IF(ISERROR('Model inputs'!H37<=8),'Model inputs'!H37<=8,IF('Model inputs'!H37="","",'Model inputs'!H37<=8))),IF('Model inputs'!B110="","",'Model inputs'!B110),IF('Model inputs'!B106="","",'Model inputs'!B106)))))) -> 0.5 | I49: =IF(IF(IF(ISERROR('Model inputs'!I37<1),'Model inputs'!I37<1,IF('Model inputs'!I37="","",'Model inputs'!I37<1))="",FALSE,IF(ISERROR('Model inputs'!I37<1),'Model inputs'!I37<1,IF('Model inputs'!I37="","",'Model inputs'!I37<1))),0,IF(IF(IF(ISERROR('Model inputs'!I37=1),'Model inputs'!I37=1,IF('Model inputs'!I37="","",'Model inputs'!I37=1))="",FALSE,IF(ISERROR('Model inputs'!I37=1),'Model inputs'!I37=1,IF('Model inputs'!I37="","",'Model inputs'!I37=1))),IF('Model inputs'!B120="","",'Model inputs'!B120),'Model inputs'!H49*(1+IF(IF(IF(IF(ISERROR('Model inputs'!I37<=8),'Model inputs'!I37<=8,IF('Model inputs'!I37="","",'Model inputs'!I37<=8))="",FALSE,IF(ISERROR('Model inputs'!I37<=8),'Model inputs'!I37<=8,IF('Model inputs'!I37="","",'Model inputs'!I37<=8))),IF('Model inputs'!B110="","",'Model inputs'!B110),IF('Model inputs'!B106="","",'Model inputs'!B106))="",0,IF(IF(IF(ISERROR('Model inputs'!I37<=8),'Model inputs'!I37<=8,IF('Model inputs'!I37="","",'Model inputs'!I37<=8))="",FALSE,IF(ISERROR('Model inputs'!I37<=8),'Model inputs'!I37<=8,IF('Model inputs'!I37="","",'Model inputs'!I37<=8))),IF('Model inputs'!B110="","",'Model inputs'!B110),IF('Model inputs'!B106="","",'Model inputs'!B106)))))) -> 0.5 | J49: =IF(IF(IF(ISERROR('Model inputs'!J37<1),'Model inputs'!J37<1,IF('Model inputs'!J37="","",'Model inputs'!J37<1))="",FALSE,IF(ISERROR('Model inputs'!J37<1),'Model inputs'!J37<1,IF('Model inputs'!J37="","",'Model inputs'!J37<1))),0,IF(IF(IF(ISERROR('Model inputs'!J37=1),'Model inputs'!J37=1,IF('Model inputs'!J37="","",'Model inputs'!J37=1))="",FALSE,IF(ISERROR('Model inputs'!J37=1),'Model inputs'!J37=1,IF('Model inputs'!J37="","",'Model inputs'!J37=1))),IF('Model inputs'!B120="","",'Model inputs'!B120),'Model inputs'!I49*(1+IF(IF(IF(IF(ISERROR('Model inputs'!J37<=8),'Model inputs'!J37<=8,IF('Model inputs'!J37="","",'Model inputs'!J37<=8))="",FALSE,IF(ISERROR('Model inputs'!J37<=8),'Model inputs'!J37<=8,IF('Model inputs'!J37="","",'Model inputs'!J37<=8))),IF('Model inputs'!B110="","",'Model inputs'!B110),IF('Model inputs'!B106="","",'Model inputs'!B106))="",0,IF(IF(IF(ISERROR('Model inputs'!J37<=8),'Model inputs'!J37<=8,IF('Model inputs'!J37="","",'Model inputs'!J37<=8))="",FALSE,IF(ISERROR('Model inputs'!J37<=8),'Model inputs'!J37<=8,IF('Model inputs'!J37="","",'Model inputs'!J37<=8))),IF('Model inputs'!B110="","",'Model inputs'!B110),IF('Model inputs'!B106="","",'Model inputs'!B106)))))) -> 0.5 | K49: =IF(IF(IF(ISERROR('Model inputs'!K37<1),'Model inputs'!K37<1,IF('Model inputs'!K37="","",'Model inputs'!K37<1))="",FALSE,IF(ISERROR('Model inputs'!K37<1),'Model inputs'!K37<1,IF('Model inputs'!K37="","",'Model inputs'!K37<1))),0,IF(IF(IF(ISERROR('Model inputs'!K37=1),'Model inputs'!K37=1,IF('Model inputs'!K37="","",'Model inputs'!K37=1))="",FALSE,IF(ISERROR('Model inputs'!K37=1),'Model inputs'!K37=1,IF('Model inputs'!K37="","",'Model inputs'!K37=1))),IF('Model inputs'!B120="","",'Model inputs'!B120),'Model inputs'!J49*(1+IF(IF(IF(IF(ISERROR('Model inputs'!K37<=8),'Model inputs'!K37<=8,IF('Model inputs'!K37="","",'Model inputs'!K37<=8))="",FALSE,IF(ISERROR('Model inputs'!K37<=8),'Model inputs'!K37<=8,IF('Model inputs'!K37="","",'Model inputs'!K37<=8))),IF('Model inputs'!B110="","",'Model inputs'!B110),IF('Model inputs'!B106="","",'Model inputs'!B106))="",0,IF(IF(IF(ISERROR('Model inputs'!K37<=8),'Model inputs'!K37<=8,IF('Model inputs'!K37="","",'Model inputs'!K37<=8))="",FALSE,IF(ISERROR('Model inputs'!K37<=8),'Model inputs'!K37<=8,IF('Model inputs'!K37="","",'Model inputs'!K37<=8))),IF('Model inputs'!B110="","",'Model inputs'!B110),IF('Model inputs'!B106="","",'Model inputs'!B106)))))) -> 0.5 | L49: =IF(IF(IF(ISERROR('Model inputs'!L37<1),'Model inputs'!L37<1,IF('Model inputs'!L37="","",'Model inputs'!L37<1))="",FALSE,IF(ISERROR('Model inputs'!L37<1),'Model inputs'!L37<1,IF('Model inputs'!L37="","",'Model inputs'!L37<1))),0,IF(IF(IF(ISERROR('Model inputs'!L37=1),'Model inputs'!L37=1,IF('Model inputs'!L37="","",'Model inputs'!L37=1))="",FALSE,IF(ISERROR('Model inputs'!L37=1),'Model inputs'!L37=1,IF('Model inputs'!L37="","",'Model inputs'!L37=1))),IF('Model inputs'!B120="","",'Model inputs'!B120),'Model inputs'!K49*(1+IF(IF(IF(IF(ISERROR('Model inputs'!L37<=8),'Model inputs'!L37<=8,IF('Model inputs'!L37="","",'Model inputs'!L37<=8))="",FALSE,IF(ISERROR('Model inputs'!L37<=8),'Model inputs'!L37<=8,IF('Model inputs'!L37="","",'Model inputs'!L37<=8))),IF('Model inputs'!B110="","",'Model inputs'!B110),IF('Model inputs'!B106="","",'Model inputs'!B106))="",0,IF(IF(IF(ISERROR('Model inputs'!L37<=8),'Model inputs'!L37<=8,IF('Model inputs'!L37="","",'Model inputs'!L37<=8))="",FALSE,IF(ISERROR('Model inputs'!L37<=8),'Model inputs'!L37<=8,IF('Model inputs'!L37="","",'Model inputs'!L37<=8))),IF('Model inputs'!B110="","",'Model inputs'!B110),IF('Model inputs'!B106="","",'Model inputs'!B106)))))) -> 0.5 | M49: =IF(IF(IF(ISERROR('Model inputs'!M37<1),'Model inputs'!M37<1,IF('Model inputs'!M37="","",'Model inputs'!M37<1))="",FALSE,IF(ISERROR('Model inputs'!M37<1),'Model inputs'!M37<1,IF('Model inputs'!M37="","",'Model inputs'!M37<1))),0,IF(IF(IF(ISERROR('Model inputs'!M37=1),'Model inputs'!M37=1,IF('Model inputs'!M37="","",'Model inputs'!M37=1))="",FALSE,IF(ISERROR('Model inputs'!M37=1),'Model inputs'!M37=1,IF('Model inputs'!M37="","",'Model inputs'!M37=1))),IF('Model inputs'!B120="","",'Model inputs'!B120),'Model inputs'!L49*(1+IF(IF(IF(IF(ISERROR('Model inputs'!M37<=8),'Model inputs'!M37<=8,IF('Model inputs'!M37="","",'Model inputs'!M37<=8))="",FALSE,IF(ISERROR('Model inputs'!M37<=8),'Model inputs'!M37<=8,IF('Model inputs'!M37="","",'Model inputs'!M37<=8))),IF('Model inputs'!B110="","",'Model inputs'!B110),IF('Model inputs'!B106="","",'Model inputs'!B106))="",0,IF(IF(IF(ISERROR('Model inputs'!M37<=8),'Model inputs'!M37<=8,IF('Model inputs'!M37="","",'Model inputs'!M37<=8))="",FALSE,IF(ISERROR('Model inputs'!M37<=8),'Model inputs'!M37<=8,IF('Model inputs'!M37="","",'Model inputs'!M37<=8))),IF('Model inputs'!B110="","",'Model inputs'!B110),IF('Model inputs'!B106="","",'Model inputs'!B106)))))) -> 0.5 | N49: =IF(IF(IF(ISERROR('Model inputs'!N37<1),'Model inputs'!N37<1,IF('Model inputs'!N37="","",'Model inputs'!N37<1))="",FALSE,IF(ISERROR('Model inputs'!N37<1),'Model inputs'!N37<1,IF('Model inputs'!N37="","",'Model inputs'!N37<1))),0,IF(IF(IF(ISERROR('Model inputs'!N37=1),'Model inputs'!N37=1,IF('Model inputs'!N37="","",'Model inputs'!N37=1))="",FALSE,IF(ISERROR('Model inputs'!N37=1),'Model inputs'!N37=1,IF('Model inputs'!N37="","",'Model inputs'!N37=1))),IF('Model inputs'!B120="","",'Model inputs'!B120),'Model inputs'!M49*(1+IF(IF(IF(IF(ISERROR('Model inputs'!N37<=8),'Model inputs'!N37<=8,IF('Model inputs'!N37="","",'Model inputs'!N37<=8))="",FALSE,IF(ISERROR('Model inputs'!N37<=8),'Model inputs'!N37<=8,IF('Model inputs'!N37="","",'Model inputs'!N37<=8))),IF('Model inputs'!B110="","",'Model inputs'!B110),IF('Model inputs'!B106="","",'Model inputs'!B106))="",0,IF(IF(IF(ISERROR('Model inputs'!N37<=8),'Model inputs'!N37<=8,IF('Model inputs'!N37="","",'Model inputs'!N37<=8))="",FALSE,IF(ISERROR('Model inputs'!N37<=8),'Model inputs'!N37<=8,IF('Model inputs'!N37="","",'Model inputs'!N37<=8))),IF('Model inputs'!B110="","",'Model inputs'!B110),IF('Model inputs'!B106="","",'Model inputs'!B106)))))) -> 0.5 | O49: =IF(IF(IF(ISERROR('Model inputs'!O37<1),'Model inputs'!O37<1,IF('Model inputs'!O37="","",'Model inputs'!O37<1))="",FALSE,IF(ISERROR('Model inputs'!O37<1),'Model inputs'!O37<1,IF('Model inputs'!O37="","",'Model inputs'!O37<1))),0,IF(IF(IF(ISERROR('Model inputs'!O37=1),'Model inputs'!O37=1,IF('Model inputs'!O37="","",'Model inputs'!O37=1))="",FALSE,IF(ISERROR('Model inputs'!O37=1),'Model inputs'!O37=1,IF('Model inputs'!O37="","",'Model inputs'!O37=1))),IF('Model inputs'!B120="","",'Model inputs'!B120),'Model inputs'!N49*(1+IF(IF(IF(IF(ISERROR('Model inputs'!O37<=8),'Model inputs'!O37<=8,IF('Model inputs'!O37="","",'Model inputs'!O37<=8))="",FALSE,IF(ISERROR('Model inputs'!O37<=8),'Model inputs'!O37<=8,IF('Model inputs'!O37="","",'Model inputs'!O37<=8))),IF('Model inputs'!B110="","",'Model inputs'!B110),IF('Model inputs'!B106="","",'Model inputs'!B106))="",0,IF(IF(IF(ISERROR('Model inputs'!O37<=8),'Model inputs'!O37<=8,IF('Model inputs'!O37="","",'Model inputs'!O37<=8))="",FALSE,IF(ISERROR('Model inputs'!O37<=8),'Model inputs'!O37<=8,IF('Model inputs'!O37="","",'Model inputs'!O37<=8))),IF('Model inputs'!B110="","",'Model inputs'!B110),IF('Model inputs'!B106="","",'Model inputs'!B106)))))) -> 0.5 | P49: =IF(IF(IF(ISERROR('Model inputs'!P37<1),'Model inputs'!P37<1,IF('Model inputs'!P37="","",'Model inputs'!P37<1))="",FALSE,IF(ISERROR('Model inputs'!P37<1),'Model inputs'!P37<1,IF('Model inputs'!P37="","",'Model inputs'!P37<1))),0,IF(IF(IF(ISERROR('Model inputs'!P37=1),'Model inputs'!P37=1,IF('Model inputs'!P37="","",'Model inputs'!P37=1))="",FALSE,IF(ISERROR('Model inputs'!P37=1),'Model inputs'!P37=1,IF('Model inputs'!P37="","",'Model inputs'!P37=1))),IF('Model inputs'!B120="","",'Model inputs'!B120),'Model inputs'!O49*(1+IF(IF(IF(IF(ISERROR('Model inputs'!P37<=8),'Model inputs'!P37<=8,IF('Model inputs'!P37="","",'Model inputs'!P37<=8))="",FALSE,IF(ISERROR('Model inputs'!P37<=8),'Model inputs'!P37<=8,IF('Model inputs'!P37="","",'Model inputs'!P37<=8))),IF('Model inputs'!B110="","",'Model inputs'!B110),IF('Model inputs'!B106="","",'Model inputs'!B106))="",0,IF(IF(IF(ISERROR('Model inputs'!P37<=8),'Model inputs'!P37<=8,IF('Model inputs'!P37="","",'Model inputs'!P37<=8))="",FALSE,IF(ISERROR('Model inputs'!P37<=8),'Model inputs'!P37<=8,IF('Model inputs'!P37="","",'Model inputs'!P37<=8))),IF('Model inputs'!B110="","",'Model inputs'!B110),IF('Model inputs'!B106="","",'Model inputs'!B106)))))) -> 0.5 | Q49: =IF(IF(IF(ISERROR('Model inputs'!Q37<1),'Model inputs'!Q37<1,IF('Model inputs'!Q37="","",'Model inputs'!Q37<1))="",FALSE,IF(ISERROR('Model inputs'!Q37<1),'Model inputs'!Q37<1,IF('Model inputs'!Q37="","",'Model inputs'!Q37<1))),0,IF(IF(IF(ISERROR('Model inputs'!Q37=1),'Model inputs'!Q37=1,IF('Model inputs'!Q37="","",'Model inputs'!Q37=1))="",FALSE,IF(ISERROR('Model inputs'!Q37=1),'Model inputs'!Q37=1,IF('Model inputs'!Q37="","",'Model inputs'!Q37=1))),IF('Model inputs'!B120="","",'Model inputs'!B120),'Model inputs'!P49*(1+IF(IF(IF(IF(ISERROR('Model inputs'!Q37<=8),'Model inputs'!Q37<=8,IF('Model inputs'!Q37="","",'Model inputs'!Q37<=8))="",FALSE,IF(ISERROR('Model inputs'!Q37<=8),'Model inputs'!Q37<=8,IF('Model inputs'!Q37="","",'Model inputs'!Q37<=8))),IF('Model inputs'!B110="","",'Model inputs'!B110),IF('Model inputs'!B106="","",'Model inputs'!B106))="",0,IF(IF(IF(ISERROR('Model inputs'!Q37<=8),'Model inputs'!Q37<=8,IF('Model inputs'!Q37="","",'Model inputs'!Q37<=8))="",FALSE,IF(ISERROR('Model inputs'!Q37<=8),'Model inputs'!Q37<=8,IF('Model inputs'!Q37="","",'Model inputs'!Q37<=8))),IF('Model inputs'!B110="","",'Model inputs'!B110),IF('Model inputs'!B106="","",'Model inputs'!B106)))))) -> 0.5 | R49: =IF(IF(IF(ISERROR('Model inputs'!R37<1),'Model inputs'!R37<1,IF('Model inputs'!R37="","",'Model inputs'!R37<1))="",FALSE,IF(ISERROR('Model inputs'!R37<1),'Model inputs'!R37<1,IF('Model inputs'!R37="","",'Model inputs'!R37<1))),0,IF(IF(IF(ISERROR('Model inputs'!R37=1),'Model inputs'!R37=1,IF('Model inputs'!R37="","",'Model inputs'!R37=1))="",FALSE,IF(ISERROR('Model inputs'!R37=1),'Model inputs'!R37=1,IF('Model inputs'!R37="","",'Model inputs'!R37=1))),IF('Model inputs'!B120="","",'Model inputs'!B120),'Model inputs'!Q49*(1+IF(IF(IF(IF(ISERROR('Model inputs'!R37<=8),'Model inputs'!R37<=8,IF('Model inputs'!R37="","",'Model inputs'!R37<=8))="",FALSE,IF(ISERROR('Model inputs'!R37<=8),'Model inputs'!R37<=8,IF('Model inputs'!R37="","",'Model inputs'!R37<=8))),IF('Model inputs'!B110="","",'Model inputs'!B110),IF('Model inputs'!B106="","",'Model inputs'!B106))="",0,IF(IF(IF(ISERROR('Model inputs'!R37<=8),'Model inputs'!R37<=8,IF('Model inputs'!R37="","",'Model inputs'!R37<=8))="",FALSE,IF(ISERROR('Model inputs'!R37<=8),'Model inputs'!R37<=8,IF('Model inputs'!R37="","",'Model inputs'!R37<=8))),IF('Model inputs'!B110="","",'Model inputs'!B110),IF('Model inputs'!B106="","",'Model inputs'!B106)))))) -> 0.5 | S49: =IF(IF(IF(ISERROR('Model inputs'!S37<1),'Model inputs'!S37<1,IF('Model inputs'!S37="","",'Model inputs'!S37<1))="",FALSE,IF(ISERROR('Model inputs'!S37<1),'Model inputs'!S37<1,IF('Model inputs'!S37="","",'Model inputs'!S37<1))),0,IF(IF(IF(ISERROR('Model inputs'!S37=1),'Model inputs'!S37=1,IF('Model inputs'!S37="","",'Model inputs'!S37=1))="",FALSE,IF(ISERROR('Model inputs'!S37=1),'Model inputs'!S37=1,IF('Model inputs'!S37="","",'Model inputs'!S37=1))),IF('Model inputs'!B120="","",'Model inputs'!B120),'Model inputs'!R49*(1+IF(IF(IF(IF(ISERROR('Model inputs'!S37<=8),'Model inputs'!S37<=8,IF('Model inputs'!S37="","",'Model inputs'!S37<=8))="",FALSE,IF(ISERROR('Model inputs'!S37<=8),'Model inputs'!S37<=8,IF('Model inputs'!S37="","",'Model inputs'!S37<=8))),IF('Model inputs'!B110="","",'Model inputs'!B110),IF('Model inputs'!B106="","",'Model inputs'!B106))="",0,IF(IF(IF(ISERROR('Model inputs'!S37<=8),'Model inputs'!S37<=8,IF('Model inputs'!S37="","",'Model inputs'!S37<=8))="",FALSE,IF(ISERROR('Model inputs'!S37<=8),'Model inputs'!S37<=8,IF('Model inputs'!S37="","",'Model inputs'!S37<=8))),IF('Model inputs'!B110="","",'Model inputs'!B110),IF('Model inputs'!B106="","",'Model inputs'!B106)))))) -> 0.5 | T49: =IF(IF(IF(ISERROR('Model inputs'!T37<1),'Model inputs'!T37<1,IF('Model inputs'!T37="","",'Model inputs'!T37<1))="",FALSE,IF(ISERROR('Model inputs'!T37<1),'Model inputs'!T37<1,IF('Model inputs'!T37="","",'Model inputs'!T37<1))),0,IF(IF(IF(ISERROR('Model inputs'!T37=1),'Model inputs'!T37=1,IF('Model inputs'!T37="","",'Model inputs'!T37=1))="",FALSE,IF(ISERROR('Model inputs'!T37=1),'Model inputs'!T37=1,IF('Model inputs'!T37="","",'Model inputs'!T37=1))),IF('Model inputs'!B120="","",'Model inputs'!B120),'Model inputs'!S49*(1+IF(IF(IF(IF(ISERROR('Model inputs'!T37<=8),'Model inputs'!T37<=8,IF('Model inputs'!T37="","",'Model inputs'!T37<=8))="",FALSE,IF(ISERROR('Model inputs'!T37<=8),'Model inputs'!T37<=8,IF('Model inputs'!T37="","",'Model inputs'!T37<=8))),IF('Model inputs'!B110="","",'Model inputs'!B110),IF('Model inputs'!B106="","",'Model inputs'!B106))="",0,IF(IF(IF(ISERROR('Model inputs'!T37<=8),'Model inputs'!T37<=8,IF('Model inputs'!T37="","",'Model inputs'!T37<=8))="",FALSE,IF(ISERROR('Model inputs'!T37<=8),'Model inputs'!T37<=8,IF('Model inputs'!T37="","",'Model inputs'!T37<=8))),IF('Model inputs'!B110="","",'Model inputs'!B110),IF('Model inputs'!B106="","",'Model inputs'!B106)))))) -> 0.5
